Workbook
Name _ftn1: demand!$B$946
Name _ftnref1: demand!$B$957
Name ALL: ALL!#REF!
Name COMPANY_HEADER: REBLD!$A$4:$D$12
Name FINAL_INVOICES_STATEMENT: ALL!$D$171
Name newclaimspacerow1: ALL!$AJ$1
Name RE___DEMAND_FOR_APPRAISAL: demand!$D$283
Name SORT_A__Z: #REF!
Name SPLM_START_INFO: ALL!#REF!

Sheet ALL
B1: A-Z | C1: NAME | D1: Property-Owner Name | E1: Sheet Map | F1: Bradley, Curtis L | G1: KOSWATTA, ERIKA | H1: Williams, Bridgett | I1: Battle, Larry Jr | J1: ANDERSON, PETE | K1: WYNN, NICK | L1: FERGUSON, ROBERT & MRS | M1: RUSH, TIFFANY LOAN # 0579206154 | N1: RUSH, TIFFANY WTR | O1: TORRES, ANGEL | P1: Harvey, CORA | Q1: ROBINSON, NiKKole | R1: LEETH, RONNIE | S1: LANEY, Anthony | T1: LAWRENCE, GENEATHA | U1: SMITH, JANET | V1: Wimbish, Tawana | W1: HICKS, JASON | X1: Akala, Ayo SMOKE FIRE | Y1: Akala, Ayo VND | Z1: Akala, Ayo TREE | AA1: Cousette, JOHN Vandalism | AB1: Cousette, JOHN ROOF | AC1: JONES, BREANNA | AD1: Collins, Darlene | AE1: NEWMAN, NICOLE | AF1: Peggy Henderson | AG1: Romero Beverly | AH1: TAYLOR DAVIDSON, WARREN | AI1: Goshen, Aaron & Shania | AJ1: Brownlee. LAVERNE | AK1: Craig Ringo | AL1: SMITH, JANET | AM1: Brown, Cassandra | AN1: Hurt, Chaunte | AO1: Dejarnette Mattie | AP1: Burns2, RUBY | AQ1: CARTER, KAREN | AR1: CHERRY, LAUREN LB8997 | AS1: Johnson, Paul & Tamra | AT1: LACEY, EUNICE | AU1: BROOKS, DANIEL;JANAE POA | AV1: Smith, Brian | AW1: THOMAS, ANITA | AX1: Hatten, Nedra | AY1: HOWARD, MATTHEW | AZ1: MONTGOMERY, JAVIONNA | BB1: BROWNLEE, KEN | BC1: HUTCHINSON | BL1: new claim | BN1: A-Z | BO1: BROWN,Courtney | BP1: JOHNSON,MIKE WTR | BQ1: JOHNSON,MIKE RFG | BR1: Burns, ERIC | BS1: Tamplin, Adalene | BT1: George Greenawalt | BU1: Brown, Charles | BV1: Lozano, Marcos | BW1: Johnson, Margaret | BX1: Carib Investment ,LLC | BY1: Franklin Annette | BZ1: Lanier, Shari | CA1: Corbin, Wanda | CB1: WILLIS, CATRERA | CC1: Greenawalt, Mike | CD1: THOMAS, LISA | CE1: Ragland | CF1: Webb, Terika | CG1: Red Ink CLE LLC Amir
A2: E1 | B2: =E1 -> Sheet Map | C2: =$F$1 -> Bradley, Curtis L | D2: Property address: street | G2: TBD | H2: CPS ADJUSTER | I2: TBD | J2: 0 | K2: SHEREFINAL 1M0N 11.28.22 | M2: 956 Roanoke Road, | N2: 956 Roanoke Road, | O2: One Tower Square | P2: TBD | Q2: TBD | R2: TBD | T2: 3936 Strandhill Road | U2: 2819-21 Ludlow Road | V2: 300 Lynhurst Drive | W2: 5630 Turney Road | X2: 3685 E153 | Y2: 3685 E153 | Z2: 3685 E153 | AA2: 1133 East 111th St | AB2: 1133 East 111th St | AC2: 6033 Bear Creek Dr #420 | AD2: 1334 Elwood RD | AE2: 4767 E 88 STR | AF2: 12413-15Gruss Ave, | AG2: 592 Clubland Circle Southeast | AH2: 15009 Harvard Ave | AI2: 969 E 348th St | AJ2: 13509 Alvin Ave | AK2: 5697 Daniel Street | AL2: 2821 Ludlow Road | AM2: 6918 Hecker Ave, | AN2: 703 E 241st St | AO2: 16755 Lorain ST. | AP2: 3 Washington Square | AQ2: 7 Washington Square | AR2: 2687 E.128th | AS2: 9402 Shepard Road | AT2: 13601 5th Ave | AU2: 3427 SANDALWOOD LN | AV2: 831 Gertrude Place NW, | AW2: 6600 GERTRUDE | AX2: 628 Quilliams Road | AY2: 3247 East 55th Street | AZ2: 3034 Ashwood Road, | BB2: 3922 E 189 STR | BC2: 17823 Rauland Dr | BL2: HOME | BM2: INACTIVE | BN2: =BO1 -> BROWN,Courtney | BO2: 6479 Veracruse Dr | BP2: 1841 Childress Dr SW | BQ2: 1841 Childress Drive Southwes | BR2: 488 Trebisky RD | BS2: 287 Roberts Rd | BT2: 11604 Governor Ave | BU2: TBD | BV2: Direct: (844) 306-0752 Ext.591641 | BW2: 3619 Rolling Green Ridge | BX2: 4745 East 88th Street, | BY2: One State Farm Plaza | BZ2: 1408 East 124th Street | CA2: 15907 Eldamere Ave | CB2: 969 E 348th St | CC2: 11601 Governor Avenue | CD2: 5149 Miller Avenue | CE2: 42 NORDHAM DR | CF2: 4981 Horizon Drive | CG2: 1790 E 43rd St,
A3: F1 | B3: =$X$1 -> Akala, Ayo SMOKE FIRE | C3: =$G$1 -> KOSWATTA, ERIKA | D3: Property city, state, zip | F3: ='[1]jobinfo(2)'!$C$53 -> GUEST CLOSET | G3: Foyer/Entry Room | H3: GUEST CLOSET | I3: FOYER/ENTRY ROOM | J3: Foyer | K3: Foyer | L3: Kitchen Travel area | M3: Cleveland Heights, OH | N3: Cleveland Heights, OH | O3: FOYER - TRAVEL AREA | P3: Front Room Foyer/entry | Q3: FOYER/ENTRY ROOM | R3: Foyer & HALL | S3: FOYER | T3: Cleveland, OH 44128 | U3: Cleveland, OH 44120 | V3: Atlanta, GA 30311 | W3: Garfield Heights, OH, 44125 | X3: Cleveland OH 44120 | Y3: Cleveland OH 44120 | Z3: Cleveland OH 44120 | AA3: Cleveland, OH | AB3: Cleveland, OH | AC3: Bedford Heights, OH 44146 | AD3: East Cleveland, OH 44108 | AE3: GARFILELD, OH 44125 | AF3: Cleveland, OH 44108 | AG3: Conyers, GA, | AH3: Cleveland, OH 4412 | AI3: Eastlake, Ohio 44095 | AJ3: Garfield Heights 44105 | AK3: Bedford Hgts OH 44146 | AL3: Cleveland, OH 44120 | AM3: Cleveland, OH 44106 | AN3: Euclid, OH 44123 | AO3: Chagrin Falls, Ohio 44023, USA | AP3: Euclid, OH 44143 | AQ3: Euclid, OH 44143 | AR3: CLEVELAND, OH 44120 | AS3: Macedonia, OH, USA | AT3: East Cleveland, OH 44112 | AU3: Austintown, OH 44511 | AV3: Atlanta, GA 30318 | AW3: Cleveland, OH 44105 | AX3: Cleveland Heights, OH 44121 | AY3: Cleveland, OH 44127 | AZ3: Cleveland, OH, USA 44120 | BB3: CLEVELAND, OH 44128 | BC3: WALTON HILLS, OH 44146 | BL3: Atlanta, GA 30318 | BN3: =#REF! -> #REF! | BO3: Morrow, GA 30260 | BP3: Atlanta, GA, 30311 | BQ3: Atlanta, GA, 30311 | BR3: Richmond Heights, OH 44143 | BS3: Barnesville, GA 30204 | BT3: Cleveland, OH 44111 | BU3: TBD | BV3: FOYER / ENTRY | BW3: Atlanta, GA, 30331 | BX3: Garfield Heights, OH | BY3: Living Room Travel Area | BZ3: Cleveland, OH 44106 | CA3: Cleveland, OH 44128 | CB3: Eastlake, Ohio 44095 | CC3: Cleveland, OH, 44111 | CD3: Maple Heights, OH | CE3: Bedford, OH 44146 | CF3: Richmond Heights 44143 | CG3: Cleveland, OH, 44103
A4: G1 | B4: =$Z$1 -> Akala, Ayo TREE | C4: =$H$1 -> Williams, Bridgett | D4: Customer Email | G4: TBD | H4: ANNA LISA | I4: TBD | J4: 0 | K4: Matthew.Mertz@LIBERTYMUTUAL.COM | M4: dr.tiffanyrw@counselingsecure.com | N4: dr.tiffanyrw@counselingsecure.com | O4: Attn: Consumer Affairs | P4: TBD | Q4: 0 | R4: TBD | T4: GANNLAWRENCE@HOTMAIL.COM | U4: smithh1963@gmail.com | V4: tawanawimbish@yahoo.com | W4: LJ53089@YAHOO.COM | X4: kiitan.akala@gmail.com | Y4: kiitan.akala@gmail.com | Z4: kiitan.akala@gmail.com | AA4: john.cousette@yahoo.com | AB4: john.cousette@yahoo.com | AC4: BREANNAJ9950@GMAI.COM | AD4: OH24ACOLLINS@ELWOOD RD | AE4: NICC524@GMAIL.COM | AF4: pthornton8@roadrunner.com | AG4: Djembepaid@gmail.com | AH4: GOLDENHAWK38@GMAIL.COM | AI4: AaronShaniaGoshen@gmail.com | AJ4: lavernbrownlee107@gmail.com | AK4: CraigRINGO@GMAIL.COM | AL4: smithh1963@gmail.com | AM4: browncass.mzsan73@gmail.com | AN4: Clhurt87@gmail.com | AO4: MIKEWILEY21@YAHOO.COM | AP4: dorothy.webb@sbcglobal.net | AQ4: KAREN.CARTER5214@GMAIL.COM | AR4: lauren@anniewillventures.com | AS4: tringo68@yahoo.com | AT4: Emdlacey@gmail.com | AU4: JANAETAB16@YAHOO.COM | AV4: BRIAN.ASHTON.SMITH.211@GMAIL.COM | AW4: Trenddamnish@yahoo.com | AX4: Msnedra1015@aol.com | AY4: HOWARDSERVICES@YAHOO.COM | AZ4: JAVIONNA@ICLOUD.COM | BB4: KHAIAKEN@SBCGLOBAL.NET | BL4: BW | BN4: =BP1 -> JOHNSON,MIKE WTR | BO4: Courtabrown88@gmail.com | BP4: majohnson3619@gmail.com | BQ4: majohnson3619@gmail.com | BR4: casino2011@gmail.com | BS4: ATLENETAMPLIN220@icloud.com | BT4: zerodark@netzero.net | BU4: www.burnsandwilcox.com | BW4: Klassykliquemj@yahoo.com | BX4: kerryanncampbell88@gmail.com | BZ4: SHARILANIER312@YAHOO. COM | CA4: corbinw27@gmail.com | CB4: CATRERAWILLIS2003@YAHOO.COM | CC4: gmail.com | CD4: LTSLIM7@GMAIL.COM | CE4: HERMANRAGLAND8268@YAHOO.COM | CF4: TERIKA86@ME.COM | CG4: CALDWELL.AMIR@GMAIL.COM
A5: H1 | B5: =$Y$1 -> Akala, Ayo VND | C5: =$I$1 -> Battle, Larry Jr | D5: Cst-owner Phone# | F5: ='[1]jobinfo(2)'!$C$67 -> BR3 CLOSET | G5: Linen CLST | H5: Basement Stairs | I5: TBD | J5: 0 | K5: STAIRS UP | M5: 2163168365 | N5: STAIRS BASEMENT | O5: - | P5: TBD | Q5: Family Room | R5: TBD | S5: RFG HOUSE | T5: (216) 262-4239 | U5: (216) 403-7739 | V5: (404) 226-8335 | W5: 216) 624-9774 | X5: (202) 830-8979 | Y5: (202) 830-8979 | Z5: (202) 830-8979 | AA5: (216) 456-1400 | AB5: (216) 456-1400 | AC5: (702) 525-1551 | AD5: (216) 851-4881 | AE5: 216 640 4975 | AF5: (216) 554-3404 | AG5: (414) 732-8842 | AH5: (216) 925-9362 | AI5: (216) 376-0509 | AJ5: 2162403945 | AK5: 216.294.5133 | AL5: (216) 403-7739 | AM5: (216) 288-5176 | AN5: (216) 334-0599 | AO5: (440) 629-9046 | AP5: (216) 408-4595 | AQ5: 2165267685 | AR5: (216) 548-8897 | AS5: (216) 399-6191 | AT5: (216) 450-4913 | AU5: (330) 951-2652 | AV5: (404) 444-1325 | AW5: (216) 315-2040 | AX5: (216) 240-4123 | AY5: (216) 224-4392 | AZ5: (216) 551-5572 | BB5: 2163241337 | BC5: (216) 8320190 | BL5: (404) 444-1325 | BN5: =BQ1 -> JOHNSON,MIKE RFG | BO5: (470) 230-2860 | BP5: (404) 380-4620 | BQ5: (404) 380-4620 | BR5: (216) 695-1629 | BS5: 478.832.4889 | BT5: (216) 476-9000 | BU5: TBD | BW5: (678) 789-2192 | BX5: (216) 855-4691 | BY5: TBD | BZ5: (216) 255-8944 | CA5: (216) 214-8560 | CB5: 2169708478 | CC5: (216) 251-5022 | CD5: (216) 632-9421 | CE5: 2162000903 | CF5: 216) 235-0005 | CG5: (216) 374-2899
A6: I1 | B6: =$J$1 -> ANDERSON, PETE | C6: =$J$1 -> ANDERSON, PETE | D6: Co-Owner.cst#2 | G6: TBD | H6: 812-235-7239 | I6: TBD | J6: Phone: (800) 326-0950 x1210210 | K6: 216.314.6086 | M6: NA | N6: NA | P6: TBD | Q6: TBD | R6: TBD | T6: TBD | U6: TERRANCE DAVIS | V6: TBD | W6: TBD | AA6: NA | AB6: NA | AC6: TBD | AD6: NA | AE6: NA | AF6: TBD | AG6: tbd | AH6: NA | AI6: Aaron Christopher Goshen | AJ6: TBD | AL6: HILLARY SMITH | AM6: TBD | AO6: TBD | AR6: TBD | AT6: TBD | AU6: TBD | AV6: MRS. | AX6: TBD | AY6: OH25 HOWARD @E55 | BB6: NA | BC6: TBD | BL6: MRS. | BN6: =BR1 -> Burns, ERIC | BP6: TBD | BQ6: TBD | BR6: na | BS6: 0 | BT6: NA | BU6: TBD | BV6: TBD | BW6: Michael Johnson | BY6: TBD | CA6: Corbin, CATHERINE | CB6: NA | CC6: TBD | CD6: TBD | CE6: MRS | CF6: TLW, LLC
A7: J1 | B7: =$I$1 -> Battle, Larry Jr | C7: =$K$1 -> WYNN, NICK | D7: cst ph # 2 | F7: ='[1]jobinfo(2)'!$C$69 -> BR2 CLOSET | G7: Bedroom # 2 | H7: LL Bathroom | I7: TBD | J7: 0 | K7: Bedroom # 1 | M7: NA | N7: Laundry Room | O7: 17 | P7: TBD | Q7: Bath Guest Flr 1 | R7: TBD | T7: TBD | U7: 2163185051 | V7: TBD | W7: 2163185051 | AA7: (216) 304-8664 | AB7: (216) 304-8664 | AC7: TBD | AD7: 216 308 5049 | AF7: TBD | AG7: tbd | AH7: NA | AJ7: TBD | AM7: TBD | AO7: 216 310 4319 | AR7: TBD | AT7: TBD | AU7: TBD | AX7: TBD | BB7: NA | BC7: TBD | BL7: TBD | BN7: =BS1 -> Tamplin, Adalene | BP7: TBD | BQ7: TBD | BR7: na | BS7: 0 | BT7: (216) 251-5022 | BU7: TBD | BW7: (404) 380-4620 | BY7: TBD | CA7: (216) 336-8742 | CB7: NA | CC7: TBD | CD7: TBD | CG7: +1 (216) 218-9027 Amir
A8: K1 | B8: =$F$1 -> Bradley, Curtis L | C8: =$L$1 -> FERGUSON, ROBERT & MRS | D8: Cst address # 2 | F8: ='[1]jobinfo(2)'!$C$56 -> Kitchen | G8: Living Room-FAMILY ROOM | H8: Kitchen | I8: BAR AREA | J8: Kitchen | K8: Dining Room | L8: CLOSET | M8: NA | N8: Nook | O8: BEDROOM1 PROTECT TRAVEL AREA | P8: Kitchen | Q8: Bathroom | R8: REC ROOM #1 /MAIN | S8: STAIRS UP | T8: TBD | U8: TBD | V8: TBD | W8: TBD | AA8: NA | AB8: NA | AC8: TBD | AD8: NA | AF8: TBD | AG8: tbd | AH8: NA | AI8: 1203 Starlight Ave | AJ8: TBD | AL8: TBD | AM8: TBD | AO8: TBD | AR8: TBD | AT8: TBD | AU8: TBD | AX8: TBD | BB8: NA | BC8: TBD | BL8: TBD | BN8: =BT1 -> George Greenawalt | BP8: TBD | BQ8: TBD | BR8: na | BS8: 0 | BT8: NA | BU8: TBD | BV8: Living Room | BW8: 3619 Rolling Green Ridge | BY8: GUEST CLOSET | CB8: NA | CC8: TBD | CD8: TBD
B9: =$AU$1 -> BROOKS, DANIEL;JANAE POA | C9: =$M$1 -> RUSH, TIFFANY LOAN # 0579206154 | D9: city, state-cst#2 | F9: ='[1]jobinfo(2)'!$C$76 -> Utility Room | G9: Master BR Closet2 | H9: TBD | I9: TBD | J9: 0 | K9: PRIMARY BR Closet | M9: NA | N9: TBD | O9: - | P9: TBD | Q9: BONUS ROOM GARAGE | R9: TBD | T9: TBD | U9: TBD | V9: TBD | W9: TBD | AA9: NA | AB9: NA | AC9: TBD | AD9: NA | AF9: TBD | AG9: tbd | AH9: NA | AI9: Aubrey TX 76227-3778 | AJ9: TBD | AL9: TBD | AM9: TBD | AO9: TBD | AR9: TBD | AT9: TBD | AU9: TBD | AX9: TBD | BB9: NA | BC9: TBD | BL9: TBD | BN9: =BU1 -> Brown, Charles | BP9: TBD | BQ9: TBD | BR9: na | BS9: 0 | BT9: NA | BU9: TBD | BW9: Atlanta, GA, 30331 | BY9: TBD | CB9: NA | CC9: TBD | CD9: TBD
B10: =$AM$1 -> Brown, Cassandra | C10: =$N$1 -> RUSH, TIFFANY WTR | D10: email-cst #2 | G10: Grange Insurance Business | H10: David Boltin | I10: TBD | J10: 0 | K10: #REF! | M10: NA | N10: TBD | O10: Attn: Consumer Affairs | P10: TBD | Q10: TBD | R10: TBD | T10: TBD | U10: TBD | V10: TBD | W10: TBD | AA10: smith.tywan@yahoo.com | AB10: smith.tywan@yahoo.com | AC10: TBD | AD10: NA | AF10: TBD | AG10: tbd | AH10: NA | AJ10: TBD | AL10: TBD | AM10: TBD | AO10: TBD | AR10: TBD | AT10: TBD | AU10: TBD | AV10: renaissancemanbs@aol.com | AX10: TBD | BB10: NA | BC10: TBD | BL10: TBD | BN10: =BV1 -> Lozano, Marcos | BP10: TBD | BQ10: TBD | BR10: na | BS10: 0 | BT10: NA | BU10: TBD | BV10: Claims Supervisor: Britt Strong | BW10: majohnson3619@gmail.com | BY10: State Farm Insurance | CB10: NA | CC10: TBD | CD10: TBD
B11: =$BB$1 -> BROWNLEE, KEN | C11: =$O$1 -> TORRES, ANGEL | D11: Cause of Loss | F11: Y | G11: Y | H11: Y | I11: Y | J11: y | K11: y | L11: y | M11: WIND & TREE | N11: Y | O11: y | P11: Y | Q11: TBD | R11: Y | S11: NA | T11: WIND/HAIL | U11: WATER | V11: Wind=Tree/HAIL | W11: WATER | X11: FIRE | Y11: VANDALISM | Z11: TREE WIND | AA11: Vandalism | AB11: TORNADO | AC11: WATER | AD11: FIRE/SMOKE | AE11: WATER | AF11: Fire & Smoke | AG11: Wind / Hail | AH11: Vehicle | AI11: WATER | AJ11: Wind=Tree | AK11: WATER LEAK | AL11: WATER | AM11: Water | AN11: FIRE | AO11: WATER | AP11: WATER | AQ11: WATER | AR11: FIRE | AS11: WATER | AT11: BATHTUB OVERFLOW | AU11: WATER PIPE BROKE | AV11: KITCHEN WATER PIPE BROKE | AW11: Water Damage=WTR | AX11: BATHTUB OVERFLOW | AY11: Wind / Hail | AZ11: WATER BATHTUB OVERFLOW | BB11: WATER | BC11: BROKEN WATER LINE | BL11: KITCHEN WATER PIPE BROKE | BN11: =BW1 -> Johnson, Margaret | BO11: Wind / Hail | BP11: WATER | BQ11: Water | BR11: wind tree | BS11: Wind = Roof | BT11: FIRE GARAGE | BU11: TBD | BV11: TBD | BW11: WIND & TREE | BX11: FIRE | BY11: N | BZ11: WINDSTORM AND HAIL | CA11: Wind / Hail | CB11: WATER | CC11: WIND | CD11: Wind / Hail | CE11: WIND | CF11: Tornado | CG11: WIND
B12: =$AJ$1 -> Brownlee. LAVERNE | C12: =$P$1 -> Harvey, CORA | D12: date of loss | F12: Y | G12: Y | H12: Y | I12: Y | J12: tbd | K12: tbd | L12: y | M12: 45331 | N12: Y | O12: tbd | P12: Y | Q12: TBD | R12: Y | S12: TBD | T12: 45163 | U12: TBD | V12: 45390 | W12: 45483 | X12: 45476 | Y12: 45476 | Z12: 45526 | AA12: 45511 | AB12: 45510 | AC12: 45402 | AD12: 45524 | AE12: 45568 | AF12: 45330 | AG12: 45335 | AH12: 45510 | AI12: 45563 | AJ12: 45618 | AK12: 44858 | AL12: 45628 | AM12: 45686 | AN12: Sunday, March 2, 2025 | AO12: 45735 | AP12: Wednesday, March 19, 2025 | AQ12: 45735 | AR12: Friday, August 16, 2024 | AS12: 45751 | AT12: 45765 | AU12: Sunday, March 2, 2025 | AV12: Tuesday, March 11, 2025 | AW12: Friday, September 12, 2025 | AX12: 45824 | AY12: 45827 | AZ12: Saturday, August 26, 2025 | BB12: 45986 | BC12: 46062 | BL12: Tuesday, March 11, 2025 | BN12: =BX1 -> Carib Investment ,LLC | BO12: 45570 | BP12: 45330 | BQ12: 45330 | BR12: 45618 | BS12: 44312 | BT12: 44638 | BU12: TBD | BV12: TBD | BW12: 45329 | BX12: 45739 | BY12: N | BZ12: 45721 | CA12: 45521 | CB12: 45563 | CC12: 45163 | CD12: 45163 | CE12: 45510 | CF12: 45510 | CG12: 45529
B13: =$AP$1 -> Burns2, RUBY | C13: =$Q$1 -> ROBINSON, NiKKole | D13: rebuild type 1 | F13: Y | G13: Y | H13: Y | I13: Y | J13: y | K13: y | L13: y | M13: ROOF REPAIR | N13: Y | O13: TBD | P13: Y | Q13: TBD | R13: Y | S13: TBD | T13: ROOF | U13: Interior Repairs LEVEL 1 &2 | V13: ROOF Exterior | W13: Interior Repairs LEVEL 1 | Z13: roofing shingles replacement | AA13: Interior Repairs LEVEL 1 | AB13: ROOF SHINGLES | AC13: Interior Repairs | AD13: Interior Repairs LEVEL 1 | AE13: Interior Repairs LEVEL 1 | AF13: interior repairs | AG13: ROOF REPLACE SHINGLES | AH13: VEHICLE HIT EAST SIDE OF THE HOME, OPPOSITE OF THE DRIVEWAY | AI13: interior repairs | AJ13: ROOF REPLACE SHINGLES | AK13: interior repairs | AL13: Interior Repairs LEVEL 1 | AM13: INTERIOR ROOMS IMPACTED | AN13: interior repairs | AO13: INTERIOR ROOMS IMPACTED | AP13: Interior Repairs LEVEL 1 | AQ13: Interior Repairs LEVEL 1 | AR13: DOORS/PORCHES EXT | AS13: Interior Repairs LEVEL 1 | AT13: interior repairs LVL2 | AU13: interior repairs | AV13: interior repairs | AW13: interior repairs LVL1 | AX13: interior repairs LVL2 | AY13: ROOF | AZ13: interior repairs LVL1 | BB13: interior repairs LVL1 | BC13: interior repairs LVL1 | BL13: interior repairs | BN13: =BY1 -> Franklin Annette | BO13: ROOF DAMAGE | BP13: interior repairs | BQ13: roof shingles | BR13: TREE HIT HOUSE FROM WIND STROM | BS13: roofing shingles replacement | BT13: exterior repairs | BU13: TBD | BV13: TBD | BW13: roofing shingles replacement | BX13: interior repairs | BY13: N | BZ13: Interior Repairs LEVEL 2 | CA13: Homesite | CB13: roofing shingles replacement | CC13: ROOF | CD13: roofing shingles replacement | CF13: SHED | CG13: ROOF EXTERIOR
B14: =$AQ$1 -> CARTER, KAREN | C14: =$R$1 -> LEETH, RONNIE | D14: rebuild type 2 | F14: grangeinsurance.com | G14: TBD | H14: claims@claims.allstate.com | I14: TBD | J14: 0 | K14: #REF! | M14: EXT REPAIRS | N14: BETH.OLDFORD@RYSECLAIMS.COM.BETH | P14: TBD | Q14: TBD | R14: TBD | T14: SIDING | V14: interior repairs | W14: Interior Repairs LEVEL 2 | Z14: exterior repairs | AA14: Interior Repairs LEVEL 2 | AB14: Interior Repairs LEVEL 3 | AD14: Interior Repairs LEVEL 2 | AE14: Interior Repairs LEVEL 2 | AF14: interior repairs | AG14: EXTERIOR REPAIRS | AH14: BRICK | AI14: interior repairs | AJ14: Interior Repairs LEVEL 1 | AK14: NA | AL14: Interior Repairs LEVEL 2 | AM14: TBD | AN14: ALL LEVELS | AO14: TBD | AR14: SDG | AS14: Interior Repairs LEVEL 2 | AT14: interior repairs LVL1 | AU14: interior repairs | AV14: interior repairs | AW14: interior repairs LVL2 | AX14: interior repairs LVL1 | AY14: interior repairs LVL2 | AZ14: interior repairs LVL2 | BB14: interior repairs LVL2 | BC14: BASEMENT | BL14: interior repairs | BN14: =BZ1 -> Lanier, Shari | BO14: INTERIOR ROOMS IMPACTED | BP14: interior repairs | BQ14: interior repairs | BR14: ROOF SHINGLES | BS14: interior repairs | BT14: exterior repairs | BU14: TBD | BV14: wgrace@alacritysolutions.com | BW14: interior repairs | BY14: TBD | BZ14: SIDING | CA14: INTERIOR ROOMS IMPACTED | CC14: INTERIOR REPAIRS | CD14: interior repairs | CE14: Interior Repairs LEVEL 2 | CF14: TREE REMOVAL | CG14: AWNING EXT
B15: =$AR$1 -> CHERRY, LAUREN LB8997 | C15: =$S$1 -> LANEY, Anthony | D15: rebuild type 3 | G15: TBD | H15: Drew over at Paul Davis. | I15: TBD | J15: Dunn Sterling | K15: #REF! | L15: CLEMENTS, NATASHA | M15: WTR INT FOYER | N15: OLDFORD, BETH | O15: Ins Adj Trvlr David Walker | P15: TBD | Q15: 0 | R15: Ann.Conway@usaa.com | T15: INTERIOR REPAIRS | V15: TBD | W15: TBD | AA15: Interior Repairs BSMNT | AB15: TBD | AD15: Interior Repairs LEVEL3 | AE15: Interior Repairs BSMNT | AF15: TBD | AG15: Interior Repairs LEVEL 1 &2 | AH15: SIDING | AJ15: Interior Repairs LEVEL 2 &3 | AK15: NA | AL15: Interior Repairs LEVEL 3 | AM15: TBD | AN15: EXTERIOR REPAIRS | AO15: TBD | AR15: Interior Repairs LEVELS = 4 | AT15: BASEMENT | AU15: TBD | AV15: TBD | AX15: BASEMENT | AY15: interior repairs LVL1 | AZ15: interior repairs BSMNT | BL15: TBD | BN15: =CA1 -> Corbin, Wanda | BO15: PBR CLST, BR2, BR1 CLST, LINEN, GARAGE | BP15: TBD | BQ15: TBD | BR15: INTERIOR DAMAGE | BS15: exterior repairs | BT15: exterior repairs | BW15: exterior repairs | BY15: Jason 931-629-2250 | BZ15: ROOF | CA15: KIT/Bath/LINEN/BR1 CLST | CB15: TBD | CC15: INTERIOR REPAIRS | CD15: TBD | CF15: GAZEBO | CG15: Interior Repairs LEVEL 3
B16: =$AD$1 -> Collins, Darlene | C16: =$T$1 -> LAWRENCE, GENEATHA | D16: DEMO | F16: grangeinsurance.com | G16: BenczeR@Grangeinsurance.com | H16: claims@claims.allstate.com | I16: tbd | J16: claims@claims.allstate.com | K16: orlando.reyes@libertymutual.com | L16: statefarmfireclaims@statefarm.com | M16: TBD | N16: TBD | O16: mptaylor@travelers.com | P16: ASIA.BABLES@LIBERTYMUTUAL.COM | Q16: Nicole.Schaumleffel@libertymutual.com | R16: 432v85zlpxmb@claims.usaa.com | S16: benjamin.bybee@allstate.COM | T16: Y | U16: Y | V16: Y | W16: Y | AA16: Y | AB16: Y | AC16: N | AD16: Y | AE16: Y | AF16: Y | AG16: Y | AH16: INTERIOR | AI16: Y | AJ16: Y | AK16: y | AL16: Y | AM16: Y | AN16: Y | AO16: Y | AP16: Y | AQ16: Y | AR16: Y | AS16: Y | AT16: Y | AU16: Y | AV16: Y | AW16: Y | AX16: Y | AY16: Y | AZ16: Y | BB16: Y | BC16: Y | BL16: Y | BN16: =CB1 -> WILLIS, CATRERA | BO16: Y | BP16: Y | BQ16: Y | BR16: y | BS16: Y | BT16: Y | BV16: candacebrown@alacritysolutions.com | BW16: Y | BY16: statefarmfireclaims@statefarm.com | CA16: Y | CB16: Y | CC16: Y | CD16: TBD | CE16: Y | CF16: Y
B17: =$AB$1 -> Cousette, JOHN ROOF | C17: =$U$1 -> SMITH, JANET | D17: Mitigation | G17: TBD | H17: TBD | I17: TBD | J17: 0 | K17: #REF! | M17: TBD | N17: TBD | O17: 0 | P17: TBD | Q17: TBD | R17: TBD | T17: Y | U17: Y | V17: Y | W17: Y | AA17: Y | AB17: Y | AC17: N | AD17: Y | AE17: Y | AF17: Y | AG17: Y | AH17: Y | AI17: Y | AJ17: Y | AK17: y | AL17: Y | AM17: Y | AN17: Y | AO17: Y | AP17: Y | AQ17: Y | AR17: Y | AS17: Y | AT17: Y | AU17: Y | AV17: Y | AW17: Y | AX17: Y | AY17: Y | AZ17: Y | BB17: Y | BC17: Y | BL17: Y | BN17: =CC1 -> Greenawalt, Mike | BO17: Y | BP17: Y | BQ17: Y | BR17: y | BS17: Y | BT17: NA | BU17: TBD | BW17: Y | BY17: TBD | CA17: Y | CB17: Y | CC17: Y | CD17: TBD | CE17: Y | CF17: Y
B18: =$AA$1 -> Cousette, JOHN Vandalism | C18: =$V$1 -> Wimbish, Tawana | D18: Other Structures | F18: C: 216-559-6953 | G18: (614) 593-7718 | H18: 8886568005 | I18: ext | J18: ext (1213490) | K18: 330-437-6722 | M18: NA | N18: TBD | O18: 813.731.6489 | P18: 469 997 2808 | Q18: 1 (757) 854-8187 | R18: 44453 | S18: x1225768 | T18: TBD | U18: NA | V18: NA | W18: NA | AA18: NA | AB18: NA | AC18: N | AD18: NA | AE18: NA | AF18: NA | AG18: TBD | AH18: TBD | AI18: Y | AJ18: NA | AK18: na | AL18: NA | AM18: Y | AN18: NA | AO18: NA | AP18: N | AQ18: N | AR18: NA | AS18: N | AT18: NA | AU18: NA | AV18: NA | AW18: NA | AX18: NA | AY18: NA | AZ18: NA | BB18: NA | BC18: NA | BL18: NA | BN18: =CD1 -> THOMAS, LISA | BO18: Y | BP18: NA | BQ18: NA | BR18: GARAGE | BS18: TBD | BT18: Y | BV18: X591641 | BW18: NA | BY18: ext | CA18: GARAGE | CB18: NA | CC18: TBD | CD18: TBD | CE18: Y | CF18: Y
B19: =$AK$1 -> Craig Ringo | C19: =$W$1 -> HICKS, JASON | D19: Replacement | F19: ='[1]jobinfo(2)'!$C$58 -> Back Foyer | G19: Hallway- DN | H19: Stairs Up | I19: CLOSET | J19: Stairs UP | K19: Kitchen | L19: STAIRS DN | M19: NA | N19: Bath @ Rear Foyer | O19: Linen Closet HALL | P19: Pantry/HALL | Q19: Guest Closet | R19: BATH | S19: PBR | T19: Y | U19: Y | V19: Y | W19: Y | AA19: Y | AB19: Y | AC19: Y | AD19: Y | AE19: Y | AF19: Y | AG19: Y | AH19: Y | AI19: Y | AJ19: Y | AK19: y | AL19: Y | AM19: Y | AN19: Y | AO19: Y | AP19: Y | AQ19: Y | AR19: Y | AS19: Y | AT19: Y | AU19: Y | AV19: Y | AW19: Y | AX19: Y | AY19: Y | AZ19: Y | BB19: Y | BC19: Y | BL19: Y | BN19: =CE1 -> Ragland | BO19: Y | BP19: Y | BQ19: Y | BR19: y | BS19: Y | BT19: Y | BU19: TBD | BV19: Kitchen | BW19: Y | BY19: PBR CLOSET | CA19: Y | CB19: Y | CC19: Y | CD19: TBD | CE19: Y | CF19: Y
B20: =$AO$1 -> Dejarnette Mattie | C20: =$X$1 -> Akala, Ayo SMOKE FIRE | D20: CPS / CLN / CON/ CGN | F20: ='[1]jobinfo(2)'!$C$59 -> Stairs Up | G20: LR CLOSET2 DN | H20: Up Hallway | I20: LAUNDRY | J20: Hallway- up | K20: BATH DN | L20: REC ROOM | M20: NA | N20: Dining Room | O20: Bedroom 2 TRAVEL AREA | P20: STAIRS UP | Q20: Bedroom 3 | R20: LAUNDRY | S20: PBR CLST | T20: Y | U20: Y | V20: Y | W20: Y | AA20: NA | AB20: NA | AC20: Y | AD20: NA | AE20: Y | AF20: Y | AG20: Y | AH20: Y | AI20: Y | AJ20: Y | AK20: y | AL20: Y | AM20: Y | AN20: Y | AO20: Y | AP20: Y | AQ20: Y | AR20: TBD | AS20: Y | AT20: Y | AU20: Y | AV20: Y | AW20: Y | AX20: Y | AY20: NA | AZ20: NA | BB20: Y | BC20: Y | BL20: Y | BN20: =CF1 -> Webb, Terika | BO20: Y | BP20: Y | BQ20: Y | BR20: y | BS20: Y | BT20: Y | BU20: TBD | BV20: Pantry | BW20: Y | BY20: STAIRS UP TRAVEL | CA20: Y | CB20: Y | CC20: Y | CD20: TBD | CE20: Y | CF20: Y
B21: =$L$1 -> FERGUSON, ROBERT & MRS | C21: =$Y$1 -> Akala, Ayo VND | D21: Year Built | F21: GRANGE 800-422-0550 | G21: TBD | H21: claims@claims.allstate.com | I21: TBD | J21: 0 | K21: 0 | M21: PRE 1978 | N21: TBD | O21: 0 | P21: TBD | Q21: 0 | R21: TBD | S21: (800) 354-2172 | T21: PRE 1980 | U21: PRE 1978 | V21: TBD | W21: PRE 1978 | AA21: PRE 1978 | AB21: PRE 1978 | AC21: POST 1978 | AD21: PRE 1978 | AE21: POST 1978 | AF21: TBD | AG21: TBD | AH21: PRE 1978 | AI21: POST 1978 | AJ21: PRE 1978 | AK21: 2016 | AL21: PRE 1978 | AM21: PRE 1978 | AN21: POST 1978 | AO21: PRE 1978 | AP21: POST 1978 | AQ21: POST 1978 | AR21: PRE 1978 | AS21: POST 1978 | AT21: PRE 1978 | AU21: POST 1978 | AV21: POST 1978 | AW21: 1920 | AX21: PRE 1978 | AY21: 1920 | AZ21: POST 1978 | BB21: 1956 | BC21: POST 1978 | BL21: POST 1978 | BN21: =CG1 -> Red Ink CLE LLC Amir | BO21: POST 1978 | BP21: TBD | BQ21: TBD | BR21: POST 1978 | BS21: post 1980 | BT21: PRE 1978 | BU21: 216.654.1548 | BW21: pre 1980 | CA21: POST 1978 | CB21: POST 1978 | CC21: PRE 1980 | CD21: TBD | CE21: PRE 1978 | CF21: 1991
B22: =$AI$1 -> Goshen, Aaron & Shania | C22: =$Z$1 -> Akala, Ayo TREE | D22: Contract Date | G22: PA 18002 | H22: Fax: (866) 447-4293 | I22: TBD | J22: 0 | K22: 469.997.6270 | N22: TBD | O22: Hartford, CT 06183 | P22: TBD | Q22: TBD | R22: TBD | T22: 45165 | U22: TBD | V22: 45371 | W22: 45483 | AA22: 45511 | AB22: 45511 | AC22: 45405 | AD22: 45525 | AE22: =AE12 -> 45568 | AF22: 45330 | AH22: 45545 | AI22: 45564 | AJ22: 45618 | AK22: 44858 | AL22: =AL12 -> 45628 | AM22: 45693 | AN22: 45727 | AO22: 45737 | AP22: Wednesday, March 26, 2025 | AQ22: 45742 | AR22: Sunday, April 6, 2025 | AS22: 45751 | AT22: 45822 | AU22: 45721 | AV22: 45727 | AW22: 45836 | AX22: 45826 | AY22: 45836 | AZ22: 45896 | BB22: =BB12+1 -> 45987 | BL22: 45727 | BN22: =CH1 -> 0 | BO22: 45571 | BP22: 45330 | BQ22: 45330 | BR22: 45620 | BS22: 44316 | BT22: 45353 | BU22: TBD | BV22: bjstrong@alacritysolutions.com | BW22: 45332 | BY22: Bloomington, IL 61710 | CA22: 45571 | CB22: 45569 | CC22: 45165 | CD22: 45189 | CE22: 45569 | CF22: 45511
B23: =$P$1 -> Harvey, CORA | C23: =$AA$1 -> Cousette, JOHN Vandalism | D23: Loss of use/ ALE | E23: JOB INFO | F23: 3525 West 47th Str | G23: 255 DOVECOTE TRACE | H23: 4514 Wellington Avenue | I23: 6389 South Canterbury Road | J23: 771 Edgewood Rd, | K23: 331 ROYAL OAK DR | L23: 23542 Hillcroft Drive | N23: 956 Roanoke Road, | O23: 1201 SPRINGWOOD DR NW | P23: 5125 Greenhurst Extension | Q23: 357 E 270TH ST | R23: 2079 Miami Road | S23: 1439 West 98th Str | T23: Y | U23: NA | V23: Y | W23: TBD | AA23: Y | AB23: Y | AC23: Y | AD23: Y | AE23: TBD | AF23: Y | AG23: NA | AH23: Y | AI23: Y | AJ23: NA | AK23: y | AL23: TBD | AM23: Y | AN23: Y | AO23: TBD | AP23: TBD | AQ23: TBD | AR23: TBD | AS23: Y | AT23: Y | AU23: Y | AV23: Y | AW23: TBD | AX23: Y | AY23: TBD | AZ23: TBD | BB23: Y | BC23: NA | BL23: Y | BO23: NA | BP23: Y | BQ23: Y | BR23: y | BS23: sample cost 3 | BT23: Y | BU23: 36875 PEPPER DR | BV23: 5992 HIDDEN HOLM LN | BW23: Y | BY23: 750 East 256th | CA23: NA | CB23: Y | CC23: Y | CD23: TBD | CE23: NA | CF23: NA
B24: =$AX$1 -> Hatten, Nedra | C24: =$AB$1 -> Cousette, JOHN ROOF | D24: Breathing issue | E24: =D22 -> Contract Date | F24: Cleveland, OH | G24: MACEDONIA, OH 44056 | H24: Parma, OH, 44134 | I24: Parma,Ohio 44129 | J24: Richmond Heights, OH 44143 | K24: RICHMOND HGTS.,OH 44143 | L24: Warrensville Heights, OH, 44128 | N24: Cleveland Heights, OH | O24: CONYERS, GA 30012 | P24: Maple Heights, OH | Q24: EUCLID OH 44132-1603 | R24: Euclid, OH, | S24: Cleveland, OH | T24: Y | U24: TBD | V24: Y | W24: TBD | AA24: TBD | AB24: TBD | AC24: Y | AD24: Y | AE24: Y | AF24: Y | AG24: TBD | AH24: TBD | AI24: Y | AJ24: TBD | AK24: TBD | AL24: TBD | AM24: TBD | AN24: TBD | AO24: TBD | AP24: TBD | AQ24: TBD | AR24: TBD | AS24: TBD | AT24: TBD | AU24: TBD | AV24: TBD | AW24: TBD | AX24: TBD | AY24: TBD | AZ24: TBD | BB24: TBD | BC24: TBD | BL24: TBD | BO24: TBD | BP24: Y | BQ24: Y | BR24: TBD | BS24: doctor letter | BT24: TBD | BU24: Cleveland, OH 44139 | BV24: AUSTELL, GA 30168 | BW24: tbd | BY24: Euclid, OH | CA24: TBD | CB24: Y | CC24: Y | CD24: TBD | CE24: Y | CF24: NA
B25: =$W$1 -> HICKS, JASON | C25: =$AC$1 -> JONES, BREANNA | D25: HMR | E25: A1 | F25: curtisbradley10@gmail.com | G25: eakoswatta@aol.com | H25: blw8958@gmail.com | I25: lbjr77@gmail.com | J25: drama_kenn2002@yahoo.com | K25: nickwynn24@gmail.com | L25: F@gmail.com | N25: dr.tiffanyrw@counselingsecure.com | O25: ngeelectric@gmail.com | P25: harvcora@icloud.com | Q25: nikkolenrob@aol.com | R25: leeth123@roadrunner.com | S25: AnthonyLANEY26@GMAIL.COM | T25: Y | U25: TBD | V25: Y | W25: TBD | AA25: Y | AB25: Y | AC25: TBD | AD25: Y | AE25: TBD | AF25: Y | AH25: TBD | AI25: TBD | AJ25: TBD | AK25: TBD | AL25: TBD | AM25: TBD | AN25: TBD | AO25: TBD | AP25: TBD | AQ25: TBD | AR25: TBD | AS25: TBD | AT25: TBD | AU25: TBD | AV25: TBD | AW25: TBD | AX25: TBD | AY25: TBD | AZ25: TBD | BB25: TBD | BC25: TBD | BL25: TBD | BO25: TBD | BP25: Y | BQ25: Y | BR25: TBD | BS25: lab test | BT25: TBD | BU25: CARWASH1946@YAHOO.COM | BV25: ml_aps@yahoo.com | BW25: Y | BY25: estrictfranklin@gmail.com | CA25: TBD | CB25: TBD | CC25: Y | CD25: TBD | CE25: TBD | CF25: TBD
B26: =$AY$1 -> HOWARD, MATTHEW | C26: =$AD$1 -> Collins, Darlene | D26: Insurance Co. Name | E26: =D157 -> 0 | F26: (216) 334-6445 | G26: (216) 219-1054 | H26: (216) 512-4318 | I26: 216) 224-1548 | J26: (216) 894-1563 | K26: 216.712.0152 | L26: (216) 785-1363 | M26: NATIONAL FIRE & MARINE | N26: 2163168265 | O26: 678-646-7704 | P26: (216) 407-1810 | Q26: (440) 431-7350 | R26: 216) 255-2231 | S26: (216) 299-6104 | T26: State Farm | U26: TBD | V26: STATEFARM | W26: STATE FARM INS | X26: STATE FARM | Y26: STATE FARM | Z26: STATE FARM | AA26: STATE FARM | AB26: STATE FARM | AC26: Trisura Insurance Company. | AD26: STATE FARM | AE26: ALLSTATE | AF26: Westfield Insurance | AG26: Statefarm | AH26: State Farm | AI26: STATE FARM | AJ26: State Farm | AK26: QBE INS | AL26: GEICO/HOMESITE | AM26: Allstate Insurance Company | AN26: Allstate Insurance Company | AO26: Allstate Insurance Company | AP26: STATE FARM | AQ26: FARMERS | AR26: Spinnaker Insurance Company | AS26: Allstate Vehicle and Property Insurance Co | AT26: AAA Insurance | AU26: Allstate Insurance Company | AV26: Esurance | AW26: ALLSTATE INS CO. | AX26: LIBERTY MUTUAL | AY26: SAFECO # | AZ26: ASSURANT INS | BB26: ALLSTATE INS CO. | BC26: AMERICAN FAMILY | BL26: Esurance | BO26: Allstate | BP26: STATEFARM | BQ26: STATEFARM | BR26: GRANGE | BS26: STANDARD GUARANTY INS. CO. | BT26: Alstate 0662951359 | BU26: (216) 402-0049 | BV26: 956.371.3974 | BW26: Universal Ins | BX26: STATE FARM | BY26: 216-407-6481 | BZ26: Allstate Vehicle and Property Insurance Co | CA26: Homesite | CB26: Geigo I | CC26: TBD | CD26: STATE FARM | CE26: PROGRESSIVE | CF26: STATE FARM | CG26: Erie
B27: =$AN$1 -> Hurt, Chaunte | C27: =$AE$1 -> NEWMAN, NICOLE | D27: Claim # | E27: w | F27: TBD | G27: TBD | H27: TBD | I27: tbd | J27: vnssmrshll@yahoo.com | K27: #REF! | L27: MRS. | M27: BH01737488 | N27: #0579206154LoaN | O27: na | P27: TBD | Q27: TBD | R27: tbd | S27: TBD | T27: 3556W964G | U27: CLM | V27: CLM 11- 65W674M | W27: 3570V537Z | Y27: CLM3570X095J | Z27: 3573K614T | AA27: 3572C952H | AB27: 3571Z117Q | AC27: TIC-00005092 | AD27: 3572Q140L | AE27: #0771511680 | AF27: #002534872 | AG27: 11-63G7-91F | AH27: 3572H977V | AI27: 3574M271X | AJ27: 3577Q641P | AK27: 873368N | AL27: # 01-008-402478 | AM27: #0782519052 | AN27: #0785946666 | AO27: #0787407485 | AP27: 3582G431B | AQ27: 7008788987-1 | AR27: 24PROH621255022 | AS27: 0790205199 | AT27: #017095711 | AU27: #0786294926 | AV27: #250254318 | AW27: 0807044169 | AX27: #059633981 | AY27: 059597581-01 | AZ27: 00201936986 | BB27: 0814056289 | BC27: TBD | BL27: 250254318 | BO27: #0772562245 | BP27: 1163C742W | BQ27: 1163C746F | BR27: ZHM003759154 | BS27: 00201358720 | BT27: Alstate 0662951359 | BU27: TBD | BV27: TBD | BW27: GA240100643 | BX27: 3582G711L | BY27: TBD | BZ27: 0786750778 | CA27: 1007995316 | CC27: TBD | CD27: 35 | CE27: 01-007-956327 | CF27: 3573H030H | CG27: A00006100647
B28: =$BC$1 -> HUTCHINSON | C28: =$AF$1 -> Peggy Henderson | D28: policy # | E28: =FINAL_INVOICES_STATEMENT -> DA Ph. Ext. # | F28: TBD | G28: TBD | H28: TBD | I28: TBD | J28: 0 | K28: #REF! | M28: 42PFP26378901 | N28: (678) 789-2192 | O28: na | P28: TBD | Q28: TBD | R28: TBD | S28: TBD | T28: PL | U28: PL | V28: 11-EY-B111-9 | W28: 70 CJ 385 L3 | X28: 95GDC4816 | Y28: 95GDC4816 | Z28: 95GDC4816 | AA28: 95EMD4258 | AB28: 95EMD4258 | AC28: 83915278 | AD28: 70-C4-Y732-1 | AE28: 826 781 155 | AF28: TBD | AG28: 11EAP8759 | AH28: 70CRP2953 | AI28: 70EHX4312 | AJ28: 70-CA-H811-3 | AK28: PHP4140181 | AL28: 38748576 | AM28: 880 0025757 | AN28: Policy 992755402 | AO28: 126 061 389 | AP28: PL | AQ28: PL# | AR28: DOH-10908612-01 | AS28: 826763419 | AT28: OHH000190052 | AU28: 980 610 253 | AV28: : 10610052 | AW28: 880 022 226 | AX28: H3V28806334771 | AY28: OK7558571 | AZ28: 2MR07293165041 | BB28: PL# 026-164-325 | BC28: # 41105-87553 | BL28: PL# | BO28: 885015525 | BP28: TBD | BQ28: TBD | BR28: TBD | BS28: MIP-RCH-00755-99 | BT28: TBD | BU28: TBD | BV28: TBD | BW28: 1701-1601-0661 | BX28: 95J8Y8775 | BY28: TBD | BZ28: 000880016618 | CA28: 39209494 | CB28: REN 1945339 | CC28: TBD | CD28: TBD | CE28: 38353012 | CF28: 95-J8-M309-7 | CG28: Q61 0295794
B29: =$AS$1 -> Johnson, Paul & Tamra | C29: =$AG$1 -> Romero Beverly | D29: Email INS. co. | E29: A154 | F29: TBD | G29: TBD | H29: TBD | I29: TBD | J29: na | K29: na | M29: BSCHEUER@PROCTORLP.COM | N29: TBD | O29: na | P29: TBD | Q29: TBD | R29: TBD | S29: TBD | T29: statefarmfireclaims@statefarm.com | U29: TBD | V29: STATEFARM | W29: TBD | Y29: statefarmfireclaims@statefarm.com | AA29: statefarmfireclaims@statefarm.com | AB29: statefarmfireclaims@statefarm.com | AD29: statefarmfireclaims@statefarm.com | AE29: CLAIMS@CLAIMS.ALLSTATE.COM | AF29: TBD | AG29: statefarmfireclaims@statefarm.com | AH29: statefarmfireclaims@statefarm.com | AJ29: statefarmfireclaims@statefarm.com | AK29: CLAIMMAIL@US.QBE.COM | AL29: Jameka.Hines@afics.com | AM29: claims@claims.allstate.com | AN29: claims@claims.allstate.com | AO29: claims@claims.allstate.com | AP29: statefarmfireclaims@statefarm.com | AQ29: myclaim@farmersinsurance.com | AR29: info+emld300ef05ab65@claims.hippo.com | AS29: claims@claims.allstate.com | AT29: STAPLES.OLIVIA @ace.aaa.com | AU29: claims@claims.allstate.com | AV29: carla.robledo@ngic.com | AW29: claims@claims.allstate.com | AX29: IMAGING@LIBERTYMUTUAL.COM | AZ29: MYCLAIMINFO@ASSURANT.COM | BB29: claims@claims.allstate.com | BL29: TBD | BO29: claims@claims.allstate.com | BP29: statefarmfireclaims@statefarm.com | BQ29: statefarmfireclaims@statefarm.com | BR29: BenczeR@Grangeinsurance.com | BS29: myclaiminfo@assurant.com | BU29: TBD | BV29: TBD | BW29: claimpathuniversalproperty.com | BX29: statefarmfireclaims@statefarm.com | BY29: TBD | BZ29: claims@claims.allstate.com | CC29: TBD | CD29: TBD | CE29: CLIMDOCUMENTS@AFICS.COM | CF29: statefarmfireclaims@statefarm.com
B30: =$AC$1 -> JONES, BREANNA | C30: =$AH$1 -> TAYLOR DAVIDSON, WARREN | D30: DESK Adjuster DA | F30: TBD | G30: POST 1978 | H30: TBD | I30: PRE 1980 | J30: POST 1978 | K30: POST 1978 | L30: AFTER 1980 | M30: SCHEUER, BRANDON | N30: TBD | O30: POST 1980 | P30: PRE 1980 | Q30: BEFORE 1980 | R30: PRE 1980 | S30: PRE 1978 | T30: DA | U30: TBD | V30: TBD | W30: TBD | Y30: RAMOS, ROSELYN | Z30: TARA HARRINGTON | AA30: RAMOS, ROSELYN | AB30: FOWLER, CHARITY | AC30: Owen Hanbury | AD30: RAMOS, ROSELYN | AF30: TBD | AG30: James Hudson | AH30: GIESEY, MATT 309 834 9661 | AI30: Amy Irwin | AJ30: GIESEY, MATT 309 834 9661 | AK30: Stewart Pile, Monica | AL30: Jameka.Hines | AM30: Spencer GASTON, Large Loss | AN30: Spencer GASTON, Large Loss | AO30: 0 | AR30: Brandon Timmins | AS30: KRISTEN | AT30: STAPLES, OLIVIA 207 776 6150 | AU30: LYLE KENDICKS | AV30: Carla Robledo| | AW30: Ticora Thomas | AX30: NICOLE.FITZGERALD | AY30: Goddraneika Merrill (469)242-7605 | AZ30: PERO, EMMANUEL | BB30: MEAGAN CHASAR, LRG LOSS ADJ | BL30: Carla Robledo| Homeowners Senior Inside Rep | BO30: CHARLES SCNIDIER | BP30: Tia Dortch | BQ30: SARAH KENNEDY | BR30: Rachael Bencze | BS30: Elaine Gebsbher | BU30: POST 1980 | BV30: POST 1978 | BW30: STERLING X1702 | BX30: RAMOS, ROSELYN | BY30: PRE 1980 | BZ30: Simon Moncada | CA30: WALKER, STEPHEN | CC30: TBD | CD30: TBD | CF30: RICHARD, CATHERINE
B31: =$G$1 -> KOSWATTA, ERIKA | C31: =$AI$1 -> Goshen, Aaron & Shania | D31: DA Phone | F31: grangeinsurance.com | G31: BenczeR@Grangeinsurance.com | H31: claims@claims.allstate.com | I31: tbd | J31: claims@claims.allstate.com | K31: #REF! | L31: EM | M31: (877) 491-7277. | N31: TBD | O31: consumeraffairs@travelers.com | P31: ASIA.BABLES@LIBERTYMUTUAL.COM | Q31: Nicole.Schaumleffel@libertymutual.com | R31: tbd | S31: claims@claims.allstate.com | T31: 844-458-4300 | U31: TBD | V31: TBD | W31: TBD | Y31: 844-458-4300 | AA31: 844-458-4300 | AB31: (866) 787-8678 | AC31: 844-503-7101 | AD31: 844-458-4300 | AF31: TBD | AG31: 1(866) 787 8676 Ext. 16799 | AK31: 844.723.2524 | AL31: 251-665-8527 | AM31: 888 656.8005 | AN31: (888) 656-8005 | AO31: 888 656.8005 | AQ31: HEATHER.CASOLA | AR31: Property Adjuster, Property Claims | Hippo Insurance Services | AS31: 888 656.8005 | AT31: 207 776 6150 | AU31: 888 656.8005 | AV31: (800) 378-7262 | AW31: (540) 725-6641 | AX31: 8002252467 | AY31: (469)242-7605 | AZ31: 800 358 0600 X 4030304 | BB31: 8007296400 | BL31: (800) 378-7262 | BP31: 8444584300 | BQ31: TBD | BR31: (614) 593-7718 | BS31: 1.800.358.0600 | BV31: MSI.SUPPORT@ALACRITYSOLUTIONS.COM | BW31: (800) 425-9113 | BX31: 844-458-4300 | BY31: statefarmfireclaims@statefarm.com | BZ31: (224) 559-9178 | CA31: (608) 286-8911 | CC31: TBD | CD31: TBD | CF31: 844 458 4300 | CG31: #VALUE!
A32: I | B32: =$AT$1 -> LACEY, EUNICE | C32: =$AJ$1 -> Brownlee. LAVERNE | D32: DA Ph. Ext. # | F32: 614-445-2880 | G32: (614) 593-7718 | H32: 8886568005 | I32: tbd | J32: 800-252-8294 | K32: 800-2-CLAIMS | L32: 844 458 4300 | M32: 8005216800 | N32: TBD | O32: 1.800.252.4633 | P32: 469 997 2808 | Q32: 1 (757) 854-8187 | R32: 800.531.8722 | S32: (800) 354-2172 | T32: ext | U32: TBD | V32: TBD | W32: TBD | Y32: 3097632550 | AA32: 3097632550 | AB32: 8667878678 X 5620 | AC32: FL License #: G087288 | AD32: 3097632550 | AF32: TBD | AG32: 1(866) 787 8676 Ext. 16799 | AI32: (972) 732-5783 | AK32: 770.303.2737 | AL32: Jameka.Hines@afics.com | AM32: 330 224-5157 | AN32: (330) 224-5157 | AO32: 0 | AQ32: 4044656346 | AR32: 855-999-9746 x 7476 | AS32: 8008173220 | AT32: 207 776 6150 | AU32: 9892774564 | AV32: (336) 331-6825 | AW32: (540) 725-6641 | AX32: 4692427672 | AY32: (469)242-7605 | AZ32: X4030304 | BB32: 2164908092 | BL32: (336) 331-6825 | BO32: 8472269228 | BP32: 3099941316 | BQ32: (678) 935-4670 | BR32: (614) 593-7718 | BS32: x4019804 | BV32: 844-306-0752 | BW32: (954) 958-1205 | BX32: 3097632550 | BY32: 844-458-4300 | BZ32: (224) 559-9178 | CC32: TBD | CD32: TBD | CF32: statefarmfireclaims@statefarm.com
A33: J | B33: =$S$1 -> LANEY, Anthony | C33: =$AK$1 -> Craig Ringo | D33: DA Email | F33: ='[1]jobinfo(2)'!$C$51 -> OH23H Bradley v3 | G33: OH23T KOSWATTA V2.1 | H33: OH24H WILLIAMS | I33: OH23A BATTLE @PARMA | J33: OH22 ANDERSON PETE | K33: OH22 WYNN FIRE @ROYAL OAK | L33: OH23P-FERGUSON@HILLCROFT | M33: BSCHEUER@PROCTORLP.COM | N33: OH24A RUSH WTR @Roanoke | O33: GA22 TORRES @ CONYERS | Q33: OH23A-ROBINSON@E270 | R33: LEETH | S33: OH24A Laney @ W98 | T33: statefarmfireclaims@statefarm.com | U33: TBD | V33: TBD | W33: TBD | Y33: ROSELYN.RAMOS.VAFA8T@statefarm.com | AA33: ROSELYN.RAMOS.VAFA8T@statefarm.com | AB33: statefarmfireclaims@statefarm.com | AC33: ext. 889098 | AD33: ROSELYN.RAMOS.VAFA8T@statefarm.com | AF33: MichaelRankin@westfieldgrp.com | AG33: statefarmfireclaims@statefarm.com | AH33: statefarmfireclaims@statefarm.com | AJ33: MATTHEW.GIESEY.VAF5GP@statefarm.com | AK33: CLAIMMAIL@US.QBE.COM | AL33: TBD | AM33: sgawu@allstate.com | AN33: sgawu@allstate.com | AO33: claims@claims.allstate.com | AQ33: HEATHER.CASOLA6@FARMERSINSURANCE.COM | AR33: info+eml39d20004afe2@claims.hippo.com | AS33: KDOWL@ALLSTATE.COM | AT33: STAPLES.OLIVIA @ace.aaa.com | AU33: lyle.kendrick@allstate.com | AV33: carla.robledo@ngic.com | AW33: claims@claims.allstate.com | AX33: NICOLE.FITZGERALD@LIBERTYMUTUAL.COM | AY33: Goddraneika.Merrill02@libertymutual.com | AZ33: MYCLAIMINFO@ASSURANT.COM | BB33: =BB29 -> claims@claims.allstate.com | BL33: carla.robledo@ngic.com | BO33: claims@claims.allstate.com | BP33: tia.dortch.k6r7@statefarm.com | BQ33: statefarmfireclaims@statefarm.com | BR33: BenczeR@Grangeinsurance.com | BS33: kharja.murdock@Assurant.com | BU33: 0H23A-MALIKA ALIM@WOODLAND | BV33: GA23A LOZAN0 @AUSTELL | BW33: SB0318@UNIVERSALPROPERTY.COM | BX33: ROSELYN.RAMOS.VAFA8T@statefarm.com | BY33: OH23A Franklin @256street | BZ33: claims@claims.allstate.com | CA33: STEPHEN.WALKER@AFICS.COM | CC33: TBD | CD33: statefarmfireclaims@statefarm.com | CF33: statefarmfireclaims@statefarm.com
A34: K | B34: =$T$1 -> LAWRENCE, GENEATHA | C34: =$AL$1 -> SMITH, JANET | D34: Field Adjuster Name | F34: ='[1]jobinfo(2)'!$C$68 -> BR 2 | G34: Bathroom | H34: Basement Rec Room | I34: TBD | J34: 0 | K34: HALL UP | M34: TBD | N34: REC ROOM 1 | O34: 16 | P34: TBD | Q34: HALL FLR1 | R34: TBD | S34: SIDING | T34: TBD | U34: TBD | V34: TBD | W34: TBD | Y34: RAMOS, ROSELYN | Z34: SEEK NOW HOWARD HOLCOMB | AA34: RAMOS, ROSELYN | AB34: MUHOMID | AC34: Email: tpa.support@alacritysolutions.com | AD34: SCOTT DANKO | AE34: WHITE, JUSTIENE | AF34: TBD | AH34: GIESEY, MATT 309 834 9661 | AI34: MICHAEL OZELLO | AJ34: GIESEY, MATT 309 834 9661 | AK34: Karlton Haynes | AL34: TBD | AM34: DREW STARK asst. | AN34: LYLE KENDRICK | AO34: TBD | AQ34: HEATHER.CASOLA | AR34: TBD | AT34: VINCENT, KATHERINE | AU34: Spencer GASTON, Large Loss | AW34: RIMKUS TPA | AX34: FA | AY34: MARCUS, HORACE | AZ34: KEVIN KIDD | BB34: MEAGAN CHASAR, LRG LOSS ADJ | BC34: FA | BL34: TBD | BP34: TBD | BQ34: TBD | BR34: TBD | BS34: Jason Jones | BU34: TBD | BW34: STERLING X1702 | BX34: RONALD MANCE | BY34: TBD | BZ34: Demrovsky, Andrew appraiser | CA34: SCOTT JACOBS | CC34: TBD | CD34: TBD | CF34: RICHARD, CATHERINE
A35: L | B35: =$R$1 -> LEETH, RONNIE | C35: =$AM$1 -> Brown, Cassandra | D35: Phone # field adj | F35: ='[1]jobinfo(2)'!$C$71 -> LL Bathroom | G35: Bathroom | H35: Utility Room | I35: TBD | J35: 0 | K35: Bedroom # 2 | M35: TBD | N35: Utility room | O35: 19 | P35: TBD | Q35: BSMNT CLOSET | R35: TBD | T35: TBD | U35: TBD | V35: TBD | W35: TBD | Y35: 844-458-4300 | Z35: 8553137311 | AA35: 844-458-4300 | AB35: 8667878678 X 4013 | AD35: 3307228703 | AE35: 4632141136 | AF35: TBD | AI35: 3097632416 | AK35: 800-647-3626 ext 3148 | AL35: TBD | AM35: 5138238034 | AN35: 9892774564 | AO35: TBD | AR35: TBD | AT35: 3306184299 | AU35: 330 224-5157 | AW35: 4106271546 | AX35: FA | AY35: 9363065323 | AZ35: 3304412955 | BB35: 2164908092 | BC35: FA | BL35: TBD | BP35: TBD | BQ35: TBD | BR35: TBD | BS35: 219.614.1819 | BU35: TBD | BW35: (954) 958-1205 | BX35: 4125237897 | BY35: TBD | BZ35: 3307068014 | CA35: 3303893040 | CC35: TBD | CD35: TBD | CF35: 844 458 4300
A36: M | B36: =$AZ$1 -> MONTGOMERY, JAVIONNA | C36: =$AN$1 -> Hurt, Chaunte | D36: Field adj email | F36: ='[1]jobinfo(2)'!$C$75 -> Basement Rec Room | G36: Master BR Closet | H36: TBD | I36: TBD | J36: 0 | K36: PRIMARY Bedroom | M36: TBD | N36: TBD | O36: - | P36: TBD | Q36: HALL BONUS ROOM | R36: TBD | T36: TBD | U36: TBD | V36: TBD | W36: TBD | Y36: ROSELYN.RAMOS.VAFA8T@statefarm.com | AA36: ROSELYN.RAMOS.VAFA8T@statefarm.com | AB36: statefarmfireclaims@statefarm.com | AC36: Alacrity Solutions | AD36: SDANKO@INSRESCON.COM | AE36: JWHK7@ALLSTATE.COM | AF36: TBD | AI36: MICHAEL.OZELLO.VAFCRL@STATEFARM.COM | AK36: khaynes@alacritysolutions.com | AL36: TBD | AM36: ASTCP@ALLSTATE.COM | AN36: lyle.kendrick@allstate.com | AO36: TBD | AR36: HIPPO INS CO. | AT36: KATHERINE@KGVINCENT.COM | AU36: sgawu@allstate.com | AW36: FA EM ? | AX36: PH | AY36: Preston.Cone@libertymutual.com | AZ36: KIDD.STANDARD.ADJUSTING@GMAIL.COM | BB36: MCHEM@ALLSTATE.COM | BC36: PH | BL36: TBD | BP36: TBD | BQ36: TBD | BR36: TBD | BS36: JKLIQUIDATION@GMAIL.COM | BU36: TBD | BW36: SB0318@UNIVERSALPROPERTY.COM | BX36: RMANCE@INSRESCON.COM | BY36: TBD | BZ36: andyd@sikegroupllc.com | CA36: SCOTT@AFICS.COM | CC36: TBD | CD36: TBD | CF36: statefarmfireclaims@statefarm.com
A37: N | B37: =$AE$1 -> NEWMAN, NICOLE | C37: =$AO$1 -> Dejarnette Mattie | D37: adj contents | F37: HM 5265029 00 | G37: HM 4186290 06 02 | H37: #000826481282 | I37: PL | J37: 992 832 919 | K37: #REF! | L37: 70B9K5636 | M37: 42PFP263789-01 /PFI 10625393 | N37: 42PFP263789-01 /PFI 10625393 | O37: 606732655-633-1 | P37: OK6372979 | Q37: H3DT8174525670 | R37: 27853880 | S37: PL # 000826686789 | T37: TBD | U37: TBD | V37: TBD | W37: TBD | Y37: Kevin Salmon, SPVR | Z37: Kevin Salmon, SPVR | AA37: Kevin Salmon, SPVR | AB37: Kevin Salmon, SPVR | AC37: Owen Hanbury | AD37: ANTONIO | AE37: FABIOLA, CHRISTENE | AF37: TBD | AH37: GIESEY, MATT 309 834 9661 | AJ37: GIESEY, MATT 309 834 9661 | AK37: mgr: Patrick Atwell ext 2218 | AL37: TBD | AM37: BRANDY CPS | AN37: KEISHA | AO37: Kianha Taylor | AR37: Info@claims.hippo.com | AT37: SPV Tanya Sayer 207-791-8544 | AU37: TENETIA MOORE | AX37: TBD | AY37: NICK | BB37: Chad Hages | BC37: TBD | BL37: TBD | BP37: TBD | BQ37: TBD | BR37: TBD | BS37: Shad Peterson | BU37: HM5097293 00 02 | BV37: PHP5336287 | BW37: TBD | BX37: Kevin Salmon, SPVR | BY37: 35GWY1289 | BZ37: insp mon 28 march 10-12am | CC37: TBD | CD37: TBD | CF37: RICHARD, CATHERINE
A38: O | B38: =$AF$1 -> Peggy Henderson | C38: =$AP$1 -> Burns2, RUBY | D38: adj CPS phone # | F38: ='[1]jobinfo(2)'!$C$62 -> Bathroom | G38: LAUNDRY CLOSET | H38: BR PRIMARY | I38: TBD | J38: BASEMENT REC | K38: STAIRS DOWN | L38: ` | N38: Up Hallway | O38: PRIMARY BATHROOM | P38: REAR/ENTRY ROOM | Q38: Closet 3 | R38: BEDROOM | S38: BATH | T38: TBD | U38: TBD | V38: TBD | W38: TBD | Y38: 3099940722 | Z38: 3099940722 | AA38: 3099940722 | AB38: 3099940722 | AC38: 844-503-7101 | AD38: 844-458-4300 | AE38: 4435657039 | AF38: TBD | AL38: TBD | AM38: 7327515219 | AN38: 4406450901 | AO38: Phone: (704) 548-2680 | AR38: 45896 | AT38: TBD | AU38: (727) 571-5062 | AX38: TBD | AY38: N/A | BB38: Phone: (425) 424-1487 | BC38: TBD | BL38: TBD | BP38: TBD | BQ38: TBD | BR38: TBD | BS38: 864.833.6360 | BU38: TBD | BV38: Hallway- up | BW38: TBD | BX38: 3099940722 | BY38: Bedroom 1 Closet | CC38: TBD | CD38: TBD | CF38: 844 458 4300
A39: P | B39: =$Q$1 -> ROBINSON, NiKKole | C39: =$AQ$1 -> CARTER, KAREN | D39: adj CPS email | F39: Michael R Carlozzi | G39: Rachael Bencze | H39: LESLIE | I39: DA | J39: Stacey Williams | K39: Orlando Reyes | L39: POLITZA,LEXI | N39: TBD | O39: Michelle Taylor , supervisor | P39: ASIA BABLES | Q39: Nicole Schaumleffel | R39: TAMI | S39: Benjamin Bybee | T39: TBD | U39: TBD | V39: TBD | W39: TBD | Y39: kevin.salmon.h9ib@statefarm.com | Z39: kevin.salmon.h9ib@statefarm.com | AA39: kevin.salmon.h9ib@statefarm.com | AB39: kevin.salmon.h9ib@statefarm.com | AC39: FL License #: G087288 | AD39: # 10135 | AE39: claims@claims.allstate.com | AF39: TBD | AL39: TBD | AM39: claims@claims.allstate.com | AN39: onsite@infraware.com | AO39: TBD | AT39: TBD | AU39: claims@claims.allstate.com | AX39: contents.claims@genpact.com | AY39: NICK@ALLCATCLAIMS.COM | BB39: claims@claims.allstate.com | BC39: TBD | BL39: TBD | BP39: TBD | BQ39: TBD | BR39: TBD | BS39: kharja.murdock@Assurant.com | BV39: Candace Brown | BW39: TBD | BX39: kevin.salmon.h9ib@statefarm.com | BY39: Jason 931-629-2250 | CC39: TBD | CD39: TBD | CF39: statefarmfireclaims@statefarm.com
A40: Q | B40: =$AG$1 -> Romero Beverly | C40: =$AR$1 -> CHERRY, LAUREN LB8997 | D40: TMP adj | F40: ='[1]jobinfo(2)'!$C$63 -> Linen Closet 2 | G40: Stairs UP | H40: CLOSET2 BR MASTER | I40: TBD | J40: STORAGE | K40: Bsmnt rec 1 | N40: Bathroom Up | O40: PRIMARY CLOSET | P40: Basement Hall/STEPS | Q40: Attic | R40: STORAGE 1 | S40: LINEN CLST | T40: TBD | U40: TBD | V40: TBD | W40: TBD | AA40: RAMOS, ROSELYN | AB40: MUHOMID | AC40: ext. 889098 | AD40: RAMOS, ROSELYN | AF40: TBD | AL40: TBD | AM40: TBD | AN40: LONGOBARDI, THOMAS | AO40: TBD | AT40: TBD | AU40: TBD | AX40: Sheree Banks | BC40: TBD | BL40: TBD | BP40: TBD | BQ40: TBD | BR40: TBD | BS40: Cory Taylor, FL Licensed Adjuster | BU40: TBD | BV40: Garage TRAVEL AREA | BW40: STERLING X1702 | BX40: RAMOS, ROSELYN | BY40: TBD | CC40: TBD | CD40: TBD | CF40: RICHARD, CATHERINE
A41: R | B41: =$M$1 -> RUSH, TIFFANY LOAN # 0579206154 | C41: =$AS$1 -> Johnson, Paul & Tamra | D41: TMP adj phone # | F41: ZHM003666130 | G41: ZHM003622222-1 | H41: #0743341489 | I41: A00005157320 | J41: #0696994516 | K41: #:051976058-01 | L41: 3549V338J | N41: BH01741315 | O41: ISR1809 | P41: #054466547 | Q41: 054398697-01 | R41: 27853880-046 | S41: #'0757376116 | T41: TBD | U41: TBD | V41: TBD | W41: TBD | AA41: 844-458-4300 | AB41: 8667878678 X 4013 | AC41: Email: tpa.support@alacritysolutions.com | AD41: 844-458-4300 | AF41: TBD | AL41: TBD | AM41: TBD | AN41: (443) 565-7237 | AO41: TBD | AR41: TBD | AT41: TBD | AU41: TBD | AX41: (469) 997-6270 | BC41: TBD | BL41: TBD | BP41: TBD | BQ41: TBD | BR41: TBD | BU41: ZHM003588773 | BV41: PRAH00908387 | BW41: (954) 958-1205 | BX41: 844-458-4300 | BY41: 3550V185H | CC41: TBD | CD41: TBD | CF41: 844 458 4300
A42: S | B42: =$N$1 -> RUSH, TIFFANY WTR | C42: =$AT$1 -> LACEY, EUNICE | D42: adj TMP email | F42: ='[1]jobinfo(2)'!$C$70 -> Basement Stairs | G42: Closet BR # 2 | H42: Laundry Room | I42: TBD | J42: 0 | K42: Closet BR # 1 | N42: REC ROOM 2 | O42: 18 | P42: TBD | Q42: BSMNT REC ROOM | R42: TBD | T42: TBD | U42: TBD | V42: TBD | W42: TBD | AA42: ROSELYN.RAMOS.VAFA8T@statefarm.com | AB42: statefarmfireclaims@statefarm.com | AD42: ROSELYN.RAMOS.VAFA8T@statefarm.com | AE42: claims@claims.allstate.com | AF42: MichaelRankin@westfieldgrp.com | AG42: agent | AL42: TBD | AM42: TBD | AN42: ALE | AO42: TBD | AR42: TBD | AT42: TBD | AU42: TBD | AX42: Sheree.Banks@libertymutual.com | BC42: TBD | BL42: TBD | BP42: TBD | BQ42: TBD | BR42: TBD | BS42: Claims Analyst | BU42: TBD | BW42: SB0318@UNIVERSALPROPERTY.COM | BX42: ROSELYN.RAMOS.VAFA8T@statefarm.com | BY42: TBD | CC42: TBD | CD42: TBD | CF42: statefarmfireclaims@statefarm.com
A43: T | B43: =$AV$1 -> Smith, Brian | C43: =$AU$1 -> BROOKS, DANIEL;JANAE POA | D43: ATT: Loss Draft Dept. | F43: 45314 | G43: 45189 | H43: 45316 | I43: 45165 | J43: 44920 | K43: 44922 | L43: 45092 | N43: 45514 | O43: 44599 | P43: 45165 | Q43: 45190 | R43: 45165 | T43: Corporation Service Company dba CSC Lawyers Incorporating Service | U43: TBD | V43: Corporation Service Company dba CSC Lawyers Incorporating Service | W43: Corporation Service Company dba CSC Lawyers Incorporating Service | AA43: NA | AB43: NA | AD43: YOLANDA FRANCE CPA/ALE | AF43: TBD | AG43: Minor, Josh | AL43: TBD | AM43: TBD | AN43: Peter, Caddy | AO43: TBD | AR43: Hippo Analytics Inc. dba Hippo Insurance Services (“Hippo”) | AT43: TBD | AU43: TBD | AX43: Liberty Mutual Insurance | Safeco Insurance | AY43: Safeco Insurance Attn: Payment Processing Operations PO Box 91016 Chicago, IL 60680-1016 | BB43: SCOTT | BC43: TBD | BL43: TBD | BP43: Corporation Service Company dba CSC Lawyers Incorporating Service | BQ43: TBD | BR43: TBD | BS43: National Water Claim Services | BU43: 45142 | BV43: 45142 | BW43: TBD | BY43: 45110 | CC43: TBD | CD43: TBD
A44: U | B44: =$U$1 -> SMITH, JANET | C44: =$AV$1 -> Smith, Brian | D44: address ins overnight mail | F44: ='[1]jobinfo(2)'!$C$77 -> TBD | H44: TBD | I44: TBD | J44: 0 | K44: PRIMARY Bathroom | N44: TBD | O44: - | P44: TBD | Q44: Roof Scope = DAMAGES & LINE ITEMS | R44: TBD | T44: TBD | U44: TBD | V44: TBD | W44: TBD | AA44: NA | AB44: NA | AD44: 840 468 4300 X10146 | AF44: TBD | AG44: undisputed law spv | AL44: TBD | AM44: TBD | AN44: (503) 603-6417 | AO44: TBD | AQ44: Heather Casola | AR44: mogunmwonyi-c@hippo.com | AT44: TBD | AU44: TBD | AX44: PO Box 5014 | BB44: (330) 461-8875 | BC44: TBD | BL44: TBD | BP44: TBD | BQ44: TBD | BR44: TBD | BS44: 877 262 9375 | BU44: TBD | BW44: TBD | BY44: TBD | CC44: TBD | CD44: TBD
A45: V | B45: =$AL$1 -> SMITH, JANET | C45: =$AW$1 -> THOMAS, ANITA | D45: city, state-zip ins | F45: grangeinsurance.com | G45: TBD | H45: claims@claims.allstate.com | I45: TBD | J45: SterlingDUNNwork@yahoo.com | K45: #REF! | N45: BETH.OLDFORD@RYSECLAIMS.COM.BETH | O45: dwalker6@travelers.com | P45: TBD | Q45: 0 | R45: Ann.Conway@usaa.com | T45: TBD | U45: TBD | V45: TBD | W45: TBD | AA45: NA | AB45: NA | AD45: NA | AF45: TBD | AG45: 770 842 2763 | AL45: TBD | AM45: TBD | AN45: RAKELLE | AO45: TBD | AQ45: Field Claims Representative | AR45: TBD | AT45: TBD | AU45: TBD | AX45: Scranton, PA 018505-5014 | BC45: TBD | BL45: TBD | BP45: TBD | BQ45: TBD | BR45: TBD | BS45: Office: (727) 753-9410 | BW45: TBD | BY45: TBD | CC45: TBD | CD45: TBD
A46: W | B46: =$AH$1 -> TAYLOR DAVIDSON, WARREN | C46: =$AX$1 -> Hatten, Nedra | D46: Insurance Co. Phone | G46: TBD | H46: Analiza Hatcher | I46: TBD | K46: #REF! | N46: OLDFORD, BETH | P46: TBD | Q46: TBD | R46: TBD | T46: TBD | U46: TBD | V46: TBD | W46: TBD | AA46: NA | AB46: NA | AD46: Kevin Salmon, SPVR | AF46: TBD | AG46: 770 982 7373 | AK46: 844.723.2524 | AL46: TBD | AM46: 888 656.8005 | AN46: TBD | AO46: TBD | AQ46: 440-465-6346 | AR46: TBD | AS46: 8002557828 | AT46: TBD | AU46: TBD | AZ46: CLAIMS: 1-800-326-7781 | BB46: 3306461840 | BC46: TBD | BL46: TBD | BP46: TBD | BQ46: TBD | BR46: TBD | BS46: Email: ctaylor@nwclaimservices.com | BU46: TBD | BV46: Wykisha Grace, MSI | BW46: TBD | BY46: TBD | CC46: TBD | CD46: TBD
A47: X | B47: =$AW$1 -> THOMAS, ANITA | C47: =$AY$1 -> HOWARD, MATTHEW | D47: Website Ins Co. | F47: ='[1]jobinfo(2)'!$C$57 -> Nook | G47: Dining Room | H47: Back Foyer | I47: Basement BR | J47: Pantry | K47: FAMILY ROOM | L47: GARAGE | N47: RR FOYER/HALL | O47: BEDROOM 1 CLOSET | P47: NOOK | Q47: Bedroom | R47: REC ROOM 2/office | S47: HALL UP TRVL | T47: Corporation Service Company dba CSC Lawyers Incorporating Service | U47: TBD | V47: Corporation Service Company dba CSC Lawyers Incorporating Service | W47: Corporation Service Company dba CSC Lawyers Incorporating Service | AA47: NA | AB47: NA | AD47: 3099940722 | AF47: TBD | AG47: josh@joshminore.com | AL47: TBD | AM47: TBD | AN47: TBD | AO47: TBD | AQ47: Farmers Group Property a | AR47: TBD | AT47: TBD | AU47: TBD | AZ47: 800 358 0600 X 4730304 | BB47: ADJ LRG LOSS ALT | BC47: TBD | BL47: TBD | BP47: Corporation Service Company dba CSC Lawyers Incorporating Service | BQ47: TBD | BR47: TBD | BS47: Elaine Gebsbher | BU47: TBD | BV47: Nook | BW47: TBD | BY47: PBR | CC47: TBD | CD47: TBD
A48: Y | B48: =$BA$1 -> 0 | C48: =$AZ$1 -> MONTGOMERY, JAVIONNA | D48: Mailing address INS | F48: ='[1]jobinfo(2)'!$C$74 -> Utility Room | G48: Master Bedroom | H48: TBD | I48: TBD | J48: 0 | K48: Closet BR # 3 | N48: TBD | O48: - | P48: TBD | Q48: WORKSHOP @ GARAGE | R48: TBD | T48: 2710 Gateway Oaks Drive Suite 150N | U48: TBD | V48: 2710 Gateway Oaks Drive Suite 150N | W48: 2710 Gateway Oaks Drive Suite 150N | AA48: NA | AB48: NA | AD48: kevin.salmon.h9ib@statefarm.com | AF48: TBD | AL48: TBD | AM48: TBD | AN48: TBD | AO48: TBD | AR48: TBD | AT48: TBD | AU48: TBD | BC48: TBD | BL48: TBD | BP48: 2710 Gateway Oaks Drive Suite 150N | BQ48: TBD | BR48: TBD | BS48: 1.800.358.0600 | BU48: TBD | BW48: TBD | BY48: TBD | CC48: TBD | CD48: TBD
A49: Z | B49: =$O$1 -> TORRES, ANGEL | C49: =$BA$1 -> 0 | D49: Mail city, state, zip INS | G49: PO Box 25196 Lehigh Valley, | H49: Phone: (937) 467-1460 | I49: TBD | J49: 0 | K49: SHEREFINAL 1M0N 11.28.22 | N49: TBD | O49: One Tower Square | P49: TBD | Q49: TBD | R49: TBD | T49: Sacramento CA 95833 | U49: TBD | V49: Sacramento CA 95833 | W49: Sacramento CA 95833 | AA49: NA | AB49: NA | AD49: NA | AF49: TBD | AL49: TBD | AM49: TBD | AN49: TBD | AO49: TBD | AR49: TBD | AT49: TBD | AU49: TBD | AX49: TBD | BC49: TBD | BL49: TBD | BP49: Sacramento CA 95833 | BQ49: TBD | BR49: TBD | BS49: x4019804 | BU49: TBD | BV49: 844-306-0752 x457415 | BW49: TBD | BY49: One State Farm Plaza | CC49: TBD | CD49: TBD
A50: BA1 | B50: =$H$1 -> Williams, Bridgett | C50: =$BB$1 -> BROWNLEE, KEN | D50: FAX Ins. Co | F50: ='[1]jobinfo(2)'!$C$61 -> LINEN CLOSET 1 | G50: Laundry | H50: Bathroom | I50: TBD | J50: FAMILY ROOM | K50: GARAGE | N50: Stairs UP LVL 2 | O50: PRIMARY BEDROOM | P50: Bathroom | Q50: Bedroom 2 | R50: HALL DN | S50: BR1 UP CLOSET | T50: TBD | U50: TBD | V50: TBD | W50: TBD | AA50: NA | AB50: NA | AD50: NA | AF50: TBD | AL50: TBD | AM50: TBD | AN50: TBD | AO50: TBD | AR50: TBD | AT50: TBD | AU50: TBD | AX50: TBD | BC50: TBD | BL50: TBD | BP50: TBD | BQ50: TBD | BR50: TBD | BS50: 0 | BU50: TBD | BV50: Stairs UP | BW50: TBD | BY50: Bedroom Up 1 TRAVEL | BZ50: =BZ2 -> 1408 East 124th Street | CC50: TBD | CD50: TBD
A51: BB1 | B51: =$V$1 -> Wimbish, Tawana | C51: =$BC$1 -> HUTCHINSON | D51: NEW CUSTOMER # | F51: ='[1]jobinfo(2)'!$C$60 -> Up Hallway | G51: Kitchen | H51: LINEN CLOSET 1 | I51: TBD | J51: Bathroom UP | K51: LAUNDRY | M51: 0H24 RUSH RFG @ROANOKE | N51: Living Room | O51: Bedroom 2 Closet | P51: Upstairs Hall | Q51: Closet 2 | R51: UTILITY ROOM | S51: BR1 UP | T51: OH23A-Lawrence v3 | U51: OH24A SMITH @ LUDLOW | V51: GA23K WIMBISH ATL | W51: OH24A HICKS@ TURNEY | X51: OH24A AKALA @E153 VANDALISM | Y51: OH24A AKALA @E153 VANDALISM | Z51: OH24A AKALA @E153 TREE | AA51: OH24 COUSETTE@E111 | AB51: OH24 COUSETTE@E111 | AC51: OH24A JONES, BH | AD51: OH24ACOLLINS@ELWOOD RD | AE51: OH24 NEWMAN @E. 88STR | AF51: OH24H HENDERSON | AG51: GA24 BEVERLY, ROMERO @ CONYERS | AI51: Oh24A Goshen @Estlake348 | AJ51: OH24A Brownlee @Alvin | AK51: OH22A RINGO @ DANIEL ST. BEDFORD | AL51: OH24A SMITH @ LUDLOW | AM51: OH25 BROWN @ HECKER | AN51: OH25 HURT @EUCLID | AO51: OH25 DEJARNETTE V2 | AP51: Oh25Burns2@Georgetown | AQ51: Oh25CARTER@Georgetown | AR51: OH25 CHERRY V2 @ Larchmere | AS51: OH25 Johnson @ Macedonia | AT51: OH25 LACEY, E | AU51: OH25 BROOKS,@YNG | AV51: GA25 SMITH @GERTRUDE PL | AW51: OH25 ANITA @GERTRUDE | AX51: OH25 HATTEN @QUILLIAMS | AY51: OH25 HOWARD @E55 | AZ51: OH25 MONTGOMERY @ ASHWOOD | BB51: OH25 BROWNLEE @E189 | BC51: OH26 HUTCHINSON WTR @WALTON HILLS | BL51: GA25 SMITH | BO51: OH24 BROWN @ MORROW | BP51: GA24M JOHNSON WTR MIKE V2 | BQ51: GA24M JOHNSON,RFG MIKE | BR51: OH24W BURNS @ TREBISKY | BS51: 0 | BT51: OH22P GREENWALT2 FIRE | BU51: TBD | BV51: HALL DN | BW51: GA24 JOHNSON TREE V2 | BX51: OH25CARIB @E88 GH | BY51: HALL UP | BZ51: OH25P Lanier, APPRAISAL Shari | CA51: OH24A CORBIN @ ELDAMERE | CB51: Oh24A Goshen @Estlake348 | CC51: OH23P-GREENWALT@W.GOVERNOR V9 | CD51: OH23A-THOMAS@MILLER | CE51: OH24A RAGLAND @NORDHAM | CF51: Oh24A Webb TreeWind @Horizon
A52: BC1 | B52: =$K$1 -> WYNN, NICK | C52: =$BD$1 -> 0 | D52: ROOM ID | F52: ='[1]jobinfo(2)'!$C$65 -> CLOSET BR MASTER | G52: Bedroom # 1 | H52: Bedroom2 | I52: TBD | J52: 0 | K52: BSMNT STORAGE | M52: =M1 -> RUSH, TIFFANY LOAN # 0579206154 | N52: Linen Closet 2 | O52: STAIRS UP PROTECT- TRAVEL AREA | P52: BSMNT BATH | Q52: Dining Room | R52: tbd | S52: CLOSET? | T52: =T1 -> LAWRENCE, GENEATHA | U52: =U1 -> SMITH, JANET | V52: =V1 -> Wimbish, Tawana | W52: =W1 -> HICKS, JASON | X52: =X1 -> Akala, Ayo SMOKE FIRE | Y52: =Y1 -> Akala, Ayo VND | Z52: =Z1 -> Akala, Ayo TREE | AA52: =AA1 -> Cousette, JOHN Vandalism | ... AG52: =AG1 -> Romero Beverly | AI52: =AI1 -> Goshen, Aaron & Shania | AJ52: =AJ1 -> Brownlee. LAVERNE | AK52: Craig Ringo | AL52: SMITH, JANET | AM52: =AM1 -> Brown, Cassandra | AN52: Hurt, Chaunte | AO52: =AO1 -> Dejarnette Mattie | AP52: Burns2, RUBY | AQ52: =AQ1 -> CARTER, KAREN | AR52: CHERRY, LAUREN LB8997 | AS52: =AS1 -> Johnson, Paul & Tamra | AT52: =AT1 -> LACEY, EUNICE | AU52: BROOKS, DANIEL;JANAE POA | AV52: Smith, Brian | AW52: THOMAS, ANITA | AX52: =AX1 -> Hatten, Nedra | AY52: =AY1 -> HOWARD, MATTHEW | AZ52: MONTGOMERY, JAVIONNA ANTONIO | BB52: =BB1 -> BROWNLEE, KEN | BC52: HUTCHINSON | BL52: Smith, Brian | BO52: =BO1 -> BROWN,Courtney | BP52: =BP1 -> JOHNSON,MIKE WTR | BQ52: =BQ1 -> JOHNSON,MIKE RFG | BR52: Burns, ERIC | BS52: =BS1 -> Tamplin, Adalene | BT52: =BT1 -> George Greenawalt | BU52: TBD | BW52: =BW1 -> Johnson, Margaret | BX52: =BX1 -> Carib Investment ,LLC | BY52: TBD | BZ52: =BZ1 -> Lanier, Shari | CA52: Corbin, Wanda | CB52: =CB1 -> WILLIS, CATRERA | CC52: =CC1 -> Greenawalt, Mike | CD52: =CD1 -> THOMAS, LISA | CE52: =CE1 -> Ragland | CF52: =CF1 -> Webb, Terika
A53: BD1 | B53: =$BD$1 -> 0 | C53: =$BE$1 -> 0 | D53: Room/Area 1 | E53: ORIGINAL INVOICES | F53: TBD | G53: TBD | H53: TBD | I53: TBD | J53: na | K53: na | M53: RFG | N53: TBD | O53: na | P53: TBD | Q53: TBD | R53: TBD | S53: TBD | T53: Living Room | U53: FRT PORCH TRAVEL | V53: FOYER | W53: FOYER / ENTRY | X53: REAR HALLWAY | Y53: REAR HALLWAY | Z53: Roof shingle replace | AA53: FOYER/ENTRY ROOM | AB53: PRIMARY BEDROOM (PBR) | AC53: Living Room | AD53: LIVING ROOM | AE53: FOYER | AF53: Rear Stairwell To Attic | AG53: GARAGE TRAVEL | AH53: FOYER | AI53: REAR/Entry room | AJ53: FOYER TRAVEL | AK53: Foyer | AL53: FOYER | AM53: Foyer | AN53: Living Room | AO53: FOYER SIDE ENTRY | AP53: FOYER ENTRY | AQ53: FOYER ENTRY | AR53: Foyer DN FRT | AS53: FOYER ENTRY /HALL TRAVEL AREA | AT53: LIVING ROOM | AU53: Garage TRAVEL AREA | AV53: Kitchen | AW53: Living Room, | AX53: LIVING ROOM | AY53: STAIRS TO FLR 2 TRAVEL unit #3 | AZ53: LIVINGROOM | BB53: Living Room, | BC53: FOYER / TRAVEL | BL53: Living Room | BO53: GARAGE | BP53: REC1 | BQ53: Living Room | BR53: Foyer/TRAVEL | BS53: Foyer | BT53: GARAGE | BU53: TBD | BV53: TBD | BW53: FOYER | BX53: Foyer | BY53: TBD | BZ53: FOYER ENTRY /HALL TRAVEL AREA | CA53: 3.FOYER/ENTRY SIDE TRAVEL | CB53: REAR/Entry room | CC53: Living Room TRAVEL AREA | CD53: Foyer travel Area | CE53: REAR/Entry room | CF53: SHED
A54: BE1 | B54: =$BE$1 -> 0 | C54: =$BF$1 -> 0 | D54: Room/Area 2 | F54: ='[1]jobinfo(2)'!$C$66 -> Bedroom Up 3 | G54: Closet BR # 1 | H54: BR2 CLOSET | I54: TBD | J54: 0 | K54: UTILITY ROOM | M54: GUTTERS | N54: Sunroom | O54: GARAGE | P54: TBD | Q54: Kitchen | R54: TBD | S54: FRTPORCH CLG | T54: Dining Room | U54: FOYER/HALL | V54: Living Room | W54: Living Room | X54: REAR STAIRS | Y54: REAR STAIRS | Z54: SOFFIT | AA54: GUEST CLOSET | AB54: PBR CLOSET 1 | AC54: Dining Room | AD54: Dining Room | AE54: LR TRAVEL | AF54: Attic | AG54: HALL RR TRAVEL | AH54: VEHICLE HIT EAST SIDE OF THE HOME, OPPOSITE OF THE DRIVEWAY | AI54: UTILITY/LAUNDRY ROOM | AJ54: KITCHEN TRAVEL | AK54: GUEST CLOSET | AL54: GUEST CLST | AM54: Living Room | AN54: GUEST CLOSET | AO54: Basement Stairs | AP54: LIVINGROOM | AQ54: LIVINGROOM | AR54: Guest Closet DN | AS54: LIVINGROOM | AT54: DINING ROOM | AU54: REC ROOM 1 | AV54: DEN | AW54: GUEST CLOSET | AX54: DINING ROOM | AY54: KITCHEN UP Unit# 3 | AZ54: GUEST CLOSET | BB54: HALLWAY dn LOS | BC54: HALL UP | BL54: HALL | BO54: KITCHEN TRVL | BP54: UTILTY | BQ54: Dining Room | BR54: LR TRAVEL | BS54: DEN | BT54: SDG | BU54: TBD | BW54: FAMILY ROOM | BX54: Guest Closet | BY54: TBD | BZ54: STAIRS UP | CA54: Kitchen | CB54: UTILITY/LAUNDRY ROOM | CC54: Dining Room TRAVEL AREA | CD54: Kitchen | CE54: Kitchen TRAVEL | CF54: TREE REMOVAL
A55: BF1 | B55: =$BF$1 -> 0 | D55: Room/Area 3 | F55: TBD | G55: TBD | H55: TBD | I55: TBD | J55: vnssmrshll@yahoo.com | K55: na | L55: NA | M55: Fascia & Ext PNT | N55: TBD | O55: na | P55: TBD | Q55: TBD | R55: TBD | S55: TBD | T55: Kitchen | U55: GUEST CLST | V55: Dining Room | W55: Hallway | X55: ATTIC STAIRS | Y55: ATTIC STAIRS | Z55: GUTTERS | AA55: LIVING ROOM | AB55: BEDROOM 2 | AC55: KITCHEN | AD55: Kitchen | AE55: Dining Room | AF55: Foyer DN | AG55: LAUNDRY | AH55: BRICK | AI55: Kitchen | AJ55: Pantry | AK55: HALL 1 | AL55: KITCHEN | AM55: Dining Room | AN55: LINEN CLOSET | AO55: Utility Room | AP55: DINING ROOM | AQ55: DINING ROOM | AR55: Living Room DN | AS55: FAMILY ROOM | AT55: KITCHEN | AU55: STORAGE UNDER STAIRS | AV55: CLOSET DEN | AW55: Dining Room, | AX55: KITCHEN | AY55: PANTRY UP Unit# 3 | AZ55: KITCHEN | BB55: Kitchen, | BC55: BATH2 UP | BL55: DINING ROOM | BO55: LIVINGROOM TRVL | BP55: LAUNDRY | BQ55: Kitchen | BR55: STAIRS UP TRAVEL | BS55: Living Room | BU55: TBD | BV55: TBD | BW55: STAIRS UP | BX55: Living Room | BY55: TBD | BZ55: HALL UP | CA55: Dining Room TRAVEL | CB55: Kitchen | CC55: Kitchen | CD55: Living Room | CE55: NOOK | CF55: GAZEBO
D56: Room/Area 4 | F56: ='[1]jobinfo(2)'!$C$72 -> Laundry Room | G56: Utility | H56: TBD | I56: TBD | J56: 0 | K56: Closet BR # 2 | M56: FOYER | N56: Under Stairs | O56: 20 | P56: TBD | Q56: UTILITY | R56: TBD | T56: STAIRS UP TRAVEL | U56: Kitchen | V56: BEDROOM 1 | W56: Dining Room | X56: ATTIC | Y56: ATTIC | Z56: Porches LOWER | AA56: Dining Room | AB56: BEDROOM 2 CLOSET | AC56: BATH | AD56: NOOK | AE56: Kitchen | AF56: Hallway Dn | AG56: KITCHEN | AH56: SIDING | AI56: LIVING ROOM | AJ56: Dining Room TRAVEL | AK56: Living Room | AL56: Living Room | AM56: Kitchen | AN56: HALL | AO56: LAUNDRY | AP56: Hallway- DN | AQ56: Hallway- DN | AR56: Dining Room DN | AS56: KITCHEN | AT56: NOOK | AU56: HALL DN | AV56: HALL | AW56: DEN | AX56: HALL FLR1 | AY56: BEDROOM 1 Unit# 3 | AZ56: DINING ROOM | BB56: DEN | BC56: PBR PRIMARY BEDROOM | BL56: Kitchen | BO56: HALL TRVL | BP56: STUDIO ROOM | BQ56: HALL | BR56: HALL UP | BS56: CLOSET | BU56: TBD | BW56: HALL UP | BX56: Dining Room | BY56: TBD | BZ56: BATHROOM | CA56: Living TRAVEL | CB56: LIVING ROOM | CC56: STAIRS UP TRAVEL | CD56: Hallway- DN | CE56: DR TRAVEL | CF56: ROOF REPAIR
D57: Room/Area 5 | E57: Supplemental Invoices TOTALS | F57: Water | G57: Water | H57: Water | I57: Water | J57: Water Damage=WTR | K57: FIRE | L57: Wind = Roof | M57: Stairs Travel area | N57: WATER | O57: Wind = Roof | P57: Water | Q57: FIRE | R57: Water | S57: Wind=Tree | T57: HALL UP TRAVEL or DAMAGES | U57: Living Room | V57: BR 1 Closet | W57: Kitchen | X57: KITCHEN | Y57: KITCHEN | Z57: Porches UPPER | AA57: Kitchen | AB57: BR ATTIC 1 | AC57: BR1 UP | AD57: REAR HALL | AE57: PANTRY | AF57: Living Rm Dn | AG57: LIVINGROOM | AH57: INTERIOR | AI57: Dining Room | AJ57: Living Room TRAVEL | AK57: KITCHEN | AL57: STAIRS UP | AM57: Stairs Basement | AN57: BR 1 | AO57: UNDER STAIRS STORAGE | AP57: BATHROOM | AQ57: BATHROOM | AR57: Hallway DN @ BR & BATH | AS57: NOOK | AT57: STAIRS UP | AU57: Bathroom Dn | AV57: LINEN | AW57: Kitchen, | AX57: STAIRS UP | AY57: BEDROOM 1 CLOSET Unit# 3 | AZ57: STAIRS TO FLR 2 | BB57: STAIRS UP | BC57: PBR BATHROOM | BL57: STUDIO/OFFICE | BO57: BR1 TRVL | BP57: CLOSET 1 | BQ57: Bathroom | BR57: PBR | BS57: HALL | BU57: WIND | BV57: WIND/WATER | BW57: LAUNDRY ROOM | BX57: Hallway | BY57: Wind Damage caused interior Damage /Roof | BZ57: Linen Closet | CA57: Stairs Up TRAVEL | CB57: Dining Room | CC57: HALL UP TRAVEL or DAMAGES | CD57: Bedroom # 1 | CE57: LR TRAVEL
D58: Room/Area 6 | F58: ='[1]jobinfo(2)'!$C$73 -> Basement Rec Room | G58: Hallway- up | H58: TBD | I58: TBD | J58: 0 | K58: Bedroom # 3 | M58: Hall Travel area | N58: TBD | O58: - | P58: TBD | Q58: GARAGE | R58: TBD | T58: Linen Closet HALL | U58: Dining Room | V58: Hallway- DN | W58: STAIRS DN | X58: PANTRY | Y58: PANTRY | Z58: ATTIC Windows | AA58: NOOK | AD58: DOWN BASEMENT STAIRS | AE58: GUEST BATHROOM | AF58: Dining Rm Dn | AG58: HALL BR BATHTRAVEL | AH58: OFFICE | AJ58: MATTHEW.GIESEY.VAF5GP@statefarm.com | AK58: PANTRY | AL58: HALL UP | AM58: Basement Rec 1 | AN58: BR1 CLOSET | AO58: Basement Rec Room | AP58: UTILITY | AQ58: UTILITY | AR58: Bedroom 1 DN | AS58: RR HALL TRAVEL AREA | AT58: Hallway UP @ BR & BATH | AU58: BEDROOM DN | AV58: GUEST CLOSET | AW58: STAIRS UP | AX58: Hallway UP @ BR & BATH | AY58: DINING ROOM UP Unit# 3 | AZ58: HALL UP | BB58: HALL UP | BC58: PBR WATER CLOSET | BL58: STUDIO/OFFICE CLOSET | BO58: BR1 CLOSET | BP58: TBD | BQ58: BR 1 | BR58: PBR CLOSET | BS58: BR1 | BU58: TBD | BW58: CLOSET HALL UP | BX58: Kitchen | BY58: TBD | BZ58: BR1 | CA58: Up Hall TRAVEL | CC58: Bathroom Up | CD58: Closet BR # 1 | CE58: STAIRS UP TRAVEL
D59: Room/Area 7 | E59: Invoice Submittal CHKLST2 INS. CO. | F59: 45311 | G59: 45168 | H59: 45315 | I59: 45127 | J59: 44920 | K59: Dec 23, 2022 | L59: 45081 | M59: BR2 up Front east | N59: 45514 | O59: 44596 | P59: 45149 | Q59: 45143 | R59: 45110 | S59: 45426 | T59: Bathroom Up | U59: STAIRS UP | V59: P BEDROOM | W59: Basement DEN | X59: DINING | Y59: DINING | Z59: LANDSCAPING yard area | AA59: REAR HALL | AD59: UTILITY/LAUNDRY ROOM | AE59: 2ND UP STAIRS TRVL | AF59: Kitchen Dn | AG59: PRIMARY BEDROOM TRAVEL | AH59: STORAGE | AJ59: HALL UP TRAVEL | AK59: Dining Room | AL59: BATHROOM UP | AM59: Basement Rec 2 | AN59: BATH FLR1 | AO59: Basement BEDROOM | AP59: PBR | AQ59: PBR | AR59: Bedroom 1 Closet DN | AS59: GARAGE TRAVEL AREA | AT59: BATHROOM | AU59: Bedroom Down Closet | AV59: Living Room | AW59: HALL UP | AX59: BATHROOM | AY59: HALL UP TRAVEL Unit# 3 | AZ59: BATHROOM UP | BB59: PBR UP | BC59: PBR CLOSET 1 | BL59: Basement Rec 1 | BO59: BR2 | BP59: TBD | BQ59: BR1 CLOSET | BR59: BR1 | BS59: BR1 CLST | BU59: 45017 | BV59: 45139 | BW59: BEDROOM 1 UP | BX59: Pantry | BY59: 45110 | BZ59: BR1 CLOSET | CA59: Linen Closet Hall Up | CC59: Bedroom Up 1 | CD59: Garage | CE59: HALL UP
D60: Room/Area 8 | F60: GRANGE | G60: GRANGE | H60: Allstate Insurance Company | I60: Erie Ins | J60: ALLSTATE | K60: Liberty Mutual | L60: sfi | N60: Universal Ins | O60: Travelers Insurance Co. | P60: Safeco | Q60: Liberty Mutual Insurance | R60: USAA | S60: ALLSTATE | T60: Bedroom Up 1 | U60: HALL UP | V60: PBR CLST | W60: Storage Room 1 | X60: LIVING | Y60: LIVING | AA60: DOWN BASEMENT STAIRS | AD60: STORAGE BSMNT | AE60: HALL UP | AF60: Kitchen Dn Pantry | AG60: PRIMARYCLOSET1 | AH60: BAR AREA ROOF | AJ60: BR1 UP | AK60: PRIMARY Bedroom | AL60: STAIRS DN BSMNT | AM60: Utility/Laundry Room | AN60: BR 2 | AO60: TBD | AP60: PBR CLOSET | AQ60: PBR CLOSET | AR60: Linen Closet DN | AS60: BASEMENT STAIRS | AT60: Basement Stairs | AU60: LAUNDRY/UTILITY ROOM | AV60: DINING ROOM | AW60: LINEN CLOSET | AX60: LINEN | AY60: Bathroom UP Unit# 3 | AZ60: PBR BEDROOM | BB60: BATH UP | BC60: DOWN BASEMENT STAIRS | BL60: TBD | BO60: LINEN | BP60: TBD | BR60: BR1 CLOSET | BS60: BR2 | BU60: GRANGE | BV60: QBE INS | BW60: CLOSET BR1 UP | BX60: Nook | BY60: State Farm | BZ60: BR2 TRAVEL | CA60: Bathroom | CC60: Bedroom Up 2 | CD60: Roof shingle replace | CE60: BR1
D61: Room/Area 9 | E61: A179 | F61: interior repairs | G61: INTERIOR REPAIRS | H61: Interior Repairs LVL1 | I61: INTERIOR REPAIRS | J61: interior repairs | K61: interior repairs | L61: interior repairs | N61: interior repairs | O61: roofing shingles replacement | P61: INTERIOR REPAIRS | Q61: INTERIOR REPAIRS | R61: INTERIOR REPAIRS | S61: ROOF REPLACE SHINGLES | T61: Bedroom 1 Closet | U61: LINEN CLST | V61: DEN CLST | W61: Storage Room 2 UNS | X61: GUEST CLST | Y61: GUEST CLST | AA61: UTILITY/LAUNDRY ROOM | AD61: 2ND FLOOR STAIRS | AE61: BATH UP | AF61: Bath Rm Dn | AG61: PRIMARYCLOSET2 | AH61: BASEMENT | AJ61: BR1 UP CLOSET | AK61: PBR Sitting Room | AL61: BASEMENT | AM61: LL Bathroom | AN61: BR2 CLOSET | AO61: TBD | AP61: BR 2 | AQ61: BR 2 | AR61: Bathroom DN | AS61: BASEMENT COMMON AREAS | AT61: Basement Rec Room | AU61: STAIRS DN | AV61: Basement Workshop/Storage | AW61: BATH UP | AX61: PBR | AY61: LIVINGROOM UP Unit #3 | AZ61: PBR CLOSET | BB61: BR2 UP | BC61: Basement REC1 TRAVEL | BL61: TBD | BO61: PRIMARY TRVL | BP61: TBD | BR61: Storage #2 secret room | BS61: BR2 CLST | BU61: ROOF | BV61: EXT SDG | BW61: BATH UP | BX61: Hallway RR | BY61: ROOF | BZ61: BR2 CLOSET | CA61: Bedroom TRAVEL | CC61: BEDROOM 2 CLOSET | CD61: Vinyl siding | CE61: BR1 CLOSET
D62: Room/Area 10 | F62: grangeinsurance.com | G62: TBD | H62: victoria.lindsay@infraware.com | I62: TBD | J62: claims@claims.allstate.com | K62: richard.walker01@liberymutual.com | N62: NA | P62: TBD | Q62: TBD | R62: TBD | T62: BEDROOM 2 CLOSET / ATTIC ACCESS | U62: Bathroom | V62: TBD | W62: Laundry Room/ UTILITY ROOM | X62: FRT PORCH | Y62: FRT PORCH | AA62: 2ND FLOOR STAIRS | AD62: 2ND FLOOR HALLWAY | AE62: Bedroom # 1 | AF62: Linen Closet Dn | AG62: PRIMARY BATHROOM | AH62: Basement Hall | AJ62: BR1 UP CLOSET 2 | AK62: PRIMARY BR Closet | AM62: Stairs Up | AN62: Kitchen | AO62: TBD | AR62: Primary Bedroom DN | AT62: Utility / LAUNDRY | AU62: 3.FOYER/ENTRY ROOM | AW62: Bedroom 1, | AX62: PBR CLOSET | AY62: ENTRY Hall /Stairs UP Unit #3 | AZ62: LINEN CLOSET | BB62: Guest Closet | BC62: Basement REC2 TRAVEL | BL62: TBD | BO62: PRIMARYCLOSET | BP62: TBD | BR62: GARAGE 1 | BS62: KITCHEN | BU62: TBD | BV62: TBD | BW62: TBD | BX62: Guest Bath | BY62: TBD | BZ62: GARAGE | CA62: Bedroom Closet | CC62: Bedroom Up 3 | CD62: Fencing | CE62: PBR TRAVEL
D63: Room/Area 11 | E63: =D250 -> 0 | F63: interior repairs | G63: INTERIOR REPAIRS | H63: Interior Repairs LVL2 | I63: TBD | J63: NA | K63: NA | L63: interior repairs | N63: interior repairs | O63: interior repairs | P63: INTERIOR REPAIRS | Q63: INTERIOR REPAIRS | R63: INTERIOR REPAIRS | S63: EXTERIOR REPAIRS | T63: Attic STAIRWAY | U63: PRIMARY Bedroom | V63: TBD | W63: Bathroom DN | X63: FRT HALLWAY | Y63: FRT HALLWAY | AA63: 2ND FLOOR HALLWAY | AD63: BATHROOM | AE63: Closet BR # 1 | AF63: Bed Rm # 1 Dn | AG63: ROOF SHINGLES | AH63: Basement | AJ63: BR2 UP | AK63: HALL 2 | AM63: Up Hallway | AN63: NOOK/Dining Room | AO63: TBD | AR63: Primary Bedroom Closet DN | AT63: TBD | AU63: STAIRS UP | AW63: BR1 Closet | AX63: BR2 | AY63: ENTRY DN Unit #1 | AZ63: BEDROOM 2 | BB63: Bath DN | BC63: HALL BSMNT | BL63: TBD | BO63: SUNROOM | BP63: TBD | BR63: GARAGE 2 | BS63: NOOK | BU63: EXTERIOR REPAIRS | BV63: INTERIOR REPAIRS | BW63: TBD | BX63: Stairs -Up | BY63: SIDING | BZ63: ROOF | CA63: Basement Stairs TRAVEL | CC63: BEDOOM 3 CLOSET | CD63: TBD | CE63: PBR CLOSET
D64: Room/Area 12 | G64: TBD | H64: Inside Property Adjuster | I64: TBD | J64: 0 | K64: #REF! | N64: 216 789 5354 | P64: TBD | Q64: TBD | R64: TBD | T64: Bedroom Up 2 / ATTIC ACCESS | U64: PRIMARY CLOSET | V64: TBD | X64: FRT STAIRS | Y64: FRT STAIRS | AA64: BOYS ROOM 1 | AD64: LINEN CLOSET1 | AE64: BR2 | AF64: Bed Rm # 1 Dn Walk In Closet | AG64: SOFFIT & FASCIA | AH64: Basement Bath | AJ64: BR2 UPCLOSET | AK64: STAIRS | AM64: Bathroom | AN64: RR FOYER | AO64: TBD | AR64: Kitchen DN | AT64: TBD | AU64: Kitchen | AW64: Bedroom 2 | AX64: BR2 CLOSET | AY64: HALL DN TRAVEL Unit#1 | AZ64: BEDROOM 2 CLOSET | BB64: SHOWER UP BATH | BC64: UTILITY ROOM | BL64: TBD | BP64: TBD | BS64: LAUNDRY | BU64: TBD | BW64: TBD | BX64: Hallway Up | BY64: TBD | BZ64: SIDING | CA64: Basement REC1 TRAVEL | CC64: Attic1 | CD64: TBD | CE64: BR2
D65: Room/Area 13 | E65: A189 | F65: TBD | G65: TBD | H65: Interior Repairs LVL3 | I65: TBD | J65: NA | K65: NA | N65: TBD | O65: na | P65: INTERIOR REPAIRS | Q65: INTERIOR REPAIRS | R65: INTERIOR REPAIRS | S65: Interior Repairs LEVEL 1 &2 | T65: Bedroom Up 3 / BABY ROOM | U65: Bedroom 2 | V65: TBD | X65: HALLWAY BATH BR | Y65: HALLWAY BATH BR | AA65: BOYS ROOM CLOSET | AD65: PRIMARY BEDROOM (PBR) | AE65: BR2 CLOSET | AF65: Bed Rm # 2 Dn | AH65: REAR/Entry room | AJ65: ATTIC STAIRS TRAVEL | AK65: BILLARDS ROOM | AM65: BR PRIMARY | AN65: Stairs Basement | AO65: TBD | AR65: Pantry DN | AT65: TBD | AU65: Living Room | AW65: BR2 Closet | AX65: Basement Stairs | AY65: Bathroom DN Unit#1 | AZ65: FOYER SIDE ENTRY | BC65: BATH DN | BL65: TBD | BP65: TBD | BS65: GARAGE | BU65: INTERIOR REPAIRS | BV65: INTERIOR REPAIRS | BW65: TBD | BX65: Linen Closet | BY65: INTERIOR REPAIRS | CA65: Laundry Room | CC65: Attic 2 | CD65: TBD | CE65: BR2 CLOSET
D66: Room/Area 14 | F66: ='[1]jobinfo(2)'!$C$64 -> BR PRIMARY | G66: Hallway- up | H66: CLOSET BR MASTER | I66: TBD | J66: 0 | K66: Bsmnt rec 2 | N66: Linen Closet | O66: BEDROOM UP | P66: Basement | Q66: Living Room | R66: STORAGE 2 | S66: BR2 UP | T66: BEDOOM 3 CLOSET / BABY ROOM | U66: Bedroom 2 CLOSET | V66: TBD | X66: PBR CLOSET | Y66: PBR CLOSET | AA66: PRIMARY BEDROOM (PBR) | AD66: PBR CLOSET 1 | AE66: BR2 CLOSET 2 | AF66: Bed Rm # 2 Dn Closet | AH66: Pantry | AJ66: ATTIC | AK66: OFFICE | AM66: CLOSET PBR | AN66: Basement Rec 1 | AO66: TBD | AR66: FOYER RR ENTRY | AT66: TBD | AU66: Dining Room | AX66: Basement Rec Room | AY66: DINING ROOM DN Unit#1 | AZ66: STAIRS TO BASEMENT | BC66: KITCHEN | BL66: TBD | BP66: TBD | BS66: Roof shingle replace | BU66: TBD | BV66: Exterior SIDING | BW66: TBD | BX66: Bathroom | BY66: TBD | CA66: ROOF EXT | CC66: Attic 3 | CD66: TBD | CE66: BATH
D67: Room/Area 15 | E67: =D287 -> 0 | F67: Y | G67: Y | H67: Y | I67: Y | J67: y | K67: y | L67: y | N67: Y | O67: y | P67: Y | Q67: Y | R67: Y | S67: Y | T67: Babyroom Storage | U67: Bedroom 3 | V67: TBD | X67: BR 2 | Y67: BR 2 | AA67: PBR CLOSET 1 | AD67: BR1 | AE67: PRIMARY BEDROOM | AF67: Rear Stairwell To Basement,1st Fl,2nd Fl | AH67: Kitchen | AJ67: RFG HOUSE | AK67: BSMNT Storage 2 | AM67: CLOSET PBR 2 | AN67: REC 1 CLOSET | AO67: TBD | AR67: RR STAIRS LVL1 | AT67: TBD | AU67: Hallway UP | AX67: Utility / LAUNDRY | AY67: BEDROOM 1 Unit#1 | AZ67: FAMILYROOM/MAN CAVE | BC67: HALL BSMNT RR | BL67: TBD | BP67: TBD | BS67: Porches | BU67: Y | BV67: Y | BW67: TBD | BX67: Primary Bedroom | BY67: Y | CA67: Garage EXT RFG | CC67: Attic 4 | CD67: TBD | CE67: FRONT STORM DOOR
D68: Room/Area 16 | G68: TBD | H68: Victoria Lindsay | I68: TBD | J68: VENUS | K68: WALKER, RICHARD | N68: NA | P68: TBD | Q68: TBD | R68: TBD | T68: Attic | U68: Bedroom 3 CLOSET | V68: TBD | X68: Bathroom | Y68: Bathroom | AA68: LINEN CLOSET | AD68: BR1 CLOSET | AE68: PRIMARY CLOSET 2 | AF68: Basement Stairs | AJ68: RFG GARAGE | AK68: MAN CAVE | AM68: BR 2 | AN68: Utility/Laundry Room | AO68: TBD | AR68: RR HALL DN | AT68: TBD | AU68: Guest Closet | AY68: BEDROOM 1 CLOSET Unit#1 | AZ68: UTILITY ROOM | BC68: PANTRY/STORAGE | BL68: TBD | BP68: TBD | BS68: Deck/patio | BV68: TBD | BW68: TBD | BX68: Primary Bedroom Closet | BY68: TBD | CA68: SIDING EXT | CC68: Attic 5 | CD68: TBD | CE68: FRONT PORCH & CLG
D69: Room/Area 17 | E69: A224 | F69: Y | G69: Y | H69: Y | I69: Y | J69: y | K69: y | L69: y | N69: Y | O69: y | P69: Y | Q69: Y | R69: Y | S69: Y | T69: TBD | U69: STAIRS DN BSMNT | V69: TBD | X69: BR3 BR3 CLOSET | Y69: BR3 BR3 CLOSET | AA69: BEDROOM 2 | AD69: LINEN CLOSET2 | AE69: Hallway- DN | AF69: Basement Rec Rm # 1 | AK69: BSMNT Storage 1 | AM69: BR2 CLOSET | AN69: Stairs Up 2ND FLR | AO69: TBD | AR69: RR STAIRS UP TO LVL2 | AT69: TBD | AU69: Linen Closet | AY69: KITCHEN DN Unit# 1 | AZ69: Bathroom DN | BC69: UTILITY 2 | BL69: TBD | BP69: TBD | BR69: GARAGE 1 | BS69: yard area | BU69: Y | BV69: Y | BW69: TBD | BX69: Primary Bedroom Bath | BY69: Y | CC69: AWNING | CD69: TBD | CE69: GARAGE
D70: Room/Area 18 | F70: ='[1]jobinfo(2)'!$C$54 -> Living Room | G70: Guest Closet | H70: Living Room | I70: Basement STAIRS | J70: Living Room | K70: CLOSET | L70: HALL | N70: Kitchen | O70: HALL 1 - TRAVEL AREA | P70: LIVING ROOM | Q70: Stairs Up | R70: TRAVEL AREA | S70: Living Room | T70: TBD | U70: CLOSET DN | V70: TBD | AA70: BEDROOM 2 CLOSET | AD70: BR2 | AE70: Stairs BSMNT | AF70: Basement Rec Rm # 2 | AM70: Bedroom Up 3 | AN70: BR3 CLOSET1 | AO70: TBD | AR70: Foyer FRT UP ========== | AT70: TBD | AU70: BATH UP | AY70: PANTRY 1 Unit# 1 | AZ70: STORAGE UNDER STAIRS | BC70: TBD | BL70: TBD | BP70: TBD | BR70: GARAGE 2 | BS70: LINEN | BU70: TBD | BV70: Guest Closet | BW70: TBD | BX70: Bedroom 1 | BY70: Dining Room Travel Area | CC70: FRONT PORCH | CD70: TBD | CE70: ROOF
D71: Room/Area 19 | E71: =D300 -> 0 | F71: NA | G71: TBD | H71: NA | I71: tbd | J71: na | K71: na | L71: NA | N71: NA | O71: tbd | P71: TBD | Q71: TBD | R71: tbd | S71: NA | T71: TBD | U71: TV ROOM DEN DN | V71: TBD | AA71: BATHROOM | AD71: BR2 CLOSET | AE71: Basement | AF71: Basement Laundry & Utility Rm | AM71: BR3 CLOSET | AN71: Bedroom Up 3 | AO71: TBD | AR71: Hallway UP FRT | AT71: TBD | AU71: Bedroom - Master PBR BR1 | AY71: EXT EMS SECURE SITE | BC71: TBD | BL71: TBD | BP71: TBD | BS71: 0 | BU71: TBD | BV71: TBD | BW71: TBD | BX71: Bedroom 1 Closet | BY71: TBD | CC71: TBD | CD71: TBD | CE71: HVAC
D72: Room/Area 20 | F72: ='[1]jobinfo(2)'!$C$52 -> Bradley, Curtis L | G72: =G21 -> TBD | H72: Williams, Bridgett | I72: =I21 -> TBD | J72: =J21 -> 0 | K72: =K21 -> 0 | L72: =L21 -> 0 | N72: =N21 -> TBD | O72: =O21 -> 0 | P72: =P21 -> TBD | Q72: =Q21 -> 0 | R72: =R21 -> TBD | S72: =S21 -> (800) 354-2172 | T72: TBD | U72: UTILITY FURNANCE | V72: TBD | AA72: ATTIC STAIRS | AD72: ATTIC STAIRS | AF72: Front Stairwell/ Hallway To 2nd Fl | AM72: FRONT PORCH | AN72: BR3 STORAGE1 | AO72: TBD | AR72: Living Room UP | AT72: TBD | AU72: Master Closet 1 | AY72: ROOF EMS TARP RFG | BC72: TBD | BL72: TBD | BP72: TBD | BS72: 0 | BU72: =BU21 -> 216.654.1548 | BV72: =BV21 -> 0 | BW72: TBD | BX72: Bedroom 1 Bath | BY72: =BY21 -> 0 | CC72: TBD | CD72: TBD | CE72: YARD/LND
D73: Room/Area 21 | E73: A235-A270 | F73: Y | G73: Y | H73: Y | I73: Y | J73: y | K73: y | L73: y | N73: Y | O73: y | P73: Y | Q73: TBD | R73: Y | S73: Y | T73: TBD | V73: TBD | AA73: ATTIC HALL | AD73: ATTIC HALL | AF73: Living Rm Up 2nd Fl | AM73: EXTERIOR | AN73: BR3 STORAGE2 NW | AO73: TBD | AR73: FIREPLACE UP | AT73: TBD | AU73: Bedroom 2 | AY73: ROOF I LOW SLOPE MAIN | BC73: TBD | BL73: TBD | BP73: TBD | BR73: 99 | BS73: 0 | BU73: TBD | BV73: TBD | BW73: TBD | BX73: Bedroom 2 | BY73: Y | CC73: TBD | CD73: TBD
D74: Room/Area 22 | F74: ='[1]jobinfo(2)'!$C$55 -> Dining Room | G74: Guest Bath | H74: Dining Room | I74: Rec room Basement | J74: Dining Room | K74: Living Room | L74: BEDROOM | N74: Broom Closet | O74: HALL2 - TRAVEL AREA | P74: Dining Room | Q74: Hall Up | R74: STAIRS DN | S74: Dining Room | T74: TBD | U74: TBD | V74: TBD | W74: TBD | AA74: BR ATTIC 1 | AF74: Dining Room Up 2nd Fl | AM74: TBD | AN74: Bath UP | AO74: TBD | AR74: Dining Room UP | AT74: TBD | AU74: Bedroom 2 Closet | AY74: ROOF 2 FRONT HOOD | BC74: TBD | BL74: TBD | BP74: TBD | BR74: 99 | BS74: 0 | BU74: TBD | BV74: Bathroom | BW74: TBD | BX74: Bedroom 2 Closet | BY74: Kitchen Travel Area | CC74: TBD | CD74: TBD
D75: Room/Area 23 | F75: Y | G75: Y | H75: Y | I75: Y | J75: y | K75: y | L75: Y | N75: Y | O75: y | P75: Y | Q75: Y | R75: Y | S75: Y | T75: TBD | U75: TBD | V75: TBD | W75: TBD | AA75: BR ATTIC 2 | AF75: Kitchen Up 2nd Fl | AM75: TBD | AN75: BR3 STORAGE3 NE | AO75: TBD | AR75: Hallway UP @ BR & BATH | AT75: TBD | AU75: Bedroom 3 | AY75: MASONRY | BC75: TBD | BL75: TBD | BP75: TBD | BR75: 99 | BS75: 0 | BU75: Y | BV75: Y | BW75: TBD | BX75: Bedroom 2 Bath | BY75: Y | CC75: TBD | CD75: TBD
D76: Room/Area 24 | G76: TBD | H76: (216) 379-9943 | I76: TBD | J76: 918-407-4740 | K76: #REF! | N76: 216 789 5354 | O76: (678) 897-1688 • Mobile | P76: TBD | Q76: 0 | R76: 440.420.0625 | T76: TBD | U76: TBD | V76: TBD | W76: TBD | AA76: CLOSET ATTIC | AF76: Hallway Up 2nd Fl | AM76: TBD | AN76: RFG | AO76: TBD | AR76: PBR UP | AT76: TBD | AU76: Bedroom Closet 3 | AY76: YARD | BC76: TBD | BL76: TBD | BP76: TBD | BR76: 99 | BS76: 0 | BW76: TBD | BX76: Bedroom 3 | BY76: TBD | CC76: TBD | CD76: TBD
D77: Room/Area 25 | G77: TBD | H77: (330) 655-3776 | I77: TBD | J77: 0 | K77: 469.997.6270 | N77: TBD | O77: Hartford, CT 06183 | P77: TBD | Q77: TBD | R77: TBD | T77: TBD | U77: TBD | V77: TBD | W77: TBD | AF77: Bathroom Up 2nd Fl | AM77: TBD | AN77: SDG | AO77: TBD | AR77: PBR CLOSET UP | AT77: TBD | AU77: TBD | AY77: PORCH Unit#1 DN | BC77: TBD | BL77: TBD | BP77: TBD | BQ77: TBD | BR77: TBD | BS77: 0 | BU77: TBD | BW77: TBD | BX77: Bedroom 3 Closet | BY77: Bloomington, IL 61710 | CC77: TBD | CD77: TBD
D78: Mortgage co | F78: ='[1]jobinfo(2)'!$C$78 -> TBD | H78: TBD | I78: TBD | J78: 0 | K78: BATH UP | N78: TBD | O78: 0 | P78: TBD | Q78: ROOF EXTERIOR PAID WHEN INSTALLED (PWI ITEMS) | R78: TBD | T78: TBD | U78: TBD | V78: TBD | W78: TBD | AF78: Bedroom # 1 Up 2nd Fl | AL78: TBD | AM78: TBD | AN78: WDV | AO78: TBD | AP78: COMPU-LINK CORPORATION | AR78: Bath UP | AT78: TBD | AU78: TBD | AY78: SELECT PORTFOLIO SERVICING Its Successors And/Or Assigns PO BOX 7277 SPRINGFIELD, OH 45501 Loan Number: 0033272097 | BC78: TBD | BL78: TBD | BP78: TBD | BQ78: TBD | BR78: TBD | BS78: 0 | BU78: TBD | BW78: TBD | BX78: Bedroom 3 Bath | BY78: TBD | CC78: TBD | CD78: TBD
D79: Account# Mtge Co. | F79: ='[1]jobinfo(2)'!$C$79 -> TBD | H79: TBD | I79: TBD | J79: 0 | K79: LINEN 2 | N79: TBD | O79: 0 | P79: TBD | Q79: REBUILD OVERVIEW WORK IN PROGRESS....... WIP | R79: TBD | T79: TBD | U79: TBD | V79: TBD | W79: TBD | AF79: Bed Rm # 1 Up 2nd Fl Closet | AL79: TBD | AM79: TBD | AN79: EXT DOORS | AO79: TBD | AP79: 412-5570603 | AR79: Bedroom 2 UP | AT79: TBD | AU79: TBD | BC79: TBD | BL79: TBD | BP79: TBD | BQ79: TBD | BR79: TBD | BS79: Scott Wilson,Spvsr | BU79: TBD | BV79: KUD, PATRICK | BW79: TBD | BX79: Storage 1 | BY79: TBD | CC79: TBD | CD79: TBD
D80: Loan status | F80: ='[1]jobinfo(2)'!$C$80 -> TBD | H80: TBD | I80: TBD | J80: 0 | K80: Closet BR # 3 | N80: TBD | O80: 0 | P80: TBD | Q80: REBUILD INTERIOR COMPLETED WORK | R80: TBD | T80: TBD | U80: TBD | V80: TBD | W80: TBD | AF80: Bed Rm # 2 Up 2nd Fl | AL80: TBD | AM80: TBD | AO80: TBD | AP80: CURRENT | AR80: Bedroom 2 Closet UP | AT80: TBD | AU80: TBD | BC80: TBD | BL80: TBD | BP80: TBD | BQ80: TBD | BR80: TBD | BS80: x4019804 | BU80: TBD | BV80: 716.602.0146 | BW80: TBD | BX80: Storage 2 | BY80: TBD | CC80: TBD | CD80: TBD
D81: contact person mtge | F81: ='[1]jobinfo(2)'!$C$81 -> TBD | H81: TBD | I81: TBD | J81: 0 | K81: #REF! | N81: TBD | O81: 0 | P81: TBD | R81: TBD | T81: TBD | U81: TBD | V81: TBD | W81: TBD | AF81: Bed Rm # 2 Up 2nd Fl Closet | AL81: TBD | AM81: TBD | AO81: TBD | AR81: Kitchen UP | AT81: TBD | AU81: TBD | BC81: TBD | BL81: TBD | BP81: TBD | BQ81: TBD | BR81: TBD | BS81: 0 | BU81: TBD | BV81: Patrick.Kud@ryzeclaims.com | BW81: TBD | BX81: Basement | BY81: TBD | CC81: TBD | CD81: TBD
D82: Phone # MTGE contact | F82: ='[1]jobinfo(2)'!$C$82 -> TBD | H82: TBD | I82: TBD | J82: 0 | K82: #REF! | N82: TBD | O82: 0 | P82: TBD | R82: TBD | T82: TBD | U82: TBD | V82: TBD | W82: TBD | AF82: Linen Closet Up 2nd Fl | AL82: TBD | AM82: TBD | AO82: TBD | AR82: Pantry UP | AT82: TBD | AU82: TBD | BC82: TBD | BL82: TBD | BP82: TBD | BQ82: TBD | BR82: TBD | BS82: Elaine Gebsbher | BU82: TBD | BW82: TBD | BX82: Under Stairs Storage | BY82: TBD | CC82: TBD | CD82: TBD
D83: Ph. Ext. Mtge contact | F83: ='[1]jobinfo(2)'!$C$83 -> TBD | H83: TBD | I83: TBD | J83: 0 | K83: #REF! | N83: TBD | O83: 0 | P83: TBD | R83: TBD | T83: TBD | U83: TBD | V83: TBD | W83: TBD | AF83: Feb 7, 202411:28 PM EST | AL83: TBD | AM83: TBD | AO83: TBD | AR83: Hallway RR FLOOR2 UP | AT83: TBD | AU83: TBD | BC83: TBD | BL83: TBD | BP83: TBD | BQ83: TBD | BR83: TBD | BS83: 1.800.358.0600 | BU83: TBD | BW83: TBD | BX83: Rec Room 1 | BY83: TBD | CC83: TBD | CD83: TBD
F84: ='[1]jobinfo(2)'!$C$84 -> TBD | H84: TBD | I84: TBD | J84: 0 | K84: #REF! | N84: TBD | O84: 0 | P84: TBD | R84: TBD | T84: TBD | U84: TBD | V84: TBD | W84: TBD | AL84: TBD | AM84: TBD | AO84: TBD | AR84: PANTRY2 UP | AT84: TBD | AU84: TBD | BC84: TBD | BL84: TBD | BP84: TBD | BQ84: TBD | BR84: TBD | BS84: x4019804 | BU84: TBD | BW84: TBD | BX84: Rec Room 2 | BY84: TBD | CC84: TBD | CD84: TBD
D85: Attn.: Loss Draft Dept | F85: ='[1]jobinfo(2)'!$C$85 -> TBD | H85: TBD | I85: TBD | J85: 0 | K85: #REF! | N85: TBD | O85: 0 | P85: TBD | R85: TBD | T85: TBD | U85: TBD | V85: TBD | W85: TBD | AL85: TBD | AM85: TBD | AO85: TBD | AR85: Attic STAIRS RR ===== | AT85: TBD | AU85: TBD | BC85: TBD | BL85: TBD | BP85: TBD | BQ85: TBD | BR85: TBD | BS85: 1.800.326.2845 | BU85: TBD | BW85: TBD | BX85: Laundry Room | BY85: TBD | CC85: TBD | CD85: TBD
D86: Mtge OVN mail | F86: ='[1]jobinfo(2)'!$C$86 -> TBD | H86: TBD | I86: TBD | J86: 0 | K86: #REF! | N86: TBD | O86: 0 | P86: TBD | R86: TBD | T86: TBD | U86: TBD | V86: TBD | W86: TBD | AL86: TBD | AM86: TBD | AO86: TBD | AR86: Attic REC ROOM | AT86: TBD | AU86: TBD | BC86: TBD | BL86: TBD | BP86: TBD | BQ86: TBD | BR86: TBD | BS86: 0 | BU86: TBD | BW86: TBD | BX86: Utility Room | BY86: TBD | CC86: TBD | CD86: TBD
D87: city, St., zip ,mtge OVN | F87: ='[1]jobinfo(2)'!$C$87 -> TBD | H87: TBD | I87: TBD | J87: 0 | K87: #REF! | N87: TBD | O87: 0 | P87: TBD | R87: TBD | T87: TBD | U87: TBD | V87: TBD | W87: TBD | AL87: TBD | AM87: TBD | AO87: TBD | AR87: ATTIC Bedroom | AT87: TBD | AU87: TBD | BC87: TBD | BL87: TBD | BP87: TBD | BQ87: TBD | BR87: TBD | BS87: 0 | BU87: TBD | BW87: TBD | BY87: TBD | CC87: TBD | CD87: TBD
D88: Phone # MTGE co. | F88: ='[1]jobinfo(2)'!$C$88 -> TBD | H88: TBD | I88: TBD | J88: 0 | K88: #REF! | N88: TBD | O88: 0 | P88: TBD | R88: TBD | T88: TBD | U88: TBD | V88: TBD | W88: TBD | AL88: TBD | AM88: TBD | AO88: TBD | AR88: ATTIC CLOSET | AT88: TBD | AU88: TBD | BC88: TBD | BL88: TBD | BP88: TBD | BQ88: TBD | BR88: TBD | BS88: 0 | BU88: TBD | BV88: TBD | BW88: TBD | BX88: FLOOR2 | BY88: TBD | CC88: TBD | CD88: TBD
D89: email mtge | F89: ='[1]jobinfo(2)'!$C$89 -> TBD | H89: TBD | I89: TBD | J89: 0 | K89: #REF! | N89: TBD | O89: 0 | P89: TBD | R89: TBD | T89: TBD | U89: TBD | V89: TBD | W89: TBD | AL89: TBD | AM89: TBD | AO89: TBD | AR89: ATTIC STAIRS FRT | AT89: TBD | AU89: TBD | BC89: TBD | BL89: TBD | BP89: TBD | BQ89: TBD | BR89: TBD | BS89: 0 | BU89: TBD | BV89: TBD | BW89: TBD | BX89: Foyer | BY89: TBD | CC89: TBD | CD89: TBD
D90: mtge website | F90: ='[1]jobinfo(2)'!$C$90 -> TBD | H90: TBD | I90: TBD | J90: 0 | K90: #REF! | N90: TBD | O90: 0 | P90: TBD | R90: TBD | T90: TBD | U90: TBD | V90: TBD | W90: TBD | AL90: TBD | AM90: TBD | AO90: TBD | AR90: ATTIC HALL FRT | AT90: TBD | AU90: TBD | BC90: TBD | BL90: TBD | BP90: TBD | BQ90: TBD | BR90: TBD | BS90: 0 | BU90: TBD | BV90: TBD | BW90: TBD | BY90: TBD | CC90: TBD | CD90: TBD
D91: MTGE co. Fax # | F91: ='[1]jobinfo(2)'!$C$91 -> TBD | H91: TBD | I91: TBD | J91: 0 | K91: #REF! | N91: TBD | O91: 0 | P91: TBD | R91: TBD | T91: TBD | U91: TBD | V91: TBD | W91: TBD | AL91: TBD | AM91: TBD | AO91: TBD | AR91: Basement STAIRS ======= | AT91: TBD | AU91: TBD | BC91: TBD | BL91: TBD | BP91: TBD | BQ91: TBD | BR91: TBD | BS91: 0 | BU91: TBD | BV91: TBD | BW91: TBD | BX91: Guest Closet | BY91: TBD | CC91: TBD | CD91: TBD
D92: Mailing address mtge | F92: ='[1]jobinfo(2)'!$C$92 -> TBD | G92: TBD | H92: TBD | I92: TBD | J92: 0 | K92: #REF! | N92: TBD | O92: 0 | P92: TBD | Q92: TBD | R92: TBD | T92: TBD | U92: TBD | V92: TBD | W92: TBD | AL92: TBD | AM92: TBD | AO92: TBD | AP92: 14002 E 21 ST STE #300 | AR92: Under Stairs Storage | AT92: TBD | AU92: TBD | BC92: TBD | BL92: TBD | BP92: TBD | BQ92: TBD | BR92: TBD | BS92: 0 | BU92: TBD | BV92: TBD | BW92: TBD | BX92: Living Room | BY92: TBD | CC92: TBD | CD92: TBD
D93: Mail city, state, zip mtge | F93: ='[1]jobinfo(2)'!$C$93 -> TBD | G93: TBD | H93: TBD | I93: TBD | J93: 0 | K93: #REF! | N93: TBD | O93: 0 | P93: TBD | Q93: TBD | R93: TBD | T93: TBD | U93: TBD | V93: TBD | W93: TBD | AL93: TBD | AM93: TBD | AO93: TBD | AP93: TULSA, OK 74134-1421 | AR93: BASEMENT COMMOM AREA | AT93: TBD | AU93: TBD | BC93: TBD | BL93: TBD | BP93: TBD | BQ93: TBD | BR93: TBD | BS93: 0 | BU93: TBD | BV93: TBD | BW93: TBD | BX93: Dining Room | BY93: TBD | CC93: TBD | CD93: TBD
F94: ='[1]jobinfo(2)'!$C$94 -> TBD | G94: TBD | H94: TBD | I94: TBD | J94: 0 | K94: #REF! | N94: TBD | O94: 0 | P94: TBD | Q94: TBD | R94: TBD | T94: TBD | U94: TBD | V94: TBD | W94: TBD | AL94: TBD | AM94: TBD | AO94: TBD | AR94: Laundry Room | AT94: TBD | AU94: TBD | BC94: TBD | BL94: TBD | BP94: TBD | BQ94: TBD | BR94: TBD | BS94: 0 | BU94: TBD | BV94: TBD | BW94: TBD | BX94: Hallway UP | BY94: TBD | CC94: TBD | CD94: TBD
D95: Initial Offer / phase 1 contract amount | F95: ='[1]jobinfo(2)'!$C$95 -> TBD | G95: TBD | H95: TBD | I95: TBD | J95: 0 | K95: #REF! | N95: TBD | O95: 0 | P95: TBD | Q95: TBD | R95: TBD | T95: TBD | U95: TBD | V95: TBD | W95: TBD | AL95: TBD | AM95: TBD | AO95: TBD | AR95: Utility Room | AT95: TBD | AU95: TBD | BC95: TBD | BL95: TBD | BP95: TBD | BQ95: TBD | BR95: TBD | BU95: TBD | BV95: TBD | BW95: TBD | BX95: Kitchen | BY95: TBD | CC95: TBD | CD95: TBD
D96: Draw Request | F96: ='[1]jobinfo(2)'!$C$96 -> TBD | G96: TBD | H96: TBD | I96: TBD | J96: 0 | K96: #REF! | N96: TBD | O96: 0 | P96: TBD | Q96: TBD | R96: TBD | T96: TBD | U96: TBD | V96: TBD | W96: TBD | AL96: TBD | AM96: TBD | AO96: TBD | AR96: BSMNT Storage 1 | AT96: TBD | AU96: TBD | BC96: TBD | BL96: TBD | BP96: TBD | BQ96: TBD | BR96: TBD | BU96: TBD | BV96: TBD | BW96: TBD | BX96: Pantry | BY96: TBD | CC96: TBD | CD96: TBD
D97: Cust id | F97: ='[1]jobinfo(2)'!$C$97 -> TBD | G97: TBD | H97: TBD | I97: TBD | J97: 0 | K97: #REF! | N97: TBD | O97: 0 | P97: TBD | Q97: TBD | R97: TBD | T97: TBD | U97: TBD | V97: TBD | W97: TBD | AL97: TBD | AM97: TBD | AO97: TBD | AR97: BSMNT Storage 2 | AT97: TBD | AU97: TBD | BC97: TBD | BL97: TBD | BP97: TBD | BQ97: TBD | BR97: TBD | BU97: TBD | BV97: TBD | BW97: TBD | BX97: Nook | BY97: TBD | CC97: TBD | CD97: TBD
F98: ='[1]jobinfo(2)'!$C$98 -> TBD | G98: TBD | H98: TBD | I98: TBD | J98: PROVISO INVESTMENTS | K98: #REF! | N98: TBD | O98: 0 | P98: TBD | Q98: TBD | R98: TBD | T98: TBD | U98: TBD | V98: TBD | W98: TBD | AL98: TBD | AM98: TBD | AO98: TBD | AR98: EXT SIDING ========== | AT98: TBD | AU98: TBD | BC98: TBD | BL98: TBD | BP98: TBD | BQ98: TBD | BR98: TBD | BU98: TBD | BV98: TBD | BW98: TBD | BX98: Hallway | BY98: TBD | CC98: TBD | CD98: TBD
D99: REP COMPANY | F99: Joe Jones, PM 216.450.7228 | G99: Joe Jones, PM 216.450.7228 | H99: Joe Jones, PM 216.450.7228 | I99: Joe Jones, PM 216.450.7228 | J99: Joe Jones, PM 216.450.7228 | K99: Joe Jones, PM 216.450.7228 | L99: Joe Jones, PM 216.450.7228 | M99: Joe Jones, PM 216.450.7228 | N99: Joe Jones, PM 216.450.7228 | O99: Joe Jones, PM 216.450.7228 | P99: Joe Jones, PM 216.450.7228 | Q99: Joe Jones, PM 216.450.7228 | R99: Joe Jones, PM 216.450.7228 | S99: Joe Jones, PM 216.450.7228 | T99: Joe Jones, PM 216.450.7228 | U99: Joe Jones, PM 216.450.7228 | V99: Joe Jones, PM 216.450.7228 | W99: Joe Jones, PM 216.450.7228 | X99: Joe Jones, PM 216.450.7228 | Y99: Joe Jones, PM 216.450.7228 | Z99: Joe Jones, PM 216.450.7228 | AA99: Joe Jones, PM 216.450.7228 | AB99: Joe Jones, PM 216.450.7228 | AC99: Joe Jones, PM 216.450.7228 | AD99: Joe Jones, PM 216.450.7228 | AE99: Joe Jones, PM 216.450.7228 | AF99: Joe Jones, PM 216.450.7228 | AG99: Joe Jones, PM 216.450.7228 | AH99: Joe Jones, PM 216.450.7228 | AI99: Joe Jones, PM 216.450.7228 | AM99: TBD | AO99: TBD | AP99: Joe Jones, PM 216.450.7228 | AQ99: Joe Jones, PM 216.450.7228 | AR99: FRONT LOWER PORCH | AS99: Joe Jones, PM 216.450.7228 | AT99: TBD | AU99: TBD | BC99: TBD | BL99: TBD | BO99: Joe Jones, PM 216.450.7228 | BP99: Joe Jones, PM 216.450.7228 | BQ99: Joe Jones, PM 216.450.7228 | BS99: Joe Jones, PM 216.450.7228 | BT99: Joe Jones, PM 216.450.7228 | BU99: Joe Jones, PM 216.450.7228 | BV99: Joe Jones, PM 216.450.7228 | BW99: Joe Jones, PM 216.450.7228 | BX99: Guest Bath | BY99: Joe Jones, PM 216.450.7228 | BZ99: Joe Jones, PM 216.450.7228 | CA99: Joe Jones, PM 216.450.7228 | CB99: Joe Jones, PM 216.450.7228 | CC99: Joe Jones, PM 216.450.7228 | CE99: Joe Jones, PM 216.450.7228 | CF99: Joe Jones, PM 216.450.7228 | CG99: Joe Jones, PM 216.450.7228
D100: co name | F100: ='[1]jobinfo(2)'!$C$100 -> All Phase Consulting, LLC | G100: Bal Construction and Restoration LLC | H100: All Phase Consulting, LLC | I100: All Phase Consulting, LLC | J100: ALL PHASE CONSULTING, LLC | K100: PROVISO INVESTMENTS | L100: ALL PHASE CONSULTING, LLC | M100: All Phase Consulting, LLC | N100: All Phase Consulting, LLC | O100: ALL PHASE CONSULTING, LLC | P100: All Phase Consulting, LLC | Q100: All Phase Consulting, LLC | R100: All Phase Consulting, LLC | S100: All Phase Consulting, LLC | T100: All Phase Consulting, LLC | U100: All Phase Consulting, LLC | V100: AK Builders Group LLC | W100: All Phase Consulting, LLC | X100: All Phase Consulting, LLC | Y100: All Phase Consulting, LLC | Z100: All Phase Consulting, LLC | AA100: All Phase Consulting, LLC | AB100: All Phase Consulting, LLC | AC100: All Phase Consulting, LLC | AD100: All Phase Consulting, LLC | AE100: All Phase Consulting, LLC | AF100: Bal Construction and Restoration LLC | AG100: All Phase Consulting, LLC | AH100: All Phase Consulting, LLC | AI100: All Phase Consulting, LLC | AJ100: All Phase Consulting, LLC | AK100: ALL PHASE CONSULTING, LLC | AL100: All Phase Consulting, LLC | AM100: All Phase Consulting, LLC | AN100: All Phase Consulting, LLC | AO100: All Phase Consulting, LLC | AP100: All Phase Consulting, LLC | AQ100: All Phase Consulting, LLC | AR100: G.M Home Renovations | AS100: All Phase Consulting, LLC | AT100: All Phase Consulting, LLC | AU100: Platinum One Properties, LLC | AV100: All Phase Consulting, LLC | AW100: All Phase Consulting, LLC | AX100: All Phase Consulting, LLC | AY100: All Phase Consulting, LLC | AZ100: All Phase Consulting, LLC | BB100: All Phase Consulting, LLC | BC100: All Phase Consulting, LLC | BL100: All Phase Consulting, LLC | BO100: All Phase Consulting, LLC | BP100: All Phase Consulting, LLC | BQ100: All Phase Consulting, LLC | BR100: All Phase Consulting, LLC | BS100: ALL PHASE CONSULTING, LLC | BU100: PROVISO INVESTMENTS | BV100: All Phase Consulting, LLC | BW100: All Phase Consulting, LLC | BX100: All Phase Consulting, LLC | BY100: All Phase Consulting, LLC | BZ100: All Phase Consulting, LLC | CA100: All Phase Consulting, LLC | CB100: All Phase Consulting, LLC | CC100: All Phase Consulting, LLC | CD100: All Phase Consulting, LLC | CE100: All Phase Consulting, LLC | CF100: All Phase Consulting, LLC | CG100: Platinum One Properties, LLC
...

Sheet ALE
A1: 1 | B1: ALE STEPS | D1: DATA INPUT FIELDS | E1: ALE INFO … APC # | F1: =ALL!#REF! -> #REF! | H1: ALE INFO … APC # | I1: =ALL!AT146 -> OH25 LACEY, E | K1: ALE INFO … APC # | L1: =ALL!AU146 -> OH25 BROOKS,@YNG | N1: ALE INFO … APC # | O1: =ALL!AV146 -> GA25 SMITH @GERTRUDE PL | P1: ALE INFO … APC # | Q1: ALE INFO … APC #
A2: =+A1+1 -> 2 | B2: Lesse info | C2: Lesse info | E2: Lesse info | F2: Lesse info | H2: Lesse info | I2: Lesse info | J2: Lesse info | K2: Lesse info | L2: Lesse info | M2: Lesse info | N2: Lesse info | O2: Lesse info | P2: Lesse info | Q2: Lesse info | R2: Lesse info | S2: Lesse info
A3: =+A2+1 -> 3 | B3: DATA INPUT | C3: IMPORTS LESSEE INFO FROM jobinfo(2) (AUTO FILL) | E3: Lesse info / NAME | F3: =ALL!#REF! -> #REF! | H3: Lesse info / NAME | I3: =ALL!AT128 -> LACEY, EUNICE | K3: Lesse info / NAME | L3: =ALL!AU128 -> BROOKS, DANIEL;JANAE POA | N3: Lesse info / NAME | O3: =ALL!AV128 -> Smith, Brian | P3: Lesse info / NAME | Q3: =ALL!AW128 -> THOMAS, ANITA
C4: INFO SHEET FOR DATA INPUT emailed to R/E CONTACT | E4: HOME ADDRESS | F4: =ALL!#REF! -> #REF! | H4: HOME ADDRESS | I4: =ALL!AT129 -> 13601 5th Ave | K4: HOME ADDRESS | L4: =ALL!AU129 -> 3427 SANDALWOOD LN | N4: HOME ADDRESS | O4: =ALL!AV129 -> 831 Gertrude Place NW, | P4: HOME ADDRESS | Q4: =ALL!AW129 -> 6600 GERTRUDE
C5: lessor info & terms manual input | E5: TENANT Property city, state, zip | F5: =ALL!#REF! -> #REF! | H5: TENANT Property city, state, zip | I5: =ALL!AT130 -> East Cleveland, OH 44112 | K5: TENANT Property city, state, zip | L5: =ALL!AU130 -> Austintown, OH 44511 | N5: Property city, state, zip | O5: =ALL!AV130 -> Atlanta, GA 30318 | P5: Property city, state, zip | Q5: =ALL!AW130 -> Cleveland, OH 44105
C6: LEASE Data APPROVED BY R/E CONTACT | E6: Customer Email | F6: =ALL!#REF! -> #REF! | H6: Customer Email | I6: =ALL!AT131 -> Emdlacey@gmail.com | K6: Customer Email | L6: =ALL!AU131 -> JANAETAB16@YAHOO.COM | N6: Customer Email | O6: =ALL!AV131 -> BRIAN.ASHTON.SMITH.211@GMAIL.COM | P6: Customer Email | Q6: Trenddamnish@yahoo.com
C7: LEASE TERMS CREATED & ENTERED (final) | E7: Cst-owner Phone# | F7: =ALL!#REF! -> #REF! | H7: Cst-owner Phone# | I7: =ALL!AT132 -> (216) 450-4913 | K7: Cst-owner Phone# | L7: =ALL!AU132 -> (330) 951-2652 | N7: Customer Phone# | O7: =ALL!AV132 -> (404) 444-1325 | P7: Customer Phone# | Q7: =ALL!AW132 -> (216) 315-2040
B9: DATA OUTPUT | C9: INFO SHEET FOR DATA INPUT (FILE COPY) | E9: RENTAL INFO | H9: RENTAL INFO | K9: RENTAL INFO | N9: RENTAL INFO | P9: RENTAL INFO | Q9: RENTAL INFO
C10: R/E ENGAGEMENT DOC CREATED | E10: bedrooms | F10: =ALL!#REF! -> #REF! | H10: bedrooms | I10: =ALL!AT148 -> 3 | K10: bedrooms | L10: =ALL!AU148 -> 3 | N10: bedrooms | O10: =ALL!AV148 -> 3 | P10: bedrooms | Q10: 3
C11: LEASECREATED | E11: months | F11: =ALL!#REF! -> #REF! | H11: months | I11: =ALL!AT149 -> 4 | K11: months | L11: =ALL!AU149 -> 4 | N11: months | O11: 6 | P11: months | Q11: 6
C12: TERM SHEET CREATED | E12: START DATE | F12: =ALL!#REF! -> #REF! | H12: START DATE | I12: =ALL!AT150 -> 45768 | K12: START DATE | L12: 45846 | N12: START DATE | O12: =ALL!AV150 -> Tuesday, March 11, 2025 | P12: START DATE | Q12: 45931
E13: END DATE | F13: =ALL!#REF! -> #REF! | H13: END DATE | I13: =ALL!AT151 -> 45888 | K13: END DATE | L13: =L12+L11*30+2 -> 45968 | N13: END DATE | O13: =ALL!AV151 -> Tuesday, March 11, 2025 | P13: END DATE | Q13: Saturday, January 31, 2026
B14: External steps SENT OUT FOR SIGNING | C14: DOCS EMAILED TO LESSOR | E14: Amount / Month | F14: =ALL!#REF! -> #REF! | H14: Amount / Month | I14: =ALL!AT152 -> 2200 | K14: Amount / Month | L14: =ALL!AU152 -> 2200 | N14: Amount / Month | O14: 3500 | P14: Amount / Month | Q14: 2200
C16: DOCS EMAILED TO TO LESSEE | E16: LESSOR INFO / NAME | F16: =ALL!#REF! -> #REF! | H16: LESSOR INFO / NAME | I16: =ALL!AT155 -> Floretta Crowell | K16: LESSOR INFO / NAME | L16: =ALL!AU155 -> BACON, MICHELLE | N16: LESSOR INFO / NAME | O16: =ALL!AV155 -> Sophia Crawford | P16: LESSOR INFO / NAME | Q16: GLOBAL REALTY INVESTOR RELATIONS, INC
E17: Leased Address | F17: =ALL!#REF! -> #REF! | H17: Leased Address | I17: =ALL!AT156 -> 19048 Watercrest Dr. | K17: Leased Address | L17: =ALL!AU156 -> 3455 MILVERTON | N17: Leased Address | O17: =ALL!AV156 -> 5507 Cascade Hills Loop SW | P17: Leased Address | Q17: 3685 E153
B18: LESSOR steps | C18: LEASE DOCS RECEIVED | E18: city zip | F18: =ALL!#REF! -> #REF! | H18: city zip | I18: =ALL!AT157 -> Mapel Heights, OH, 44137 | K18: city zip | L18: =ALL!AU157 -> SHAKER HEIGHTS, OH 44120 | N18: city zip | O18: =ALL!AV157 -> Atlanta, GA 30331 | P18: city zip | Q18: Cleveland OH 44120
C19: LEASE DOCS SIGNED BY LESSOR & RETURNED | E19: phone # | F19: =ALL!#REF! -> #REF! | H19: phone # | I19: 2164086035 | K19: phone # | L19: 3309512497 | N19: phone # | O19: =ALL!AV158 -> 404-444-7271 | P19: phone # | Q19: 216-938-2176
E20: Email lessor | F20: =ALL!#REF! -> #REF! | H20: Email lessor | I20: =ALL!AT159 -> FLOCROW48@AOL.COM | K20: Email lessor | L20: bch3oh10@gmail.com | N20: Email lessor | O20: =ALL!AV159 -> Top4118@aol.com | P20: Email lessor | Q20: grirmanagement@gmail.com
B22: LESSEE steps | C22: LEASE DOCS RECEIVED | E22: Lessor mailing Address | F22: =ALL!#REF! -> #REF! | H22: Lessor mailing Address | I22: =ALL!AT161 -> 2479 Greenvale | K22: Lessor mailing Address | L22: =ALL!AU161 -> 16100 VAN AKEN BLVD #206, | N22: Lessor mailing Address | O22: =ALL!AV161 -> 66 Crawford Rd | P22: Lessor mailing Address | Q22: 3043 Superior Avenue #301
C23: LEASE DOCS SIGNED BY LESSEE & RETURNED | E23: city zip | F23: =ALL!#REF! -> #REF! | H23: city zip | I23: =ALL!AT162 -> Cleveland, OH, 44121 | K23: city zip | L23: =ALL!AU162 -> SHAKER HEIGHTS, OH 44120 | N23: city zip | O23: =ALL!AV162 -> Pine Hill, AL 36769 | P23: city zip | Q23: Cleveland Ohio 44114
E24: LESSOR CONTACT PERSON | F24: =ALL!#REF! -> #REF! | H24: LESSOR CONTACT PERSON | I24: =ALL!AT163 -> Floretta Crowell | K24: LESSOR CONTACT PERSON | L24: =ALL!AU163 -> BACON, MICHELLE | N24: LESSOR CONTACT PERSON | O24: =ALL!AV163 -> 0 | P24: LESSOR CONTACT PERSON | Q24: Kelly Williams
A26: =+#REF!+1 -> #REF! | B26: REAL ESTATE COMPANY TASKS | C26: SIGNED LEASE APPROVED BY R/E CONTACT | E26: CLAIM INFO | F26: =ALL!#REF! -> #REF! | H26: CLAIM INFO | I26: =ALL!AT133 -> CLAIM INFO | K26: CLAIM INFO | L26: =ALL!AU133 -> CLAIM INFO | N26: CLAIM INFO | O26: =ALL!AV133 -> CLAIM INFO | P26: CLAIM INFO | Q26: =ALL!AW133 -> CLAIM INFO
A27: =+A26+1 -> #REF! | C27: DOCS SENT TO INSURANCE COMPANY | E27: Cause of Loss | F27: =ALL!#REF! -> #REF! | H27: Cause of Loss | I27: =ALL!AT134 -> BATHTUB OVERFLOW | K27: Cause of Loss | L27: =ALL!AU134 -> WATER PIPE BROKE | N27: Cause of Loss | O27: =ALL!AV134 -> KITCHEN WATER PIPE BROKE | P27: Cause of Loss | Q27: =ALL!AW134 -> Water Damage=WTR
A28: =+A27+1 -> #REF! | C28: R/E ENGAGEMENT DOC | E28: date of loss | F28: =ALL!#REF! -> #REF! | H28: date of loss | I28: =ALL!AT135 -> 45765 | K28: date of loss | L28: =ALL!AU135 -> Sunday, March 2, 2025 | N28: date of loss | O28: =ALL!AV135 -> Tuesday, March 11, 2025 | P28: date of loss | Q28: =ALL!AW135 -> Friday, September 12, 2025
A29: =+#REF!+1 -> #REF! | C29: TERM SHEET | E29: Insurance Co. Name | F29: =ALL!#REF! -> #REF! | H29: Insurance Co. Name | I29: =ALL!AT138 -> AAA Insurance | K29: Insurance Co. Name | L29: =ALL!AU138 -> Allstate Insurance Company | N29: Insurance Co. Name | O29: =ALL!AV138 -> Esurance | P29: Insurance Co. Name | Q29: ALLSTATE INS CO.
A30: =+A29+1 -> #REF! | C30: LEASE/SIGNED | E30: Claim # | F30: =ALL!#REF! -> #REF! | H30: Claim # | I30: =ALL!AT139 -> #017095711 | K30: Claim # | L30: =ALL!AU139 -> #0786294926 | N30: Claim # | O30: =ALL!AV139 -> #250254318 | P30: Claim # | Q30: #0808044169
A31: =+A30+1 -> #REF! | C31: LEAD DOCS | E31: policy # | F31: =ALL!#REF! -> #REF! | H31: policy # | I31: =ALL!AT140 -> OHH000190052 | K31: policy # | L31: =ALL!AU140 -> 980 610 253 | N31: policy # | O31: =ALL!AV140 -> : 10610052 | P31: policy # | Q31: 880 022 226
A32: =+A31+1 -> #REF! | C32: CONFIRM RECEIPT | E32: Email INS. co. | F32: =ALL!#REF! -> #REF! | H32: Email INS. co. | I32: =ALL!AT141 -> STAPLES.OLIVIA @ace.aaa.com | K32: Email INS. co. | L32: =ALL!AU141 -> claims@claims.allstate.com | N32: Email INS. co. | O32: =ALL!AV141 -> carla.robledo@ngic.com | P32: Email INS. co. | Q32: claims@claims.allstate.com
A33: =+A32+1 -> #REF! | C33: CONFIRM PAYMENT | E33: DESK Adjuster DA | F33: =ALL!#REF! -> #REF! | H33: DESK Adjuster DA | I33: =ALL!AT142 -> STAPLES, OLIVIA 207 776 6150 | K33: DESK Adjuster DA | L33: =ALL!AU142 -> LYLE KENDICKS | N33: DESK Adjuster DA | O33: =ALL!AV142 -> Carla Robledo| | P33: DESK Adjuster DA | Q33: =ALL!#REF! -> #REF!
A34: =+A33+1 -> #REF! | C34: DISBURSE FUNDS | E34: DA Phone | F34: =ALL!#REF! -> #REF! | H34: DA Phone | I34: =ALL!AT143 -> 207 776 6150 | K34: DA Phone | L34: =ALL!AU143 -> 888 656.8005 | N34: DA Phone | O34: =ALL!AV143 -> (800) 378-7262 | P34: DA Phone | Q34: TBD
A35: =+A34+1 -> #REF! | C35: FILE EXTENSION AS NEEDED (50% FEE = NEW LEASE) | E35: DA Ph. Ext. # | F35: =ALL!#REF! -> #REF! | H35: DA Ph. Ext. # | I35: =ALL!AT144 -> 207 776 6150 | K35: DA Ph. Ext. # | L35: =ALL!AU144 -> 9892774564 | N35: DA Ph. Ext. # | O35: =ALL!AV144 -> (336) 331-6825 | P35: DA Ph. Ext. # | Q35: TBD
A36: =+A35+1 -> #REF! | E36: DA Email | F36: =ALL!#REF! -> #REF! | H36: DA Email | I36: =ALL!AT145 -> STAPLES.OLIVIA @ace.aaa.com | K36: DA Email | L36: =ALL!AU145 -> lyle.kendrick@allstate.com | N36: DA Email | O36: =ALL!AV145 -> carla.robledo@ngic.com | P36: DA Email | Q36: TBD
A37: =+A36+1 -> #REF!
A38: =+#REF!+1 -> #REF! | E38: REAL ESTATE COMPANY | F38: =ALL!#REF! -> #REF! | H38: REAL ESTATE COMPANY | I38: DREAM TEAM REALTY, INC | K38: REAL ESTATE COMPANY | L38: DREAM TEAM REALTY, INC | N38: REAL ESTATE COMPANY | O38: DREAM TEAM REALTY, INC | P38: REAL ESTATE COMPANY | Q38: DREAM TEAM REALTY, INC
A39: =+A38+1 -> #REF! | E39: MAILING ADDRESS | F39: =ALL!#REF! -> #REF! | H39: MAILING ADDRESS | I39: 17419 BROADWAY AVE | K39: MAILING ADDRESS | L39: 17419 BROADWAY AVE | N39: MAILING ADDRESS | O39: 17419 BROADWAY AVE | P39: MAILING ADDRESS | Q39: 17419 BROADWAY AVE
A40: =+A39+1 -> #REF! | B40: STACKING LIST | C40: R/E ENGAGEMENT DOC | E40: city zip | F40: =ALL!#REF! -> #REF! | H40: city zip | I40: MAPLE HEIGHTS,OH 44137 | K40: city zip | L40: MAPLE HEIGHTS,OH 44137 | N40: city zip | O40: MAPLE HEIGHTS,OH 44137 | P40: city zip | Q40: MAPLE HEIGHTS,OH 44137
A41: =+A40+1 -> #REF! | C41: TERM SHEET | E41: CONTACT | F41: =ALL!#REF! -> #REF! | H41: CONTACT | I41: TREVOR ARCHER | K41: CONTACT | L41: TREVOR ARCHER | N41: CONTACT | O41: TREVOR ARCHER | P41: CONTACT | Q41: TREVOR ARCHER
A42: =+A41+1 -> #REF! | C42: LEASE/SIGNED | E42: phone # | F42: =ALL!#REF! -> #REF! | H42: phone # | I42: (914) 217-3339 | K42: phone # | L42: (914) 217-3339 | N42: phone # | O42: (914) 217-3339 | P42: phone # | Q42: (914) 217-3339
A43: =+A42+1 -> #REF! | C43: LEAD DOCS | E43: Email | F43: =ALL!#REF! -> #REF! | H43: Email | I43: INFO@2GETTREVOR.COM | K43: Email | L43: INFO@2GETTREVOR.COM | N43: Email | O43: INFO@2GETTREVOR.COM | P43: Email | Q43: INFO@2GETTREVOR.COM
A44: =+A43+1 -> #REF! | C44: INFO SHEET FOR DATA INPUT (FILE COPY) | E44: OWNER/BROKER | F44: =ALL!#REF! -> #REF! | H44: OWNER/BROKER | I44: JULIUS CARTWRIGHT | K44: OWNER/BROKER | L44: JULIUS CARTWRIGHT | N44: OWNER/BROKER | O44: JULIUS CARTWRIGHT | P44: OWNER/BROKER | Q44: JULIUS CARTWRIGHT
A45: =+A44+1 -> #REF! | E45: phone # | F45: =ALL!#REF! -> #REF! | H45: phone # | I45: 2169901501 | K45: phone # | L45: 2169901501 | N45: phone # | O45: 2169901501 | P45: phone # | Q45: 2169901501
A46: =+A45+1 -> #REF! | E46: Email | F46: =ALL!#REF! -> #REF! | H46: Email | I46: JULIUSCARTWRIGHT@gmail.com | K46: Email | L46: JULIUSCARTWRIGHT@gmail.com | N46: Email | O46: JULIUSCARTWRIGHT@gmail.com | P46: Email | Q46: JULIUSCARTWRIGHT@gmail.com
A47: =+A46+1 -> #REF! | F47: =ALL!#REF! -> #REF! | I47: =ALL!AT178 -> 0 | L47: =ALL!AU178 -> 0 | O47: =ALL!AV178 -> 0
A48: =+A47+1 -> #REF! | F48: =ALL!#REF! -> #REF! | I48: =ALL!AT179 -> 0 | L48: =ALL!AU179 -> #N/A | O48: =ALL!AV179 -> 0
A49: =+A48+1 -> #REF! | F49: =ALL!#REF! -> #REF! | I49: =ALL!AT180 -> 0 | L49: =ALL!AU180 -> #N/A | O49: =ALL!AV180 -> 0
A50: =+#REF!+1 -> #REF!
A51: =+A50+1 -> #REF! | O51: =6*3500 -> 21000
A52: =+A51+1 -> #REF! | O52: =5*3500 -> 17500
A53: =+A52+1 -> #REF! | O53: =4*3500 -> 14000
A54: =+A53+1 -> #REF!
A55: =+A54+1 -> #REF!
A56: =+A55+1 -> #REF!
A57: =+A56+1 -> #REF!
A58: =+A57+1 -> #REF!
A59: =+A58+1 -> #REF!
A60: =+A59+1 -> #REF!
A61: =+A60+1 -> #REF!
A62: =+A61+1 -> #REF!
A63: =+A62+1 -> #REF!
A64: =+A63+1 -> #REF!
A65: =+A64+1 -> #REF!

Sheet dashb
C7: Row Labels | D7: Max of Percentages | M7: ROOF | N7: EMS EXT | O7: INT MIT | P7: CPS | Q7: PPR | R7: REBLD | S7: SPLM | T7: ALE
C8: ANDERSON, PETE | D8: 0.8835 | M8: TBD | N8: JJ | O8: TBD | P8: TBD | Q8: TBD | R8: TBD | S8: TBD | T8: TBD
C9: Battle, Larry Jr | D9: 0.3704 | E9: TBD | F9: TBD | M9: TBD | N9: TBD | O9: TBD | P9: TBD | Q9: TBD | R9: TBD | S9: TBD | T9: TBD
C10: Bradley, Curtis L | D10: 0.6044
C11: Brown, Charles | D11: 0.5088
C12: FERGUSON, ROBERT & MRS | D12: 0.8596
C13: Franklin Annette | D13: 0.5812
C14: Harvey, CORA | D14: 0.4786
C15: HICKS, JASON | D15: 1
C16: JOHNSON,MIKE RFG | D16: 0.5053
C17: JOHNSON,MIKE WTR | D17: 0.5373
C18: KOSWATTA, ERIKA | D18: 0.6386
C19: LANEY, Anthony | D19: 0.6386
C20: LAWRENCE, GENEATHA | D20: 0.7175
C21: LEETH, RONNIE | D21: 0.6538
... C34: Grand Total | D34: 1
B44: Claims | C44: P | D44: Percentages
B45: {=_xlfn.LET( _xlpm.data_range, ALL!A1:T1049, _xlpm.column_count, COLUMNS(_xlpm.data_range), _xlpm.first_values, _xlfn.MAKEARRAY(_xlpm.column_count, 1, _xlfn.LAMBDA(_xlpm.r,_xlpm.c, _xlfn.LET( _xlpm.column_data, INDEX(_xlpm.data_range, 0, _xlpm.r), _xlpm.first_non_empty_index, IFERROR(MATCH(TRUE, _xlpm.column_data<>"", 0), 0), IF(_xlpm.first_non_empty_index>0, INDEX(_xlpm.column_data, _xlpm.first_non_empty_index), "No data in " & ADDRESS(1,_xlpm.r,4)) ) )), _xlpm.first_values )} -> E1 | C45: {=_xlfn.LET( _xlpm.data_range, ALL!A44:T1049, _xlpm.column_count, COLUMNS(_xlpm.data_range), _xlpm.completion_percentages, _xlfn.MAKEARRAY(_xlpm.column_count, 1, _xlfn.LAMBDA(_xlpm.r,_xlpm.c, _xlfn.LET( _xlpm.column_data, INDEX(_xlpm.data_range, 0, _xlpm.r), _xlpm.total_cells, COUNTA(_xlpm.column_data), _xlpm.valid_cells, COUNTIFS( _xlpm.column_data, "<>", _xlpm.column_data, "<>NA", _xlpm.column_data, "<>TBD" ), _xlpm.valid_percent, IF(_xlpm.total_cells>0, ROUND(_xlpm.valid_cells/_xlpm.total_cells*100, 2), 0), TEXT(_xlpm.valid_percent, "0.00") & "%" ) )), _xlpm.completion_percentages )} -> 100.00% | D45: =VALUE(SUBSTITUTE(C45,"%",""))/100 -> 1
B46: A-Z | C46: 100.00% | D46: =VALUE(SUBSTITUTE(C46,"%",""))/100 -> 1
B47: NAME | C47: 100.00% | D47: =VALUE(SUBSTITUTE(C47,"%",""))/100 -> 1
B48: Property-Owner Name | C48: 100.00% | D48: =VALUE(SUBSTITUTE(C48,"%",""))/100 -> 1
B49: Sheet Map | C49: 100.00% | D49: =VALUE(SUBSTITUTE(C49,"%",""))/100 -> 1
B50: Bradley, Curtis L | C50: 60.44% | D50: =VALUE(SUBSTITUTE(C50,"%",""))/100 -> 0.6044
B51: KOSWATTA, ERIKA | C51: 63.86% | D51: =VALUE(SUBSTITUTE(C51,"%",""))/100 -> 0.6386
B52: Williams, Bridgett | C52: 59.26% | D52: =VALUE(SUBSTITUTE(C52,"%",""))/100 -> 0.5926
B53: Battle, Larry Jr | C53: 37.04% | D53: =VALUE(SUBSTITUTE(C53,"%",""))/100 -> 0.3704
B54: ANDERSON, PETE | C54: 88.24% | D54: =VALUE(SUBSTITUTE(C54,"%",""))/100 -> 0.8824
B55: WYNN, NICK | C55: 88.70% | D55: =VALUE(SUBSTITUTE(C55,"%",""))/100 -> 0.887
B56: FERGUSON, ROBERT & MRS | C56: 85.96% | D56: =VALUE(SUBSTITUTE(C56,"%",""))/100 -> 0.8596
B57: RUSH, TIFFANY LOAN # 0579206154 | C57: 88.24% | D57: =VALUE(SUBSTITUTE(C57,"%",""))/100 -> 0.8824
... B64: LAWRENCE, GENEATHA | C64: 71.75% | D64: =VALUE(SUBSTITUTE(C64,"%",""))/100 -> 0.7175
D65: =VALUE(SUBSTITUTE(C65,"%",""))/100 -> #VALUE!
D66: =VALUE(SUBSTITUTE(C66,"%",""))/100 -> #VALUE!
D67: =VALUE(SUBSTITUTE(C67,"%",""))/100 -> #VALUE!
D68: =VALUE(SUBSTITUTE(C68,"%",""))/100 -> #VALUE!
D69: =VALUE(SUBSTITUTE(C69,"%",""))/100 -> #VALUE!
D70: =VALUE(SUBSTITUTE(C70,"%",""))/100 -> #VALUE!
A75: 1 | B75: Please email and create simple chart
B77: Project name
B78: Simple summary of function
B79: Readiness %
B81: Screenshot before & after
A83: 2 | B83: #2 Pages detailed how2 usage
B85: Leases???
B88: App List | C88: PRIORITY
A89: =A111 -> 1 | B89: =B111 -> Template Creator: Up to version 25. Generates 8+ templates. | C89: 1
A90: =A156 -> 5.7 | B90: =B156 -> 0 | C90: 3
A91: =#REF! -> #REF! | B91: =#REF! -> #REF! | C91: 4
A92: =A164 -> 8.1 | B92: =B164 -> Each claim has a checklist associated with it by default. You can check off the tasks per claim and see each claims progress. | C92: 4
A93: 8.C | B93: =B165 -> 0 | C93: 4
A94: 8.D | B94: =B166 -> Currently can add more checklists upon REQUEST | C94: 4
A95: =A174 -> 0 | B95: =B174 -> 0 | C95: 5
A96: =A170 -> 8.B | B96: =B170 -> SOURCE OF LOSS PICTURE DOCUMENTATION | C96: 5
A97: =A153 -> 5.4 | B97: =B153 -> Tracks Task completion. JOB types, Age of Claims. | C97: 6
A98: =A151 -> 5.2 | B98: =B151 -> Data check: whenever uploading data from the 30 master we generate automatic reports telling you about the missing data points, percentage of completion of each claim. | C98: 7
A99: =A148 -> 0 | B99: =B148 -> 0 | C99: 10
A100: =A151 -> 5.2 | B100: =B151 -> Data check: whenever uploading data from the 30 master we generate automatic reports telling you about the missing data points, percentage of completion of each claim. | C100: 11
A101: =#REF! -> #REF! | B101: =#REF! -> #REF! | C101: 12
A102: =A188 -> 0 | B102: =B188 -> 0 | C102: 12
A103: =A192 -> 0 | B103: =B192 -> 0 | C103: 12
A104: 8.B | B104: =B176 -> Gets the dimensions and floorplan of a room seemlessly from encircle. | C104: 12
B109: Production List so far: | C109: Readiness %
A111: 1 | B111: Template Creator: Up to version 25. Generates 8+ templates. | C111: 1
A112: 1 | B112: POPULATE/UPDATE ENCIRCLE
A114: 4 | B114: Encircle List creator: ROOM LISTS | C114: 2
A115: 4.1 | B115: Created Lists in encircle for future claims. A master list of rooms with corresponding numbers. | C115: 2
A116: 4.2 | B116: Latest addition, code that will allow the Rooms and Images Numbering to line up. So that workers taking pictures make sure they are taking all the right ones | C116: 2
A117: 1 | B117: POPULATE/UPDATE ENCIRCLE
A118: 7 | B118: Labels Generator: | C118: 3
A119: 7.1 | B119: Generates claim room labels, Can generate any amount of claims for any room under that claim. | C119: 3
A120: 7.2 | C120: 3
A139: 2 | B139: Document Generator: generates 3 documents | C139: ???
A140: 2.1 | B140: More can be added as we per needs. All documents have their own category, such as mit, lease, etc.
A142: 3 | B142: Image downloader:
A143: 3.1 | B143: Application downloads all images for a claim into a zip file, all images are numbered sequentially.
A149: 5 | B149: Management Dashboard: | C149: 6
A150: 5.1 | B150: Claim upload: System takes 30 Master and imports the ALL tab data. | C150: 6
A151: 5.2 | B151: Data check: whenever uploading data from the 30 master we generate automatic reports telling you about the missing data points, percentage of completion of each claim. | C151: 6
A152: 5.3 | B152: Tracks all claims uploaded into system. | C152: 6
A153: 5.4 | B153: Tracks Task completion. JOB types, Age of Claims. | C153: 6
A154: 5.5 | B154: What is missing from most claims what's TBD, a full detailed break down. | C154: 6
A155: 5.6 | C155: 6
A156: 5.7 | C156: 6
A157: 6 | B157: Add new tracking upon request. | C157: 11
A158: 6.1 | C158: 11
A163: 8 | B163: JOB Checklist: SCOPE LIST….MITIGATION ….. CPS
A164: 8.1 | B164: Each claim has a checklist associated with it by default. You can check off the tasks per claim and see each claims progress.
A165: 8.2
A166: 8.3 | B166: Currently can add more checklists upon REQUEST
A167: 8.4 | B167: All MIT, CPS, ... checklists imported from the templates with checklists into the system.
A168: 8.5
A169: 8.A | B169: SCOPE CHECKLIST & PICTURE DOCUMENTATION … 360 CAMERA PICS
A170: 8.B | B170: SOURCE OF LOSS PICTURE DOCUMENTATION
A171: 8.C | B171: MITIGATION EQUIPTMENT & WIP ; SETUP & PICTURE DOCUMENTATION
A172: 8.D | B172: CPS …... PICTURE DOCUMENTATION
A173: 8.E
A175: 9 | B175: Room Dimensions App: | C175: 6
A176: 9.1 | B176: Gets the dimensions and floorplan of a room seemlessly from encircle. | C176: 6
A177: 9.2 | B177: Room Dimensions in Feet for each room. | C177: 6
A178: 9.3 | B178: To be populated in our files where needed for accurate calculations. | C178: 6
...

Sheet LISTS
B1: Reorder Rooms | D1: LIST 1 PRIMARY | K1: INITIAL ROOMS LIST 1-18=JOB/SOURCE/FOYER/CPS/MIT/RFG | T1: ROOMS ONLY SHORT 3BR LIST
B2: Rooms | D2: 1. Jobsite Verification (Address Photos), | K2: 1. Jobsite Verification (Address Photos), | T2: FOYER, Guest Closet, Living Room, Dining Room, Kitchen, Nook, Pantry, Hallway, Linen Closet, Bedroom 1, Bedroom Closet 1, Bedroom 2, Bedroom Closet 2, Primary Bedroom, Primary Bedroom Closet 2, Primary Bathroom, Rec Room/ office, Garage, Guest Bathroom
B3: Wip/work In Progress | D3: 2. Source of Loss Pics (ROOMS / STRUCTURAL) | K3: 2. Source of Loss Pics (ROOMS / STRUCTURAL) ,
B4: Mitigation Work In Progress WIP | D4: 3. FOYER/ENTRY ROOM | K4: 3.FOYER/ENTRY ROOM,
B5: 8. MITIGATION EQUIPMENT OVERVIEW WIP | D5: 4. CPS1 DAY1 CONTENTS OVERVIEW/DOCUMENT PICS | K5: 4. CPS1 DAY 1 CONTENTS ROOM OVERVIEW ===============
B6: RHT Day 1 MONDAY 03/10/25 | D6: 5. CPS2 DAY2 CONTENTS OVERVIEW WIP BOXES PACKOUT PICS, | K6: 5. CPS2 DAY2 CONTENTS OVERVIEW WIP BOXES PACKOUT PICS,
B7: RHT DAY 2 03/11/25 TUESDAY | D7: 6. CPS3 DAY3 CONTENTS OVERVIEW STORAGE MOVE OUT PICS, | K7: 6. CPS3 DAY3 CONTENTS OVERVIEW STORAGE MOVE OUT PICS,
B8: RHT DAY 3 WEDNESDAY 03/12/25 RHT | D8: 7. CPS4 CONTENTS OVERVIEW PACK-BACK / RESET PICS | K8: 7. CPS4 CONTENTS OVERVIEW PACK-BACK / RESET PICS,============
B9: RHT DAY 4 THRUSDAY 03/13/25 | D9: 8. MITIGATION EQUIPMENT OVERVIEW INTERIOR & WIP, | K9: 8. MITIGATION EQUIPMENT OVERVIEW INTERIOR & WIP
B10: RHT DAY 5 FRIDAY 03/14/25 READINGS = RH, TEMP F & DEH & EXTERIOR | D10: 9. MITIGATION Readings Moisture = MC | K10: 9. MITIGATION Readings Moisture = MC, =========================
B11: RHT Reading Day 6 Friday | D11: 10. MITIGATION READINGS = RH, TEMP F & DEH & EXTERIOR | K11: 10. MITIGATION READINGS = RH, TEMP F & DEH & EXTERIOR,
B12: Moisture Reading 03/07/25 FRIDAY STABILIZATION | D12: 11. REPLACEMENT 1 CON OVERVIEW DAY PICS | K12: 11. REPLACEMENT 1 CON OVERVIEW DAY PICS, ===================
B13: 3/10 Moisture READING | D13: 12. REPLACEMENT 2 CON WIP | K13: 12. REPLACEMENT 2 CON WIP,
B14: 3/11/ Moisture Reading | D14: 13. REPLACEMENT 3 CON STORAGE | K14: 13. REPLACEMENT 3 CON STORAGE,
... B19: 1. Jobsite Verification | D19: 18. ROOF EXTERIOR PAID WHEN INSTALLED (PWI ITEMS). | K19: 18. ROOF EXTERIOR PAID WHEN INSTALLED (PWI ITEMS),
B20: 2. Source of Loss Pics (ROOMS / STRUCTURAL) | K20: 19. ROOM LABELS ==========================================
A21: 1 | B21: Garage TRAVEL AREA | K21: DOCUMENT PICS,
A22: =1+A21 -> 2 | B22: REC ROOM 1 | D22: All Rooms Fire Smoke /MIT 5 DAY
A23: =1+A22 -> 3 | B23: STORAGE UNDER STAIRS | D23: Foyer, Guest Closet, Living Room, Dining Room, Hallway, Kitchen, Pantry, Nook, Hallway, Guest Bath, Stairs -Up, Hallway Up, Linen Closet, Bathroom, Primary Bedroom, Primary Bedroom Closet, Primary Bedroom Bath, Bedroom 1, Bedroom 1 Closet, Bedroom 1 Bath, Bedroom 2, Bedroom 2 Closet, Bedroom 2 Bath, Bedroom 3, Bedroom 3 Closet, Bedroom 3 Bath, Attic, Storage 1, Storage 2, Basement, Under Stairs Storage, Rec Room 1, Rec Room 2, Laundry Room, Utility Room, CPS 2 With Room Labels, Mitigation Equipment, Jobsite Verification, Source Of Loss, STABILIZATION, MC DAY1, MC DAY2, MC DAY 3, MC DAY 4, MC DAY 5, RHT DAY 1, RHT DAY 2, RHT DAY 3, RHT DAY 4, RHT DAY 5, CPS DAY 3 STORAGE & MOVE OUT, PPR REPLACEMENT ITEMS
A24: =1+A23 -> 4 | B24: HALL DN
A25: =1+A24 -> 5 | B25: Bathroom Dn
A26: =1+A25 -> 6 | B26: BEDROOM DN | L26: INITIAL ROOMS LIST 1-18=JOB/SOURCE/FOYER/CPS/MIT/RFG
A27: =1+A26 -> 7 | B27: Bedroom Down Closet
A28: =1+A27 -> 8 | B28: LAUNDRY/UTILITY ROOM
A29: =1+A28 -> 9 | B29: STAIRS DN
A30: =1+A29 -> 10 | B30: 3.FOYER/ENTRY ROOM
A31: =1+A30 -> 11 | B31: STAIRS UP
A32: =1+A31 -> 12 | B32: Kitchen
A33: =1+A32 -> 13 | B33: Living Room
A34: =1+A33 -> 14 | B34: Dining Room
A35: =1+A34 -> 15 | B35: Hallway UP
A36: =1+A35 -> 16 | B36: Guest Closet
A37: =1+A36 -> 17 | B37: Linen Closet
A38: =1+A37 -> 18 | B38: BATH UP
... A56: =1+A55 -> 36 | B56: B/U moisture readings SAVE
B65: Reorder Rooms
A66: 1 | B66: Foyer
A67: =1+A66 -> 2 | B67: Guest Closet
A68: =1+A67 -> 3 | B68: Living Room
A69: =1+A68 -> 4 | B69: Dining Room
A70: =1+A69 -> 5 | B70: Hallway
A71: =1+A70 -> 6 | B71: Kitchen
A72: =1+A71 -> 7 | B72: Pantry
A73: =1+A72 -> 8 | B73: Nook
A74: =1+A73 -> 9 | B74: Hallway RR
A75: =1+A74 -> 10 | B75: Guest Bath
A76: =1+A75 -> 11 | B76: Stairs -Up
A77: =1+A76 -> 12 | B77: Hallway Up
A78: =1+A77 -> 13 | B78: Linen Closet
... A99: =1+A98 -> 34 | B99: Utility Room
B101: FLOOR2
B102: Foyer
B104: Guest Closet
B105: Living Room
B106: Dining Room
B107: Hallway UP
B108: Kitchen
B109: Pantry
B110: Nook
B111: Hallway
B112: Guest Bath
B113: Stairs -Up
... B136: Rec Room 2
B137: 3
A141: ` | C141: 3 LEVELS NO ROOF
C142: Jobsite Verification
A143: All Room list Fire Smoke All | C143: Source Of Loss ============
C144: Foyer DN | D144: Jobsite Verification & Source of Loss | G144: Interior list & ROOF / 5DAY MIT | I144: 1. (PWI ITEMS) | J144: RFG RANCH/1 STORY
A145: Interior list & ROOF | C145: Living Room DN | D145: 1. Jobsite Verification (Address Photos) | G145: 1. Jobsite Verification (Address Photos), | J145: FOYER,
C146: Guest Closet DN | D146: 2. Pics (ROOMS / STRUCTURAL) ----- --------------------------------------- ROOMS ------------------------------------------------------------------------------ | G146: 2. Source of Loss Pics (ROOMS / STRUCTURAL) , | I146: ROOMS ONLY SHORT 3BR LIST | J146: Guest Closet,
C147: FIREPLACE DN | D147: 3. FOYER/ENTRY ROOM | G147: 3.FOYER/ENTRY ROOM, | I147: FOYER, | J147: Living Room,
C148: Dining Room DN | D148: 4. ROOMS TRAVEL AREAS | G148: 5. CPS2 DAY2 CONTENTS OVERVIEW WIP BOXES PACKOUT PICS, | I148: Guest Closet, | J148: Dining Room,
C149: Hallway DN @ BR&BATH | D149: 5. AFFECTED ROOM ______________ | G149: 6. CPS3 DAY3 CONTENTS OVERVIEW STORAGE MOVE OUT PICS , | I149: Living Room, | J149: Kitchen,
A150: 1. 1.Jobsite Verification (Address Photos) | C150: Bedroom 1 DN | D150: 6. AFFECTED ROOM ______________ | G150: 7. CPS4 CONTENTS OVERVIEW PACK-BACK / RESET PICS, | I150: Dining Room, | J150: Nook,
A151: 2. 2.Source of Loss Pics (ROOMS / STRUCTURAL) , | C151: Primary BR DN | D151: 7. AFFECTED ROOM ______________ | G151: 8. MITIGATION EQUIPMENT OVERVIEW INTERIOR & WIP , | I151: Kitchen, | J151: Pantry,
A152: 3. 3.FOYER/ENTRY ROOM, | C152: Primary BR Closet DN | D152: 8. AFFECTED ROOM ______________ | G152: 9. MITIGATION Readings Moisture = MC, | I152: Nook, | J152: Hallway,
A153: 4. ROOM2 | C153: Bedroom 2 DN | D153: 9. AFFECTED ROOM ______________ | G153: 10. MITIGATION READINGS = RH, TEMP F & DEH & EXTERIOR, | I153: Pantry, | J153: Linen Closet,
A154: 5. ROOM3 | C154: BR 2 Closet DN | D154: 10. AFFECTED ROOM ______________ | G154: 11. REPLACEMENT 1 CON OVERVIEW DAY PICS, | I154: Hallway, | J154: Bedroom 1,
A155: 6. ROOM4 | C155: Bathroom DN | G155: 12. REPLACEMENT 2 CON WIP, | I155: Linen Closet, | J155: Bedroom Closet 1,
A156: 7. ROOM5 | C156: Linen Closet DN | D156: CPS ---------------- | G156: 13. REPLACEMENT 3 CON STORAGE , | I156: Bedroom 1, | J156: Bedroom 2,
A157: 8. 4. CPS1 DAY 1 CONTENTS ROOM OVERVIEW / DOCUMENT PICS | C157: Kitchen DN | D157: 11. CPS1 DAY1 CONTENTS OVERVIEW/DOCUMENT PICS | G157: 14. REPLACEMENT 4 CON DISPOSAL, | I157: Bedroom Closet 1, | J157: Bedroom Closet 2,
A158: 9. 5. CPS2 DAY2 CONTENTS OVERVIEW WIP BOXES PACKOUT PICS, | C158: Pantry Down DN | D158: 12. CPS2 DAY2 CONTENTS OVERVIEW WIP BOXES PACKOUT PICS | G158: 15. REBUILD OVERVIEW WORK IN PROGRESS.......WIP, | I158: Bedroom 2, | J158: Primary Bedroom,
A159: 10. 6. CPS3 DAY3 CONTENTS OVERVIEW STORAGE MOVE OUT PICS, | C159: Hallway/ Closet Dn | D159: 13. CPS3 DAY3 CONTENTS OVERVIEW STORAGE MOVE OUT PICS | G159: 16. REBUILD INTERIOR COMPLETED WORK, | I159: Bedroom Closet 2, | J159: Primary Bedroom Closet 2,
A160: 11. 7. CPS4 CONTENTS OVERVIEW PACK-BACK / RESET PICS, | C160: SIDE DN FOYER HALL STAIRS | D160: 14. CPS4 CONTENTS OVERVIEW PACK-BACK / RESET PICS ---------------------------------------------- | G160: 17. Roof Scope = DAMAGES & LINE ITEMS, | I160: Primary Bedroom, | J160: Primary Bathroom,
A161: 12. 8. MITIGATION EQUIPMENT OVERVIEW INTERIOR & WIP, | C161: Frt Stairwell / Hallway Up ====== | D161: MITIGATION --------------------------------------------------------- | G161: 18. ROOF EXTERIOR PAID WHEN INSTALLED (PWI ITEMS), | I161: Primary Bedroom Closet 2, | J161: Rec Room/ office,
A162: 13. 9. MITIGATION Readings Moisture = MC, | C162: Living Room 2nd | D162: 15. MITIGATION EQUIPMENT OVERVIEW INTERIOR & WIP | G162: 4. CPS1 DAY 1 CONTENTS ROOM OVERVIEW / DOCUMENT PICS, | I162: Primary Bathroom, | J162: Garage,
A163: 14. 10. MITIGATION READINGS = RH, TEMP F & DEH & EXTERIOR, | C163: Guest Closet 2nd | D163: 16. MITIGATION Readings Moisture = MC | G163: RHT DAY 1, | I163: Rec Room/ office, | J163: Guest Bathroom
A164: 15. 11. REPLACEMENT 1 CON OVERVIEW DAY PICS, | C164: Fireplace 2nd up | D164: 17. MITIGATION READINGS = RH, TEMP F & DEH & EXTERIOR ----------------------------------------- REPLACEMENT ------------------ | G164: RHT DAY 2, | I164: Garage,
A165: 16. 12. REPLACEMENT 2 CON WIP, | C165: Dining Room 2nd | D165: 18. REPLACEMENT 1 CON OVERVIEW DAY PICS | G165: RHT DAY 3, | I165: Guest Bathroom
A166: 17. 13. REPLACEMENT 3 CON STORAGE | C166: Hallway Bathroom 2nd | D166: 19. REPLACEMENT 2 CON WIP | G166: RHT DAY 4,
A167: 18. 14. REPLACEMENT 4 CON DISPOSAL, | C167: Bedroom 1 2nd | D167: 20. REPLACEMENT 3 CON STORAGE | G167: RHT DAY 5,
A168: 19. 15. REBUILD OVERVIEW WORK IN PROGRESS.......WIP, | C168: Primary Bedroom 2nd | D168: 21. REPLACEMENT 4 CON DISPOSAL---- ---------------------------------------------------------------------REBUILD -------------------- | G168: MC DAY1 ,
A169: 20. 16. REBUILD INTERIOR COMPLETED WORK, | C169: Primary Bedroom Closet 2nd | D169: 22. REBUILD OVERVIEW WORK IN PROGRESS.......WIP | G169: MC DAY 2,
A170: 21. 17. Roof Scope = DAMAGES & LINE ITEMS, | C170: Bedroom 2 2nd | D170: 23. REBUILD INTERIOR COMPLETED WORK -- --------------------------------------------------------------------------------------------------------------------------------------------------------- ROOF & EXTERIOR ---------- | G170: MC DAY3,
A171: 22. 18. ROOF EXTERIOR PAID WHEN INSTALLED (PWI ITEMS), | C171: BR 2 Closet 2nd | D171: 24. Roof Scope = DAMAGES & LINE ITEMS | G171: MC DAY 4,
A172: 23. EMPLOYEES SIGNATURE CHECK LIST ROOM, | C172: Linen Closet 2ND | D172: ROOF EXTERIOR PAID WHEN INSTALLED | G172: MC DAY 5,
A173: 24. RHT DAY 1, | C173: Bathroom UP 2nd | G173: STABILIZATION READINGS,
A174: 25. RHT DAY 2, | C174: Kitchen 2nd | G174: MIT LABELS,
A175: 26. RHT DAY 3, | C175: Rear/entry Foyer 2nd | G175: ROOM LABELS
A176: 27. RHT DAY 4, | C176: Stairs -Up =REAR ========
...

Sheet jobinfo(2)
A1: Smith, Brian | B1: Property-Owner Name | C1: LACEY, EUNICE | G1: Enter info here | K1: ADD SOS LINK
A2: 831 Gertrude Place NW, | B2: Property address: street | C2: 13601 5th Ave | G2: New Customer Info required | K2: LINK TO VIDEOS
A3: Atlanta, GA 30318 | B3: Property city, state, zip | C3: East Cleveland, OH 44112 | K3: BEFORE AND AFTER P[CS
A4: BRIAN.ASHTON.SMITH.211@GMAIL.COM | B4: Customer Email | C4: Emdlacey@gmail.com | K4: CLE ATL NY NC NY
A5: (404) 444-1325 | B5: Cst-owner Phone# | C5: (216) 450-4913
A6: MRS. | B6: Co-Owner.cst#2 | C6: TBD
B7: cst ph # 2 | C7: TBD | K7: RFG WIP…CURRENT JOBS
B8: Cst address # 2 | C8: TBD | K8: SIGNAGE
B9: city, state-cst#2 | C9: TBD
A10: renaissancemanbs@aol.com | B10: email-cst #2 | C10: TBD
A11: KITCHEN WATER PIPE BROKE | B11: Cause of Loss | C11: BATHTUB OVERFLOW | D11: FIRE | G11: Wind = Roof | H11: Water Damage=WTR | I11: Fire Smoke | J11: Wind=Tree | K11: Hurricane =HURR
A12: Tuesday, March 11, 2025 | B12: date of loss | C12: 45765 | G12: rebuild type
A13: interior repairs | B13: rebuild type 1 | C13: interior repairs LVL2 | G13: roofing shingles replacement | I13: fencing
A14: interior repairs | B14: rebuild type 2 | C14: interior repairs LVL1 | G14: interior repairs | I14: shed
A15: TBD | B15: rebuild type 3 | C15: BASEMENT | G15: exterior repairs | I15: porch patio
A16: Y | B16: DEMO | C16: Y | G16: Y
A17: Y | B17: Mitigation | C17: Y | G17: Y
A18: NA | B18: Other Structures | C18: NA | G18: Y
A19: Y | B19: Replacement | C19: Y | G19: Y
A20: Y | B20: CPS / CLN / CON/ CGN | C20: Y | G20: Y
A21: POST 1978 | B21: Year Built | C21: PRE 1978 | G21: TBD
A22: 45727 | B22: Contract Date | C22: 45822 | G22: TBD | H22: pre 1980 | I22: post 1980
A23: Y | B23: Loss of use/ ALE | C23: Y | G23: sample cost 3
A24: TBD | B24: Breathing issue | C24: TBD | G24: doctor letter
A25: TBD | B25: HMR | C25: TBD | G25: lab test
A26: Esurance | B26: Insurance Co. Name | C26: AAA Insurance | G26: Insurance Company Supplied Info | H26: Per declaration pages | J26: 34-H-6822C9-2
A27: #250254318 | B27: Claim # | C27: #017095711 | H27: Assigned by Insurer
A28: : 10610052 | B28: policy # | C28: OHH000190052 | H28: Per declaration pages | I28: OFP DWF 7266580
A29: carla.robledo@ngic.com | B29: Email INS. co. | C29: STAPLES.OLIVIA @ace.aaa.com | H29: Per declaration pages
A30: Carla Robledo| | B30: DESK Adjuster DA | C30: STAPLES, OLIVIA 207 776 6150 | H30: Assigned by Insurer
A31: (800) 378-7262 | B31: DA Phone | C31: 207 776 6150 | H31: customer service rep
A32: (336) 331-6825 | B32: DA Ph. Ext. # | C32: 207 776 6150 | H32: Hazel
A33: carla.robledo@ngic.com | B33: DA Email | C33: STAPLES.OLIVIA @ace.aaa.com | H33: 43789
B34: Field Adjuster Name | C34: VINCENT, KATHERINE | H34: 5pm
B35: Phone # field adj | C35: 3306184299
B36: Field adj email | C36: KATHERINE@KGVINCENT.COM
B37: adj contents | C37: SPV Tanya Sayer 207-791-8544 | H37: Assigned by Insurer
B38: adj CPS phone # | C38: TBD
B39: adj CPS email | C39: TBD
B40: TMP adj | C40: TBD | H40: Assigned by Insurer
B41: TMP adj phone # | C41: TBD
B42: adj TMP email | C42: TBD
B43: ATT: Loss Draft Dept. | C43: TBD | H43: =+H26 -> Per declaration pages
B44: address ins overnight mail | C44: TBD
B45: city, state-zip ins | C45: TBD
B46: Insurance Co. Phone | C46: TBD
B47: Website Ins Co. | C47: TBD
B48: Mailing address INS | C48: TBD
B49: Mail city, state, zip INS | C49: TBD | H49: Leave Label/ID tag in place for each room/area until final completion !!!
B50: FAX Ins. Co | C50: TBD
B51: NEW CUSTOMER # | C51: OH25 LACEY, E
B52: ROOM ID | C52: =C1 -> LACEY, EUNICE | D52: Scope | E52: Pics | F52: Sketch | G52: Floor 1 | H52: Floor 2 | I52: BASEMENT | J52: Affected Areas, Include Line of Sight room /areas
B53: Room/Area 1 | C53: LIVING ROOM | G53: Foyer | H53: Stairs UP | I53: Basement | J53: ROOM Name & Number | K53: LOCATION & Basic damage / work Description
B54: Room/Area 2 | C54: DINING ROOM | G54: Guest Closet | H54: Bathroom | I54: Stairs 1 | J54: example # 0 = Master bedroom | K54: Ceilings N corner | L54: repair water damage drywall paint
B55: Room/Area 3 | C55: KITCHEN | G55: Front Hall | H55: Hallway- up | I55: Storage | L55: Scope | M55: Pics | O55: Sketch
B56: Room/Area 4 | C56: NOOK | G56: Living Room | H56: Linen CLST | I56: Hallway- DN | J56: {#=_1_} | K56: {____} | M56: {_______} {_ _____}
B57: Room/Area 5 | C57: STAIRS UP | G57: Dining Room | H57: Bedroom # 1 | I57: Laundry | J57: Room/Area 1
B58: Room/Area 6 | C58: Hallway UP @ BR & BATH | G58: Hallway- DN | H58: Closet BR # 1 | I58: Utility
B59: Room/Area 7 | C59: BATHROOM | G59: DEN | H59: Bedroom # 2 | I59: Man cave
B60: Room/Area 8 | C60: Basement Stairs | G60: FAMILY ROOM | H60: Closet BR # 2 | I60: Crawlspace
B61: Room/Area 9 | C61: Basement Rec Room | G61: Kitchen | H61: Bedroom # 3 | I61: EXTERIOR
B62: Room/Area 10 | C62: Utility / LAUNDRY | G62: Pantry | H62: Closet BR # 3 | I62: Roof shingle replace | J62: 10
B63: Room/Area 11 | C63: TBD | G63: Nook | H63: Master Bedroom | I63: Vinyl siding
B64: Room/Area 12 | C64: TBD | G64: Guest Bath | H64: Master BR Closet | I64: fencing
B65: Room/Area 13 | C65: TBD | G65: Office | H65: Master Bathroom | I65: shed
B66: Room/Area 14 | C66: TBD | I66: exterior repairs
B67: Room/Area 15 | C67: TBD | G67: ATTIC | I67: Porches
B68: Room/Area 16 | C68: TBD | G68: Storage | I68: Garage
B69: Room/Area 17 | C69: TBD | G69: Stairs 2 | I69: Deck/patio
B70: Room/Area 18 | C70: TBD | I70: yard area
B71: Room/Area 19 | C71: TBD | I71: Windows
B72: Room/Area 20 | C72: TBD
B73: Room/Area 21 | C73: TBD
B74: Room/Area 22 | C74: TBD
B75: Room/Area 23 | C75: TBD
B76: Room/Area 24 | C76: TBD
B77: Room/Area 25 | C77: TBD
B78: Mortgage co | C78: TBD | G78: Customer Supplied Info | H78: Per mortgage statement
B79: Account# Mtge Co. | C79: TBD
B80: Loan status | C80: TBD | H80: Loan status = current, foreclosure, Paid in full, Late days
B81: contact person mtge | C81: TBD
B82: Phone # MTGE contact | C82: TBD
B83: Ph. Ext. Mtge contact | C83: TBD
C84: TBD
B85: Attn.: Loss Draft Dept | C85: TBD
B86: Mtge OVN mail | C86: TBD
B87: city, St., zip ,mtge OVN | C87: TBD
B88: Phone # MTGE co. | C88: TBD
B89: email mtge | C89: TBD
B90: mtge website | C90: TBD
B91: MTGE co. Fax # | C91: TBD
B92: Mailing address mtge | C92: TBD
B93: Mail city, state, zip mtge | C93: TBD
C94: TBD
B95: Initial Offer / phase 1 contract amount | C95: TBD
B96: Draw Request | C96: TBD
B97: Cust id | C97: TBD
C98: TBD | L98: WSB JOE
B99: REP COMPANY | C99: TBD | D99: QUINTON DURHAM 216 214 6747 | F99: TONY | L99: Joe Jones 216.450.7228 | O99: CLAUDECarson@yahoo.com | P99: MO (216) 214-5700 | T99: CARR, JasmiNe 216 633-7048 | W99: JAMAL (216) 835-8544 | Y99: AL HOUSTON
A100: All Phase Consulting, LLC | B100: co name | C100: All Phase Consulting, LLC | D100: All Phase Consulting, LLC | E100: Ian His Hands LLC | F100: Wayside Builders, LLC | H100: All Phase Consulting, LLC | L100: Wayside Builders, LLC | O100: Alpha Omega Construction | P100: YASMEEN PROPERTIES.INC | T100: SUPREME ONE ENTERPRISE, LLC | W100: PROVISO INVESTMENTS | Y100: Bal Construction and Restoration LLC | Z100: J THOMAS CONTRACTING, LLC
...

Sheet REBLD
A1: =E2 -> Rebuild BID; additional photos & documentation ATTACHED & to follow. | E1: Rebuild estimate (additional photos & documentation to follow under separate email).
E2: Rebuild BID; additional photos & documentation ATTACHED & to follow.
A3: Per your request;
A4: =+'jobinfo(2)'!$C$100 -> All Phase Consulting, LLC | G4: Additional photos & documentation as per attached
A5: =+'jobinfo(2)'!$C$101 -> WWW.MYAPCLLC.COM | C5: =+'jobinfo(2)'!$C$102 -> Insured & GA Registered #09073201 | E5: PHOTO REPORT INCLUDED
A6: =+'jobinfo(2)'!$C$105 -> ECI 531 FIFTH AVE, | B6: =+'jobinfo(2)'!$C$103 -> 375 Rockbridge Road, Suite 172-343 | D6: =+'jobinfo(2)'!$C$107 -> 20810 AURORA RD | E6: Rebuild estimate (additional photos & documentation to follow under separate email).
A7: =+'jobinfo(2)'!$C$106 -> PELHAM, NY 10803 | B7: =+'jobinfo(2)'!$C$104 -> Lilburn, GA, 30047 | D7: =+'jobinfo(2)'!$C$108 -> BEDFORD,OH 44146 | E7: Enclosed; Assignment of Insurance Benefits & Direct Payment Authorization
A8: =+'jobinfo(2)'!$C$109 -> Providing Cost Estimating & Project Management Services
A9: =+'jobinfo(2)'!$C$110 -> Five Generations of Great Work | C9: =+'jobinfo(2)'!$C$111 -> Five Generations of Pride & Skills | E9: REVISED Rebuild BID, per your request & agreement please attached Revision
A10: =+'jobinfo(2)'!C$112 -> Joe Jones, PM 216.450.7228 | C10: =+'jobinfo(2)'!$C$113 -> wsbjoe9@gmail.com
A11: COMPANY REP. #2 | B11: =+'jobinfo(2)'!$C$114 -> 404-446-9060 | C11: =+'jobinfo(2)'!$C$115 -> info@myapcllc.com | E11: FINAL INVOICES STATEMENT (additional photos & documentation to follow under separate email)
A12: EIN # | B12: =+'jobinfo(2)'!$C$116 -> TIN 83-226 0563 | C12: FEDEX# | D12: =+'jobinfo(2)'!$C$117 -> FEDEX # 9836-2151-1 | E12: SKETCH
E13: Request for Depreciation Hold and/or Undisputed Claim Portion Release
A14: =A1 -> Rebuild BID; additional photos & documentation ATTACHED & to follow. | D14: =+'jobinfo(2)'!$C$27 -> #017095711
A15: =+'jobinfo(2)'!$C$1 -> LACEY, EUNICE | B15: =+'jobinfo(2)'!$C$5 -> (216) 450-4913
A16: =+'jobinfo(2)'!$C$2 -> 13601 5th Ave | C16: =+'jobinfo(2)'!$C$4 -> Emdlacey@gmail.com
A17: =+'jobinfo(2)'!$C$3 -> East Cleveland, OH 44112 | E17: EMS ROOFING TEMP REPAIRS RFG Invoicing
A18: Per your request; enclosed are Estimates / Proof of Loss Supporting Documentation per subject property / current risk. | E18: Per your request; Rebuild Estimate additional photos & documentation attached.
A19: Insurance Co. Name | B19: =+'jobinfo(2)'!$C$26 -> AAA Insurance | C19: =+'jobinfo(2)'!$B$28 -> policy # | D19: =+'jobinfo(2)'!$C$28 -> OHH000190052 | E19: Letter of Satisfaction/COMPLETION
A20: Email INS. co. | B20: =+'jobinfo(2)'!$C$29 -> STAPLES.OLIVIA @ace.aaa.com | C20: =+'jobinfo(2)'!B46 -> Insurance Co. Phone | D20: =+'jobinfo(2)'!C46 -> TBD | E20: Supplemental Invoices
A21: DESK Adjuster DA | B21: =+'jobinfo(2)'!$C$30 -> STAPLES, OLIVIA 207 776 6150 | C21: =+'jobinfo(2)'!B32 -> DA Ph. Ext. # | D21: =+'jobinfo(2)'!C32 -> 207 776 6150 | E21: Supplemental Exterior Emergency Services Invoice
A22: DA Phone | B22: =+'jobinfo(2)'!$C$31 -> 207 776 6150 | C22: =+'jobinfo(2)'!$C$33 -> STAPLES.OLIVIA @ace.aaa.com | D22: =+'jobinfo(2)'!B33 -> DA Email | E22: Supplemental INTERIOR Rebuild Invoicing
A23: Field Adjuster Name | B23: =+'jobinfo(2)'!$C$34 -> VINCENT, KATHERINE | C23: =+'jobinfo(2)'!$C$36 -> KATHERINE@KGVINCENT.COM | E23: Supplemental EMS TREE REMOVAL Invoicing
A24: Phone # field adj | B24: =+'jobinfo(2)'!$C$35 -> 3306184299 | E24: Supplemental EMS INTERIOR MITIGATION Invoicing
A25: TMP adj | B25: =+'jobinfo(2)'!$C$40 -> TBD | C25: =+'jobinfo(2)'!C37 -> SPV Tanya Sayer 207-791-8544 | D25: adj contents | E25: Supplemental Rebuild Invoicing TO FOLLOW
A26: TMP adj phone # | B26: =+'jobinfo(2)'!$C$41 -> TBD | C26: =+'jobinfo(2)'!C38 -> TBD | D26: adj CPS phone # | E26: As per attached job specifications and estimates, roof mitigation and exterior supplemental repairs only
A27: adj TMP email | B27: =+'jobinfo(2)'!$C$42 -> TBD | C27: =+'jobinfo(2)'!C39 -> TBD | D27: adj CPS email | E27: EMS TREE REMOVAL Invoicing
A29: USE OF OUR SERVICES IS OPTIONAL ! Subject Customer has chosen to utilize our services and has accordingly executed the attached documents; including yet not limited to the following: | E29: Supplemental Invoices Attached; (photos to follow under separate email)
A30: CONTRACT PACKAGE: | B30: EMERGENCY SERVICES WORK AUTHORIZATION | E30: Supplemental Invoices to follow under separate email. __________
B31: Contract | C31: General AUTHORIZATION_ | E31: exterior payment (less o&P)
B32: Advance Payment Request | E32: Acceptance of $10,000 for interior and
A33: Assignment of Insurance Benefits and Direct Payment Authorization: & Copy of W9 | D33: =+$B$12 -> TIN 83-226 0563 | E33: exterior payment (less o&P)
E34: REPORTS
E35: Per your request; VANDALISM POLICE REPORT & LEASE INFO
A36: Estimates /"Proof of Loss" Supporting Documentation | D36: Pictures | E36: Per your request; PLUMBER REPORT & PICTURES
A37: EMS EXT | D37: ` | E37: Per your request; FIRE REPORT & PICTURES
A38: Mitigation$____________________ | C38: [ ] | D38: [ ] | E38: Per your request; UTILITIES BILLS & PICTURES
A39: Demo $____________________ | C39: [ ] | D39: [ ] | E39: Advance Payment Request & Copy of = W9
A40: Rebuild $____________________ | C40: [ x ] | D40: [ x ] | E40: BID ITEM / INVOICE PER SUBCONTRACTOR
A41: Contents $____________________ | B41: TBD' | C41: [ ] | D41: [ ] | E41: CONDITIONAL WAIVER OF LIEN PER SUBCONTRACTOR
A42: Eagleview Full report | C42: NA | E42: Supplemental EXTERIOR Rebuild Invoicing
A43: Enclosed is an Assignment of Insurance Benefits and Direct Payment Authorization.
A44: Thus all monies due to named herein contractor are to be released without delay; solely and directly to the contractor. | E44: AWAITING WRITTEN CLEARANCE TO START DEMO & MITIGATION
A45: *Per our signed Assignment of Insurance Benefits / Pay Directive, any payments remitted to any party other than ….................................. | E45: SPOKE TO C&O VENDOR , HE STATED ALL CLEAR ON HIS INSPECTION
B46: ='jobinfo(2)'!$C$100 -> All Phase Consulting, LLC
A47: will require a stop payment and a new payment issued directly to | E47: BID ITEM / INVOICE PER SUBCONTRACTOR
B48: ='jobinfo(2)'!$C$100 -> All Phase Consulting, LLC | E48: INITIAL DEMOLITION INVOICE
A49: I/We select the option of overnight shipping for expedited delivery of claim funds. | E49: CODE UPGRADES
A50: Accordingly, please do not issue payment under the Assigned Rights directly to the Policyholder. Doing so will not result in a credit toward the balance owed to us. Directly paying the Policyholder for the assigned portion of the claim will not discharge your obligations under the policy and may require double-payment! | E50: REQUEST TO PROPERLY UPDATE AND ADJUST CLAIM PAYMENTS TO INCLUDE THE REQUIRED OVERHEAD AND PROFIT
E52: Per your request attached are the Invoices in PDF & ESX formats
A54: PREPAID (FEDEX / UPS) | B54: =+D12 -> FEDEX # 9836-2151-1 | E54: Advance Payment Request & Copy of = W9
A55: I/We select the option of overnight shipping for expedited delivery of claim funds. | E55: When a debt has a settled and unsettled amount, the insured can request the debtor the payment from the insurer of the settled amount without having to wait for the unsettled amount to be determined.
A56: Payments: Issuance, payment and acceptance of payment are without prejudice to any rights of the Owner or the Contractor under the terms of this agreement. | E56: Georgia
A57: Owner and or the Contractor also specifically reserves the right to submit for review and payment any additional/supplemental invoices as may be deemed necessary to restore the property to the pre-loss condition or better. | E57: In Georgia, insurance companies have 15 days to acknowledge receipt of a claim, as well as provide proof claim forms. Once all forms are received, the insurance adjuster has 15 days to deny or accept the claim. Once a settlement has been reached, and or there is an undisputed amount determined, they have 10 days to pay.
A58: It is stated that this submittal does not represent a final invoice of any type. | E58: O.C.G.A. § 33‐6‐33 (Copy w/ Cite) O.C.G.A. § 33‐6‐33 GEORGIA CODE Copyright 2010 by The State of Georgia
E59: O.C.G.A. § 33‐6‐33 (Copy w/ Cite) O.C.G.A. § 33‐6‐33 GEORGIA CODE Copyright 2010 by The State of Georgia
A60: =+'jobinfo(2)'!$B$4 -> Customer Email | B60: =+'jobinfo(2)'!$B$33 -> DA Email | C60: =+'jobinfo(2)'!$B$36 -> Field adj email | D60: =+'jobinfo(2)'!$B$42 -> adj TMP email
A61: =+'jobinfo(2)'!$C$4 -> Emdlacey@gmail.com | B61: =+'jobinfo(2)'!$C$33 -> STAPLES.OLIVIA @ace.aaa.com | C61: =+'jobinfo(2)'!$C$36 -> KATHERINE@KGVINCENT.COM | D61: =+'jobinfo(2)'!$C$42 -> TBD | E61: The purpose of OCGA § 33-4-6 (a)'s demand requirement was met here — "to adequately notify an insurer that it is facing a bad faith claim so that it may make a decision about whether to pay, deny or further investigate the claim within the 60-day [statutory] deadline."
A62: manage.apc@gmail.com | B62: =+'jobinfo(2)'!$C$39 -> TBD | C62: =+'jobinfo(2)'!$C$29 -> STAPLES.OLIVIA @ace.aaa.com | D62: =+'jobinfo(2)'!$C$41 -> TBD
A63: APC = GD Consulting | B63: =+'jobinfo(2)'!$B$39 -> adj CPS email | C63: =+'jobinfo(2)'!$B$29 -> Email INS. co. | D63: =+'jobinfo(2)'!$B$40 -> TMP adj | E63: WHY ARE YOU REFUSING TO ABIDE BY THE LEGAL REQUIREMENTS ON PAYMENT DISBURSEMENTS ?
A64: ATTACHMENTS INDEX | C64: =A14 -> Rebuild BID; additional photos & documentation ATTACHED & to follow.
E65: IS THERE A REASON WHY ARE YOU REFUSING TO ABIDE BY THE LEGAL REQUIREMENTS ON PAYMENT DISBURSEMENTS ?
A66: ='jobinfo(2)'!C1 -> LACEY, EUNICE | B66: ='jobinfo(2)'!C129 -> 13601 5th Ave | C66: ='jobinfo(2)'!C3 -> East Cleveland, OH 44112 | D66: ='jobinfo(2)'!C5 -> (216) 450-4913
D67: ='jobinfo(2)'!C26 -> AAA Insurance | E67: Request for Depreciation Hold and/or Undisputed Claim Portion Release
A68: ='jobinfo(2)'!C12 -> 45765 | C68: ='jobinfo(2)'!C27 -> #017095711
E69: When a debt has a settled and unsettled amount, the insured can request the debtor the payment from the insurer of the settled amount without having to wait for the unsettled amount to be determined.
A70: 00. AOB CVR LTR
A71: Details direct payment authorization & Assignment of Benefits
A73: =A171 -> 000. XACTIMATE Invoice/ESTIMATE
A74: =A172 -> A). PDF FILE | E74: If you don't comprehend this request , then please provide me with your supervisors contact information.
A75: =A173 -> (MIT SUB & GC O&P INVOICES/W9 as needed)
A76: 006.B ESX FILE, | B76: NOT ALL INSURERS allow ESX file. {SFI ALS} …... (except adjuster direct email)
E77: Ohio law stipulates that an insurance company has 15 days to acknowledge receipt of a claim. After receipt of all properly executed proof of loss forms, the insurance company has 21 days to accept or deny the claim and provide their reasons for same. They have 10 days after a settlement to pay.
A78: 1. GENERAL AUTHORIZATION PACKAGE (maybe combo report Encircle / Excel)
A79: 2. CUSTOMER AGREEMENT/Contract Package (signed).
A80: 3. W9 form. | B80: supplied to process direct payment to company | E80: Rule 3901-1-54 | Unfair property/casualty claims settlement practices.
E81: Ohio Administrative Code CHAPTER 3901-1 GENERAL PROVISIONS
A82: =A184 -> 4. “JOBSITE VERIFICATION & SOURCE OF LOSS” (Combined REPORT) | E82: Rule 3901-1-54 | Unfair property/casualty claims settlement practices.
A83: DOCUMENTS our presence at actual named jobsite & site exterior conditions | E83: Effective: 14-Feb-22 Promulgated Under:119.03
A84: "SOURCE OF LOSS” picture report
A85: Picture report details 'source of loss'/damages in specific areas to be addressed
E86: (6) An insurer shall tender payment to a first party claimant no later than ten days after acceptance of a claim if the amount of the claim is determined and is not in dispute, unless the settlement involves a structured settlement, action by a probate court, or other extraordinary circumstances as documented in the claim file.
A87: =A185 -> PER JOB TYPE (VARIES) PDF REPORTS as follows: | D87: =D185 -> (AS NEEDED PER CLAIM)
A88: =A186 -> 5.A EAGLEVIEW (as needed). | C88: =C186 -> 5.B EXTERIOR OVERVIEW PICS
A89: =A187 -> 5.C PLUMBER | B89: =B187 -> 5.D UTILITIES BILL 3MONTHS | D89: =D187 -> 5.E FIRE / POLICE
E90: (8) If a claim involves multiple coverages under any policy, no insurer shall withhold payment under any such coverage when the payment is known, the payment is not in dispute, and the payment would extinguish the insurer's liability under that coverage. No insurer shall withhold such payment for the purpose of forcing settlement on all other coverage to effect a single payment
A92: =A190 -> ENCIRLE REPORTS :
A93: =A191 -> 7. “JOB/ROOMS Overview Pictures’’
A94: =MIT!B201 -> 0
E95: .(10) An insurer shall not use settlement practices that result in compelling first party claimants to litigate by offering substantially less than the amounts claimed compared to the amount ultimately recovered in actions brought by such claimants.
A96: 8. ATTACHMENTS INDEX | C96: =TODAY() -> 46069
B97: SUBMITTED | E97: WHY ARE YOU REFUSING TO ABIDE BY THE LEGAL REQUIREMENTS ON PAYMENT DISBURSEMENTS ?
E99: IS THERE A REASON WHY ARE YOU REFUSING TO ABIDE BY THE LEGAL REQUIREMENTS ON PAYMENT DISBURSEMENTS ?
E106: Ohio
E107: Ohio law stipulates that an insurance company has 15 days to acknowledge receipt of a claim. After receipt of all properly executed proof of loss forms, the insurance company has 21 days to accept or deny the claim and provide their reasons for same. They have 10 days after a settlement to pay.
E109: Georgia
E110: In Georgia, insurance companies have 15 days to acknowledge receipt of a claim, as well as provide proof claim forms. Once all forms are received, the insurance adjuster has 15 days to deny or accept the claim. Once a settlement has been reached, and or there is an undisputed amount determined, they have 10 days to pay.
E111: O.C.G.A. § 33‐6‐33 (Copy w/ Cite) O.C.G.A. § 33‐6‐33 GEORGIA CODE Copyright 2010 by The State of Georgia
E113: New York
E114: New York laws provide that insurance companies have 15 days to acknowledge receipt of a claim. They have 15 days to commence an investigation and 15 days after receipt of all proof to accept or deny the claim. Payment must then be made within five business days of settlement.
...

Sheet MIT
A1: HMR Pictures & further documentation ATTACHED | E1: Per your request please find attached our MITIGATION BID for services WORK IN PROGRESS. TO BE PERFORMED and or to be Performed.
A2: (Note: Pictures & further documentation to follow under separate email). | E2: HAZARDOUS MATERIAL REMEDIATION PHASE #2
A3: ='jobinfo(2)'!C100 -> All Phase Consulting, LLC | E3: EMS INTERIOR MITIGATION Invoicing
A5: ='jobinfo(2)'!C101 -> WWW.MYAPCLLC.COM | C5: ='jobinfo(2)'!C102 -> Insured & GA Registered #09073201 | E5: Pictures & further documentation ATTACHED
A6: ='jobinfo(2)'!C105 -> ECI 531 FIFTH AVE, | B6: ='jobinfo(2)'!C103 -> 375 Rockbridge Road, Suite 172-343 | D6: ='jobinfo(2)'!C107 -> 20810 AURORA RD | E6: EMS EXTERIOR EMERGENCY SERVICES Invoicing
A7: ='jobinfo(2)'!C106 -> PELHAM, NY 10803 | B7: ='jobinfo(2)'!C104 -> Lilburn, GA, 30047 | D7: ='jobinfo(2)'!C108 -> BEDFORD,OH 44146
A8: ='jobinfo(2)'!C109 -> Providing Cost Estimating & Project Management Services | E8: INTERIOR EMS MITIGATION INVOICE for services WORK IN PROGRESS…. TO BE PERFORMED and or to be Performed.Per your request please find attached.
A9: ='jobinfo(2)'!C110 -> Five Generations of Great Work | C9: ='jobinfo(2)'!C111 -> Five Generations of Pride & Skills
A10: Co. REP. / PH | B10: ='jobinfo(2)'!C112 -> Joe Jones, PM 216.450.7228 | D10: ='jobinfo(2)'!C113 -> wsbjoe9@gmail.com
A11: COMPANY REP. #2 | B11: ='jobinfo(2)'!C114 -> 404-446-9060 | D11: =C5 -> Insured & GA Registered #09073201 | E11: Supplemental Invoices
A12: TIN W9 | B12: ='jobinfo(2)'!C116 -> TIN 83-226 0563 | C12: ='jobinfo(2)'!C117 -> FEDEX # 9836-2151-1 | E12: Supplemental EMS INTERIOR MITIGATION Invoicing
A14: =A1 -> HMR Pictures & further documentation ATTACHED | C14: Claim # | D14: =+'jobinfo(2)'!C27 -> #017095711 | E14: Revised Mitigation Invoice per Agreement & your request Attached
A16: ='jobinfo(2)'!C1 -> LACEY, EUNICE | C16: ='jobinfo(2)'!C4 -> Emdlacey@gmail.com
A17: ='jobinfo(2)'!C2 -> 13601 5th Ave | C17: ='jobinfo(2)'!C5 -> (216) 450-4913 | E17: Supplemental Invoices Attached; (photos to follow under separate email)
A18: ='jobinfo(2)'!C3 -> East Cleveland, OH 44112 | E18: Supplemental Invoices to follow under separate email. __________
A20: Per your request; enclosed are Estimates / Proof of Loss Supporting Documentation per subject property / current risk.
A21: Insurance Co. Name | B21: ='jobinfo(2)'!C26 -> AAA Insurance | C21: policy # | D21: ='jobinfo(2)'!C28 -> OHH000190052 | E21: Create Email (#2) (Note: Pictures & further documentation as follows.
A22: Email INS. co. | B22: ='jobinfo(2)'!C33 -> STAPLES.OLIVIA @ace.aaa.com | C22: Insurance Co. Phone | D22: ='jobinfo(2)'!C46 -> TBD | E22: `Per your request; enclosed are Proof of Loss Supporting Documentation per subject property / current risk.
A23: DESK Adjuster DA | B23: ='jobinfo(2)'!C30 -> STAPLES, OLIVIA 207 776 6150 | C23: adj contents | D23: ='jobinfo(2)'!C37 -> SPV Tanya Sayer 207-791-8544 | E23: 7. “JOB/ROOMS Overview Pictures’’
A24: DA Phone | B24: ='jobinfo(2)'!C31 -> 207 776 6150 | C24: adj CPS phone # | D24: ='jobinfo(2)'!C38 -> TBD | E24: MSDS
A25: DA Ph. Ext. # | B25: ='jobinfo(2)'!C32 -> 207 776 6150 | C25: adj CPS email | D25: ='jobinfo(2)'!C39 -> TBD | E25: A safety data sheet (SDS), material safety data sheet (MSDS), or product safety data sheet (PSDS)
A26: DA Email | B26: ='jobinfo(2)'!C33 -> STAPLES.OLIVIA @ace.aaa.com | D26: -------------------------------- | E26: A safety data sheet (SDS), material safety data sheet (MSDS), or product safety data sheet (PSDS) is a document that lists information relating to occupational safety and health for the use of various substances and products.
A27: Field Adjuster Name | B27: ='jobinfo(2)'!C34 -> VINCENT, KATHERINE | C27: TMP adj | D27: ='jobinfo(2)'!C40 -> TBD | E27: material safety data sheet (MSDS), or product safety data sheet (PSDS) is a document that lists information relating to occupational safety and health for the use of various substances and products.
A28: Phone # field adj | B28: ='jobinfo(2)'!C35 -> 3306184299 | C28: TMP adj phone # | D28: ='jobinfo(2)'!C41 -> TBD | E28: HAZARDOUS MATERIAL REMEDIATION PHASE
A29: Field adj email | B29: ='jobinfo(2)'!C36 -> KATHERINE@KGVINCENT.COM | C29: adj TMP email | D29: ='jobinfo(2)'!C42 -> TBD
A30: Per your request please find attached our MITIGATION INVOICE for services performed at your property.
A31: As a courtesy to you and per your request we have also forwarded a copy to your insurer.
E32: Stabilization per IICRC 2021 S500 Section 12.4.2
A33: Enclosed is an Assignment of Insurance Benefits and Direct Payment Authorization. | F33: Preventing Secondary Damage to Unaffected Areas of Structure.
A34: Thus all monies due to named herein contractor are to be released | F34: 12.3.5 Humidity Control in Contaminated Structures
A35: without delay; solely and directly to contractor. | F35: 12.4.2 Controlling Humidity & Stabilization (Initial Humidity Control)
F36: Minimize further structural damage. Mitigation Phase 1 & Phase 2
A37: There is a payment due for emergency and mitigation; these services that have already been performed;
A38: consequently the mortgage company has no interest in these specific funds; therefore make direct payment. | F38: ACTIVITES
G39: Determine Coverage /Payment / Contract.
A40: *Per our signed Assignment of Insurance Benefits / Pay Directive, any payments remitted to any party other than …..................................
B41: =A3 -> All Phase Consulting, LLC | G41: Respond to Job site & Evaluate Damages
A42: will require a stop payment and a new payment issued directly to | E42: . | G42: Determine WATER CATEGORY
B43: =B41 -> All Phase Consulting, LLC
A44: Accordingly, please do not issue payment under the Assigned Rights directly to the Policyholder. Doing so will not result in a credit toward the balance owed to us. Directly paying the Policyholder for the assigned portion of the claim will not discharge your obligations under the policy and may require double-payment!
E46: . | G46: Testing for HMR Hazardous Materials.
A47: Payments: Issuance, payment, and acceptance of payment are without prejudice to any rights of the Owner, Assignee, or Contractor under the terms of this agreement.
A48: Owner, Assignee, and or Contractor also specifically reserves the right to submit for review and payment any additional/supplemental invoices as may be deemed necessary to restore the property to the pre-loss condition or better. | G48: Establish Access to Property per work In Progress. Per owners & Tenants.
A49: I/We select the option of overnight shipping for expedited delivery of claim funds. | G49: Mobilize resources. Document Equipment as needed per IICRC Standards.
A50: Attachments may include: | B50: Invoice | C50: W9 | G50: Determine Content Manipulation & Storage.
A51: Authorization/Assignment of Benefits/Contract | G51: Document Equipment as needed per IICRC Standards. Dehumidifiers Calc.
A52: DryLogs/ Moisture Map | C52: Test / Lab results | G52: Determine Dry Chambers per IICRC Standards.
A53: Pictures; may be sent under separate emails. | G53: Install per Dehumidifiers per Dry Chamber
A54: Equipment | B54: Demolition | C54: ESX file | G54: Install Air Scrubbers / Hydroxoyl per Dry Chamber
G55: Establish Containment per Dry Chamber
A56: Your intention should be to fully cooperate with us in this matter; along with fully paying us for our services. | G56: Cover HVAC Vents / Supports Drying?
A57: We may exercise our rights that may result in; ONLY IF YOU DO NOT PAY US, in full per our contract: | G57: Extract bulk materials and or water.
A58: liens on the real property; your residence garnishment of your bank accounts | G58: Spray/treat with anti microbials.
A59: liens on your personal assets garnishment of your wages | G59: Securing Job site and Equipment
A60: foreclosure of the real property interest charges
A61: sale and auction of your personal belongings payment of our legal fees to collect | G61: ELECTRICAL LOAD CALCULATIONS; Calculate Existing Services Available
A62: criminal charges for theft of services. insurance fraud charges | G62: DETERMINE POWER SUPPLY REQUIRED, GENERATOR and or POWER BOX.
G63: DETERMINE POWER SUPPLY REQUIRED, GENERATOR and or POWER BOX.
A64: Please also, be advised all the subcontractors and workers involved may also have the option to utilize all of the above along with seeking recovery in Small Claims Court.
A66: By your signing of the original Authorization contract you were committing to allow us to proceed fully.
A67: Please take the time to review all components and documents.
A68: Also, we encourage you to review this with your legal advisors or whomever you may wish to consult with.
A69: All parties reserve all rights and nothing contained herein shall serve as a waiver of any rights. | F69: ...................................................................................................................................
A70: It is stated that this submittal does not represent a final invoice of any type.
A72: Customer Email | B72: DA Email | C72: Field adj email | D72: adj TMP email
A73: Courtabrown88@gmail.com | B73: =+'[3]jobinfo(2)'!$C$33 -> claims@claims.allstate.com | C73: =+'[3]jobinfo(2)'!$C$36 -> TBD | D73: =+'[3]jobinfo(2)'!$C$42 -> TBD
A74: =+'jobinfo(2)'!$C$4 -> Emdlacey@gmail.com | B74: =+'jobinfo(2)'!$C$29 -> STAPLES.OLIVIA @ace.aaa.com | C74: ='jobinfo(2)'!C36 -> KATHERINE@KGVINCENT.COM | D74: =+'jobinfo(2)'!$C$39 -> TBD
A75: APC = GD Consulting | B75: manage.apc@gmail.com | C75: ='jobinfo(2)'!$B$29 -> Email INS. co.
A77: 0. ATTACHMENTS INDEX | C77: =A1 -> HMR Pictures & further documentation ATTACHED
A79: ='jobinfo(2)'!C1 -> LACEY, EUNICE | B79: ='jobinfo(2)'!C2 -> 13601 5th Ave | C79: ='jobinfo(2)'!C3 -> East Cleveland, OH 44112
A80: ='jobinfo(2)'!C4 -> Emdlacey@gmail.com | D80: ='jobinfo(2)'!C26 -> AAA Insurance
A81: ='jobinfo(2)'!C12 -> 45765 | D81: ='jobinfo(2)'!C27 -> #017095711
A83: 00. AOB CVR LTR
A84: Details direct payment authorization & Assignment of Benefits
A86: 000. XACTIMATE Invoice/ESTIMATE
A87: A). PDF FILE | C87: (MIT SUB & GC O&P INVOICES as needed)
A89: B) ESX FILE, | B89: NOT ALL INSURERS allow ESX file. {SFI/ALS} (OR adjuster direct email)
A91: 1. GENERAL AUTHORIZATION PACKAGE (maybe combo report Encircle / Excel)
A92: 2. CUSTOMER AGREEMENT/Contract Package (signed).
A93: 3. W9 form. | B93: supplied to process direct payment to company
A95: 4. “JOBSITE VERIFICATION & SOURCE OF LOSS” (Combined REPORT)
A96: DOCUMENTS our presence at actual named jobsite & site exterior conditions
A97: "SOURCE OF LOSS” picture report
A98: Picture report details 'source of loss'/damages in specific areas to be addressed
A100: PER JOB TYPE (VARIES) PDF REPORTS as follows: | C100: (AS NEEDED PER CLAIM)
A101: 5.A EAGLEVIEW (as needed). | C101: 5.B EXTERIOR OVERVIEW PICS
A102: 5.C PLUMBER | B102: 5.D UTILITIES BILL 3MONTHS | D102: 5.E FIRE / POLICE
A104: MIT.7. MITIGATION Equipment,INITIAL
A105: ENCIRLE REPORTS :
A106: 7. “JOB/ROOMS Overview Pictures’’
A110: MIT.7. MITIGATION Equipment,INITIAL | C110: ='jobinfo(2)'!C1 -> LACEY, EUNICE | D110: ='jobinfo(2)'!C11 -> BATHTUB OVERFLOW | E110: 8. DRY LOGS REPORTS (FULL) EXCEL | G110: MIT.7. MITIGATION Equipment,INITIAL
A111: ='jobinfo(2)'!C26 -> AAA Insurance | B111: ='jobinfo(2)'!C2 -> 13601 5th Ave | C111: ='jobinfo(2)'!C3 -> East Cleveland, OH 44112 | D111: ='jobinfo(2)'!C5 -> (216) 450-4913
A112: ='jobinfo(2)'!C27 -> #017095711 | D112: ='jobinfo(2)'!C12 -> 45765
A113: MIT 1. CVR SHEET
A115: MIT 2. CAUSE OF LOSS | C115: =A80 -> Emdlacey@gmail.com
A116: 2.A EAGLEVIEW (as needed). = RFG | C116: 2.B Exterior PICS = RFG / WIND/ VEHICLE
A117: 2.C PLUMBER | B117: WATER METER/GAS | C117: 2.D UTILITIES BILL 3 MONTHS
A118: WATER METER READING/Water Gallon Spillage Potential | C118: Water Gallon Spillage Potential
A119: 2.E FIRE DEPT. / SMOKE | C119: 2.F VANDALISM = POLICE
A121: MIT 3. Test / Lab results | C121: LEAD | D121: ASBESTOES
...

Sheet CPS
A1: =F2 -> Contents Pack Out/Manipulation Services performed and or to be performed . | F1: NON SALVAGEABLE ITEMS PPR #1
F2: Contents Pack Out/Manipulation Services performed and or to be performed .
F3: CON PERSONAL PROPERTY REPLACEMENT ITEMS SERVICES
F4: REPLACEMENT ITEMS PACKING & EVALUATION INVOICING
A5: Per your REQUEST please find attached our INVOICE;
A6: (Note: Pictures & further documentation to follow under separate email). | F6: LABOR ONLY FOR HANDLING NON SALAGEABLE PERSONAL PROPERTY
F7: Contents Pack Out/Manipulation Services performed and or to be performed .
A8: =+'jobinfo(2)'!$C$100 -> All Phase Consulting, LLC | F8: (Note: Pictures & further documentation to follow under separate email).
A9: =+'jobinfo(2)'!$C$101 -> WWW.MYAPCLLC.COM | C9: =+'jobinfo(2)'!$C$102 -> Insured & GA Registered #09073201
A10: =+'jobinfo(2)'!$C$105 -> ECI 531 FIFTH AVE, | B10: =+'jobinfo(2)'!$C$103 -> 375 Rockbridge Road, Suite 172-343 | D10: =+'jobinfo(2)'!$C$107 -> 20810 AURORA RD | F10: Per your request and mutual agreement please find attached our INVOICE;
A11: =+'jobinfo(2)'!$C$106 -> PELHAM, NY 10803 | B11: =+'jobinfo(2)'!$C$104 -> Lilburn, GA, 30047 | D11: =+'jobinfo(2)'!$C$108 -> BEDFORD,OH 44146 | F11: (Note: Pictures & further documentation to follow as per attached).
A12: =+'jobinfo(2)'!$C$109 -> Providing Cost Estimating & Project Management Services
A13: =+'jobinfo(2)'!$C$110 -> Five Generations of Great Work | C13: =+'jobinfo(2)'!$C$111 -> Five Generations of Pride & Skills | F13: NON SALVAGEABLE ITEMS PPR #2
A14: =+'jobinfo(2)'!C$112 -> Joe Jones, PM 216.450.7228 | C14: =+'jobinfo(2)'!$C$113 -> wsbjoe9@gmail.com | F14: Pictures & further Documentation ATTACHED;
A15: COMPANY REP. #2 | B15: =+'jobinfo(2)'!$C$114 -> 404-446-9060 | C15: =+'jobinfo(2)'!$C$115 -> info@myapcllc.com | F15: INVOICE per Contents Pack Out/Manipulation Services performed and or to be performed .
A16: EIN # | B16: =+'jobinfo(2)'!$C$116 -> TIN 83-226 0563 | C16: FEDEX# | D16: =+'jobinfo(2)'!$C$117 -> FEDEX # 9836-2151-1 | F16: Revised Contents Pack Out Invoice per Agreement
F17: LABOR ONLY FOR HANDLING PERSONAL REPLACEMENT PROPERTY
A18: =A1 -> Contents Pack Out/Manipulation Services performed and or to be performed . | D18: =+'jobinfo(2)'!$C$27 -> #017095711
A19: =+'jobinfo(2)'!$C$1 -> LACEY, EUNICE | B19: =+'jobinfo(2)'!$C$5 -> (216) 450-4913 | F19: Email (#2) | G19: (Pictures & further documentation as follows.
A20: =+'jobinfo(2)'!$C$2 -> 13601 5th Ave | C20: =+'jobinfo(2)'!$C$4 -> Emdlacey@gmail.com
A21: =+'jobinfo(2)'!$C$3 -> East Cleveland, OH 44112
A22: Per your request; enclosed are Estimates / Proof of Loss Supporting Documentation per subject property / current risk. | F22: Email (#3)
A23: Insurance Co. Name | B23: =+'jobinfo(2)'!$C$26 -> AAA Insurance | C23: =+'jobinfo(2)'!$B$28 -> policy # | D23: =+'jobinfo(2)'!$C$28 -> OHH000190052 | F23: LABOR ONLY FOR CLEANING / HANDLING PERSONAL PROPERTY
A24: Email INS. co. | B24: =+'jobinfo(2)'!$C$29 -> STAPLES.OLIVIA @ace.aaa.com | C24: =+'jobinfo(2)'!B46 -> Insurance Co. Phone | D24: =+'jobinfo(2)'!C46 -> TBD
A25: DESK Adjuster DA | B25: =+'jobinfo(2)'!$C$30 -> STAPLES, OLIVIA 207 776 6150 | C25: =+'jobinfo(2)'!B32 -> DA Ph. Ext. # | D25: =+'jobinfo(2)'!C32 -> 207 776 6150 | F25: CPS ….. ATTACHMENTS INDEX
A26: DA Phone | B26: =+'jobinfo(2)'!$C$31 -> 207 776 6150 | C26: =+'jobinfo(2)'!$C$33 -> STAPLES.OLIVIA @ace.aaa.com | D26: =+'jobinfo(2)'!B33 -> DA Email | F26: PROVIDES EXPLANATION OF THE PURPOSE OF ENCLOSED ATTACHMENTS
A27: Field Adjuster Name | B27: =+'jobinfo(2)'!$C$34 -> VINCENT, KATHERINE | C27: =+'jobinfo(2)'!$C$36 -> KATHERINE@KGVINCENT.COM
A28: Phone # field adj | B28: =+'jobinfo(2)'!$C$35 -> 3306184299 | F28: Request for Depreciation Hold and/or Undisputed Claim Portion Release
A29: TMP adj | B29: =+'jobinfo(2)'!$C$40 -> TBD | C29: =+'jobinfo(2)'!C37 -> SPV Tanya Sayer 207-791-8544 | D29: adj contents | F29: When a debt has a settled and unsettled amount, the insured can request the debtor the payment from the insurer of the settled amount without having to wait for the unsettled amount to be determined.
A30: TMP adj phone # | B30: =+'jobinfo(2)'!$C$41 -> TBD | C30: =+'jobinfo(2)'!C38 -> TBD | D30: adj CPS phone #
A31: adj TMP email | B31: =+'jobinfo(2)'!$C$42 -> TBD | C31: =+'jobinfo(2)'!C39 -> TBD | D31: adj CPS email
A32: =+REBLD!A27 -> adj TMP email | B32: =+REBLD!B27 -> TBD | C32: =+REBLD!#REF! -> #REF! | D32: =+REBLD!C27 -> TBD
A33: As a courtesy to you and per your request we have also forwarded a copy to your insurer.
A34: Enclosed is an Assignment of Insurance Benefits and Direct Payment Authorization.
A35: Thus all monies due to named herein contractor are to be released without delay; solely and directly to the contractor.
A36: *Per our signed Assignment of Insurance Benefits / Pay Directive, any payments remitted to any party other than …..................................
B37: ='jobinfo(2)'!$C$100 -> All Phase Consulting, LLC
A38: will require a stop payment and a new payment issued directly to
B39: ='jobinfo(2)'!$C$100 -> All Phase Consulting, LLC
A40: Accordingly, please do not issue payment under the Assigned Rights directly to the Policyholder. Doing so will not result in a credit toward the balance owed to us. Directly paying the Policyholder for the assigned portion of the claim will not discharge your obligations under the policy and may require double-payment!
F42: I/We select the option of overnight shipping for expedited delivery of claim funds.
A43: There is a payment due for contents pack out and manipulation services performed; these services that have already been performed; consequently the mortgage company has no interest in these specific funds; therefore make direct payment.
A45: Please refrain from including mortgage company on the INVOICE for Contents Pack out and CONTENT Manipulation services performed Check.
A47: Payments: Issuance, payment and acceptance of payment are without prejudice to any rights of the Owner, Assignee or Contractor under the terms of this agreement.
A48: Owner, Assignee and or Contractor also specifically reserves the right to submit for review and payment any supplemental invoices as maybe deemed necessary to restore the property to it's pre-loss condition or better.
A50: It is stated that this submittal does not represent a final invoice of any type.
A51: I/We select the option of overnight shipping for expedited delivery of claim funds.
A52: Attachments may include:
A53: Invoice | B53: W9 | C53: ESX file
A54: Authorization/Assignment of Benefits/Contract
A55: Pictures; may be sent under separate emails. | C55: Equipment
A57: Your intention should be to fully cooperate with us in this matter; along with fully paying us for our services.
A58: We may exercise our rights that may result in; ONLY IF YOU DO NOT PAY US, in full per our contract:
A59: liens on the real property; your residence garnishment of your bank accounts
A60: liens on your personal assets garnishment of your wages
A61: foreclosure of the real property interest charges
A62: sale and auction of your personal belongings payment of our legal fees to collect
A63: criminal charges for theft of services. insurance fraud charges
A65: Please also, be advised all the subcontractors and workers involved may also have the option to utilize all of the above along with seeking recovery in Small Claims Court.
A67: So, basically, it shall be the intention to fully cooperate with us in this matter; along with fully paying us for our services.
A69: By signing of the original Authorization contract you were committing to allow us to proceed fully..
A70: Please take the time to review all components and documents.
A71: Also, we encourage you to review this with your legal advisors or whomever you may wish to consult with.
... A73: It is stated that this submittal does not represent a final invoice of any type.
A75: =+'jobinfo(2)'!$B$4 -> Customer Email | B75: =+'jobinfo(2)'!$B$33 -> DA Email | C75: =+'jobinfo(2)'!$B$36 -> Field adj email | D75: =+'jobinfo(2)'!$B$42 -> adj TMP email
A76: =+'jobinfo(2)'!$C$4 -> Emdlacey@gmail.com | B76: =+'jobinfo(2)'!$C$33 -> STAPLES.OLIVIA @ace.aaa.com | C76: =+'jobinfo(2)'!$C$36 -> KATHERINE@KGVINCENT.COM | D76: =+'jobinfo(2)'!$C$42 -> TBD
A78: manage.apc@gmail.com | B78: =+'jobinfo(2)'!$C$39 -> TBD | C78: =+'jobinfo(2)'!$C$29 -> STAPLES.OLIVIA @ace.aaa.com
A79: APC = GD Consulting | B79: =+'jobinfo(2)'!$B$39 -> adj CPS email | C79: =+'jobinfo(2)'!$B$29 -> Email INS. co.
C81: =A122 -> CPS PACKOUT Items EMAIL to Insurer; CHECKLIST. …
A83: =D156 -> LACEY, EUNICE | B83: =D157 -> 13601 5th Ave | C83: =D158 -> East Cleveland, OH 44112 | D83: =D162 -> AAA Insurance
A84: =C127 -> 45765 | C84: =D160 -> (216) 450-4913 | D84: =D18 -> #017095711
D85: =D159 -> Emdlacey@gmail.com
A86: =MIT!B142 -> 0
A87: =MIT!C142 -> TENSION POSTS & ZIPPERS
A89: =MIT!B144 -> 0 | C89: PDF
A90: 01.B ESX FILE, NOT ALL INSURERS allow ESX file. {SFI ALS} ….. (except adjuster direct email)
A92: =MIT!B146 -> ADDITIONAL CIRCUITS # REQUIRED
A93: =MIT!B147 -> 0
A94: =MIT!B148 -> A. MATERIAL TYPE & include DRY GOAL | B94: =MIT!C148 -> 0
A96: =MIT!B151 -> C. Moisture Mapping Readings Chart
A97: =MIT!B152 -> 0
A99: =MIT!B154 -> B. READINGS Pictures
A100: =MIT!B155 -> C. Psychrometric Readings; RH & Temp & GPP & EVP & Chart
A101: Consequently, AREAS where contents had to be removed from to perform remediation tasks
A103: =A139 -> 5. CPS 5.A BOX COUNT REPORT ……......(BOX COUNT TOTALS BY ROOM)
A104: We calculate labor based on number of boxed/tagged items,
A106: =A142 -> CPS 5.B BOX COUNT PHOTO REPORT;
A107: We calculate labor based on number of boxed/tagged items,
A109: =A149 -> CPS 500.A DAY1 “ Overview PICS ….. PER ROOM ” (Personal Property Initial SITUATION).
A110: Picture Report to document Initial jobsite conditions per personal property….......
A112: =A150 -> CPS 588.B DAY2 “ Overview PICS WORK In PROGRESS(pack out/boxes being packed).
A113: Picture Report to demonstrate WORK IN PROGRESS> items being packed into boxes
A115: =A151 -> CPS 588.C DAY3 “.PICS ( storage /moving truck / stack of boxes). OVERVIEW
A116: Picture Report to provide support for all materials/storage
A118: =A152 -> CPS 588.D DAY4 “ Demo / Trash or Pack back / Reset). OVERVIEW PICS
A119: Picture Report to provide support for “ Demo / Trash or Pack back / Reset
A122: CPS PACKOUT Items EMAIL to Insurer; CHECKLIST. … | D122: ='jobinfo(2)'!C1 -> LACEY, EUNICE | E122: HOW 2 NOTES
A123: Email (#1) | D123: ='jobinfo(2)'!C5 -> (216) 450-4913 | E123: Email (#1) per the numbered following attachments list:
A124: (Note: Pictures & further documentation to follow under separate Email #2) | D124: ='jobinfo(2)'!C3 -> East Cleveland, OH 44112
A125: ALL REPORTS TO INCLUDE the following prefix : | D125: ='jobinfo(2)'!C4 -> Emdlacey@gmail.com
...

Sheet PPR
A1: =F1 -> NON SALVAGEABLES # 1 | E1: I | F1: NON SALVAGEABLES # 1
A2: =F2 -> NON SALVAGEABLES ITEMS SERVICES | E2: I | F2: NON SALVAGEABLES ITEMS SERVICES
A3: =F3 -> NON SALVAGEABLES ITEMS PACKING & EVALUATION INVOICING | F3: NON SALVAGEABLES ITEMS PACKING & EVALUATION INVOICING
A4: =F4 -> (Note: Pictures & further documentation as follows). | F4: (Note: Pictures & further documentation as follows).
A5: =F5 -> INVOICE FOR LABOR ONLY FOR HANDLING NON SALVAGEABLES ITEMS | F5: INVOICE FOR LABOR ONLY FOR HANDLING NON SALVAGEABLES ITEMS
F6: Contents Pack Out/Manipulation Services performed and or to be performed .
F7: (Note: Pictures & further documentation to follow under separate email).
F8: Per your request and mutual agreement please find attached our INVOICE;
A10: =+'jobinfo(2)'!$C$100 -> All Phase Consulting, LLC | E10: I
A11: =+'jobinfo(2)'!$C$101 -> WWW.MYAPCLLC.COM | C11: =+'jobinfo(2)'!$C$102 -> Insured & GA Registered #09073201 | E11: I
A12: =+'jobinfo(2)'!$C$105 -> ECI 531 FIFTH AVE, | B12: =+'jobinfo(2)'!$C$103 -> 375 Rockbridge Road, Suite 172-343 | D12: =+'jobinfo(2)'!$C$107 -> 20810 AURORA RD | E12: I
A13: =+'jobinfo(2)'!$C$106 -> PELHAM, NY 10803 | B13: =+'jobinfo(2)'!$C$104 -> Lilburn, GA, 30047 | D13: =+'jobinfo(2)'!$C$108 -> BEDFORD,OH 44146 | E13: I
A14: =+'jobinfo(2)'!$C$109 -> Providing Cost Estimating & Project Management Services | E14: I | F14: NON SALVAGEABLES # 2
A15: =+'jobinfo(2)'!$C$110 -> Five Generations of Great Work | C15: =+'jobinfo(2)'!$C$111 -> Five Generations of Pride & Skills | E15: I | F15: NON SALVAGEABLES ITEMS & EVALUATION INVOICING
A16: =+'jobinfo(2)'!C$112 -> Joe Jones, PM 216.450.7228 | C16: =+'jobinfo(2)'!$C$113 -> wsbjoe9@gmail.com | E16: I | F16: Supporting Justification for Work Performed
A17: COMPANY REP. #2 | B17: =+'jobinfo(2)'!$C$114 -> 404-446-9060 | C17: =+'jobinfo(2)'!$C$115 -> info@myapcllc.com | E17: I | F17: BID ITEM / INVOICE PER SUBCONTRACTOR
A18: EIN # | B18: =+'jobinfo(2)'!$C$116 -> TIN 83-226 0563 | C18: FEDEX# | D18: =+'jobinfo(2)'!$C$117 -> FEDEX # 9836-2151-1 | E18: I | F18: CONDITIONAL WAIVER OF LIEN PER SUBCONTRACTOR
E19: I | F19: Per your request and mutual agreement please find attached our INVOICE;
A20: =A1 -> NON SALVAGEABLES # 1 | B20: Re: Check Processing | C20: =+'jobinfo(2)'!$C$27 -> #017095711 | E20: I
A21: =+'jobinfo(2)'!$C$1 -> LACEY, EUNICE | B21: =+'jobinfo(2)'!$C$5 -> (216) 450-4913 | E21: I | F21: Pictures & further Documentation ATTACHED;
A22: =+'jobinfo(2)'!$C$2 -> 13601 5th Ave | C22: =+'jobinfo(2)'!$C$4 -> Emdlacey@gmail.com | E22: I | F22: Contents Pack Out/Manipulation Services performed and or to be performed .
A23: =+'jobinfo(2)'!$C$3 -> East Cleveland, OH 44112 | E23: I | F23: Revised Contents Pack Out Invoice per Agreement
A24: Per your request; enclosed are Estimates / Proof of Loss Supporting Documentation per subject property / current risk. | E24: I | F24: LABOR ONLY FOR HANDLING NON SALVAGEABLES ITEMS
A25: Insurance Co. Name | B25: =+'jobinfo(2)'!$C$26 -> AAA Insurance | C25: =+'jobinfo(2)'!$B$28 -> policy # | D25: =+'jobinfo(2)'!$C$28 -> OHH000190052 | E25: I
A26: Email INS. co. | B26: =+'jobinfo(2)'!$C$29 -> STAPLES.OLIVIA @ace.aaa.com | C26: =+'jobinfo(2)'!B46 -> Insurance Co. Phone | D26: =+'jobinfo(2)'!C46 -> TBD | E26: I | F26: Email (#2)
A27: DESK Adjuster DA | B27: =+'jobinfo(2)'!$C$30 -> STAPLES, OLIVIA 207 776 6150 | C27: =+'jobinfo(2)'!B32 -> DA Ph. Ext. # | D27: =+'jobinfo(2)'!C32 -> 207 776 6150 | E27: I | F27: (Pictures & further documentation as follows.
A28: DA Phone | B28: =+'jobinfo(2)'!$C$31 -> 207 776 6150 | C28: =+'jobinfo(2)'!$C$33 -> STAPLES.OLIVIA @ace.aaa.com | D28: =+'jobinfo(2)'!B33 -> DA Email | E28: I
A29: Field Adjuster Name | B29: =+'jobinfo(2)'!$C$34 -> VINCENT, KATHERINE | C29: =+'jobinfo(2)'!$C$36 -> KATHERINE@KGVINCENT.COM | E29: I | F29: PPR
A30: Phone # field adj | B30: =+'jobinfo(2)'!$C$35 -> 3306184299 | E30: I | F30: PPR 5.A. PPR "Schedule of Loss"
A31: TMP adj | B31: =+'jobinfo(2)'!$C$40 -> TBD | C31: =+'jobinfo(2)'!C37 -> SPV Tanya Sayer 207-791-8544 | D31: adj contents | E31: I | F31: NON SALVAGEABLES ITEMS
A32: TMP adj phone # | B32: =+'jobinfo(2)'!$C$41 -> TBD | C32: =+'jobinfo(2)'!C38 -> TBD | D32: adj CPS phone # | E32: I
A33: adj TMP email | B33: =+'jobinfo(2)'!$C$42 -> TBD | C33: =+'jobinfo(2)'!C39 -> TBD | D33: adj CPS email | E33: I | F33: (Pictures & further documentation as follows.
A34: =+REBLD!A27 -> adj TMP email | B34: =+REBLD!B27 -> TBD | C34: =+REBLD!#REF! -> #REF! | D34: =+REBLD!C27 -> TBD | E34: I
A35: =+REBLD!A27 -> adj TMP email | B35: =+REBLD!B27 -> TBD | C35: =+REBLD!#REF! -> #REF! | D35: =+REBLD!C27 -> TBD | E35: I
A36: Per your request please find attached our INVOICE; contents pack out and manipulation services performed. | E36: I
E37: I
A38: As a courtesy to you and per your request we have also forwarded a copy to your insurer. | E38: I
E39: I
A40: Enclosed is an Assignment of Insurance Benefits and Direct Payment Authorization. | E40: I
A41: Thus all monies due to the named herein contractor are to be released without delay; | E41: I
A42: solely and directly to the contractor. | E42: I
E43: I
A44: There is a payment due for contents pack out and manipulation services performed; these services that have already been performed; consequently the mortgage company has no interest in these specific funds; therefore make direct payment. | E44: I
E45: I
E46: I
A47: Please refrain from including mortgage company on the INVOICE for contents pack out and manipulation services performed Check. | E47: I
E48: I
A49: Payments: Issuance , payment and acceptance of payment are without prejudice to any rights of the Owner, Assignee or Contractor under the terms of this agreement. | E49: I
A50: Owner, Assignee and or Contractor also specifically reserves the right to submit for review and payment any additional / supplemental invoices as maybe deemed necessary to restore the property to it's pre-loss condition or better. | E50: I
E51: I
A52: It is stated that this submittal does not represent a final invoice of any type. | E52: I
A53: I/We select the option of overnight shipping for expedited delivery of claim funds. | E53: I
A54: Attachments may include: | E54: I
A55: Invoice | C55: ESX file | E55: I
A56: Authorization/Assignment of Benefits/Contract | C56: W9 | D56: ='jobinfo(2)'!C116 -> TIN 83-226 0563 | E56: I
E57: I
A58: Pictures; may be sent under separate emails. | C58: Equipment | E58: I
E59: I
E60: I
A61: Your intention should be to fully cooperate with us in this matter; along with fully paying us for our services. | E61: I
A62: We may exercise our rights that may result in; ONLY IF YOU DO NOT PAY US, in full per our contract: | E62: I
A63: liens on the real property; your residence garnishment of your bank accounts | E63: I
A64: liens on your personal assets garnishment of your wages | E64: I
A65: foreclosure of the real property interest charges | E65: I
A66: sale and auction of your personal belongings payment of our legal fees to collect | E66: I
A67: criminal charges for theft of services. insurance fraud charges | E67: I
E68: I
A69: Please also, be advised all the subcontractors and workers involved may also have the option to utilize all of the above along with seeking recovery in Small Claims Court. | E69: I
E70: I
A71: So, basically, it is the intention to fully cooperate with us in this matter; along with fully paying us for our services. | E71: I
E72: I
A73: By signing of the original Authorization contract you were committing to allow us to proceed fully.. | E73: I
A74: Please take the time to review all components and documents. | E74: I
A75: Also, we encourage you to review this with your legal advisors or whomever you may wish to consult with. | E75: I
A76: All parties reserve all rights and nothing contained herein shall serve as a waiver of any rights. | E76: I
E77: I
A78: CC: | B78: APC = GD Consulting | E78: I
A79: =+'jobinfo(2)'!$B$4 -> Customer Email | B79: master file bu | C79: =+'jobinfo(2)'!$B$29 -> Email INS. co. | D79: =+'jobinfo(2)'!$B$33 -> DA Email | E79: I
A80: =+'jobinfo(2)'!$C$4 -> Emdlacey@gmail.com | B80: manage.apc@gmail.com | C80: =+'jobinfo(2)'!$C$29 -> STAPLES.OLIVIA @ace.aaa.com | D80: =+'jobinfo(2)'!$C$33 -> STAPLES.OLIVIA @ace.aaa.com | E80: I
A81: =+'jobinfo(2)'!$C$10 -> TBD | B81: =+'jobinfo(2)'!$B$36 -> Field adj email | C81: =+'jobinfo(2)'!$B$42 -> adj TMP email | D81: =+'jobinfo(2)'!$B$39 -> adj CPS email | E81: I
B82: =+'jobinfo(2)'!$C$36 -> KATHERINE@KGVINCENT.COM | C82: =+'jobinfo(2)'!$C$42 -> TBD | D82: =+'jobinfo(2)'!$C$39 -> TBD | E82: I
E83: I
E84: I
A85: ATTACHMENTS INDEX
B86: =A122 -> NON SALVAGEABLES Documents Stacking List:
A87: =A124 -> LACEY, EUNICE | C87: =C124 -> AAA Insurance | D87: =D124 -> #017095711
A88: ='jobinfo(2)'!C4 -> Emdlacey@gmail.com | C88: =C125 -> 45765
A90: =REBLD!A178 -> 0. AOB COVER
A91: Details our direct payment authorization & Assignment of Benefits
A93: =C131 -> XACTIMATE REPORT/INVOICE | C93: =A131 -> XACTIMATE NON SALVAGEABLES ITEMS
A94: B). ESX FILE NOT ALL INSURERS allow ESX file. {SFI ALS} … (except adjuster direct email)
A96: =REBLD!A179 -> 1. GENERAL AUTHORIZATION PACKAGE
A97: =REBLD!A180 -> 2. CUSTOMER AGREEMENT/Contract Package (signed).
A98: =REBLD!A181 -> 3. W9 form. | B98: =MIT!C148 -> 0
A100: =MIT!B151 -> C. Moisture Mapping Readings Chart
A101: =MIT!B152 -> 0
A102: =MIT!B154 -> B. READINGS Pictures
A103: =MIT!B155 -> C. Psychrometric Readings; RH & Temp & GPP & EVP & Chart
A105: NON SALVAGEABLES 5.A. "Schedule of Loss" DETAILED (WITH PICTURES) (Encircle #1)
A106: Industry standard document picture chart of non salvageable items with pictures & prices
...

Sheet INS
A1: FOLLOW UP SHEET | C1: INSURANCE COMPANY TRACKING | E1: =+REBLD!A4 -> All Phase Consulting, LLC
A3: Name -cst | C3: =+'jobinfo(2)'!C1 -> LACEY, EUNICE | H3: THE CPS PACKOUT INVOICE ALSO IN SOME SORT OF LIMBO.
A4: street- cst | C4: =+'jobinfo(2)'!C2 -> 13601 5th Ave | E4: Co-Owner Name; | F4: =+'jobinfo(2)'!C6 -> TBD
A5: city, state-cst | C5: =+'jobinfo(2)'!C3 -> East Cleveland, OH 44112 | E5: cst ph # 2 | F5: =+'jobinfo(2)'!C7 -> TBD | H5: NEXT WE NEED TO DEAL WITH THE WTR INVOICE......
A6: email-cst | C6: =+'jobinfo(2)'!C4 -> Emdlacey@gmail.com | E6: Cst address # 2 | F6: =+'jobinfo(2)'!C8 -> TBD
A7: Phone# - cst | C7: =+'jobinfo(2)'!C5 -> (216) 450-4913 | E7: city, state-cst#2 | F7: =+'jobinfo(2)'!C9 -> TBD
C8: =+'jobinfo(2)'!C6 -> TBD | E8: email-cst #2 | F8: =+'jobinfo(2)'!C10 -> TBD | H8: an estimated completion date.
A9: Loss info | H9: 30 DAYS AFTER RECEIPT OF REQUESTED SUPPLEMENT FUNDS
A10: =+'jobinfo(2)'!B11 -> Cause of Loss | C10: =+'jobinfo(2)'!C11 -> BATHTUB OVERFLOW | D10: =+'jobinfo(2)'!B13 -> rebuild type 1 | E10: =+'jobinfo(2)'!C13 -> interior repairs LVL2
A11: =+'jobinfo(2)'!B12 -> date of loss | C11: =+'jobinfo(2)'!C12 -> 45765 | D11: =+'jobinfo(2)'!B14 -> rebuild type 2 | E11: =+'jobinfo(2)'!C14 -> interior repairs LVL1 | H11: Have repairs not been ongoing lately? YES
D12: =+'jobinfo(2)'!B15 -> rebuild type 3 | E12: =+'jobinfo(2)'!C15 -> BASEMENT
A13: Ins co info
A14: =+'jobinfo(2)'!B26 -> Insurance Co. Name | B14: =+'jobinfo(2)'!C26 -> AAA Insurance | D14: =+'jobinfo(2)'!B43 -> ATT: Loss Draft Dept. | E14: =+'jobinfo(2)'!C43 -> TBD
A15: =+'jobinfo(2)'!B27 -> Claim # | B15: =+'jobinfo(2)'!C27 -> #017095711 | D15: =+'jobinfo(2)'!B44 -> address ins overnight mail | E15: =+'jobinfo(2)'!C44 -> TBD
A16: =+'jobinfo(2)'!B28 -> policy # | B16: =+'jobinfo(2)'!C28 -> OHH000190052 | D16: =+'jobinfo(2)'!B45 -> city, state-zip ins | E16: =+'jobinfo(2)'!C45 -> TBD
A17: =+'jobinfo(2)'!B29 -> Email INS. co. | B17: =+'jobinfo(2)'!C29 -> STAPLES.OLIVIA @ace.aaa.com | D17: =+'jobinfo(2)'!B46 -> Insurance Co. Phone | E17: =+'jobinfo(2)'!C46 -> TBD
A18: =+'jobinfo(2)'!B30 -> DESK Adjuster DA | B18: =+'jobinfo(2)'!C30 -> STAPLES, OLIVIA 207 776 6150 | D18: =+'jobinfo(2)'!B37 -> adj contents | E18: =+'jobinfo(2)'!C37 -> SPV Tanya Sayer 207-791-8544
A19: =+'jobinfo(2)'!B31 -> DA Phone | B19: =+'jobinfo(2)'!C31 -> 207 776 6150 | D19: =+'jobinfo(2)'!B38 -> adj CPS phone # | E19: =+'jobinfo(2)'!C38 -> TBD
A20: =+'jobinfo(2)'!B32 -> DA Ph. Ext. # | B20: =+'jobinfo(2)'!C32 -> 207 776 6150 | D20: =+'jobinfo(2)'!B39 -> adj CPS email | E20: =+'jobinfo(2)'!C39 -> TBD
A21: =+'jobinfo(2)'!B33 -> DA Email | B21: =+'jobinfo(2)'!C33 -> STAPLES.OLIVIA @ace.aaa.com | D21: =+'jobinfo(2)'!B40 -> TMP adj | E21: =+'jobinfo(2)'!C40 -> TBD
A22: =+'jobinfo(2)'!B34 -> Field Adjuster Name | B22: =+'jobinfo(2)'!C34 -> VINCENT, KATHERINE | D22: =+'jobinfo(2)'!B41 -> TMP adj phone # | E22: =+'jobinfo(2)'!C41 -> TBD
A23: =+'jobinfo(2)'!B35 -> Phone # field adj | B23: =+'jobinfo(2)'!C35 -> 3306184299 | D23: =+'jobinfo(2)'!B42 -> adj TMP email | E23: =+'jobinfo(2)'!C42 -> TBD
A24: =+'jobinfo(2)'!B36 -> Field adj email | B24: =+'jobinfo(2)'!C36 -> KATHERINE@KGVINCENT.COM
A25: =+'jobinfo(2)'!B83 -> Ph. Ext. Mtge contact | C25: =+'jobinfo(2)'!C83 -> TBD | E25: Acct # Mtge Co. | F25: =+'jobinfo(2)'!C84 -> TBD
C26: Scanned | D26: Sent | F26: Scanned | G26: Sent
A27: CUSTOMER CONTRACT PACKAGE: | C27: [ ] | D27: [ ] | E27: Co. = W9 | F27: [ ] | G27: [ ]
A29: Estimates = Proof of Loss Supporting Documentation | E29: Pictures | G29: Sent
A30: Mitigation$_______ | C30: [ ] | D30: [ ] | E30: Mitigation | F30: [ ] | G30: [ ]
A31: Demo $________ | C31: [ ] | D31: [ ] | E31: Demo | F31: [ ] | G31: [ ]
A32: Rebuild $________ | C32: [ ] | D32: [ ] | E32: Rebuild | F32: [ ] | G32: [ ]
A33: Contents $________ | C33: [ ] | D33: [ ] | E33: Contents | F33: [ ] | G33: [ ]
A35: DAY & DATE & TIME | C35: SPOKE TO | D35: CONTACT# | F35: Status | G35: By
D36: FOLLOW UP ACTION/NOTES: DATE DUE BY
A43: FOLLOW UP SHEET | C43: =+C1 -> INSURANCE COMPANY TRACKING
A44: DAY & DATE & TIME | C44: SPOKE TO | D44: CONTACT# | F44: Status | G44: By
D45: FOLLOW UP ACTION/NOTES: DATE DUE BY
A52: STATEMENT | D52: =+#REF! -> #REF!
A53: Final
C54: =+C66 -> Mortgage co | D54: =+D66 -> TBD
A55: =+'jobinfo(2)'!C151 -> 45888
A56: =+'jobinfo(2)'!C152 -> 2200 | C56: =+'jobinfo(2)'!C153 -> 0
A57: =+'jobinfo(2)'!C158 -> 2164086035 | B57: =+'jobinfo(2)'!C154 -> LESSOR INFO | D57: =+'jobinfo(2)'!C156 -> 19048 Watercrest Dr.
A58: =+'jobinfo(2)'!C159 -> FLOCROW48@AOL.COM | B58: =+'jobinfo(2)'!C155 -> Floretta Crowell | D58: =+'jobinfo(2)'!C157 -> Mapel Heights, OH, 44137
A59: =+'jobinfo(2)'!C160 -> ++++++++++
A60: =+'jobinfo(2)'!C161 -> 2479 Greenvale | C60: =+'jobinfo(2)'!C162 -> Cleveland, OH, 44121
A61: =+'jobinfo(2)'!C163 -> Floretta Crowell | C61: =+'jobinfo(2)'!C164 -> 2164086035
A62: =+'jobinfo(2)'!B164 -> city zip | B62: =+'jobinfo(2)'!C165 -> FLOCROW48@AOL.COM | C62: =+'jobinfo(2)'!C166 -> 0
A63: =+'jobinfo(2)'!B166 -> phone # | B63: =+'jobinfo(2)'!C167 -> 0 | C63: =+'jobinfo(2)'!B167 -> Email | D63: =+'jobinfo(2)'!C168 -> REAL ESTATE COMPANY
A65: =+'jobinfo(2)'!B52 -> ROOM ID | B65: =+'jobinfo(2)'!C52 -> LACEY, EUNICE | C65: =+'jobinfo(2)'!B77 -> Room/Area 25 | D65: =+'jobinfo(2)'!C77 -> TBD
A66: =+'jobinfo(2)'!B53 -> Room/Area 1 | B66: =+'jobinfo(2)'!C53 -> LIVING ROOM | C66: =+'jobinfo(2)'!B78 -> Mortgage co | D66: =+'jobinfo(2)'!C78 -> TBD
A67: =+'jobinfo(2)'!B54 -> Room/Area 2 | B67: =+'jobinfo(2)'!C54 -> DINING ROOM | C67: =+'jobinfo(2)'!B79 -> Account# Mtge Co. | D67: =+'jobinfo(2)'!C79 -> TBD
A68: =+'jobinfo(2)'!B55 -> Room/Area 3 | B68: =+'jobinfo(2)'!C56 -> NOOK | C68: =+'jobinfo(2)'!C80 -> TBD
A69: =+'jobinfo(2)'!B56 -> Room/Area 4 | B69: =+'jobinfo(2)'!C57 -> STAIRS UP | C69: =+'jobinfo(2)'!B81 -> contact person mtge | D69: =+'jobinfo(2)'!C81 -> TBD
C70: =+'jobinfo(2)'!C84 -> TBD
A71: To Whom It May Concern: | B71: =+'jobinfo(2)'!C81 -> TBD | C71: =+'jobinfo(2)'!C82 -> TBD
A72: Please find enclosed the necessary documents to process the attached Supplemental Invoice.
A74: =+A52 -> STATEMENT
H79: FINAL INVOICES STATEMENT
A80: Thanking you in advance for your prompt handling of this matter. | H80: =+'jobinfo(2)'!$C$100 -> All Phase Consulting, LLC
A81: Enclosed is an Assignment of Insurance Benefits and Direct Payment Authorization Thus, all monies due to named herein contractor are to be released without delay; solely and directly to contractor. | H81: =+'jobinfo(2)'!$C$101 -> WWW.MYAPCLLC.COM | K81: =+'jobinfo(2)'!$C$102 -> Insured & GA Registered #09073201
A82: Please contact us if you have any further questions. | D82: =NOW() -> 46069.563 | H82: =+'jobinfo(2)'!$C$103 -> 375 Rockbridge Road, Suite 172-343 | K82: =+'jobinfo(2)'!$C$104 -> Lilburn, GA, 30047
A84: Sincerely yours, | H84: =+'jobinfo(2)'!$C$109 -> Providing Cost Estimating & Project Management Services
H85: =+'jobinfo(2)'!$C$110 -> Five Generations of Great Work | J85: =+'jobinfo(2)'!$C$111 -> Five Generations of Pride & Skills
H86: =+'jobinfo(2)'!J$112 -> 0 | J86: =+'jobinfo(2)'!$C$113 -> wsbjoe9@gmail.com
H87: COMPANY REP. #2 | I87: =+'jobinfo(2)'!$C$114 -> 404-446-9060 | K87: =+'jobinfo(2)'!$C$115 -> info@myapcllc.com
H88: EIN # | I88: =+'jobinfo(2)'!$C$116 -> TIN 83-226 0563 | K88: =+'jobinfo(2)'!$C$117 -> FEDEX # 9836-2151-1
H90: =+'jobinfo(2)'!$C$26 -> AAA Insurance | J90: =+'jobinfo(2)'!$B$27 -> Claim # | K90: =+'jobinfo(2)'!$C$27 -> #017095711
H91: =+'jobinfo(2)'!$B$30 -> DESK Adjuster DA | I91: =+'jobinfo(2)'!$C$30 -> STAPLES, OLIVIA 207 776 6150 | K91: =+'jobinfo(2)'!C32 -> 207 776 6150
H92: =+'jobinfo(2)'!$C$33 -> STAPLES.OLIVIA @ace.aaa.com | I92: =+'jobinfo(2)'!$C$31 -> 207 776 6150
H94: =+'jobinfo(2)'!$C$1 -> LACEY, EUNICE | J94: =+'jobinfo(2)'!B4 -> Customer Email | K94: =+'jobinfo(2)'!$C$4 -> Emdlacey@gmail.com
H95: =+'jobinfo(2)'!$C$2 -> 13601 5th Ave | I95: =+'jobinfo(2)'!$C$3 -> East Cleveland, OH 44112 | J95: =+'jobinfo(2)'!B5 -> Cst-owner Phone# | K95: =+'jobinfo(2)'!$C$5 -> (216) 450-4913
I98: FINAL INVOICES STATEMENT
H99: ORIGINAL INVOICES | K99: TTD
H100: Rebuild INVOICE | K100: 310000
H101: Request for Depreciation Hold and/or Undisputed Claim Portion Release | J101: 0 | K101: 4474
H102: Rebuild estimate PWI-UPGRADES | I102: INCLUDED | J102: 0
K103: =J102+J101+J100 -> 0
H104: EMS INTERIOR MITIGATION Invoicing | J104: 0 | K104: 30000
H105: INVOICE; Contents Pack Out & Contents Manipulation. | J105: 0 | K105: 20000
H106: ` | I106: ORIGINAL INVOICES TOTALS | L106: =SUM(K100:K106) -> 364474
H108: Supplemental Invoices
H109: Supplemental Exterior Emergency Services Invoice
H110: Supplemental Rebuild Invoicing | J110: 0
I111: Supplemental Invoices TOTALS | L111: =SUM(J108:J117) -> 0
I112: CURRENT TOTALS ALL DUE | L112: =SUM(L99:L111) -> 364474
H113: Thanking you in advance for your prompt handling of this matter.
H114: LESS PAYMENTS RECEIVED | J114: =H90 -> AAA Insurance | L114: -44482.26
H116: CUSTOMER DEDUCTABLE PAID | J116: =H94 -> LACEY, EUNICE | L116: -5000
I117: CURRENT TOTALS ALL DUE | L117: =SUM(L112:L116) -> 314991.74
H118: Thanking you in advance for your prompt handling of this matter.
N119: ORIGINAL INVOICES | Q119: INS PAID | R119: CHECKLIST
N120: EMS RFG Invoicing | P120: 2400 | Q120: 2400 | R120: =+P120-Q120 -> 0
N122: EMS TREE REMOVAL Invoicing | O122: hmr | P122: 15000 | Q122: 15000 | R122: =+P122-Q122 -> 0
N123: Rebuild estimate | P123: 80000 | Q123: 46000 | R123: =+P123-Q123 -> 34000
N124: Request for Depreciation Hold and/or Undisputed Claim Portion Release | R124: =+P124-Q124 -> 0
N125: EMS INTERIOR MITIGATION Invoicing | P125: 35645.4 | Q125: 0 | R125: =+P125-Q125 -> 35645.4
N126: INVOICE; Contents Pack out and Contents Manipulation services performed. | P126: 22000 | Q126: 0 | R126: =+P126-Q126 -> 22000
P127: =SUM(P120:P126) -> 155045.4 | Q127: =SUM(Q120:Q126) -> 63400 | R127: =+P127-Q127 -> 91645.4
N130: Supplemental Invoices
N131: Request for Depreciation Hold and/or Undisputed Claim Portion Release | Q131: 1 | R131: 44137
...

Sheet CST
A1: FOLLOW UP SHEET | C1: CUSTOMER Contact TRACKING | E1: =+REBLD!A4 -> All Phase Consulting, LLC
H2: 0
A3: Name -cst | C3: =+'jobinfo(2)'!C1 -> LACEY, EUNICE | E3: =+'jobinfo(2)'!B6 -> Co-Owner.cst#2
A4: street- cst | C4: =+'jobinfo(2)'!C2 -> 13601 5th Ave | F4: =+'jobinfo(2)'!C6 -> TBD
A5: city, state-cst | C5: =+'jobinfo(2)'!C3 -> East Cleveland, OH 44112 | F5: =+'jobinfo(2)'!C7 -> TBD
A6: email-cst | C6: =+'jobinfo(2)'!C4 -> Emdlacey@gmail.com | F6: =+'jobinfo(2)'!C8 -> TBD
A7: Phone# - cst | C7: =+'jobinfo(2)'!C5 -> (216) 450-4913 | F7: =+'jobinfo(2)'!C10 -> TBD
A9: Loss info | D9: =+'jobinfo(2)'!B13 -> rebuild type 1 | E9: =+'jobinfo(2)'!C13 -> interior repairs LVL2
A10: =+'jobinfo(2)'!B11 -> Cause of Loss | C10: =+'jobinfo(2)'!C11 -> BATHTUB OVERFLOW | D10: =+'jobinfo(2)'!B14 -> rebuild type 2 | E10: =+'jobinfo(2)'!C14 -> interior repairs LVL1
A11: =+'jobinfo(2)'!B12 -> date of loss | C11: =+'jobinfo(2)'!C12 -> 45765 | D11: =+'jobinfo(2)'!B15 -> rebuild type 3 | E11: =+'jobinfo(2)'!C15 -> BASEMENT
A12: Ins co info
A13: =+'jobinfo(2)'!B26 -> Insurance Co. Name | C13: =+'jobinfo(2)'!C26 -> AAA Insurance | E13: =+'jobinfo(2)'!C43 -> TBD
A14: =+'jobinfo(2)'!B27 -> Claim # | C14: =+'jobinfo(2)'!C27 -> #017095711 | E14: =+'jobinfo(2)'!C44 -> TBD
A15: =+'jobinfo(2)'!B28 -> policy # | C15: =+'jobinfo(2)'!C28 -> OHH000190052 | E15: =+'jobinfo(2)'!C45 -> TBD
A16: =+'jobinfo(2)'!B29 -> Email INS. co. | C16: =+'jobinfo(2)'!C29 -> STAPLES.OLIVIA @ace.aaa.com | E16: =+'jobinfo(2)'!C46 -> TBD
A18: =+'jobinfo(2)'!B30 -> DESK Adjuster DA | C18: =+'jobinfo(2)'!C30 -> STAPLES, OLIVIA 207 776 6150 | D18: =+'jobinfo(2)'!B37 -> adj contents | E18: =+'jobinfo(2)'!C37 -> SPV Tanya Sayer 207-791-8544
A19: =+'jobinfo(2)'!B31 -> DA Phone | C19: =+'jobinfo(2)'!C31 -> 207 776 6150 | D19: =+'jobinfo(2)'!B38 -> adj CPS phone # | E19: =+'jobinfo(2)'!C38 -> TBD
A20: =+'jobinfo(2)'!B32 -> DA Ph. Ext. # | C20: =+'jobinfo(2)'!C32 -> 207 776 6150 | D20: =+'jobinfo(2)'!B39 -> adj CPS email | E20: =+'jobinfo(2)'!C39 -> TBD
A21: =+'jobinfo(2)'!B33 -> DA Email | C21: =+'jobinfo(2)'!C33 -> STAPLES.OLIVIA @ace.aaa.com | D21: =+'jobinfo(2)'!B40 -> TMP adj | E21: =+'jobinfo(2)'!C40 -> TBD
A22: =+'jobinfo(2)'!B34 -> Field Adjuster Name | C22: =+'jobinfo(2)'!C34 -> VINCENT, KATHERINE | D22: =+'jobinfo(2)'!B41 -> TMP adj phone # | E22: =+'jobinfo(2)'!C41 -> TBD
A23: =+'jobinfo(2)'!B35 -> Phone # field adj | C23: =+'jobinfo(2)'!C35 -> 3306184299 | D23: =+'jobinfo(2)'!B42 -> adj TMP email | E23: =+'jobinfo(2)'!C42 -> TBD
A24: =+'jobinfo(2)'!B36 -> Field adj email | C24: =+'jobinfo(2)'!C36 -> KATHERINE@KGVINCENT.COM
A26: =+'jobinfo(2)'!B83 -> Ph. Ext. Mtge contact | C26: =+'jobinfo(2)'!C83 -> TBD | D26: Acct # Mtge Co. | E26: =+'jobinfo(2)'!C84 -> TBD
C28: Scanned / Sent | F28: Scanned / Sent
A29: CUSTOMER CONTRACT PACKAGE: | C29: [ ] [ ] | E29: Co. = W9 | F29: [ ] | G29: [ ]
A31: Estimates = Proof of Loss Supporting Documentation | E31: Pictures | G31: Sent
A32: Mitigation$_______ | C32: [ ] [ ] | E32: Mitigation | F32: ENCIRCLE | G32: [ ]
A33: Demo $________ | C33: [ ] [ ] | E33: Demo | G33: [ ]
A34: Rebuild $________ | C34: [ ] [ ] | E34: Rebuild | G34: [ ]
A35: Contents $________ | C35: [ ] [ ] | E35: Contents | G35: [ ]
A37: DAY & DATE & TIME | C37: SPOKE TO | D37: CONTACT# | F37: Status | G37: By
D38: FOLLOW UP ACTION/NOTES: DATE DUE BY
A49: =+A1 -> FOLLOW UP SHEET | C49: =+C1 -> CUSTOMER Contact TRACKING
A50: DAY & DATE & TIME | C50: SPOKE TO | D50: CONTACT# | F50: Status | G50: By
D51: =+D38 -> FOLLOW UP ACTION/NOTES: DATE DUE BY

Sheet SUBS LTR
A1: FOLLOW UP SHEET | B1: Vendor/SUBS = | G1: APC JJ
A3: Name -cst | C3: =+'jobinfo(2)'!C1 -> LACEY, EUNICE | E3: Co-Owner Name;
A4: street- cst | C4: =+'jobinfo(2)'!C2 -> 13601 5th Ave | E4: Co-Owner Name; | F4: =+'jobinfo(2)'!C6 -> TBD
A5: city, state-cst | C5: =+'jobinfo(2)'!C3 -> East Cleveland, OH 44112 | E5: cst ph # 2 | F5: =+'jobinfo(2)'!C7 -> TBD
A6: email-cst | C6: =+'jobinfo(2)'!C4 -> Emdlacey@gmail.com | E6: Cst address # 2 | F6: =+'jobinfo(2)'!C8 -> TBD
A7: Phone# - cst | C7: =+'jobinfo(2)'!C5 -> (216) 450-4913 | E7: city, state-cst#2 | F7: =+'jobinfo(2)'!C9 -> TBD
C8: =+'jobinfo(2)'!C6 -> TBD | E8: email-cst #2 | F8: =+'jobinfo(2)'!C10 -> TBD
A9: Loss info
A10: =+'jobinfo(2)'!B11 -> Cause of Loss | B10: =+'jobinfo(2)'!C11 -> BATHTUB OVERFLOW | D10: =+'jobinfo(2)'!B13 -> rebuild type 1 | E10: =+'jobinfo(2)'!C13 -> interior repairs LVL2
A11: =+'jobinfo(2)'!B12 -> date of loss | C11: =+'jobinfo(2)'!C12 -> 45765 | D11: =+'jobinfo(2)'!B14 -> rebuild type 2 | E11: =+'jobinfo(2)'!C14 -> interior repairs LVL1
D12: =+'jobinfo(2)'!B15 -> rebuild type 3 | E12: =+'jobinfo(2)'!C15 -> BASEMENT
A13: Ins co info | B13: =+'jobinfo(2)'!C26 -> AAA Insurance | D13: =+'jobinfo(2)'!B27 -> Claim # | E13: =+'jobinfo(2)'!C27 -> #017095711
A14: =+'jobinfo(2)'!B83 -> Ph. Ext. Mtge contact | B14: =+'jobinfo(2)'!C83 -> TBD | D14: Acct # Mtge Co. | E14: =+'jobinfo(2)'!C84 -> TBD
C15: Scanned | D15: Sent | F15: Scanned | G15: Sent
A16: CUSTOMER CONTRACT PACKAGE: | C16: [ ] | D16: [ ] | E16: Co. = W9 | F16: [ ] | G16: [ ]
A18: Estimates = Proof of Loss Supporting Documentation | E18: Pictures | G18: Sent
A19: Mitigation$_______ | C19: [ ] | D19: [ ] | E19: Mitigation | F19: [ ] | G19: [ ]
A20: Demo $________ | C20: [ ] | D20: [ ] | E20: Demo | F20: [ ] | G20: [ ]
A21: Rebuild $________ | C21: [ ] | D21: [ ] | E21: Rebuild | F21: [ ] | G21: [ ]
A22: Contents $________ | C22: [ ] | D22: [ ] | E22: Contents | F22: [ ] | G22: [ ]
A24: DAY & DATE & TIME | C24: SPOKE TO | D24: CONTACT# | F24: Status | G24: By
D25: FOLLOW UP ACTION/NOTES: DATE DUE BY
D26: 450 | E26: =D26*B27 -> 30600
A27: RFG | B27: 68 | D27: 350 | E27: =D27*B27 -> 23800
E28: 6555
E29: =E27-E28 -> 17245
A41: FOLLOW UP SHEET | B41: =+B1 -> Vendor/SUBS = | D41: =+D1 -> 0 | G41: =+G1 -> APC JJ
A42: DAY & DATE & TIME | C42: SPOKE TO | D42: CONTACT# | F42: Status | G42: By
D43: FOLLOW UP ACTION/NOTES: DATE DUE BY
A105: wsb tj oh | E105: =A105 -> wsb tj oh | F105: 1 | G105: 1
A106: WAYSIDE BUILDERS, LLC | E106: =A115 -> wsb jj oh | F106: 11
A107: www.waysidebuilders.com. | C107: Licensed, Insured & Bonded | E107: =A125 -> wsb jj GA | F107: 21
A108: 1860 Sandy Plains Rd # 204-141 | B108: 34194 AURORA RD #218 | D108: ECI 531 FIFTH AVE, | E108: =A135 -> APC | F108: 31
A109: Atlanta, GA 30066 | B109: Solon, OH 44139 | D109: PELHAM, NY 10803 | E109: =A145 -> jthomascontracting@gmail.com | F109: =F108+F106-F105 -> 41 | G109: 2
