Workbook
Name a...new_customer: #REF!
Name Column.a.new.cst: #REF!
Name culpepper: #REF!
Name data: #REF!
Name Document_Stacking_List: #REF!
Name Enter_new_cst_data: #REF!
Name Jefferies: #REF!
Name LOVEJOY_INTERIOR: #REF!
Name Lovejoy_ROOF: #REF!
Name LxWxH: #REF!
Name new_customer: #REF!
Name PRICE_P: #REF!
Name Robinson: #REF!
Name Robinson: #REF!
Name sigtj: "Picture 9859"
Name SubContractor_Summary: #REF!
Name Wayside_Builders__LLC_…...OH: #REF!
Name WSB...GA.Wayside_Builders__LLC……GA: #REF!

Sheet email cvr
A1: This may seem like a lot of information; because it is a lot of information.
A2: Yet, it is the level of estimates/documentation required to substantiate the restoration process fully.
A3: It is also what separates us from many others.
A5: =+'jobinfo(2)'!C100 -> All Phase Consulting, LLC
A6: =+'jobinfo(2)'!C101 -> WWW.MYAPCLLC.COM | C6: =+'jobinfo(2)'!C102 -> Insured & GA Registered #09073201
A7: =+'jobinfo(2)'!C105 -> ECI 531 FIFTH AVE, | B7: =+'jobinfo(2)'!C103 -> 375 Rockbridge Road, Suite 172-343 | D7: =+'jobinfo(2)'!#REF! -> #REF!
A8: =+'jobinfo(2)'!C106 -> PELHAM, NY 10803 | B8: =+'jobinfo(2)'!C104 -> Lilburn, GA, 30047 | D8: =+'jobinfo(2)'!#REF! -> #REF!
A9: =+'jobinfo(2)'!C109 -> Providing Cost Estimating & Project Management Services
A10: =+'jobinfo(2)'!C110 -> Five Generations of Great Work | C10: =+'jobinfo(2)'!C111 -> Five Generations of Pride & Skills
A11: COMPANY REP. | B11: =+'jobinfo(2)'!$C$112 -> Joe Jones, PM 216.450.7228 | C11: =+'jobinfo(2)'!C113 -> wsbjoe9@gmail.com | F11: (740) 235-8196
A12: COMPANY REP. #2 | B12: =+'jobinfo(2)'!C114 -> 404-446-9060 | C12: =+'jobinfo(2)'!C115 -> info@myapcllc.com
A13: EIN # | B13: =+'jobinfo(2)'!C116 -> TIN 83-226 0563 | C13: FEDEX# | D13: =+'jobinfo(2)'!C117 -> FEDEX # 9836-2151-1
A15: Re: Initial Documents Processing
A16: =+'jobinfo(2)'!B1 -> Property-Owner Name | B16: =+'jobinfo(2)'!C1 -> Johnson, Paul & Tamra | C16: =+'jobinfo(2)'!B5 -> Cst-owner Phone# | D16: =+'jobinfo(2)'!C5 -> (216) 399-6191
A17: =+'jobinfo(2)'!B2 -> Property address: street | B17: =+'jobinfo(2)'!C2 -> 9402 Shepard Road | C17: =+'jobinfo(2)'!B6 -> Co-Owner.cst#2 | D17: =+'jobinfo(2)'!C6 -> TBD
A18: =+'jobinfo(2)'!B3 -> Property city, state, zip | B18: =+'jobinfo(2)'!C3 -> Macedonia, OH, USA | C18: =+'jobinfo(2)'!B6 -> Co-Owner.cst#2 | D18: =+'jobinfo(2)'!C10 -> TBD
A19: =+'jobinfo(2)'!B4 -> Customer Email | B19: =+'jobinfo(2)'!C4 -> tringo68@yahoo.com | C19: =+'jobinfo(2)'!B7 -> cst ph # 2 | D19: =+'jobinfo(2)'!C7 -> TBD
A20: =+signpgs!A14 -> Insurance Co. Name | B20: =+signpgs!B14 -> Allstate Insurance Company | C20: =+'jobinfo(2)'!C27 -> 0 | D20: =+'jobinfo(2)'!C28 -> 0
A22: Greetings : Please find attached the contractual documents for your review and signatures.
A23: Please sign each line indicated by your name.
A24: ALSO please INITIAL each space as indicated in Contract & MOU docs
A25: Upon your approval please print out a copy for your file.
A26: Scan and return a fully signed copy back to us. If this is a challenge for you then please advise us and we will make arrangements to get the signed documents back to us.
A27: Pages 1 -12 are what we need to get started; the remaining pages will be used later in the process.
A28: Re: Insurance Claim Check Processing, Mortgage Co.
A29: Please fill in any missing items with the info that you may have at this time. We will work with you to get all needed info as we move forward.
A30: Of course; if you have ANY questions please give us a call , text or email.
A32: Thank you for your confidence placed in us ; we shall do all within our power to be continually earn and respect that trust.
A34: The following pages 1 -12 are what we need to get started; the remaining pages will be used later in the process.
A35: 1 | B35: =+signpgs!A1 -> ** GENERAL AUTHORIZATION **
B36: gives us permission to talk with your insurance and mortgage company
A37: 2 | B37: =+signpgs!A36 -> EMERGENCY SERVICES WORK AUTHORIZATION
B38: allows us to do the emergency services/mitigation work
A40: 3 thru 6 | B40: =+aob!A5 -> Assignment of Insurance Benefits & Direct Payment Authorization:
B41: Allows us to proceed to work without payment from you !!!!!!!!!!
B42: Or you may enclose payment or provide credit card info
A43: 7 thru 8 | B43: =+signpgs!$A$97 -> CONTRACTOR & HOMEOWNER AGREEMENT
B44: rebuild contract; authorizes us to begin the resoration process on your property
A46: 9 | B46: =+signpgs!$A$188 -> Notice of Right of Recession
B47: 3 days to allow you to cancel contract
A49: 10 | B49: =+signpgs!A218 -> Advance Payment Request
B50: request immediate payment from insurance company
A52: 11 | B52: =+signpgs!A276 -> Customer Consultation & Memorandum of Understanding
B53: details of our work, the paperwork involved and general procedures
A55: 12 | B55: Key Items to the Process
A57: 13 | B57: =+signpgs!A327 -> CLAIMS HISTORY INFO
A59: COMPANY REP. | B59: =B11 -> Joe Jones, PM 216.450.7228 | C59: =C11 -> wsbjoe9@gmail.com
A60: Key Items to the Process
A61: CONTRACTOR & HOMEOWNER AGREEMENT
A62: 16. The Owner and the contractor agree that the contractor shall '“discuss the amount of damage to the consumer’s home, the appropriate replacement, and reasonable cost of replacement with the insurance company.”; as needed. The Contractor agrees to release the owner from any obligation to complete work not covered by the insurance company.
A63: The Owner may choose to pay the contractor for work not covered by insurance proceeds.
A65: Assignment of Insurance Benefits & Direct Payment Authorization:
A66: Essentially the Restoration Company is extending credit to the customer.
A68: I do understand that there will be a large amount of time, research, money, resources, equipment supplies and man-hours spent working (pictures, documentation, inspections, setup) on my estimate to properly present to my insurer.
A69: We are very willing to take the educated calculated risk of having the insurance pay for the restoration work.
A70: We are very willing to invest our following items towards the restoration work on your property;
A71: Time | B71: Materials | C71: Mitigation Services
A72: Money | B72: Resources | C72: Jobsite Protection
A73: Labor | B73: Expertise | C73: Damages Control
A74: Inspection services | C74: Estimating services
A75: Cost analysis /repair specifications, | C75: Testing
A76: Document preparation services | C76: Damages report & discovery
A77: Miscellaneous services rendered | C77: Jobsite visits
A78: Proof of loss supporting documents and scheduling.
A80: CONTRACTOR & HOMEOWNER AGREEMENT
A81: 15. The Owner shall promptly notify the contractor of any funds received and promptly remit to the Contractor;
A82: without delay. The Contractor also agrees to notify the Owner of any funds received on their behalf.
A83: The Owner shall promptly notify and provide the Contractor with a copy of any paperwork received.
A84: The Contractor agrees to wait for payments as disbursed from the insurance and or the escrow company.
A85: The Contractor further agrees to not demand payments from the Owner unless otherwise agreed.
A86: cc: | B86: =C11 -> wsbjoe9@gmail.com
A87: attachments: | B87: CONTRACTOR & HOMEOWNER AGREEMENT
B88: Customer Consultation & Memorandum of Understanding

Sheet quicklist
C1: BASIC SUMMARY OF RESTORATION PROCESS; (Quick version). | D1: =+'jobinfo(2)'!C3 -> Macedonia, OH, USA | F1: DoneDate
A2: JOB | C2: =+'jobinfo(2)'!C1 -> Johnson, Paul & Tamra | D2: Status | E2: %
A3: 1 | B3: Introduction, Analysis & Verification | C3: Introduction, Analysis & Verification | D3: source/reffered by:
C4: Who is the Insurance Company ?!?
A5: POI | C5: Does customer Comprehend Our Role in the process?
C6: Is this an LEGITIMATE COVERED INSURANCE Claim? Or Self Pay ?
C7: IS THE DAMAGE $ MORE THAN THE DEDUCTIBLE?
C8: Do they have coverage; for AOB?
A9: 2 | B9: Contracts & Documentation | C9: Contracts & Documentation
C10: Has Customer been fully advised of Contract Contents?
C11: Has Customer had a full Consultation to Our Terms & Conditions?
A12: DOC | C12: Does Customer FULLY Agree to Our Terms & Conditions? Initials?
C13: Notary Page explained/ Fast track
A14: mou | C14: Company investment (dollars, time ,materials)into their Project?
A15: 3 | C15: Claim Reporting
A16: INS | C16: DOES THE CUSTOMER HAVE THE REQUIRED INFO?
C17: Insurer Mitigation / DMO / CPS Approval Info Sheet
A18: mit | B18: Mitigation & Demolition | C18: Mitigation & Demolition
A19: 4 | C19: Roof & EXT Mitigation TEMPORARY & EMERGENCY REPAIRS
A20: 5 | C20: Contents_ item list_; storage details; security explained?
A21: 6 | C21: HMR / Secondary Damages; Equipment & Electricity $
A22: 7 | C22: Interior Mitigation; household disruption explained? | D22: 0.5
A23: esx | B23: Estimates | C23: Estimates
A24: 8 | C24: Interior Inspection/Scope Form | D24: 0.1
C25: SKETCH/DRAWING;[1] sheet per floor
C26: PICTURES; VIA ENCIRCLE APP
C27: Create Estimates…Rebuild……...REPAIR SPECS & COST ANALYSIS
C28: Mitigation & Demolition
A29: 9 | B29: Insurance Company Meetings | C29: Insurance Company Meetings
A30: adj | C30: Prepare docs for adjuster meeting; Print & bind docs
C31: BE PRESENT WHEN ADJUSTER VISITS The PROPERTY.
A32: 10 | B32: Cashflow
A33: job | C33: General Contractor / Subcontracts
B34: Mitigation & Demolition | C34: Mitigation & Demolition
B35: Rebuild
B36: Contents
B37: Closeout | C37: Closeout

Sheet signpgs
A1: ** GENERAL AUTHORIZATION **
A2: =+'jobinfo(2)'!$C$100 -> All Phase Consulting, LLC
A3: =+'jobinfo(2)'!C$109 -> Providing Cost Estimating & Project Management Services
A4: =+'jobinfo(2)'!$C$101 -> WWW.MYAPCLLC.COM | C4: =+'jobinfo(2)'!$C$102 -> Insured & GA Registered #09073201
A5: ='jobinfo(2)'!$C$107 -> 20810 AURORA RD | B5: =+'jobinfo(2)'!$C$103 -> 375 Rockbridge Road, Suite 172-343 | D5: =+'jobinfo(2)'!$C$105 -> ECI 531 FIFTH AVE,
A6: ='jobinfo(2)'!$C$108 -> BEDFORD,OH 44146 | B6: =+'jobinfo(2)'!$C$104 -> Lilburn, GA, 30047 | D6: =+'jobinfo(2)'!$C$106 -> PELHAM, NY 10803
A7: =+'jobinfo(2)'!$C$110 -> Five Generations of Great Work | C7: =+'jobinfo(2)'!$C$111 -> Five Generations of Pride & Skills
A8: COMPANY REP. | B8: =+'jobinfo(2)'!$C$112 -> Joe Jones, PM 216.450.7228 | C8: =+'jobinfo(2)'!$C$113 -> wsbjoe9@gmail.com
A9: COMPANY REP. #2 | B9: =+'jobinfo(2)'!$C$114 -> 404-446-9060 | C9: =+'jobinfo(2)'!$C$115 -> info@myapcllc.com
A10: Claim # | B10: ='jobinfo(2)'!$C$27 -> 0 | C10: Cst-owner Phone# | D10: ='jobinfo(2)'!$C$5 -> (216) 399-6191
A11: =+'jobinfo(2)'!$B$1 -> Property-Owner Name | B11: =+'jobinfo(2)'!C$1 -> Johnson, Paul & Tamra | C11: Customer Email | D11: ='jobinfo(2)'!$C$4 -> tringo68@yahoo.com
A12: =+'jobinfo(2)'!$B$2 -> Property address: street | B12: =+'jobinfo(2)'!$C$2 -> 9402 Shepard Road | C12: Co-Owner.cst#2 | D12: =+'jobinfo(2)'!$C$6 -> TBD
A13: =+'jobinfo(2)'!$B$3 -> Property city, state, zip | B13: =+'jobinfo(2)'!$C$3 -> Macedonia, OH, USA | C13: cst ph # 2 | D13: =+'jobinfo(2)'!$C$7 -> TBD
A14: =+'jobinfo(2)'!$B$26 -> Insurance Co. Name | B14: =+'jobinfo(2)'!$C$26 -> Allstate Insurance Company | C14: =+'jobinfo(2)'!$B$28 -> policy # | D14: =+'jobinfo(2)'!$C$27 -> 0
A15: =+'jobinfo(2)'!$B$46 -> Insurance Co. Phone | B15: =+'jobinfo(2)'!$C$46 -> (800) 255-7828 | C15: =+'jobinfo(2)'!$C$29 -> 0
A16: =+'jobinfo(2)'!$B$30 -> DESK Adjuster DA | B16: =+'jobinfo(2)'!$C$30 -> 0 | C16: =+'jobinfo(2)'!$B$33 -> DA Email | D16: =+'jobinfo(2)'!$C$33 -> claims@claims.allstate.com
A17: =+'jobinfo(2)'!$B$31 -> DA Phone | B17: =+'jobinfo(2)'!$C$31 -> 888 656.8005 | C17: =+'jobinfo(2)'!$B$32 -> DA Ph. Ext. # | D17: =+'jobinfo(2)'!$C$32 -> 0
A20: Dear Insurance Company/ Mortgage Company and or To Whom It May Concern:
A21: The undersigned property owner agrees to employ | C21: =+$A$2 -> All Phase Consulting, LLC
A22: to assist in the repair of the above mentioned property that was damaged by
A23: =IF(ISBLANK('jobinfo(2)'!C11),"____________________",'jobinfo(2)'!C11) -> WATER | C23: on or about (date). | D23: =IF(ISBLANK('jobinfo(2)'!C12),"__________________________________",'jobinfo(2)'!C12) -> Friday, April 4, 2025
A24: Owners ACKNOWLEDGE as party of interest; | C24: =C21 -> All Phase Consulting, LLC
A25: and will be noted as such on all drafts, correspondence, and communications between the owner, insurer and my mortgage company. I hereby authorize all parties to discuss my account as it relates to the above noted loss and or repairs; as well as the release of draws for all repairs. This applies in full to it's employees / assigns / representatives.
A29: OWNER HEREBY SPECIFICALLY REQUESTS THAT ALL EMS & CPS PAYMENTS BE PAID TO: ; | E29: OWNER HEREBY SPECIFICALLY REQUESTS THAT EMS Mitigation & CPS Packout / Cleaning of
A30: =+$C$24 -> All Phase Consulting, LLC | C30: =+'email cvr'!A13 -> EIN # | D30: =+'email cvr'!B13 -> TIN 83-226 0563 | E30: Personal Property (ONLY) PAYMENTS ; PAYMENTS BE PAID TO REBUILD Items Excluded::
A31: ( REBUILD PAYMENT EXCLUDED AND PAID TO OWNER )
A32: X___________________________________ _____________ | C32: X_ _________________________________ _____________ | D32: =+'jobinfo(2)'!C22 -> Friday, April 4, 2025
A33: =IF(ISBLANK('jobinfo(2)'!C1),"__Property owner Signature________________________________",'jobinfo(2)'!$C$1) -> Johnson, Paul & Tamra | C33: =IF(ISBLANK('jobinfo(2)'!C6),"co-owner Signature______________________________",'jobinfo(2)'!C6) -> TBD
A35: =+$A$186 -> COMPANY REP. | B35: =+B67 -> Joe Jones, PM 216.450.7228 | D35: =+D67 -> wsbjoe9@gmail.com
A36: EMERGENCY SERVICES WORK AUTHORIZATION
A37: =+$A$2 -> All Phase Consulting, LLC
A38: =+A3 -> Providing Cost Estimating & Project Management Services | D38: =+$A$100 -> WWW.MYAPCLLC.COM
A40: =+A5 -> 20810 AURORA RD | B40: =+B5 -> 375 Rockbridge Road, Suite 172-343 | D40: =+D5 -> ECI 531 FIFTH AVE,
A41: =+A6 -> BEDFORD,OH 44146 | B41: =+B6 -> Lilburn, GA, 30047 | D41: =+D6 -> PELHAM, NY 10803
C42: =+$C$104 -> wsbjoe9@gmail.com
A43: =+A8 -> COMPANY REP. | B43: =+B35 -> Joe Jones, PM 216.450.7228 | C43: =+$D$186 -> wsbjoe9@gmail.com
A44: Claim Number: | B44: =+'jobinfo(2)'!C27 -> 0 | C44: =+B14 -> Allstate Insurance Company
A45: =+'jobinfo(2)'!B1 -> Property-Owner Name | B45: =+'jobinfo(2)'!C1 -> Johnson, Paul & Tamra | C45: =+A15 -> Insurance Co. Phone | D45: ='jobinfo(2)'!C31 -> 888 656.8005
A46: =+'jobinfo(2)'!B2 -> Property address: street | B46: =+'jobinfo(2)'!C2 -> 9402 Shepard Road
A47: =+'jobinfo(2)'!B3 -> Property city, state, zip | B47: =+'jobinfo(2)'!C3 -> Macedonia, OH, USA | C47: =+'jobinfo(2)'!B11 -> Cause of Loss | D47: =+A23 -> WATER
A48: =+'jobinfo(2)'!B4 -> Customer Email | B48: =+'jobinfo(2)'!C4 -> tringo68@yahoo.com | C48: =+'jobinfo(2)'!B5 -> Cst-owner Phone# | D48: =+D10 -> (216) 399-6191
B49: =+'jobinfo(2)'!C5 -> (216) 399-6191
A50: AUTHORIZATED ANTIMICROBIAL AGENTS; I understand that in the best judgment of Company, antimicrobial agents maybe used to inhibit the growth of micro-organisms during the drying/restoration process. I have received notice of the use of such. I understand it is beyond the expertise of Company to determine if someone is sensitive to its use and will hold Company harmless for its use. STOP WORK-HOLD HARMLESS. If the Company is not allowed to perform its recommended procedures and/or drying equipment is removed prematurely, I agree to release and hold Company harmless, indemnify Company against all claims or actions.
A53: =+$B$11 -> Johnson, Paul & Tamra | B53: as Owner, do hereby authorize | C53: =+A37 -> All Phase Consulting, LLC
A54: , their Assignee or Representative of and for herein named contractor to enter my property, furnish materials, supply all equipment and perform all labor necessary to preserve and protect my property from further damage. Including evaluation, inventory, storage and or cleaning of contents/personal property.
A55: I understand that I am personally responsible for all sums due to contractor for work related
A56: to LOSS TYPE of damages stated herein; performed at my property listed here.
A57: =+'jobinfo(2)'!C13 -> Interior Repairs LEVEL 1 | C57: =+'jobinfo(2)'!C14 -> Interior Repairs LEVEL 2 | D57: =+'jobinfo(2)'!C15 -> TBD
A58: I hereby assign the insurance rights; as specified herein, benefits, and proceeds under my | E58: I hereby assign the insurance rights; as specified herein, benefits, and proceeds under my
A59: insurance policy for the Emergency /mitigation services to: | C59: =+$A$2 -> All Phase Consulting, LLC | E59: insurance policy for the Emergency /mitigation services to: | G59: =+$A$2 -> All Phase Consulting, LLC
A60: Thus, monies due to named herein contractor are to be released without delay; solely, directly to contractor. | E60: Thus, monies due to named herein contractor are to be released without delay; solely, directly to contractor.
A61: This is payment for emergency and mitigation; for services that have already been performed; consequently the mortgage company has no interest in these specific funds; therefore make direct payment; refrain from including Mortgage Company name on the check. | E61: This is payment for emergency and mitigation; for services that have already been performed; consequently the mortgage company has no interest in these specific funds; therefore make direct payment; refrain from including Mortgage Company name on the check.
A62: OWNER HEREBY REQUESTS PAYMENTS BE PAID TO: | C62: =+C59 -> All Phase Consulting, LLC | D62: =+D30 -> TIN 83-226 0563 | E62: OWNER HEREBY REQUESTS PAYMENTS BE PAID TO: | G62: =+'email cvr'!B13 -> TIN 83-226 0563 | H62: =+C53 -> All Phase Consulting, LLC
A63: I/We select the option of overnight shipping for expedited delivery. | D63: =+'email cvr'!D13 -> FEDEX # 9836-2151-1
A64: This is a LEGALLY BINDING, Irrevocable Document; Fully Enforceable. Please read carefully
A65: =+$A$32 -> X___________________________________ _____________ | C65: =+$C$32 -> X_ _________________________________ _____________ | D65: =+$D$32 -> Friday, April 4, 2025
A66: =+B45 -> Johnson, Paul & Tamra | C66: =+C185 -> TBD
A67: =+$A$186 -> COMPANY REP. | B67: =+'jobinfo(2)'!C112 -> Joe Jones, PM 216.450.7228 | C67: =C35 -> 0 | D67: =+'jobinfo(2)'!C113 -> wsbjoe9@gmail.com
A68: “Assignments of Insurance Rights.” Includes Assignment of Benefits, the Right to Appraisal, the Rights to Sue and Direction to Pay. | J68: Assignment of Insurance Benefits & Direct Payment Authorization:
A69: =+'jobinfo(2)'!$C$100 -> All Phase Consulting, LLC
A70: =+'jobinfo(2)'!C$109 -> Providing Cost Estimating & Project Management Services
A71: =+'jobinfo(2)'!$C$101 -> WWW.MYAPCLLC.COM | C71: =+'jobinfo(2)'!$C$102 -> Insured & GA Registered #09073201
A72: ='jobinfo(2)'!C107 -> 20810 AURORA RD | B72: =+'jobinfo(2)'!$C$103 -> 375 Rockbridge Road, Suite 172-343 | D72: =+'jobinfo(2)'!$C$105 -> ECI 531 FIFTH AVE,
A73: ='jobinfo(2)'!C108 -> BEDFORD,OH 44146 | B73: =+'jobinfo(2)'!$C$104 -> Lilburn, GA, 30047 | D73: =+'jobinfo(2)'!$C$106 -> PELHAM, NY 10803
A74: =+'jobinfo(2)'!$C$110 -> Five Generations of Great Work | C74: =+'jobinfo(2)'!$C$111 -> Five Generations of Pride & Skills
A75: COMPANY REP. | B75: =+'jobinfo(2)'!$C$112 -> Joe Jones, PM 216.450.7228 | C75: =+'jobinfo(2)'!$C$113 -> wsbjoe9@gmail.com
A76: COMPANY REP. #2 | B76: =+'jobinfo(2)'!$C$114 -> 404-446-9060 | C76: =+'jobinfo(2)'!$C$115 -> info@myapcllc.com
A77: =+'jobinfo(2)'!B26 -> Insurance Co. Name | B77: =+'jobinfo(2)'!C26 -> Allstate Insurance Company | C77: =+'jobinfo(2)'!B27 -> Claim # | D77: =IF(ISBLANK('jobinfo(2)'!C27),"________________________________",'jobinfo(2)'!$C$27) -> 0
A78: =+A45 -> Property-Owner Name | B78: =+B45 -> Johnson, Paul & Tamra | C78: =+'jobinfo(2)'!B11 -> Cause of Loss | D78: =+'jobinfo(2)'!C11 -> WATER
A79: =+A46 -> Property address: street | B79: =+B46 -> 9402 Shepard Road | C79: =+'jobinfo(2)'!B12 -> date of loss | D79: =+'jobinfo(2)'!C12 -> Friday, April 4, 2025
A80: =+A47 -> Property city, state, zip | B80: =+B47 -> Macedonia, OH, USA | C80: =+'jobinfo(2)'!B13 -> rebuild type 1 | D80: =+'jobinfo(2)'!C13 -> Interior Repairs LEVEL 1
A81: =+A48 -> Customer Email | B81: =+B48 -> tringo68@yahoo.com | C81: =+'jobinfo(2)'!B14 -> rebuild type 2 | D81: =+'jobinfo(2)'!C14 -> Interior Repairs LEVEL 2
A82: =+C48 -> Cst-owner Phone# | B82: =+B49 -> (216) 399-6191 | C82: =+'jobinfo(2)'!B15 -> rebuild type 3 | D82: =+'jobinfo(2)'!C15 -> TBD
A84: ASSIGNMENT OF INSURANCE BENEFITS; I, | C84: =+'jobinfo(2)'!C1 -> Johnson, Paul & Tamra
A85: ,as Owner, do hereby assign any and all insurance rights, benefits, proceeds and any causes of action, including APPRAISAL AND DEMAND Thereof, under applicable insurance policies to
A86: =+A69 -> All Phase Consulting, LLC | C86: =+C30 -> EIN # | D86: =+D30 -> TIN 83-226 0563
A87: their Assignee or Representative of and for herein named contractor for service rendered or to be rendered by Company. In this regard,I make this assignment in consideration of Company’s agreement to perform services and supply materials and otherwise perform its obligations under this contract, including not requiring full payment at the time of service. I also hereby direct my insurance carrier(s) to release any and all information requested by Company, for the direct purpose of obtaining actual benefits to be paid for services rendered or to be rendered.
A88: DIRECT PAYMENT AUTHORIZATION & PAYMENT TERMS
A89: I also hereby authorize and unequivocally instruct direct payment of any benefits or proceeds to Company.
A90: Payment terms are net upon completion. Late fees 1.5% monthly and reimbursement for costs of collection.
A91: I/We select the option of overnight shipping for expedited delivery.
A95: X X | D95: =+D32 -> Friday, April 4, 2025
A96: =+'jobinfo(2)'!C1 -> Johnson, Paul & Tamra | B96: =+'jobinfo(2)'!C6 -> TBD | C96: =C67 -> 0
A97: CONTRACTOR & HOMEOWNER AGREEMENT
A98: =+'jobinfo(2)'!$C$100 -> All Phase Consulting, LLC
A99: =+'jobinfo(2)'!C$109 -> Providing Cost Estimating & Project Management Services
A100: =+'jobinfo(2)'!$C$101 -> WWW.MYAPCLLC.COM | C100: =+'jobinfo(2)'!$C$102 -> Insured & GA Registered #09073201
A101: =+'jobinfo(2)'!$C$107 -> 20810 AURORA RD | B101: =+'jobinfo(2)'!$C$103 -> 375 Rockbridge Road, Suite 172-343 | D101: =+'jobinfo(2)'!$C$105 -> ECI 531 FIFTH AVE,
A102: =+'jobinfo(2)'!$C$108 -> BEDFORD,OH 44146 | B102: =+'jobinfo(2)'!$C$104 -> Lilburn, GA, 30047 | D102: =+'jobinfo(2)'!$C$106 -> PELHAM, NY 10803
A103: =+'jobinfo(2)'!$C$110 -> Five Generations of Great Work | C103: =+'jobinfo(2)'!$C$111 -> Five Generations of Pride & Skills
A104: COMPANY REP. | B104: =+'jobinfo(2)'!$C$112 -> Joe Jones, PM 216.450.7228 | C104: =+'jobinfo(2)'!$C$113 -> wsbjoe9@gmail.com
A105: COMPANY REP. #2 | B105: =+'jobinfo(2)'!$C$114 -> 404-446-9060 | C105: =+'jobinfo(2)'!$C$115 -> info@myapcllc.com
A106: =+B11 -> Johnson, Paul & Tamra | B106: =+B12 -> 9402 Shepard Road | C106: =+B13 -> Macedonia, OH, USA | D106: as OWNER. And
A108: =+A98 -> All Phase Consulting, LLC | C108: as CONTRACTOR. | D108: Concerning
A110: RELATED DAMAGES : | B110: =+$A$23 -> WATER | C110: on or about | D110: =+D23 -> Friday, April 4, 2025
A112: The said parties, for the considerations hereinafter mentioned, hereby agree to the following:
A114: 1. The CONTRACTOR agrees to provide all of the labor and materials required to perform the following
A115: work as per attachment; ( ____) pages. subject to adjustment based upon mutually agreed scope of work.
A116: =+A57 -> Interior Repairs LEVEL 1 | B116: =+C57 -> Interior Repairs LEVEL 2 | C116: =+D57 -> TBD | D116: =+#REF! -> #REF!
A118: 2. The OWNER hereby agrees to pay the CONTRACTOR, for the aforesaid materials & labor, $___ _________
...

Sheet cst o&p to ins co.
A1: ='jobinfo(2)'!C27 -> 0
A2: ='jobinfo(2)'!C1 -> Johnson, Paul & Tamra
A3: ='jobinfo(2)'!C2 -> 9402 Shepard Road
A4: ='jobinfo(2)'!C3 -> Macedonia, OH, USA
A6: To whom it may concern,
A8: After discussing in depth the damages and necessary repairs per my claim with my Project Manager/Contractor of choice, I have been made aware of what needs to be done to restore my property back to the condition before the loss.
A10: My Project Manager/Contractor has educated me on what type of labor, materials, scheduling and supervision of crews will be necessary.
A12: There will also be an investment of time coordinating and managing the project that will be required due to the multiple trades and trade-specific subcontractors involved.
A14: Understanding the time, effort, and supervision necessary for the restoration of my home, I do not have the time nor the resources to coordinate or manage this project to completion.
A16: Therefore, this letter is to inform you that my Project Manager/Contractor of choice, shall be managing, coordinating and supervising the entirety of my property repairs from start to finish.
A18: I understand what “overhead and profit” is and I understand my policy’s premium includes coverage for O&P as well as material tax. Upon examination of my homeowner’s policy, I have confirmed that I have a replacement cost policy on my home and therefore overhead and profit should be included in my estimate due to the following reasons:
A19: 1. My Project Manager/Contractor of choice, is qualified, experienced and has many references.
A20: 2. Being a Project Manager/Contractor must include overhead and profit to provide their contracting services to stay in business, as they have expenses and overhead above and beyond the normal expenses of a laborer who does the work themselves.
A21: 3. As a Project Manager/Contractor coordinating the trades and overseeing the work, they have overhead costs not connected to specific line items on the estimate that must be included and factored in for all sub-contracted trades.
A22: 4. Multiple trades are involved and I feel it would be impractical/unfair to require me to coordinate these trades without my Project Manager/Contractor’s assistance, as it is not my area of expertise.
A23: 5. I would like my Project Manager/Contractor to locate, choose and hire skilled and qualified tradesman and coordinating/scheduling/supervising the work to be done
A25: Included is the actual replacement cost for the damages to my home. Please speak directly with my Project Manager/Contractor to finalize my restoration items.
A27: ='jobinfo(2)'!C100 -> All Phase Consulting, LLC
A28: ='jobinfo(2)'!C101 -> WWW.MYAPCLLC.COM
A29: ='jobinfo(2)'!C103 -> 375 Rockbridge Road, Suite 172-343
A30: ='jobinfo(2)'!C104 -> Lilburn, GA, 30047
A31: ='jobinfo(2)'!C105 -> ECI 531 FIFTH AVE,
A32: ='jobinfo(2)'!C106 -> PELHAM, NY 10803
A33: ='jobinfo(2)'!C107 -> 20810 AURORA RD
A34: ='jobinfo(2)'!C108 -> BEDFORD,OH 44146
A35: ='jobinfo(2)'!C109 -> Providing Cost Estimating & Project Management Services
A36: ='jobinfo(2)'!C110 -> Five Generations of Great Work
A37: ='jobinfo(2)'!C111 -> Five Generations of Pride & Skills
A38: ='jobinfo(2)'!C112 -> Joe Jones, PM 216.450.7228
A39: ='jobinfo(2)'!C113 -> wsbjoe9@gmail.com
A40: ='jobinfo(2)'!C114 -> 404-446-9060
... A42: ='jobinfo(2)'!C116 -> TIN 83-226 0563
A43: ='jobinfo(2)'!C118 -> 0

Sheet jobinfo(2)
A1: Customer | B1: Property-Owner Name | C1: ='[2]jobinfo(2)'!$C$1 -> Johnson, Paul & Tamra | D1: ='[2]jobinfo(2)'!$D$1 -> 0 | E1: ='[2]jobinfo(2)'!$E$1 -> 0 | F1: ='[2]jobinfo(2)'!$F$1 -> 0 | G1: ='[2]jobinfo(2)'!$G$1 -> 0 | H1: ='[2]jobinfo(2)'!$H$1 -> 0 | I1: ='[2]jobinfo(2)'!$I$1 -> 0 | J1: ='[2]jobinfo(2)'!$J$1 -> 0 | K1: Property-Owner Name | L1: SMITH, JANET
B2: Property address: street | C2: ='[2]jobinfo(2)'!$C$2 -> 9402 Shepard Road | D2: ='[2]jobinfo(2)'!$D$2 -> 0 | E2: ='[2]jobinfo(2)'!$E$2 -> 0 | F2: ='[2]jobinfo(2)'!$F$2 -> 0 | G2: ='[2]jobinfo(2)'!$G$2 -> 0 | H2: ='[2]jobinfo(2)'!$H$2 -> 0 | I2: ='[2]jobinfo(2)'!$I$2 -> 0 | J2: ='[2]jobinfo(2)'!$J$2 -> 0 | K2: Property address: street | L2: 216) 403-7739
B3: Property city, state, zip | C3: ='[2]jobinfo(2)'!$C$3 -> Macedonia, OH, USA | D3: ='[2]jobinfo(2)'!$D$3 -> 0 | E3: ='[2]jobinfo(2)'!$E$3 -> 0 | F3: ='[2]jobinfo(2)'!$F$3 -> 0 | G3: ='[2]jobinfo(2)'!$G$3 -> 0 | H3: ='[2]jobinfo(2)'!$H$3 -> 0 | I3: ='[2]jobinfo(2)'!$I$3 -> 0 | J3: ='[2]jobinfo(2)'!$J$3 -> 0 | K3: Property city, state, zip | L3: Cleveland, OH
B4: Customer Email | C4: ='[2]jobinfo(2)'!$C$4 -> tringo68@yahoo.com | D4: ='[2]jobinfo(2)'!$D$4 -> 0 | E4: ='[2]jobinfo(2)'!$E$4 -> 0 | F4: ='[2]jobinfo(2)'!$F$4 -> 0 | G4: ='[2]jobinfo(2)'!$G$4 -> 0 | H4: ='[2]jobinfo(2)'!$H$4 -> 0 | I4: ='[2]jobinfo(2)'!$I$4 -> 0 | J4: ='[2]jobinfo(2)'!$J$4 -> 0 | K4: Customer Email | L4: SMITH, JANET
B5: Cst-owner Phone# | C5: ='[2]jobinfo(2)'!$C$5 -> (216) 399-6191 | D5: ='[2]jobinfo(2)'!$D$5 -> 0 | E5: ='[2]jobinfo(2)'!$E$5 -> 0 | F5: ='[2]jobinfo(2)'!$F$5 -> 0 | G5: ='[2]jobinfo(2)'!$G$5 -> 0 | H5: ='[2]jobinfo(2)'!$H$5 -> 0 | I5: ='[2]jobinfo(2)'!$I$5 -> 0 | K5: Cst-owner Phone# | L5: (216) 403-7739
B6: Co-Owner.cst#2 | C6: ='[2]jobinfo(2)'!$C$6 -> TBD | D6: ='[2]jobinfo(2)'!$D$6 -> 0 | E6: ='[2]jobinfo(2)'!$E$6 -> 0 | F6: ='[2]jobinfo(2)'!$F$6 -> 0 | G6: ='[2]jobinfo(2)'!$G$6 -> 0 | H6: ='[2]jobinfo(2)'!$H$6 -> 0 | I6: ='[2]jobinfo(2)'!$I$6 -> 0 | J6: ='[2]jobinfo(2)'!$J$6 -> 0 | K6: Co-Owner.cst#2 | L6: TERRANCE DAVIS
B7: cst ph # 2 | C7: ='[2]jobinfo(2)'!$C$7 -> TBD | D7: ='[2]jobinfo(2)'!$D$7 -> 0 | E7: ='[2]jobinfo(2)'!$E$7 -> 0 | F7: ='[2]jobinfo(2)'!$F$7 -> 0 | G7: ='[2]jobinfo(2)'!$G$7 -> 0 | H7: ='[2]jobinfo(2)'!$H$7 -> 0 | I7: ='[2]jobinfo(2)'!$I$7 -> 0 | J7: ='[2]jobinfo(2)'!$J$7 -> 0 | K7: cst ph # 2 | L7: 2163185051
B8: Cst address # 2 | C8: ='[2]jobinfo(2)'!$C$8 -> TBD | D8: ='[2]jobinfo(2)'!$D$8 -> 0 | E8: ='[2]jobinfo(2)'!$E$8 -> 0 | F8: ='[2]jobinfo(2)'!$F$8 -> 0 | G8: ='[2]jobinfo(2)'!$G$8 -> 0 | H8: ='[2]jobinfo(2)'!$H$8 -> 0 | I8: ='[2]jobinfo(2)'!$I$8 -> 0 | J8: ='[2]jobinfo(2)'!$J$8 -> 0 | K8: Cst address # 2 | L8: TBD
B9: city, state-cst#2 | C9: ='[2]jobinfo(2)'!$C$9 -> TBD | D9: ='[2]jobinfo(2)'!$D$9 -> 0 | E9: ='[2]jobinfo(2)'!$E$9 -> 0 | F9: ='[2]jobinfo(2)'!$F$9 -> 0 | G9: ='[2]jobinfo(2)'!$G$9 -> 0 | H9: ='[2]jobinfo(2)'!$H$9 -> 0 | I9: ='[2]jobinfo(2)'!$I$9 -> 0 | J9: ='[2]jobinfo(2)'!$J$9 -> 0 | K9: city, state-cst#2 | L9: TBD
B10: email-cst #2 | C10: ='[2]jobinfo(2)'!$C$10 -> TBD | D10: ='[2]jobinfo(2)'!$D$10 -> 0 | E10: ='[2]jobinfo(2)'!$E$10 -> 0 | F10: ='[2]jobinfo(2)'!$F$10 -> 0 | G10: ='[2]jobinfo(2)'!$G$10 -> 0 | H10: ='[2]jobinfo(2)'!$H$10 -> 0 | I10: ='[2]jobinfo(2)'!$I$10 -> 0 | J10: ='[2]jobinfo(2)'!$J$10 -> 0 | K10: email-cst #2 | L10: TBD
A11: Loss Info | B11: Cause of Loss | C11: ='[2]jobinfo(2)'!$C$11 -> WATER | D11: ='[2]jobinfo(2)'!$D$11 -> 0 | E11: ='[2]jobinfo(2)'!$E$11 -> 0 | F11: ='[2]jobinfo(2)'!$F$11 -> 0 | G11: ='[2]jobinfo(2)'!$G$11 -> 0 | H11: ='[2]jobinfo(2)'!$H$11 -> 0 | I11: ='[2]jobinfo(2)'!$I$11 -> 0 | J11: ='[2]jobinfo(2)'!$J$11 -> 0 | K11: Cause of Loss | L11: WATER
B12: date of loss | C12: ='[2]jobinfo(2)'!$C$12 -> Friday, April 4, 2025 | D12: ='[2]jobinfo(2)'!$D$12 -> 0 | E12: ='[2]jobinfo(2)'!$E$12 -> 0 | F12: ='[2]jobinfo(2)'!$F$12 -> 0 | G12: ='[2]jobinfo(2)'!$G$12 -> 0 | H12: ='[2]jobinfo(2)'!$H$12 -> 0 | I12: ='[2]jobinfo(2)'!$I$12 -> 0 | J12: ='[2]jobinfo(2)'!$J$12 -> 0 | K12: date of loss | L12: TBD
B13: rebuild type 1 | C13: ='[2]jobinfo(2)'!$C$13 -> Interior Repairs LEVEL 1 | D13: ='[2]jobinfo(2)'!$D$13 -> 0 | E13: ='[2]jobinfo(2)'!$E$13 -> 0 | F13: ='[2]jobinfo(2)'!$F$13 -> 0 | G13: ='[2]jobinfo(2)'!$G$13 -> 0 | H13: ='[2]jobinfo(2)'!$H$13 -> 0 | I13: ='[2]jobinfo(2)'!$I$13 -> 0 | J13: ='[2]jobinfo(2)'!$J$13 -> 0 | K13: rebuild type 1 | L13: Interior Repairs LEVEL 1 &2
B14: rebuild type 2 | C14: ='[2]jobinfo(2)'!$C$14 -> Interior Repairs LEVEL 2 | D14: ='[2]jobinfo(2)'!$D$14 -> 0 | E14: ='[2]jobinfo(2)'!$E$14 -> 0 | F14: ='[2]jobinfo(2)'!$F$14 -> 0 | G14: ='[2]jobinfo(2)'!$G$14 -> 0 | H14: ='[2]jobinfo(2)'!$H$14 -> 0 | I14: ='[2]jobinfo(2)'!$I$14 -> 0 | J14: ='[2]jobinfo(2)'!$J$14 -> 0 | K14: rebuild type 2
B15: rebuild type 3 | C15: ='[2]jobinfo(2)'!$C$15 -> TBD | D15: ='[2]jobinfo(2)'!$D$15 -> 0 | E15: ='[2]jobinfo(2)'!$E$15 -> 0 | F15: ='[2]jobinfo(2)'!$F$15 -> 0 | G15: ='[2]jobinfo(2)'!$G$15 -> 0 | H15: ='[2]jobinfo(2)'!$H$15 -> 0 | I15: ='[2]jobinfo(2)'!$I$15 -> 0 | J15: ='[2]jobinfo(2)'!$J$15 -> 0 | K15: rebuild type 3
B16: DEMO | C16: ='[2]jobinfo(2)'!$C$16 -> Y | D16: ='[2]jobinfo(2)'!$D$16 -> 0 | E16: ='[2]jobinfo(2)'!$E$16 -> 0 | F16: ='[2]jobinfo(2)'!$F$16 -> 0 | G16: ='[2]jobinfo(2)'!$G$16 -> 0 | H16: ='[2]jobinfo(2)'!$H$16 -> 0 | I16: ='[2]jobinfo(2)'!$I$16 -> 0 | J16: ='[2]jobinfo(2)'!$J$16 -> 0 | K16: DEMO | L16: Y
B17: Mitigation | C17: ='[2]jobinfo(2)'!$C$17 -> Y | D17: ='[2]jobinfo(2)'!$D$17 -> 0 | E17: ='[2]jobinfo(2)'!$E$17 -> 0 | F17: ='[2]jobinfo(2)'!$F$17 -> 0 | G17: ='[2]jobinfo(2)'!$G$17 -> 0 | H17: ='[2]jobinfo(2)'!$H$17 -> 0 | I17: ='[2]jobinfo(2)'!$I$17 -> 0 | J17: ='[2]jobinfo(2)'!$J$17 -> 0 | K17: Mitigation | L17: Y
B18: Other Structures | C18: ='[2]jobinfo(2)'!$C$18 -> N | D18: ='[2]jobinfo(2)'!$D$18 -> 0 | E18: ='[2]jobinfo(2)'!$E$18 -> 0 | F18: ='[2]jobinfo(2)'!$F$18 -> 0 | G18: ='[2]jobinfo(2)'!$G$18 -> 0 | H18: ='[2]jobinfo(2)'!$H$18 -> 0 | I18: ='[2]jobinfo(2)'!$I$18 -> 0 | J18: ='[2]jobinfo(2)'!$J$18 -> 0 | K18: Other Structures | L18: NA
A19: CPS | B19: Replacement | C19: ='[2]jobinfo(2)'!$C$19 -> Y | D19: ='[2]jobinfo(2)'!$D$19 -> 0 | E19: ='[2]jobinfo(2)'!$E$19 -> 0 | F19: ='[2]jobinfo(2)'!$F$19 -> 0 | G19: ='[2]jobinfo(2)'!$G$19 -> 0 | H19: ='[2]jobinfo(2)'!$H$19 -> 0 | I19: ='[2]jobinfo(2)'!$I$19 -> 0 | J19: ='[2]jobinfo(2)'!$J$19 -> 0 | K19: Replacement | L19: Y
B20: CPS / CLN / CON/ CGN | C20: ='[2]jobinfo(2)'!$C$20 -> Y | D20: ='[2]jobinfo(2)'!$D$20 -> 0 | E20: ='[2]jobinfo(2)'!$E$20 -> 0 | F20: ='[2]jobinfo(2)'!$F$20 -> 0 | G20: ='[2]jobinfo(2)'!$G$20 -> 0 | H20: ='[2]jobinfo(2)'!$H$20 -> 0 | I20: ='[2]jobinfo(2)'!$I$20 -> 0 | J20: ='[2]jobinfo(2)'!$J$20 -> 0 | K20: CPS / CLN / CON/ CGN | L20: Y
B21: Year Built | C21: ='[2]jobinfo(2)'!$C$21 -> POST 1978 | D21: ='[2]jobinfo(2)'!$D$21 -> 0 | E21: ='[2]jobinfo(2)'!$E$21 -> 0 | F21: ='[2]jobinfo(2)'!$F$21 -> 0 | G21: ='[2]jobinfo(2)'!$G$21 -> 0 | H21: ='[2]jobinfo(2)'!$H$21 -> 0 | I21: ='[2]jobinfo(2)'!$I$21 -> 0 | J21: ='[2]jobinfo(2)'!$J$21 -> 0 | K21: Year Built | L21: PRE 1978
B22: Contract Date | C22: ='[2]jobinfo(2)'!$C$22 -> Friday, April 4, 2025 | D22: ='[2]jobinfo(2)'!$D$22 -> 0 | E22: ='[2]jobinfo(2)'!$E$22 -> 0 | F22: ='[2]jobinfo(2)'!$F$22 -> 0 | G22: ='[2]jobinfo(2)'!$G$22 -> 0 | H22: ='[2]jobinfo(2)'!$H$22 -> 0 | I22: ='[2]jobinfo(2)'!$I$22 -> 0 | J22: ='[2]jobinfo(2)'!$J$22 -> 0 | K22: Contract Date | L22: TBD
B23: Loss of use/ ALE | C23: ='[2]jobinfo(2)'!$C$23 -> Y | D23: ='[2]jobinfo(2)'!$D$23 -> 0 | E23: ='[2]jobinfo(2)'!$E$23 -> 0 | F23: ='[2]jobinfo(2)'!$F$23 -> 0 | G23: ='[2]jobinfo(2)'!$G$23 -> 0 | H23: ='[2]jobinfo(2)'!$H$23 -> 0 | I23: ='[2]jobinfo(2)'!$I$23 -> 0 | J23: ='[2]jobinfo(2)'!$J$23 -> 0 | K23: Loss of use/ ALE | L23: NA
B24: Breathing issue | C24: ='[2]jobinfo(2)'!$C$24 -> TBD | D24: ='[2]jobinfo(2)'!$D$24 -> 0 | E24: ='[2]jobinfo(2)'!$E$24 -> 0 | F24: ='[2]jobinfo(2)'!$F$24 -> 0 | G24: ='[2]jobinfo(2)'!$G$24 -> 0 | H24: ='[2]jobinfo(2)'!$H$24 -> 0 | I24: ='[2]jobinfo(2)'!$I$24 -> 0 | J24: ='[2]jobinfo(2)'!$J$24 -> 0 | K24: Breathing issue | L24: TBD
B25: HMR | C25: ='[2]jobinfo(2)'!$C$25 -> TBD | D25: ='[2]jobinfo(2)'!$D$25 -> 0 | E25: ='[2]jobinfo(2)'!$E$25 -> 0 | F25: ='[2]jobinfo(2)'!$F$25 -> 0 | G25: ='[2]jobinfo(2)'!$G$25 -> 0 | H25: ='[2]jobinfo(2)'!$H$25 -> 0 | I25: ='[2]jobinfo(2)'!$I$25 -> 0 | J25: ='[2]jobinfo(2)'!$J$25 -> 0 | K25: HMR | L25: TBD
B26: Insurance Co. Name | C26: ='[2]jobinfo(2)'!$C$26 -> Allstate Insurance Company | D26: ='[2]jobinfo(2)'!$D$26 -> 0 | E26: ='[2]jobinfo(2)'!$E$26 -> 0 | F26: ='[2]jobinfo(2)'!$F$26 -> 0 | G26: ='[2]jobinfo(2)'!$G$26 -> 0 | H26: ='[2]jobinfo(2)'!$H$26 -> 0 | I26: ='[2]jobinfo(2)'!$I$26 -> 0 | J26: ='[2]jobinfo(2)'!$J$26 -> 0 | K26: Insurance Co. Name | L26: TBD
A27: Insurance Co. | B27: Claim # | C27: ='[2]jobinfo(2)'!$C$27 -> 0 | D27: ='[2]jobinfo(2)'!$D$27 -> 0 | E27: ='[2]jobinfo(2)'!$E$27 -> 0 | F27: ='[2]jobinfo(2)'!$F$27 -> 0 | G27: ='[2]jobinfo(2)'!$G$27 -> 0 | H27: ='[2]jobinfo(2)'!$H$27 -> 0 | I27: ='[2]jobinfo(2)'!$I$27 -> 0 | J27: ='[2]jobinfo(2)'!$J$27 -> 0 | K27: Claim # | L27: CLM
B28: policy # | C28: ='[2]jobinfo(2)'!$C$28 -> 0 | D28: ='[2]jobinfo(2)'!$D$28 -> 0 | E28: ='[2]jobinfo(2)'!$E$28 -> 0 | F28: ='[2]jobinfo(2)'!$F$28 -> 0 | G28: ='[2]jobinfo(2)'!$G$28 -> 0 | H28: ='[2]jobinfo(2)'!$H$28 -> 0 | I28: ='[2]jobinfo(2)'!$I$28 -> 0 | J28: ='[2]jobinfo(2)'!$J$28 -> 0 | K28: policy # | L28: PL
B29: Email INS. co. | C29: ='[2]jobinfo(2)'!$C$29 -> 0 | D29: ='[2]jobinfo(2)'!$D$29 -> 0 | E29: ='[2]jobinfo(2)'!$E$29 -> 0 | F29: ='[2]jobinfo(2)'!$F$29 -> 0 | G29: ='[2]jobinfo(2)'!$G$29 -> 0 | H29: ='[2]jobinfo(2)'!$H$29 -> 0 | I29: ='[2]jobinfo(2)'!$I$29 -> 0 | J29: ='[2]jobinfo(2)'!$J$29 -> 0 | K29: Email INS. co. | L29: TBD
B30: DESK Adjuster DA | C30: ='[2]jobinfo(2)'!$C$30 -> 0 | D30: ='[2]jobinfo(2)'!$D$30 -> 0 | E30: ='[2]jobinfo(2)'!$E$30 -> 0 | F30: ='[2]jobinfo(2)'!$F$30 -> 0 | G30: ='[2]jobinfo(2)'!$G$30 -> 0 | H30: ='[2]jobinfo(2)'!$H$30 -> 0 | I30: ='[2]jobinfo(2)'!$I$30 -> 0 | J30: ='[2]jobinfo(2)'!$J$30 -> 0 | K30: DESK Adjuster DA | L30: TBD
B31: DA Phone | C31: ='[2]jobinfo(2)'!$C$31 -> 888 656.8005 | D31: ='[2]jobinfo(2)'!$D$31 -> 0 | E31: ='[2]jobinfo(2)'!$E$31 -> 0 | F31: ='[2]jobinfo(2)'!$F$31 -> 0 | G31: ='[2]jobinfo(2)'!$G$31 -> 0 | H31: ='[2]jobinfo(2)'!$H$31 -> 0 | I31: ='[2]jobinfo(2)'!$I$31 -> 0 | J31: ='[2]jobinfo(2)'!$J$31 -> 0 | K31: DA Phone | L31: TBD
B32: DA Ph. Ext. # | C32: ='[2]jobinfo(2)'!$C$32 -> 0 | D32: ='[2]jobinfo(2)'!$D$32 -> 0 | E32: ='[2]jobinfo(2)'!$E$32 -> 0 | F32: ='[2]jobinfo(2)'!$F$32 -> 0 | G32: ='[2]jobinfo(2)'!$G$32 -> 0 | H32: ='[2]jobinfo(2)'!$H$32 -> 0 | I32: ='[2]jobinfo(2)'!$I$32 -> 0 | J32: ='[2]jobinfo(2)'!$J$32 -> 0 | K32: DA Ph. Ext. # | L32: TBD
B33: DA Email | C33: ='[2]jobinfo(2)'!$C$33 -> claims@claims.allstate.com | D33: ='[2]jobinfo(2)'!$D$33 -> 0 | E33: ='[2]jobinfo(2)'!$E$33 -> 0 | F33: ='[2]jobinfo(2)'!$F$33 -> 0 | G33: ='[2]jobinfo(2)'!$G$33 -> 0 | H33: ='[2]jobinfo(2)'!$H$33 -> 0 | I33: ='[2]jobinfo(2)'!$I$33 -> 0 | J33: ='[2]jobinfo(2)'!$J$33 -> 0 | K33: DA Email | L33: TBD
B34: Field Adjuster Name | C34: ='[2]jobinfo(2)'!$C$34 -> TBD | D34: ='[2]jobinfo(2)'!$D$34 -> 0 | E34: ='[2]jobinfo(2)'!$E$34 -> 0 | F34: ='[2]jobinfo(2)'!$F$34 -> 0 | G34: ='[2]jobinfo(2)'!$G$34 -> 0 | H34: ='[2]jobinfo(2)'!$H$34 -> 0 | I34: ='[2]jobinfo(2)'!$I$34 -> 0 | J34: ='[2]jobinfo(2)'!$J$34 -> 0 | K34: Field Adjuster Name | L34: TBD
B35: Phone # field adj | C35: ='[2]jobinfo(2)'!$C$35 -> TBD | D35: ='[2]jobinfo(2)'!$D$35 -> 0 | E35: ='[2]jobinfo(2)'!$E$35 -> 0 | F35: ='[2]jobinfo(2)'!$F$35 -> 0 | G35: ='[2]jobinfo(2)'!$G$35 -> 0 | H35: ='[2]jobinfo(2)'!$H$35 -> 0 | I35: ='[2]jobinfo(2)'!$I$35 -> 0 | J35: ='[2]jobinfo(2)'!$J$35 -> 0 | K35: Phone # field adj | L35: TBD
B36: Field adj email | C36: ='[2]jobinfo(2)'!$C$36 -> TBD | D36: ='[2]jobinfo(2)'!$D$36 -> 0 | E36: ='[2]jobinfo(2)'!$E$36 -> 0 | F36: ='[2]jobinfo(2)'!$F$36 -> 0 | G36: ='[2]jobinfo(2)'!$G$36 -> 0 | H36: ='[2]jobinfo(2)'!$H$36 -> 0 | I36: ='[2]jobinfo(2)'!$I$36 -> 0 | J36: ='[2]jobinfo(2)'!$J$36 -> 0 | K36: Field adj email | L36: TBD
B37: adj contents | C37: ='[2]jobinfo(2)'!$C$37 -> TBD | D37: ='[2]jobinfo(2)'!$D$37 -> 0 | E37: ='[2]jobinfo(2)'!$E$37 -> 0 | F37: ='[2]jobinfo(2)'!$F$37 -> 0 | G37: ='[2]jobinfo(2)'!$G$37 -> 0 | H37: ='[2]jobinfo(2)'!$H$37 -> 0 | I37: ='[2]jobinfo(2)'!$I$37 -> 0 | J37: ='[2]jobinfo(2)'!$J$37 -> 0 | K37: adj contents | L37: TBD
B38: adj CPS phone # | C38: ='[2]jobinfo(2)'!$C$38 -> TBD | D38: ='[2]jobinfo(2)'!$D$38 -> 0 | E38: ='[2]jobinfo(2)'!$E$38 -> 0 | F38: ='[2]jobinfo(2)'!$F$38 -> 0 | G38: ='[2]jobinfo(2)'!$G$38 -> 0 | H38: ='[2]jobinfo(2)'!$H$38 -> 0 | I38: ='[2]jobinfo(2)'!$I$38 -> 0 | J38: ='[2]jobinfo(2)'!$J$38 -> 0 | K38: adj CPS phone # | L38: TBD
B39: adj CPS email | C39: ='[2]jobinfo(2)'!$C$39 -> TBD | D39: ='[2]jobinfo(2)'!$D$39 -> 0 | E39: ='[2]jobinfo(2)'!$E$39 -> 0 | F39: ='[2]jobinfo(2)'!$F$39 -> 0 | G39: ='[2]jobinfo(2)'!$G$39 -> 0 | H39: ='[2]jobinfo(2)'!$H$39 -> 0 | I39: ='[2]jobinfo(2)'!$I$39 -> 0 | J39: ='[2]jobinfo(2)'!$J$39 -> 0 | K39: adj CPS email | L39: TBD
B40: TMP adj | C40: ='[2]jobinfo(2)'!$C$40 -> TBD | D40: ='[2]jobinfo(2)'!$D$40 -> 0 | E40: ='[2]jobinfo(2)'!$E$40 -> 0 | F40: ='[2]jobinfo(2)'!$F$40 -> 0 | G40: ='[2]jobinfo(2)'!$G$40 -> 0 | H40: ='[2]jobinfo(2)'!$H$40 -> 0 | I40: ='[2]jobinfo(2)'!$I$40 -> 0 | J40: ='[2]jobinfo(2)'!$J$40 -> 0 | K40: TMP adj | L40: TBD
B41: TMP adj phone # | C41: ='[2]jobinfo(2)'!$C$41 -> TBD | D41: ='[2]jobinfo(2)'!$D$41 -> 0 | E41: ='[2]jobinfo(2)'!$E$41 -> 0 | F41: ='[2]jobinfo(2)'!$F$41 -> 0 | G41: ='[2]jobinfo(2)'!$G$41 -> 0 | H41: ='[2]jobinfo(2)'!$H$41 -> 0 | I41: ='[2]jobinfo(2)'!$I$41 -> 0 | J41: ='[2]jobinfo(2)'!$J$41 -> 0 | K41: TMP adj phone # | L41: TBD
B42: adj TMP email | C42: ='[2]jobinfo(2)'!$C$42 -> TBD | D42: ='[2]jobinfo(2)'!$D$42 -> 0 | E42: ='[2]jobinfo(2)'!$E$42 -> 0 | F42: ='[2]jobinfo(2)'!$F$42 -> 0 | G42: ='[2]jobinfo(2)'!$G$42 -> 0 | H42: ='[2]jobinfo(2)'!$H$42 -> 0 | I42: ='[2]jobinfo(2)'!$I$42 -> 0 | J42: ='[2]jobinfo(2)'!$J$42 -> 0 | K42: adj TMP email | L42: TBD
B43: ATT: Loss Draft Dept. | C43: ='[2]jobinfo(2)'!$C$43 -> TBD | D43: ='[2]jobinfo(2)'!$D$43 -> 0 | E43: ='[2]jobinfo(2)'!$E$43 -> 0 | F43: ='[2]jobinfo(2)'!$F$43 -> 0 | G43: ='[2]jobinfo(2)'!$G$43 -> 0 | H43: ='[2]jobinfo(2)'!$H$43 -> 0 | I43: ='[2]jobinfo(2)'!$I$43 -> 0 | J43: ='[2]jobinfo(2)'!$J$43 -> 0 | K43: ATT: Loss Draft Dept. | L43: TBD
B44: address ins overnight mail | C44: ='[2]jobinfo(2)'!$C$44 -> TBD | D44: ='[2]jobinfo(2)'!$D$44 -> 0 | E44: ='[2]jobinfo(2)'!$E$44 -> 0 | F44: ='[2]jobinfo(2)'!$F$44 -> 0 | G44: ='[2]jobinfo(2)'!$G$44 -> 0 | H44: ='[2]jobinfo(2)'!$H$44 -> 0 | I44: ='[2]jobinfo(2)'!$I$44 -> 0 | J44: ='[2]jobinfo(2)'!$J$44 -> 0 | K44: address ins overnight mail | L44: TBD
B45: city, state-zip ins | C45: ='[2]jobinfo(2)'!$C$45 -> TBD | D45: ='[2]jobinfo(2)'!$D$45 -> 0 | E45: ='[2]jobinfo(2)'!$E$45 -> 0 | F45: ='[2]jobinfo(2)'!$F$45 -> 0 | G45: ='[2]jobinfo(2)'!$G$45 -> 0 | H45: ='[2]jobinfo(2)'!$H$45 -> 0 | I45: ='[2]jobinfo(2)'!$I$45 | J45: ='[2]jobinfo(2)'!$J$45 -> 0 | K45: city, state-zip ins | L45: TBD
B46: Insurance Co. Phone | C46: ='[2]jobinfo(2)'!$C$46 -> (800) 255-7828 | D46: ='[2]jobinfo(2)'!$D$46 -> 0 | E46: ='[2]jobinfo(2)'!$E$46 -> 0 | F46: ='[2]jobinfo(2)'!$F$46 -> 0 | G46: ='[2]jobinfo(2)'!$G$46 -> 0 | H46: ='[2]jobinfo(2)'!$H$46 -> 0 | I46: ='[2]jobinfo(2)'!$I$46 -> 0 | J46: ='[2]jobinfo(2)'!$J$46 -> 0 | K46: Insurance Co. Phone | L46: TBD
B47: Website Ins Co. | C47: ='[2]jobinfo(2)'!$C$47 -> TBD | D47: ='[2]jobinfo(2)'!$D$47 -> 0 | E47: ='[2]jobinfo(2)'!$E$47 -> 0 | F47: ='[2]jobinfo(2)'!$F$47 -> 0 | G47: ='[2]jobinfo(2)'!$G$47 -> 0 | H47: ='[2]jobinfo(2)'!$H$47 -> 0 | I47: ='[2]jobinfo(2)'!$I$47 -> 0 | J47: ='[2]jobinfo(2)'!$J$47 -> 0 | K47: Website Ins Co. | L47: TBD
B48: Mailing address INS | C48: ='[2]jobinfo(2)'!$C$48 -> TBD | D48: ='[2]jobinfo(2)'!$D$48 -> 0 | E48: ='[2]jobinfo(2)'!$E$48 -> 0 | F48: ='[2]jobinfo(2)'!$F$48 -> 0 | G48: ='[2]jobinfo(2)'!$G$48 -> 0 | H48: ='[2]jobinfo(2)'!$H$48 -> 0 | I48: ='[2]jobinfo(2)'!$I$48 -> 0 | J48: ='[2]jobinfo(2)'!$J$48 -> 0 | K48: Mailing address INS | L48: TBD
B49: Mail city, state, zip INS | C49: ='[2]jobinfo(2)'!$C$49 -> TBD | D49: ='[2]jobinfo(2)'!$D$49 -> 0 | E49: ='[2]jobinfo(2)'!$E$49 -> 0 | F49: ='[2]jobinfo(2)'!$F$49 -> 0 | G49: ='[2]jobinfo(2)'!$G$49 -> 0 | H49: ='[2]jobinfo(2)'!$H$49 -> 0 | I49: ='[2]jobinfo(2)'!$I$49 -> 0 | J49: ='[2]jobinfo(2)'!$J$49 -> 0 | K49: Mail city, state, zip INS | L49: TBD
B50: FAX Ins. Co | C50: ='[2]jobinfo(2)'!$C$50 -> TBD | D50: ='[2]jobinfo(2)'!$D$50 -> 0 | E50: ='[2]jobinfo(2)'!$E$50 -> 0 | F50: ='[2]jobinfo(2)'!$F$50 -> 0 | G50: ='[2]jobinfo(2)'!$G$50 -> 0 | H50: ='[2]jobinfo(2)'!$H$50 -> 0 | I50: ='[2]jobinfo(2)'!$I$50 -> 0 | J50: ='[2]jobinfo(2)'!$J$50 -> 0 | K50: FAX Ins. Co | L50: TBD
B51: NEW CUSTOMER # | C51: ='[2]jobinfo(2)'!$C$51 -> OH25 JOHNSON | D51: ='[2]jobinfo(2)'!$D$51 -> 0 | E51: ='[2]jobinfo(2)'!$E$51 -> Room Sizes | F51: ='[2]jobinfo(2)'!$F$51 -> 0 | G51: ='[2]jobinfo(2)'!$G$51 -> 0 | J51: ='[2]jobinfo(2)'!$J$51 -> 0 | K51: 0 | L51: OH24A SMITH @ LUDLOW
B52: ROOM ID | C52: ='[2]jobinfo(2)'!$C$52 -> Johnson, Paul & Tamra | D52: ='[2]jobinfo(2)'!$D$52 -> 0 | E52: ='[2]jobinfo(2)'!$E$52 -> L | F52: ='[2]jobinfo(2)'!$F$52 -> W | G52: ='[2]jobinfo(2)'!$G$52 -> H | H52: ='[2]jobinfo(2)'!$H$52 -> WALL | I52: ='[2]jobinfo(2)'!$I$52 -> FLOOR | J52: ='[2]jobinfo(2)'!$J$52 -> CEILING | K52: Room Index | L52: SMITH, JANET
A53: =1+A52 -> 1 | B53: Room/Area 1 | C53: ='[2]jobinfo(2)'!$C$53 -> FOYER ENTRY /HALL TRAVEL AREA | D53: ='[2]jobinfo(2)'!$D$53 -> SPACER COLUMN | E53: ='[2]jobinfo(2)'!$E$53 -> 20 | F53: ='[2]jobinfo(2)'!$F$53 -> 20 | G53: ='[2]jobinfo(2)'!$G$53 -> 10 | H53: ='[2]jobinfo(2)'!$H$53 -> 0.45 | I53: ='[2]jobinfo(2)'!$I$53 -> 0.15 | J53: ='[2]jobinfo(2)'!$J$53 -> 1 | K53: Room/Area 1 | L53: Living Room
A54: =1+A53 -> 2 | B54: Room/Area 2 | C54: ='[2]jobinfo(2)'!$C$54 -> LIVINGROOM | D54: ='[2]jobinfo(2)'!$D$54 -> 0 | E54: ='[2]jobinfo(2)'!$E$54 -> 12 | F54: ='[2]jobinfo(2)'!$F$54 -> 12 | G54: ='[2]jobinfo(2)'!$G$54 -> 8 | H54: ='[2]jobinfo(2)'!$H$54 -> 0.33 | I54: ='[2]jobinfo(2)'!$I$54 -> 1 | J54: ='[2]jobinfo(2)'!$J$54 -> 0.15 | K54: Room/Area 2 | L54: Dining Room
A55: =1+A54 -> 3 | B55: Room/Area 3 | C55: ='[2]jobinfo(2)'!$C$55 -> FAMILY ROOM | D55: ='[2]jobinfo(2)'!$D$55 -> 0 | E55: ='[2]jobinfo(2)'!$E$55 -> 12 | F55: ='[2]jobinfo(2)'!$F$55 -> 12 | G55: ='[2]jobinfo(2)'!$G$55 -> 8 | H55: ='[2]jobinfo(2)'!$H$55 -> 0.33 | I55: ='[2]jobinfo(2)'!$I$55 -> 1 | J55: ='[2]jobinfo(2)'!$J$55 -> 0.15 | K55: Room/Area 3 | L55: KITCHEN
A56: =1+A55 -> 4 | B56: Room/Area 4 | C56: ='[2]jobinfo(2)'!$C$56 -> KITCHEN | D56: ='[2]jobinfo(2)'!$D$56 -> 0 | E56: ='[2]jobinfo(2)'!$E$56 -> 12 | F56: ='[2]jobinfo(2)'!$F$56 -> 12 | G56: ='[2]jobinfo(2)'!$G$56 -> 8 | H56: ='[2]jobinfo(2)'!$H$56 -> 0.33 | I56: ='[2]jobinfo(2)'!$I$56 -> 1 | J56: ='[2]jobinfo(2)'!$J$56 -> 0.15 | K56: Room/Area 4 | L56: HALL BATH
A57: =1+A56 -> 5 | B57: Room/Area 5 | C57: ='[2]jobinfo(2)'!$C$57 -> NOOK | D57: ='[2]jobinfo(2)'!$D$57 -> 0 | E57: ='[2]jobinfo(2)'!$E$57 -> 12 | F57: ='[2]jobinfo(2)'!$F$57 -> 12 | G57: ='[2]jobinfo(2)'!$G$57 -> 8 | H57: ='[2]jobinfo(2)'!$H$57 -> 0.33 | I57: ='[2]jobinfo(2)'!$I$57 -> 1 | J57: ='[2]jobinfo(2)'!$J$57 -> 0.15 | K57: Room/Area 5 | L57: HALL RR TRVL
A58: =1+A57 -> 6 | B58: Room/Area 6 | C58: ='[2]jobinfo(2)'!$C$58 -> RR HALL TRAVEL AREA | D58: ='[2]jobinfo(2)'!$D$58 -> 0 | E58: ='[2]jobinfo(2)'!$E$58 -> 12 | F58: ='[2]jobinfo(2)'!$F$58 -> 12 | G58: ='[2]jobinfo(2)'!$G$58 -> 8 | H58: ='[2]jobinfo(2)'!$H$58 -> 0.33 | I58: ='[2]jobinfo(2)'!$I$58 -> 1 | J58: ='[2]jobinfo(2)'!$J$58 -> 0.15 | K58: Room/Area 6
A59: =1+A58 -> 7 | B59: Room/Area 7 | C59: ='[2]jobinfo(2)'!$C$59 -> GARAGE TRAVEL AREA | D59: ='[2]jobinfo(2)'!$D$59 -> 0 | E59: ='[2]jobinfo(2)'!$E$59 -> 12 | F59: ='[2]jobinfo(2)'!$F$59 -> 12 | G59: ='[2]jobinfo(2)'!$G$59 -> 8 | H59: ='[2]jobinfo(2)'!$H$59 -> 0.33 | I59: ='[2]jobinfo(2)'!$I$59 -> 1 | J59: ='[2]jobinfo(2)'!$J$59 -> 0.15 | K59: Room/Area 7 | L59: STAIRS UP
A60: =1+A59 -> 8 | B60: Room/Area 8 | C60: ='[2]jobinfo(2)'!$C$60 -> BASEMENT STAIRS | D60: ='[2]jobinfo(2)'!$D$60 -> 0 | E60: ='[2]jobinfo(2)'!$E$60 -> 0 | F60: ='[2]jobinfo(2)'!$F$60 -> 0 | G60: ='[2]jobinfo(2)'!$G$60 -> 0 | H60: ='[2]jobinfo(2)'!$H$60 -> 0 | I60: ='[2]jobinfo(2)'!$I$60 -> 0 | J60: ='[2]jobinfo(2)'!$J$60 -> 0 | K60: Room/Area 8 | L60: BR1 UP
A61: =1+A60 -> 9 | B61: Room/Area 9 | C61: ='[2]jobinfo(2)'!$C$61 -> BASEMENT COMMON AREAS | D61: ='[2]jobinfo(2)'!$D$61 -> 0 | E61: ='[2]jobinfo(2)'!$E$61 -> 0 | F61: ='[2]jobinfo(2)'!$F$61 -> 0 | G61: ='[2]jobinfo(2)'!$G$61 -> 0 | H61: ='[2]jobinfo(2)'!$H$61 -> 0 | I61: ='[2]jobinfo(2)'!$I$61 -> 0 | J61: ='[2]jobinfo(2)'!$J$61 -> 0 | K61: Room/Area 9 | L61: BR2 UP
A62: =1+A61 -> 10 | B62: Room/Area 10 | C62: ='[2]jobinfo(2)'!$C$62 -> TBD | D62: ='[2]jobinfo(2)'!$D$62 -> 0 | E62: ='[2]jobinfo(2)'!$E$62 -> 0 | F62: ='[2]jobinfo(2)'!$F$62 -> 0 | G62: ='[2]jobinfo(2)'!$G$62 -> 0 | H62: ='[2]jobinfo(2)'!$H$62 -> 0 | I62: ='[2]jobinfo(2)'!$I$62 -> 0 | J62: ='[2]jobinfo(2)'!$J$62 -> 0 | K62: Room/Area 10 | L62: CLOSET?
A63: =1+A62 -> 11 | B63: Room/Area 11 | C63: ='[2]jobinfo(2)'!$C$63 -> TBD | D63: ='[2]jobinfo(2)'!$D$63 -> 0 | E63: ='[2]jobinfo(2)'!$E$63 -> 0 | F63: ='[2]jobinfo(2)'!$F$63 -> 0 | G63: ='[2]jobinfo(2)'!$G$63 -> 0 | H63: ='[2]jobinfo(2)'!$H$63 -> 0 | I63: ='[2]jobinfo(2)'!$I$63 -> 0 | J63: ='[2]jobinfo(2)'!$J$63 -> 0 | K63: Room/Area 11
A64: =1+A63 -> 12 | B64: Room/Area 12 | C64: ='[2]jobinfo(2)'!$C$64 -> TBD | D64: ='[2]jobinfo(2)'!$D$64 -> 0 | E64: ='[2]jobinfo(2)'!$E$64 -> 0 | F64: ='[2]jobinfo(2)'!$F$64 -> 0 | G64: ='[2]jobinfo(2)'!$G$64 -> 0 | H64: ='[2]jobinfo(2)'!$H$64 -> 0 | I64: ='[2]jobinfo(2)'!$I$64 -> 0 | J64: ='[2]jobinfo(2)'!$J$64 -> 0 | K64: Room/Area 12
A65: =1+A64 -> 13 | B65: Room/Area 13 | C65: ='[2]jobinfo(2)'!$C$65 -> TBD | D65: ='[2]jobinfo(2)'!$D$65 -> 0 | E65: ='[2]jobinfo(2)'!$E$65 -> 0 | F65: ='[2]jobinfo(2)'!$F$65 -> 0 | G65: ='[2]jobinfo(2)'!$G$65 -> 0 | H65: ='[2]jobinfo(2)'!$H$65 -> 0 | I65: ='[2]jobinfo(2)'!$I$65 -> 0 | J65: ='[2]jobinfo(2)'!$J$65 -> 0 | K65: Room/Area 13 | L65: TBD
A66: =1+A65 -> 14 | B66: Room/Area 14 | C66: ='[2]jobinfo(2)'!$C$66 -> TBD | D66: ='[2]jobinfo(2)'!$D$66 -> 0 | E66: ='[2]jobinfo(2)'!$E$66 -> 0 | F66: ='[2]jobinfo(2)'!$F$66 -> 0 | G66: ='[2]jobinfo(2)'!$G$66 -> 0 | H66: ='[2]jobinfo(2)'!$H$66 -> 0 | I66: ='[2]jobinfo(2)'!$I$66 -> 0 | J66: ='[2]jobinfo(2)'!$J$66 -> 0 | K66: Room/Area 14 | L66: TBD
A67: =1+A66 -> 15 | B67: Room/Area 15 | C67: ='[2]jobinfo(2)'!$C$67 -> TBD | D67: ='[2]jobinfo(2)'!$D$67 -> 0 | E67: ='[2]jobinfo(2)'!$E$67 -> 0 | F67: ='[2]jobinfo(2)'!$F$67 -> 0 | G67: ='[2]jobinfo(2)'!$G$67 -> 0 | H67: ='[2]jobinfo(2)'!$H$67 -> 0 | I67: ='[2]jobinfo(2)'!$I$67 -> 0 | J67: ='[2]jobinfo(2)'!$J$67 -> 0 | K67: Room/Area 15 | L67: TBD
A68: =1+A67 -> 16 | B68: Room/Area 16 | C68: ='[2]jobinfo(2)'!$C$68 -> TBD | D68: ='[2]jobinfo(2)'!$D$68 -> 0 | E68: ='[2]jobinfo(2)'!$E$68 -> 0 | F68: ='[2]jobinfo(2)'!$F$68 -> 0 | G68: ='[2]jobinfo(2)'!$G$68 -> 0 | H68: ='[2]jobinfo(2)'!$H$68 -> 0 | I68: ='[2]jobinfo(2)'!$I$68 -> 0 | J68: ='[2]jobinfo(2)'!$J$68 -> 0 | K68: Room/Area 16 | L68: TBD
A69: =1+A68 -> 17 | B69: Room/Area 17 | C69: ='[2]jobinfo(2)'!$C$69 -> TBD | D69: ='[2]jobinfo(2)'!$D$69 -> 0 | E69: ='[2]jobinfo(2)'!$E$69 -> 0 | F69: ='[2]jobinfo(2)'!$F$69 -> 0 | G69: ='[2]jobinfo(2)'!$G$69 -> 0 | H69: ='[2]jobinfo(2)'!$H$69 -> 0 | I69: ='[2]jobinfo(2)'!$I$69 -> 0 | J69: ='[2]jobinfo(2)'!$J$69 -> 0 | K69: Room/Area 17 | L69: TBD
A70: =1+A69 -> 18 | B70: Room/Area 18 | C70: ='[2]jobinfo(2)'!$C$70 -> TBD | D70: ='[2]jobinfo(2)'!$D$70 -> 0 | E70: ='[2]jobinfo(2)'!$E$70 -> 0 | F70: ='[2]jobinfo(2)'!$F$70 -> 0 | G70: ='[2]jobinfo(2)'!$G$70 -> 0 | H70: ='[2]jobinfo(2)'!$H$70 -> 0 | I70: ='[2]jobinfo(2)'!$I$70 -> 0 | J70: ='[2]jobinfo(2)'!$J$70 -> 0 | K70: Room/Area 18 | L70: TBD
A71: =1+A70 -> 19 | B71: Room/Area 19 | C71: ='[2]jobinfo(2)'!$C$71 -> TBD | D71: ='[2]jobinfo(2)'!$D$71 -> 0 | E71: ='[2]jobinfo(2)'!$E$71 -> 0 | F71: ='[2]jobinfo(2)'!$F$71 -> 0 | G71: ='[2]jobinfo(2)'!$G$71 -> 0 | H71: ='[2]jobinfo(2)'!$H$71 -> 0 | I71: ='[2]jobinfo(2)'!$I$71 -> 0 | J71: ='[2]jobinfo(2)'!$J$71 -> 0 | K71: Room/Area 19 | L71: TBD
A72: =1+A71 -> 20 | B72: Room/Area 20 | C72: ='[2]jobinfo(2)'!$C$72 -> TBD | D72: ='[2]jobinfo(2)'!$D$72 -> 0 | E72: ='[2]jobinfo(2)'!$E$72 -> 0 | F72: ='[2]jobinfo(2)'!$F$72 -> 0 | G72: ='[2]jobinfo(2)'!$G$72 -> 0 | H72: ='[2]jobinfo(2)'!$H$72 -> 0 | I72: ='[2]jobinfo(2)'!$I$72 -> 0 | J72: ='[2]jobinfo(2)'!$J$72 -> 0 | K72: Room/Area 20 | L72: TBD
A73: =1+A72 -> 21 | B73: Room/Area 21 | C73: ='[2]jobinfo(2)'!$C$73 -> TBD | D73: ='[2]jobinfo(2)'!$D$73 -> 0 | E73: ='[2]jobinfo(2)'!$E$73 -> 0 | F73: ='[2]jobinfo(2)'!$F$73 -> 0 | G73: ='[2]jobinfo(2)'!$G$73 -> 0 | H73: ='[2]jobinfo(2)'!$H$73 -> 0 | I73: ='[2]jobinfo(2)'!$I$73 -> 0 | J73: ='[2]jobinfo(2)'!$J$73 -> 0 | L73: TBD
A74: =1+A73 -> 22 | B74: Room/Area 22 | C74: ='[2]jobinfo(2)'!$C$74 -> TBD | D74: ='[2]jobinfo(2)'!$D$74 -> 0 | E74: ='[2]jobinfo(2)'!$E$74 -> 0 | F74: ='[2]jobinfo(2)'!$F$74 -> 0 | G74: ='[2]jobinfo(2)'!$G$74 -> 0 | H74: ='[2]jobinfo(2)'!$H$74 -> 0 | I74: ='[2]jobinfo(2)'!$I$74 -> 0 | J74: ='[2]jobinfo(2)'!$J$74 -> 0 | L74: TBD
A75: =1+A74 -> 23 | B75: Room/Area 23 | C75: ='[2]jobinfo(2)'!$C$75 -> TBD | D75: ='[2]jobinfo(2)'!$D$75 -> 0 | E75: ='[2]jobinfo(2)'!$E$75 -> 0 | F75: ='[2]jobinfo(2)'!$F$75 -> 0 | G75: ='[2]jobinfo(2)'!$G$75 -> 0 | H75: ='[2]jobinfo(2)'!$H$75 -> 0 | I75: ='[2]jobinfo(2)'!$I$75 -> 0 | J75: ='[2]jobinfo(2)'!$J$75 -> 0 | L75: TBD
A76: =1+A75 -> 24 | B76: Room/Area 24 | C76: ='[2]jobinfo(2)'!$C$76 -> TBD | D76: ='[2]jobinfo(2)'!$D$76 -> 0 | E76: ='[2]jobinfo(2)'!$E$76 -> 0 | F76: ='[2]jobinfo(2)'!$F$76 -> 0 | G76: ='[2]jobinfo(2)'!$G$76 -> 0 | H76: ='[2]jobinfo(2)'!$H$76 -> 0 | I76: ='[2]jobinfo(2)'!$I$76 -> 0 | J76: ='[2]jobinfo(2)'!$J$76 -> 0 | L76: TBD
A77: =1+A76 -> 25 | B77: Room/Area 25 | C77: ='[2]jobinfo(2)'!$C$77 -> TBD | D77: ='[2]jobinfo(2)'!$D$77 -> 0 | E77: ='[2]jobinfo(2)'!$E$77 -> 0 | F77: ='[2]jobinfo(2)'!$F$77 -> 0 | G77: ='[2]jobinfo(2)'!$G$77 -> 0 | H77: ='[2]jobinfo(2)'!$H$77 -> 0 | I77: ='[2]jobinfo(2)'!$I$77 -> 0 | J77: ='[2]jobinfo(2)'!$J$77 -> 0 | L77: TBD
A78: Mortgage Company | B78: Mortgage co | C78: ='[2]jobinfo(2)'!$C$78 -> TBD | D78: ='[2]jobinfo(2)'!$D$78 -> 0 | E78: ='[2]jobinfo(2)'!$E$78 -> 0 | F78: ='[2]jobinfo(2)'!$F$78 -> 0 | G78: ='[2]jobinfo(2)'!$G$78 -> 0 | H78: ='[2]jobinfo(2)'!$H$78 -> 0 | I78: ='[2]jobinfo(2)'!$I$78 -> 0 | J78: ='[2]jobinfo(2)'!$J$78 -> 0 | K78: Mortgage co | L78: TBD
B79: Account# Mtge Co. | C79: ='[2]jobinfo(2)'!$C$79 -> TBD | D79: ='[2]jobinfo(2)'!$D$79 -> 0 | E79: ='[2]jobinfo(2)'!$E$79 -> 0 | F79: ='[2]jobinfo(2)'!$F$79 -> 0 | G79: ='[2]jobinfo(2)'!$G$79 -> 0 | H79: ='[2]jobinfo(2)'!$H$79 -> 0 | I79: ='[2]jobinfo(2)'!$I$79 -> 0 | J79: ='[2]jobinfo(2)'!$J$79 -> 0 | K79: Account# Mtge Co. | L79: TBD
B80: Loan status | C80: ='[2]jobinfo(2)'!$C$80 -> TBD | D80: ='[2]jobinfo(2)'!$D$80 -> 0 | E80: ='[2]jobinfo(2)'!$E$80 -> 0 | F80: ='[2]jobinfo(2)'!$F$80 -> 0 | G80: ='[2]jobinfo(2)'!$G$80 -> 0 | H80: ='[2]jobinfo(2)'!$H$80 -> 0 | I80: ='[2]jobinfo(2)'!$I$80 -> 0 | J80: ='[2]jobinfo(2)'!$J$80 -> 0 | K80: Loan status | L80: TBD
B81: contact person mtge | C81: ='[2]jobinfo(2)'!$C$81 -> TBD | D81: ='[2]jobinfo(2)'!$D$81 -> 0 | E81: ='[2]jobinfo(2)'!$E$81 -> 0 | F81: ='[2]jobinfo(2)'!$F$81 -> 0 | G81: ='[2]jobinfo(2)'!$G$81 -> 0 | H81: ='[2]jobinfo(2)'!$H$81 -> 0 | I81: ='[2]jobinfo(2)'!$I$81 -> 0 | J81: ='[2]jobinfo(2)'!$J$81 -> 0 | K81: contact person mtge | L81: TBD
B82: Phone # MTGE contact | C82: ='[2]jobinfo(2)'!$C$82 -> TBD | D82: ='[2]jobinfo(2)'!$D$82 -> 0 | E82: ='[2]jobinfo(2)'!$E$82 -> 0 | F82: ='[2]jobinfo(2)'!$F$82 -> 0 | G82: ='[2]jobinfo(2)'!$G$82 -> 0 | H82: ='[2]jobinfo(2)'!$H$82 -> 0 | I82: ='[2]jobinfo(2)'!$I$82 -> 0 | J82: ='[2]jobinfo(2)'!$J$82 -> 0 | K82: Phone # MTGE contact | L82: TBD
B83: Ph. Ext. Mtge contact | C83: ='[2]jobinfo(2)'!$C$83 -> TBD | D83: ='[2]jobinfo(2)'!$D$83 -> 0 | E83: ='[2]jobinfo(2)'!$E$83 -> 0 | F83: ='[2]jobinfo(2)'!$F$83 -> 0 | G83: ='[2]jobinfo(2)'!$G$83 -> 0 | H83: ='[2]jobinfo(2)'!$H$83 -> 0 | I83: ='[2]jobinfo(2)'!$I$83 -> 0 | J83: ='[2]jobinfo(2)'!$J$83 -> 0 | K83: Ph. Ext. Mtge contact | L83: TBD
C84: ='[2]jobinfo(2)'!$C$84 -> TBD | D84: ='[2]jobinfo(2)'!$D$84 -> 0 | E84: ='[2]jobinfo(2)'!$E$84 -> 0 | F84: ='[2]jobinfo(2)'!$F$84 -> 0 | G84: ='[2]jobinfo(2)'!$G$84 -> 0 | H84: ='[2]jobinfo(2)'!$H$84 -> 0 | I84: ='[2]jobinfo(2)'!$I$84 -> 0 | J84: ='[2]jobinfo(2)'!$J$84 -> 0 | K84: 0 | L84: TBD
B85: Attn.: Loss Draft Dept | C85: ='[2]jobinfo(2)'!$C$85 -> TBD | D85: ='[2]jobinfo(2)'!$D$85 -> 0 | E85: ='[2]jobinfo(2)'!$E$85 -> 0 | F85: ='[2]jobinfo(2)'!$F$85 -> 0 | G85: ='[2]jobinfo(2)'!$G$85 -> 0 | H85: ='[2]jobinfo(2)'!$H$85 -> 0 | I85: ='[2]jobinfo(2)'!$I$85 -> 0 | J85: ='[2]jobinfo(2)'!$J$85 -> 0 | K85: Attn.: Loss Draft Dept | L85: TBD
B86: Mtge OVN mail | C86: ='[2]jobinfo(2)'!$C$86 -> TBD | D86: ='[2]jobinfo(2)'!$D$86 -> 0 | E86: ='[2]jobinfo(2)'!$E$86 -> 0 | F86: ='[2]jobinfo(2)'!$F$86 -> 0 | G86: ='[2]jobinfo(2)'!$G$86 -> 0 | H86: ='[2]jobinfo(2)'!$H$86 -> 0 | I86: ='[2]jobinfo(2)'!$I$86 -> 0 | J86: ='[2]jobinfo(2)'!$J$86 -> 0 | K86: Mtge OVN mail | L86: TBD
B87: city, St., zip ,mtge OVN | C87: ='[2]jobinfo(2)'!$C$87 -> TBD | D87: ='[2]jobinfo(2)'!$D$87 -> 0 | E87: ='[2]jobinfo(2)'!$E$87 -> 0 | F87: ='[2]jobinfo(2)'!$F$87 -> 0 | G87: ='[2]jobinfo(2)'!$G$87 -> 0 | H87: ='[2]jobinfo(2)'!$H$87 -> 0 | I87: ='[2]jobinfo(2)'!$I$87 -> 0 | J87: ='[2]jobinfo(2)'!$J$87 -> 0 | K87: city, St., zip ,mtge OVN | L87: TBD
B88: Phone # MTGE co. | C88: ='[2]jobinfo(2)'!$C$88 -> TBD | D88: ='[2]jobinfo(2)'!$D$88 -> 0 | E88: ='[2]jobinfo(2)'!$E$88 -> 0 | F88: ='[2]jobinfo(2)'!$F$88 -> 0 | G88: ='[2]jobinfo(2)'!$G$88 -> 0 | H88: ='[2]jobinfo(2)'!$H$88 -> 0 | I88: ='[2]jobinfo(2)'!$I$88 -> 0 | J88: ='[2]jobinfo(2)'!$J$88 -> 0 | K88: Phone # MTGE co. | L88: TBD
B89: email mtge | C89: ='[2]jobinfo(2)'!$C$89 -> TBD | D89: ='[2]jobinfo(2)'!$D$89 -> 0 | E89: ='[2]jobinfo(2)'!$E$89 -> 0 | F89: ='[2]jobinfo(2)'!$F$89 -> 0 | G89: ='[2]jobinfo(2)'!$G$89 -> 0 | H89: ='[2]jobinfo(2)'!$H$89 -> 0 | I89: ='[2]jobinfo(2)'!$I$89 -> 0 | J89: ='[2]jobinfo(2)'!$J$89 -> 0 | K89: email mtge | L89: TBD
B90: mtge website | C90: ='[2]jobinfo(2)'!$C$90 -> TBD | D90: ='[2]jobinfo(2)'!$D$90 -> 0 | E90: ='[2]jobinfo(2)'!$E$90 -> 0 | F90: ='[2]jobinfo(2)'!$F$90 -> 0 | G90: ='[2]jobinfo(2)'!$G$90 -> 0 | H90: ='[2]jobinfo(2)'!$H$90 -> 0 | I90: ='[2]jobinfo(2)'!$I$90 -> 0 | J90: ='[2]jobinfo(2)'!$J$90 -> 0 | K90: mtge website | L90: TBD
B91: MTGE co. Fax # | C91: ='[2]jobinfo(2)'!$C$91 -> TBD | D91: ='[2]jobinfo(2)'!$D$91 -> 0 | E91: ='[2]jobinfo(2)'!$E$91 -> 0 | F91: ='[2]jobinfo(2)'!$F$91 -> 0 | G91: ='[2]jobinfo(2)'!$G$91 -> 0 | H91: ='[2]jobinfo(2)'!$H$91 -> 0 | I91: ='[2]jobinfo(2)'!$I$91 -> 0 | J91: ='[2]jobinfo(2)'!$J$91 -> 0 | K91: MTGE co. Fax # | L91: TBD
B92: Mailing address mtge | C92: ='[2]jobinfo(2)'!$C$92 -> TBD | D92: ='[2]jobinfo(2)'!$D$92 -> 0 | E92: ='[2]jobinfo(2)'!$E$92 -> 0 | F92: ='[2]jobinfo(2)'!$F$92 -> 0 | G92: ='[2]jobinfo(2)'!$G$92 -> 0 | H92: ='[2]jobinfo(2)'!$H$92 -> 0 | I92: ='[2]jobinfo(2)'!$I$92 -> 0 | J92: ='[2]jobinfo(2)'!$J$92 -> 0 | K92: Mailing address mtge | L92: TBD
B93: Mail city, state, zip mtge | C93: ='[2]jobinfo(2)'!$C$93 -> TBD | D93: ='[2]jobinfo(2)'!$D$93 -> 0 | E93: ='[2]jobinfo(2)'!$E$93 -> 0 | F93: ='[2]jobinfo(2)'!$F$93 -> 0 | G93: ='[2]jobinfo(2)'!$G$93 -> 0 | H93: ='[2]jobinfo(2)'!$H$93 -> 0 | I93: ='[2]jobinfo(2)'!$I$93 -> 0 | J93: ='[2]jobinfo(2)'!$J$93 -> 0 | K93: Mail city, state, zip mtge | L93: TBD
C94: ='[2]jobinfo(2)'!$C$94 -> TBD | D94: ='[2]jobinfo(2)'!$D$94 -> 0 | E94: ='[2]jobinfo(2)'!$E$94 -> 0 | F94: ='[2]jobinfo(2)'!$F$94 -> 0 | G94: ='[2]jobinfo(2)'!$G$94 -> 0 | H94: ='[2]jobinfo(2)'!$H$94 -> 0 | I94: ='[2]jobinfo(2)'!$I$94 -> 0 | J94: ='[2]jobinfo(2)'!$J$94 -> 0 | K94: 0 | L94: TBD
B95: Initial Offer / phase 1 contract amount | C95: ='[2]jobinfo(2)'!$C$95 -> TBD | D95: ='[2]jobinfo(2)'!$D$95 -> 0 | E95: ='[2]jobinfo(2)'!$E$95 -> 0 | F95: ='[2]jobinfo(2)'!$F$95 -> 0 | G95: ='[2]jobinfo(2)'!$G$95 -> 0 | H95: ='[2]jobinfo(2)'!$H$95 -> 0 | I95: ='[2]jobinfo(2)'!$I$95 -> 0 | J95: ='[2]jobinfo(2)'!$J$95 -> 0 | K95: Initial Offer / phase 1 contract amount | L95: TBD
B96: Draw Request | C96: ='[2]jobinfo(2)'!$C$96 -> TBD | D96: ='[2]jobinfo(2)'!$D$96 -> 0 | E96: ='[2]jobinfo(2)'!$E$96 -> 0 | F96: ='[2]jobinfo(2)'!$F$96 -> 0 | G96: ='[2]jobinfo(2)'!$G$96 -> 0 | H96: ='[2]jobinfo(2)'!$H$96 -> 0 | I96: ='[2]jobinfo(2)'!$I$96 -> 0 | J96: ='[2]jobinfo(2)'!$J$96 -> 0 | K96: Draw Request | L96: TBD
B97: Cust id | C97: ='[2]jobinfo(2)'!$C$97 -> TBD | D97: ='[2]jobinfo(2)'!$D$97 -> 0 | E97: ='[2]jobinfo(2)'!$E$97 -> 0 | F97: ='[2]jobinfo(2)'!$F$97 -> 0 | G97: ='[2]jobinfo(2)'!$G$97 -> 0 | H97: ='[2]jobinfo(2)'!$H$97 -> 0 | I97: ='[2]jobinfo(2)'!$I$97 -> 0 | J97: ='[2]jobinfo(2)'!$J$97 -> 0 | K97: Cust id | L97: TBD
C98: ='[2]jobinfo(2)'!$C$98 -> TBD | D98: ='[2]jobinfo(2)'!$D$98 -> 0 | E98: ='[2]jobinfo(2)'!$E$98 -> 0 | F98: ='[2]jobinfo(2)'!$F$98 -> 0 | G98: ='[2]jobinfo(2)'!$G$98 -> 0 | H98: ='[2]jobinfo(2)'!$H$98 -> 0 | I98: ='[2]jobinfo(2)'!$I$98 -> 0 | J98: ='[2]jobinfo(2)'!$J$98 -> 0 | K98: - | L98: TBD
C99: ='[2]jobinfo(2)'!$C$99 -> Joe Jones, PM 216.450.7228 | D99: ='[2]jobinfo(2)'!$D$99 -> 0 | E99: ='[2]jobinfo(2)'!$E$99 -> 0 | F99: ='[2]jobinfo(2)'!$F$99 -> 0 | G99: ='[2]jobinfo(2)'!$G$99 -> 0 | H99: ='[2]jobinfo(2)'!$H$99 -> 0 | I99: ='[2]jobinfo(2)'!$I$99 -> 0 | J99: ='[2]jobinfo(2)'!$J$99 -> 0 | K99: - | L99: TBD
B100: co name | C100: ='[2]jobinfo(2)'!$C$100 -> All Phase Consulting, LLC | D100: ='[2]jobinfo(2)'!$D$100 -> 0 | E100: ='[2]jobinfo(2)'!$E$100 -> 0 | F100: ='[2]jobinfo(2)'!$F$100 -> 0 | G100: ='[2]jobinfo(2)'!$G$100 -> 0 | H100: ='[2]jobinfo(2)'!$H$100 -> 0 | I100: ='[2]jobinfo(2)'!$I$100 -> 0 | J100: ='[2]jobinfo(2)'!$J$100 -> 0 | K100: ALL PHASE CONSULTING, LLC | L100: All Phase Consulting, LLC | N100: Bal Construction and Restoration LLC | O100: Hardrock Builders Llc
...

Sheet AOBOH
A1: =+'jobinfo(2)'!$C$100 -> All Phase Consulting, LLC
A2: =+'jobinfo(2)'!$C$103 -> 375 Rockbridge Road, Suite 172-343 | C2: Claim Number: | D2: ='jobinfo(2)'!$C$27 -> 0
A3: =+'jobinfo(2)'!$C$104 -> Lilburn, GA, 30047 | C3: =+'jobinfo(2)'!$C$110 -> Five Generations of Great Work
A4: ='jobinfo(2)'!$C$112 -> Joe Jones, PM 216.450.7228 | B4: ='jobinfo(2)'!$C$113 -> wsbjoe9@gmail.com | C4: =+'jobinfo(2)'!$C$111 -> Five Generations of Pride & Skills
A6: VIA ELECTRONIC MAIL TO (EMAIL ADDRESS) | C6: & PRIORITY MAIL WITH TRACKING
A8: ='jobinfo(2)'!B29 -> Email INS. co. | B8: ='jobinfo(2)'!C29 -> 0 | D8: ='jobinfo(2)'!B30 -> DESK Adjuster DA
A9: ='jobinfo(2)'!B26 -> Insurance Co. Name | B9: ='jobinfo(2)'!C26 -> Allstate Insurance Company | D9: ='jobinfo(2)'!C30 -> 0
A10: ='jobinfo(2)'!B48 -> Mailing address INS | B10: ='jobinfo(2)'!C48 -> TBD | C10: ='jobinfo(2)'!C33 -> claims@claims.allstate.com
A11: ='jobinfo(2)'!B49 -> Mail city, state, zip INS | B11: ='jobinfo(2)'!C49 -> TBD
A13: Re: | B13: ='jobinfo(2)'!C11 -> WATER | D13: Date of Loss:
A14: ='jobinfo(2)'!B27 -> Claim # | B14: ='jobinfo(2)'!C27 -> 0 | C14: ='jobinfo(2)'!C4 -> tringo68@yahoo.com | D14: ='jobinfo(2)'!C12 -> Friday, April 4, 2025
A15: Insured: | B15: ='jobinfo(2)'!C1 -> Johnson, Paul & Tamra | C15: ='jobinfo(2)'!C5 -> (216) 399-6191 | D15: POLICY NUMBER
A16: Property Address: | B16: ='jobinfo(2)'!C2 -> 9402 Shepard Road | C16: ='jobinfo(2)'!C3 -> Macedonia, OH, USA | D16: ='jobinfo(2)'!C28 -> 0
A18: REQUEST FOR INSURANCE INFORMATION AND NOTICE OF POST-LOSS ASSIGNMENT OF INSURANCE RIGHTS
A20: Dear Adjuster, | C20: ='jobinfo(2)'!C30 -> 0
A22: Please take notice that | C22: ='jobinfo(2)'!C100 -> All Phase Consulting, LLC
A23: was engaged to perform work at your insured's property on the date of: | D23: =D14 -> Friday, April 4, 2025
A24: to address the damage sustained in the above­ referenced loss.
A25: Our scope of work is described in the enclosed contract.
A27: Enclosed, please find an Insurance Information Release and Authorization executed by the policyholder. It includes a waiver of the policyholder's right to privacy as to the portion of the claim that relates to our scope of work and irrevocably directs you to release the following documents and information to us. Therefore, please immediately confirm in writing that you will provide the following:
A28: (1) A complete certified copy of the policy packet (including declarations, policy provisions, …........... and endorsements);
A30: (2) All information and documentation regarding this property damage claim, including status reports, letters, emails, estimates, competitive bids, and correspondence from consultants and independent adjusters engaged by the insurance company; and
A32: (3) "CC:" us on all such future correspondence for the duration of the claim.
A34: Transmit all documents by email to [address #1] | C34: ='jobinfo(2)'!C113 -> wsbjoe9@gmail.com
A36: and cc: [address #2, for redundancy]. | C36: ='jobinfo(2)'!C103 -> 375 Rockbridge Road, Suite 172-343
C37: ='jobinfo(2)'!C104 -> Lilburn, GA, 30047
A39: After the loss occurred, the insured ("Policyholder") irrevocably transferred and assigned to us all rights and policy benefits for claims for the damage we were hired to address, pursuant to the enclosed, fully-executed and enforceable post-loss Assignment of Insurance Rights and Direction to Pay ("Assignment"). Also enclosed is a copy of the Contract executed by your insured, and an irrevocable Information Release and Authorization.
A41: In pertinent part, the Assignment states:
A42: 1. Irrevocable Post-Loss Assignment of Policyholders' Rights Against Insurance Company To Contractor: By execution of this irrevocable Post-Loss Assignment of Insurance Rights and Direction of Pay ("Assignment"), the policyholder(s) identified above ("Policyholders") completely, irrevocably, and fully assign and transfer to the Contractor named above all of the Policyholders' legal and equitable rights, title, and interest under all insurance policies arising from claims for the damage Contractor was hired to address (collectively referred to as the "Assigned Rights"). The Assigned Rights include without limitation the rights to collect insurance policy benefits and proceeds, and the right but not the obligation to participate in appraisal of the loss or the portion of the loss in which Contractor is involved. The Assigned Rights include without limitation the Policyholders' rights as a first-party insured under the Policyholders' policy of insurance, the right to sue the insurance company to enforce the Assigned Rights, and to prosecute any applicable causes of action for breach of contract, breach of the implied covenant of good faith and fair dealing (insurance bad faith), fraud, and negligence. This Assignment shall be liberally construed to the fullest extent permitted by law and so that Contractor is deemed to stand in a first party position as to the policies. The Policyholders shall remain obligated with respect to all duties and liabilities under the terms of the insurance policies, including the duty to properly document all claims and cooperate with the insurer's investigation. Contractor owes none of those duties. This Assignment may only be revoked by written notice to the Contractor after the contract is terminated in writing, but is permanently irrevocable as to work performed before the contract is terminated.
A43: 2. Exclusions: Nothing in this Assignment shall be construed as an assignment of other parts of the insurance claim that are unrelated to Contractor's scope of work, such as additional living expenses, personal property, or services performed after Contractor's services are terminated. Nothing in this Assignment shall be construed as a delegation of duties.
A44: 3. No Conditions: The Policyholders agree and understand that this Assignment and each of its component parts are irrevocable. The Policyholders expressly acknowledge that it is the Policyholders' intent to assign the Policyholders' insurance policy rights and benefits under the claims to the Contractor as explained above. The Policyholders agree and understand that this irrevocable Assignment is unconditional and effective immediately upon execution of this document, and that no further action needs to be taken to make it valid, enforceable, or binding upon the Policyholders and the Policyholders' insurance company.
A45: 4. Cooperation: The Policyholders shall cooperate fully with Contractor's efforts to enforce the Assigned rights, and to collect policy benefits. Policyholders agree to execute any and all documents presented by Contractor to the Policyholders, which are reasonably required for the prosecution of Contractor's claims against the Policyholders' insurance company and/or its agents with respect to the Assigned Rights.
A46: 5. Direction to Pay: The Policyholders hereby authorize and instruct all insurance carriers who may be liable to the Policyholders for this loss in whole or in part to pay directly to Contractor the amounts due or to become due in connection with the work Contractor has been authorized to perform, and to deliver said payments directly and exclusively to Contractor within fifteen (15) calendar days of the invoice. In the event an insurer fails to name Contractor on any check for the Work, the Policyholders shall immediately notify Contractor in writing, and return the check to the insurer with a written request to the insurer to issue a replacement check payable to Contractor.
A47: 6. Security and Consideration: This Assignment is given to Contractor as security and is made in consideration for Contractor's agreement to perform services without immediate full payment from the Policyholders upon completion of services. The Policyholders acknowledge the sufficiency of this consideration.
A48: ALL PHASE CONSULTING, LLC hereby tenders the insured's assignment of the Assigned Rights, which we received as security.
A49: As assignee of the policy benefits, we step into the shoes of the insured and hold legal title to all rights for policy benefits paid pursuant to the Assigned Rights. Since this is a post-loss assignment, it is valid and enforceable. Therefore, all insurers with applicable coverage are bound by the Assignment, and we now stand in a first party position as to this portion of the claim.
A50: It is important to emphasize that this is not an assignment of the entire policy; it is merely a post-loss assignment of rights and benefits arising from a specific loss. The anti­ assignment provision in the policy only applies to pre-loss assignments of the policy.
A51: An assignment is a transfer of property or of some right or interest from one person to another that causes the property, right, or interest to vest in the other person. Ford Motor Credit Co. v. Ryan, 2010-Ohio-4601, ii 89, 189 Ohio App. 3d 560,598,939 N.E.2d 891,920
... A61: Very truly yours,
A62: .All Phase Consulting, LLC | B62: ='jobinfo(2)'!C100 -> All Phase Consulting, LLC
A64: ='jobinfo(2)'!B112 -> Co. REP. / PH | C64: ='jobinfo(2)'!B113 -> CO.REP. email
A65: ='jobinfo(2)'!C112 -> Joe Jones, PM 216.450.7228 | C65: ='jobinfo(2)'!C113 -> wsbjoe9@gmail.com
A66: =+'jobinfo(2)'!$C$100 -> All Phase Consulting, LLC | C66: ='jobinfo(2)'!C101 -> WWW.MYAPCLLC.COM
A67: =+'jobinfo(2)'!$C$103 -> 375 Rockbridge Road, Suite 172-343 | C67: Claim Number: | D67: ='jobinfo(2)'!$C$27 -> 0
A68: =+'jobinfo(2)'!$C$104 -> Lilburn, GA, 30047 | C68: =+'jobinfo(2)'!$C$110 -> Five Generations of Great Work
A69: ='jobinfo(2)'!$C$112 -> Joe Jones, PM 216.450.7228 | B69: ='jobinfo(2)'!$C$113 -> wsbjoe9@gmail.com | C69: =+'jobinfo(2)'!$C$111 -> Five Generations of Pride & Skills
A70: OHIO POST-LOSS ASSIGNMENT OF INSURANCE RIGHTS & DIRECTION TO PAY
A71: Policyholder #1: | B71: =+'jobinfo(2)'!C$1 -> Johnson, Paul & Tamra | C71: ='jobinfo(2)'!$B$26 -> Insurance Co. Name | D71: ='jobinfo(2)'!$C$26 -> Allstate Insurance Company
A72: Policyholder #2: | B72: =+'jobinfo(2)'!C$6 -> TBD | C72: PoIicy Number: | D72: ='jobinfo(2)'!$C$28 -> 0
A73: =+'jobinfo(2)'!$C$2 -> 9402 Shepard Road | B73: =+'jobinfo(2)'!$C$3 -> Macedonia, OH, USA | C73: Date of Loss: | D73: =D14 -> Friday, April 4, 2025
A75: 1. Irrevocable Post-Loss Assignment of Policyholders' Rights Against Insurance Company To Contractor: By execution of this irrevocable Post-Loss Assignment of Insurance Rights and Direction of Pay ("Assignment"), the policyholder(s) identified above ("Policyholders") completely, irrevocably, and fully assign and transfer to the Contractor named above all of the Policyholders' legal and equitable rights, title, and interest under all insurance policies arising from claims for the damage Contractor was hired to address (collectively referred to as the "Assigned Rights"). The Assigned Rights include without limitation the rights to collect insurance policy benefits and proceeds, and the right but not the obligation to participate in appraisal of the loss or the portion of the loss in which Contractor is involved. The Assigned Rights include without limitation the Policyholders' rights as a first-party insured under the Policyholders' policy of insurance, the right to sue the insurance company to enforce the Assigned Rights, and to prosecute any applicable causes of action for breach of contract, breach of the implied covenant of good faith and fair dealing (insurance bad faith), fraud, and negligence. This Assignment shall be liberally construed to the fullest extent permitted by law and so that Contractor is deemed to stand in a first party position as to the policies. The Policyholders shall remain obligated with respect to all duties and liabilities under the terms of the insurance policies, including the duty to properly document all claims and cooperate with the insurer's investigation. Contractor owes none of those duties. This Assignment may only be revoked by written notice to the Contractor after the contract is terminated in writing, but is permanently irrevocable as to work performed before the contract is terminated.
A76: 2. Exclusions: Nothing in this Assignment shall be construed as an assignment of other parts of the insurance claim that are unrelated to Contractor's scope of work, such as additional living expenses, the value oflost personal property, or services performed after Contractor's services are terminated. Nothing in this Assignment shall be construed as a delegation of duties.
A77: 3. No Conditions: The Policyholders agree and understand that this Assignment and each of its component parts are irrevocable. The Policyholders expressly acknowledge that it is the Policyholders' intent to assign the Policyholders' insurance policy rights and benefits under the claims to the Contractor as explained above. The Policyholders agree and understand that this irrevocable Assignment is unconditional and effective immediately upon execution of this document, and that no further action needs to be taken to make it valid, enforceable, or binding upon the Policyholders and the Policyholders' insurance company.
A78: 4. Cooperation: The Policyholders shall cooperate fully with Contractor's efforts to enforce the Assigned rights, and to collect policy benefits. Policyholders agree to execute any and all documents presented by Contractor to the Policyholders, which are reasonably required for the prosecution of Contractor's claims against the Policyholders' insurance company and/or its agents with respect to the Assigned Rights.
A79: 5. Direction to Pay: The Policyholders hereby authorize and instruct all insurance carriers who may be liable to the Policyholders for this loss in whole or in part to pay directly to Contractor the amounts due or to become due in connection with the work Contractor has been authorized to perform, and to deliver said payments directly and exclusively to Contractor within fifteen (15) calendar days of the invoice. In the event an insurer fails to name Contractor on any check for the Work, the Policyholders shall immediately notify Contractor in writing, and return the check to the insurer with a written request to the insurer to issue a replacement check payable to Contractor.
A80: 6. Security and Consideration: This Assignment is given to Contractor as security and is made in consideration for Contractor's agreement to perform services without immediate full payment from the Policyholders upon completion of services. The Policyholders acknowledge the sufficiency of this consideration.
A81: 7. No Release: The Policyholders remain primarily and ultimately responsible for payment for services rendered by Contractor. This Assignment does not relieve the Policyholders from the duty to compensate Contractor for any amount due to Contractor that is not paid by insurance, including the cost of the work, deductibles, betterments, depreciation and other amounts not paid by insurance, all of which are ultimately the Policyholders' responsibility.
A82: "Policyholder #1" (I read this Assignment and understand it.) | C82: "Policyholder #2" (I read this Assignment and understand it.)
A83: X___________________ | C83: X___________________
A84: ='jobinfo(2)'!$C$1 -> Johnson, Paul & Tamra | C84: ='jobinfo(2)'!$C$6 -> TBD
A86: Contractor Representative's Name | C86: Contractor Representative Signature X_____________________
A88: NOTARY PAGE
A89: Assignment of Insurance Benefits and Direct Payment Authorization:
A91: =+'jobinfo(2)'!$C$1 -> Johnson, Paul & Tamra | C91: =+'jobinfo(2)'!B22 -> Contract Date | D91: =+'[1]jobinfo(2)'!$C$22 -> 45497
A92: =+'jobinfo(2)'!$C$2 -> 9402 Shepard Road | C92: =+'jobinfo(2)'!B12 -> date of loss | D92: =+'[1]jobinfo(2)'!$C$12 -> 45492
A93: =+'jobinfo(2)'!$C$3 -> Macedonia, OH, USA | C93: =+'jobinfo(2)'!C13 -> Interior Repairs LEVEL 1
A94: =+'jobinfo(2)'!$C$4 -> tringo68@yahoo.com | C94: =+'jobinfo(2)'!C14 -> Interior Repairs LEVEL 2
A95: =+'jobinfo(2)'!$C$5 -> (216) 399-6191 | C95: =+'jobinfo(2)'!C15 -> TBD
A96: =+'[1]jobinfo(2)'!$B$26 -> Insurance Co. Name | B96: =+'[1]jobinfo(2)'!$C$26 -> STATE FARM | C96: ='jobinfo(2)'!B11 -> Cause of Loss | D96: ='jobinfo(2)'!C11 -> WATER
A97: =+'[1]jobinfo(2)'!$B$27 -> Claim # | B97: =+'[1]jobinfo(2)'!$C$27 -> 3571C126N | C97: =+'jobinfo(2)'!B17 -> Mitigation | D97: =+'jobinfo(2)'!C17 -> Y
A99: X______________________________ _______________________________ | D99: _____/______/2024
A100: =A91 -> Johnson, Paul & Tamra
A102: X______________________________ _______________________________ | D102: =D99 -> _____/______/2024
A103: ='[1]jobinfo(2)'!C93 -> 0
A105: Sworn to before me & subscribed in my presence on this ________ day of_________, 2024
A106: State of: ____________ County/Parish of: ______________________ | B106: =A93 -> Macedonia, OH, USA | C106: County/Parish of: ______________________
A107: Notary Signature: ______________________________________________
A108: My Commission Expires: ______/_______ / 20_______ Notary Seal:
A110: Assigned to: | B110: ='jobinfo(2)'!C100 -> All Phase Consulting, LLC
C112: =+'[1]email cvr'!$A$15 -> EIN # | D112: =+'[1]jobinfo(2)'!$C$116 -> TIN 83-226 0563

Sheet AOBGA
A1: =+'jobinfo(2)'!$C$100 -> All Phase Consulting, LLC
A2: =+'jobinfo(2)'!$C$103 -> 375 Rockbridge Road, Suite 172-343 | C2: Claim Number: | D2: ='jobinfo(2)'!$C$27 -> 0
A3: =+'jobinfo(2)'!$C$104 -> Lilburn, GA, 30047 | C3: =+'jobinfo(2)'!$C$110 -> Five Generations of Great Work
A4: ='jobinfo(2)'!$C$112 -> Joe Jones, PM 216.450.7228 | B4: ='jobinfo(2)'!$C$113 -> wsbjoe9@gmail.com | C4: =+'jobinfo(2)'!$C$111 -> Five Generations of Pride & Skills
A6: VIA ELECTRONIC MAIL TO (EMAIL ADDRESS) | C6: & PRIORITY MAIL WITH TRACKING
A8: ='jobinfo(2)'!B29 -> Email INS. co. | B8: ='jobinfo(2)'!C29 -> 0 | D8: ='jobinfo(2)'!B30 -> DESK Adjuster DA
A9: ='jobinfo(2)'!B26 -> Insurance Co. Name | B9: ='jobinfo(2)'!C26 -> Allstate Insurance Company | D9: ='jobinfo(2)'!C30 -> 0
A10: ='jobinfo(2)'!B48 -> Mailing address INS | B10: ='jobinfo(2)'!C48 -> TBD
A11: ='jobinfo(2)'!B49 -> Mail city, state, zip INS | B11: ='jobinfo(2)'!C49 -> TBD
A13: Re: | B13: ='jobinfo(2)'!C11 -> WATER | D13: Date of Loss:
A14: ='jobinfo(2)'!B27 -> Claim # | B14: ='jobinfo(2)'!C27 -> 0 | D14: ='jobinfo(2)'!C12 -> Friday, April 4, 2025
A15: Insured: | B15: ='jobinfo(2)'!C1 -> Johnson, Paul & Tamra | C15: ='jobinfo(2)'!C6 -> TBD | D15: POLICY NUMBER
A16: Property Address: | B16: ='jobinfo(2)'!C2 -> 9402 Shepard Road | C16: ='jobinfo(2)'!C3 -> Macedonia, OH, USA | D16: ='jobinfo(2)'!C28 -> 0
A18: REQUEST FOR INSURANCE INFORMATION AND NOTICE OF POST-LOSS ASSIGNMENT OF INSURANCE RIGHTS
A20: Dear Adjuster, | C20: ='jobinfo(2)'!C30 -> 0
A21: Please take notice that | C21: ='jobinfo(2)'!C100 -> All Phase Consulting, LLC
A22: was engaged to perform work at your insured's property on the date of: | D22: =D14 -> Friday, April 4, 2025
A23: to address the damage sustained in the above­ referenced loss.
A24: Our scope of work is described in the enclosed ESTIMATE & contract.
A26: Enclosed, please find an Insurance Information Release and Authorization executed by the policyholder. It includes a waiver of the policyholder's right to privacy as to the portion of the claim that relates to our scope of work and irrevocably directs you to release the following documents and information to us. Therefore, please immediately confirm in writing that you will provide the following:
A27: (1) A complete certified copy of the policy packet (including declarations, policy provisions, …........... and endorsements);
A29: (2) All information and documentation regarding this property damage claim, including status reports, letters, emails, estimates, competitive bids, and correspondence from consultants and independent adjusters engaged by the insurance company; and
A31: (3) "CC:" us on all such future correspondence for the duration of the claim.
A33: Transmit all documents by email to [address #1] | C33: ='jobinfo(2)'!C113 -> wsbjoe9@gmail.com
A35: and cc: [address #2, for redundancy]. | C35: ='jobinfo(2)'!C103 -> 375 Rockbridge Road, Suite 172-343
C36: ='jobinfo(2)'!C104 -> Lilburn, GA, 30047
A38: After the loss occurred, the insured ("Policyholder") irrevocably transferred and assigned to us all rights and policy benefits for claims for the damage we were hired to address, pursuant to the enclosed, fully-executed and enforceable post-loss Assignment of Insurance Rights and Direction to Pay ("Assignment"). Also enclosed is a copy of the Contract executed by your insured, and an irrevocable Information Release and Authorization.
A40: In pertinent part, the Assignment states:
A41: 1. Irrevocable Post-Loss Assignment of Policyholders' Rights Against Insurance Company To Contractor: By execution of this irrevocable Post-Loss Assignment of Insurance Rights and Direction of Pay ("Assignment"), the policyholder(s) identified above ("Policyholders") completely, irrevocably, and fully assign and transfer to the Contractor named above all of the Policyholders' legal and equitable rights, title, and interest under all insurance policies arising from claims for the damage Contractor was hired to address (collectively referred to as the "Assigned Rights"). The Assigned Rights include without limitation the rights to collect insurance policy benefits and proceeds, and the right but not the obligation to participate in appraisal of the loss or the portion of the loss in which Contractor is involved. The Assigned Rights include without limitation the Policyholders' rights as a first-party insured under the Policyholders' policy of insurance, the right to sue the insurance company to enforce the Assigned Rights, and to prosecute any applicable causes of action for breach of contract, breach of the implied covenant of good faith and fair dealing (insurance bad faith), fraud, and negligence. This Assignment shall be liberally construed to the fullest extent permitted by law and so that Contractor is deemed to stand in a first party position as to the policies. The Policyholders shall remain obligated with respect to all duties and liabilities under the terms of the insurance policies, including the duty to properly document all claims and cooperate with the insurer's investigation. Contractor owes none of those duties. This Assignment may only be revoked by written notice to the Contractor after the contract is terminated in writing, but is permanently irrevocable as to work performed before the contract is terminated.
A42: 2. Exclusions: Nothing in this Assignment shall be construed as an assignment of other parts of the insurance claim that are unrelated to Contractor's scope of work, such as additional living expenses, personal property, or services performed after Contractor's services are terminated. Nothing in this Assignment shall be construed as a delegation of duties.
A43: 3. No Conditions: The Policyholders agree and understand that this Assignment and each of its component parts are irrevocable. The Policyholders expressly acknowledge that it is the Policyholders' intent to assign the Policyholders' insurance policy rights and benefits under the claims to the Contractor as explained above. The Policyholders agree and understand that this irrevocable Assignment is unconditional and effective immediately upon execution of this document, and that no further action needs to be taken to make it valid, enforceable, or binding upon the Policyholders and the Policyholders' insurance company.
A44: 4. Cooperation: The Policyholders shall cooperate fully with Contractor's efforts to enforce the Assigned rights, and to collect policy benefits. Policyholders agree to execute any and all documents presented by Contractor to the Policyholders, which are reasonably required for the prosecution of Contractor's claims against the Policyholders' insurance company and/or its agents with respect to the Assigned Rights.
A45: 5. Direction to Pay: The Policyholders hereby authorize and instruct all insurance carriers who may be liable to the Policyholders for this loss in whole or in part to pay directly to Contractor the amounts due or to become due in connection with the work Contractor has been authorized to perform, and to deliver said payments directly and exclusively to Contractor within fifteen (15) calendar days of the invoice. In the event an insurer fails to name Contractor on any check for the Work, the Policyholders shall immediately notify Contractor in writing, and return the check to the insurer with a written request to the insurer to issue a replacement check payable to Contractor.
A46: 6. Security and Consideration: This Assignment is given to Contractor as security and is made in consideration for Contractor's agreement to perform services without immediate full payment from the Policyholders upon completion of services. The Policyholders acknowledge the sufficiency of this consideration.
A47: ALL PHASE CONSULTING, LLC hereby tenders the insured's assignment of the Assigned Rights, which we received as security.
A48: As assignee of the policy benefits, we step into the shoes of the insured and hold legal title to all rights for policy benefits paid pursuant to the Assigned Rights. Since this is a post-loss assignment, it is valid and enforceable. Therefore, all insurers with applicable coverage are bound by the Assignment, and we now stand in a first party position as to this portion of the claim.
A49: It is important to emphasize that this is not an assignment of the entire policy; it is merely a post-loss assignment of rights and benefits arising from a specific loss. The anti­ assignment provision in the policy only applies to pre-loss assignments of the policy.
A50: A policy may be assignable or not assignable, as provided by its terms. Subject to its terms relating to assignability, any life or accident and sickness policy issued under the terms of which the beneficiary may be changed upon the sole request of the policy owner may be assigned either by pledge or by transfer of title by an assignment executed by the policy owner alone and delivered to the insurer, whether or not the pledgee or assignee is the insurer. Any assignment shall entitle the insurer to deal with the assignee as the owner or pledgee of the policy in accordance with the terms of the assignment until the insurer has received at its home office written notice of termination of the assignment or pledge or written notice by or on behalf of some other person claiming some interest in the policy in conflict with the assignment. Ga. Code Ann., § 33-24-17.
... A56: If you have any questions, please do not hesitate to call. We thank you in advance for the documents and information listed on the first page of this letter. We look forward to working cooperatively with you for a smooth and expeditious resolution of this claim. Thank you.
A57: Very truly yours, | C57: ='jobinfo(2)'!C100 -> All Phase Consulting, LLC
A58: ='jobinfo(2)'!B112 -> Co. REP. / PH | C58: ='jobinfo(2)'!B113 -> CO.REP. email
A59: ='jobinfo(2)'!C112 -> Joe Jones, PM 216.450.7228 | C59: ='jobinfo(2)'!C113 -> wsbjoe9@gmail.com
A60: =+'jobinfo(2)'!$C$100 -> All Phase Consulting, LLC | C60: ='jobinfo(2)'!C101 -> WWW.MYAPCLLC.COM | F60: =+'jobinfo(2)'!$C$100 -> All Phase Consulting, LLC
A61: =+'jobinfo(2)'!$C$103 -> 375 Rockbridge Road, Suite 172-343 | C61: Claim Number: | D61: ='jobinfo(2)'!$C$27 -> 0 | F61: =+'jobinfo(2)'!H$109 -> 0
A62: =+'jobinfo(2)'!$C$104 -> Lilburn, GA, 30047 | C62: =+'jobinfo(2)'!$C$110 -> Five Generations of Great Work | F62: =+'jobinfo(2)'!$C$101 -> WWW.MYAPCLLC.COM | H62: =+'jobinfo(2)'!$C$102 -> Insured & GA Registered #09073201
A63: ='jobinfo(2)'!$C$112 -> Joe Jones, PM 216.450.7228 | B63: ='jobinfo(2)'!$C$113 -> wsbjoe9@gmail.com | C63: =+'jobinfo(2)'!$C$111 -> Five Generations of Pride & Skills | F63: ='jobinfo(2)'!$C$107 -> 20810 AURORA RD | I63: =+'jobinfo(2)'!$C$105 -> ECI 531 FIFTH AVE,
A64: GEORGIA POST-LOSS ASSIGNMENT OF INSURANCE RIGHTS & DIRECTION TO PAY | F64: COMPANY REP. | G64: =+'jobinfo(2)'!$C$112 -> Joe Jones, PM 216.450.7228 | H64: =+'jobinfo(2)'!$C$113 -> wsbjoe9@gmail.com
A65: Policyholder #1: | B65: =+'jobinfo(2)'!C$1 -> Johnson, Paul & Tamra | C65: ='jobinfo(2)'!$B$26 -> Insurance Co. Name | D65: ='jobinfo(2)'!$C$26 -> Allstate Insurance Company | F65: COMPANY REP. #2 | G65: =+'jobinfo(2)'!$C$114 -> 404-446-9060 | H65: =+'jobinfo(2)'!$C$115 -> info@myapcllc.com
A66: Policyholder #2: | B66: =+'jobinfo(2)'!C$6 -> TBD | C66: PoIicy Number: | D66: ='jobinfo(2)'!$C$28 -> 0 | F66: Claim # | H66: Cst-owner Phone# | I66: ='jobinfo(2)'!$C$5 -> (216) 399-6191
A67: =+'jobinfo(2)'!$C$2 -> 9402 Shepard Road | B67: =+'jobinfo(2)'!$C$3 -> Macedonia, OH, USA | C67: Date of Loss: | D67: ='jobinfo(2)'!C12 -> Friday, April 4, 2025
A68: City/State/Zip: | B68: =+'jobinfo(2)'!$C$3 -> Macedonia, OH, USA
A69: 1. Irrevocable Post-Loss Assignment of Policyholders' Rights Against Insurance Company To Contractor: By execution of this irrevocable Post-Loss Assignment of Insurance Rights and Direction of Pay ("Assignment"), the policyholder(s) identified above ("Policyholders") completely, irrevocably, and fully assign and transfer to the Contractor named above all of the Policyholders' legal and equitable rights, title, and interest under all insurance policies arising from claims for the damage Contractor was hired to address (collectively referred to as the "Assigned Rights"). The Assigned Rights include without limitation the rights to collect insurance policy benefits and proceeds, and the right but not the obligation to participate in appraisal of the loss or the portion of the loss in which Contractor is involved. The Assigned Rights include without limitation the Policyholders' rights as a first-party insured under the Policyholders' policy of insurance, the right to sue the insurance company to enforce the Assigned Rights, and to prosecute any applicable causes of action for breach of contract, breach of the implied covenant of good faith and fair dealing (insurance bad faith), fraud, and negligence. This Assignment shall be liberally construed to the fullest extent permitted by law and so that Contractor is deemed to stand in a first party position as to the policies. The Policyholders shall remain obligated with respect to all duties and liabilities under the terms of the insurance policies, including the duty to properly document all claims and cooperate with the insurer's investigation. Contractor owes none of those duties. This Assignment may only be revoked by written notice to the Contractor after the contract is terminated in writing, but is permanently irrevocable as to work performed before the contract is terminated.
A70: 2. Exclusions: Nothing in this Assignment shall be construed as an assignment of other parts of the insurance claim that are unrelated to Contractor's scope of work, such as additional living expenses, or services performed after Contractor's services are terminated. Nothing in this Assignment shall be construed as a delegation of duties. | F70: =+'jobinfo(2)'!$B$26 -> Insurance Co. Name | G70: =+'jobinfo(2)'!$C$26 -> Allstate Insurance Company | H70: =+'jobinfo(2)'!$B$28 -> policy # | I70: =+'jobinfo(2)'!$C$27 -> 0
A71: 3. No Conditions: The Policyholders agree and understand that this Assignment and each of its component parts are irrevocable. The Policyholders expressly acknowledge that it is the Policyholders' intent to assign the Policyholders' insurance policy rights and benefits under the claims to the Contractor as explained above. The Policyholders agree and understand that this irrevocable Assignment is unconditional and effective immediately upon execution of this document, and that no further action needs to be taken to make it valid, enforceable, or binding upon the Policyholders and the Policyholders' insurance company. | F71: =+'jobinfo(2)'!$B$46 -> Insurance Co. Phone | G71: =+'jobinfo(2)'!$C$46 -> (800) 255-7828 | H71: =+'jobinfo(2)'!$C$29 -> 0
A72: 4. Cooperation: The Policyholders shall cooperate fully with Contractor's efforts to enforce the Assigned rights, and to collect policy benefits. Policyholders agree to execute any and all documents presented by Contractor to the Policyholders, which are reasonably required for the prosecution of Contractor's claims against the Policyholders' insurance company and/or its agents with respect to the Assigned Rights. | F72: =+'jobinfo(2)'!$B$30 -> DESK Adjuster DA | G72: =+'jobinfo(2)'!$C$30 -> 0 | H72: =+'jobinfo(2)'!$B$33 -> DA Email | I72: =+'jobinfo(2)'!$C$33 -> claims@claims.allstate.com
A73: 5. Direction to Pay: The Policyholders hereby authorize and instruct all insurance carriers who may be liable to the Policyholders for this loss in whole or in part to pay directly to Contractor the amounts due or to become due in connection with the work Contractor has been authorized to perform, and to deliver said payments directly and exclusively to Contractor within fifteen (15) calendar days of the invoice. In the event an insurer fails to name Contractor on any check for the Work, the Policyholders shall immediately notify Contractor in writing, and return the check to the insurer with a written request to the insurer to issue a replacement check payable to Contractor. | F73: =+'jobinfo(2)'!$B$31 -> DA Phone | G73: =+'jobinfo(2)'!$C$31 -> 888 656.8005 | H73: =+'jobinfo(2)'!$B$32 -> DA Ph. Ext. # | I73: =+'jobinfo(2)'!$C$32 -> 0
A74: 6. Security and Consideration: This Assignment is given to Contractor as security and is made in consideration for Contractor's agreement to perform services without immediate full payment from the Policyholders upon completion of services. The Policyholders acknowledge the sufficiency of this consideration.
A75: 7. No Release: The Policyholders remain primarily and ultimately responsible for payment for services rendered by Contractor. This Assignment does not relieve the Policyholders from the duty to compensate Contractor for any amount due to Contractor that is not paid by insurance, including the cost of the work, deductibles, betterments, depreciation and other amounts not paid by insurance, all of which are ultimately the Policyholders' responsibility.
A77: "Policyholder #1" (I read this Assignment and understand it.) | C77: "Policyholder #2" (I read this Assignment and understand it.)
A78: X _________________________ | C78: X___________________
A79: Signature.of PoIicyhoIder | C79: Signature.of PoIicyhoIder
A80: ='jobinfo(2)'!$C$1 -> Johnson, Paul & Tamra | C80: ='jobinfo(2)'!$C$6 -> TBD | D80: Title __________________
A82: Contractor Representative's Signature __________________________/ ____________________________ | C82: /Contractor Representative Name | D82: ='jobinfo(2)'!C112 -> Joe Jones, PM 216.450.7228

Sheet SUB MIT
A1: ** GENERAL AUTHORIZATION ** | E1: OWNER HEREBY SPECIFICALLY REQUESTS THAT EMS Mitigation & CPS Packout / Cleaning of
A2: =+'jobinfo(2)'!$C$100 -> All Phase Consulting, LLC | E2: Personal Property (ONLY) PAYMENTS ; REBUILD Items Excluded: PAYMENTS BE PAID TO:
A3: =+'jobinfo(2)'!C$109 -> Providing Cost Estimating & Project Management Services
A4: =+'jobinfo(2)'!$C$101 -> WWW.MYAPCLLC.COM | C4: =+'jobinfo(2)'!$C$102 -> Insured & GA Registered #09073201
A5: ='jobinfo(2)'!$C$107 -> 20810 AURORA RD | B5: =+'jobinfo(2)'!$C$103 -> 375 Rockbridge Road, Suite 172-343 | D5: =+'jobinfo(2)'!$C$105 -> ECI 531 FIFTH AVE,
A6: ='jobinfo(2)'!$C$108 -> BEDFORD,OH 44146 | B6: =+'jobinfo(2)'!$C$104 -> Lilburn, GA, 30047 | D6: =+'jobinfo(2)'!$C$106 -> PELHAM, NY 10803
A7: =+'jobinfo(2)'!$C$110 -> Five Generations of Great Work | C7: =+'jobinfo(2)'!$C$111 -> Five Generations of Pride & Skills
A8: COMPANY REP. | B8: =+'jobinfo(2)'!$C$112 -> Joe Jones, PM 216.450.7228 | C8: =+'jobinfo(2)'!$C$113 -> wsbjoe9@gmail.com
A9: COMPANY REP. #2 | B9: =+'jobinfo(2)'!$C$114 -> 404-446-9060 | C9: =+'jobinfo(2)'!$C$115 -> info@myapcllc.com
A10: Claim # | B10: ='jobinfo(2)'!$C$27 -> 0 | C10: Cst-owner Phone# | D10: ='jobinfo(2)'!$C$5 -> (216) 399-6191
A11: =+'jobinfo(2)'!$B$1 -> Property-Owner Name | B11: =+'jobinfo(2)'!C$1 -> Johnson, Paul & Tamra | C11: Customer Email | D11: ='jobinfo(2)'!$C$4 -> tringo68@yahoo.com
A12: =+'jobinfo(2)'!$B$2 -> Property address: street | B12: =+'jobinfo(2)'!$C$2 -> 9402 Shepard Road | C12: Co-Owner.cst#2 | D12: =+'jobinfo(2)'!$C$6 -> TBD
A13: =+'jobinfo(2)'!$B$3 -> Property city, state, zip | B13: =+'jobinfo(2)'!$C$3 -> Macedonia, OH, USA | C13: cst ph # 2 | D13: =+'jobinfo(2)'!$C$7 -> TBD
A14: =+'jobinfo(2)'!$B$26 -> Insurance Co. Name | B14: =+'jobinfo(2)'!$C$26 -> Allstate Insurance Company | C14: =+'jobinfo(2)'!$B$28 -> policy # | D14: =+'jobinfo(2)'!$C$27 -> 0
A15: =+'jobinfo(2)'!$B$46 -> Insurance Co. Phone | B15: =+'jobinfo(2)'!$C$46 -> (800) 255-7828 | C15: =+'jobinfo(2)'!$C$29 -> 0
A16: =+'jobinfo(2)'!$B$30 -> DESK Adjuster DA | B16: =+'jobinfo(2)'!$C$30 -> 0 | C16: =+'jobinfo(2)'!$B$33 -> DA Email | D16: =+'jobinfo(2)'!$C$33 -> claims@claims.allstate.com
A17: =+'jobinfo(2)'!$B$31 -> DA Phone | B17: =+'jobinfo(2)'!$C$31 -> 888 656.8005 | C17: =+'jobinfo(2)'!$B$32 -> DA Ph. Ext. # | D17: =+'jobinfo(2)'!$C$32 -> 0
A20: Dear Insurance Company/ Mortgage Company and or To Whom It May Concern:
A21: The undersigned property owner agrees to employ | C21: =+$A$2 -> All Phase Consulting, LLC
A22: to assist in the repair of the above mentioned property that was damaged by
A23: =IF(ISBLANK('jobinfo(2)'!C11),"____________________",'jobinfo(2)'!C11) -> WATER | C23: on or about (date). | D23: =IF(ISBLANK('jobinfo(2)'!C12),"__________________________________",'jobinfo(2)'!C12) -> Friday, April 4, 2025
A24: Owners ACKNOWLEDGE as party of interest; | C24: =C21 -> All Phase Consulting, LLC
A25: and will be noted as such on all drafts, correspondence, and communications between the owner, insurer and my mortgage company. I hereby authorize all parties to discuss my account as it relates to the above noted loss and or repairs; as well as the release of draws for all repairs. This applies in full to it's employees / assigns / representatives.
A28: OWNER HEREBY SPECIFICALLY REQUESTS THAT EMS Mitigation & CPS Packout / Cleaning of | E28: EMS Mitigation & CPS Packout/Cleaning (ONLY) PAYMENTS BE PAID TO; REBUILD Items Excluded:
A29: Personal Property (ONLY) PAYMENTS ; REBUILD Items Excluded: PAYMENTS BE PAID TO:
A30: =+$C$24 -> All Phase Consulting, LLC | C30: =+'email cvr'!A13 -> EIN # | D30: =+'email cvr'!B13 -> TIN 83-226 0563
A31: X___________________________________ _____________ | C31: X_ _________________________________ _____________ | D31: =+'jobinfo(2)'!C22 -> Friday, April 4, 2025
A32: =IF(ISBLANK('jobinfo(2)'!C1),"__Property owner Signature________________________________",'jobinfo(2)'!C1) -> Johnson, Paul & Tamra | C32: =IF(ISBLANK('jobinfo(2)'!C6),"co-owner Signature______________________________",'jobinfo(2)'!C6) -> TBD
A34: =+$A$185 -> COMPANY REP. | B34: =+B66 -> Joe Jones, PM 216.450.7228 | D34: =+D66 -> wsbjoe9@gmail.com
A35: EMERGENCY SERVICES WORK AUTHORIZATION
A36: =+$A$2 -> All Phase Consulting, LLC
A37: =+A3 -> Providing Cost Estimating & Project Management Services | C37: =+$A$99 -> WWW.MYAPCLLC.COM
A39: =+A5 -> 20810 AURORA RD | B39: =+B5 -> 375 Rockbridge Road, Suite 172-343 | D39: =+D5 -> ECI 531 FIFTH AVE,
A40: =+A6 -> BEDFORD,OH 44146 | B40: =+B6 -> Lilburn, GA, 30047 | D40: =+D6 -> PELHAM, NY 10803
C41: =+$C$103 -> wsbjoe9@gmail.com
A42: =+A8 -> COMPANY REP. | B42: =+B34 -> Joe Jones, PM 216.450.7228 | C42: =+$D$185 -> wsbjoe9@gmail.com
A43: Claim Number: | B43: =+'jobinfo(2)'!C27 -> 0 | C43: =+B14 -> Allstate Insurance Company
A44: =+'jobinfo(2)'!B1 -> Property-Owner Name | B44: =+'jobinfo(2)'!C1 -> Johnson, Paul & Tamra | C44: =+A15 -> Insurance Co. Phone | D44: ='jobinfo(2)'!C31 -> 888 656.8005
A45: =+'jobinfo(2)'!B2 -> Property address: street | B45: =+'jobinfo(2)'!C2 -> 9402 Shepard Road
A46: =+'jobinfo(2)'!B3 -> Property city, state, zip | B46: =+'jobinfo(2)'!C3 -> Macedonia, OH, USA | C46: =+'jobinfo(2)'!B11 -> Cause of Loss | D46: =+A23 -> WATER
A47: =+'jobinfo(2)'!B4 -> Customer Email | B47: =+'jobinfo(2)'!C4 -> tringo68@yahoo.com | C47: =+'jobinfo(2)'!B5 -> Cst-owner Phone# | D47: =+D10 -> (216) 399-6191
B48: =+'jobinfo(2)'!C5 -> (216) 399-6191
A49: AUTHORIZATED ANTIMICROBIAL AGENTS; I understand that in the best judgment of Company, antimicrobial agents maybe used to inhibit the growth of micro-organisms during the drying/restoration process. I have received notice of the use of such. I understand it is beyond the expertise of Company to determine if someone is sensitive to its use and will hold Company harmless for its use. STOP WORK-HOLD HARMLESS. If the Company is not allowed to perform its recommended procedures and/or drying equipment is removed prematurely, I agree to release and hold Company harmless, indemnify Company against all claims or actions.
A52: =+$B$11 -> Johnson, Paul & Tamra | B52: as Owner, do hereby authorize | C52: =+A36 -> All Phase Consulting, LLC
A53: , their Assignee or Representative of and for herein named contractor to enter my property, furnish materials, supply all equipment and perform all labor necessary to preserve and protect my property from further damage. Including evaluation, inventory, storage and or cleaning of contents/personal property.
A54: I understand that I am personally responsible for all sums due to contractor for work related
A55: to LOSS TYPE of damages stated herein; performed at my property listed here.
A56: =+'jobinfo(2)'!C13 -> Interior Repairs LEVEL 1 | B56: =+'jobinfo(2)'!C14 -> Interior Repairs LEVEL 2 | C56: =+'jobinfo(2)'!C15 -> TBD | D56: =+'jobinfo(2)'!C16 -> Y
A57: I hereby assign the insurance rights; as specified herein, benefits, and proceeds under my | E57: I hereby assign the insurance rights; as specified herein, benefits, and proceeds under my
A58: insurance policy for the Emergency /mitigation services to: | C58: =+$A$2 -> All Phase Consulting, LLC | E58: insurance policy for the Emergency /mitigation services to: | G58: =+$A$2 -> All Phase Consulting, LLC
A59: Thus, monies due to named herein contractor are to be released without delay; solely, directly to contractor. | E59: Thus, monies due to named herein contractor are to be released without delay; solely, directly to contractor.
A60: This is payment for emergency and mitigation; for services that have already been performed; consequently the mortgage company has no interest in these specific funds; therefore make direct payment; refrain from including Mortgage Company name on the check. | E60: This is payment for emergency and mitigation; for services that have already been performed; consequently the mortgage company has no interest in these specific funds; therefore make direct payment; refrain from including Mortgage Company name on the check.
A61: OWNER HEREBY REQUESTS PAYMENTS BE PAID TO: | C61: =+C58 -> All Phase Consulting, LLC | D61: =+D30 -> TIN 83-226 0563 | E61: OWNER HEREBY REQUESTS PAYMENTS BE PAID TO: | G61: =+'email cvr'!B13 -> TIN 83-226 0563 | H61: =+C52 -> All Phase Consulting, LLC
A62: I/We select the option of overnight shipping for expedited delivery. | D62: =+'email cvr'!D13 -> FEDEX # 9836-2151-1
A63: This is a LEGALLY BINDING, Irrevocable Document; Fully Enforceable. Please read carefully
A64: =+$A$31 -> X___________________________________ _____________ | C64: =+$C$31 -> X_ _________________________________ _____________ | D64: =+$D$31 -> Friday, April 4, 2025
A65: =+B44 -> Johnson, Paul & Tamra | C65: =+C184 -> TBD
A66: =+$A$185 -> COMPANY REP. | B66: =+'jobinfo(2)'!C112 -> Joe Jones, PM 216.450.7228 | C66: =C34 -> 0 | D66: =+'jobinfo(2)'!C113 -> wsbjoe9@gmail.com
A67: “Assignments of Insurance Rights.” Includes Assignment of Benefits, the Right to Appraisal, the Rights to Sue and Direction to Pay. | J67: Assignment of Insurance Benefits & Direct Payment Authorization:
A68: =+'jobinfo(2)'!$C$100 -> All Phase Consulting, LLC
A69: =+'jobinfo(2)'!C$109 -> Providing Cost Estimating & Project Management Services
A70: =+'jobinfo(2)'!$C$101 -> WWW.MYAPCLLC.COM | C70: =+'jobinfo(2)'!$C$102 -> Insured & GA Registered #09073201
A71: =+'jobinfo(2)'!#REF! -> #REF! | B71: =+'jobinfo(2)'!$C$103 -> 375 Rockbridge Road, Suite 172-343 | D71: =+'jobinfo(2)'!$C$105 -> ECI 531 FIFTH AVE,
A72: =+'jobinfo(2)'!#REF! -> #REF! | B72: =+'jobinfo(2)'!$C$104 -> Lilburn, GA, 30047 | D72: =+'jobinfo(2)'!$C$106 -> PELHAM, NY 10803
A73: =+'jobinfo(2)'!$C$110 -> Five Generations of Great Work | C73: =+'jobinfo(2)'!$C$111 -> Five Generations of Pride & Skills
A74: COMPANY REP. | B74: =+'jobinfo(2)'!$C$112 -> Joe Jones, PM 216.450.7228 | C74: =+'jobinfo(2)'!$C$113 -> wsbjoe9@gmail.com
A75: COMPANY REP. #2 | B75: =+'jobinfo(2)'!$C$114 -> 404-446-9060 | C75: =+'jobinfo(2)'!$C$115 -> info@myapcllc.com
A76: =+'jobinfo(2)'!B26 -> Insurance Co. Name | B76: =+'jobinfo(2)'!C26 -> Allstate Insurance Company | C76: =+'jobinfo(2)'!B27 -> Claim # | D76: =IF(ISBLANK('jobinfo(2)'!C27),"________________________________",'jobinfo(2)'!$C$27) -> 0
A77: =+A44 -> Property-Owner Name | B77: =+B44 -> Johnson, Paul & Tamra | C77: =+'jobinfo(2)'!B11 -> Cause of Loss | D77: =+'jobinfo(2)'!C11 -> WATER
A78: =+A45 -> Property address: street | B78: =+B45 -> 9402 Shepard Road | C78: =+'jobinfo(2)'!B12 -> date of loss | D78: =+'jobinfo(2)'!C12 -> Friday, April 4, 2025
A79: =+A46 -> Property city, state, zip | B79: =+B46 -> Macedonia, OH, USA | C79: =+'jobinfo(2)'!B13 -> rebuild type 1 | D79: =+'jobinfo(2)'!C13 -> Interior Repairs LEVEL 1
A80: =+A47 -> Customer Email | B80: =+B47 -> tringo68@yahoo.com | C80: =+'jobinfo(2)'!B14 -> rebuild type 2 | D80: =+'jobinfo(2)'!C14 -> Interior Repairs LEVEL 2
A81: =+C47 -> Cst-owner Phone# | B81: =+B48 -> (216) 399-6191 | C81: =+'jobinfo(2)'!B15 -> rebuild type 3 | D81: =+'jobinfo(2)'!C15 -> TBD
A83: ASSIGNMENT OF INSURANCE BENEFITS; I, | C83: =+'jobinfo(2)'!C1 -> Johnson, Paul & Tamra
A84: ,as Owner, do hereby assign any and all insurance rights, benefits, proceeds and any causes of action, including APPRAISAL AND DEMAND Thereof, under applicable insurance policies to
A85: =+A68 -> All Phase Consulting, LLC | C85: =+C30 -> EIN # | D85: =+D30 -> TIN 83-226 0563
A86: their Assignee or Representative of and for herein named contractor for service rendered or to be rendered by Company. In this regard,I make this assignment in consideration of Company’s agreement to perform services and supply materials and otherwise perform its obligations under this contract, including not requiring full payment at the time of service. I also hereby direct my insurance carrier(s) to release any and all information requested by Company, for the direct purpose of obtaining actual benefits to be paid for services rendered or to be rendered.
A87: DIRECT PAYMENT AUTHORIZATION & PAYMENT TERMS
A88: I also hereby authorize and unequivocally instruct direct payment of any benefits or proceeds to Company. Mitigation & CPS Packout/Cleaning (ONLY) PAYMENTS BE PAID TO; REBUILD Items Excluded:PAYMENTS BE PAID TO:
A89: Payment terms are net upon completion. Late fees 1.5% monthly and reimbursement for costs of collection.
A90: I/We select the option of overnight shipping for expedited delivery.
A94: X X | D94: =+D31 -> Friday, April 4, 2025
A95: =+'jobinfo(2)'!C1 -> Johnson, Paul & Tamra | B95: =+'jobinfo(2)'!C6 -> TBD | C95: =C66 -> 0
A96: CONTRACTOR & HOMEOWNER AGREEMENT
A97: =+'jobinfo(2)'!$C$100 -> All Phase Consulting, LLC
A98: =+'jobinfo(2)'!C$109 -> Providing Cost Estimating & Project Management Services
A99: =+'jobinfo(2)'!$C$101 -> WWW.MYAPCLLC.COM | C99: =+'jobinfo(2)'!$C$102 -> Insured & GA Registered #09073201
A100: =+'jobinfo(2)'!$C$107 -> 20810 AURORA RD | B100: =+'jobinfo(2)'!$C$103 -> 375 Rockbridge Road, Suite 172-343 | D100: =+'jobinfo(2)'!$C$105 -> ECI 531 FIFTH AVE,
A101: =+'jobinfo(2)'!$C$108 -> BEDFORD,OH 44146 | B101: =+'jobinfo(2)'!$C$104 -> Lilburn, GA, 30047 | D101: =+'jobinfo(2)'!$C$106 -> PELHAM, NY 10803
A102: =+'jobinfo(2)'!$C$110 -> Five Generations of Great Work | C102: =+'jobinfo(2)'!$C$111 -> Five Generations of Pride & Skills
A103: COMPANY REP. | B103: =+'jobinfo(2)'!$C$112 -> Joe Jones, PM 216.450.7228 | C103: =+'jobinfo(2)'!$C$113 -> wsbjoe9@gmail.com
A104: COMPANY REP. #2 | B104: =+'jobinfo(2)'!$C$114 -> 404-446-9060 | C104: =+'jobinfo(2)'!$C$115 -> info@myapcllc.com
A105: =+B11 -> Johnson, Paul & Tamra | B105: =+B12 -> 9402 Shepard Road | C105: =+B13 -> Macedonia, OH, USA | D105: as OWNER. And
A107: =+A97 -> All Phase Consulting, LLC | C107: as CONTRACTOR. | D107: Concerning
A109: RELATED DAMAGES : | B109: =+$A$23 -> WATER | C109: on or about | D109: =+D23 -> Friday, April 4, 2025
A111: The said parties, for the considerations hereinafter mentioned, hereby agree to the following:
A113: 1. The CONTRACTOR agrees to provide all of the labor and materials required to perform the following
A114: work as per attachment; ( ____) pages. subject to adjustment based upon mutually agreed scope of work.
A115: =+A56 -> Interior Repairs LEVEL 1 | B115: =+B56 -> Interior Repairs LEVEL 2 | C115: =+C56 -> TBD | D115: =+D56 -> Y
A117: 2. The OWNER hereby agrees to pay the CONTRACTOR, for the aforesaid materials & labor, $___ _________
...

Sheet SUBC
A1: ** GENERAL AUTHORIZATION ** | E1: OWNER HEREBY SPECIFICALLY REQUESTS THAT EMS Mitigation & CPS Packout / Cleaning of
A2: =+'jobinfo(2)'!$C$100 -> All Phase Consulting, LLC | E2: Personal Property (ONLY) PAYMENTS ; REBUILD Items Excluded: PAYMENTS BE PAID TO:
A3: =+'jobinfo(2)'!C$109 -> Providing Cost Estimating & Project Management Services
A4: =+'jobinfo(2)'!$C$101 -> WWW.MYAPCLLC.COM | C4: =+'jobinfo(2)'!$C$102 -> Insured & GA Registered #09073201
A5: ='jobinfo(2)'!$C$107 -> 20810 AURORA RD | B5: =+'jobinfo(2)'!$C$103 -> 375 Rockbridge Road, Suite 172-343 | D5: =+'jobinfo(2)'!$C$105 -> ECI 531 FIFTH AVE,
A6: ='jobinfo(2)'!$C$108 -> BEDFORD,OH 44146 | B6: =+'jobinfo(2)'!$C$104 -> Lilburn, GA, 30047 | D6: =+'jobinfo(2)'!$C$106 -> PELHAM, NY 10803
A7: =+'jobinfo(2)'!$C$110 -> Five Generations of Great Work | C7: =+'jobinfo(2)'!$C$111 -> Five Generations of Pride & Skills
A8: COMPANY REP. | B8: =+'jobinfo(2)'!$C$112 -> Joe Jones, PM 216.450.7228 | C8: =+'jobinfo(2)'!$C$113 -> wsbjoe9@gmail.com
A9: COMPANY REP. #2 | B9: =+'jobinfo(2)'!$C$114 -> 404-446-9060 | C9: =+'jobinfo(2)'!$C$115 -> info@myapcllc.com
A10: Claim # | B10: ='jobinfo(2)'!$C$27 -> 0 | C10: Cst-owner Phone# | D10: ='jobinfo(2)'!$C$5 -> (216) 399-6191
A11: =+'jobinfo(2)'!$B$1 -> Property-Owner Name | B11: =+'jobinfo(2)'!C$1 -> Johnson, Paul & Tamra | C11: Customer Email | D11: ='jobinfo(2)'!$C$4 -> tringo68@yahoo.com
A12: =+'jobinfo(2)'!$B$2 -> Property address: street | B12: =+'jobinfo(2)'!$C$2 -> 9402 Shepard Road | C12: Co-Owner.cst#2 | D12: =+'jobinfo(2)'!$C$6 -> TBD
A13: =+'jobinfo(2)'!$B$3 -> Property city, state, zip | B13: =+'jobinfo(2)'!$C$3 -> Macedonia, OH, USA | C13: cst ph # 2 | D13: =+'jobinfo(2)'!$C$7 -> TBD
A14: =+'jobinfo(2)'!$B$26 -> Insurance Co. Name | B14: =+'jobinfo(2)'!$C$26 -> Allstate Insurance Company | C14: =+'jobinfo(2)'!$B$28 -> policy # | D14: =+'jobinfo(2)'!$C$27 -> 0
A15: =+'jobinfo(2)'!$B$46 -> Insurance Co. Phone | B15: =+'jobinfo(2)'!$C$46 -> (800) 255-7828 | C15: =+'jobinfo(2)'!$C$29 -> 0
A16: =+'jobinfo(2)'!$B$30 -> DESK Adjuster DA | B16: =+'jobinfo(2)'!$C$30 -> 0 | C16: =+'jobinfo(2)'!$B$33 -> DA Email | D16: =+'jobinfo(2)'!$C$33 -> claims@claims.allstate.com
A17: =+'jobinfo(2)'!$B$31 -> DA Phone | B17: =+'jobinfo(2)'!$C$31 -> 888 656.8005 | C17: =+'jobinfo(2)'!$B$32 -> DA Ph. Ext. # | D17: =+'jobinfo(2)'!$C$32 -> 0
A20: Dear Insurance Company/ Mortgage Company and or To Whom It May Concern:
A21: The undersigned property owner agrees to employ | C21: =+$A$2 -> All Phase Consulting, LLC
A22: to assist in the repair of the above mentioned property that was damaged by
A23: =IF(ISBLANK('jobinfo(2)'!C11),"____________________",'jobinfo(2)'!C11) -> WATER | C23: on or about (date). | D23: =IF(ISBLANK('jobinfo(2)'!C12),"__________________________________",'jobinfo(2)'!C12) -> Friday, April 4, 2025
A24: Owners ACKNOWLEDGE as party of interest; | C24: =C21 -> All Phase Consulting, LLC
A25: and will be noted as such on all drafts, correspondence, and communications between the owner, insurer and my mortgage company. I hereby authorize all parties to discuss my account as it relates to the above noted loss and or repairs; as well as the release of draws for all repairs. This applies in full to it's employees / assigns / representatives.
A28: OWNER HEREBY SPECIFICALLY REQUESTS THAT EMS Mitigation & CPS Packout / Cleaning of | E28: EMS Mitigation & CPS Packout/Cleaning (ONLY) PAYMENTS BE PAID TO; REBUILD Items Excluded:
A29: Personal Property (ONLY) PAYMENTS ; PAYMENTS BE PAID TO REBUILD Items Excluded::
A30: =+$C$24 -> All Phase Consulting, LLC | C30: =+'email cvr'!A13 -> EIN # | D30: =+'email cvr'!B13 -> TIN 83-226 0563
A31: X___________________________________ _____________ | C31: X_ _________________________________ _____________ | D31: =+'jobinfo(2)'!C22 -> Friday, April 4, 2025
A32: =IF(ISBLANK('jobinfo(2)'!C1),"__Property owner Signature________________________________",'jobinfo(2)'!C1) -> Johnson, Paul & Tamra | C32: =IF(ISBLANK('jobinfo(2)'!C6),"co-owner Signature______________________________",'jobinfo(2)'!C6) -> TBD
A34: =+$A$185 -> COMPANY REP. | B34: =+B66 -> Joe Jones, PM 216.450.7228 | D34: =+D66 -> wsbjoe9@gmail.com
A35: EMERGENCY SERVICES WORK AUTHORIZATION
A36: =+$A$2 -> All Phase Consulting, LLC
A37: =+A3 -> Providing Cost Estimating & Project Management Services | C37: =+$A$99 -> WWW.MYAPCLLC.COM
A39: =+A5 -> 20810 AURORA RD | B39: =+B5 -> 375 Rockbridge Road, Suite 172-343 | D39: =+D5 -> ECI 531 FIFTH AVE,
A40: =+A6 -> BEDFORD,OH 44146 | B40: =+B6 -> Lilburn, GA, 30047 | D40: =+D6 -> PELHAM, NY 10803
C41: =+$C$103 -> wsbjoe9@gmail.com
A42: =+A8 -> COMPANY REP. | B42: =+B34 -> Joe Jones, PM 216.450.7228 | C42: =+$D$185 -> wsbjoe9@gmail.com
A43: Claim Number: | B43: =+'jobinfo(2)'!C27 -> 0 | C43: =+B14 -> Allstate Insurance Company
A44: =+'jobinfo(2)'!B1 -> Property-Owner Name | B44: =+'jobinfo(2)'!C1 -> Johnson, Paul & Tamra | C44: =+A15 -> Insurance Co. Phone | D44: ='jobinfo(2)'!C31 -> 888 656.8005
A45: =+'jobinfo(2)'!B2 -> Property address: street | B45: =+'jobinfo(2)'!C2 -> 9402 Shepard Road
A46: =+'jobinfo(2)'!B3 -> Property city, state, zip | B46: =+'jobinfo(2)'!C3 -> Macedonia, OH, USA | C46: =+'jobinfo(2)'!B11 -> Cause of Loss | D46: =+A23 -> WATER
A47: =+'jobinfo(2)'!B4 -> Customer Email | B47: =+'jobinfo(2)'!C4 -> tringo68@yahoo.com | C47: =+'jobinfo(2)'!B5 -> Cst-owner Phone# | D47: =+D10 -> (216) 399-6191
B48: =+'jobinfo(2)'!C5 -> (216) 399-6191
A49: AUTHORIZATED ANTIMICROBIAL AGENTS; I understand that in the best judgment of Company, antimicrobial agents maybe used to inhibit the growth of micro-organisms during the drying/restoration process. I have received notice of the use of such. I understand it is beyond the expertise of Company to determine if someone is sensitive to its use and will hold Company harmless for its use. STOP WORK-HOLD HARMLESS. If the Company is not allowed to perform its recommended procedures and/or drying equipment is removed prematurely, I agree to release and hold Company harmless, indemnify Company against all claims or actions.
A52: =+$B$11 -> Johnson, Paul & Tamra | B52: as Owner, do hereby authorize | C52: =+A36 -> All Phase Consulting, LLC
A53: , their Assignee or Representative of and for herein named contractor to enter my property, furnish materials, supply all equipment and perform all labor necessary to preserve and protect my property from further damage. Including evaluation, inventory, storage and or cleaning of contents/personal property.
A54: I understand that I am personally responsible for all sums due to contractor for work related
A55: to LOSS TYPE of damages stated herein; performed at my property listed here.
A56: =+'jobinfo(2)'!C13 -> Interior Repairs LEVEL 1 | B56: =+'jobinfo(2)'!C14 -> Interior Repairs LEVEL 2 | C56: =+'jobinfo(2)'!C15 -> TBD | D56: =+'jobinfo(2)'!C16 -> Y
A57: I hereby assign the insurance rights; as specified herein, benefits, and proceeds under my | E57: I hereby assign the insurance rights; as specified herein, benefits, and proceeds under my
A58: insurance policy for the Emergency /mitigation services to: | C58: =+$A$2 -> All Phase Consulting, LLC | E58: insurance policy for the Emergency /mitigation services to: | G58: =+$A$2 -> All Phase Consulting, LLC
A59: Thus, monies due to named herein contractor are to be released without delay; solely, directly to contractor. | E59: Thus, monies due to named herein contractor are to be released without delay; solely, directly to contractor.
A60: This is payment for emergency and mitigation; for services that have already been performed; consequently the mortgage company has no interest in these specific funds; therefore make direct payment; refrain from including Mortgage Company name on the check. | E60: This is payment for emergency and mitigation; for services that have already been performed; consequently the mortgage company has no interest in these specific funds; therefore make direct payment; refrain from including Mortgage Company name on the check.
A61: OWNER HEREBY REQUESTS PAYMENTS BE PAID TO: | C61: =+C58 -> All Phase Consulting, LLC | D61: =+D30 -> TIN 83-226 0563 | E61: OWNER HEREBY REQUESTS PAYMENTS BE PAID TO: | G61: =+'email cvr'!B13 -> TIN 83-226 0563 | H61: =+C52 -> All Phase Consulting, LLC
A62: I/We select the option of overnight shipping for expedited delivery. | D62: =+'email cvr'!D13 -> FEDEX # 9836-2151-1
A63: This is a LEGALLY BINDING, Irrevocable Document; Fully Enforceable. Please read carefully
A64: =+$A$31 -> X___________________________________ _____________ | C64: =+$C$31 -> X_ _________________________________ _____________ | D64: =+$D$31 -> Friday, April 4, 2025
A65: =+B44 -> Johnson, Paul & Tamra | C65: =+C184 -> TBD
A66: =+$A$185 -> COMPANY REP. | B66: =+'jobinfo(2)'!C112 -> Joe Jones, PM 216.450.7228 | C66: =C34 -> 0 | D66: =+'jobinfo(2)'!C113 -> wsbjoe9@gmail.com
A67: “Assignments of Insurance Rights.” Includes Assignment of Benefits, the Right to Appraisal, the Rights to Sue and Direction to Pay. | J67: Assignment of Insurance Benefits & Direct Payment Authorization:
A68: =+'jobinfo(2)'!$C$100 -> All Phase Consulting, LLC
A69: =+'jobinfo(2)'!C$109 -> Providing Cost Estimating & Project Management Services
A70: =+'jobinfo(2)'!$C$101 -> WWW.MYAPCLLC.COM | C70: =+'jobinfo(2)'!$C$102 -> Insured & GA Registered #09073201
A71: =+'jobinfo(2)'!#REF! -> #REF! | B71: =+'jobinfo(2)'!$C$103 -> 375 Rockbridge Road, Suite 172-343 | D71: =+'jobinfo(2)'!$C$105 -> ECI 531 FIFTH AVE,
A72: =+'jobinfo(2)'!#REF! -> #REF! | B72: =+'jobinfo(2)'!$C$104 -> Lilburn, GA, 30047 | D72: =+'jobinfo(2)'!$C$106 -> PELHAM, NY 10803
A73: =+'jobinfo(2)'!$C$110 -> Five Generations of Great Work | C73: =+'jobinfo(2)'!$C$111 -> Five Generations of Pride & Skills
A74: COMPANY REP. | B74: =+'jobinfo(2)'!$C$112 -> Joe Jones, PM 216.450.7228 | C74: =+'jobinfo(2)'!$C$113 -> wsbjoe9@gmail.com
A75: COMPANY REP. #2 | B75: =+'jobinfo(2)'!$C$114 -> 404-446-9060 | C75: =+'jobinfo(2)'!$C$115 -> info@myapcllc.com
A76: =+'jobinfo(2)'!B26 -> Insurance Co. Name | B76: =+'jobinfo(2)'!C26 -> Allstate Insurance Company | C76: =+'jobinfo(2)'!B27 -> Claim # | D76: =IF(ISBLANK('jobinfo(2)'!C27),"________________________________",'jobinfo(2)'!$C$27) -> 0
A77: =+A44 -> Property-Owner Name | B77: =+B44 -> Johnson, Paul & Tamra | C77: =+'jobinfo(2)'!B11 -> Cause of Loss | D77: =+'jobinfo(2)'!C11 -> WATER
A78: =+A45 -> Property address: street | B78: =+B45 -> 9402 Shepard Road | C78: =+'jobinfo(2)'!B12 -> date of loss | D78: =+'jobinfo(2)'!C12 -> Friday, April 4, 2025
A79: =+A46 -> Property city, state, zip | B79: =+B46 -> Macedonia, OH, USA | C79: =+'jobinfo(2)'!B13 -> rebuild type 1 | D79: =+'jobinfo(2)'!C13 -> Interior Repairs LEVEL 1
A80: =+A47 -> Customer Email | B80: =+B47 -> tringo68@yahoo.com | C80: =+'jobinfo(2)'!B14 -> rebuild type 2 | D80: =+'jobinfo(2)'!C14 -> Interior Repairs LEVEL 2
A81: =+C47 -> Cst-owner Phone# | B81: =+B48 -> (216) 399-6191 | C81: =+'jobinfo(2)'!B15 -> rebuild type 3 | D81: =+'jobinfo(2)'!C15 -> TBD
A83: ASSIGNMENT OF INSURANCE BENEFITS; I, | C83: =+'jobinfo(2)'!C1 -> Johnson, Paul & Tamra
A84: ,as Owner, do hereby assign any and all insurance rights, benefits, proceeds and any causes of action, including APPRAISAL AND DEMAND Thereof, under applicable insurance policies to
A85: =+A68 -> All Phase Consulting, LLC | C85: =+C30 -> EIN # | D85: =+D30 -> TIN 83-226 0563
A86: their Assignee or Representative of and for herein named contractor for service rendered or to be rendered by Company. In this regard,I make this assignment in consideration of Company’s agreement to perform services and supply materials and otherwise perform its obligations under this contract, including not requiring full payment at the time of service. I also hereby direct my insurance carrier(s) to release any and all information requested by Company, for the direct purpose of obtaining actual benefits to be paid for services rendered or to be rendered.
A87: DIRECT PAYMENT AUTHORIZATION & PAYMENT TERMS
A88: I also hereby authorize and unequivocally instruct direct payment of any benefits or proceeds to Company. Mitigation & CPS Packout/Cleaning (ONLY) PAYMENTS BE PAID TO; REBUILD Items Excluded:PAYMENTS BE PAID TO:
A89: Payment terms are net upon completion. Late fees 1.5% monthly and reimbursement for costs of collection.
A90: I/We select the option of overnight shipping for expedited delivery.
A94: X X | D94: =+D31 -> Friday, April 4, 2025
A95: =+'jobinfo(2)'!C1 -> Johnson, Paul & Tamra | B95: =+'jobinfo(2)'!C6 -> TBD | C95: =C66 -> 0
A96: CONTRACTOR & HOMEOWNER AGREEMENT
A97: =+'jobinfo(2)'!$C$100 -> All Phase Consulting, LLC
A98: =+'jobinfo(2)'!C$109 -> Providing Cost Estimating & Project Management Services
A99: =+'jobinfo(2)'!$C$101 -> WWW.MYAPCLLC.COM | C99: =+'jobinfo(2)'!$C$102 -> Insured & GA Registered #09073201
A100: =+'jobinfo(2)'!$C$107 -> 20810 AURORA RD | B100: =+'jobinfo(2)'!$C$103 -> 375 Rockbridge Road, Suite 172-343 | D100: =+'jobinfo(2)'!$C$105 -> ECI 531 FIFTH AVE,
A101: =+'jobinfo(2)'!$C$108 -> BEDFORD,OH 44146 | B101: =+'jobinfo(2)'!$C$104 -> Lilburn, GA, 30047 | D101: =+'jobinfo(2)'!$C$106 -> PELHAM, NY 10803
A102: =+'jobinfo(2)'!$C$110 -> Five Generations of Great Work | C102: =+'jobinfo(2)'!$C$111 -> Five Generations of Pride & Skills
A103: COMPANY REP. | B103: =+'jobinfo(2)'!$C$112 -> Joe Jones, PM 216.450.7228 | C103: =+'jobinfo(2)'!$C$113 -> wsbjoe9@gmail.com
A104: COMPANY REP. #2 | B104: =+'jobinfo(2)'!$C$114 -> 404-446-9060 | C104: =+'jobinfo(2)'!$C$115 -> info@myapcllc.com
A105: =+B11 -> Johnson, Paul & Tamra | B105: =+B12 -> 9402 Shepard Road | C105: =+B13 -> Macedonia, OH, USA | D105: as OWNER. And
A107: =+A97 -> All Phase Consulting, LLC | C107: as CONTRACTOR. | D107: Concerning
A109: RELATED DAMAGES : | B109: =+$A$23 -> WATER | C109: on or about | D109: =+D23 -> Friday, April 4, 2025
A111: The said parties, for the considerations hereinafter mentioned, hereby agree to the following:
A113: 1. The CONTRACTOR agrees to provide all of the labor and materials required to perform the following
A114: work as per attachment; ( ____) pages. subject to adjustment based upon mutually agreed scope of work.
A115: =+A56 -> Interior Repairs LEVEL 1 | B115: =+B56 -> Interior Repairs LEVEL 2 | C115: =+C56 -> TBD | D115: =+D56 -> Y
A117: 2. The OWNER hereby agrees to pay the CONTRACTOR, for the aforesaid materials & labor, $___ _________
...

Sheet signpgs (3)
A1: ** GENERAL AUTHORIZATION ** | E1: OWNER HEREBY SPECIFICALLY REQUESTS THAT ALL Payments for the Rebuild BE PAID TO: Owner & Contractor
A2: =+'jobinfo(2)'!$C$100 -> All Phase Consulting, LLC
A3: =+'jobinfo(2)'!C$109 -> Providing Cost Estimating & Project Management Services
A4: =+'jobinfo(2)'!$C$101 -> WWW.MYAPCLLC.COM | C4: =+'jobinfo(2)'!$C$102 -> Insured & GA Registered #09073201
A5: ='jobinfo(2)'!$C$107 -> 20810 AURORA RD | B5: =+'jobinfo(2)'!$C$103 -> 375 Rockbridge Road, Suite 172-343 | D5: =+'jobinfo(2)'!$C$105 -> ECI 531 FIFTH AVE,
A6: ='jobinfo(2)'!$C$108 -> BEDFORD,OH 44146 | B6: =+'jobinfo(2)'!$C$104 -> Lilburn, GA, 30047 | D6: =+'jobinfo(2)'!$C$106 -> PELHAM, NY 10803
A7: =+'jobinfo(2)'!$C$110 -> Five Generations of Great Work | C7: =+'jobinfo(2)'!$C$111 -> Five Generations of Pride & Skills
A8: COMPANY REP. | B8: =+'jobinfo(2)'!$C$112 -> Joe Jones, PM 216.450.7228 | C8: =+'jobinfo(2)'!$C$113 -> wsbjoe9@gmail.com
A9: COMPANY REP. #2 | B9: =+'jobinfo(2)'!$C$114 -> 404-446-9060 | C9: =+'jobinfo(2)'!$C$115 -> info@myapcllc.com
A10: Claim # | B10: ='jobinfo(2)'!$C$27 -> 0 | C10: Cst-owner Phone# | D10: ='jobinfo(2)'!$C$5 -> (216) 399-6191
A11: =+'jobinfo(2)'!$B$1 -> Property-Owner Name | B11: =+'jobinfo(2)'!C$1 -> Johnson, Paul & Tamra | C11: Customer Email | D11: ='jobinfo(2)'!$C$4 -> tringo68@yahoo.com
A12: =+'jobinfo(2)'!$B$2 -> Property address: street | B12: =+'jobinfo(2)'!$C$2 -> 9402 Shepard Road | C12: Co-Owner.cst#2 | D12: =+'jobinfo(2)'!$C$6 -> TBD
A13: =+'jobinfo(2)'!$B$3 -> Property city, state, zip | B13: =+'jobinfo(2)'!$C$3 -> Macedonia, OH, USA | C13: cst ph # 2 | D13: =+'jobinfo(2)'!$C$7 -> TBD
A14: =+'jobinfo(2)'!$B$26 -> Insurance Co. Name | B14: =+'jobinfo(2)'!$C$26 -> Allstate Insurance Company | C14: =+'jobinfo(2)'!$B$28 -> policy # | D14: =+'jobinfo(2)'!$C$27 -> 0
A15: =+'jobinfo(2)'!$B$46 -> Insurance Co. Phone | B15: =+'jobinfo(2)'!$C$46 -> (800) 255-7828 | C15: =+'jobinfo(2)'!$C$29 -> 0
A16: =+'jobinfo(2)'!$B$30 -> DESK Adjuster DA | B16: =+'jobinfo(2)'!$C$30 -> 0 | C16: =+'jobinfo(2)'!$B$33 -> DA Email | D16: =+'jobinfo(2)'!$C$33 -> claims@claims.allstate.com
A17: =+'jobinfo(2)'!$B$31 -> DA Phone | B17: =+'jobinfo(2)'!$C$31 -> 888 656.8005 | C17: =+'jobinfo(2)'!$B$32 -> DA Ph. Ext. # | D17: =+'jobinfo(2)'!$C$32 -> 0
A20: Dear Insurance Company/ Mortgage Company and or To Whom It May Concern:
A21: The undersigned property owner agrees to employ | C21: =+$A$2 -> All Phase Consulting, LLC
A22: to assist in the repair of the above mentioned property that was damaged by
A23: =IF(ISBLANK('jobinfo(2)'!C11),"____________________",'jobinfo(2)'!C11) -> WATER | C23: on or about (date). | D23: =IF(ISBLANK('jobinfo(2)'!C12),"__________________________________",'jobinfo(2)'!C12) -> Friday, April 4, 2025
A24: Owners ACKNOWLEDGE as party of interest; | C24: =C21 -> All Phase Consulting, LLC
A25: and will be noted as such on all drafts, correspondence, and communications between the owner, insurer and my mortgage company. I hereby authorize all parties to discuss my account as it relates to the above noted loss and or repairs; as well as the release of draws for all repairs. This applies in full to it's employees / assigns / representatives.
A29: OWNER HEREBY SPECIFICALLY REQUESTS THAT ALL Payments for the Rebuild BE PAID TO: Owner & Contractor
A30: =+$C$24 -> All Phase Consulting, LLC | C30: =+'email cvr'!A13 -> EIN # | D30: =+'email cvr'!B13 -> TIN 83-226 0563
A31: X___________________________________ _____________ | C31: X_ _________________________________ _____________ | D31: =+'jobinfo(2)'!C22 -> Friday, April 4, 2025
A32: =IF(ISBLANK('jobinfo(2)'!C1),"__Property owner Signature________________________________",'jobinfo(2)'!C1) -> Johnson, Paul & Tamra | C32: =IF(ISBLANK('jobinfo(2)'!C6),"co-owner Signature______________________________",'jobinfo(2)'!C6) -> TBD
A34: =+$A$185 -> COMPANY REP. | B34: =+B66 -> Joe Jones, PM 216.450.7228 | D34: =+D66 -> wsbjoe9@gmail.com
A35: EMERGENCY SERVICES WORK AUTHORIZATION
A36: =+$A$2 -> All Phase Consulting, LLC
A37: =+A3 -> Providing Cost Estimating & Project Management Services | C37: =+$A$99 -> WWW.MYAPCLLC.COM
A39: =+A5 -> 20810 AURORA RD | B39: =+B5 -> 375 Rockbridge Road, Suite 172-343 | D39: =+D5 -> ECI 531 FIFTH AVE,
A40: =+A6 -> BEDFORD,OH 44146 | B40: =+B6 -> Lilburn, GA, 30047 | D40: =+D6 -> PELHAM, NY 10803
C41: =+$C$103 -> wsbjoe9@gmail.com
A42: =+A8 -> COMPANY REP. | B42: =+B34 -> Joe Jones, PM 216.450.7228 | C42: =+$D$185 -> wsbjoe9@gmail.com
A43: Claim Number: | B43: =+'jobinfo(2)'!C27 -> 0 | C43: =+B14 -> Allstate Insurance Company
A44: =+'jobinfo(2)'!B1 -> Property-Owner Name | B44: =+'jobinfo(2)'!C1 -> Johnson, Paul & Tamra | C44: =+A15 -> Insurance Co. Phone | D44: ='jobinfo(2)'!C31 -> 888 656.8005
A45: =+'jobinfo(2)'!B2 -> Property address: street | B45: =+'jobinfo(2)'!C2 -> 9402 Shepard Road
A46: =+'jobinfo(2)'!B3 -> Property city, state, zip | B46: =+'jobinfo(2)'!C3 -> Macedonia, OH, USA | C46: =+'jobinfo(2)'!B11 -> Cause of Loss | D46: =+A23 -> WATER
A47: =+'jobinfo(2)'!B4 -> Customer Email | B47: =+'jobinfo(2)'!C4 -> tringo68@yahoo.com | C47: =+'jobinfo(2)'!B5 -> Cst-owner Phone# | D47: =+D10 -> (216) 399-6191
B48: =+'jobinfo(2)'!C5 -> (216) 399-6191
A49: AUTHORIZATED ANTIMICROBIAL AGENTS; I understand that in the best judgment of Company, antimicrobial agents maybe used to inhibit the growth of micro-organisms during the drying/restoration process. I have received notice of the use of such. I understand it is beyond the expertise of Company to determine if someone is sensitive to its use and will hold Company harmless for its use. STOP WORK-HOLD HARMLESS. If the Company is not allowed to perform its recommended procedures and/or drying equipment is removed prematurely, I agree to release and hold Company harmless, indemnify Company against all claims or actions.
A52: =+$B$11 -> Johnson, Paul & Tamra | B52: as Owner, do hereby authorize | C52: =+A36 -> All Phase Consulting, LLC
A53: , their Assignee or Representative of and for herein named contractor to enter my property, furnish materials, supply all equipment and perform all labor necessary to preserve and protect my property from further damage. Including evaluation, inventory, storage and or cleaning of contents/personal property.
A54: I understand that I am personally responsible for all sums due to contractor for work related
A55: to LOSS TYPE of damages stated herein; performed at my property listed here.
A56: =+'jobinfo(2)'!C13 -> Interior Repairs LEVEL 1 | B56: =+'jobinfo(2)'!C14 -> Interior Repairs LEVEL 2 | C56: =+'jobinfo(2)'!C15 -> TBD | D56: =+'jobinfo(2)'!C16 -> Y
A57: I hereby assign the insurance rights; as specified herein, benefits, and proceeds under my | E57: I hereby assign the insurance rights; as specified herein, benefits, and proceeds under my
A58: insurance policy for the Emergency /mitigation services to: | C58: =+$A$2 -> All Phase Consulting, LLC | E58: insurance policy for the Emergency /mitigation services to: | G58: =+$A$2 -> All Phase Consulting, LLC
A59: Thus, monies due to named herein contractor are to be released without delay; solely, directly to contractor. | E59: Thus, monies due to named herein contractor are to be released without delay; solely, directly to contractor.
A60: This is payment for emergency and mitigation; for services that have already been performed; consequently the mortgage company has no interest in these specific funds; therefore make direct payment; refrain from including Mortgage Company name on the check. | E60: This is payment for emergency and mitigation; for services that have already been performed; consequently the mortgage company has no interest in these specific funds; therefore make direct payment; refrain from including Mortgage Company name on the check.
A61: OWNER HEREBY SPECIFICALLY REQUESTS THAT ALL Payments for the Rebuild BE PAID TO: Owner & Contractor | E61: OWNER HEREBY REQUESTS PAYMENTS BE PAID TO: | G61: =+'email cvr'!B13 -> TIN 83-226 0563 | H61: =+C52 -> All Phase Consulting, LLC
A62: I/We select the option of overnight shipping for expedited delivery. | D62: =+'email cvr'!D13 -> FEDEX # 9836-2151-1
A63: This is a LEGALLY BINDING, Irrevocable Document; Fully Enforceable. Please read carefully
A64: =+$A$31 -> X___________________________________ _____________ | C64: =+$C$31 -> X_ _________________________________ _____________ | D64: =+$D$31 -> Friday, April 4, 2025
A65: =+B44 -> Johnson, Paul & Tamra | C65: =+C184 -> TBD
A66: =+$A$185 -> COMPANY REP. | B66: =+'jobinfo(2)'!C112 -> Joe Jones, PM 216.450.7228 | C66: =C34 -> 0 | D66: =+'jobinfo(2)'!C113 -> wsbjoe9@gmail.com
A67: “Assignments of Insurance Rights.” Includes Assignment of Benefits, the Right to Appraisal, the Rights to Sue and Direction to Pay. | J67: Assignment of Insurance Benefits & Direct Payment Authorization:
A68: =+'jobinfo(2)'!$C$100 -> All Phase Consulting, LLC
A69: =+'jobinfo(2)'!C$109 -> Providing Cost Estimating & Project Management Services
A70: =+'jobinfo(2)'!$C$101 -> WWW.MYAPCLLC.COM | C70: =+'jobinfo(2)'!$C$102 -> Insured & GA Registered #09073201
A71: ='jobinfo(2)'!C107 -> 20810 AURORA RD | B71: =+'jobinfo(2)'!$C$103 -> 375 Rockbridge Road, Suite 172-343 | D71: =+'jobinfo(2)'!$C$105 -> ECI 531 FIFTH AVE,
A72: ='jobinfo(2)'!C108 -> BEDFORD,OH 44146 | B72: =+'jobinfo(2)'!$C$104 -> Lilburn, GA, 30047 | D72: =+'jobinfo(2)'!$C$106 -> PELHAM, NY 10803
A73: =+'jobinfo(2)'!$C$110 -> Five Generations of Great Work | C73: =+'jobinfo(2)'!$C$111 -> Five Generations of Pride & Skills
A74: COMPANY REP. | B74: =+'jobinfo(2)'!$C$112 -> Joe Jones, PM 216.450.7228 | C74: =+'jobinfo(2)'!$C$113 -> wsbjoe9@gmail.com
A75: COMPANY REP. #2 | B75: =+'jobinfo(2)'!$C$114 -> 404-446-9060 | C75: =+'jobinfo(2)'!$C$115 -> info@myapcllc.com
A76: =+'jobinfo(2)'!B26 -> Insurance Co. Name | B76: =+'jobinfo(2)'!C26 -> Allstate Insurance Company | C76: =+'jobinfo(2)'!B27 -> Claim # | D76: =IF(ISBLANK('jobinfo(2)'!C27),"________________________________",'jobinfo(2)'!$C$27) -> 0
A77: =+A44 -> Property-Owner Name | B77: =+B44 -> Johnson, Paul & Tamra | C77: =+'jobinfo(2)'!B11 -> Cause of Loss | D77: =+'jobinfo(2)'!C11 -> WATER
A78: =+A45 -> Property address: street | B78: =+B45 -> 9402 Shepard Road | C78: =+'jobinfo(2)'!B12 -> date of loss | D78: =+'jobinfo(2)'!C12 -> Friday, April 4, 2025
A79: =+A46 -> Property city, state, zip | B79: =+B46 -> Macedonia, OH, USA | C79: =+'jobinfo(2)'!B13 -> rebuild type 1 | D79: =+'jobinfo(2)'!C13 -> Interior Repairs LEVEL 1
A80: =+A47 -> Customer Email | B80: =+B47 -> tringo68@yahoo.com | C80: =+'jobinfo(2)'!B14 -> rebuild type 2 | D80: =+'jobinfo(2)'!C14 -> Interior Repairs LEVEL 2
A81: =+C47 -> Cst-owner Phone# | B81: =+B48 -> (216) 399-6191 | C81: =+'jobinfo(2)'!B15 -> rebuild type 3 | D81: =+'jobinfo(2)'!C15 -> TBD
A83: ASSIGNMENT OF INSURANCE BENEFITS; I, | C83: =+'jobinfo(2)'!C1 -> Johnson, Paul & Tamra
A84: ,as Owner, do hereby assign any and all insurance rights, benefits, proceeds and any causes of action, including APPRAISAL AND DEMAND Thereof, under applicable insurance policies to
A85: =+A68 -> All Phase Consulting, LLC | C85: =+C30 -> EIN # | D85: =+D30 -> TIN 83-226 0563
A86: their Assignee or Representative of and for herein named contractor for service rendered or to be rendered by Company. In this regard,I make this assignment in consideration of Company’s agreement to perform services and supply materials and otherwise perform its obligations under this contract, including not requiring full payment at the time of service. I also hereby direct my insurance carrier(s) to release any and all information requested by Company, for the direct purpose of obtaining actual benefits to be paid for services rendered or to be rendered.
A87: DIRECT PAYMENT AUTHORIZATION & PAYMENT TERMS
A88: OWNER HEREBY SPECIFICALLY REQUESTS THAT ALL Payments for the Rebuild BE PAID TO: Owner & Contractor
A89: Payment terms are net upon completion. Late fees 1.5% monthly and reimbursement for costs of collection.
A90: I/We select the option of overnight shipping for expedited delivery.
A94: X X | D94: =+D31 -> Friday, April 4, 2025
A95: =+'jobinfo(2)'!C1 -> Johnson, Paul & Tamra | B95: =+'jobinfo(2)'!C6 -> TBD | C95: =C66 -> 0
A96: CONTRACTOR & HOMEOWNER AGREEMENT
A97: =+'jobinfo(2)'!$C$100 -> All Phase Consulting, LLC
A98: =+'jobinfo(2)'!C$109 -> Providing Cost Estimating & Project Management Services
A99: =+'jobinfo(2)'!$C$101 -> WWW.MYAPCLLC.COM | C99: =+'jobinfo(2)'!$C$102 -> Insured & GA Registered #09073201
A100: =+'jobinfo(2)'!$C$107 -> 20810 AURORA RD | B100: =+'jobinfo(2)'!$C$103 -> 375 Rockbridge Road, Suite 172-343 | D100: =+'jobinfo(2)'!$C$105 -> ECI 531 FIFTH AVE,
A101: =+'jobinfo(2)'!$C$108 -> BEDFORD,OH 44146 | B101: =+'jobinfo(2)'!$C$104 -> Lilburn, GA, 30047 | D101: =+'jobinfo(2)'!$C$106 -> PELHAM, NY 10803
A102: =+'jobinfo(2)'!$C$110 -> Five Generations of Great Work | C102: =+'jobinfo(2)'!$C$111 -> Five Generations of Pride & Skills
A103: COMPANY REP. | B103: =+'jobinfo(2)'!$C$112 -> Joe Jones, PM 216.450.7228 | C103: =+'jobinfo(2)'!$C$113 -> wsbjoe9@gmail.com
A104: COMPANY REP. #2 | B104: =+'jobinfo(2)'!$C$114 -> 404-446-9060 | C104: =+'jobinfo(2)'!$C$115 -> info@myapcllc.com
A105: =+B11 -> Johnson, Paul & Tamra | B105: =+B12 -> 9402 Shepard Road | C105: =+B13 -> Macedonia, OH, USA | D105: as OWNER. And
A107: =+A97 -> All Phase Consulting, LLC | C107: as CONTRACTOR. | D107: Concerning
A109: RELATED DAMAGES : | B109: =+$A$23 -> WATER | C109: on or about | D109: =+D23 -> Friday, April 4, 2025
A111: The said parties, for the considerations hereinafter mentioned, hereby agree to the following:
A113: 1. The CONTRACTOR agrees to provide all of the labor and materials required to perform the following
A114: work as per attachment; ( ____) pages. subject to adjustment based upon mutually agreed scope of work.
A115: =+A56 -> Interior Repairs LEVEL 1 | B115: =+B56 -> Interior Repairs LEVEL 2 | C115: =+C56 -> TBD | D115: =+D56 -> Y
A117: 2. The OWNER hereby agrees to pay the CONTRACTOR, for the aforesaid materials & labor, $___ _________
A119: Phase # 1 ______X_________ | C119: =+'jobinfo(2)'!C95 -> TBD
...

Sheet SUBCPS1
A1: ** SUBCONTRACTOR GENERAL AUTHORIZATION **
A2: SUBCONTRACTOR | B2: =+'jobinfo(2)'!$E$100 -> 0
A3: =+'jobinfo(2)'!E$109 -> 0
A4: =+'jobinfo(2)'!$E$101 -> 0 | C4: =+'jobinfo(2)'!$E$102 -> 0
A5: ='jobinfo(2)'!$E$107 -> 0 | B5: =+'jobinfo(2)'!$E$103 -> 0 | D5: =+'jobinfo(2)'!$E$105 -> 0
A6: ='jobinfo(2)'!$E$108 -> 0 | B6: =+'jobinfo(2)'!$E$104 -> 0 | D6: =+'jobinfo(2)'!$E$106 -> 0
A7: =+'jobinfo(2)'!$D$110 -> 0 | C7: =+'jobinfo(2)'!$E$111 -> 0
A8: COMPANY REP. | B8: =+'jobinfo(2)'!$E$112 -> 0 | C8: =+'jobinfo(2)'!$E$113 -> 0
A9: COMPANY REP. #2 | B9: =+'jobinfo(2)'!$E$114 -> 0 | C9: =+'jobinfo(2)'!$E$115 -> 0
A10: Claim # | B10: ='jobinfo(2)'!$C$27 -> 0
A11: GENERAL CONTRACTOR | B11: =+'jobinfo(2)'!C100 -> All Phase Consulting, LLC | C11: ='jobinfo(2)'!C113 -> wsbjoe9@gmail.com
A12: ='jobinfo(2)'!B1 -> Property-Owner Name | B12: ='jobinfo(2)'!C1 -> Johnson, Paul & Tamra | C12: ='jobinfo(2)'!B3 -> Property city, state, zip | D12: ='jobinfo(2)'!C3 -> Macedonia, OH, USA
A13: ='jobinfo(2)'!B2 -> Property address: street | B13: ='jobinfo(2)'!C2 -> 9402 Shepard Road | C13: ='jobinfo(2)'!B5 -> Cst-owner Phone# | D13: ='jobinfo(2)'!C5 -> (216) 399-6191 | F13: ='jobinfo(2)'!E4 -> 0
A15: =+'jobinfo(2)'!B26 -> Insurance Co. Name | B15: =+'jobinfo(2)'!$C$26 -> Allstate Insurance Company | C15: =+'jobinfo(2)'!B28 -> policy # | D15: =+'jobinfo(2)'!C28 -> 0
A16: =+'jobinfo(2)'!B46 -> Insurance Co. Phone | B16: =+'jobinfo(2)'!$C$31 -> 888 656.8005 | C16: =+'jobinfo(2)'!C29 -> 0
A17: =+'jobinfo(2)'!B30 -> DESK Adjuster DA | B17: =+'jobinfo(2)'!$C$30 -> 0 | C17: =+'jobinfo(2)'!C33 -> claims@claims.allstate.com
A18: =+'jobinfo(2)'!B31 -> DA Phone | B18: =+'jobinfo(2)'!C31 -> 888 656.8005 | C18: DA Ph. Ext. # | D18: =+'jobinfo(2)'!C32 -> 0
A20: Dear Insurance Company/ Mortgage Company and or To Whom It May Concern:
A21: The undersigned GENERAL CONTRACTOR & | C21: ='jobinfo(2)'!C1 -> Johnson, Paul & Tamra | D21: agree to employ
B22: ='jobinfo(2)'!$E$100 -> 0 | C22: EIN # | D22: ='jobinfo(2)'!$E$116 -> 0
A23: to assist in the repair of the above mentioned property that was damaged by
A24: ='jobinfo(2)'!C11 -> WATER | C24: on or about (date). | D24: ='jobinfo(2)'!C12 -> Friday, April 4, 2025
A25: GENERAL CONTRACTOR/Owners ACKNOWLEDGE as party of interest;
B26: ='jobinfo(2)'!$E$100 -> 0 | D26: ='jobinfo(2)'!$E$116 -> 0
A27: and will be noted as such on all drafts, correspondence, and communications between the owner, insurer and my mortgage company. I hereby authorize all parties to discuss my account as it relates to the above noted loss and or repairs; as well as the release of draws for all repairs. This applies in full to it's employees / assigns / representatives.
A31: =B11 -> All Phase Consulting, LLC | C31: CONTACT # | D31: ='jobinfo(2)'!C114 -> 404-446-9060
A32: X___________________________________ _____________ | C32: ='jobinfo(2)'!C112 -> Joe Jones, PM 216.450.7228 | D32: =+'jobinfo(2)'!C22 -> Friday, April 4, 2025
A35: =+$A$196 -> COMPANY REP. | B35: =B8 -> 0 | C35: =C8 -> 0
A36: SUBCONTRACTOR EMERGENCY SERVICES WORK AUTHORIZATION
A37: SUBCONTRACTOR | B37: =+'jobinfo(2)'!$E$100 -> 0
A38: =+A3 -> 0
A40: =+A5 -> 0 | B40: =+B5 -> 0 | D40: =+D5 -> 0
A41: =+A6 -> 0 | B41: =+B6 -> 0 | D41: =+D6 -> 0
C42: =+$C$104 -> 0
A43: =+A8 -> COMPANY REP. | B43: =+B35 -> 0 | C43: =+$D$196 -> wsbjoe9@gmail.com
A44: Claim Number: | B44: =B10 -> 0 | C44: =A15 -> Insurance Co. Name | D44: =+B15 -> Allstate Insurance Company
A45: GENERAL CONTRACTOR | B45: =B11 -> All Phase Consulting, LLC | D45: =D31 -> 404-446-9060
A46: =A12 -> Property-Owner Name | B46: =B12 -> Johnson, Paul & Tamra | C46: Cause of Loss | D46: =+A24 -> WATER
A47: =C12 -> Property city, state, zip | B47: =B13 -> 9402 Shepard Road | C47: DOL | D47: =D24 -> Friday, April 4, 2025
A48: =C12 -> Property city, state, zip | B48: =D12 -> Macedonia, OH, USA | C48: =C13 -> Cst-owner Phone# | D48: =D13 -> (216) 399-6191
A49: AUTHORIZATED ANTIMICROBIAL AGENTS; I understand that in the best judgment of Company, antimicrobial agents maybe used to inhibit the growth of micro-organisms during the drying/restoration process. I have received notice of the use of such. I understand it is beyond the expertise of Company to determine if someone is sensitive to its use and will hold Company harmless for its use. STOP WORK-HOLD HARMLESS. If the Company is not allowed to perform its recommended procedures and/or drying equipment is removed prematurely, I agree to release and hold Company harmless, indemnify Company against all claims or actions.
A52: =+$B$11 -> All Phase Consulting, LLC | C52: as GENERAL CONTRACTOR and the Owner,
A53: do hereby authorize | B53: =B37 -> 0 | C53: =+A37 -> SUBCONTRACTOR
A54: , their Assignee or Representative of and for herein named contractor to enter my property, furnish materials, supply all equipment and perform all labor necessary to preserve and protect my property from further damage. Including evaluation, inventory, storage and or cleaning of contents/personal property.
A55: I understand that I am personally responsible for all sums due to contractor for work related
A56: to LOSS TYPE of damages stated herein; performed at my property listed here.
A58: I hereby assign the insurance rights; as specified herein, benefits, and proceeds under my insurance policy for | E58: I hereby assign the insurance rights; as specified herein, benefits, and proceeds under my
A59: the Personal Property services to: | C59: =+$B$2 -> 0 | E59: insurance policy for the Emergency /mitigation services to: | G59: =+$B$2 -> 0
A60: Thus, monies due to named herein contractor are to be released without delay; solely, directly to contractor. | E60: Thus, monies due to named herein contractor are to be released without delay; solely, directly to contractor.
A61: This is payment for PERSONAL PROPERTY SERVICES; for services that have already been performed; consequently the mortgage company has no interest in these specific funds; therefore make direct payment; refrain from including Mortgage Company name on the check. | E61: This is payment for emergency and mitigation; for services that have already been performed; consequently the mortgage company has no interest in these specific funds; therefore make direct payment; refrain from including Mortgage Company name on the check.
E62: OWNER HEREBY REQUESTS PAYMENTS BE PAID TO: | G62: TIN 83-226 0563 | H62: =+C53 -> SUBCONTRACTOR | K62: OWNER HEREBY REQUESTS PAYMENTS BE PAID TO: | M62: =+C59 -> 0 | N62: =+D31 -> 404-446-9060
A63: This is a LEGALLY BINDING, Irrevocable Document; Fully Enforceable. Please read carefully
A64: =+$A$32 -> X___________________________________ _____________ | C64: ='jobinfo(2)'!D13 -> 0 | D64: =+$D$32 -> Friday, April 4, 2025
A65: =+B45 -> All Phase Consulting, LLC | C65: =+C195 -> 0
A66: =+$A$196 -> COMPANY REP. | B66: =+'jobinfo(2)'!D112 -> 0 | D66: =+'jobinfo(2)'!C113 -> wsbjoe9@gmail.com
A69: CONTRACTOR & SUBCONTRACTOR AGREEMENT
A70: =+'jobinfo(2)'!$E$100 -> 0
A71: =+'jobinfo(2)'!E$109 -> 0
A72: =+'jobinfo(2)'!$E$101 -> 0 | C72: =+'jobinfo(2)'!$E$102 -> 0
A73: ='jobinfo(2)'!$C$107 -> 20810 AURORA RD | B73: =+'jobinfo(2)'!$E$103 -> 0 | D73: =+'jobinfo(2)'!$C$105 -> ECI 531 FIFTH AVE,
A74: ='jobinfo(2)'!$C$108 -> BEDFORD,OH 44146 | B74: =+'jobinfo(2)'!$E$104 -> 0 | D74: =+'jobinfo(2)'!$C$106 -> PELHAM, NY 10803
A75: =+'jobinfo(2)'!$E$110 -> 0 | C75: =+'jobinfo(2)'!$E$111 -> 0
A77: =A11 -> GENERAL CONTRACTOR | B77: =B11 -> All Phase Consulting, LLC | C77: =C64 -> 0 | D77: =D45 -> 404-446-9060
A78: =A12 -> Property-Owner Name | B78: =B12 -> Johnson, Paul & Tamra | C78: =C12 -> Property city, state, zip | D78: =D12 -> Macedonia, OH, USA
A79: =A13 -> Property address: street | B79: =B13 -> 9402 Shepard Road | C79: =C13 -> Cst-owner Phone# | D79: =D13 -> (216) 399-6191
A80: =C46 -> Cause of Loss | B80: =D46 -> WATER | C80: =C47 -> DOL | D80: =D47 -> Friday, April 4, 2025
A81: =A15 -> Insurance Co. Name | B81: =B15 -> Allstate Insurance Company | C81: =A44 -> Claim Number: | D81: =B44 -> 0
A82: ='jobinfo(2)'!B30 -> DESK Adjuster DA | B82: ='jobinfo(2)'!C30 -> 0 | C82: ='jobinfo(2)'!B31 -> DA Phone | D82: ='jobinfo(2)'!C31 -> 888 656.8005
A83: The General Contractor hereby acknowledges that he has informed the customer of our services to be provided in accordance with our company's contract with the General Contractor. Furthermore; the customer is in agreement with the Sub-Contractor working on this project.
A84: The General Contractor further hereby declares and states that they have a valid signed contract to perform the services stated herein with the proper customer.
A85: The General Contractor further agrees to abide by contract that has been executed with the Sub-Contractor.
A86: The General Contractor & Customer agrees to pay the Sub-Contractor in full.
A87: The Sub-Contractor agrees to provide a fully executed Conditional Waiver Of Lein
A88: OWNER HEREBY SPECIFICALLY REQUESTS THAT EMS CPS Packout / Cleaning of
A89: Personal Property (ONLY) PAYMENTS ; REBUILD Items Excluded: PAYMENTS BE PAID TO:
A90: ='jobinfo(2)'!$E$100 -> 0 | D90: ='jobinfo(2)'!$D$116 -> 0
A91: =+$A$32 -> X___________________________________ _____________ | C91: =C64 -> 0 | D91: =+$D$32 -> Friday, April 4, 2025
B92: =A65 -> All Phase Consulting, LLC
A93: X___________________________________ _____________
A94: __Property owner Signature________________________________ | C94: ='jobinfo(2)'!$C$1 -> Johnson, Paul & Tamra
A95: =+$A$196 -> COMPANY REP. | B95: =+$B$196 -> Joe Jones, PM 216.450.7228 | C95: =+$D$196 -> wsbjoe9@gmail.com
A97: CONTRACTOR & SUBCONTRACTOR AGREEMENT
A98: =+'jobinfo(2)'!$E$100 -> 0 | C98: =+'jobinfo(2)'!$C$100 -> All Phase Consulting, LLC
A99: =+'jobinfo(2)'!E$109 -> 0
A100: =+'jobinfo(2)'!$E$101 -> 0 | C100: =+'jobinfo(2)'!$E$102 -> 0
A101: =+'jobinfo(2)'!$D$107 -> 0 | B101: =+'jobinfo(2)'!$E$103 -> 0 | D101: =+'jobinfo(2)'!$E$105 -> 0
A102: =+'jobinfo(2)'!$D$107 -> 0 | B102: =+'jobinfo(2)'!$E$104 -> 0 | D102: =+'jobinfo(2)'!$E$106 -> 0
A103: =+'jobinfo(2)'!$E$110 -> 0 | C103: =+'jobinfo(2)'!$E$111 -> 0
A104: COMPANY REP. | B104: =+'jobinfo(2)'!$E$112 -> 0 | C104: =+'jobinfo(2)'!$D$113 -> 0
A105: COMPANY REP. #2 | B105: =+'jobinfo(2)'!$E$114 -> 0 | C105: =+'jobinfo(2)'!$E$115 -> 0
A106: =+B11 -> All Phase Consulting, LLC | C106: as GENERAL CONTRACTOR
A108: =+A98 -> 0 | C108: as SUBCONTRACTOR., concerning | D108: Concerning
A110: RELATED DAMAGES : | B110: =+$A$24 -> WATER | C110: on or about | D110: =+D24 -> Friday, April 4, 2025
A112: The said parties, for the considerations hereinafter mentioned, hereby agree to the following:
A114: 1. The SUBCONTRACTOR agrees to provide all of the labor and materials required to perform the following
A115: work as per attachment; ( ____) pages. subject to adjustment based upon mutually agreed scope of work.
A116: =A59 -> the Personal Property services to:
A118: 2. The GENERAL CONTRACTOR hereby agrees to pay the SUBCONTRACTOR, for the aforesaid materials & labor, $
A120: Phase # 1 ______X_________ | C120: =+'jobinfo(2)'!C95 -> TBD
A122: per the attached; subject to adjustment based upon mutually agreed scope of work and pricing.
...

Sheet CHANGES
A1: Change order request / WishList
A2: Property-owner Name | B2: =+'jobinfo(2)'!C1 -> Johnson, Paul & Tamra | C2: =+'jobinfo(2)'!B26 -> Insurance Co. Name | D2: =+'jobinfo(2)'!C26 -> Allstate Insurance Company
A3: Property address: street | B3: =+'jobinfo(2)'!C2 -> 9402 Shepard Road | C3: =+'jobinfo(2)'!B27 -> Claim # | D3: =+'jobinfo(2)'!C27 -> 0
A4: Property city, state, zip | B4: =+'jobinfo(2)'!C3 -> Macedonia, OH, USA | C4: =+'jobinfo(2)'!B11 -> Cause of Loss | D4: =+'jobinfo(2)'!C11 -> WATER
A5: Customer Email | B5: =+'jobinfo(2)'!C4 -> tringo68@yahoo.com | C5: =+'jobinfo(2)'!B12 -> date of loss | D5: =+'jobinfo(2)'!C12 -> Friday, April 4, 2025
A6: Cst-owner Phone# | B6: =+'jobinfo(2)'!C5 -> (216) 399-6191 | C6: =+'jobinfo(2)'!B13 -> rebuild type 1 | D6: =+'jobinfo(2)'!C13 -> Interior Repairs LEVEL 1
B7: _______________________ | C7: =+'jobinfo(2)'!B14 -> rebuild type 2 | D7: =+'jobinfo(2)'!C14 -> Interior Repairs LEVEL 2
A8: Customer may wish to alter the original job work scope and or add additional work.
A9: There may or may not be enough alternate funds to cover these changes.
A10: Each item will be individually addressed with the best interest of the customer in mind.
A11: ROOM Name & Number | C11: LOCATION & Basic damage / work Description | D11: Scope notes | E11: Photos | F11: Sketch
A12: # 0 = Master bedroom | B12: Ceilings N corner | C12: repair water damage drywall paint
A13: {#=_1_} | D13: {_______} | E13: {_______} | F13: {_______}
A14: {#=_2_} | D14: {_______} | E14: {_______} | F14: {_______}
A15: {#=_3_} | D15: {_______} | E15: {_______} | F15: {_______}
A16: {#=_4_} | D16: {_______} | E16: {_______} | F16: {_______}
A17: {#=_5_} | D17: {_______} | E17: {_______} | F17: {_______}
B18: ______________________________________________________________________________________________

Sheet POL
A1: Sworn Statement in Proof of Loss
A2: This form is provided to comply with the Insurance Act, where required, and without prejudice to the liability of the Insurer.
A4: ='jobinfo(2)'!B26 -> Insurance Co. Name | B4: ='jobinfo(2)'!C26 -> Allstate Insurance Company | C4: ='jobinfo(2)'!B27 -> Claim # | D4: ='jobinfo(2)'!C27 -> 0
A5: ='jobinfo(2)'!B28 -> policy # | B5: ='jobinfo(2)'!C28 -> 0 | C5: dates in effect thru | D5: 46022
C6: coverage Amounts | D6: 450000
A7: Insured | B7: ='jobinfo(2)'!C1 -> Johnson, Paul & Tamra | D7: ='jobinfo(2)'!C3 -> Macedonia, OH, USA
A8: Address | B8: ='jobinfo(2)'!C2 -> 9402 Shepard Road
A9: ='jobinfo(2)'!B5 -> Cst-owner Phone# | B9: ='jobinfo(2)'!C5 -> (216) 399-6191 | C9: ='jobinfo(2)'!C4 -> tringo68@yahoo.com
A11: At time of loss, by the above-indicated policy of insurance, herein named policyholder was
A12: insured, against a loss by, to the property described, | D12: ='jobinfo(2)'!C11 -> WATER
A13: in the statement of loss, according to the terms and conditions of the said policy and all forms, endorsements, transfers and assignments attached thereto.
A15: Time & Origin Of LOSS: | B15: ='jobinfo(2)'!C12 -> Friday, April 4, 2025 | D15: TIME AM/PM
A16: The cause & origin of the said loss were: | C16: =D12 -> WATER
A17: LOSS LOCATION | B17: =B8 -> 9402 Shepard Road | C17: =D7 -> Macedonia, OH, USA
A19: Occupancy: The building described, or containing the property described, was occupied
A20: at the time of the loss as follows, and for no other purpose whatever; other the following:
A21: personal residence
A23: Title and Interest: At the time of the loss the interest in the property described therein was
A24: No other person or persons had any interest therein or encumbrance thereon, except:
A25: ='jobinfo(2)'!B78 -> Mortgage co | B25: ='jobinfo(2)'!C78 -> TBD
A27: Changes: Since the said policy was issued there has been no assignment thereof, or change of interest, use, occupancy, possession, location or exposure of the property described except:
A28: N/A
A30: The said loss did not originate by any act, design or procurement on the part of your insured, or this affiant: nothing has been done by or with the privity or consent of your insured or this affiant, to violate the conditions of the policy, or render it void; no articles are mentioned herein or in annexed schedules but such as were destroyed or damaged at the time of said loss; no property saved has in any manner been concealed, and no attempt to deceive the said company, as to the extent of said loss, has in any manner been made. Any other information that may be required will be furnished and considered a part of this proof.
A32: The insured hereby covenants that no release has been or will be given to or settlement or compromise made with any third party who may be liable to damages to the insured and the insured in consideration of the payment made under this policy hereby subrogates the said Company to all rights and causes of action the said insured has against any person, persons, or corporations whomsoever for damage arising out of or incident to said loss or damage to said property and authorizes said Company to sue in the name of the Insured but at the cost of the Company any such third party, pledging full cooperation in such action.
A34: Insurance and Loss
A35: A particular account of the loss is attached heretoand forms part of this proof. The actual cash value of the property insured, the actual amount of loss or damage, the total insurance thereon at the time of the said loss and the amount claimed under this policy are as follows:
A36: Coverage Involved | B36: Replacement Cost | C36: Cash Value Estimate | D36: Total Loss or Damage
A37: ale
A38: rebuild costs
A39: mitigation
A40: personal property
A43: Coverage Involved | B43: Total Insurance Under all Policies | C43: Total Insurance Under this Policy | D43: Amount Claimed Under this Policy
A44: =A37 -> ale | D44: =D37 -> 0
A45: =A38 -> rebuild costs | D45: =D38 -> 0
A46: =A39 -> mitigation | D46: =D39 -> 0
A47: =A40 -> personal property | D47: =D40 -> 0
A48: =A41 -> 0 | D48: =D41 -> 0
A53: The furnishing of this blank or the preparation of proofs by a representative of the above insurance company is not a waiver of any of its rights.
A54: "Any person who knowingly and with intent to defraud any insurance company, or other person, files an application for insurance or statement of claim containing any materially false information or conceals for the purpose of misleading, information concerning any fact material thereto commits a fraudulent insurance act, which is a crime and subjects such person to criminal and civil penalties."
A56: State of | C56: County of
A58: The insured subscribed and sworn before me this day of | B58: .
A61: Insured | C61: Insured
A65: Notary Public/or Adjuster
A67: Sworn to before me & subscribed in my presence on this ____ day of_________, 2024
A68: State of: ____________ County/Parish of: ______________________
A69: Notary Signature: ______________________________________________
A70: My Commission Expires: ______/_______ / 20_______ Notary Seal:
A72: Assigned to: | B72: =+'[1]email cvr'!A36 -> 0
C74: =+'[1]email cvr'!$A$15 -> EIN # | D74: =+'[1]jobinfo(2)'!C146 -> TBD

Sheet DRAWS
A1: DRAW SCHEDULE
A2: Property-owner Name | B2: =+'jobinfo(2)'!C1 -> Johnson, Paul & Tamra | C2: =+'jobinfo(2)'!B26 -> Insurance Co. Name | D2: =+'jobinfo(2)'!C26 -> Allstate Insurance Company
A3: Property address: street | B3: =+'jobinfo(2)'!C2 -> 9402 Shepard Road | C3: =+'jobinfo(2)'!B27 -> Claim # | D3: =+'jobinfo(2)'!C27 -> 0
A4: Property city, state, zip | B4: =+'jobinfo(2)'!C3 -> Macedonia, OH, USA | C4: =+'jobinfo(2)'!B11 -> Cause of Loss | D4: =+'jobinfo(2)'!C11 -> WATER
A5: Customer Email | B5: =+'jobinfo(2)'!C4 -> tringo68@yahoo.com | C5: =+'jobinfo(2)'!B12 -> date of loss | D5: =+'jobinfo(2)'!C12 -> Friday, April 4, 2025
A6: Cst-owner Phone# | B6: =+'jobinfo(2)'!C5 -> (216) 399-6191 | C6: =+'jobinfo(2)'!B13 -> rebuild type 1 | D6: =+'jobinfo(2)'!C13 -> Interior Repairs LEVEL 1
B7: _______________________ | C7: =+'jobinfo(2)'!B14 -> rebuild type 2 | D7: =+'jobinfo(2)'!C14 -> Interior Repairs LEVEL 2
A8: Customer may wish to alter the original job work scope and or add additional work.
A10: Each item will be individually addressed with the best interest of the customer in mind.
C11: LOCATION & Basic damage / work Description | D11: Scope notes | E11: Photos | F11: Sketch
A12: # 0 = Master bedroom | B12: Ceilings N corner | C12: repair water damage drywall paint
A13: DRAW # | B13: PERCENTAGE OF WORK COMPLETED | D13: {_______} | E13: {_______} | F13: TTD
A14: 1 | B14: INITIAL DEPOSIT | D14: 0.33 | F14: =+D14 -> 0.33
A15: 2 | B15: 0.5 | D15: 0.33 | F15: =+D15+D14 -> 0.66
A16: 3 | B16: 0.75 | D16: 0.1 | F16: =+F15+D16 -> 0.76
A17: 4 | B17: 0.9 | D17: 0.14 | F17: =+F16+D17 -> 0.9
A18: 5 | B18: 1 | D18: 0.1 | F18: =+F17+D18 -> 1
H20: GC & SUB TERMS % | J20: CASH FLOW | O20: JOB = | P20: ='jobinfo(2)'!C51 -> OH25 JOHNSON
H21: ='jobinfo(2)'!C100 -> All Phase Consulting, LLC | K21: =+'jobinfo(2)'!D100 -> 0 | N21: APC | P21: ='jobinfo(2)'!C1 -> Johnson, Paul & Tamra
H22: ='jobinfo(2)'!C112 -> Joe Jones, PM 216.450.7228 | K22: ='jobinfo(2)'!D112 -> 0 | P22: ='jobinfo(2)'!C2 -> 9402 Shepard Road
P23: ='jobinfo(2)'!C3 -> Macedonia, OH, USA
H24: ='jobinfo(2)'!B5 -> Cst-owner Phone# | I24: ='jobinfo(2)'!C5 -> (216) 399-6191 | J24: ='jobinfo(2)'!B26 -> Insurance Co. Name | K24: ='jobinfo(2)'!C26 -> Allstate Insurance Company | L24: ='jobinfo(2)'!B37 -> adj contents | M24: ='jobinfo(2)'!C37 -> TBD
H25: ='jobinfo(2)'!B6 -> Co-Owner.cst#2 | I25: ='jobinfo(2)'!C6 -> TBD | J25: ='jobinfo(2)'!B27 -> Claim # | K25: ='jobinfo(2)'!C27 -> 0 | L25: ='jobinfo(2)'!B38 -> adj CPS phone # | M25: ='jobinfo(2)'!C38 -> TBD | O25: ='jobinfo(2)'!B34 -> Field Adjuster Name | P25: ='jobinfo(2)'!C34 -> TBD
H26: ='jobinfo(2)'!B11 -> Cause of Loss | I26: ='jobinfo(2)'!C11 -> WATER | J26: ='jobinfo(2)'!B28 -> policy # | K26: ='jobinfo(2)'!C28 -> 0 | L26: ='jobinfo(2)'!B39 -> adj CPS email | M26: ='jobinfo(2)'!C39 -> TBD | O26: ='jobinfo(2)'!B35 -> Phone # field adj | P26: ='jobinfo(2)'!C35 -> TBD
H27: ='jobinfo(2)'!B12 -> date of loss | I27: ='jobinfo(2)'!C12 -> Friday, April 4, 2025 | J27: ='jobinfo(2)'!B29 -> Email INS. co. | K27: ='jobinfo(2)'!C29 -> 0 | L27: ='jobinfo(2)'!B40 -> TMP adj | M27: ='jobinfo(2)'!C40 -> TBD | O27: ='jobinfo(2)'!B36 -> Field adj email | P27: ='jobinfo(2)'!C36 -> TBD
H28: ='jobinfo(2)'!B13 -> rebuild type 1 | I28: ='jobinfo(2)'!C13 -> Interior Repairs LEVEL 1 | J28: ='jobinfo(2)'!B30 -> DESK Adjuster DA | K28: ='jobinfo(2)'!C30 -> 0 | L28: ='jobinfo(2)'!B41 -> TMP adj phone # | M28: ='jobinfo(2)'!C41 -> TBD | O28: ='jobinfo(2)'!B21 -> Year Built | P28: ='jobinfo(2)'!C21 -> POST 1978
H29: ='jobinfo(2)'!B14 -> rebuild type 2 | I29: ='jobinfo(2)'!C14 -> Interior Repairs LEVEL 2 | J29: ='jobinfo(2)'!B31 -> DA Phone | K29: ='jobinfo(2)'!C31 -> 888 656.8005 | L29: ='jobinfo(2)'!B42 -> adj TMP email | M29: ='jobinfo(2)'!C42 -> TBD | O29: ='jobinfo(2)'!B22 -> Contract Date | P29: ='jobinfo(2)'!C22 -> Friday, April 4, 2025
H30: ='jobinfo(2)'!B15 -> rebuild type 3 | I30: ='jobinfo(2)'!C15 -> TBD | J30: ='jobinfo(2)'!B32 -> DA Ph. Ext. # | K30: ='jobinfo(2)'!C32 -> 0 | O30: ='jobinfo(2)'!B19 -> Replacement | P30: ='jobinfo(2)'!C19 -> Y
H31: ='jobinfo(2)'!B16 -> DEMO | I31: ='jobinfo(2)'!C16 -> Y | J31: ='jobinfo(2)'!B33 -> DA Email | K31: ='jobinfo(2)'!C33 -> claims@claims.allstate.com | O31: ='jobinfo(2)'!B23 -> Loss of use/ ALE | P31: ='jobinfo(2)'!C23 -> Y | Q31: ='jobinfo(2)'!B18 -> Other Structures | R31: ='jobinfo(2)'!C18 -> N
H32: ='jobinfo(2)'!B17 -> Mitigation | I32: ='jobinfo(2)'!C17 -> Y | K32: ='jobinfo(2)'!B20 -> CPS / CLN / CON/ CGN | L32: ='jobinfo(2)'!C20 -> Y | O32: ='jobinfo(2)'!B24 -> Breathing issue | P32: ='jobinfo(2)'!C24 -> TBD | Q32: ='jobinfo(2)'!B25 -> HMR | R32: ='jobinfo(2)'!C25 -> TBD
H34: ESTIMATES | J34: BEST CASE SCENARIO | N34: MOST LIKELY | Q34: WORST CASE SCENARIO
J35: 1 | K35: SUB | L35: =K21 -> 0 | N35: 0.7 | O35: =L35 -> 0 | Q35: 0.5 | R35: =K35 -> SUB
H36: Roof & EXT Mitigation TEMP. & EMERGENCY REPAIRS | J36: 1 | K36: 0 | L36: =J36*K36 -> 0 | N36: =J36*$N$35 -> 0.7 | O36: =N36*K36 -> 0 | Q36: =J36*$Q$35 -> 0.5 | R36: =Q36*K36 -> 0 | U36: 0.5 | V36: 0.5
H37: TREE & EXT Mitigation TEMP. & EMERGENCY REPAIRS | J37: 1 | K37: 0 | L37: =J37*K37 -> 0 | N37: =J37*$N$35 -> 0.7 | O37: =N37*K37 -> 0 | Q37: =J37*$Q$35 -> 0.5 | R37: =Q37*K37 -> 0
H38: Mitigation INTERIOR | J38: 33149.78 | K38: 0.2 | L38: =J38*K38 -> 6629.956 | N38: =J38*$N$35 -> 23204.846 | O38: =N38*K38 -> 4640.9692 | Q38: =J38*$Q$35 -> 16574.89 | R38: =Q38*K38 -> 3314.978 | U38: 0.66 | V38: 0.33
H39: Contents_ PERSONAL PROPERTY Packout = CPS | J39: 0 | K39: 0.2 | L39: =J39*K39 -> 0 | N39: =J39*$N$35 -> 0 | O39: =N39*K39 -> 0 | Q39: =J39*$Q$35 -> 0 | R39: =Q39*K39 -> 0 | U39: 0.66 | V39: 0.33
H40: REBUILD Interior & EXTERIOR | J40: =97116.91-J38-4 -> 63963.13 | K40: 0.8 | L40: =J40*K40 -> 51170.504 | N40: =J40*$N$35 -> 44774.191 | O40: =N40*K40 -> 35819.353 | Q40: =J40*$Q$35 -> 31981.565 | R40: =Q40*K40 -> 25585.252 | U40: 0.8 | V40: 0.2
H41: Roof & EXT REBUILD | J41: 1 | K41: 0 | L41: =J41*K41 -> 0 | N41: =J41*$N$35 -> 0.7 | O41: =N41*K41 -> 0 | Q41: =J41*$Q$35 -> 0.5 | R41: =Q41*K41 -> 0
H42: PERSONAL PROPERTY REPLACEMENT Customer's * | J42: 0 | K42: 0.1 | L42: =J42*K42 -> 0 | N42: =J42*$N$35 -> 0 | O42: =N42*K42 -> 0 | Q42: =J42*$Q$35 -> 0 | R42: =Q42*K42 -> 0 | U42: 0.66 | V42: 0.33
H43: TOTALS | J43: =SUM(J36:J42) -> 97115.91 | L43: =SUM(L36:L42) -> 57800.46 | N43: =SUM(N36:N42) -> 67981.137 | O43: =SUM(O36:O42) -> 40460.322 | Q43: =SUM(Q36:Q42) -> 48557.955 | R43: =SUM(R36:R42) -> 28900.23
H45: ESTIMATES | J45: BEST CASE SCENARIO | N45: POTENTIAL ADDITIONAL FUNDS | Q45: WORST CASE SCENARIO
J46: 1 | K46: APC | N46: 0.7 | O46: =L46 -> 0 | Q46: 0.5 | R46: =K46 -> APC
H47: Roof & EXT Mitigation TEMP. & EMERGENCY REPAIRS | J47: =J36 -> 1 | K47: =100%-K36 -> 1 | L47: =J47*K47 -> 1 | N47: =J47*$N$35 -> 0.7 | O47: =N47*K47 -> 0.7 | Q47: =J47*$Q$35 -> 0.5 | R47: =Q47*K47 -> 0.5
H48: TREE & EXT Mitigation TEMP. & EMERGENCY REPAIRS | J48: 1 | K48: =100%-K37 -> 1 | L48: =J48*K48 -> 1 | N48: =J48*$N$35 -> 0.7 | O48: =N48*K48 -> 0.7 | Q48: =J48*$Q$35 -> 0.5 | R48: =Q48*K48 -> 0.5
H49: Mitigation INTERIOR | J49: =J38 -> 33149.78 | K49: =100%-K38 -> 0.8 | L49: =J49*K49 -> 26519.824 | N49: =J49*$N$35 -> 23204.846 | O49: =N49*K49 -> 18563.877 | Q49: =J49*$Q$35 -> 16574.89 | R49: =Q49*K49 -> 13259.912
H50: Contents_ PERSONAL PROPERTY Packout = CPS | J50: 0 | K50: =100%-K39 -> 0.8 | L50: =J50*K50 -> 0 | N50: =J50*$N$35 -> 0 | O50: =N50*K50 -> 0 | Q50: =J50*$Q$35 -> 0 | R50: =Q50*K50 -> 0
H51: REBUILD Interior & EXTERIOR | J51: =J40 -> 63963.13 | K51: =100%-K40 -> 0.2 | L51: =J51*K51 -> 12792.626 | N51: =J51*$N$35 -> 44774.191 | O51: =N51*K51 -> 8954.8382 | Q51: =J51*$Q$35 -> 31981.565 | R51: =Q51*K51 -> 6396.313
H52: Roof & EXT REBUILD | J52: 1 | K52: =100%-K41 -> 1 | L52: =J52*K52 -> 1 | N52: =J52*$N$35 -> 0.7 | O52: =N52*K52 -> 0.7 | Q52: =J52*$Q$35 -> 0.5 | R52: =Q52*K52 -> 0.5
H53: PERSONAL PROPERTY REPLACEMENT Customer's * | J53: 0 | K53: =100%-K42 -> 0.9 | L53: =J53*K53 -> 0 | N53: =J53*$N$35 -> 0 | O53: =N53*K53 -> 0 | Q53: =J53*$Q$35 -> 0 | R53: =Q53*K53 -> 0
H54: TOTALS | J54: =SUM(J47:J53) -> 97115.91 | L54: =SUM(L47:L53) -> 39315.45 | N54: =SUM(N47:N53) -> 67981.137 | O54: =SUM(O47:O53) -> 27520.815 | Q54: =SUM(Q47:Q53) -> 48557.955 | R54: =SUM(R47:R53) -> 19657.725
H55: GROSS TOTAL TO DATE | J55: HENDKING
H56: REBUILD Interior & EXTERIOR | J56: =J54 -> 97115.91 | K56: APC
H57: Mitigation INTERIOR | J57: =-J49 -> -33149.78
J58: =J57+J56 -> 63966.13
I59: 0.2 | J59: =-J58*I59 -> -12793.226 | K59: =-J59 -> 12793.226
J60: =J58+J59 -> 51172.904
H62: advance | J62: -20000
J63: =J60+J62 -> 31172.904
H65: repayment | J65: 14000 | K65: =-J65 -> -14000
J66: 1
J67: =J63+J65 -> 45172.904
H68: advance | J68: 7000
J70: =J67+J68 -> 52172.904
H73: Mitigation INTERIOR
I74: =J49 -> 33149.78
I75: 0.2 | J75: =I74*I75 -> 6629.956 | K75: =I74-J75 -> 26519.824
J76: =J70+J75 -> 58802.86 | K76: =SUM(K59:K75) -> 25313.05 | N76: 33150
N77: 36917.18 | Q77: =N77 -> 36917.18
N78: =N76+N77 -> 70067.18 | Q78: =K82 -> 7836.73
N79: 20000 | Q79: =+Q77+Q78 -> 44753.91
J80: =J76+K76 -> 84115.91 | K80: =I74 -> 33149.78 | L80: MIT TOTAL T APC | N80: =N78+N79 -> 90067.18 | Q80: =+N81 -> 7048.73
J81: =-J62 -> 20000 | K81: =-K76 -> -25313.05 | L81: NET DUE | N81: =J84-N80 -> 7048.73 | O81: DEPRECIATION HELD
J82: =J80+J81 -> 104115.91 | K82: =K80+K81 -> 7836.73 | L82: DUE IAN/HARDROCK | N82: =+N80+N81 -> 97115.91 | Q82: =SUM(Q79:Q81) -> 51802.64
J83: =-J68 -> -7000
J84: =J82+J83 -> 97115.91

Sheet AOB2
A1: =+'jobinfo(2)'!$C$100 -> All Phase Consulting, LLC | C1: ='jobinfo(2)'!C101 -> WWW.MYAPCLLC.COM | F1: =+'jobinfo(2)'!$C$100 -> All Phase Consulting, LLC
A2: =+'jobinfo(2)'!$C$103 -> 375 Rockbridge Road, Suite 172-343 | C2: Claim Number: | D2: ='jobinfo(2)'!$C$27 -> 0 | F2: =+'jobinfo(2)'!H$109 -> 0
A3: =+'jobinfo(2)'!$C$104 -> Lilburn, GA, 30047 | C3: =+'jobinfo(2)'!$C$110 -> Five Generations of Great Work | F3: =+'jobinfo(2)'!$C$101 -> WWW.MYAPCLLC.COM | H3: =+'jobinfo(2)'!$C$102 -> Insured & GA Registered #09073201
A4: ='jobinfo(2)'!$C$112 -> Joe Jones, PM 216.450.7228 | B4: ='jobinfo(2)'!$C$113 -> wsbjoe9@gmail.com | C4: =+'jobinfo(2)'!$C$111 -> Five Generations of Pride & Skills | F4: ='jobinfo(2)'!$C$107 -> 20810 AURORA RD | I4: =+'jobinfo(2)'!$C$105 -> ECI 531 FIFTH AVE,
A5: OHIO POST-LOSS ASSIGNMENT OF INSURANCE RIGHTS & DIRECTION TO PAY | F5: COMPANY REP. | G5: =+'jobinfo(2)'!$C$112 -> Joe Jones, PM 216.450.7228 | H5: =+'jobinfo(2)'!$C$113 -> wsbjoe9@gmail.com
A6: Policyholder #1: | B6: =+'jobinfo(2)'!C$1 -> Johnson, Paul & Tamra | C6: ='jobinfo(2)'!$B$26 -> Insurance Co. Name | D6: ='jobinfo(2)'!$C$26 -> Allstate Insurance Company | F6: COMPANY REP. #2 | G6: =+'jobinfo(2)'!$C$114 -> 404-446-9060 | H6: =+'jobinfo(2)'!$C$115 -> info@myapcllc.com
A7: Policyholder #2: | B7: =+'jobinfo(2)'!C$6 -> TBD | C7: PoIicy Number: | D7: ='jobinfo(2)'!$C$28 -> 0 | F7: Claim # | H7: Cst-owner Phone# | I7: ='jobinfo(2)'!$C$5 -> (216) 399-6191
A8: =+'jobinfo(2)'!$C$2 -> 9402 Shepard Road | B8: =+'jobinfo(2)'!$C$3 -> Macedonia, OH, USA | C8: Date of Loss: | D8: ='jobinfo(2)'!C12 -> Friday, April 4, 2025
A9: City/State/Zip: | B9: =+'jobinfo(2)'!$C$3 -> Macedonia, OH, USA
A10: 1. Irrevocable Post-Loss Assignment of Policyholders' Rights Against Insurance Company To Contractor: By execution of this irrevocable Post-Loss Assignment of Insurance Rights and Direction of Pay ("Assignment"), the policyholder(s) identified above ("Policyholders") completely, irrevocably, and fully assign and transfer to the Contractor named above all of the Policyholders' legal and equitable rights, title, and interest under all insurance policies arising from claims for the damage Contractor was hired to address (collectively referred to as the "Assigned Rights"). The Assigned Rights include without limitation the rights to collect insurance policy benefits and proceeds, and the right but not the obligation to participate in appraisal of the loss or the portion of the loss in which Contractor is involved. The Assigned Rights include without limitation the Policyholders' rights as a first-party insured under the Policyholders' policy of insurance, the right to sue the insurance company to enforce the Assigned Rights, and to prosecute any applicable causes of action for breach of contract, breach of the implied covenant of good faith and fair dealing (insurance bad faith), fraud, and negligence. This Assignment shall be liberally construed to the fullest extent permitted by law and so that Contractor is deemed to stand in a first party position as to the policies. The Policyholders shall remain obligated with respect to all duties and liabilities under the terms of the insurance policies, including the duty to properly document all claims and cooperate with the insurer's investigation. Contractor owes none of those duties. This Assignment may only be revoked by written notice to the Contractor after the contract is terminated in writing, but is permanently irrevocable as to work performed before the contract is terminated.
A11: 2. Exclusions: Nothing in this Assignment shall be construed as an assignment of other parts of the insurance claim that are unrelated to Contractor's scope of work, such as additional living expenses, the value oflost personal property, or services performed after Contractor's services are terminated. Nothing in this Assignment shall be construed as a delegation of duties. | F11: =+'jobinfo(2)'!$B$26 -> Insurance Co. Name | G11: =+'jobinfo(2)'!$C$26 -> Allstate Insurance Company | H11: =+'jobinfo(2)'!$B$28 -> policy # | I11: =+'jobinfo(2)'!$C$27 -> 0
A12: 3. No Conditions: The Policyholders agree and understand that this Assignment and each of its component parts are irrevocable. The Policyholders expressly acknowledge that it is the Policyholders' intent to assign the Policyholders' insurance policy rights and benefits under the claims to the Contractor as explained above. The Policyholders agree and understand that this irrevocable Assignment is unconditional and effective immediately upon execution of this document, and that no further action needs to be taken to make it valid, enforceable, or binding upon the Policyholders and the Policyholders' insurance company. | F12: =+'jobinfo(2)'!$B$46 -> Insurance Co. Phone | G12: =+'jobinfo(2)'!$C$46 -> (800) 255-7828 | H12: =+'jobinfo(2)'!$C$29 -> 0
A13: 4. Cooperation: The Policyholders shall cooperate fully with Contractor's efforts to enforce the Assigned rights, and to collect policy benefits. Policyholders agree to execute any and all documents presented by Contractor to the Policyholders, which are reasonably required for the prosecution of Contractor's claims against the Policyholders' insurance company and/or its agents with respect to the Assigned Rights. | F13: =+'jobinfo(2)'!$B$30 -> DESK Adjuster DA | G13: =+'jobinfo(2)'!$C$30 -> 0 | H13: =+'jobinfo(2)'!$B$33 -> DA Email | I13: =+'jobinfo(2)'!$C$33 -> claims@claims.allstate.com
A14: 5. Direction to Pay: The Policyholders hereby authorize and instruct all insurance carriers who may be liable to the Policyholders for this loss in whole or in part to pay directly to Contractor the amounts due or to become due in connection with the work Contractor has been authorized to perform, and to deliver said payments directly and exclusively to Contractor within fifteen (15) calendar days of the invoice. In the event an insurer fails to name Contractor on any check for the Work, the Policyholders shall immediately notify Contractor in writing, and return the check to the insurer with a written request to the insurer to issue a replacement check payable to Contractor. | F14: =+'jobinfo(2)'!$B$31 -> DA Phone | G14: =+'jobinfo(2)'!$C$31 -> 888 656.8005 | H14: =+'jobinfo(2)'!$B$32 -> DA Ph. Ext. # | I14: =+'jobinfo(2)'!$C$32 -> 0
A15: 6. Security and Consideration: This Assignment is given to Contractor as security and is made in consideration for Contractor's agreement to perform services without immediate full payment from the Policyholders upon completion of services. The Policyholders acknowledge the sufficiency of this consideration.
A16: 7. No Release: The Policyholders remain primarily and ultimately responsible for payment for services rendered by Contractor. This Assignment does not relieve the Policyholders from the duty to compensate Contractor for any amount due to Contractor that is not paid by insurance, including the cost of the work, deductibles, betterments, depreciation and other amounts not paid by insurance, all of which are ultimately the Policyholders' responsibility.
A18: "Policyholder #1" (I read this Assignment and understand it.) | C18: "Policyholder #2" (I read this Assignment and understand it.)
A19: X___________________ | C19: X___________________
A20: Signature.of PoIicyhoIder | C20: Signature.of PoIicyhoIder
A21: ='jobinfo(2)'!$C$1 -> Johnson, Paul & Tamra | B21: Title _______________________________ | C21: ='jobinfo(2)'!$C$6 -> TBD | D21: Title __________________
A23: Contractor Representative's Signature __________________________/ ____________________________ | C23: /Contractor Representative Name

Sheet aob
A5: Assignment of Insurance Benefits & Direct Payment Authorization:
A6: Insurer / Claim# | B6: =+signpgs!B14 -> Allstate Insurance Company | C6: =+signpgs!B10 -> 0
A7: Insurer Address | B7: =+'jobinfo(2)'!C48 -> TBD | C7: =+'jobinfo(2)'!B12 -> date of loss | D7: =+signpgs!$D$23 -> Friday, April 4, 2025
A8: City / State / Zip | B8: =+'jobinfo(2)'!C49 -> TBD | C8: =+'jobinfo(2)'!B11 -> Cause of Loss | D8: =+signpgs!$D$47 -> WATER
A9: Insured / Assigner | B9: =+signpgs!B45 -> Johnson, Paul & Tamra
A10: Property Address | B10: =+signpgs!B47 -> Macedonia, OH, USA | D10: =+signpgs!D10 -> (216) 399-6191
A11: City / State / Zip | B11: =+signpgs!B48 -> tringo68@yahoo.com | C11: =+signpgs!D11 -> tringo68@yahoo.com
A12: Contractor/Assignee | B12: =+signpgs!A2 -> All Phase Consulting, LLC
A13: =+signpgs!$A$186 -> COMPANY REP. | B13: =+signpgs!$B$186 -> Joe Jones, PM 216.450.7228 | C13: =+signpgs!$D$186 -> wsbjoe9@gmail.com
A14: =+signpgs!A57 -> Interior Repairs LEVEL 1 | B14: =+signpgs!C57 -> Interior Repairs LEVEL 2 | C14: =+signpgs!D57 -> TBD | D14: =+signpgs!#REF! -> #REF!
A15: It is well established that after a covered loss has occurred, the policyholder ordinarily may assign the claim to another person or entity.
A16: The post-loss assignment pertains to, yet is not limited to, the assignment of a payment that may have been a payment that has been reduced to a specific amount owed by the Insurance company and regarding which there is nothing more that that the policyholder must do to be entitled to receive full payment of the claim.
A17: A restoration company is entitled to full and complete payment for services rendered and an
A18: Assignment of Benefits is one way to provide payment.
A19: This assignment essentially allows the restoration service company to perform its work on credit or with no immediate payment by the homeowner, leaving the homeowner with the comforting satisfaction that the restoration company will collect its fee for service from the homeowners insurance company directly.
A20: As per the requirements for assignment of post-loss benefits from personal residential
A21: insurance policies the following stipulations are herein incorporated into this agreement:
A23: Is in writing between the policyholder & assignee and is to be timely delivered to the insurer;
A25: " Allows the policyholder to unilaterally rescind the assignment of post-loss benefits within 5 days of execution of the agreement.
A27: Is limited to claims that are contractually obligated / work performed by the assignee for damages claimed to be covered;
A29: -Contains an accurate and up-to-date statement of the scope of work to be performed.
A30: Provides the policyholder with an accurate and up-to date revised statements of the scope of work to be performed as supplemental or additional repairs are required;
... A59: Assignment of Insurance Benefits and Direct Payment Authorization:
A60: =+$A$6 -> Insurer / Claim# | B60: =+$B$6 -> Allstate Insurance Company | C60: =+$C$6 -> 0
B61: =+$B$7 -> TBD | C61: =+$C$7 -> date of loss | D61: =+signpgs!$D$23 -> Friday, April 4, 2025
B62: =+$B$8 -> TBD | C62: =+C8 -> Cause of Loss | D62: =+signpgs!$D$47 -> WATER
A63: =+$A$9 -> Insured / Assigner | B63: =+signpgs!$B$11 -> Johnson, Paul & Tamra | D63: =+$D$10 -> (216) 399-6191
B64: =+signpgs!$B$12 -> 9402 Shepard Road | C64: =+'jobinfo(2)'!$C$4 -> tringo68@yahoo.com
B65: =+signpgs!$B$13 -> Macedonia, OH, USA | D65: =+signpgs!$D$13 -> TBD
A66: =+$A$12 -> Contractor/Assignee | B66: =+signpgs!A$2 -> All Phase Consulting, LLC
B67: =+signpgs!B$5 -> 375 Rockbridge Road, Suite 172-343
B68: =+signpgs!B$6 -> Lilburn, GA, 30047 | C68: =+'email cvr'!$A$13 -> EIN # | D68: =+signpgs!$G$62 -> TIN 83-226 0563
A69: =+signpgs!$A$186 -> COMPANY REP. | B69: =+signpgs!B$186 -> Joe Jones, PM 216.450.7228 | C69: =+signpgs!$D$186 -> wsbjoe9@gmail.com
A70: =+B$63 -> Johnson, Paul & Tamra | B70: , as the owner for the job site listed herein, does hereby authorize
A71: Contractor/Assignee or Representative of and for herein named contractor to enter
A72: my property, furnish materials, supply all equipment and perform all labor necessary to preserve and protect my property from further damage and to rebuild my property to it's pre-loss condition or better. Including evaluation, inventory, storage and or cleaning of contents and or personal property.
A73: I hereby assign the insurance rights; as specified herein, benefits, and proceeds under the
A74: applicable insurance policy to | C74: =+signpgs!$A$2 -> All Phase Consulting, LLC
A75: This shall also serve as a Irrevocable Direction To Pay; I/We hereby authorize
A76: direct payment of any benefits or proceeds to: | C76: =+signpgs!$A$2 -> All Phase Consulting, LLC
A77: I/We select the option of overnight shipping for delivery of claim funds. I/We make
A78: this assignment and authorization in consideration of | C78: =+$C$76 -> All Phase Consulting, LLC
A79: agreement to perform services and supply materials and otherwise perform its
A80: Obligations under this contract, including not requiring full payment at the time of service.
A81: Contractor agrees to wait for payments as disbursed from the insurance and or escrow company.
A82: Contractor further agrees to not demand payments from Owner unless otherwise agreed.
A83: All monies due to named herein contractor are to be released without delay; solely & directly to contractor.
A84: Insurer may make payment per it's legal obligation to include all parties of interest to include policyholders, mortgagor and contractor/assignee. Contractor/ Assignee has no objection to this manner of disbursement and reserves all other rights contained herein.
A85: OWNER HEREBY SPECIFICALLY REQUESTS THAT ALL REBUILD PAYMENTS BE PAID TO CONTRACTOR:
A86: =+signpgs!$A$57 -> Interior Repairs LEVEL 1 | B86: =+signpgs!$C$57 -> Interior Repairs LEVEL 2 | C86: =+signpgs!$D$57 -> TBD | D86: =+signpgs!#REF! -> #REF!
A87: =+'jobinfo(2)'!B78 -> Mortgage co | B87: =+'jobinfo(2)'!$C$78 -> TBD | D87: =+'jobinfo(2)'!$C$79 -> TBD
A88: This is a LEGALLY BINDING, Irrevocable Document; Fully Enforceable. Please read carefully
A89: =+signpgs!$A$32 -> X___________________________________ _____________ | C89: =+signpgs!$C$32 -> X_ _________________________________ _____________ | D89: =+signpgs!$D$32 -> Friday, April 4, 2025
A90: =+signpgs!$A$185 -> Johnson, Paul & Tamra | C90: =+signpgs!$C$185 -> TBD
A91: Contractor or Rep. | B91: =+$B$69 -> Joe Jones, PM 216.450.7228 | D91: =+$C$69 -> wsbjoe9@gmail.com
A96: “Assignments of Insurance Rights.” A well-drafted Assignment of Insurance rights includes assignments of benefits, the right to appraisal, and the rights to sue, as well as a direction to pay.
A100: IRREVOCABLE DIRECTION. Assignor hereby irrevocably directs the contracting party to, or grantor or licensor of, any such Assigned Contract , whether identified in Schedule A or otherwise, to the extent not prohibited by either such Assigned Contract or applicable law, or to the extent permitted under any recognition or other agreement executed by such grantor, upon demand and after notice from Agent of the occurrence of an Event of Default under any of the Loan Documents, to recognize and accept Agent as the holder of such Assigned Contract and Permit for any and all purposes as fully as it would recognize and accept Assignor and the performance of Assignor thereunder. Assignor does hereby constitute and appoint Agent, while this Assignment remains in force and effect, irrevocably, and with full power of substitution and revocation, its true and lawful attorney for and in its name, place and stead, after the occurrence of such an Event of Default, to demand and enforce compliance with all the terms and conditions of the Assigned Contracts and all benefits accrued thereunder, whether at law, in equity or otherwise.
