Workbook
Name a...new_customer: #REF!
Name a...new_customer: #REF!
Name a...new_customer: #REF!
Name Advance_Payment_Request: 'notary pgs'!#REF!
Name Advance_Payment_Request: release!#REF!
Name Advance_Payment_Request: current!#REF!
Name Assignment_of_Benefits_and_Direct_Payment_Authorization: 'notary pgs'!#REF!
Name Assignment_of_Benefits_and_Direct_Payment_Authorization: release!#REF!
Name Assignment_of_Benefits_and_Direct_Payment_Authorization: current!#REF!
Name causeoflosslist: #REF!
Name CO.REP._email: [1]current!$F$14
Name Column.a.new.cst: 'jobinfo(2)'!$B$1:$B$43
Name Column.a.new.cst: 'jobinfo(2)'!$B$1:$B$43
Name Column.a.new.cst: current!#REF!
Name column.c.new.cst: #REF!
Name column.c.new.cst: #REF!
Name column.c.new.cst: #REF!
Name company.rep.1: [1]current!$F$13
Name cst.Barnes: #REF!
Name cst.Barnes: #REF!
Name cst.Barnes: #REF!
Name cst.Bethlehem_Temple_of_Praise: #REF!
Name cst.Bradford_Rivers: #REF!
Name cst.Hamilton__Nakeysha: #REF!
Name cst.Motley__Gloria: #REF!
Name cst.Motley__Gloria: #REF!
Name cst.Motley__Gloria: #REF!
Name cst.nori9rock_gmail.com: #REF!
Name cst.Nunn: #REF!
Name cst.Nunn: #REF!
Name cst.Nunn: #REF!
Name cst.Stewart__Antwain: #REF!
Name cst.Stewart__Antwain: #REF!
Name cst.Stewart__Antwain: #REF!
Name culpepper: #REF!
Name culpepper: #REF!
Name culpepper: #REF!
Name data: [2]QUOTE!$A$267:$R$424
Name DATA2: [3]estimate!$A$117:$R$440
Name Emergency: [4]estimate!#REF!
Name Emergency: [4]estimate!#REF!
Name Emergency: [4]estimate!#REF!
Name EMERGENCY_Repairs: [4]estimate!#REF!
Name EMERGENCY_Repairs: [4]estimate!#REF!
Name EMERGENCY_Repairs: [4]estimate!#REF!
Name Homeowner_______________________________________________Phone_________________________: [5]estimate!$D$10
Name Insurance_Claim___Check_Processing: 'notary pgs'!#REF!
Name Insurance_Claim___Check_Processing: release!#REF!
Name Insurance_Claim___Check_Processing: current!$A$292:$D$336
Name Jefferies: #REF!
Name Jefferies: #REF!
Name Jefferies: #REF!
Name LOVEJOY_INTERIOR: #REF!
Name LOVEJOY_INTERIOR: #REF!
Name LOVEJOY_INTERIOR: #REF!
Name Lovejoy_ROOF: #REF!
Name Lovejoy_ROOF: #REF!
Name Lovejoy_ROOF: #REF!
Name LxWxH: [2]QUOTE!#REF!
Name LxWxH: [2]QUOTE!#REF!

Sheet notary pgs
A1: GLOBAL SETTLEMENT AGREEMENT & MUTUAL RELEASE OF ALL CLAIMS BY ALL PARTIES
A4: Governing Law
A5: This RELEASE is to be construed under the laws of the State of | D5: =+'jobinfo(2)'!C3 -> 0
A6: The prevailing party in any action to enforce this RELEASE shall be entitled to attorneys’ fees, interest, costs and expenses of litigation (both at trial and upon appeal).
A7: Severability
A8: If any provision of this RELEASE is declared unenforceable for any reason, the remaining provisions of this RELEASE shall be unaffected thereby and shall remain in full force and effect.
A10: Attachments as fully associated and as fully part of the foregoing document:
A12: Witness Attestation; "Contractor" " of "The Parties" | D12: "Party #1"
A13: Accceptance of Full Agreement & Full Authority to execute This Agreement | D13: "Party #1"
A14: Accceptance of Full Agreement & Full Authority to execute This Agreement | D14: "Party #2"
A15: Witness Attestation; "Owner" " of "The Parties" | D15: "Party #2"
A16: Accceptance of Full Agreement & Full Authority to execute This Agreement | D16: "Party #3"
A17: Witness Attestation; "PARTY #3" " of "The Parties" | D17: "Party #3"
A19: Witness Attestation; "Contractor" " of "The Parties" | D19: "Party #1"
A20: We, the undersigned "Contractor" as one of "The Parties" and the undersigned witnesses, respectively, whose names are signed to the attached or foregoing instrument declare:
A21: (1) that the "Contractor " as one of "The Parties" executed this "Agreement" .
A22: (2) that, in the presence of both witnesses, the "Contractor " as one of "The Parties" signed this document
A23: (3) that the "Contractor" as one of "The Parties" executed this "Agreement" as a free and voluntary act for the purposes expressed in it;
A24: (4) that each of the witnesses, in the presence of the "Contractor " as one of "The Parties" and of each other, signed this "Agreement" as a witness;
A25: (5) that the "Contractor " as one of "The Parties" was of sound mind when the "Agreement" was ….. .. executed;
A26: (6) that to the best knowledge of each of the witnesses the "Contractor " as one of "The Parties" was, …. at the time the will was executed, at least eighteen (18) years of age .
A27: Witness Signature # 1 of 2_ X_____________________________________ Date ____/_____/_____
A28: Printed Legal Name ____________________________________________
A29: Witness Signature # 2 of 2_ X_____________________________________ Date ____/_____/_____
A30: Printed Legal Name ____________________________________________
A31: =+A19 -> Witness Attestation; "Contractor" " of "The Parties" | D31: =+D19 -> "Party #1"
A32: Accceptance of Full Agreement & Full Authority to execute This Agreement | D32: "Party #1"
A33: " The Parties" represent and warrant that the representative signing this agreement:
A34: • has read this agreement and is knowingly and voluntarily executing this agreement
A35: in good faith for the reasons set forth herein;
A36: • is at least eighteen (18) years of age and has never been declared incompetent by
A37: any court or agency of the government; and
A38: • has been fully advised as to its legal effect.
A39: * fully understands that by signing this pages agrees to to the foregoing above pages
A40: " The Parties" declare that they have read and understand the foregoing
A41: RELEASE and have full legal capacity to execute this RELEASE.
A42: SIGNED WITNESSED AND SEALED this _____ day of ____________, 20_____.
A43: X ________________________________________________
A44: =+'jobinfo(2)'!C96 -> 0
B45: as one of "The Parties" executed this "Agreement"
A46: The foregoing instrument was acknowledged before me this _____ day of
A47: _________, 20_____ by ______________________________________, and who is
A48: personally known to me OR who has produced _______________________________ as
A49: identification and who did take an oath. | C49: ________________________________
A50: {SEAL} | C50: NOTARY PUBLIC
C51: My Commission Expires: ____________
A52: =+A32 -> Accceptance of Full Agreement & Full Authority to execute This Agreement | D52: =+D32 -> "Party #1"
A53: Witness Attestation; "Owner" " of "The Parties" | D53: "Party #2"
A54: We, the undersigned "Owner" as one of "The Parties" and the undersigned witnesses, respectively, whose names are signed to the attached or foregoing instrument declare:
A55: (1) that the "Owners " as one of "The Parties" executed this "Agreement" as the "Owners ".
A56: (2) that, in the presence of both witnesses, the "Owners " as one of "The Parties" signed this document
A57: (3) that the "Owners" as one of "The Parties" executed this "Agreement" as a free and voluntary act for the purposes expressed in it;
A58: (4) that each of the witnesses, in the presence of the "Owners " as one of "The Parties" and of each other, signed this "Agreement" as a witness;
A59: (5) that the "Owners " as one of "The Parties" was of sound mind when the "Agreement" was ….. .. executed;
A60: (6) that to the best knowledge of each of the witnesses the "Owners " as one of "The Parties" was, at the time the document was executed, at least eighteen (18) years of age .
A61: Witness Signature # 1 of 2_ X_____________________________________ Date ____/_____/_____
A62: Printed Legal Name ____________________________________________
A63: Witness Signature # 2 of 2_ X_____________________________________ Date ____/_____/_____
A64: Printed Legal Name ____________________________________________
A65: =+A53 -> Witness Attestation; "Owner" " of "The Parties" | D65: =+D53 -> "Party #2"
A66: Accceptance of Full Agreement & Full Authority to execute This Agreement | D66: "Party #2"
A67: " The Parties" represent and warrant that the representative signing this agreement:
A68: • has read this agreement and is knowingly and voluntarily executing this agreement
A69: in good faith for the reasons set forth herein;
A70: • is at least eighteen (18) years of age and has never been declared incompetent by
A71: any court or agency of the government; and
A72: • has been fully advised as to its legal effect.
A73: * fully understands that by signing this pages agrees to to the foregoing above pages
A74: " The Parties" declare that they have read and understand the foregoing
A75: RELEASE and have full legal capacity to execute this RELEASE.
A76: SIGNED WITNESSED AND SEALED this _____ day of ____________, 20__.
A77: X ________________________________________________
A78: =+#REF! -> #REF! | B78: as the "Owner " and as one of "The Parties" executed this "Agreement"
A79: X ________________________________________________
B80: as the "Owner " and as one of "The Parties" executed this "Agreement"
A81: The foregoing instrument was acknowledged before me this _____ day of
A82: ______________, 20_______ by ______________________________________, and who is
A83: personally known to me OR who has produced _______________________________ as
A84: identification and who did take an oath. | C84: ________________________________
A85: {SEAL} | C85: NOTARY PUBLIC
C86: My Commission Expires: ____________
A88: =+A66 -> Accceptance of Full Agreement & Full Authority to execute This Agreement | D88: =+D66 -> "Party #2"
A89: Witness Attestation; "PARTY#3 " of "The Parties" | D89: "Party #3"
A90: We, the undersigned as one of "The Parties" and the undersigned witnesses, respectively, whose names are signed to the attached or foregoing instrument declare:
A91: (1) that the as one of "The Parties" executed this "Agreement" .
A92: (2) that, in the presence of both witnesses, as one of "The Parties" signed this document
A93: (3) that the as one of "The Parties" executed this "Agreement" as a free and voluntary act for the purposes expressed in it;
A94: (4) that each of the witnesses, in the presence of the, as one of "The Parties" and of each other, signed this "Agreement" as a witness;
A95: (5) that the as one of "The Parties" was of sound mind when the "Agreement" was executed;
A96: (6) that to the best knowledge of each of the witnesses, at the time the document was executed, was at least eighteen (18) years of age .
A97: Witness Signature # 1 of 2_ X_____________________________________ Date ____/_____/_____
A98: Printed Legal Name ____________________________________________
A99: Witness Signature # 2 of 2_ X_____________________________________ Date ____/_____/_____
A100: Printed Legal Name ____________________________________________
A101: =+A89 -> Witness Attestation; "PARTY#3 " of "The Parties" | D101: =+D89 -> "Party #3"
A102: Accceptance of Full Agreement & Full Authority to execute This Agreement | D102: =+D101 -> "Party #3"
A103: " The Parties" represent and warrant that the representative signing this agreement:
A104: • has read this agreement and is knowingly and voluntarily executing this agreement
A105: in good faith for the reasons set forth herein;
A106: • is at least eighteen (18) years of age and has never been declared incompetent by
...

Sheet release
A1: GLOBAL SETTLEMENT AGREEMENT & MUTUAL RELEASE OF ALL CLAIMS BY ALL PARTIES
D2: page #
A3: "The Parties" | D3: 2
A4: ACKNOWLEDGEMENT OF CONSIDERATION | D4: 3
A5: "The Parties" Responsible for Fees | D5: 4
A6: No Assignment Clause | D6: 4
A7: Non Disclosure Clause | D7: 5
A8: A general release intended to release all claims | D8: 5
A9: Voluntary and Non inducement Clause of Agreement | D9: 5
A10: "The Project " Work performed | D10: 6
A11: Covenant not to cause or to institute any lawsuit. | D11: 7
A12: Withdrawal of Any Existing Lawsuits / Litigation | D12: 7
A13: Waiver of Liens | D13: 7
A14: Complete and FINAL RELEASE. | D14: 7
A15: Governing Law | D15: 7
A16: Severability
A19: Attachments as fully associated and as fully part of the foregoing document:
A20: Witness Attestation; "Contractor" " of "The Parties" | D20: "Party #1"
A21: Acceptance of Full Agreement & Full Authority to execute This Agreement | D21: "Party #1"
A22: Acceptance of Full Agreement & Full Authority to execute This Agreement | D22: "Party #2"
A23: Witness Attestation; "Owner" " of "The Parties" | D23: "Party #2"
A24: Acceptance of Full Agreement & Full Authority to execute This Agreement | D24: "Party #3"
A25: Witness Attestation; "PARTY #3" " of "The Parties" | D25: "Party #3"
A26: Witness Attestation; "Contractor" " of "The Parties" | D26: "Party #1"
A29: X | B29: the referring/connecting party | D29: Party #3
A31: GLOBAL SETTLEMENT AGREEMENT & MUTUAL RELEASE OF ALL CLAIMS BY ALL PARTIES
A32: "The Parties"
A33: THIS GLOBAL SETTLEMENT AGREEMENT & MUTUAL RELEASE OF ALL CLAIMS BY ALL PARTIES (“Agreement”) is dated, entered into and made fully effective
A34: 44510 | B34: (irrespective of the date actually signed by "THE PARTIES").
A35: =+'jobinfo(2)'!C100 -> 0 | C35: =+'jobinfo(2)'!C112 -> 0
A36: Project Manager, | B36: personally and corporately. | D36: , Party #1/Contractor
A37: =+'jobinfo(2)'!C1 -> 0 | B37: =+'jobinfo(2)'!C6 -> 0 | D37: , Party #2/Owner{s}
A38: =+A29 -> X | B38: the referring/connecting party | D38: Party #3
A39: ( "The Parties" as herein collectively referred to.) Have been in settlement discussions regarding the herein stated matter ( "Contract" or "PROJECT").
A41: As per our conversation, we ( "The Parties") have reached an "Agreement" in compromise of this "Contract & or PROJECT"; as a resolution to bring this matter to closure. In no way do ( "The Parties"") imply or convey that the execution of the release of all claims is required for settlement of this matter; as other settlement options and means are available for resolution.
A43: Execution of this Agreement or any act or failure to act on the part of all "THE PARTIES" by contract or at law as all such rights and defenses are hereby specifically reserved.
A45: Whereas the herein stated parties with full purpose and intent desire to sever and forever cancel and extinguish any and all contractual relationships by mutual execution of this document.
A47: COMES NOW, | B47: =+A35 -> 0 | C47: in its individual capacity and as assignee.
A48: =+C35 -> 0 | C48: , personally and corporately.
A49: =+A29 -> X | B49: the referring/connecting party
A50: Also COMES NOW | B50: =+'jobinfo(2)'!$C$1 -> 0 | C50: =+'jobinfo(2)'!$C$6 -> 0
B51: =+'jobinfo(2)'!C2 -> 0
B52: =+'jobinfo(2)'!C3 -> 0 | C52: as full legal "Property Owner/s".
A53: ALL PARTIES, on behalf each individual party of and including all of each of their predecessors, successors, assigns, subsidiaries, affiliates, partners, insurers, estates, agents, servants, employees, receivers, administrators, directors, shareholders, officers, parent and related corporations and/or business organizations of any kind, attorneys and legal representatives (hereinafter collectively referred to as " The Parties"), having read the terms of this RELEASE (hereinafter sometimes referred to as the "RELEASE"), does agree as follows:
A55: ACKNOWLEDGEMENT OF CONSIDERATION
A56: IN CONSIDERATION of a Full and Final Mutual Release evidenced by signature of "THE PARTIES", subsidiaries, employers, current and former employees, servants, officers, directors, independent adjusters, appraisers, experts, parent and related corporations and/or business organizations of any kind, and attorneys (hereinafter collectively referred to as "THE PARTIES"), in addition to any and all amounts previously tendered, made payable to " THE PARTIES" and sufficiency of which is hereby acknowledged.
A58: Also, Forbearing enforcement of legally enforceable remedies is enough consideration to support this "Agreement". This "Agreement" represents the entire "Agreement" between the parties. Any statements made orally, written, or otherwise which are not contained herein shall have no impact on either parties’ rights or obligations elaborated in this "Agreement".
A59: " The Parties" do hereby remise, release, acquit, and forever discharge " The Parties" from any and all claims, actions, suits, losses, causes of action, demands, rights, damages (whether compensatory, consequential, statutory and/or punitive), loss of services, attorney’s fees, expenses, compensation, obligations towards " The Parties", and liabilities of whatsoever kind, nature, or description, whether known or unknown, liquidated or unliquidated, absolute or contingent, presently existing or hereafter discovered, in law or in equity, arising out of, relating to, or concerning the "Contract & or PROJECT"; for the insured property at:
B60: =+'jobinfo(2)'!C2 -> 0 | C60: =+'jobinfo(2)'!C3 -> 0
A62: (hereinafter referred to as “THE PROPERTY”), concerning damages that occurred on or about
A63: =+'jobinfo(2)'!C12 -> 0 | B63: , Contract date on or about, | C63: =+'jobinfo(2)'!C22 -> 0
A65: (the “INCIDENT”), which may have been caused by any | C65: =+'jobinfo(2)'!C11 -> 0
A66: , and any concurrent or resulting damage, under Claim Number | D66: =+'jobinfo(2)'!C27 -> 0
A67: (the "Claim"), and/or relating to any assertions, allegations or claims for loss, damage or entitlement to proceeds that are now or could be brought by " The Parties" .
A68: The said parties, for the considerations hereinafter mentioned, hereby agree to the following:
A69: The contactor has provided inspection services, estimating services, document preparation services
A70: cost analysis /repair specifications, damages report & discovery, testing , services rendered,
A71: jobsite visits, phone calls, project management, proof of loss supporting documents and scheduling.
A72: CONTRACTOR has provided professional services, labor and materials to this date and time.
A74: The Owner accepts all work, unless excluded by other contracts, "as is", as of today's date.
A76: Contractor, "Party #1", is hereby released from any obligation to perform all and any work related to "The Project".
F77: The Owner accepts all work , "as is", as of the "Agreement" date.
A78: Contractor agrees not to interfere in any manner whatsoever concerning "The Project".
A80: Contractor agrees to cooperate to the best of his ability in providing consultations as they may deem
A81: appropriate and agrees to not unreasonably withhold the same at their sole discretion.
F82: X___________________________________ _____________ | H82: X_ _________________________________ _____________ | I82: 44466
A83: Contractor shall have no further interest in any funds designated for the '' The Project".
A84: Owner is hereby released to hire any Contractor of their choosing. | F84: LEWIS, SANDI | H84: NA
A86: Owner accepts all further responsibility for and acknowledges receipt of all related Work materials and documentation associated with this matter.
A88: Nothing herein shall be considered legal advice, this is informational research ONLY !!!!! We are neither attorneys nor Public Adjusters. Of course it is your choice to hire whom to deem fit to assist you. We shall cooperate with whomever you choose.
A90: 20. This is a LEGALLY BINDING, Irrevocable Document; Fully Enforceable. Please read carefully
A92: IN FURTHER CONSIDERATION for the aforementioned “AGREEMENT” by " The Parties", “THE Parties” do hereby remise, release, acquit, and forever discharge " The Parties". from any and all claims, liens, actions, causes of action, possible causes of action demands, rights, damages (whether compensatory, consequential, statutory and/or punitive), costs, loss of services, expenses, compensation, and obligations towards " The Parties" whatsoever, which " The Parties" now have or which may accrue on account of or in any way growing out of any and all known and unknown, foreseen and unforeseen, claims or damages, resulting or to result from " The Parties' “PROJECT “handling practices and/or relating to any assertions, allegations or claims that " The Parties" alleged or may have alleged in the above referenced “Project”. Including but not limited to any claim or suit for breach of contract, declaratory action, common law and statutory bad-faith, and breach of the covenant of good faith and fair dealing, anticipatory or otherwise.
A93: " The Parties" hereby acknowledges and agrees that the release set forth above is a general release intended to release all claims. " The Parties" expressly waive and assume the risk of any and all unknown or unanticipated claims, whether through ignorance, oversight, error, negligence, or otherwise, even if knowledge of such claims would materially affect its decision to enter into this RELEASE. " The Parties" further agree that it has accepted the consideration in this RELEASE as a complete compromise of matters involving disputes of law and fact, and it assumes the risk, on behalf of itself, that that the facts or law may be otherwise than they believe.
A94: "The Parties" Responsible for Fees
A95: " The Parties" hereby agree that they shall bear their own costs, attorney’s fees, fees, cost or interest related in any way to this claim.
A96: No Assignment Clause
A97: " The Parties" represent and warrant that they have not previously assigned or otherwise transferred, or attempted to assign or otherwise transfer, any of the rights or claims released by " The Parties" in this RELEASE. " The Parties" further represent and warrant that they have no other claims or rights against " The Parties" other than the rights or claims released by " The Parties" in this "Agreement". It is also stipulated that can be no future assignment of any rights concerning "The Project".
A99: Non Disclosure Clause
A100: " The Parties" covenant and agree that it will not disclose, directly or indirectly, orally or in writing, the settlement discussions between the Parties, the terms of this settlement, nor the amounts of payment hereunder, to any person not a party to this RELEASE. Further, " The Parties" covenant and agree that it will hold all terms of this settlement confidential and will not disclose any terms of this agreement to anyone who is not a party to this RELEASE, including, but not limited to: all persons, entities, members of the news media, and professional organizations, except upon the written consent of " The Parties" , by court order, for tax purposes, or to enforce the terms of this RELEASE. As to any inquiries made by a person knowing that a dispute existed between " The Parties"; The Parties", will respond only to the effect that such a dispute was amicably resolved between " The Parties".
A102: A general release intended to release all claims
... A110: CONTRACTOR has provided professional services, labor and materials to this date and time.
A111: OWNER has paid the CONTRACTOR-"IN FULL", for the herein specified services, materials and labor, including , yet not limited to the following: This shall be in payment for | E111: The said parties, for the considerations hereinafter mentioned, hereby agree to the following:
A112: Contractor, "Party #1", is hereby released from any obligation to perform all and any work related to "The Project".
A114: Contractor agrees to cooperate to the best of his ability in providing consultations as he may deem appropriate and agrees to not unreasonably withhold the same at his sole discretion. This is not an obligation upon contractor; it is a courtesy extended to owner.
A115: Contractor shall have no further interest in any funds designated for the '' The Project".
A116: Owner is hereby released to hire any Contractor of their choosing.
A117: Owner accepts all further responsibility for and acknowledges receipt of all related
A118: paperwork created for "The Project".
A119: The Owner accepts all work, unless excluded by other contracts, "as is", as of today's date.
A120: Owner hereby agree to hold harmless and indemnify Contractor for any and all work, errors, omissions, licensing requirements, permits, bonds, and or insurances of any type as maybe be required for "The Project".
A121: Owner further acknowledges that "The Project" shall be completed to their full discretion and direction. Owner shall forever hold harmless and indemnify Contractor for any and all work previously performed or in the future; this shall apply to the impact any work, "from any and all claims, actions, suits, losses, causes of action, demands, rights, damages (whether compensatory, consequential, statutory and/or punitive), loss of services, attorney’s fees, expenses, compensation, obligations towards "" The Parties"", and liabilities of whatsoever kind, nature, or description, whether known or unknown, liquidated or unliquidated, absolute or contingent, presently existing or hereafter discovered, in law or in equity, arising out of, relating to, or concerning ""PROJECT"". "
A122: " The Parties" hereby acknowledge and agree that the release set forth in herein and terms contained herein is a general release intended to release all claims." The Parties" expressly waive and assume the risk of any and all unknown or unanticipated claims, whether through ignorance, oversight, error, negligence, or otherwise, even if knowledge of such claims would materially affect their decision to enter into this RELEASE. " The Parties" further agree that they have accepted the consideration in this RELEASE as a complete compromise of matters involving disputes of law and fact, and they assume the risk, on behalf of themselves, that that the facts or law may be otherwise than they believe.
A124: It is understood and agreed by " The Parties" that this is a settlement of a disputed "Project" and that " The Parties", by making the "AGREEMENT" described herein, intends merely to resolve controversy and avoid the burden, expense and annoyance of litigation. "THE PARTIES" further understand and agree that this "AGREEMENT" is not to be construed as an admission of liability on the part of " The Parties".
A126: Covenant not to cause or to institute any lawsuit.
... A143: Governing Law
A144: This RELEASE is to be construed under the laws of the State of | D144: =+'jobinfo(2)'!C3 -> 0
A145: The prevailing party in any action to enforce this RELEASE shall be entitled to attorneys’ fees, interest, costs and expenses of litigation (both at trial and upon appeal).
A146: Severability
A147: If any provision of this RELEASE is declared unenforceable for any reason, the remaining provisions of this RELEASE shall be unaffected thereby and shall remain in full force and effect.
A149: Attachments as fully associated and as fully part of the foregoing document:
...

Sheet atty rel
A1: =+'jobinfo(2)'!C95 -> 0
A2: =+'jobinfo(2)'!C96 -> 0 | C2: =+'jobinfo(2)'!C97 -> 0
A3: =+'jobinfo(2)'!C100 -> 0 | B3: =+'jobinfo(2)'!C98 -> 0 | D3: =+'jobinfo(2)'!C102 -> 0
A4: =+'jobinfo(2)'!C101 -> 0 | B4: =+'jobinfo(2)'!C99 -> 0 | D4: =+'jobinfo(2)'!C103 -> 0
A5: =+'jobinfo(2)'!C104 -> 0
A6: =+'jobinfo(2)'!C105 -> 0 | C6: =+'jobinfo(2)'!C106 -> 0
A7: COMPANY REP. | B7: =+'jobinfo(2)'!C107 -> 0 | C7: =+'jobinfo(2)'!C108 -> 0
A8: COMPANY REP. #2 | B8: =+'jobinfo(2)'!C109 -> 0 | C8: =+'jobinfo(2)'!C110 -> 0
A9: =+'jobinfo(2)'!B1 -> Property-Owner Name | B9: =+'jobinfo(2)'!C1 -> 0 | C9: =+'jobinfo(2)'!B11 -> Cause of Loss | D9: =+'jobinfo(2)'!C11 -> 0
A10: =+'jobinfo(2)'!B2 -> Property address: street | B10: =+'jobinfo(2)'!C2 -> 0 | C10: =+'jobinfo(2)'!B12 -> date of loss | D10: =+'jobinfo(2)'!C12 -> 0
A11: =+'jobinfo(2)'!B3 -> Property city, state, zip | B11: =+'jobinfo(2)'!C3 -> 0 | C11: =+'jobinfo(2)'!B13 -> rebuild type 1 | D11: =+'jobinfo(2)'!C13 -> 0
A12: =+'jobinfo(2)'!B4 -> Customer Email | B12: =+'jobinfo(2)'!C4 -> 0 | C12: =+'jobinfo(2)'!B14 -> rebuild type 2 | D12: =+'jobinfo(2)'!C14 -> 0
A13: =+'jobinfo(2)'!B5 -> Cst-owner Phone# | B13: =+'jobinfo(2)'!C5 -> 0 | C13: =+'jobinfo(2)'!B15 -> rebuild type 3 | D13: =+'jobinfo(2)'!C15 -> 0
A14: Insurance Co. Name & Policy # | B14: =+'jobinfo(2)'!C26 -> 0 | C14: =+'jobinfo(2)'!C27 -> 0 | D14: =+'jobinfo(2)'!C16 -> 0
A15: To Whom It May Concern:
A16: Please be advised that we are under the impression that you either desire to cancel or modify the terms of our original legally binding contract
A17: dated on or about | B17: =+'jobinfo(2)'!C22 -> 0
A18: It is our stern and fast position that we choose only to work with people whom we can maintain a cordial , professional relationship.
A19: Your actions suggest and have caused the nature of the relationship to deteriorate greatly, some of your remarks could occur as personal threats and or harassment. Also possible liebel and or slander. We do have concerns for our safety in dealing with you. No one from our firm will meet with in person any longer; unless it is a highly public place where we feel safe.
A20: We have invested more time into this file that than our standard time frame and we will not proceed any further without a clear , well defined understanding with you.
A21: Including raising the insurance company's offer from $2,144 to 8,914; an increase of $6,770. That was round one only!!!!!!
A22: Then raising the insurance company's offer from $8,914 to $17,814; an increase of $9,000. That was based on our efforts and expertise!!!!!!
A23: If you desire to end this business relationship you may prepare your own release proposal , use our standard mutual release form or possibly have your attorney prepare a mutual release document.
A24: Per the contract terms please advise us " in writing" of your position on this matter.
A26: =+current!#REF! -> #REF! | B26: =+current!#REF! -> #REF! | D26: =+current!#REF! -> #REF!
E30: 2000
A31: =+current!#REF! -> #REF! | E31: 6625.18
A32: =+current!#REF! -> #REF! | E32: 6800
A33: =+current!#REF! -> #REF! | E33: 9000
A34: =+current!#REF! -> #REF! | E34: =SUM(E30:E33) -> 24425.18
A35: =+current!#REF! -> #REF!
A36: =+current!#REF! -> #REF!
D40: Gross | E40: 17913.76
D41: 0.2 | E41: =-E40*D41 -> -3582.752
E42: =+E40+E41 -> 14331.008
D43: MTGE | E43: -6500
E44: =+E42+E43 -> 7831.008
D45: roof | E45: =-250*25 -> -6250
D46: Paint | E46: =+E44+E45 -> 1581.008
D47: Deductible | E47: -1000
D48: Misc. | E48: =+E46+E47 -> 581.008
D50: Check | E50: 9000
D51: Mitigation | E51: -6625.18
E52: =+E50+E51 -> 2374.82
D53: Fees 20% | E53: =+E41 -> -3582.752
D54: Bal Due | E54: 1656.2
D56: Customer Loans | E56: 530
E57: 100
E58: 100
E59: 60
E60: 40
D61: Total Due | E61: =SUM(E54:E60) -> 2486.2
A68: William Hopkins
A69: 1529 Wilmar Ave.
A70: Cleveland Heights, OH 44118
A72: Dear Mr. William Jones and or Fowlkes Remodeling:
A73: Please be advised that your services are no longer needed. You are fired.
A74: Your threats and attempts and intimidation against me are taken as a highly disrespectful personal attack.
A76: Your poor performance has caused me numerous problems not limited to emotional stress, investigation and embarrassment with my longtime insurer, personal discomfort with my family and living arrangments, financial issues.
A78: Your failed promises and delays have disrupted my peaceful enjoyment of my home.
A79: Your highly unprofessional tactics are an insult upon the integrity and character of your trade.
A80: I have been an electrical contractor for many years and have seen the likes of you before. Not good !!
A81: Any further contact by you , other than a complete apology and retraction of your threatened actions (within 3 days of receipt of this notice) may result in the following:
A82: Arrest for trespassing
... A107: Please be advised that I hereby give my full consent for
A108: =+current!#REF! -> #REF! | B108: to cash / negotiate the attached check in the
A109: Amount of : | B109: 25245.31 | C109: 43242
A110: CK # 104944 | B110: =+#REF! -> #REF! | C110: =+#REF! -> #REF!
A111: Payor | B111: =+#REF! -> #REF!
A113: It is fully understood that this permission is based upon the construction contract
A114: that we have executed.
A116: We agree and are bound to hold harmless any patties that handle this current matter in
A117: conjunction with
A119: Under penalty of perjury I do Attest to the herein statements of fact.
A120: I affix my legal signature of my own free will.
A121: X______________________________ _______________________________ | C121: ______/_______/2018
A122: =+cst.Hamilton__Nakeysha -> #REF!
A124: Affix copy of Driver's License
B125: OR
A127: AFFIDAVIT AND CERTIFICATION OF Signature
A128: Sworn to before me and subscribed in my presence on this ____ day of __ _________, 20___.
A129: X______________________________ _______________________________
C130: ______/_______/2018
A131: =+A122 -> #REF! | C131: Signature of Co- Owner Date
A132: State of: ____________ County/Parish of: ______________________
A133: Notary Signature: ______________________________________________
A134: My Commission Expires: ______/_______ / 20_______ Notary Seal:
A137: =+#REF! -> #REF! | C137: =+#REF! -> #REF!
A138: =+#REF! -> #REF! | C138: =+#REF! -> #REF!
A139: =+#REF! -> #REF! | C139: =+#REF! -> #REF!
A141: Mr. Joseph Jasper Jr. | B141: Attorney at Law | C141: 216.406.7967 | E141: www.murtistaylor.info
A142: 614 Superior Ave. | B142: Rockerfeller Building
A143: Cleveland, OH 44113 | B143: lawjasper@hotmail.com | D143: 43271
E144: 940
A145: NOTICE OF RELEASE OF LEGAL COUNSEL
A146: =+A154 -> #REF! | B146: =+B154 -> #REF!
A147: Dear Mr Jasper and TO WHOM IT MAY CONCERN:
A148: Mr.Jasper Please accept this letter as formal notice that you are hereby released from any obligation and or contract to litigate on my behalf or to represent me as legal counsel, effective immediately. This is in reference to the above specific matter ONLY as fully stated below. | E148: www.murtistaylor.info/files/60113459.pdf
A149: =+#REF! -> #REF! | B149: =+#REF! -> #REF!
A150: =+#REF! -> #REF! | C150: =+#REF! -> #REF!
...

Sheet current
A1: ** GENERAL AUTHORIZATION **
A2: _____CONTRACTOR & HOMEOWNER AGREEMENT_____
A3: AFFIDAVIT AND CERTIFICATION OF INTENT TO REPAIR
A4: Mortgage Company Insurance Claim Check Processing,
A5: Enclosed is an Assignment of Insurance Benefits and Direct Payment Authorization Thus, all monies due to named herein contractor are to be released without delay; solely and directly to contractor.
A6: Original Documents | B6: GENERAL AUTHORIZATION | C6: Policyholder {___} CONTRACTOR {___} | E6: page # | F6: Cover Letter
B7: EMERGENCY SERVICES WORK AUTHORIZATION
B8: Assignment Of Benefits AOB | C8: Policyholder {___} CONTRACTOR {___}
B9: CONTRACTOR & HOMEOWNER AGREEMENT_____
B10: $$ Amount | C10: Policyholder {___} CONTRACTOR {___} | E10: 1
B11: Notice of Right of Recession | E11: =1+E10 -> 2 | F11: EMERGENCY SERVICES WORK AUTHORIZATION
B12: AFFIDAVIT AND CERTIFICATION OF INTENT TO REPAIR | D12: Policyholder {___}
B13: NOTARY | C13: Policyholder {___} | D13: na
A14: Contractor Documents | B14: CONDITIONAL WAIVER OF LIEN | D14: CONTRACTOR {___}
B15: NOTARY PAGE | D15: CONTRACTOR {___}
A16: Enclosed is an Assignment of Insurance Benefits and Direct Payment Authorization Thus, all monies due to named herein contractor are to be released without delay; solely and directly to contractor. | E16: =1+#REF! -> #REF!
A18: FRAUD STATEMENT
A19: Any person who knowingly and with intent to defraud any insurance company or other person files an application for insurance or statement of claim containing any materially false information, or conceals for the purpose of misleading, information concerning any fact material thereto commits a fraudulent insurance act, which is a crime and subjects such person to criminal and civil penalties.
A20: This may include submitting or causing to be submitted on your behalf documents which claim to be for the purpose of obtaining funds not used for the specific purpose of paying the contractor whom provides his services in relation to such documentation.
A22: 14. Owner agrees to use all funds received from insurance proceeds as originally reported and declares all the information concerning their damages and or loss are true to the best of their knowledge. Owner agrees to indemnify and hold harmless the contractor. in relation to this item specifically.
A23: 15. Owner shall promptly notify contractor of any funds received and promptly remit to Contractor;
A24: without delay. Contractor also agrees to notify Owner of any funds received on their behalf.
A25: Owner shall promptly notify and provide contractor with a copy of any paperwork received.
A26: Contractor agrees to wait for payments as disbursed from the insurance and or escrow company.
A27: Contractor further agrees to not demand payments from Owner unless otherwise agreed.
A28: X______________________________ X ___________________________________ | D28: ____/_____/2018
A29: =+$A$62 -> #REF! | C29: Signature of Co- Owner Date
A30: Contract Addendum / Memorandum of UNDERSTANDING
A31: Dear Property-owner:
A32: Please note that we have compiled a listing of issues that may cause unneccessary delays or claim failure or our withdrawal from the claim process.
A33: We ask that you please review the list and initial each and every item. If you feel that any item is not workable for you , then it may be best that we not move forward. .
A34: We are more than willing to discuss in detail any of these or any others and get a mutual understanding
A35: Deductible | D35: ___________INITIAL
A36: * HOMEOWNER MAY USE THE Referral program FUNDS TO PAY FOR THE INSURANCE DEDUCTIBLE.
A37: * HOMEOWNER MAY perform as subcontractor for some of the work; paint / clean/ inventory contents
A38: Roof upgrade & Other work upgrades
A39: HOMEOWNER MAY USE Referrals FUNDS TO PAY FOR UPGRADED 30 YEAR ROOF. | D39: ___________INITIAL
A40: Fear | B40: Fear &Intimidation from insurer | D40: ___________INITIAL
B41: Integrity, concern that we are doing something illegal.
A42: Greed | B42: Overly Concern about our profits. | D42: ___________INITIAL
B43: Not wanting to pay agreed upon fees.
B44: Attempting to control the released funds.
B45: Greed over money; wanting unrealistic rebates / compensations.
B46: Greed over additional work; unrealistic expectations
A47: Control Issues | B47: Attempting to control the released funds. | D47: ___________INITIAL
B48: Releasing control to allow us to do our job.
B49: Wanting to control the job/ workflow
B50: Allow us to show how you are able to "economize"
A51: Trust | B51: History of past contractors | D51: ___________INITIAL
A52: Cooperation as a team | B52: Cooperation as a team | D52: ___________INITIAL
B53: Failure to provide required info.
B54: Failure to sign needed documents.
A55: Patience | B55: Unable to deal with insurer's delays | D55: ___________INITIAL
B56: Trying to rush the process
B57: Giving us false information. Being honest is the best policy.
A58: We will not lie to the insurance company because it is unnecessary. We ask the same of you. With proper documentation lying is not needed; to recover your full claim benefits. Insures want to close claim files.
A59: USE Referral FUNDS TO PAY FOR ADDITIONAL WORK NOT COVERED BY INSURANCE. | D59: ___________INITIAL
A60: A combination of the above elements handled properly can result in zero cost to you.
A61: Letter of Satisfaction
A62: =+#REF! -> #REF!
A63: =+#REF! -> #REF!
A64: =+#REF! -> #REF!
A65: =+#REF! -> #REF! | C65: =+#REF! -> #REF!
A66: =+#REF! -> #REF! | C66: =+#REF! -> #REF!
A67: =+#REF! -> #REF! | C67: =+#REF! -> #REF!
A68: =+#REF! -> #REF! | C68: =+#REF! -> #REF!
A69: =+#REF! -> #REF! | C69: =+#REF! -> #REF!
A70: =+#REF! -> #REF! | C70: =+#REF! -> #REF!
A71: =+#REF! -> #REF!
A72: =+#REF! -> #REF!
A73: =+#REF! -> #REF!
A75: I/ We hereby certify that the restoration, repairs, or improvements have been completed and the property is in as good or better than existed prior to the loss, and that I/We are fully satisfied with the repairs.
A76: =+#REF! -> #REF! | B76: =+#REF! -> #REF! | C76: =+#REF! -> #REF! | D76: =+#REF! -> #REF!
A77: Thus all monies due to named herein named contractor are to be released without delay; solely and directly to contractor.
A78: =+#REF! -> #REF!
A79: =+#REF! -> #REF! | B79: =+#REF! -> #REF! | D79: =+#REF! -> #REF!
A80: =+#REF! -> #REF! | B80: =+#REF! -> #REF! | D80: =+#REF! -> #REF!
A81: I / We select the option of overnight shipping for expedited delivery of claim funds.
A82: =+#REF! -> #REF! | C82: =+#REF! -> #REF!
A83: =+#REF! -> #REF! | C83: =+#REF! -> #REF!
A84: X______________________________ _______________________________
A86: =+$A$62 -> #REF! | B86: =+#REF! -> #REF! | C86: Date _____/_______/2018
A88: Be aware that insurers, and adjusters, may not have to account for covered damage to a structure UNLESS the damage is brought to their attention.
A89: It is part of our job, & yours, to assist in showing your damages and loss to your insurer.
A90: Most Insurance contracts state that you must submit "proof of loss" documentation.
A91: It is akin to don't ask , don't tell; however ask and it is given.
A92: It has been stated that "for the lack of knowledge my people shall perish".
A93: WIND, HAIL, RAIN, WATER, VANDALISM, TREE, FIRE, SMOKE, Etc., DAMAGE AFFECTS a property may have sustained are listed as follows..
A94: We may inspect the following areas for damages and any others as noted:
A95: Exterior Components-
A96: 1. Roofing Systems. {___} | C96: 11. Garage doors. | D96: {___}
A97: 2. Roof decking, plywood. | C97: 12. Wood, vinyl, metal, masonry fencing. | D97: {___}
A98: 3. Attic ventilation systems. | C98: 13. Exterior lighting.
A99: 4. Fascia boards. | B99: {___} | C99: 14. Yard PlayStation.
A100: 5. Rain guttering systems. Storm Debris accumulation, | C100: 15. Patio coverings. | D100: {___}
A101: 6. Vinyl, wood, stucco, brick siding. | C101: 17. Out-buildings, sheds. | D101: {___}
A102: 7. Painted surfaces. | B102: {___} | C102: 18. AC units cooling fins, foils.
A103: 8. Windows, window frames. Window screens. | B103: {___} | C103: 19. Boats, recreational crafts.
A104: 9. Pool cage, window, porch screening. | C104: 20. Pets, livestock. | D104: {___}
A105: 10. Entry doors. | B105: {___} | C105: 21. Miscellaneous personal property. | D105: {___}
...

Sheet letter close
A1: =+'jobinfo(2)'!C95 -> 0
A2: =+'jobinfo(2)'!C96 -> 0 | C2: =+'jobinfo(2)'!C97 -> 0
A3: =+'jobinfo(2)'!C100 -> 0 | B3: =+'jobinfo(2)'!C98 -> 0 | D3: =+'jobinfo(2)'!C102 -> 0
A4: =+'jobinfo(2)'!C101 -> 0 | B4: =+'jobinfo(2)'!C99 -> 0 | D4: =+'jobinfo(2)'!C103 -> 0
A5: =+'jobinfo(2)'!C104 -> 0
A6: =+'jobinfo(2)'!C105 -> 0 | C6: =+'jobinfo(2)'!C106 -> 0
A7: COMPANY REP. | B7: =+'jobinfo(2)'!C107 -> 0 | C7: =+'jobinfo(2)'!C108 -> 0
A8: COMPANY REP. #2 | B8: =+'jobinfo(2)'!C109 -> 0 | C8: =+'jobinfo(2)'!C110 -> 0
A9: =+'jobinfo(2)'!B1 -> Property-Owner Name | B9: =+'jobinfo(2)'!C1 -> 0 | C9: =+'jobinfo(2)'!B11 -> Cause of Loss | D9: =+'jobinfo(2)'!C11 -> 0
A10: =+'jobinfo(2)'!B2 -> Property address: street | B10: =+'jobinfo(2)'!C2 -> 0 | C10: =+'jobinfo(2)'!B12 -> date of loss | D10: =+'jobinfo(2)'!C12 -> 0
A11: =+'jobinfo(2)'!B3 -> Property city, state, zip | B11: =+'jobinfo(2)'!C3 -> 0 | C11: =+'jobinfo(2)'!B13 -> rebuild type 1 | D11: =+'jobinfo(2)'!C13 -> 0
A12: =+'jobinfo(2)'!B4 -> Customer Email | B12: =+'jobinfo(2)'!C4 -> 0 | C12: =+'jobinfo(2)'!B14 -> rebuild type 2 | D12: =+'jobinfo(2)'!C14 -> 0
A13: =+'jobinfo(2)'!B5 -> Cst-owner Phone# | B13: =+'jobinfo(2)'!C5 -> 0 | C13: =+'jobinfo(2)'!B15 -> rebuild type 3 | D13: =+'jobinfo(2)'!C15 -> 0
A14: Insurance Co. Name & Policy # | B14: =+'jobinfo(2)'!C26 -> 0 | C14: =+'jobinfo(2)'!C27 -> 0 | D14: =+'jobinfo(2)'!C16 -> 0
A15: To Whom It May Concern:
A16: Please be advised that we are under the impression that you either desire to cancel or modify the terms of our original legally binding contract
A17: dated on or about | B17: =+'jobinfo(2)'!C22 -> 0
A18: It is our stern and fast position that we choose only to work with people whom we can maintain a cordial , professional relationship. | E18: It is our stern and fast position that we choose only to work with people whom we can maintain a cordial , professional relationship.
A19: Your actions suggest and have caused the nature of the relationship to deteriorate greatly, some of your remarks could occur as personal threats and or harassment. Also possible liebel and or slander. We do have concerns for our safety in dealing with you. No one from our firm will meet with in person any longer; unless it is a highly public place where we feel safe. | E19: Your actions suggest and have caused the nature of the relationship to deteriorate greatly, some of your remarks could occur as personal threats and or harassment. Also possible liebel and or slander. We do have concerns for our safety in dealing with you. No one from our firm will meet with in person any longer; unless it is a highly public place where we feel safe.
A20: We have invested more time into this file that than our standard time frame and we will not proceed any further without a clear , well defined understanding with you. | E20: We have invested more time into this file that than our standard time frame and we will not proceed any further without a clear , well defined understanding with you.
A21: Including raising the insurance company's offer from $2,144 to 8,914; an increase of $6,770. That was round one only!!!!!! | E21: Including raising the insurance company's offer from $2,144 to 8,914; an increase of $6,770. That was round one only!!!!!!
A22: Then raising the insurance company's offer from $8,914 to $17,814; an increase of $9,000. That was based on our efforts and expertise!!!!!! | E22: Then raising the insurance company's offer from $8,914 to 17 8,914; an increase of $9,000. That was based on our efforts and expertise!!!!!!
A23: If you desire to end this business relationship you may prepare your own release proposal , use our standard mutual release form or possibly have your attorney prepare a mutual release document.
A24: Per the contract terms please advise us " in writing" of your position on this matter.
A26: =+current!#REF! -> #REF! | B26: =+current!#REF! -> #REF! | D26: =+current!#REF! -> #REF!
E30: 2000
A31: =+current!#REF! -> #REF! | E31: 6625.18
A32: =+current!#REF! -> #REF! | E32: 6800
A33: =+current!#REF! -> #REF! | E33: 9000
A34: =+current!#REF! -> #REF! | E34: =SUM(E30:E33) -> 24425.18
A35: =+current!#REF! -> #REF!
A36: =+current!#REF! -> #REF!
D40: Gross | E40: 17913.76
D41: 0.2 | E41: =-E40*D41 -> -3582.752
E42: =+E40+E41 -> 14331.008
D43: MTGE | E43: -6500
E44: =+E42+E43 -> 7831.008
D45: roof | E45: =-250*25 -> -6250
D46: Paint | E46: =+E44+E45 -> 1581.008
D47: Deductible | E47: -1000
D48: Misc. | E48: =+E46+E47 -> 581.008
D50: Check | E50: 9000
D51: Mitigation | E51: -6625.18
E52: =+E50+E51 -> 2374.82
D53: Fees 20% | E53: =+E41 -> -3582.752
D54: Bal Due | E54: 1656.2
D56: Customer Loans | E56: 530
E57: 100
E58: 100
E59: 60
E60: 40
D61: Total Due | E61: =SUM(E54:E60) -> 2486.2
A68: William Hopkins
A69: 1529 Wilmar Ave.
A70: Cleveland Heights, OH 44118
A72: Dear Mr. William Jones and or Fowlkes Remodeling:
A73: Please be advised that your services are no longer needed. You are fired.
A74: Your threats and attempts and intimidation against me are taken as a highly disrespectful personal attack.
A76: Your poor performance has caused me numerous problems not limited to emotional stress, investigation and embarrassment with my longtime insurer, personal discomfort with my family and living arrangments, financial issues.
A78: Your failed promises and delays have disrupted my peaceful enjoyment of my home.
A79: Your highly unprofessional tactics are an insult upon the integrity and character of your trade.
A80: I have been an electrical contractor for many years and have seen the likes of you before. Not good !!
A81: Any further contact by you , other than a complete apology and retraction of your threatened actions (within 3 days of receipt of this notice) may result in the following:
A82: Arrest for trespassing
... A107: Please be advised that I hereby give my full consent for
A108: =+current!#REF! -> #REF! | B108: to cash / negotiate the attached check in the
A109: Amount of : | B109: 25245.31 | C109: 43242
A110: CK # 104944 | B110: =+#REF! -> #REF! | C110: =+#REF! -> #REF!
A111: Payor | B111: =+#REF! -> #REF!
A113: It is fully understood that this permission is based upon the construction contract
A114: that we have executed.
A116: We agree and are bound to hold harmless any patties that handle this current matter in
A117: conjunction with
A119: Under penalty of perjury I do Attest to the herein statements of fact.
A120: I affix my legal signature of my own free will.
A121: X______________________________ _______________________________ | C121: ______/_______/2018
A122: =+cst.Hamilton__Nakeysha -> #REF!
A124: Affix copy of Driver's License
B125: OR
A127: AFFIDAVIT AND CERTIFICATION OF Signature
A128: Sworn to before me and subscribed in my presence on this ____ day of __ _________, 20___.
A129: X______________________________ _______________________________
C130: ______/_______/2018
A131: =+A122 -> #REF! | C131: Signature of Co- Owner Date
A132: State of: ____________ County/Parish of: ______________________
A133: Notary Signature: ______________________________________________
A134: My Commission Expires: ______/_______ / 20_______ Notary Seal:
A136: =+#REF! -> #REF!
A137: =+#REF! -> #REF!
A138: =+#REF! -> #REF!
A139: =+#REF! -> #REF!
A140: =+#REF! -> #REF!
A141: =+#REF! -> #REF!
A142: =+#REF! -> #REF!
A143: =+#REF! -> #REF! | B143: =+#REF! -> #REF!
A144: =+#REF! -> #REF! | B144: =+#REF! -> #REF!
A145: =+#REF! -> #REF! | B145: =+#REF! -> #REF!
A146: =+#REF! -> #REF! | B146: =+#REF! -> #REF!
A147: =+#REF! -> #REF! | B147: =+#REF! -> #REF!
A148: =+#REF! -> #REF! | B148: =+#REF! -> #REF!
...

Sheet jobinfo(2)
A1: Customer | B1: Property-Owner Name
B2: Property address: street
B3: Property city, state, zip
B4: Customer Email
B5: Cst-owner Phone#
B6: Co-Owner.cst#2
B7: cst ph # 2
B8: Cst address # 2
B9: city, state-cst#2
B10: email-cst #2
A11: Loss Info | B11: Cause of Loss
B12: date of loss
B13: rebuild type 1
B14: rebuild type 2
B15: rebuild type 3
B16: DEMO
B17: Mitigation
B18: Other Structures
A19: CPS | B19: Replacement
B20: CPS / CLN / CON/ CGN
B21: Year Built
B22: Contract Date
B23: Loss of use/ ALE
B24: Breathing issue
B25: HMR
B26: Insurance Co. Name
A27: Insurance Co. | B27: Claim #
B28: policy #
B29: Email INS. co.
B30: DESK Adjuster DA
B31: DA Phone
B32: DA Ph. Ext. #
B33: DA Email
B34: Field Adjuster Name
B35: Phone # field adj
B36: Field adj email
B37: adj contents
B38: adj CPS phone #
B39: adj CPS email
... B52: ROOM ID
A53: 1 | B53: Room/Area 1
A54: =1+A53 -> 2 | B54: Room/Area 2
A55: =1+A54 -> 3 | B55: Room/Area 3
A56: =1+A55 -> 4 | B56: Room/Area 4
A57: =1+A56 -> 5 | B57: Room/Area 5
A58: =1+A57 -> 6 | B58: Room/Area 6
A59: =1+A58 -> 7 | B59: Room/Area 7
A60: =1+A59 -> 8 | B60: Room/Area 8
A61: =1+A60 -> 9 | B61: Room/Area 9
A62: =1+A61 -> 10 | B62: Room/Area 10
A63: =1+A62 -> 11 | B63: Room/Area 11
A64: =1+A63 -> 12 | B64: Room/Area 12
A65: =1+A64 -> 13 | B65: Room/Area 13
... A77: =1+A76 -> 25 | B77: Room/Area 25
A78: Mortgage Company | B78: Mortgage co
B79: Account# Mtge Co.
B80: Loan status
B81: contact person mtge
B82: Phone # MTGE contact
B83: Ph. Ext. Mtge contact
B85: Attn.: Loss Draft Dept
B86: Mtge OVN mail
B87: city, St., zip ,mtge OVN
B88: Phone # MTGE co.
B89: email mtge
B90: mtge website
B91: MTGE co. Fax #
... B97: Cust id
A100: CONTRACTOR INFO | B100: co name
B101: Co. website
B102: co. EMAIL/co. status
B103: co adress
B104: co. city state
B105: co. address 2
B106: co. city state 2
B107: co adress 3
B108: co. city state 3
B109: Co. logo 1
B110: Co. logo 2
B111: Co. logo 3
B112: Co. REP. / PH
... B133: tenant lesee
B134: =+B2 -> Property address: street
B135: =+B3 -> Property city, state, zip
B136: =+B4 -> Customer Email
B137: =+B5 -> Cst-owner Phone#
B138: =+B11 -> Cause of Loss
B139: =+B12 -> date of loss
B140: =+B22 -> Contract Date
B141: =+B26 -> Insurance Co. Name
B142: =+B27 -> Claim #
B143: =+B28 -> policy #
B144: =+B29 -> Email INS. co.
B145: =+B30 -> DESK Adjuster DA
B146: =+B31 -> DA Phone
B147: =+B32 -> DA Ph. Ext. #
B148: =+B33 -> DA Email
B149: Tenant shall pay
B150: POSSESSION OF PREMISES
B151: start date of this Agreement is
...
