Workbook
Name a...new_customer: #REF!
Name a...new_customer: #REF!
Name a...new_customer: #REF!
Name basicroompichow2: #REF!
Name box_names: +#REF!
Name Column.a.new.cst: #REF!
Name culpepper: #REF!
Name data: #REF!
Name Document_Stacking_List: #REF!
Name Enter_new_cst_data: #REF!
Name Jefferies: #REF!
Name LOVEJOY_INTERIOR: #REF!
Name Lovejoy_ROOF: #REF!
Name LxWxH: #REF!
Name new_customer: #REF!
Name PRICE_P: #REF!
Name Robinson: #REF!
Name sigtj: "Picture 9859"
Name SubContractor_Summary: #REF!
Name Wayside_Builders__LLC_…...OH: #REF!
Name WSB...GA.Wayside_Builders__LLC……GA: #REF!

Sheet quick chklst
A1: BASIC SUMMARY OF RESTORATION PROCESS; (Quick version). | D1: =+'jobinfo(2)'!C2 -> 6600 GERTRUDE
A2: JOB | C2: =+'jobinfo(2)'!C51 -> OH25THOMAS@GERTRUDE | D2: =+'jobinfo(2)'!C3 -> Cleveland, OH 44105
A3: 1 | B3: Introduction, Analysis & Verification | C3: Introduction, Analysis & Verification /source/referred by: | D3: Status Notes / %
C4: Who is the Insurance Company ?!? | D4: ='jobinfo(2)'!C26 -> ALLSTATE INS CO. | G4: 100
A5: POI | C5: Does customer Comprehend Our Role in the process? | D5: Y
C6: Is this a COVERED INSURANCE Claim? Or Self Pay ? | D6: Y
C7: IS THE DAMAGE $ MORE THAN THE DEDUCTIBLE? | D7: Y
C8: Do they have coverage; for AOB? = POLICY & DEC PAGE | D8: Y | G8: 200
A9: 2 | B9: Contracts & Documentation | C9: Contracts & Documentation | D9: Y
C10: Has Customer been fully advised of Contract Contents? | D10: Y
C11: Has Customer had a full Consultation to Our Terms & Conditions? | D11: Y | G11: 500
A12: DOC | C12: Does Customer FULLY Agree to Terms &Conditions? Signed / Initials? | D12: Y
C13: Notary Page explained/ Fast track | D13: Y
A14: mou | C14: Company investment (dollars, time ,materials)into their Project? | D14: Y
C15: Mutual trust , cooperation & confidence | D15: Y
A16: 3 | C16: CLAIM REPORTING;DOES THE CUSTOMER HAVE REQUIRED INFO? | D16: Y
A17: INS | C17: Insurer Mitigation / DMO / CPS Approval Info Sheet | D17: Y | G17: 100
A18: PICS | C18: Create ENCIRCLE project (Pictures critical part of PAYMENTprocess! | D18: Y
A19: mit | B19: Mitigation & Demolition | C19: Mitigation & Demolition (ROOM LABELS POSTED)
A20: 4 | C20: Roof & EXT Mitigation TEMPORARY & EMERGENCY REPAIRS | D20: Y | G20: 1000
A21: 5 | C21: Contents_ item list_; storage details; security explained? | D21: Y | G21: 2000
A22: 6 | C22: Interior Mitigation; household disruption explained? | D22: NA | G22: 2000
C23: HMR / Secondary Damages; Equipment & Electricity $ | D23: NA
A24: esx | B24: Estimates | C24: Estimates (Inspection/Scope Form)
C25: SKETCH/DRAWING;[1] sheet per floor
A26: 7 | C26: Interior & EXTERIOR REBUILD | G26: 200
C27: EXTERIOR MITIGATION | D27: Y
C28: INTERIOR Mitigation & Demolition | D28: NA
A29: 8 | B29: Insurance Company Meetings | C29: Insurance Company Meetings
A30: adj | C30: Docs for adjuster meeting; Print & bind docs BE PRESENT WHEN ADJUSTER VISITS The PROPERTY. | G30: 500
A31: 9 | B31: Cashflow General Contractor / Subcontracts | C31: Cashflow General Contractor / Subcontracts
A32: job | C32: Contents
A33: 10 | B33: Mitigation & Demolition | C33: & EXterior Mitigation & Demolition
B34: Interior Mitigation & Demolition | C34: Closeout Interior Mitigation & Demolition
C35: Rebuild
G36: =SUM(G1:G35) -> 6600
C37: BASIC SUMMARY OF RESTORATION PROCESS; (Quick version). | D37: =+'jobinfo(2)'!$C$2 -> 6600 GERTRUDE
A38: JOB | C38: =+'jobinfo(2)'!C51 -> OH25THOMAS@GERTRUDE | D38: =+'jobinfo(2)'!$C$3 -> Cleveland, OH 44105
A39: 1 | B39: Introduction, Analysis & Verification | C39: Introduction, Analysis & Verification /source/referred by: | D39: ='jobinfo(2)'!$C$27 -> CLM
C40: Who is the Insurance Company ?!? | D40: ='jobinfo(2)'!$C$26 -> ALLSTATE INS CO.
A41: POI | C41: Does customer Comprehend DEDUCTABLE PAYMENT? PAID____
C42: Do they have coverage; for AOB? = POLICY & DEC PAGE
A43: 2 | B43: Contracts & Documentation | C43: Contracts & Documentation
A44: Customer full Consultation to Our Terms & Conditions? Comprehend Our Role in process?
C45: CONTRACT SIGNED / Notary Page explained/ Fast track
A46: mou | C46: Mutual trust/cooperation & confidence/Company investment dollars, time ,materials?
A47: 3 | C47: CLAIM REPORTING;DOES THE CUSTOMER HAVE REQUIRED INFO?
A48: INS | C48: Insurer Mitigation / DMO / CPS Approval Info Sheet
A49: EGV | C49: Order REPORT ; Eagleview Roof/ Siding / PLUMBERS / FIRE / POLICE
A50: PICS | C50: Create ENCIRCLE project; ENTER NEW CUSTOMER INFO; SHARE 2 TEAM
C51: Create ENCIRCLE FLOOR PLAN & VERIFY COMPLETE
A52: EXCEL | C52: CREATE EXCEL FILE; Copy & Paste DATA from Encircle
C53: RUN EXCEL MACRO & VERIFY
A55: mit | B55: Mitigation & Demolition | C55: Mitigation & Demolition (ROOM LABELS POSTED)
A56: CREATE & SEND; MIT EQUIPMENT SETUP / CPS / ROOMS SCOPE FORM /
A57: 4 | C57: Roof & EXT Mitigation TEMPORARY & EMERGENCY REPAIRS
A58: 5 | C58: Contents_ item list_; storage details; security explained?
A59: 6 | C59: Interior Mitigation; household disruption explained?
C60: HMR / Secondary Damages; Equipment & Electricity $
A61: esx | B61: Estimates | C61: CREATE XACTIMATE PROJECT; Copy & Paste DATA from Encircle
C62: GET Inspection/Scope Form [ ENCIRCLE or Genius Scan]
A63: IMPORT The ENCIRCLE FLOOR PLAN to XACTIMATE/ CREATE PROJECT SKETCH
C64: EXTERIOR MITIGATION
A65: 7 | C65: INTERIOR Mitigation & Demolition
C66: Interior & EXTERIOR REBUILD
C67: Contents
A68: 8 | B68: Insurance Company Meetings | C68: Insurance Company Meetings ENCIRCLE FLOOR PLAN & SCOPE SHEET
A69: adj | C69: Adjuster meeting DOCS; Print & bind docs / PRESENT FOR ADJUSTER VISITS
C70: ENCIRLE / EXCEL / XACTIMATE REPORTS: …Retrieve/DOWNLOAD REPORTS; (Create as needed)
C71: MIT …. Ext & INT …...CPS….... REPL = CON …..... REBUILD
C72: EMAIL Estimates & REPORTS to Insurer.
A73: 9 | B73: Cashflow General Contractor / Subcontracts | C73: Cashflow General Contractor / Subcontracts
C74: Followup & Collect Payments
A75: job | C75: Contents
A76: 10 | B76: Mitigation & Demolition | C76: & EXterior Mitigation & Demolition
B77: Interior Mitigation & Demolition | C77: Closeout Interior Mitigation & Demolition
C78: Interior & EXTERIOR REBUILD
A79: BASIC JOB WORKFLOW | D79: ='jobinfo(2)'!$C$51 -> OH25THOMAS@GERTRUDE
A80: Has Customer had a full Consultation to WORK PROCESS | D80: ='jobinfo(2)'!$C$1 -> THOMAS, ANITA
A81: explain | C81: CPS; storage details; security explained? | D81: ='jobinfo(2)'!$C$2 -> 6600 GERTRUDE
C82: INT MIT DMO household disruption?
C83: MIT EQUIPMENT RUNNING (3 DAYS); ELECTRIC BILL REIMBURSEMENT | D83: ='jobinfo(2)'!$C$4 -> A@EM
D84: ='jobinfo(2)'!$C$5 -> (216) 315-2040
C86: Create ENCIRCLE project (Pictures critical part of PAYMENTprocess!)
A87: CREW TO …...... JOB | C87: Create & Post room Labels (Traffic Area = foot coverings) | D87: ='jobinfo(2)'!$C$27 -> CLM
C88: Verify & Add Rooms to Encircle; as needed; Verify | D88: ='jobinfo(2)'!$C$11 -> Water Damage=WTR
C89: Take Room Overview Pics = …. Job Scope FORM | D89: ='jobinfo(2)'!$C$12 -> Friday, September 12, 2025
C90: Inspection/Scope Form [Send to ENCIRCLE or via Genius scan] | D90: ='jobinfo(2)'!$C$13 -> interior repairs LVL1
C91: Take CPS # 1 Pics contents Overview Pics ... (CPS#2, Cps#3, CPS#4) | D91: ='jobinfo(2)'!$C$14 -> interior repairs LVL2
C92: Scan/Create Floor Plan / Submit to Encircle; / Print Copy for Adjuster | D92: ='jobinfo(2)'!$C$15 -> interior repairs LVL13
C94: MITIGATION CHECKLIST/WORK FLOW
C95: Set Up Basic Equipment….... / ....... Protect Contents, Floors, & Walls
C97: Roof & EXT / Interior Mitigation TEMPORARY & EMERGENCY REPAIRS
C98: INTERIOR Mitigation & Demolition; household disruption explained?
C99: Interior & EXTERIOR REBUILD Estimates (Inspection/Scope Forms)
C100: Contents_ item list_; storage details; security explained?
C102: CREATE EXCEL FILE; Copy & Paste DATA from Encircle
C103: Run Excel Macro; create Templates & Subfolders
C104: Enter Room Sizes (from Encircle Floor Plan) & Damage Percentages %: @ jobinfo2
C105: Calculate MIT Equipment (MITEqpmnt ALL) & Deliver To Jobsite/Set Up Equipment
...

Sheet OFS INITIAL CKLST
B1: OFFICE QUICKLIST | D1: ='jobinfo(2)'!C1 -> THOMAS, ANITA
A2: INITIAL DOCS IN ( to start claim)
A3: 1 | B3: VERIFY / ASSESS DAMAGE; Full Consultation to Our Terms/Conditions? MOU Our Role in process? | C3: REQUEST IN & OUT | E3: 201
A4: 2 | B4: POLICY & DEC PAGE = ACV or Replacement Do they have coverage; | C4: REQUEST IN | D4: ='jobinfo(2)'!C2 -> 6600 GERTRUDE | E4: =E3+1 -> 202
A5: 3 | B5: Does customer Comprehend AOB? DEDUCTABLE PAYMENT? PAID____ | C5: REQUEST IN | E5: =E4+1 -> 203
A6: 4 | B6: Create ENCIRCLE project; CONTRACT SIGNED / Notary Page explained = Fast track ….AOB? | C6: REQUEST SENT & IN | E6: =E5+1 -> 204
A7: 5 | B7: JOBSITE VERIFICATION PICS & ROOMS VIDEO …..& SHORT ROOM LIST... (upon initial visit) | C7: CREATE | D7: ='jobinfo(2)'!B5 -> Cst-owner Phone# | E7: =E6+1 -> 205
A8: INITIAL DOCS OUT TO CUSTOMER ( to start claim) | D8: ='jobinfo(2)'!C5 -> (216) 315-2040 | E8: =E7+1 -> 206
A9: 6 | B9: CLAIM REPORTING Info Sheet;Insurer Approval [Mitigation/DMO/CPS] DOCUMENT CONTACT | C9: REQUEST SENT & IN | E9: =E8+1 -> 207
A10: 7 | B10: MOU SENT OUT TO CUSTOMER | C10: REQUEST SENT & IN | D10: ='jobinfo(2)'!C4 -> A@EM | E10: =E9+1 -> 208
A11: INITIAL REPORTS/DOCS GENERATED ( to start claim) | E11: =E10+1 -> 209
A12: 8 | B12: Order REPORT ..; Eagleview Roof / …. Siding / ….. PLUMBERS / …. FIRE / …..POLICE | C12: CREATE | E12: =E11+1 -> 210
B13: LEAD HMR TESTING
A14: 9 | B14: ENCIRCLE FLOOR PLAN …................... CREATED @ JOBSITE | C14: CREATE | E14: =E12+1 -> 211
A15: 10 | B15: Create ENCIRCLE Project; ROOM LISTS….. SHARE 2 TEAM Option ( V2 then Merge) | C15: CREATE | E15: =E14+1 -> 212
B16: SELECT JOB TYPE per STOCK ROOM LISTS; = WTR / FIRE or RFG & WTR | C16: CREATE | D16: ='jobinfo(2)'!C26 -> ALLSTATE INS CO. | E16: =E15+1 -> 213
B17: Determine / Input job Room names per jobsite visit ROOM ORDER SET-UP | C17: CREATE | E17: =E16+1 -> 214
B18: GENERATE ROOM LABELS & CPS BOX LABELS ; EMAIL OUT | C18: CREATE | E18: =E17+1 -> 215
B19: 100 ROOMS Overview / 360 = Scope Form | C19: CREATE | E19: =E18+1 -> 216
B20: 400 SOURCE OF LOSS 500 CPS DAY 1 / 2 / 3 / 4 | C20: CREATE | E20: =E19+1 -> 217
B21: 800 MIT W.I.P. & EQPT Mitigation LABELS (Demolition) | C21: CREATE | E21: =E20+1 -> 218
B22: READINGS DAY 1 / 2 / 3 / 4 … 6000 MC & 7000 RHT+GPP | C22: CREATE | E22: =E21+1 -> 219
A23: 12 | B23: IMPORT & EDIT The ENCIRCLE FLOOR PLAN (PRINT AS NEEDED) | C23: IN | E23: =E22+1 -> 220
A24: 13 | B24: (UPDATE AS NEEDED) CREATE ROOM Names LISTS in ENCIRCLE & EXCEL | E24: =E23+1 -> 221
A25: 14 | B25: RUN EXCEL MACRO & VERIFY TEMPLATES | C25: CREATE | D25: ='jobinfo(2)'!C27 -> CLM | E25: =E24+1 -> 222
A26: AUTOMATE THE FOLLOWING | E26: =E25+1 -> 223
A27: GENERATE LABELS = ROOMS / CPS BOXES / MITIGATION EQUIPTMENT PLACEMENT; …. | C27: EMAIL OUT | E27: =E26+1 -> 224
A28: 16 | B28: RUN EXCEL MACRO 4 MITIGATION WORK & EQUIPMENT | C28: CREATE | E28: =E27+1 -> 225
A29: 17 | B29: CREATE & SEND; ROOMS SCOPE FORM (FUTURE = 360 CAMERA) | C29: EMAIL OUT
A30: 19 | B30: Mitigation LABELS (Demolition) | C30: EMAIL OUT
A31: 20 | B31: Enter Room Sizes (from Encircle Floor Plan) & Damage Percentages %: @ jobinfo2 | C31: CREATE
A32: 21 | B32: Calculate MIT Equipment (MIT Eqpmnt ALL) & Deliver To Jobsite/Set Up Equipment | C32: EMAIL OUT
B33: CREATE & SEND; MIT EQUIPMENT SETUP WORK & EQUIPMENT FORM | C33: EMAIL OUT
A34: 22 | B34: Calculate/Estimate CPS Supplies | C34: EMAIL OUT
A35: 23 | B35: Order & Deliver to Jobsite…..... Packout Supplies = boxes / tape / shrink wrap | C35: EMAIL OUT
A36: 24 | B36: GET Inspection/Scope Form [ ENCIRCLE or Genius Scan] sent from app | C36: REQUEST IN
A37: 25 | B37: CREATE XACTIMATE PROJECT; (Copy & Paste DATA from Encircle)
B38: Estimates
A40: 26
A41: 27
A42: 28
A43: 29
A44: 30
A45: 31
I46: JOBSITE FLOW SHEET
I47: ACCESS or Create ENCIRCLE project; SHARE 2 TEAM
I48: Create ENCIRCLE FLOOR PLAN & VERIFY COMPLETE
I49: ='quick chklst'!C54 -> 0
I50: BASIC SUMMARY OF RESTORATION PROCESS; (Quick version). | J50: =+'jobinfo(2)'!$C$2 -> 6600 GERTRUDE
G51: JOB | I51: =+'jobinfo(2)'!C138 -> end date | J51: =+'jobinfo(2)'!$C$3 -> Cleveland, OH 44105
G52: PICS | I52: Create ENCIRCLE project; ENTER NEW CUSTOMER INFO; SHARE 2 TEAM
I53: Create ENCIRCLE FLOOR PLAN & VERIFY COMPLETE
G54: CREATE & SEND; MIT EQUIPMENT SETUP / CPS / ROOMS SCOPE FORM /
G55: mit | H55: Mitigation & Demolition | I55: Mitigation & Demolition (ROOM LABELS POSTED)
G56: 4 | I56: Roof & EXT Mitigation TEMPORARY & EMERGENCY REPAIRS
G57: 5 | I57: Contents_ item list_; storage details; security explained?
G58: 6 | I58: Interior Mitigation; household disruption explained?
I59: HMR / Secondary Damages; Equipment & Electricity $
I60: GET Inspection/Scope Form [ ENCIRCLE or Genius Scan]
I61: EXTERIOR MITIGATION
G62: 7 | I62: INTERIOR Mitigation & Demolition
I63: Interior & EXTERIOR REBUILD
I64: Contents
G65: 8 | H65: Insurance Company Meetings | I65: Insurance Company Meetings ENCIRCLE FLOOR PLAN & SCOPE SHEET
G66: adj | I66: Adjuster meeting DOCS; Print & bind docs / PRESENT FOR ADJUSTER VISITS
I67: MIT …. Ext & INT …...CPS….... REPL = CON …..... REBUILD
G68: job | I68: Contents
G69: 10 | H69: Mitigation & Demolition | I69: & EXterior Mitigation & Demolition
H70: Interior Mitigation & Demolition | I70: Closeout Interior Mitigation & Demolition
I71: Interior & EXTERIOR REBUILD
G72: BASIC JOB WORKFLOW | J72: ='jobinfo(2)'!$C$51 -> OH25THOMAS@GERTRUDE
G73: Has Customer had a full Consultation to WORK PROCESS | J73: ='jobinfo(2)'!$C$1 -> THOMAS, ANITA
G74: explain | I74: CPS; storage details; security explained? | J74: ='jobinfo(2)'!$C$2 -> 6600 GERTRUDE
I75: INT MIT DMO household disruption?
I76: MIT EQUIPMENT RUNNING (3 DAYS); ELECTRIC BILL REIMBURSEMENT | J76: ='jobinfo(2)'!$C$4 -> A@EM
J77: ='jobinfo(2)'!$C$5 -> (216) 315-2040
I78: Create ENCIRCLE project (Pictures critical part of PAYMENTprocess!)
G79: CREW TO …...... JOB | I79: Create & Post room Labels (Traffic Area = foot coverings) | J79: ='jobinfo(2)'!$C$27 -> CLM
I80: Verify & Add Rooms to Encircle; as needed; Verify | J80: ='jobinfo(2)'!$C$11 -> Water Damage=WTR
I81: Take Room Overview Pics = …. Job Scope FORM | J81: ='jobinfo(2)'!$C$12 -> Friday, September 12, 2025
I82: Inspection/Scope Form [Send to ENCIRCLE or via Genius scan] | J82: ='jobinfo(2)'!$C$13 -> interior repairs LVL1
I83: Take CPS # 1 Pics contents Overview Pics ... (CPS#2, Cps#3, CPS#4) | J83: ='jobinfo(2)'!$C$14 -> interior repairs LVL2
I84: Scan/Create Floor Plan / Submit to Encircle; / Print Copy for Adjuster | J84: ='jobinfo(2)'!$C$15 -> interior repairs LVL13
I85: MITIGATION CHECKLIST/WORK FLOW
I86: Set Up Basic Equipment….... / ....... Protect Contents, Floors, & Walls
I87: Roof & EXT / Interior Mitigation TEMPORARY & EMERGENCY REPAIRS
I89: INTERIOR Mitigation & Demolition; household disruption explained?
I90: Interior & EXTERIOR REBUILD Estimates (Inspection/Scope Forms)
I91: Contents_ item list_; storage details; security explained?
I93: Enter Room Sizes (from Encircle Floor Plan) & Damage Percentages %: @ jobinfo2
I94: Calculate MIT Equipment (MITEqpmnt ALL) & Deliver To Jobsite/Set Up Equipment
I95: Calculate CPS Supplies & Deliver to Jobsite…..... Packout Contents; boxes/tape/wrap
I97: ENCIRLE / EXCEL / XACTIMATE REPORTS: …Retrieve/DOWNLOAD REPORTS; (Create as needed)
G98: Email # 1 1 & 2 . CONTRACT . 3. W9 .4. JOB VERIFICATION /SOURCE OF LOSS
G99: 5. MIT.. CPS .. REBUILD ,,, REPLACE ITEMS 6. XACT INVOICE & ESX
G100: Email # 2 … 7..ROOMS Overview …./.. 8. MIT CPS REBUILD REPLACE /… 9. TMPL30 /…10 OTHER

Sheet jobinfo(2)
A1: Customer | B1: Property-Owner Name | C1: THOMAS, ANITA | M1: Enter info here | Q1: ADD SOS LINK
B2: Property address: street | C2: 6600 GERTRUDE | M2: New Customer Info required | N2: NEEDS TO SELF POPULATE | Q2: LINK TO VIDEOS
B3: Property city, state, zip | C3: Cleveland, OH 44105 | Q3: BEFORE AND AFTER P[CS
B4: Customer Email | C4: A@EM | Q4: CLE ATL NY NC NY
B5: Cst-owner Phone# | C5: (216) 315-2040
B6: Co-Owner.cst#2
B7: cst ph # 2 | Q7: RFG WIP…CURRENT JOBS
B8: Cst address # 2 | Q8: SIGNAGE
B9: city, state-cst#2
B10: email-cst #2
A11: Loss Info | B11: Cause of Loss | C11: Water Damage=WTR | M11: Wind = Roof | N11: Water Damage=WTR | O11: Fire Smoke | P11: Wind=Tree | Q11: Hurricane =HURR
B12: date of loss | C12: Friday, September 12, 2025 | M12: rebuild type
B13: rebuild type 1 | C13: interior repairs LVL1 | M13: roofing shingles replacement | O13: fencing
B14: rebuild type 2 | C14: interior repairs LVL2 | M14: interior repairs | O14: shed
B15: rebuild type 3 | C15: interior repairs LVL13 | M15: exterior repairs | O15: porch patio
B16: DEMO | C16: Y | M16: Y
B17: Mitigation | C17: Y | M17: Y
B18: Other Structures | C18: NA | M18: Y
A19: CPS | B19: Replacement | C19: Y | M19: Y
B20: CPS / CLN / CON/ CGN | C20: Y | M20: Y
B21: Year Built | C21: 1920 | M21: TBD
B22: Contract Date | C22: 45836 | M22: TBD | N22: pre 1980 | O22: post 1980
B23: Loss of use/ ALE | C23: TBD | M23: sample cost 3
B24: Breathing issue | C24: TBD | M24: doctor letter
B25: HMR | C25: TBD | M25: lab test
B26: Insurance Co. Name | C26: ALLSTATE INS CO. | M26: Insurance Company Supplied Info | N26: Per declaration pages | P26: 34-H-6822C9-2
A27: Insurance Co. | B27: Claim # | C27: CLM | N27: Assigned by Insurer
B28: policy # | C28: 880 022 226 | N28: Per declaration pages | O28: OFP DWF 7266580
B29: Email INS. co. | N29: Per declaration pages
B30: DESK Adjuster DA | N30: Assigned by Insurer
B31: DA Phone | N31: customer service rep
B32: DA Ph. Ext. # | N32: Hazel
B33: DA Email | N33: 43789
B34: Field Adjuster Name | N34: 5pm
B35: Phone # field adj
B36: Field adj email
B37: adj contents | N37: Assigned by Insurer
B38: adj CPS phone #
B39: adj CPS email
B40: TMP adj | N40: Assigned by Insurer
B41: TMP adj phone #
B42: adj TMP email
B43: ATT: Loss Draft Dept. | N43: =+N26 -> Per declaration pages
B44: address ins overnight mail
B45: city, state-zip ins
B46: Insurance Co. Phone
B47: Website Ins Co.
B48: Mailing address INS
B49: Mail city, state, zip INS | N49: Leave Label/ID tag in place for each room/area until final completion !!!
B50: FAX Ins. Co
B51: NEW CUSTOMER # | C51: OH25THOMAS@GERTRUDE
B52: ROOM ID | C52: THOMAS, ANITA | D52: Scope | E52: Pics | F52: SOURCE of LOSS | G52: CPS #5 | H52: DMO | I52: HMR | J52: MITIGATION | M52: Floor 1 | N52: Floor 2 | O52: BASEMENT | P52: Affected Areas, Include Line of Sight room /areas
A53: 1 | B53: Room/Area 101 | C53: Living Room, | F53: 401 | G53: 501 | H53: 601 | I53: 701 | J53: 901 | M53: Foyer | N53: Stairs UP | O53: Basement | P53: ROOM Name & Number | Q53: LOCATION & Basic damage / work Description
A54: 2 | B54: Room/Area 102 | C54: GUEST CLOSET | F54: =F53+1 -> 402 | G54: =G53+1 -> 502 | H54: =H53+1 -> 602 | I54: =I53+1 -> 702 | J54: =J53+1 -> 902 | M54: Guest Closet | N54: Bathroom | O54: Stairs 1 | P54: example # 0 = Master bedroom | Q54: Ceilings N corner | R54: repair water damage drywall paint
A55: 3 | B55: Room/Area 103 | C55: Dining Room, | F55: =F54+1 -> 403 | G55: =G54+1 -> 503 | H55: =H54+1 -> 603 | I55: =I54+1 -> 703 | J55: =J54+1 -> 903 | M55: Front Hall | N55: Hallway- up | O55: Storage | R55: Scope | S55: Pics | T55: Sketch
A56: 4 | B56: Room/Area 104 | C56: DEN | F56: =F55+1 -> 404 | G56: =G55+1 -> 504 | H56: =H55+1 -> 604 | I56: =I55+1 -> 704 | J56: =J55+1 -> 904 | M56: Living Room | N56: Linen CLST | O56: Hallway- DN | P56: {#=_1_} | Q56: {____} | S56: {_______} {_ _____}
A57: 5 | B57: Room/Area 105 | C57: Kitchen, | F57: =F56+1 -> 405 | G57: =G56+1 -> 505 | H57: =H56+1 -> 605 | I57: =I56+1 -> 705 | J57: =J56+1 -> 905 | M57: Dining Room | N57: Bedroom # 1 | O57: Laundry | P57: Room/Area 1
A58: 6 | B58: Room/Area 106 | C58: STAIRS UP | F58: =F57+1 -> 406 | G58: =G57+1 -> 506 | H58: =H57+1 -> 606 | I58: =I57+1 -> 706 | J58: =J57+1 -> 906 | M58: Hallway- DN | N58: Closet BR # 1 | O58: Utility
A59: 7 | B59: Room/Area 107 | C59: HALL UP | F59: =F58+1 -> 407 | G59: =G58+1 -> 507 | H59: =H58+1 -> 607 | I59: =I58+1 -> 707 | J59: =J58+1 -> 907 | M59: DEN | N59: Bedroom # 2 | O59: Man cave
A60: 8 | B60: Room/Area 8 | C60: LINEN CLOSET | F60: =F59+1 -> 408 | G60: =G59+1 -> 508 | H60: =H59+1 -> 608 | I60: =I59+1 -> 708 | J60: =J59+1 -> 908 | M60: FAMILY ROOM | N60: Closet BR # 2 | O60: Crawlspace
A61: 9 | B61: Room/Area 9 | C61: BATH UP | F61: =F60+1 -> 409 | G61: =G60+1 -> 509 | H61: =H60+1 -> 609 | I61: =I60+1 -> 709 | J61: =J60+1 -> 909 | M61: Kitchen | N61: Bedroom # 3 | O61: EXTERIOR | Q61: Jobsite Verification (Address Photos)
A62: 10 | B62: Room/Area 10 | C62: Bedroom 1, | F62: =F61+1 -> 410 | G62: =G61+1 -> 510 | H62: =H61+1 -> 610 | I62: =I61+1 -> 710 | J62: =J61+1 -> 910 | M62: Pantry | N62: Closet BR # 3 | O62: Roof shingle replace | Q62: Source of Loss Pics
A63: 11 | B63: Room/Area 11 | C63: BR1 Closet | F63: =F62+1 -> 411 | G63: =G62+1 -> 511 | H63: =H62+1 -> 611 | I63: =I62+1 -> 711 | J63: =J62+1 -> 911 | M63: Nook | N63: Master Bedroom | O63: Vinyl siding | Q63: FOYER/ENTRY ROOM
A64: 12 | B64: Room/Area 12 | C64: Bedroom 2 | F64: =F63+1 -> 412 | G64: =G63+1 -> 512 | H64: =H63+1 -> 612 | I64: =I63+1 -> 712 | J64: =J63+1 -> 912 | M64: Guest Bath | N64: Master BR Closet | O64: fencing
A65: 13 | B65: Room/Area 13 | C65: BR2 Closet | F65: =F64+1 -> 413 | G65: =G64+1 -> 513 | H65: =H64+1 -> 613 | I65: =I64+1 -> 713 | J65: =J64+1 -> 913 | M65: Office | N65: Master Bathroom | O65: shed
A66: 14 | B66: Room/Area 14 | C66: STAIRS TO BASEMENT | F66: =F65+1 -> 414 | G66: =G65+1 -> 514 | H66: =H65+1 -> 614 | I66: =I65+1 -> 714 | J66: =J65+1 -> 914 | M66: SUNROOM | O66: exterior repairs
A67: 15 | B67: Room/Area 15 | C67: LAUNDRY/UTILITY ROOM | F67: =F66+1 -> 415 | G67: =G66+1 -> 515 | H67: =H66+1 -> 615 | I67: =I66+1 -> 715 | J67: =J66+1 -> 915 | M67: ATTIC | O67: Porches
A68: 16 | B68: Room/Area 16 | C68: STORAGE UNDER STAIRS | F68: =F67+1 -> 416 | G68: =G67+1 -> 516 | H68: =H67+1 -> 616 | I68: =I67+1 -> 716 | J68: =J67+1 -> 916 | M68: Storage | O68: Garage
A69: 17 | B69: Room/Area 17 | C69: STORAGE ROOM # 1 | F69: =F68+1 -> 417 | G69: =G68+1 -> 517 | H69: =H68+1 -> 617 | I69: =I68+1 -> 717 | J69: =J68+1 -> 917 | M69: Stairs 2 | O69: Deck/patio
A70: 18 | B70: Room/Area 18 | C70: STORAGE ROOM # 2 | F70: =F69+1 -> 418 | G70: =G69+1 -> 518 | H70: =H69+1 -> 618 | I70: =I69+1 -> 718 | J70: =J69+1 -> 918 | O70: yard area
A71: 19 | B71: Room/Area 19 | C71: STORAGE ROOM # 3 | F71: =F70+1 -> 419 | G71: =G70+1 -> 519 | H71: =H70+1 -> 619 | I71: =I70+1 -> 719 | J71: =J70+1 -> 919 | O71: Windows
A72: 20 | B72: Room/Area 20 | F72: =F71+1 -> 420 | G72: =G71+1 -> 520 | H72: =H71+1 -> 620 | I72: =I71+1 -> 720 | J72: =J71+1 -> 920
A73: 21 | B73: Room/Area 21 | F73: =F72+1 -> 421 | G73: =G72+1 -> 521 | H73: =H72+1 -> 621 | I73: =I72+1 -> 721 | J73: =J72+1 -> 921
A74: 22 | B74: Room/Area 22 | F74: =F73+1 -> 422 | G74: =G73+1 -> 522 | H74: =H73+1 -> 622 | I74: =I73+1 -> 722 | J74: =J73+1 -> 922
A75: 23 | B75: Room/Area 23 | F75: =F74+1 -> 423 | G75: =G74+1 -> 523 | H75: =H74+1 -> 623 | I75: =I74+1 -> 723 | J75: =J74+1 -> 923
A76: 24 | B76: Room/Area 24 | F76: =F75+1 -> 424 | G76: =G75+1 -> 524 | H76: =H75+1 -> 624 | I76: =I75+1 -> 724 | J76: =J75+1 -> 924
A77: 25 | B77: Room/Area 25 | F77: =F76+1 -> 425 | G77: =G76+1 -> 525 | H77: =H76+1 -> 625 | I77: =I76+1 -> 725 | J77: =J76+1 -> 925
A78: 26 | B78: Mortgage co | F78: =F77+1 -> 426 | G78: =G77+1 -> 526 | H78: =H77+1 -> 626 | I78: =I77+1 -> 726 | J78: =J77+1 -> 926 | M78: Customer Supplied Info | N78: Per mortgage statement
A79: 27 | B79: Account# Mtge Co. | F79: =F78+1 -> 427 | G79: =G78+1 -> 527 | H79: =H78+1 -> 627 | I79: =I78+1 -> 727 | J79: =J78+1 -> 927
A80: 28 | B80: Loan status | F80: =F79+1 -> 428 | G80: =G79+1 -> 528 | H80: =H79+1 -> 628 | I80: =I79+1 -> 728 | J80: =J79+1 -> 928 | N80: Loan status = current, foreclosure, Paid in full, Late days
A81: 29 | B81: contact person mtge | F81: =F80+1 -> 429 | G81: =G80+1 -> 529 | H81: =H80+1 -> 629 | I81: =I80+1 -> 729 | J81: =J80+1 -> 929
A82: 30 | B82: Phone # MTGE contact | F82: =F81+1 -> 430 | G82: =G81+1 -> 530 | H82: =H81+1 -> 630 | I82: =I81+1 -> 730 | J82: =J81+1 -> 930
A83: 31 | B83: Ph. Ext. Mtge contact | F83: =F82+1 -> 431 | G83: =G82+1 -> 531 | H83: =H82+1 -> 631 | I83: =I82+1 -> 731 | J83: =J82+1 -> 931
A84: Mortgage Company | F84: =F83+1 -> 432 | G84: =G83+1 -> 532 | H84: =H83+1 -> 632 | I84: =I83+1 -> 732 | J84: =J83+1 -> 932
B85: Attn.: Loss Draft Dept | F85: =F84+1 -> 433 | G85: =G84+1 -> 533 | H85: =H84+1 -> 633 | I85: =I84+1 -> 733 | J85: =J84+1 -> 933
B86: Mtge OVN mail | F86: =F85+1 -> 434 | G86: =G85+1 -> 534 | H86: =H85+1 -> 634 | I86: =I85+1 -> 734 | J86: =J85+1 -> 934
B87: city, St., zip ,mtge OVN | F87: =F86+1 -> 435 | G87: =G86+1 -> 535 | H87: =H86+1 -> 635 | I87: =I86+1 -> 735 | J87: =J86+1 -> 935
B88: Phone # MTGE co. | F88: =F87+1 -> 436 | G88: =G87+1 -> 536 | H88: =H87+1 -> 636 | I88: =I87+1 -> 736 | J88: =J87+1 -> 936
B89: email mtge | F89: =F88+1 -> 437 | G89: =G88+1 -> 537 | H89: =H88+1 -> 637 | I89: =I88+1 -> 737 | J89: =J88+1 -> 937
B90: mtge website | F90: =F89+1 -> 438 | G90: =G89+1 -> 538 | H90: =H89+1 -> 638 | I90: =I89+1 -> 738 | J90: =J89+1 -> 938
B91: MTGE co. Fax # | F91: =F90+1 -> 439 | G91: =G90+1 -> 539 | H91: =H90+1 -> 639 | I91: =I90+1 -> 739 | J91: =J90+1 -> 939
B92: Mailing address mtge | F92: =F91+1 -> 440 | G92: =G91+1 -> 540 | H92: =H91+1 -> 640 | I92: =I91+1 -> 740 | J92: =J91+1 -> 940
B93: Mail city, state, zip mtge | F93: =F92+1 -> 441 | G93: =G92+1 -> 541 | H93: =H92+1 -> 641 | I93: =I92+1 -> 741 | J93: =J92+1 -> 941
F94: =F93+1 -> 442 | G94: =G93+1 -> 542 | H94: =H93+1 -> 642 | I94: =I93+1 -> 742 | J94: =J93+1 -> 942
B95: Initial Offer / phase 1 contract amount | F95: =F94+1 -> 443 | G95: =G94+1 -> 543 | H95: =H94+1 -> 643 | I95: =I94+1 -> 743 | J95: =J94+1 -> 943
B96: Draw Request | F96: =F95+1 -> 444 | G96: =G95+1 -> 544 | H96: =H95+1 -> 644 | I96: =I95+1 -> 744 | J96: =J95+1 -> 944
B97: Cust id | F97: =F96+1 -> 445 | G97: =G96+1 -> 545 | H97: =H96+1 -> 645 | I97: =I96+1 -> 745 | J97: =J96+1 -> 945
F98: =F97+1 -> 446 | G98: =G97+1 -> 546 | H98: =H97+1 -> 646 | I98: =I97+1 -> 746 | J98: =J97+1 -> 946
F99: =F98+1 -> 447 | G99: =G98+1 -> 547 | H99: =H98+1 -> 647 | I99: =I98+1 -> 747 | J99: =J98+1 -> 947
B100: co name | C100: All Phase Consulting, LLC | P100: AK Builders Group LLC | Q100: Platinum One Properties, LLC | R100: PROVISO INVESTMENTS | S100: J THOMAS CONTRACTING, LLC | T100: ALL PHASE CONSULTING, LLC | U100: Wayside Builders, LLC | V100: Wayside Builders, LLC | W100: Alpha Omega Construction | X100: YASMEEN PROPERTIES.INC
...

Sheet ROOMS#
A1: ='jobinfo(2)'!C51 -> OH25THOMAS@GERTRUDE | B1: ='jobinfo(2)'!C3 -> Cleveland, OH 44105 | C1: SOURCE of LOSS | D1: CPS | E1: PPR | F1: DMO DEMO | G1: MIT WTR | H1: MC ... READ INGS | L1: RH &T & GPP DRY CHAMBERS [DC] .READ INGS | P1: LISTS | R1: INPUT = ROOM NAMES | T1: LOS / TRAVEL | U1: OUTPUT = | W1: ROOM NAME ADD TO ENCIRCLE ROOM LISTS | Y1: LOS / TRAVEL | Z1: OUTPUT = ENC ROOM NAME | AD1: LOS / TRAVEL | AE1: OUTPUT = ENC ROOM NAME | AI1: LOS / TRAVEL | AJ1: OUTPUT = ENC ROOM NAME | AK1: OUTPUT = ENC ROOM NAME | AO1: LOS / TRAVEL | AP1: ? | AT1: LOS / TRAVEL | AU1: … MITIGATION EQUIPMENT & W.I.P . ... | AY1: LOS / TRAVEL | AZ1: ... DAY1 MC READINGS .. | BE1: LOS / TRAVEL | BF1: ... DAY2 MC READINGS .. | BJ1: LOS / TRAVEL | BK1: ... DAY3 MC READINGS .. | BO1: LOS / TRAVEL | BP1: ... DAY4 MC READINGS | BT1: LOS / TRAVEL | BU1: RH &T & GPP DRY CHAMBERS [DC] .READ INGS | CB1: DEFAULT TMP1 1 | CD1: WTR METER | CE1: ADD CPS OVERVIEW = MULTIPLE ROOMS / WITH LABELS | CH1: … DAY # 0 … MC READINGS STABILIZATION | CP1: ROOM LABELS
A2: ='jobinfo(2)'!C2 -> 6600 GERTRUDE | H2: DAY1 | I2: DAY2 | J2: DAY3 | K2: DAY4 | L2: DAY1 | M2: DAY2 | N2: DAY3 | O2: DAY4 | P2: = … JOB/ROOMS OVERVIEW PICS .. | U2: =P2 -> = … JOB/ROOMS OVERVIEW PICS .. | Z2: ….. SOURCE of LOSS PICS ….. | AE2: ….. C.P.S. …... | AK2: NON SALVAGEABLE ITEMS | AN2: =E1 -> PPR | AP2: ,,,,,, DMO = DEMOLITION ….... | AU2: =G1 -> MIT WTR | AZ2: .. DAY 1 … | BF2: ….. DAY 2 ….. | BK2: ….. DAY 3 ….. | BP2: ….. DAY 4 ….. | BU2: ….. DAY 1 ….. | CB2: KITCHEN CABINETS SIZES | CE2: BATHROOM VANITY SIZE & FIXTURES | CH2: =CH1 -> … DAY # 0 … MC READINGS STABILIZATION | CL2: LOS / TRAVEL | CP2: ROOM LABELS
A3: =R3 -> JOB/ROOMS OVERVIEW PICS | B3: =B4-1 -> 100 | C3: =C4-1 -> 200 | D3: 300 | E3: =E4-1 -> 400 | F3: 500 | G3: =G4-1 -> 800 | H3: =H4-1 -> 6100.1 | I3: =I4-1 -> 6200.2 | J3: =J4-1 -> 6300.3 | K3: =K4-1 -> 6400.4 | P3: =P4-1 -> 100 | Q3: …. | R3: JOB/ROOMS OVERVIEW PICS | S3: , | T3: ======= | U3: =P3 -> 100 | V3: =Q3 -> …. | W3: =U2 -> = … JOB/ROOMS OVERVIEW PICS .. | Y3: ====== | Z3: =C3 -> 200 | AA3: =V3 -> …. | AB3: =Z2 -> ….. SOURCE of LOSS PICS ….. | AC3: ==================== | AD3: ====== | AE3: =D3 -> 300 | AF3: =AA3 -> …. | AG3: =AE2 -> ….. C.P.S. …... | AH3: ============== | AI3: ====== | AK3: =E3 -> 400 | AL3: =AF3 -> …. | AM3: =AK2 -> NON SALVAGEABLE ITEMS | AN3: ============================== | AP3: =F3 -> 500 | AQ3: …. | AR3: =AP2 -> ,,,,,, DMO = DEMOLITION ….... | AS3: ============================== | AT3: ============================== | AU3: =G3 -> 800 | AV3: . | AW3: MITIGATION EQUIPMENT & W.I.P. ================ MIT & WIP === | AY3: ============================== | AZ3: =AZ4-0.1 -> 6101 | BA3: . | BB3: =AZ1 -> ... DAY1 MC READINGS .. | BC3: ========= | BD3: =============== | BE3: ===== | BF3: =BF4-0.2 -> 6201 | BG3: . | BH3: =BF1 -> ... DAY2 MC READINGS .. | BI3: =============== | BJ3: ====== | BK3: =BK4-0.3 -> 6301 | BL3: . | BM3: =BK2 -> ….. DAY 3 ….. | BN3: ===================== | BO3: ====== | BP3: =BP4-0.4 -> 6401 | BQ3: . | BR3: =BP2 -> ….. DAY 4 ….. | BS3: =============== | BT3: =BP2 -> ….. DAY 4 ….. | BU3: =BU5-0.1 -> 7099.9 | BV3: STABILIZATION READINGS | BW3: ---------------- | CB3: 0 | CC3: ….. | CD3: DEFAULT LIST EXISTS (AS BELOW); CLICK DROPDOWN MENU; ADD JOB TYPES AS NEEDED | CH3: 70000 | CI3: ….. | CJ3: ======= DAY # 0 ….. MC READINGS STABILIZATION =============== | CP3: =R4 -> Living Room | CQ3: =T4 -> ….........
A4: =R4 -> Living Room | B4: =P4 -> 101 | C4: 201 | D4: 301 | E4: 401 | F4: 501 | G4: 801 | H4: 6101.1 | I4: 6201.2 | J4: 6301.3 | K4: 6401.4 | P4: 101 | Q4: …. | R4: Living Room | S4: , | T4: …......... | U4: =P4 -> 101 | V4: =Q4 -> …. | W4: =R4 -> Living Room | X4: =$U$2 -> = … JOB/ROOMS OVERVIEW PICS .. | Y4: =$T$4 -> …......... | Z4: =C4 -> 201 | AA4: =V4 -> …. | AB4: =W4 -> Living Room | AC4: =$Z$2 -> ….. SOURCE of LOSS PICS ….. | AD4: =$T$4 -> …......... | AE4: =D4 -> 301 | AF4: =AA4 -> …. | AG4: =AB4 -> Living Room | AH4: =$AE$2 -> ….. C.P.S. …... | AI4: =$T$4 -> …......... | AK4: =E4 -> 401 | AL4: =AF4 -> …. | AM4: =AG4 -> Living Room | AN4: =$AK$2 -> NON SALVAGEABLE ITEMS | AO4: =$T$4 -> …......... | AP4: =F4 -> 501 | AQ4: …. | AR4: =AM4 -> Living Room | AS4: =AR3 -> ,,,,,, DMO = DEMOLITION ….... | AT4: =T4 -> …......... | AU4: =G4 -> 801 | AV4: . | AW4: =AM4 -> Living Room | AX4: =AU1 -> … MITIGATION EQUIPMENT & W.I.P . ... | AY4: =$T$4 -> …......... | AZ4: =H4 -> 6101.1 | BA4: . | BB4: =AW4 -> Living Room | BC4: =AZ1 -> ... DAY1 MC READINGS .. | BE4: =$T$4 -> …......... | BF4: =I4 -> 6201.2 | BG4: . | BH4: =BB4 -> Living Room | BI4: =BF1 -> ... DAY2 MC READINGS .. | BJ4: =$T$4 -> …......... | BK4: =J4 -> 6301.3 | BL4: . | BM4: =BH4 -> Living Room | BN4: =BK1 -> ... DAY3 MC READINGS .. | BO4: =$T$4 -> …......... | BP4: =K4 -> 6401.4 | BQ4: . | BR4: =BM4 -> Living Room | BS4: =BP1 -> ... DAY4 MC READINGS | BT4: =$T$4 -> …......... | BU4: 7100 | BV4: RH &T & GPP DRY CHAMBERS [DC] .READ INGS =========== | BW4: =BU2 -> ….. DAY 1 ….. | CB4: 0.0001 | CC4: ….. | CD4: JOBSITE VERIFICATION | CH4: 70101 | CI4: . | CJ4: =R4 -> Living Room | CK4: , | CL4: =T4 -> …......... | CM4: , | CN4: =CH1 -> … DAY # 0 … MC READINGS STABILIZATION | CP4: =R5 -> GUEST CLOSET | CQ4: =T5 -> …..........
A5: =R5 -> GUEST CLOSET | B5: =P5 -> 102 | C5: =C4+1 -> 202 | D5: =D4+1 -> 302 | E5: =E4+1 -> 402 | F5: =F4+1 -> 502 | G5: 802 | H5: =H4+1 -> 6102.1 | I5: =I4+1 -> 6202.2 | J5: =J4+1 -> 6302.3 | K5: =K4+1 -> 6402.4 | L5: STABILIZATION READINGS | P5: 102 | Q5: …. | R5: GUEST CLOSET | S5: , | T5: ….......... | U5: =P5 -> 102 | V5: =Q5 -> …. | W5: =R5 -> GUEST CLOSET | X5: =$U$2 -> = … JOB/ROOMS OVERVIEW PICS .. | Y5: =$T$5 -> ….......... | Z5: =C5 -> 202 | AA5: =V5 -> …. | AB5: =W5 -> GUEST CLOSET | AC5: =$Z$2 -> ….. SOURCE of LOSS PICS ….. | AD5: =$T$5 -> ….......... | AE5: =D5 -> 302 | AF5: =AA5 -> …. | AG5: =AB5 -> GUEST CLOSET | AH5: =$AE$2 -> ….. C.P.S. …... | AI5: =$T$5 -> ….......... | AK5: =E5 -> 402 | AL5: =AF5 -> …. | AM5: =AG5 -> GUEST CLOSET | AN5: =$AK$2 -> NON SALVAGEABLE ITEMS | AO5: =$T$5 -> ….......... | AP5: =F5 -> 502 | AQ5: …. | AR5: =AM5 -> GUEST CLOSET | AS5: =AS4 -> ,,,,,, DMO = DEMOLITION ….... | AT5: =T5 -> ….......... | AU5: =G5 -> 802 | AV5: . | AW5: =AM5 -> GUEST CLOSET | AX5: =AX4 -> … MITIGATION EQUIPMENT & W.I.P . ... | AY5: =$T$5 -> ….......... | AZ5: =H5 -> 6102.1 | BA5: . | BB5: =AW5 -> GUEST CLOSET | BC5: =BC4 -> ... DAY1 MC READINGS .. | BE5: =$T$5 -> ….......... | BF5: =I5 -> 6202.2 | BG5: . | BH5: =BB5 -> GUEST CLOSET | BI5: =BI4 -> ... DAY2 MC READINGS .. | BJ5: =$T$5 -> ….......... | BK5: =J5 -> 6302.3 | BL5: . | BM5: =BH5 -> GUEST CLOSET | BN5: =BN4 -> ... DAY3 MC READINGS .. | BO5: =$T$5 -> ….......... | BP5: =K5 -> 6402.4 | BQ5: . | BR5: =BM5 -> GUEST CLOSET | BS5: =BS4 -> ... DAY4 MC READINGS | BT5: =$T$5 -> ….......... | BU5: 7100 | BV5: EXTERIOR & UNAFFECTED AREA | BW5: =BU2 -> ….. DAY 1 ….. | CB5: 0.0002 | CC5: . | CD5: MECHANICALS = WATER METER READING & PLUMBING REPORT/INVOICE | CF5: , | CG5: ====== | CH5: =CH4+1 -> 70102 | CI5: . | CJ5: =R5 -> GUEST CLOSET | CK5: , | CL5: N/A | CM5: , | CN5: =CN4 -> … DAY # 0 … MC READINGS STABILIZATION | CP5: =R6 -> Dining Room | CQ5: =T6 -> ….........
A6: =R6 -> Dining Room | B6: =P6 -> 103 | C6: =C5+1 -> 203 | D6: =D5+1 -> 303 | E6: =E5+1 -> 403 | F6: =F5+1 -> 503 | G6: 803 | H6: =H5+1 -> 6103.1 | I6: =I5+1 -> 6203.2 | J6: =J5+1 -> 6303.3 | K6: =K5+1 -> 6403.4 | L6: =L8-0.1 -> 7100 | M6: =M8-0.1 -> 7200.1 | P6: 103 | Q6: …. | R6: Dining Room | S6: , | T6: …......... | U6: =P6 -> 103 | V6: =Q6 -> …. | W6: =R6 -> Dining Room | X6: =$U$2 -> = … JOB/ROOMS OVERVIEW PICS .. | Y6: =$T$6 -> …......... | Z6: =C6 -> 203 | AA6: =V6 -> …. | AB6: =W6 -> Dining Room | AC6: =$Z$2 -> ….. SOURCE of LOSS PICS ….. | AD6: =$T$6 -> …......... | AE6: =D6 -> 303 | AF6: =AA6 -> …. | AG6: =AB6 -> Dining Room | AH6: =$AE$2 -> ….. C.P.S. …... | AI6: =$T$6 -> …......... | AK6: =E6 -> 403 | AL6: =AF6 -> …. | AM6: =AG6 -> Dining Room | AN6: =$AK$2 -> NON SALVAGEABLE ITEMS | AO6: =$T$6 -> …......... | AP6: =F6 -> 503 | AQ6: …. | AR6: =AM6 -> Dining Room | AS6: =AS5 -> ,,,,,, DMO = DEMOLITION ….... | AT6: =T6 -> …......... | AU6: =G6 -> 803 | AV6: . | AW6: =AM6 -> Dining Room | AX6: =AX5 -> … MITIGATION EQUIPMENT & W.I.P . ... | AY6: =$T$6 -> …......... | AZ6: =H6 -> 6103.1 | BA6: . | BB6: =AW6 -> Dining Room | BC6: =BC5 -> ... DAY1 MC READINGS .. | BE6: =$T$6 -> …......... | BF6: =I6 -> 6203.2 | BG6: . | BH6: =BB6 -> Dining Room | BI6: =BI5 -> ... DAY2 MC READINGS .. | BJ6: =$T$6 -> …......... | BK6: =J6 -> 6303.3 | BL6: . | BM6: =BH6 -> Dining Room | BN6: =BN5 -> ... DAY3 MC READINGS .. | BO6: =$T$6 -> …......... | BP6: =K6 -> 6403.4 | BQ6: . | BR6: =BM6 -> Dining Room | BS6: =BS5 -> ... DAY4 MC READINGS | BT6: =$T$6 -> …......... | BU6: =BU5+1 -> 7101 | BV6: DRY CHAMBER # 1 | BW6: =BW5 -> ….. DAY 1 ….. | BX6: RH &T & GPP | CB6: 0.0003 | CC6: . | CD6: MECHANICALS = ELECTRICAL HAZARDS | CF6: , | CG6: ====== | CH6: =CH5+1 -> 70103 | CI6: . | CJ6: =R6 -> Dining Room | CK6: , | CL6: =T6 -> …......... | CM6: , | CN6: =CN5 -> … DAY # 0 … MC READINGS STABILIZATION | CP6: =R7 -> DEN | CQ6: =T7 -> ….........
A7: =R7 -> DEN | B7: =P7 -> 104 | C7: =C6+1 -> 204 | D7: =D6+1 -> 304 | E7: =E6+1 -> 404 | F7: =F6+1 -> 504 | G7: 804 | H7: =H6+1 -> 6104.1 | I7: =I6+1 -> 6204.2 | J7: =J6+1 -> 6304.3 | K7: =K6+1 -> 6404.4 | L7: EXTERIOR & UNAFFECTED AREA | P7: 104 | Q7: …. | R7: DEN | S7: , | T7: …......... | U7: =P7 -> 104 | V7: =Q7 -> …. | W7: =R7 -> DEN | X7: =$U$2 -> = … JOB/ROOMS OVERVIEW PICS .. | Y7: =$T$7 -> …......... | Z7: =C7 -> 204 | AA7: =V7 -> …. | AB7: =W7 -> DEN | AC7: =$Z$2 -> ….. SOURCE of LOSS PICS ….. | AD7: =$T$7 -> …......... | AE7: =D7 -> 304 | AF7: =AA7 -> …. | AG7: =AB7 -> DEN | AH7: =$AE$2 -> ….. C.P.S. …... | AI7: =$T$7 -> …......... | AK7: =E7 -> 404 | AL7: =AF7 -> …. | AM7: =AG7 -> DEN | AN7: =$AK$2 -> NON SALVAGEABLE ITEMS | AO7: =$T$7 -> …......... | AP7: =F7 -> 504 | AQ7: …. | AR7: =AM7 -> DEN | AS7: =AS6 -> ,,,,,, DMO = DEMOLITION ….... | AT7: =T7 -> …......... | AU7: =G7 -> 804 | AV7: . | AW7: =AM7 -> DEN | AX7: =AX6 -> … MITIGATION EQUIPMENT & W.I.P . ... | AY7: =$T$7 -> …......... | AZ7: =H7 -> 6104.1 | BA7: . | BB7: =AW7 -> DEN | BC7: =BC6 -> ... DAY1 MC READINGS .. | BE7: =$T$7 -> …......... | BF7: =I7 -> 6204.2 | BG7: . | BH7: =BB7 -> DEN | BI7: =BI6 -> ... DAY2 MC READINGS .. | BJ7: =$T$7 -> …......... | BK7: =J7 -> 6304.3 | BL7: . | BM7: =BH7 -> DEN | BN7: =BN6 -> ... DAY3 MC READINGS .. | BO7: =$T$7 -> …......... | BP7: =K7 -> 6404.4 | BQ7: . | BR7: =BM7 -> DEN | BS7: =BS6 -> ... DAY4 MC READINGS | BT7: =$T$7 -> …......... | BU7: =BU6+1 -> 7102 | BV7: DRY CHAMBER # 2 | BW7: =BW6 -> ….. DAY 1 ….. | BX7: RH &T & GPP | CB7: 0.0004 | CC7: . | CD7: EXT DAMAGE IF APPLICABLE | CE7: ROOF TARPS …............................. | CF7: , | CG7: ====== | CH7: =CH6+1 -> 70104 | CI7: . | CJ7: =R7 -> DEN | CK7: , | CL7: =T7 -> …......... | CM7: , | CN7: =CN6 -> … DAY # 0 … MC READINGS STABILIZATION | CP7: =R8 -> Kitchen | CQ7: =T8 -> ….........
A8: =R8 -> Kitchen | B8: =P8 -> 105 | C8: =C7+1 -> 205 | D8: =D7+1 -> 305 | E8: =E7+1 -> 405 | F8: =F7+1 -> 505 | G8: 805 | H8: =H7+1 -> 6105.1 | I8: =I7+1 -> 6205.2 | J8: =J7+1 -> 6305.3 | K8: =K7+1 -> 6405.4 | L8: 7100.1 | M8: 7200.2 | N8: 7300.3 | O8: 7400.4 | P8: 105 | Q8: …. | R8: Kitchen | S8: , | T8: …......... | U8: =P8 -> 105 | V8: =Q8 -> …. | W8: =R8 -> Kitchen | X8: =$U$2 -> = … JOB/ROOMS OVERVIEW PICS .. | Y8: =$T$8 -> …......... | Z8: =C8 -> 205 | AA8: =V8 -> …. | AB8: =W8 -> Kitchen | AC8: =$Z$2 -> ….. SOURCE of LOSS PICS ….. | AD8: =$T$8 -> …......... | AE8: =D8 -> 305 | AF8: =AA8 -> …. | AG8: =AB8 -> Kitchen | AH8: =$AE$2 -> ….. C.P.S. …... | AI8: =$T$8 -> …......... | AK8: =E8 -> 405 | AL8: =AF8 -> …. | AM8: =AG8 -> Kitchen | AN8: =$AK$2 -> NON SALVAGEABLE ITEMS | AO8: =$T$8 -> …......... | AP8: =F8 -> 505 | AQ8: …. | AR8: =AM8 -> Kitchen | AS8: =AS7 -> ,,,,,, DMO = DEMOLITION ….... | AT8: =T8 -> …......... | AU8: =G8 -> 805 | AV8: . | AW8: =AM8 -> Kitchen | AX8: =AX7 -> … MITIGATION EQUIPMENT & W.I.P . ... | AY8: =$T$8 -> …......... | AZ8: =H8 -> 6105.1 | BA8: . | BB8: =AW8 -> Kitchen | BC8: =BC7 -> ... DAY1 MC READINGS .. | BE8: =$T$8 -> …......... | BF8: =I8 -> 6205.2 | BG8: . | BH8: =BB8 -> Kitchen | BI8: =BI7 -> ... DAY2 MC READINGS .. | BJ8: =$T$8 -> …......... | BK8: =J8 -> 6305.3 | BL8: . | BM8: =BH8 -> Kitchen | BN8: =BN7 -> ... DAY3 MC READINGS .. | BO8: =$T$8 -> …......... | BP8: =K8 -> 6405.4 | BQ8: . | BR8: =BM8 -> Kitchen | BS8: =BS7 -> ... DAY4 MC READINGS | BT8: =$T$8 -> …......... | BU8: =BU7+1 -> 7103 | BV8: DRY CHAMBER # 3 | BW8: =BW7 -> ….. DAY 1 ….. | BX8: RH &T & GPP | CB8: 1997 | CC8: . | CD8: LEAD & HMR TESTING | CE8: LAB RESULTS | CF8: , | CG8: ====== | CH8: =CH7+1 -> 70105 | CI8: . | CJ8: =R8 -> Kitchen | CK8: , | CL8: =T8 -> …......... | CM8: , | CN8: =CN7 -> … DAY # 0 … MC READINGS STABILIZATION | CP8: =R9 -> STAIRS UP | CQ8: =T9 -> LOS / TRAVEL
A9: =R9 -> STAIRS UP | B9: =P9 -> 106 | C9: =C8+1 -> 206 | D9: =D8+1 -> 306 | E9: =E8+1 -> 406 | F9: =F8+1 -> 506 | G9: 806 | H9: =H8+1 -> 6106.1 | I9: =I8+1 -> 6206.2 | J9: =J8+1 -> 6306.3 | K9: =K8+1 -> 6406.4 | L9: DRY CHAMBER 1 | P9: 106 | Q9: …. | R9: STAIRS UP | S9: , | T9: LOS / TRAVEL | U9: =P9 -> 106 | V9: =Q9 -> …. | W9: =R9 -> STAIRS UP | X9: =$U$2 -> = … JOB/ROOMS OVERVIEW PICS .. | Y9: =$T$9 -> LOS / TRAVEL | Z9: =C9 -> 206 | AA9: =V9 -> …. | AB9: =W9 -> STAIRS UP | AC9: =$Z$2 -> ….. SOURCE of LOSS PICS ….. | AD9: =$T$9 -> LOS / TRAVEL | AE9: =D9 -> 306 | AF9: =AA9 -> …. | AG9: =AB9 -> STAIRS UP | AH9: =$AE$2 -> ….. C.P.S. …... | AI9: =$T$9 -> LOS / TRAVEL | AK9: =E9 -> 406 | AL9: =AF9 -> …. | AM9: =AG9 -> STAIRS UP | AN9: =$AK$2 -> NON SALVAGEABLE ITEMS | AO9: =$T$9 -> LOS / TRAVEL | AP9: =F9 -> 506 | AQ9: …. | AR9: =AM9 -> STAIRS UP | AS9: =AS8 -> ,,,,,, DMO = DEMOLITION ….... | AT9: =T9 -> LOS / TRAVEL | AU9: =G9 -> 806 | AV9: . | AW9: =AM9 -> STAIRS UP | AX9: =AX8 -> … MITIGATION EQUIPMENT & W.I.P . ... | AY9: =$T$9 -> LOS / TRAVEL | AZ9: =H9 -> 6106.1 | BA9: . | BB9: =AW9 -> STAIRS UP | BC9: =BC8 -> ... DAY1 MC READINGS .. | BE9: =$T$9 -> LOS / TRAVEL | BF9: =I9 -> 6206.2 | BG9: . | BH9: =BB9 -> STAIRS UP | BI9: =BI8 -> ... DAY2 MC READINGS .. | BJ9: =$T$9 -> LOS / TRAVEL | BK9: =J9 -> 6306.3 | BL9: . | BM9: =BH9 -> STAIRS UP | BN9: =BN8 -> ... DAY3 MC READINGS .. | BO9: =$T$9 -> LOS / TRAVEL | BP9: =K9 -> 6406.4 | BQ9: . | BR9: =BM9 -> STAIRS UP | BS9: =BS8 -> ... DAY4 MC READINGS | BT9: =$T$9 -> LOS / TRAVEL | BU9: =BU8+1 -> 7104 | BV9: DRY CHAMBER # 4 | BW9: =BW8 -> ….. DAY 1 ….. | BX9: RH &T & GPP | CB9: 1998 | CC9: . | CD9: KITCHEN CABINETS SIZES | CE9: U & L =LF/ CT = SF; APPLIANCES | CF9: , | CG9: ====== | CH9: =CH8+1 -> 70106 | CI9: . | CJ9: =R9 -> STAIRS UP | CK9: , | CL9: =T9 -> LOS / TRAVEL | CM9: , | CN9: =CN8 -> … DAY # 0 … MC READINGS STABILIZATION | CP9: =R10 -> HALL UP | CQ9: =T10 -> ….........
A10: =R10 -> HALL UP | B10: =P10 -> 107 | C10: =C9+1 -> 207 | D10: =D9+1 -> 307 | E10: =E9+1 -> 407 | F10: =F9+1 -> 507 | G10: 807 | H10: =H9+1 -> 6107.1 | I10: =I9+1 -> 6207.2 | J10: =J9+1 -> 6307.3 | K10: =K9+1 -> 6407.4 | L10: =L8+1 -> 7101.1 | M10: =M8+1 -> 7201.2 | N10: =N8+1 -> 7301.3 | O10: =O8+1 -> 7401.4 | P10: 107 | Q10: …. | R10: HALL UP | S10: , | T10: …......... | U10: =P10 -> 107 | V10: =Q10 -> …. | W10: =R10 -> HALL UP | X10: =$U$2 -> = … JOB/ROOMS OVERVIEW PICS .. | Y10: =$T$10 -> …......... | Z10: =C10 -> 207 | AA10: =V10 -> …. | AB10: =W10 -> HALL UP | AC10: =$Z$2 -> ….. SOURCE of LOSS PICS ….. | AD10: =$T$10 -> …......... | AE10: =D10 -> 307 | AF10: =AA10 -> …. | AG10: =AB10 -> HALL UP | AH10: =$AE$2 -> ….. C.P.S. …... | AI10: =$T$10 -> …......... | AK10: =E10 -> 407 | AL10: =AF10 -> …. | AM10: =AG10 -> HALL UP | AN10: =$AK$2 -> NON SALVAGEABLE ITEMS | AO10: =$T$10 -> …......... | AP10: =F10 -> 507 | AQ10: …. | AR10: =AM10 -> HALL UP | AS10: =AS9 -> ,,,,,, DMO = DEMOLITION ….... | AT10: =T10 -> …......... | AU10: =G10 -> 807 | AV10: . | AW10: =AM10 -> HALL UP | AX10: =AX9 -> … MITIGATION EQUIPMENT & W.I.P . ... | AY10: =$T$10 -> …......... | AZ10: =H10 -> 6107.1 | BA10: . | BB10: =AW10 -> HALL UP | BC10: =BC9 -> ... DAY1 MC READINGS .. | BE10: =$T$10 -> …......... | BF10: =I10 -> 6207.2 | BG10: . | BH10: =BB10 -> HALL UP | BI10: =BI9 -> ... DAY2 MC READINGS .. | BJ10: =$T$10 -> …......... | BK10: =J10 -> 6307.3 | BL10: . | BM10: =BH10 -> HALL UP | BN10: =BN9 -> ... DAY3 MC READINGS .. | BO10: =$T$10 -> …......... | BP10: =K10 -> 6407.4 | BQ10: . | BR10: =BM10 -> HALL UP | BS10: =BS9 -> ... DAY4 MC READINGS | BT10: =$T$10 -> …......... | BU10: =BU11-0.2 -> 7200 | BV10: =BV4 -> RH &T & GPP DRY CHAMBERS [DC] .READ INGS =========== | BW10: ….. DAY 2 ….. | CB10: 1999 | CC10: . | CD10: BATHROOM FIXTURES | CE10: CAB SIZE & FIXTURES & TYPE | CF10: , | CG10: ====== | CH10: =CH9+1 -> 70107 | CI10: . | CJ10: =R10 -> HALL UP | CK10: , | CL10: =T10 -> …......... | CM10: , | CN10: =CN9 -> … DAY # 0 … MC READINGS STABILIZATION | CP10: =R11 -> LINEN CLOSET | CQ10: =T11 -> ….........
A11: =R11 -> LINEN CLOSET | B11: =P11 -> 108 | C11: =C10+1 -> 208 | D11: =D10+1 -> 308 | E11: =E10+1 -> 408 | F11: =F10+1 -> 508 | G11: 808 | H11: =H10+1 -> 6108.1 | I11: =I10+1 -> 6208.2 | J11: =J10+1 -> 6308.3 | K11: =K10+1 -> 6408.4 | L11: DRY CHAMBER 2 | P11: 108 | Q11: …. | R11: LINEN CLOSET | S11: , | T11: …......... | U11: =P11 -> 108 | V11: =Q11 -> …. | W11: =R11 -> LINEN CLOSET | X11: =$U$2 -> = … JOB/ROOMS OVERVIEW PICS .. | Y11: =$T$11 -> …......... | Z11: =C11 -> 208 | AA11: =V11 -> …. | AB11: =W11 -> LINEN CLOSET | AC11: =$Z$2 -> ….. SOURCE of LOSS PICS ….. | AD11: =$T$11 -> …......... | AE11: =D11 -> 308 | AF11: =AA11 -> …. | AG11: =AB11 -> LINEN CLOSET | AH11: =$AE$2 -> ….. C.P.S. …... | AI11: =$T$11 -> …......... | AK11: =E11 -> 408 | AL11: =AF11 -> …. | AM11: =AG11 -> LINEN CLOSET | AN11: =$AK$2 -> NON SALVAGEABLE ITEMS | AO11: =$T$11 -> …......... | AP11: =F11 -> 508 | AQ11: …. | AR11: =AM11 -> LINEN CLOSET | AS11: =AS10 -> ,,,,,, DMO = DEMOLITION ….... | AT11: =T11 -> …......... | AU11: =G11 -> 808 | AV11: . | AW11: =AM11 -> LINEN CLOSET | AX11: =AX10 -> … MITIGATION EQUIPMENT & W.I.P . ... | AY11: =$T$11 -> …......... | AZ11: =H11 -> 6108.1 | BA11: . | BB11: =AW11 -> LINEN CLOSET | BC11: =BC10 -> ... DAY1 MC READINGS .. | BE11: =$T$11 -> …......... | BF11: =I11 -> 6208.2 | BG11: . | BH11: =BB11 -> LINEN CLOSET | BI11: =BI10 -> ... DAY2 MC READINGS .. | BJ11: =$T$11 -> …......... | BK11: =J11 -> 6308.3 | BL11: . | BM11: =BH11 -> LINEN CLOSET | BN11: =BN10 -> ... DAY3 MC READINGS .. | BO11: =$T$11 -> …......... | BP11: =K11 -> 6408.4 | BQ11: . | BR11: =BM11 -> LINEN CLOSET | BS11: =BS10 -> ... DAY4 MC READINGS | BT11: =$T$11 -> …......... | BU11: 7200.2 | BV11: EXTERIOR & UNAFFECTED AREA | BW11: =BW10 -> ….. DAY 2 ….. | CB11: 3222 | CC11: . | CD11: CPS DAY2 WIP | CE11: OVERVIEW WIP BOXES PACKOUT PICS | CF11: , | CG11: ====== | CH11: =CH10+1 -> 70108 | CI11: . | CJ11: =R11 -> LINEN CLOSET | CK11: , | CL11: =T11 -> …......... | CM11: , | CN11: =CN10 -> … DAY # 0 … MC READINGS STABILIZATION | CP11: =R12 -> BATH UP | CQ11: =T12 -> ….........
A12: =R12 -> BATH UP | B12: =P12 -> 109 | C12: =C11+1 -> 209 | D12: =D11+1 -> 309 | E12: =E11+1 -> 409 | F12: =F11+1 -> 509 | G12: 809 | H12: =H11+1 -> 6109.1 | I12: =I11+1 -> 6209.2 | J12: =J11+1 -> 6309.3 | K12: =K11+1 -> 6409.4 | L12: =L10+1 -> 7102.1 | M12: =M10+1 -> 7202.2 | N12: =N10+1 -> 7302.3 | O12: =O10+1 -> 7402.4 | P12: 109 | Q12: …. | R12: BATH UP | S12: , | T12: …......... | U12: =P12 -> 109 | V12: =Q12 -> …. | W12: =R12 -> BATH UP | X12: =$U$2 -> = … JOB/ROOMS OVERVIEW PICS .. | Y12: =$T$12 -> …......... | Z12: =C12 -> 209 | AA12: =V12 -> …. | AB12: =W12 -> BATH UP | AC12: =$Z$2 -> ….. SOURCE of LOSS PICS ….. | AD12: =$T$12 -> …......... | AE12: =D12 -> 309 | AF12: =AA12 -> …. | AG12: =AB12 -> BATH UP | AH12: =$AE$2 -> ….. C.P.S. …... | AI12: =$T$12 -> …......... | AK12: =E12 -> 409 | AL12: =AF12 -> …. | AM12: =AG12 -> BATH UP | AN12: =$AK$2 -> NON SALVAGEABLE ITEMS | AO12: =$T$12 -> …......... | AP12: =F12 -> 509 | AQ12: …. | AR12: =AM12 -> BATH UP | AS12: =AS11 -> ,,,,,, DMO = DEMOLITION ….... | AT12: =T12 -> …......... | AU12: =G12 -> 809 | AV12: . | AW12: =AM12 -> BATH UP | AX12: =AX11 -> … MITIGATION EQUIPMENT & W.I.P . ... | AY12: =$T$12 -> …......... | AZ12: =H12 -> 6109.1 | BA12: . | BB12: =AW12 -> BATH UP | BC12: =BC11 -> ... DAY1 MC READINGS .. | BE12: =$T$12 -> …......... | BF12: =I12 -> 6209.2 | BG12: . | BH12: =BB12 -> BATH UP | BI12: =BI11 -> ... DAY2 MC READINGS .. | BJ12: =$T$12 -> …......... | BK12: =J12 -> 6309.3 | BL12: . | BM12: =BH12 -> BATH UP | BN12: =BN11 -> ... DAY3 MC READINGS .. | BO12: =$T$12 -> …......... | BP12: =K12 -> 6409.4 | BQ12: . | BR12: =BM12 -> BATH UP | BS12: =BS11 -> ... DAY4 MC READINGS | BT12: =$T$12 -> …......... | BU12: =BU11+1 -> 7201.2 | BV12: DRY CHAMBER # 1 | BW12: =BW11 -> ….. DAY 2 ….. | BX12: RH &T & GPP | CB12: 3322 | CC12: . | CD12: CPS3 DAY3 STORAGE | CE12: OVERVIEW STORAGE MOVE OUT PICS | CF12: , | CG12: ====== | CH12: =CH11+1 -> 70109 | CI12: . | CJ12: =R12 -> BATH UP | CK12: , | CL12: =T12 -> …......... | CM12: , | CN12: =CN11 -> … DAY # 0 … MC READINGS STABILIZATION | CP12: =R13 -> Bedroom 1 | CQ12: =T13 -> ….........
A13: =R13 -> Bedroom 1 | B13: =P13 -> 110 | C13: =C12+1 -> 210 | D13: =D12+1 -> 310 | E13: =E12+1 -> 410 | F13: =F12+1 -> 510 | G13: 810 | H13: =H12+1 -> 6110.1 | I13: =I12+1 -> 6210.2 | J13: =J12+1 -> 6310.3 | K13: =K12+1 -> 6410.4 | L13: DRY CHAMBER 3 | P13: 110 | Q13: …. | R13: Bedroom 1 | S13: , | T13: …......... | U13: =P13 -> 110 | V13: =Q13 -> …. | W13: =R13 -> Bedroom 1 | X13: =$U$2 -> = … JOB/ROOMS OVERVIEW PICS .. | Y13: =$T$13 -> …......... | Z13: =C13 -> 210 | AA13: =V13 -> …. | AB13: =W13 -> Bedroom 1 | AC13: =$Z$2 -> ….. SOURCE of LOSS PICS ….. | AD13: =$T$13 -> …......... | AE13: =D13 -> 310 | AF13: =AA13 -> …. | AG13: =AB13 -> Bedroom 1 | AH13: =$AE$2 -> ….. C.P.S. …... | AI13: =$T$13 -> …......... | AK13: =E13 -> 410 | AL13: =AF13 -> …. | AM13: =AG13 -> Bedroom 1 | AN13: =$AK$2 -> NON SALVAGEABLE ITEMS | AO13: =$T$13 -> …......... | AP13: =F13 -> 510 | AQ13: …. | AR13: =AM13 -> Bedroom 1 | AS13: =AS12 -> ,,,,,, DMO = DEMOLITION ….... | AT13: =T13 -> …......... | AU13: =G13 -> 810 | AV13: . | AW13: =AM13 -> Bedroom 1 | AX13: =AX12 -> … MITIGATION EQUIPMENT & W.I.P . ... | AY13: =$T$13 -> …......... | AZ13: =H13 -> 6110.1 | BA13: . | BB13: =AW13 -> Bedroom 1 | BC13: =BC12 -> ... DAY1 MC READINGS .. | BE13: =$T$13 -> …......... | BF13: =I13 -> 6210.2 | BG13: . | BH13: =BB13 -> Bedroom 1 | BI13: =BI12 -> ... DAY2 MC READINGS .. | BJ13: =$T$13 -> …......... | BK13: =J13 -> 6310.3 | BL13: . | BM13: =BH13 -> Bedroom 1 | BN13: =BN12 -> ... DAY3 MC READINGS .. | BO13: =$T$13 -> …......... | BP13: =K13 -> 6410.4 | BQ13: . | BR13: =BM13 -> Bedroom 1 | BS13: =BS12 -> ... DAY4 MC READINGS | BT13: =$T$13 -> …......... | BU13: =BU12+1 -> 7202.2 | BV13: DRY CHAMBER # 2 | BW13: =BW12 -> ….. DAY 2 ….. | BX13: RH &T & GPP | CB13: 3444 | CC13: . | CD13: CPS4 DAY4 PACKBACK | CE13: OVERVIEW PACK-BACK / RESET PICS | CF13: , | CG13: ====== | CH13: =CH12+1 -> 70110 | CI13: . | CJ13: =R13 -> Bedroom 1 | CK13: , | CL13: =T13 -> …......... | CM13: , | CN13: =CN12 -> … DAY # 0 … MC READINGS STABILIZATION | CP13: =R14 -> BR1 Closet | CQ13: =T14 -> LOS / TRAVEL
A14: =R14 -> BR1 Closet | B14: =P14 -> 111 | C14: =C13+1 -> 211 | D14: =D13+1 -> 311 | E14: =E13+1 -> 411 | F14: =F13+1 -> 511 | G14: 811 | H14: =H13+1 -> 6111.1 | I14: =I13+1 -> 6211.2 | J14: =J13+1 -> 6311.3 | K14: =K13+1 -> 6411.4 | L14: =L12+1 -> 7103.1 | M14: =M12+1 -> 7203.2 | N14: =N12+1 -> 7303.3 | O14: =O12+1 -> 7403.4 | P14: 111 | Q14: …. | R14: BR1 Closet | S14: , | T14: LOS / TRAVEL | U14: =P14 -> 111 | V14: =Q14 -> …. | W14: =R14 -> BR1 Closet | X14: =$U$2 -> = … JOB/ROOMS OVERVIEW PICS .. | Y14: =$T$14 -> LOS / TRAVEL | Z14: =C14 -> 211 | AA14: =V14 -> …. | AB14: =W14 -> BR1 Closet | AC14: =$Z$2 -> ….. SOURCE of LOSS PICS ….. | AD14: =$T$14 -> LOS / TRAVEL | AE14: =D14 -> 311 | AF14: =AA14 -> …. | AG14: =AB14 -> BR1 Closet | AH14: =$AE$2 -> ….. C.P.S. …... | AI14: =$T$14 -> LOS / TRAVEL | AK14: =E14 -> 411 | AL14: =AF14 -> …. | AM14: =AG14 -> BR1 Closet | AN14: =$AK$2 -> NON SALVAGEABLE ITEMS | AO14: =$T$14 -> LOS / TRAVEL | AP14: =F14 -> 511 | AQ14: …. | AR14: =AM14 -> BR1 Closet | AS14: =AS13 -> ,,,,,, DMO = DEMOLITION ….... | AT14: =T14 -> LOS / TRAVEL | AU14: =G14 -> 811 | AV14: . | AW14: =AM14 -> BR1 Closet | AX14: =AX13 -> … MITIGATION EQUIPMENT & W.I.P . ... | AY14: =$T$14 -> LOS / TRAVEL | AZ14: =H14 -> 6111.1 | BA14: . | BB14: =AW14 -> BR1 Closet | BC14: =BC13 -> ... DAY1 MC READINGS .. | BE14: =$T$14 -> LOS / TRAVEL | BF14: =I14 -> 6211.2 | BG14: . | BH14: =BB14 -> BR1 Closet | BI14: =BI13 -> ... DAY2 MC READINGS .. | BJ14: =$T$14 -> LOS / TRAVEL | BK14: =J14 -> 6311.3 | BL14: . | BM14: =BH14 -> BR1 Closet | BN14: =BN13 -> ... DAY3 MC READINGS .. | BO14: =$T$14 -> LOS / TRAVEL | BP14: =K14 -> 6411.4 | BQ14: . | BR14: =BM14 -> BR1 Closet | BS14: =BS13 -> ... DAY4 MC READINGS | BT14: =$T$14 -> LOS / TRAVEL | BU14: =BU13+1 -> 7203.2 | BV14: DRY CHAMBER # 3 | BW14: =BW12 -> ….. DAY 2 ….. | BX14: RH &T & GPP | CB14: 4111.1 | CC14: . | CD14: REPLACEMENT 1 CON OVERVIEW DAY PICS, | CF14: , | CG14: ====== | CH14: =CH13+1 -> 70111 | CI14: . | CJ14: =R14 -> BR1 Closet | CK14: , | CL14: =T14 -> LOS / TRAVEL | CM14: , | CN14: =CN13 -> … DAY # 0 … MC READINGS STABILIZATION | CP14: =R15 -> Bedroom 2 | CQ14: =T15 -> ….........
A15: =R15 -> Bedroom 2 | B15: =P15 -> 112 | C15: =C14+1 -> 212 | D15: =D14+1 -> 312 | E15: =E14+1 -> 412 | F15: =F14+1 -> 512 | G15: 812 | H15: =H14+1 -> 6112.1 | I15: =I14+1 -> 6212.2 | J15: =J14+1 -> 6312.3 | K15: =K14+1 -> 6412.4 | L15: DRY CHAMBER 4 | P15: 112 | Q15: …. | R15: Bedroom 2 | S15: , | T15: …......... | U15: =P15 -> 112 | V15: =Q15 -> …. | W15: =R15 -> Bedroom 2 | X15: =$U$2 -> = … JOB/ROOMS OVERVIEW PICS .. | Y15: =$T$15 -> …......... | Z15: =C15 -> 212 | AA15: =V15 -> …. | AB15: =W15 -> Bedroom 2 | AC15: =$Z$2 -> ….. SOURCE of LOSS PICS ….. | AD15: =$T$15 -> …......... | AE15: =D15 -> 312 | AF15: =AA15 -> …. | AG15: =AB15 -> Bedroom 2 | AH15: =$AE$2 -> ….. C.P.S. …... | AI15: =$T$15 -> …......... | AK15: =E15 -> 412 | AL15: =AF15 -> …. | AM15: =AG15 -> Bedroom 2 | AN15: =$AK$2 -> NON SALVAGEABLE ITEMS | AO15: =$T$15 -> …......... | AP15: =F15 -> 512 | AQ15: …. | AR15: =AM15 -> Bedroom 2 | AS15: =AS14 -> ,,,,,, DMO = DEMOLITION ….... | AT15: =T15 -> …......... | AU15: =G15 -> 812 | AV15: . | AW15: =AM15 -> Bedroom 2 | AX15: =AX14 -> … MITIGATION EQUIPMENT & W.I.P . ... | AY15: =$T$15 -> …......... | AZ15: =H15 -> 6112.1 | BA15: . | BB15: =AW15 -> Bedroom 2 | BC15: =BC14 -> ... DAY1 MC READINGS .. | BE15: =$T$15 -> …......... | BF15: =I15 -> 6212.2 | BG15: . | BH15: =BB15 -> Bedroom 2 | BI15: =BI14 -> ... DAY2 MC READINGS .. | BJ15: =$T$15 -> …......... | BK15: =J15 -> 6312.3 | BL15: . | BM15: =BH15 -> Bedroom 2 | BN15: =BN14 -> ... DAY3 MC READINGS .. | BO15: =$T$15 -> …......... | BP15: =K15 -> 6412.4 | BQ15: . | BR15: =BM15 -> Bedroom 2 | BS15: =BS14 -> ... DAY4 MC READINGS | BT15: =$T$15 -> …......... | BU15: =BU14+1 -> 7204.2 | BV15: DRY CHAMBER # 4 | BW15: =BW13 -> ….. DAY 2 ….. | BX15: RH &T & GPP | CB15: 4222.2 | CC15: . | CD15: REPLACEMENT 2 CON WIP, | CF15: , | CH15: =CH14+1 -> 70112 | CI15: . | CJ15: =R15 -> Bedroom 2 | CK15: , | CL15: =T15 -> …......... | CM15: , | CN15: =CN14 -> … DAY # 0 … MC READINGS STABILIZATION | CP15: =R16 -> BR2 Closet, | CQ15: =T16 -> LOS / TRAVEL
A16: =R16 -> BR2 Closet, | B16: =P16 -> 113 | C16: =C15+1 -> 213 | D16: =D15+1 -> 313 | E16: =E15+1 -> 413 | F16: =F15+1 -> 513 | G16: 813 | H16: =H15+1 -> 6113.1 | I16: =I15+1 -> 6213.2 | J16: =J15+1 -> 6313.3 | K16: =K15+1 -> 6413.4 | L16: =L14+1 -> 7104.1 | M16: =M14+1 -> 7204.2 | N16: =N14+1 -> 7304.3 | O16: =O14+1 -> 7404.4 | P16: 113 | Q16: …. | R16: BR2 Closet, | S16: , | T16: LOS / TRAVEL | U16: =P16 -> 113 | V16: =Q16 -> …. | W16: =R16 -> BR2 Closet, | X16: =$U$2 -> = … JOB/ROOMS OVERVIEW PICS .. | Y16: =$T$16 -> LOS / TRAVEL | Z16: =C16 -> 213 | AA16: =V16 -> …. | AB16: =W16 -> BR2 Closet, | AC16: =$Z$2 -> ….. SOURCE of LOSS PICS ….. | AD16: =$T$16 -> LOS / TRAVEL | AE16: =D16 -> 313 | AF16: =AA16 -> …. | AG16: =AB16 -> BR2 Closet, | AH16: =$AE$2 -> ….. C.P.S. …... | AI16: =$T$16 -> LOS / TRAVEL | AK16: =E16 -> 413 | AL16: =AF16 -> …. | AM16: =AG16 -> BR2 Closet, | AN16: =$AK$2 -> NON SALVAGEABLE ITEMS | AO16: =$T$16 -> LOS / TRAVEL | AP16: =F16 -> 513 | AQ16: …. | AR16: =AM16 -> BR2 Closet, | AS16: =AS15 -> ,,,,,, DMO = DEMOLITION ….... | AT16: =T16 -> LOS / TRAVEL | AU16: =G16 -> 813 | AV16: . | AW16: =AM16 -> BR2 Closet, | AX16: =AX15 -> … MITIGATION EQUIPMENT & W.I.P . ... | AY16: =$T$16 -> LOS / TRAVEL | AZ16: =H16 -> 6113.1 | BA16: . | BB16: =AW16 -> BR2 Closet, | BC16: =BC15 -> ... DAY1 MC READINGS .. | BE16: =$T$16 -> LOS / TRAVEL | BF16: =I16 -> 6213.2 | BG16: . | BH16: =BB16 -> BR2 Closet, | BI16: =BI15 -> ... DAY2 MC READINGS .. | BJ16: =$T$16 -> LOS / TRAVEL | BK16: =J16 -> 6313.3 | BL16: . | BM16: =BH16 -> BR2 Closet, | BN16: =BN15 -> ... DAY3 MC READINGS .. | BO16: =$T$16 -> LOS / TRAVEL | BP16: =K16 -> 6413.4 | BQ16: . | BR16: =BM16 -> BR2 Closet, | BS16: =BS15 -> ... DAY4 MC READINGS | BT16: =$T$16 -> LOS / TRAVEL | BU16: =BU15+1 -> 7205.2 | BV16: DRY CHAMBER # 5 | BW16: =BW14 -> ….. DAY 2 ….. | BX16: RH &T & GPP | CB16: 4333.3 | CC16: . | CD16: REPLACEMENT 3 CON STORAGE | CF16: , | CH16: =CH15+1 -> 70113 | CI16: . | CJ16: =R16 -> BR2 Closet, | CK16: , | CL16: =T16 -> LOS / TRAVEL | CM16: , | CN16: =CN15 -> … DAY # 0 … MC READINGS STABILIZATION | CP16: =R17 -> 0 | CQ16: =T17 -> ….........
A17: =R17 -> 0 | B17: =P17 -> 114 | C17: =C16+1 -> 214 | D17: =D16+1 -> 314 | E17: =E16+1 -> 414 | F17: =F16+1 -> 514 | G17: 814 | H17: =H16+1 -> 6114.1 | I17: =I16+1 -> 6214.2 | J17: =J16+1 -> 6314.3 | K17: =K16+1 -> 6414.4 | L17: DRY CHAMBER 5 | P17: 114 | Q17: …. | S17: , | T17: …......... | U17: =P17 -> 114 | V17: =Q17 -> …. | W17: =R17 -> 0 | X17: =$U$2 -> = … JOB/ROOMS OVERVIEW PICS .. | Y17: =$T$17 -> …......... | Z17: =C17 -> 214 | AA17: =V17 -> …. | AB17: =W17 -> 0 | AC17: =$Z$2 -> ….. SOURCE of LOSS PICS ….. | AD17: =$T$17 -> …......... | AE17: =D17 -> 314 | AF17: =AA17 -> …. | AG17: =AB17 -> 0 | AH17: =$AE$2 -> ….. C.P.S. …... | AI17: =$T$17 -> …......... | AK17: =E17 -> 414 | AL17: =AF17 -> …. | AM17: =AG17 -> 0 | AN17: =$AK$2 -> NON SALVAGEABLE ITEMS | AO17: =$T$17 -> …......... | AP17: =F17 -> 514 | AQ17: …. | AR17: =AM17 -> 0 | AS17: =AS16 -> ,,,,,, DMO = DEMOLITION ….... | AT17: =T17 -> …......... | AU17: =G17 -> 814 | AV17: . | AW17: =AM17 -> 0 | AX17: =AX16 -> … MITIGATION EQUIPMENT & W.I.P . ... | AY17: =$T$17 -> …......... | AZ17: =H17 -> 6114.1 | BA17: . | BB17: =AW17 -> 0 | BC17: =BC16 -> ... DAY1 MC READINGS .. | BE17: =$T$17 -> …......... | BF17: =I17 -> 6214.2 | BG17: . | BH17: =BB17 -> 0 | BI17: =BI16 -> ... DAY2 MC READINGS .. | BJ17: =$T$17 -> …......... | BK17: =J17 -> 6314.3 | BL17: . | BM17: =BH17 -> 0 | BN17: =BN16 -> ... DAY3 MC READINGS .. | BO17: =$T$17 -> …......... | BP17: =K17 -> 6414.4 | BQ17: . | BR17: =BM17 -> 0 | BS17: =BS16 -> ... DAY4 MC READINGS | BT17: =$T$17 -> …......... | BU17: 7300 | BV17: =BV4 -> RH &T & GPP DRY CHAMBERS [DC] .READ INGS =========== | BW17: ….. DAY 3 ….. | CB17: 4444.4 | CC17: . | CD17: REPLACEMENT 4 CON DISPOSAL, | CF17: , | CH17: =CH16+1 -> 70114 | CI17: . | CJ17: =R17 -> 0 | CK17: , | CL17: =T17 -> …......... | CM17: , | CN17: =CN16 -> … DAY # 0 … MC READINGS STABILIZATION | CP17: =R18 -> 0 | CQ17: =T18 -> ….........
A18: =R18 -> 0 | B18: =P18 -> 115 | C18: =C17+1 -> 215 | D18: =D17+1 -> 315 | E18: =E17+1 -> 415 | F18: =F17+1 -> 515 | G18: 815 | H18: =H17+1 -> 6115.1 | I18: =I17+1 -> 6215.2 | J18: =J17+1 -> 6315.3 | K18: =K17+1 -> 6415.4 | L18: =L16+1 -> 7105.1 | M18: =M16+1 -> 7205.2 | N18: =N16+1 -> 7305.3 | O18: =O16+1 -> 7405.4 | P18: 115 | Q18: …. | S18: , | T18: …......... | U18: =P18 -> 115 | V18: =Q18 -> …. | W18: =R18 -> 0 | X18: =$U$2 -> = … JOB/ROOMS OVERVIEW PICS .. | Y18: =$T$18 -> …......... | Z18: =C18 -> 215 | AA18: =V18 -> …. | AB18: =W18 -> 0 | AC18: =$Z$2 -> ….. SOURCE of LOSS PICS ….. | AD18: =$T$18 -> …......... | AE18: =D18 -> 315 | AF18: =AA18 -> …. | AG18: =AB18 -> 0 | AH18: =$AE$2 -> ….. C.P.S. …... | AI18: =$T$18 -> …......... | AK18: =E18 -> 415 | AL18: =AF18 -> …. | AM18: =AG18 -> 0 | AN18: =$AK$2 -> NON SALVAGEABLE ITEMS | AO18: =$T$18 -> …......... | AP18: =F18 -> 515 | AQ18: …. | AR18: =AM18 -> 0 | AS18: =AS17 -> ,,,,,, DMO = DEMOLITION ….... | AT18: =T18 -> …......... | AU18: =G18 -> 815 | AV18: . | AW18: =AM18 -> 0 | AX18: =AX17 -> … MITIGATION EQUIPMENT & W.I.P . ... | AY18: =$T$18 -> …......... | AZ18: =H18 -> 6115.1 | BA18: . | BB18: =AW18 -> 0 | BC18: =BC17 -> ... DAY1 MC READINGS .. | BE18: =$T$18 -> …......... | BF18: =I18 -> 6215.2 | BG18: . | BH18: =BB18 -> 0 | BI18: =BI17 -> ... DAY2 MC READINGS .. | BJ18: =$T$18 -> …......... | BK18: =J18 -> 6315.3 | BL18: . | BM18: =BH18 -> 0 | BN18: =BN17 -> ... DAY3 MC READINGS .. | BO18: =$T$18 -> …......... | BP18: =K18 -> 6415.4 | BQ18: . | BR18: =BM18 -> 0 | BS18: =BS17 -> ... DAY4 MC READINGS | BT18: =$T$18 -> …......... | BU18: =BU17 -> 7300 | BV18: EXTERIOR & UNAFFECTED AREA | BW18: =BW17 -> ….. DAY 3 ….. | CB18: 9998 | CC18: . | CD18: REBUILD OVERVIEW WORK IN PROGRESS.......WIP, | CF18: , | CG18: ====== | CH18: =CH17+1 -> 70115 | CI18: . | CJ18: =R19 -> 0 | CK18: , | CL18: =T18 -> …......... | CM18: , | CN18: =CN17 -> … DAY # 0 … MC READINGS STABILIZATION | CP18: =R19 -> 0 | CQ18: =T19 -> ….........
A19: =R19 -> 0 | B19: =P19 -> 116 | C19: =C18+1 -> 216 | D19: =D18+1 -> 316 | E19: =E18+1 -> 416 | F19: =F18+1 -> 516 | G19: 816 | H19: =H18+1 -> 6116.1 | I19: =I18+1 -> 6216.2 | J19: =J18+1 -> 6316.3 | K19: =K18+1 -> 6416.4 | P19: 116 | Q19: …. | S19: , | T19: …......... | U19: =P19 -> 116 | V19: =Q19 -> …. | W19: =R19 -> 0 | X19: =$U$2 -> = … JOB/ROOMS OVERVIEW PICS .. | Y19: =$T$19 -> …......... | Z19: =C19 -> 216 | AA19: =V19 -> …. | AB19: =W19 -> 0 | AC19: =$Z$2 -> ….. SOURCE of LOSS PICS ….. | AD19: =$T$19 -> …......... | AE19: =D19 -> 316 | AF19: =AA19 -> …. | AG19: =AB19 -> 0 | AH19: =$AE$2 -> ….. C.P.S. …... | AI19: =$T$19 -> …......... | AK19: =E19 -> 416 | AL19: =AF19 -> …. | AM19: =AG19 -> 0 | AN19: =$AK$2 -> NON SALVAGEABLE ITEMS | AO19: =$T$19 -> …......... | AP19: =F19 -> 516 | AQ19: …. | AR19: =AM19 -> 0 | AS19: =AS18 -> ,,,,,, DMO = DEMOLITION ….... | AT19: =T19 -> …......... | AU19: =G19 -> 816 | AV19: . | AW19: =AM19 -> 0 | AX19: =AX18 -> … MITIGATION EQUIPMENT & W.I.P . ... | AY19: =$T$19 -> …......... | AZ19: =H19 -> 6116.1 | BA19: . | BB19: =AW19 -> 0 | BC19: =BC18 -> ... DAY1 MC READINGS .. | BE19: =$T$19 -> …......... | BF19: =I19 -> 6216.2 | BG19: . | BH19: =BB19 -> 0 | BI19: =BI18 -> ... DAY2 MC READINGS .. | BJ19: =$T$19 -> …......... | BK19: =J19 -> 6316.3 | BL19: . | BM19: =BH19 -> 0 | BN19: =BN18 -> ... DAY3 MC READINGS .. | BO19: =$T$19 -> …......... | BP19: =K19 -> 6416.4 | BQ19: . | BR19: =BM19 -> 0 | BS19: =BS18 -> ... DAY4 MC READINGS | BT19: =$T$19 -> …......... | BU19: =BU18+1 -> 7301 | BV19: DRY CHAMBER # 1 | BW19: =BW18 -> ….. DAY 3 ….. | BX19: RH &T & GPP | CB19: 9999 | CC19: . | CD19: REBUILD INTERIOR COMPLETED WORK, | CF19: , | CH19: =CH18+1 -> 70116 | CJ19: =R20 -> 0 | CK19: , | CL19: =T19 -> …......... | CM19: , | CN19: =CN18 -> … DAY # 0 … MC READINGS STABILIZATION | CP19: =R20 -> 0 | CQ19: =T20 -> ….........
A20: =R20 -> 0 | B20: =P20 -> 117 | C20: =C19+1 -> 217 | D20: =D19+1 -> 317 | E20: =E19+1 -> 417 | F20: =F19+1 -> 517 | G20: 817 | H20: =H19+1 -> 6117.1 | I20: =I19+1 -> 6217.2 | J20: =J19+1 -> 6317.3 | K20: =K19+1 -> 6417.4 | P20: 117 | Q20: …. | S20: , | T20: …......... | U20: =P20 -> 117 | V20: =Q20 -> …. | W20: =R20 -> 0 | X20: =$U$2 -> = … JOB/ROOMS OVERVIEW PICS .. | Y20: =$T$20 -> …......... | Z20: =C20 -> 217 | AA20: =V20 -> …. | AB20: =W20 -> 0 | AC20: =$Z$2 -> ….. SOURCE of LOSS PICS ….. | AD20: =$T$20 -> …......... | AE20: =D20 -> 317 | AF20: =AA20 -> …. | AG20: =AB20 -> 0 | AH20: =$AE$2 -> ….. C.P.S. …... | AI20: =$T$20 -> …......... | AK20: =E20 -> 417 | AL20: =AF20 -> …. | AM20: =AG20 -> 0 | AN20: =$AK$2 -> NON SALVAGEABLE ITEMS | AO20: =$T$20 -> …......... | AP20: =F20 -> 517 | AQ20: …. | AR20: =AM20 -> 0 | AS20: =AS19 -> ,,,,,, DMO = DEMOLITION ….... | AT20: =T20 -> …......... | AU20: =G20 -> 817 | AV20: . | AW20: =AM20 -> 0 | AX20: =AX19 -> … MITIGATION EQUIPMENT & W.I.P . ... | AY20: =$T$20 -> …......... | AZ20: =H20 -> 6117.1 | BA20: . | BB20: =AW20 -> 0 | BC20: =BC19 -> ... DAY1 MC READINGS .. | BE20: =$T$20 -> …......... | BF20: =I20 -> 6217.2 | BG20: . | BH20: =BB20 -> 0 | BI20: =BI19 -> ... DAY2 MC READINGS .. | BJ20: =$T$20 -> …......... | BK20: =J20 -> 6317.3 | BL20: . | BM20: =BH20 -> 0 | BN20: =BN19 -> ... DAY3 MC READINGS .. | BO20: =$T$20 -> …......... | BP20: =K20 -> 6417.4 | BQ20: . | BR20: =BM20 -> 0 | BS20: =BS19 -> ... DAY4 MC READINGS | BT20: =$T$20 -> …......... | BU20: =BU19+1 -> 7302 | BV20: DRY CHAMBER # 2 | BW20: =BW19 -> ….. DAY 3 ….. | BX20: RH &T & GPP | CF20: , | CH20: =CH19+1 -> 70117 | CI20: ---------------- | CJ20: =R21 -> 0 | CK20: , | CL20: =T20 -> …......... | CM20: , | CN20: =CN19 -> … DAY # 0 … MC READINGS STABILIZATION | CP20: =R21 -> 0 | CQ20: =T21 -> ….........
A21: =R21 -> 0 | B21: =P21 -> 118 | C21: =C20+1 -> 218 | D21: =D20+1 -> 318 | E21: =E20+1 -> 418 | F21: =F20+1 -> 518 | G21: 818 | H21: =H20+1 -> 6118.1 | I21: =I20+1 -> 6218.2 | J21: =J20+1 -> 6318.3 | K21: =K20+1 -> 6418.4 | P21: 118 | Q21: …. | S21: , | T21: …......... | U21: =P21 -> 118 | V21: =Q21 -> …. | W21: =R21 -> 0 | X21: =$U$2 -> = … JOB/ROOMS OVERVIEW PICS .. | Y21: =$T$21 -> …......... | Z21: =C21 -> 218 | AA21: =V21 -> …. | AB21: =W21 -> 0 | AC21: =$Z$2 -> ….. SOURCE of LOSS PICS ….. | AD21: =$T$21 -> …......... | AE21: =D21 -> 318 | AF21: =AA21 -> …. | AG21: =AB21 -> 0 | AH21: =$AE$2 -> ….. C.P.S. …... | AI21: =$T$21 -> …......... | AK21: =E21 -> 418 | AL21: =AF21 -> …. | AM21: =AG21 -> 0 | AN21: =$AK$2 -> NON SALVAGEABLE ITEMS | AO21: =$T$21 -> …......... | AP21: =F21 -> 518 | AQ21: …. | AR21: =AM21 -> 0 | AS21: =AS20 -> ,,,,,, DMO = DEMOLITION ….... | AT21: =T21 -> …......... | AU21: =G21 -> 818 | AV21: . | AW21: =AM21 -> 0 | AX21: =AX20 -> … MITIGATION EQUIPMENT & W.I.P . ... | AY21: =$T$21 -> …......... | AZ21: =H21 -> 6118.1 | BA21: . | BB21: =AW21 -> 0 | BC21: =BC20 -> ... DAY1 MC READINGS .. | BE21: =$T$21 -> …......... | BF21: =I21 -> 6218.2 | BG21: . | BH21: =BB21 -> 0 | BI21: =BI20 -> ... DAY2 MC READINGS .. | BJ21: =$T$21 -> …......... | BK21: =J21 -> 6318.3 | BL21: . | BM21: =BH21 -> 0 | BN21: =BN20 -> ... DAY3 MC READINGS .. | BO21: =$T$21 -> …......... | BP21: =K21 -> 6418.4 | BQ21: . | BR21: =BM21 -> 0 | BS21: =BS20 -> ... DAY4 MC READINGS | BT21: =$T$21 -> …......... | BU21: =BU20+1 -> 7303 | BV21: DRY CHAMBER # 3 | BW21: =BW19 -> ….. DAY 3 ….. | BX21: RH &T & GPP | CF21: , | CH21: =CH20+1 -> 70118 | CI21: ….. DAY 1 ….. | CJ21: =R22 -> 0 | CK21: , | CL21: =T21 -> …......... | CM21: , | CN21: =CN20 -> … DAY # 0 … MC READINGS STABILIZATION | CP21: =R22 -> 0 | CQ21: =T22 -> ….........
A22: =R22 -> 0 | B22: =P22 -> 119 | C22: =C21+1 -> 219 | D22: =D21+1 -> 319 | E22: =E21+1 -> 419 | F22: =F21+1 -> 519 | G22: 819 | H22: =H21+1 -> 6119.1 | I22: =I21+1 -> 6219.2 | J22: =J21+1 -> 6319.3 | K22: =K21+1 -> 6419.4 | P22: 119 | Q22: …. | S22: , | T22: …......... | U22: =P22 -> 119 | V22: =Q22 -> …. | W22: =R22 -> 0 | X22: =$U$2 -> = … JOB/ROOMS OVERVIEW PICS .. | Y22: =$T$22 -> …......... | Z22: =C22 -> 219 | AA22: =V22 -> …. | AB22: =W22 -> 0 | AC22: =$Z$2 -> ….. SOURCE of LOSS PICS ….. | AD22: =$T$22 -> …......... | AE22: =D22 -> 319 | AF22: =AA22 -> …. | AG22: =AB22 -> 0 | AH22: =$AE$2 -> ….. C.P.S. …... | AI22: =$T$22 -> …......... | AK22: =E22 -> 419 | AL22: =AF22 -> …. | AM22: =AG22 -> 0 | AN22: =$AK$2 -> NON SALVAGEABLE ITEMS | AO22: =$T$22 -> …......... | AP22: =F22 -> 519 | AQ22: …. | AR22: =AM22 -> 0 | AS22: =AS21 -> ,,,,,, DMO = DEMOLITION ….... | AT22: =T22 -> …......... | AU22: =G22 -> 819 | AV22: . | AW22: =AM22 -> 0 | AX22: =AX21 -> … MITIGATION EQUIPMENT & W.I.P . ... | AY22: =$T$22 -> …......... | AZ22: =H22 -> 6119.1 | BA22: . | BB22: =AW22 -> 0 | BC22: =BC21 -> ... DAY1 MC READINGS .. | BE22: =$T$22 -> …......... | BF22: =I22 -> 6219.2 | BG22: . | BH22: =BB22 -> 0 | BI22: =BI21 -> ... DAY2 MC READINGS .. | BJ22: =$T$22 -> …......... | BK22: =J22 -> 6319.3 | BL22: . | BM22: =BH22 -> 0 | BN22: =BN21 -> ... DAY3 MC READINGS .. | BO22: =$T$22 -> …......... | BP22: =K22 -> 6419.4 | BQ22: . | BR22: =BM22 -> 0 | BS22: =BS21 -> ... DAY4 MC READINGS | BT22: =$T$22 -> …......... | BU22: =BU21+1 -> 7304 | BV22: DRY CHAMBER # 4 | BW22: =BW20 -> ….. DAY 3 ….. | BX22: RH &T & GPP | CF22: , | CH22: =CH21+1 -> 70119 | CI22: ….. DAY 1 ….. | CJ22: =R23 -> 0 | CK22: , | CL22: =T22 -> …......... | CM22: , | CN22: =CN21 -> … DAY # 0 … MC READINGS STABILIZATION | CP22: =R23 -> 0 | CQ22: =T23 -> ….........
A23: =R23 -> 0 | B23: =P23 -> 120 | C23: =C22+1 -> 220 | D23: =D22+1 -> 320 | E23: =E22+1 -> 420 | F23: =F22+1 -> 520 | G23: 820 | H23: =H22+1 -> 6120.1 | I23: =I22+1 -> 6220.2 | J23: =J22+1 -> 6320.3 | K23: =K22+1 -> 6420.4 | P23: 120 | Q23: …. | S23: , | T23: …......... | U23: =P23 -> 120 | V23: =Q23 -> …. | W23: =R23 -> 0 | X23: =$U$2 -> = … JOB/ROOMS OVERVIEW PICS .. | Y23: =$T$23 -> …......... | Z23: =C23 -> 220 | AA23: =V23 -> …. | AB23: =W23 -> 0 | AC23: =$Z$2 -> ….. SOURCE of LOSS PICS ….. | AD23: =$T$23 -> …......... | AE23: =D23 -> 320 | AF23: =AA23 -> …. | AG23: =AB23 -> 0 | AH23: =$AE$2 -> ….. C.P.S. …... | AI23: =$T$23 -> …......... | AK23: =E23 -> 420 | AL23: =AF23 -> …. | AM23: =AG23 -> 0 | AN23: =$AK$2 -> NON SALVAGEABLE ITEMS | AO23: =$T$23 -> …......... | AP23: =F23 -> 520 | AQ23: …. | AR23: =AM23 -> 0 | AS23: =AS22 -> ,,,,,, DMO = DEMOLITION ….... | AT23: =T23 -> …......... | AU23: =G23 -> 820 | AV23: . | AW23: =AM23 -> 0 | AX23: =AX22 -> … MITIGATION EQUIPMENT & W.I.P . ... | AY23: =$T$23 -> …......... | AZ23: =H23 -> 6120.1 | BA23: . | BB23: =AW23 -> 0 | BC23: =BC22 -> ... DAY1 MC READINGS .. | BE23: =$T$23 -> …......... | BF23: =I23 -> 6220.2 | BG23: . | BH23: =BB23 -> 0 | BI23: =BI22 -> ... DAY2 MC READINGS .. | BJ23: =$T$23 -> …......... | BK23: =J23 -> 6320.3 | BL23: . | BM23: =BH23 -> 0 | BN23: =BN22 -> ... DAY3 MC READINGS .. | BO23: =$T$23 -> …......... | BP23: =K23 -> 6420.4 | BQ23: . | BR23: =BM23 -> 0 | BS23: =BS22 -> ... DAY4 MC READINGS | BT23: =$T$23 -> …......... | BU23: 7400 | BV23: =BV17 -> RH &T & GPP DRY CHAMBERS [DC] .READ INGS =========== | BW23: ….. DAY 4 ….. | CF23: , | CH23: =CH22+1 -> 70120 | CI23: ….. DAY 1 ….. | CJ23: =R24 -> 0 | CK23: , | CL23: =T23 -> …......... | CM23: , | CN23: =CN22 -> … DAY # 0 … MC READINGS STABILIZATION | CP23: =R24 -> 0 | CQ23: =T24 -> ….........
A24: =R24 -> 0 | B24: =P24 -> 121 | C24: =C23+1 -> 221 | D24: =D23+1 -> 321 | E24: =E23+1 -> 421 | F24: =F23+1 -> 521 | G24: 821 | H24: =H23+1 -> 6121.1 | I24: =I23+1 -> 6221.2 | J24: =J23+1 -> 6321.3 | K24: =K23+1 -> 6421.4 | P24: 121 | Q24: …. | S24: , | T24: …......... | U24: =P24 -> 121 | V24: =Q24 -> …. | W24: =R24 -> 0 | X24: =$U$2 -> = … JOB/ROOMS OVERVIEW PICS .. | Y24: =$T$24 -> …......... | Z24: =C24 -> 221 | AA24: =V24 -> …. | AB24: =W24 -> 0 | AC24: =$Z$2 -> ….. SOURCE of LOSS PICS ….. | AD24: =$T$24 -> …......... | AE24: =D24 -> 321 | AF24: =AA24 -> …. | AG24: =AB24 -> 0 | AH24: =$AE$2 -> ….. C.P.S. …... | AI24: =$T$24 -> …......... | AK24: =E24 -> 421 | AL24: =AF24 -> …. | AM24: =AG24 -> 0 | AN24: =$AK$2 -> NON SALVAGEABLE ITEMS | AO24: =$T$24 -> …......... | AP24: =F24 -> 521 | AQ24: …. | AR24: =AM24 -> 0 | AS24: =AS23 -> ,,,,,, DMO = DEMOLITION ….... | AT24: =T24 -> …......... | AU24: =G24 -> 821 | AV24: . | AW24: =AM24 -> 0 | AX24: =AX23 -> … MITIGATION EQUIPMENT & W.I.P . ... | AY24: =$T$24 -> …......... | AZ24: =H24 -> 6121.1 | BA24: . | BB24: =AW24 -> 0 | BC24: =BC23 -> ... DAY1 MC READINGS .. | BE24: =$T$24 -> …......... | BF24: =I24 -> 6221.2 | BG24: . | BH24: =BB24 -> 0 | BI24: =BI23 -> ... DAY2 MC READINGS .. | BJ24: =$T$24 -> …......... | BK24: =J24 -> 6321.3 | BL24: . | BM24: =BH24 -> 0 | BN24: =BN23 -> ... DAY3 MC READINGS .. | BO24: =$T$24 -> …......... | BP24: =K24 -> 6421.4 | BQ24: . | BR24: =BM24 -> 0 | BS24: =BS23 -> ... DAY4 MC READINGS | BT24: =$T$24 -> …......... | BU24: 7400 | BV24: EXTERIOR & UNAFFECTED AREA | BW24: ….. DAY 4 ….. | CF24: , | CH24: =CH23+1 -> 70121 | CI24: ….. DAY 1 ….. | CJ24: =R25 -> 0 | CK24: , | CL24: =T24 -> …......... | CM24: , | CN24: =CN23 -> … DAY # 0 … MC READINGS STABILIZATION | CP24: =R25 -> 0 | CQ24: =T25 -> ….........
A25: =R25 -> 0 | B25: =P25 -> 122 | C25: =C24+1 -> 222 | D25: =D24+1 -> 322 | E25: =E24+1 -> 422 | F25: =F24+1 -> 522 | G25: 822 | H25: =H24+1 -> 6122.1 | I25: =I24+1 -> 6222.2 | J25: =J24+1 -> 6322.3 | K25: =K24+1 -> 6422.4 | P25: 122 | Q25: …. | S25: , | T25: …......... | U25: =P25 -> 122 | V25: =Q25 -> …. | W25: =R25 -> 0 | X25: =$U$2 -> = … JOB/ROOMS OVERVIEW PICS .. | Y25: =$T$25 -> …......... | Z25: =C25 -> 222 | AA25: =V25 -> …. | AB25: =W25 -> 0 | AC25: =$Z$2 -> ….. SOURCE of LOSS PICS ….. | AD25: =$T$25 -> …......... | AE25: =D25 -> 322 | AF25: =AA25 -> …. | AG25: =AB25 -> 0 | AH25: =$AE$2 -> ….. C.P.S. …... | AI25: =$T$25 -> …......... | AK25: =E25 -> 422 | AL25: =AF25 -> …. | AM25: =AG25 -> 0 | AN25: =$AK$2 -> NON SALVAGEABLE ITEMS | AO25: =$T$25 -> …......... | AP25: =F25 -> 522 | AQ25: …. | AR25: =AM25 -> 0 | AS25: =AS24 -> ,,,,,, DMO = DEMOLITION ….... | AT25: =T25 -> …......... | AU25: =G25 -> 822 | AV25: . | AW25: =AM25 -> 0 | AX25: =AX24 -> … MITIGATION EQUIPMENT & W.I.P . ... | AY25: =$T$25 -> …......... | AZ25: =H25 -> 6122.1 | BA25: . | BB25: =AW25 -> 0 | BC25: =BC24 -> ... DAY1 MC READINGS .. | BE25: =$T$25 -> …......... | BF25: =I25 -> 6222.2 | BG25: . | BH25: =BB25 -> 0 | BI25: =BI24 -> ... DAY2 MC READINGS .. | BJ25: =$T$25 -> …......... | BK25: =J25 -> 6322.3 | BL25: . | BM25: =BH25 -> 0 | BN25: =BN24 -> ... DAY3 MC READINGS .. | BO25: =$T$25 -> …......... | BP25: =K25 -> 6422.4 | BQ25: . | BR25: =BM25 -> 0 | BS25: =BS24 -> ... DAY4 MC READINGS | BT25: =$T$25 -> …......... | BU25: =BU24+1 -> 7401 | BV25: DRY CHAMBER # 1 | BW25: =BW24 -> ….. DAY 4 ….. | BX25: RH &T & GPP | CF25: , | CH25: =CH24+1 -> 70122 | CI25: ….. DAY 1 ….. | CJ25: =R26 -> 0 | CK25: , | CL25: =T25 -> …......... | CM25: , | CN25: =CN24 -> … DAY # 0 … MC READINGS STABILIZATION | CP25: =R26 -> 0 | CQ25: =T26 -> ….........
A26: =R26 -> 0 | B26: =P26 -> 123 | C26: =C25+1 -> 223 | D26: =D25+1 -> 323 | E26: =E25+1 -> 423 | F26: =F25+1 -> 523 | G26: 823 | H26: =H25+1 -> 6123.1 | I26: =I25+1 -> 6223.2 | J26: =J25+1 -> 6323.3 | K26: =K25+1 -> 6423.4 | P26: 123 | Q26: …. | S26: , | T26: …......... | U26: =P26 -> 123 | V26: =Q26 -> …. | W26: =R26 -> 0 | X26: =$U$2 -> = … JOB/ROOMS OVERVIEW PICS .. | Y26: =$T$26 -> …......... | Z26: =C26 -> 223 | AA26: =V26 -> …. | AB26: =W26 -> 0 | AC26: =$Z$2 -> ….. SOURCE of LOSS PICS ….. | AD26: =$T$26 -> …......... | AE26: =D26 -> 323 | AF26: =AA26 -> …. | AG26: =AB26 -> 0 | AH26: =$AE$2 -> ….. C.P.S. …... | AI26: =$T$26 -> …......... | AK26: =E26 -> 423 | AL26: =AF26 -> …. | AM26: =AG26 -> 0 | AN26: =$AK$2 -> NON SALVAGEABLE ITEMS | AO26: =$T$26 -> …......... | AP26: =F26 -> 523 | AQ26: …. | AR26: =AM26 -> 0 | AS26: =AS25 -> ,,,,,, DMO = DEMOLITION ….... | AT26: =T26 -> …......... | AU26: =G26 -> 823 | AV26: . | AW26: =AM26 -> 0 | AX26: =AX25 -> … MITIGATION EQUIPMENT & W.I.P . ... | AY26: =$T$26 -> …......... | AZ26: =H26 -> 6123.1 | BA26: . | BB26: =AW26 -> 0 | BC26: =BC25 -> ... DAY1 MC READINGS .. | BE26: =$T$26 -> …......... | BF26: =I26 -> 6223.2 | BG26: . | BH26: =BB26 -> 0 | BI26: =BI25 -> ... DAY2 MC READINGS .. | BJ26: =$T$26 -> …......... | BK26: =J26 -> 6323.3 | BL26: . | BM26: =BH26 -> 0 | BN26: =BN25 -> ... DAY3 MC READINGS .. | BO26: =$T$26 -> …......... | BP26: =K26 -> 6423.4 | BQ26: . | BR26: =BM26 -> 0 | BS26: =BS25 -> ... DAY4 MC READINGS | BT26: =$T$26 -> …......... | BU26: =BU25+1 -> 7402 | BV26: DRY CHAMBER # 2 | BW26: =BW25 -> ….. DAY 4 ….. | BX26: RH &T & GPP | CF26: , | CH26: =CH25+1 -> 70123 | CI26: ….. DAY 1 ….. | CJ26: =R27 -> 0 | CK26: , | CL26: =T26 -> …......... | CM26: , | CN26: =CN25 -> … DAY # 0 … MC READINGS STABILIZATION | CP26: =R27 -> 0 | CQ26: =T27 -> ….........
A27: =R27 -> 0 | B27: =P27 -> 124 | C27: =C26+1 -> 224 | D27: =D26+1 -> 324 | E27: =E26+1 -> 424 | F27: =F26+1 -> 524 | G27: 824 | H27: =H26+1 -> 6124.1 | I27: =I26+1 -> 6224.2 | J27: =J26+1 -> 6324.3 | K27: =K26+1 -> 6424.4 | P27: 124 | Q27: …. | S27: , | T27: …......... | U27: =P27 -> 124 | V27: =Q27 -> …. | W27: =R27 -> 0 | X27: =$U$2 -> = … JOB/ROOMS OVERVIEW PICS .. | Y27: =$T$27 -> …......... | Z27: =C27 -> 224 | AA27: =V27 -> …. | AB27: =W27 -> 0 | AC27: =$Z$2 -> ….. SOURCE of LOSS PICS ….. | AD27: =$T$27 -> …......... | AE27: =D27 -> 324 | AF27: =AA27 -> …. | AG27: =AB27 -> 0 | AH27: =$AE$2 -> ….. C.P.S. …... | AI27: =$T$27 -> …......... | AK27: =E27 -> 424 | AL27: =AF27 -> …. | AM27: =AG27 -> 0 | AN27: =$AK$2 -> NON SALVAGEABLE ITEMS | AO27: =$T$27 -> …......... | AP27: =F27 -> 524 | AQ27: …. | AR27: =AM27 -> 0 | AS27: =AS26 -> ,,,,,, DMO = DEMOLITION ….... | AT27: =T27 -> …......... | AU27: =G27 -> 824 | AV27: . | AW27: =AM27 -> 0 | AX27: =AX26 -> … MITIGATION EQUIPMENT & W.I.P . ... | AY27: =$T$27 -> …......... | AZ27: =H27 -> 6124.1 | BA27: . | BB27: =AW27 -> 0 | BC27: =BC26 -> ... DAY1 MC READINGS .. | BE27: =$T$27 -> …......... | BF27: =I27 -> 6224.2 | BG27: . | BH27: =BB27 -> 0 | BI27: =BI26 -> ... DAY2 MC READINGS .. | BJ27: =$T$27 -> …......... | BK27: =J27 -> 6324.3 | BL27: . | BM27: =BH27 -> 0 | BN27: =BN26 -> ... DAY3 MC READINGS .. | BO27: =$T$27 -> …......... | BP27: =K27 -> 6424.4 | BQ27: . | BR27: =BM27 -> 0 | BS27: =BS26 -> ... DAY4 MC READINGS | BT27: =$T$27 -> …......... | BU27: =BU26+1 -> 7403 | BV27: DRY CHAMBER # 3 | BW27: =BW25 -> ….. DAY 4 ….. | BX27: RH &T & GPP | CF27: , | CH27: =CH26+1 -> 70124 | CJ27: =R28 -> 0 | CK27: , | CL27: =T27 -> …......... | CM27: , | CN27: =CN26 -> … DAY # 0 … MC READINGS STABILIZATION | CP27: =R28 -> 0 | CQ27: =T28 -> ….........
A28: =R28 -> 0 | B28: =P28 -> 125 | C28: =C27+1 -> 225 | D28: =D27+1 -> 325 | E28: =E27+1 -> 425 | F28: =F27+1 -> 525 | G28: 825 | H28: =H27+1 -> 6125.1 | I28: =I27+1 -> 6225.2 | J28: =J27+1 -> 6325.3 | K28: =K27+1 -> 6425.4 | P28: 125 | Q28: …. | S28: , | T28: …......... | U28: =P28 -> 125 | V28: =Q28 -> …. | W28: =R28 -> 0 | X28: =$U$2 -> = … JOB/ROOMS OVERVIEW PICS .. | Y28: =$T$28 -> …......... | Z28: =C28 -> 225 | AA28: =V28 -> …. | AB28: =W28 -> 0 | AC28: =$Z$2 -> ….. SOURCE of LOSS PICS ….. | AD28: =$T$28 -> …......... | AE28: =D28 -> 325 | AF28: =AA28 -> …. | AG28: =AB28 -> 0 | AH28: =$AE$2 -> ….. C.P.S. …... | AI28: =$T$28 -> …......... | AK28: =E28 -> 425 | AL28: =AF28 -> …. | AM28: =AG28 -> 0 | AN28: =$AK$2 -> NON SALVAGEABLE ITEMS | AO28: =$T$28 -> …......... | AP28: =F28 -> 525 | AQ28: …. | AR28: =AM28 -> 0 | AS28: =AS27 -> ,,,,,, DMO = DEMOLITION ….... | AT28: =T28 -> …......... | AU28: =G28 -> 825 | AV28: . | AW28: =AM28 -> 0 | AX28: =AX27 -> … MITIGATION EQUIPMENT & W.I.P . ... | AY28: =$T$28 -> …......... | AZ28: =H28 -> 6125.1 | BA28: . | BB28: =AW28 -> 0 | BC28: =BC27 -> ... DAY1 MC READINGS .. | BE28: =$T$28 -> …......... | BF28: =I28 -> 6225.2 | BG28: . | BH28: =BB28 -> 0 | BI28: =BI27 -> ... DAY2 MC READINGS .. | BJ28: =$T$28 -> …......... | BK28: =J28 -> 6325.3 | BL28: . | BM28: =BH28 -> 0 | BN28: =BN27 -> ... DAY3 MC READINGS .. | BO28: =$T$28 -> …......... | BP28: =K28 -> 6425.4 | BQ28: . | BR28: =BM28 -> 0 | BS28: =BS27 -> ... DAY4 MC READINGS | BT28: =$T$28 -> …......... | BU28: =BU27+1 -> 7404 | BV28: DRY CHAMBER # 4 | BW28: =BW26 -> ….. DAY 4 ….. | BX28: RH &T & GPP | CF28: , | CH28: =CH27+1 -> 70125 | CI28: . | CJ28: =R29 -> 0 | CK28: , | CL28: =T28 -> …......... | CM28: , | CN28: =CN27 -> … DAY # 0 … MC READINGS STABILIZATION | CP28: =R29 -> 0 | CQ28: =T29 -> 0
A29: FORMAT OF ROOM LISTS | CL29: …......... | CQ29: FCC CARPET/FCW | CR29: 20
A30: MUST BE 5 COLUMNS WIDE | U30: 103.. Dining Room ... = ROOM OVERVIEW PICS ...DAY 1 ...LOS | CJ30: Room/Area 8
CJ31: BATH UP | CN31: NA
CN32: FLOORING/STONE
CN33: WALL/PLASTER
CJ34: Room/Area 9
CJ35: Bedroom 1, | CN35: NA
CN36: FCC CARPET/FCW
CN37: WALL/PLASTER
CJ38: Room/Area 10
CJ39: Bedroom 2 | CN39: NA
CN40: FCC CARPET/FCW
CN41: WALL/PLASTER
CN42: WALL/PLASTER

Sheet ROOMS-out
A1: ='jobinfo(2)'!C51 -> OH25THOMAS@GERTRUDE | B1: ='jobinfo(2)'!C3 -> Cleveland, OH 44105 | D1: SOURCE of LOSS | F1: CPS | H1: PPR | J1: MIT | L1: MC ... READ INGS | P1: RH &T & GPP DRY CHAMBERS [DC] .READ INGS | T1: LISTS | V1: INPUT = ROOM NAMES | W1: LOS / TRAVEL | X1: OUTPUT = ROOM NAME ADD TO ENCIRCLE ROOM LISTS | AB1: LOS / TRAVEL | AC1: OUTPUT = ENC ROOM NAME | AG1: LOS / TRAVEL | AH1: OUTPUT = ENC ROOM NAME | AL1: LOS / TRAVEL | AM1: OUTPUT = ENC ROOM NAME | AN1: OUTPUT = ENC ROOM NAME | AR1: LOS / TRAVEL | AS1: … MITIGATION EQUIPMENT & W.I.P . ... | AW1: LOS / TRAVEL | AX1: ... MC READINGS .. | BC1: LOS / TRAVEL | BD1: =AX1 -> ... MC READINGS .. | BH1: LOS / TRAVEL | BI1: =AX1 -> ... MC READINGS .. | BN1: LOS / TRAVEL | BO1: =BD1 -> ... MC READINGS .. | BT1: LOS / TRAVEL | BU1: RH &T & GPP DRY CHAMBERS [DC] .READ INGS | CD1: ADD CPS OVERVIEW = MULTIPLE ROOMS / WITH LABELS
A2: ='jobinfo(2)'!C2 -> 6600 GERTRUDE | L2: DAY1 | M2: DAY2 | N2: DAY3 | O2: DAY4 | P2: DAY1 | Q2: DAY2 | R2: DAY3 | S2: DAY4 | T2: = … ROOM OVERVIEW PICS ... DAY 1 … | X2: =T2 -> = … ROOM OVERVIEW PICS ... DAY 1 … | AC2: ….. SOURCE of LOSS ….. | AH2: ….. C.P.S. …... | AN2: NON SALVAGEABLE ITEMS | AQ2: =H1 -> PPR | AS2: =J1 -> MIT | AX2: .. DAY 1 … | BD2: ….. DAY 2 ….. | BI2: ….. DAY 3 ….. | BO2: ….. DAY 4 ….. | BU2: ….. DAY 1 ….. | CB2: ROOM LABELS | CD2: KITCHEN CABINETS SIZES | CG2: BATHROOM VANITY SIZE & FIXTURES
A3: =V3 -> Living Room, | B3: =B4-1 -> 100 | D3: =D4-1 -> 200 | F3: =F4-1 -> 300 | H3: =H4-1 -> 400 | J3: =J4-1 -> 800 | L3: =L4-1 -> 6100.1 | M3: =M4-1 -> 6200.2 | N3: =N4-1 -> 6300.3 | O3: =O4-1 -> 6400.4 | T3: =T4-1 -> 100 | U3: …. | V3: Living Room, | W3: ======= | X3: =T3 -> 100 | Y3: =U3 -> …. | Z3: =X2 -> = … ROOM OVERVIEW PICS ... DAY 1 … | AB3: ====== | AC3: =D3 -> 200 | AD3: =Y3 -> …. | AE3: =AC2 -> ….. SOURCE of LOSS ….. | AF3: ==================== | AG3: ====== | AH3: =F3 -> 300 | AI3: =AD3 -> …. | AJ3: =AH2 -> ….. C.P.S. …... | AK3: ============== | AL3: ====== | AN3: =H3 -> 400 | AO3: =AI3 -> …. | AP3: =AN2 -> NON SALVAGEABLE ITEMS | AQ3: ============================== | AS3: =J3 -> 800 | AT3: . | AU3: MITIGATION EQUIPMENT & W.I.P. ================ MIT & WIP === | AW3: ============================== | AX3: =AX4-0.1 -> 6101 | AY3: . | AZ3: =AX2 -> .. DAY 1 … | BA3: …... MC READINGS … | BB3: =============== | BC3: =AX2 -> .. DAY 1 … | BD3: =BD4-0.2 -> 6201 | BE3: . | BF3: …... MC READINGS … | BG3: =============== | BH3: =BD2 -> ….. DAY 2 ….. | BI3: =BI4-0.3 -> 6301 | BJ3: . | BK3: =BI2 -> ….. DAY 3 ….. | BL3: …... MC READINGS … | BM3: =============== | BN3: =BI2 -> ….. DAY 3 ….. | BO3: =BO4-0.4 -> 6401 | BP3: . | BQ3: =BO2 -> ….. DAY 4 ….. | BR3: …... MC READINGS … | BS3: =============== | BT3: =BO2 -> ….. DAY 4 ….. | BU3: =BU5-0.1 -> 7099.9 | BV3: ---------------- | BW3: STABILIZATION READINGS | CB3: =V4 -> Living Room | CC3: =W4 -> LOS | CD3: 552 | CE3: . | CF3: CPS DAY2 WIP | CG3: OVERVIEW WIP BOXES PACKOUT PICS | CH3: ====== | CI3: ======
A4: =V4 -> Living Room | B4: =T4 -> 101 | D4: 201 | F4: 301 | H4: 401 | J4: 801 | L4: 6101.1 | M4: 6201.2 | N4: 6301.3 | O4: 6401.4 | T4: 101 | U4: …. | V4: ='ROOMS#'!R4 -> Living Room | W4: LOS | X4: =T4 -> 101 | Y4: =U4 -> …. | Z4: =V4 -> Living Room | AA4: =$X$2 -> = … ROOM OVERVIEW PICS ... DAY 1 … | AB4: =$W$4 -> LOS | AC4: =D4 -> 201 | AD4: =Y4 -> …. | AE4: =Z4 -> Living Room | AF4: =$AC$2 -> ….. SOURCE of LOSS ….. | AG4: =$W$4 -> LOS | AH4: =F4 -> 301 | AI4: =AD4 -> …. | AJ4: =AE4 -> Living Room | AK4: =$AH$2 -> ….. C.P.S. …... | AL4: =$W$4 -> LOS | AN4: =H4 -> 401 | AO4: =AI4 -> …. | AP4: =AJ4 -> Living Room | AQ4: =$AN$2 -> NON SALVAGEABLE ITEMS | AR4: =$W$4 -> LOS | AS4: =J4 -> 801 | AT4: . | AU4: =AP4 -> Living Room | AV4: =AS1 -> … MITIGATION EQUIPMENT & W.I.P . ... | AW4: =$W$4 -> LOS | AX4: =L4 -> 6101.1 | AY4: . | AZ4: =AX2 -> .. DAY 1 … | BA4: =AU4 -> Living Room | BB4: =AX1 -> ... MC READINGS .. | BC4: =$W$4 -> LOS | BD4: =M4 -> 6201.2 | BE4: . | BF4: =BA4 -> Living Room | BG4: =BD1 -> ... MC READINGS .. | BH4: =$W$4 -> LOS | BI4: =N4 -> 6301.3 | BJ4: . | BK4: =BK3 -> ….. DAY 3 ….. | BL4: =BF4 -> Living Room | BM4: =BI1 -> ... MC READINGS .. | BN4: =$W$4 -> LOS | BO4: =O4 -> 6401.4 | BP4: . | BQ4: =BQ3 -> ….. DAY 4 ….. | BR4: =BL4 -> Living Room | BS4: =BO1 -> ... MC READINGS .. | BT4: =$W$4 -> LOS | BU4: 7100 | BV4: =BU2 -> ….. DAY 1 ….. | BW4: RH &T & GPP DRY CHAMBERS [DC] .READ INGS =========== | CB4: =V5 -> GUEST CLOSET | CC4: =W5 -> LOS | CD4: 553 | CE4: . | CF4: CPS3 DAY3 STORAGE | CG4: OVERVIEW STORAGE MOVE OUT PICS
A5: =V5 -> GUEST CLOSET | B5: =T5 -> 102 | D5: =D4+1 -> 202 | F5: =F4+1 -> 302 | H5: =H4+1 -> 402 | J5: 802 | L5: =L4+1 -> 6102.1 | M5: =M4+1 -> 6202.2 | N5: =N4+1 -> 6302.3 | O5: =O4+1 -> 6402.4 | P5: STABILIZATION READINGS | T5: 102 | U5: …. | V5: ='ROOMS#'!R5 -> GUEST CLOSET | W5: LOS | X5: =T5 -> 102 | Y5: =U5 -> …. | Z5: =V5 -> GUEST CLOSET | AA5: =$X$2 -> = … ROOM OVERVIEW PICS ... DAY 1 … | AB5: =$W$5 -> LOS | AC5: =D5 -> 202 | AD5: =Y5 -> …. | AE5: =Z5 -> GUEST CLOSET | AF5: =$AC$2 -> ….. SOURCE of LOSS ….. | AG5: =$W$5 -> LOS | AH5: =F5 -> 302 | AI5: =AD5 -> …. | AJ5: =AE5 -> GUEST CLOSET | AK5: =$AH$2 -> ….. C.P.S. …... | AL5: =$W$5 -> LOS | AN5: =H5 -> 402 | AO5: =AI5 -> …. | AP5: =AJ5 -> GUEST CLOSET | AQ5: =$AN$2 -> NON SALVAGEABLE ITEMS | AR5: =$W$5 -> LOS | AS5: =J5 -> 802 | AT5: . | AU5: =AP5 -> GUEST CLOSET | AV5: =AV4 -> … MITIGATION EQUIPMENT & W.I.P . ... | AW5: =$W$5 -> LOS | AX5: =L5 -> 6102.1 | AY5: . | AZ5: =AZ4 -> .. DAY 1 … | BA5: =AU5 -> GUEST CLOSET | BB5: =BB4 -> ... MC READINGS .. | BC5: =$W$5 -> LOS | BD5: =M5 -> 6202.2 | BE5: . | BF5: =BA5 -> GUEST CLOSET | BG5: =BG4 -> ... MC READINGS .. | BH5: =$W$5 -> LOS | BI5: =N5 -> 6302.3 | BJ5: . | BK5: =BK4 -> ….. DAY 3 ….. | BL5: =BF5 -> GUEST CLOSET | BM5: =BM4 -> ... MC READINGS .. | BN5: =$W$5 -> LOS | BO5: =O5 -> 6402.4 | BP5: . | BQ5: =BQ4 -> ….. DAY 4 ….. | BR5: =BL5 -> GUEST CLOSET | BS5: =BS4 -> ... MC READINGS .. | BT5: =$W$5 -> LOS | BU5: 7100 | BV5: =BU2 -> ….. DAY 1 ….. | BW5: EXTERIOR & UNAFFECTED AREA | CB5: =V6 -> Dining Room | CC5: =W6 -> LOS | CD5: 554 | CE5: . | CF5: CPS4 DAY4 PACKBACK | CG5: OVERVIEW PACK-BACK / RESET PICS
A6: =V6 -> Dining Room | B6: =T6 -> 103 | D6: =D5+1 -> 203 | F6: =F5+1 -> 303 | H6: =H5+1 -> 403 | J6: 803 | L6: =L5+1 -> 6103.1 | M6: =M5+1 -> 6203.2 | N6: =N5+1 -> 6303.3 | O6: =O5+1 -> 6403.4 | P6: =P8-0.1 -> 7100 | Q6: =Q8-0.1 -> 7200.1 | T6: 103 | U6: …. | V6: ='ROOMS#'!R6 -> Dining Room | W6: LOS | X6: =T6 -> 103 | Y6: =U6 -> …. | Z6: =V6 -> Dining Room | AA6: =$X$2 -> = … ROOM OVERVIEW PICS ... DAY 1 … | AB6: =$W$6 -> LOS | AC6: =D6 -> 203 | AD6: =Y6 -> …. | AE6: =Z6 -> Dining Room | AF6: =$AC$2 -> ….. SOURCE of LOSS ….. | AG6: =$W$6 -> LOS | AH6: =F6 -> 303 | AI6: =AD6 -> …. | AJ6: =AE6 -> Dining Room | AK6: =$AH$2 -> ….. C.P.S. …... | AL6: =$W$6 -> LOS | AN6: =H6 -> 403 | AO6: =AI6 -> …. | AP6: =AJ6 -> Dining Room | AQ6: =$AN$2 -> NON SALVAGEABLE ITEMS | AR6: =$W$6 -> LOS | AS6: =J6 -> 803 | AT6: . | AU6: =AP6 -> Dining Room | AV6: =AV5 -> … MITIGATION EQUIPMENT & W.I.P . ... | AW6: =$W$6 -> LOS | AX6: =L6 -> 6103.1 | AY6: . | AZ6: =AZ5 -> .. DAY 1 … | BA6: =AU6 -> Dining Room | BB6: =BB5 -> ... MC READINGS .. | BC6: =$W$6 -> LOS | BD6: =M6 -> 6203.2 | BE6: . | BF6: =BA6 -> Dining Room | BG6: =BG5 -> ... MC READINGS .. | BH6: =$W$6 -> LOS | BI6: =N6 -> 6303.3 | BJ6: . | BK6: =BK5 -> ….. DAY 3 ….. | BL6: =BF6 -> Dining Room | BM6: =BM5 -> ... MC READINGS .. | BN6: =$W$6 -> LOS | BO6: =O6 -> 6403.4 | BP6: . | BQ6: =BQ5 -> ….. DAY 4 ….. | BR6: =BL6 -> Dining Room | BS6: =BS5 -> ... MC READINGS .. | BT6: =$W$6 -> LOS | BU6: =BU5+1 -> 7101 | BV6: =BV5 -> ….. DAY 1 ….. | BW6: DRY CHAMBER # 1 | BX6: RH &T & GPP | CB6: =V7 -> DEN | CC6: =W7 -> ….......... | CD6: 198 | CE6: . | CF6: KITCHEN CABINETS SIZES | CG6: U & L =LF/ CT = SF; APPLIANCES | CH6: ====== | CI6: ======
A7: =V7 -> DEN | B7: =T7 -> 104 | D7: =D6+1 -> 204 | F7: =F6+1 -> 304 | H7: =H6+1 -> 404 | J7: 804 | L7: =L6+1 -> 6104.1 | M7: =M6+1 -> 6204.2 | N7: =N6+1 -> 6304.3 | O7: =O6+1 -> 6404.4 | P7: EXTERIOR & UNAFFECTED AREA | T7: 104 | U7: …. | V7: ='ROOMS#'!R7 -> DEN | W7: ….......... | X7: =T7 -> 104 | Y7: =U7 -> …. | Z7: =V7 -> DEN | AA7: =$X$2 -> = … ROOM OVERVIEW PICS ... DAY 1 … | AB7: =$W$7 -> ….......... | AC7: =D7 -> 204 | AD7: =Y7 -> …. | AE7: =Z7 -> DEN | AF7: =$AC$2 -> ….. SOURCE of LOSS ….. | AG7: =$W$7 -> ….......... | AH7: =F7 -> 304 | AI7: =AD7 -> …. | AJ7: =AE7 -> DEN | AK7: =$AH$2 -> ….. C.P.S. …... | AL7: =$W$7 -> ….......... | AN7: =H7 -> 404 | AO7: =AI7 -> …. | AP7: =AJ7 -> DEN | AQ7: =$AN$2 -> NON SALVAGEABLE ITEMS | AR7: =$W$7 -> ….......... | AS7: =J7 -> 804 | AT7: . | AU7: =AP7 -> DEN | AV7: =AV6 -> … MITIGATION EQUIPMENT & W.I.P . ... | AW7: =$W$7 -> ….......... | AX7: =L7 -> 6104.1 | AY7: . | AZ7: =AZ6 -> .. DAY 1 … | BA7: =AU7 -> DEN | BB7: =BB6 -> ... MC READINGS .. | BC7: =$W$7 -> ….......... | BD7: =M7 -> 6204.2 | BE7: . | BF7: =BA7 -> DEN | BG7: =BG6 -> ... MC READINGS .. | BH7: =$W$7 -> ….......... | BI7: =N7 -> 6304.3 | BJ7: . | BK7: =BK6 -> ….. DAY 3 ….. | BL7: =BF7 -> DEN | BM7: =BM6 -> ... MC READINGS .. | BN7: =$W$7 -> ….......... | BO7: =O7 -> 6404.4 | BP7: . | BQ7: =BQ6 -> ….. DAY 4 ….. | BR7: =BL7 -> DEN | BS7: =BS6 -> ... MC READINGS .. | BT7: =$W$7 -> ….......... | BU7: =BU6+1 -> 7102 | BV7: =BV6 -> ….. DAY 1 ….. | BW7: DRY CHAMBER # 2 | BX7: RH &T & GPP | CB7: =V8 -> Kitchen | CC7: =W8 -> ….......... | CD7: 199 | CE7: . | CF7: BATHROOM FIXTURES | CG7: CAB SIZE & FIXTURES & TYPE | CH7: ====== | CI7: ======
A8: =V8 -> Kitchen | B8: =T8 -> 105 | D8: =D7+1 -> 205 | F8: =F7+1 -> 305 | H8: =H7+1 -> 405 | J8: 805 | L8: =L7+1 -> 6105.1 | M8: =M7+1 -> 6205.2 | N8: =N7+1 -> 6305.3 | O8: =O7+1 -> 6405.4 | P8: 7100.1 | Q8: 7200.2 | R8: 7300.3 | S8: 7400.4 | T8: 105 | U8: …. | V8: ='ROOMS#'!R8 -> Kitchen | W8: ….......... | X8: =T8 -> 105 | Y8: =U8 -> …. | Z8: =V8 -> Kitchen | AA8: =$X$2 -> = … ROOM OVERVIEW PICS ... DAY 1 … | AB8: =$W$8 -> ….......... | AC8: =D8 -> 205 | AD8: =Y8 -> …. | AE8: =Z8 -> Kitchen | AF8: =$AC$2 -> ….. SOURCE of LOSS ….. | AG8: =$W$8 -> ….......... | AH8: =F8 -> 305 | AI8: =AD8 -> …. | AJ8: =AE8 -> Kitchen | AK8: =$AH$2 -> ….. C.P.S. …... | AL8: =$W$8 -> ….......... | AN8: =H8 -> 405 | AO8: =AI8 -> …. | AP8: =AJ8 -> Kitchen | AQ8: =$AN$2 -> NON SALVAGEABLE ITEMS | AR8: =$W$8 -> ….......... | AS8: =J8 -> 805 | AT8: . | AU8: =AP8 -> Kitchen | AV8: =AV7 -> … MITIGATION EQUIPMENT & W.I.P . ... | AW8: =$W$8 -> ….......... | AX8: =L8 -> 6105.1 | AY8: . | AZ8: =AZ7 -> .. DAY 1 … | BA8: =AU8 -> Kitchen | BB8: =BB7 -> ... MC READINGS .. | BC8: =$W$8 -> ….......... | BD8: =M8 -> 6205.2 | BE8: . | BF8: =BA8 -> Kitchen | BG8: =BG7 -> ... MC READINGS .. | BH8: =$W$8 -> ….......... | BI8: =N8 -> 6305.3 | BJ8: . | BK8: =BK7 -> ….. DAY 3 ….. | BL8: =BF8 -> Kitchen | BM8: =BM7 -> ... MC READINGS .. | BN8: =$W$8 -> ….......... | BO8: =O8 -> 6405.4 | BP8: . | BQ8: =BQ7 -> ….. DAY 4 ….. | BR8: =BL8 -> Kitchen | BS8: =BS7 -> ... MC READINGS .. | BT8: =$W$8 -> ….......... | BU8: =BU7+1 -> 7103 | BV8: =BV7 -> ….. DAY 1 ….. | BW8: DRY CHAMBER # 3 | BX8: RH &T & GPP | CB8: =V9 -> STAIRS UP | CC8: =W9 -> ….......... | CE8: .
A9: =V9 -> STAIRS UP | B9: =T9 -> 106 | D9: =D8+1 -> 206 | F9: =F8+1 -> 306 | H9: =H8+1 -> 406 | J9: 806 | L9: =L8+1 -> 6106.1 | M9: =M8+1 -> 6206.2 | N9: =N8+1 -> 6306.3 | O9: =O8+1 -> 6406.4 | P9: DRY CHAMBER 1 | T9: 106 | U9: …. | V9: ='ROOMS#'!R9 -> STAIRS UP | W9: ….......... | X9: =T9 -> 106 | Y9: =U9 -> …. | Z9: =V9 -> STAIRS UP | AA9: =$X$2 -> = … ROOM OVERVIEW PICS ... DAY 1 … | AB9: =$W$9 -> ….......... | AC9: =D9 -> 206 | AD9: =Y9 -> …. | AE9: =Z9 -> STAIRS UP | AF9: =$AC$2 -> ….. SOURCE of LOSS ….. | AG9: =$W$9 -> ….......... | AH9: =F9 -> 306 | AI9: =AD9 -> …. | AJ9: =AE9 -> STAIRS UP | AK9: =$AH$2 -> ….. C.P.S. …... | AL9: =$W$9 -> ….......... | AN9: =H9 -> 406 | AO9: =AI9 -> …. | AP9: =AJ9 -> STAIRS UP | AQ9: =$AN$2 -> NON SALVAGEABLE ITEMS | AR9: =$W$9 -> ….......... | AS9: =J9 -> 806 | AT9: . | AU9: =AP9 -> STAIRS UP | AV9: =AV8 -> … MITIGATION EQUIPMENT & W.I.P . ... | AW9: =$W$9 -> ….......... | AX9: =L9 -> 6106.1 | AY9: . | AZ9: =AZ8 -> .. DAY 1 … | BA9: =AU9 -> STAIRS UP | BB9: =BB8 -> ... MC READINGS .. | BC9: =$W$9 -> ….......... | BD9: =M9 -> 6206.2 | BE9: . | BF9: =BA9 -> STAIRS UP | BG9: =BG8 -> ... MC READINGS .. | BH9: =$W$9 -> ….......... | BI9: =N9 -> 6306.3 | BJ9: . | BK9: =BK8 -> ….. DAY 3 ….. | BL9: =BF9 -> STAIRS UP | BM9: =BM8 -> ... MC READINGS .. | BN9: =$W$9 -> ….......... | BO9: =O9 -> 6406.4 | BP9: . | BQ9: =BQ8 -> ….. DAY 4 ….. | BR9: =BL9 -> STAIRS UP | BS9: =BS8 -> ... MC READINGS .. | BT9: =$W$9 -> ….......... | BU9: =BU8+1 -> 7104 | BV9: =BV8 -> ….. DAY 1 ….. | BW9: DRY CHAMBER # 4 | BX9: RH &T & GPP | CB9: =V10 -> HALL UP | CC9: =W10 -> ….......... | CE9: .
A10: =V10 -> HALL UP | B10: =T10 -> 107 | D10: =D9+1 -> 207 | F10: =F9+1 -> 307 | H10: =H9+1 -> 407 | J10: 807 | L10: =L9+1 -> 6107.1 | M10: =M9+1 -> 6207.2 | N10: =N9+1 -> 6307.3 | O10: =O9+1 -> 6407.4 | P10: =P8+1 -> 7101.1 | Q10: =Q8+1 -> 7201.2 | R10: =R8+1 -> 7301.3 | S10: =S8+1 -> 7401.4 | T10: 107 | U10: …. | V10: ='ROOMS#'!R10 -> HALL UP | W10: ….......... | X10: =T10 -> 107 | Y10: =U10 -> …. | Z10: =V10 -> HALL UP | AA10: =$X$2 -> = … ROOM OVERVIEW PICS ... DAY 1 … | AB10: =$W$10 -> ….......... | AC10: =D10 -> 207 | AD10: =Y10 -> …. | AE10: =Z10 -> HALL UP | AF10: =$AC$2 -> ….. SOURCE of LOSS ….. | AG10: =$W$10 -> ….......... | AH10: =F10 -> 307 | AI10: =AD10 -> …. | AJ10: =AE10 -> HALL UP | AK10: =$AH$2 -> ….. C.P.S. …... | AL10: =$W$10 -> ….......... | AN10: =H10 -> 407 | AO10: =AI10 -> …. | AP10: =AJ10 -> HALL UP | AQ10: =$AN$2 -> NON SALVAGEABLE ITEMS | AR10: =$W$10 -> ….......... | AS10: =J10 -> 807 | AT10: . | AU10: =AP10 -> HALL UP | AV10: =AV9 -> … MITIGATION EQUIPMENT & W.I.P . ... | AW10: =$W$10 -> ….......... | AX10: =L10 -> 6107.1 | AY10: . | AZ10: =AZ9 -> .. DAY 1 … | BA10: =AU10 -> HALL UP | BB10: =BB9 -> ... MC READINGS .. | BC10: =$W$10 -> ….......... | BD10: =M10 -> 6207.2 | BE10: . | BF10: =BA10 -> HALL UP | BG10: =BG9 -> ... MC READINGS .. | BH10: =$W$10 -> ….......... | BI10: =N10 -> 6307.3 | BJ10: . | BK10: =BK9 -> ….. DAY 3 ….. | BL10: =BF10 -> HALL UP | BM10: =BM9 -> ... MC READINGS .. | BN10: =$W$10 -> ….......... | BO10: =O10 -> 6407.4 | BP10: . | BQ10: =BQ9 -> ….. DAY 4 ….. | BR10: =BL10 -> HALL UP | BS10: =BS9 -> ... MC READINGS .. | BT10: =$W$10 -> ….......... | BU10: =BU11-0.2 -> 7200 | BV10: ….. DAY 2 ….. | BW10: =BW4 -> RH &T & GPP DRY CHAMBERS [DC] .READ INGS =========== | CB10: =V11 -> LINEN CLOSET | CC10: =W11 -> ….......... | CE10: .
A11: =V11 -> LINEN CLOSET | B11: =T11 -> 108 | D11: =D10+1 -> 208 | F11: =F10+1 -> 308 | H11: =H10+1 -> 408 | J11: 808 | L11: =L10+1 -> 6108.1 | M11: =M10+1 -> 6208.2 | N11: =N10+1 -> 6308.3 | O11: =O10+1 -> 6408.4 | P11: DRY CHAMBER 2 | T11: 108 | U11: …. | V11: ='ROOMS#'!R11 -> LINEN CLOSET | W11: ….......... | X11: =T11 -> 108 | Y11: =U11 -> …. | Z11: =V11 -> LINEN CLOSET | AA11: =$X$2 -> = … ROOM OVERVIEW PICS ... DAY 1 … | AB11: =$W$11 -> ….......... | AC11: =D11 -> 208 | AD11: =Y11 -> …. | AE11: =Z11 -> LINEN CLOSET | AF11: =$AC$2 -> ….. SOURCE of LOSS ….. | AG11: =$W$11 -> ….......... | AH11: =F11 -> 308 | AI11: =AD11 -> …. | AJ11: =AE11 -> LINEN CLOSET | AK11: =$AH$2 -> ….. C.P.S. …... | AL11: =$W$11 -> ….......... | AN11: =H11 -> 408 | AO11: =AI11 -> …. | AP11: =AJ11 -> LINEN CLOSET | AQ11: =$AN$2 -> NON SALVAGEABLE ITEMS | AR11: =$W$11 -> ….......... | AS11: =J11 -> 808 | AT11: . | AU11: =AP11 -> LINEN CLOSET | AV11: =AV10 -> … MITIGATION EQUIPMENT & W.I.P . ... | AW11: =$W$11 -> ….......... | AX11: =L11 -> 6108.1 | AY11: . | AZ11: =AZ10 -> .. DAY 1 … | BA11: =AU11 -> LINEN CLOSET | BB11: =BB10 -> ... MC READINGS .. | BC11: =$W$11 -> ….......... | BD11: =M11 -> 6208.2 | BE11: . | BF11: =BA11 -> LINEN CLOSET | BG11: =BG10 -> ... MC READINGS .. | BH11: =$W$11 -> ….......... | BI11: =N11 -> 6308.3 | BJ11: . | BK11: =BK10 -> ….. DAY 3 ….. | BL11: =BF11 -> LINEN CLOSET | BM11: =BM10 -> ... MC READINGS .. | BN11: =$W$11 -> ….......... | BO11: =O11 -> 6408.4 | BP11: . | BQ11: =BQ10 -> ….. DAY 4 ….. | BR11: =BL11 -> LINEN CLOSET | BS11: =BS10 -> ... MC READINGS .. | BT11: =$W$11 -> ….......... | BU11: 7200.2 | BV11: =BV10 -> ….. DAY 2 ….. | BW11: EXTERIOR & UNAFFECTED AREA | CB11: =V12 -> BATH UP | CC11: =W12 -> ….......... | CE11: .
A12: =V12 -> BATH UP | B12: =T12 -> 109 | D12: =D11+1 -> 209 | F12: =F11+1 -> 309 | H12: =H11+1 -> 409 | J12: 809 | L12: =L11+1 -> 6109.1 | M12: =M11+1 -> 6209.2 | N12: =N11+1 -> 6309.3 | O12: =O11+1 -> 6409.4 | P12: =P10+1 -> 7102.1 | Q12: =Q10+1 -> 7202.2 | R12: =R10+1 -> 7302.3 | S12: =S10+1 -> 7402.4 | T12: 109 | U12: …. | V12: ='ROOMS#'!R12 -> BATH UP | W12: ….......... | X12: =T12 -> 109 | Y12: =U12 -> …. | Z12: =V12 -> BATH UP | AA12: =$X$2 -> = … ROOM OVERVIEW PICS ... DAY 1 … | AB12: =$W$12 -> ….......... | AC12: =D12 -> 209 | AD12: =Y12 -> …. | AE12: =Z12 -> BATH UP | AF12: =$AC$2 -> ….. SOURCE of LOSS ….. | AG12: =$W$12 -> ….......... | AH12: =F12 -> 309 | AI12: =AD12 -> …. | AJ12: =AE12 -> BATH UP | AK12: =$AH$2 -> ….. C.P.S. …... | AL12: =$W$12 -> ….......... | AN12: =H12 -> 409 | AO12: =AI12 -> …. | AP12: =AJ12 -> BATH UP | AQ12: =$AN$2 -> NON SALVAGEABLE ITEMS | AR12: =$W$12 -> ….......... | AS12: =J12 -> 809 | AT12: . | AU12: =AP12 -> BATH UP | AV12: =AV11 -> … MITIGATION EQUIPMENT & W.I.P . ... | AW12: =$W$12 -> ….......... | AX12: =L12 -> 6109.1 | AY12: . | AZ12: =AZ11 -> .. DAY 1 … | BA12: =AU12 -> BATH UP | BB12: =BB11 -> ... MC READINGS .. | BC12: =$W$12 -> ….......... | BD12: =M12 -> 6209.2 | BE12: . | BF12: =BA12 -> BATH UP | BG12: =BG11 -> ... MC READINGS .. | BH12: =$W$12 -> ….......... | BI12: =N12 -> 6309.3 | BJ12: . | BK12: =BK11 -> ….. DAY 3 ….. | BL12: =BF12 -> BATH UP | BM12: =BM11 -> ... MC READINGS .. | BN12: =$W$12 -> ….......... | BO12: =O12 -> 6409.4 | BP12: . | BQ12: =BQ11 -> ….. DAY 4 ….. | BR12: =BL12 -> BATH UP | BS12: =BS11 -> ... MC READINGS .. | BT12: =$W$12 -> ….......... | BU12: =BU11+1 -> 7201.2 | BV12: =BV11 -> ….. DAY 2 ….. | BW12: DRY CHAMBER # 1 | BX12: RH &T & GPP | CB12: =V13 -> Bedroom 1 | CC12: =W13 -> LOS | CE12: .
A13: =V13 -> Bedroom 1 | B13: =T13 -> 110 | D13: =D12+1 -> 210 | F13: =F12+1 -> 310 | H13: =H12+1 -> 410 | J13: 810 | L13: =L12+1 -> 6110.1 | M13: =M12+1 -> 6210.2 | N13: =N12+1 -> 6310.3 | O13: =O12+1 -> 6410.4 | P13: DRY CHAMBER 3 | T13: 110 | U13: …. | V13: ='ROOMS#'!R13 -> Bedroom 1 | W13: LOS | X13: =T13 -> 110 | Y13: =U13 -> …. | Z13: =V13 -> Bedroom 1 | AA13: =$X$2 -> = … ROOM OVERVIEW PICS ... DAY 1 … | AB13: =$W$13 -> LOS | AC13: =D13 -> 210 | AD13: =Y13 -> …. | AE13: =Z13 -> Bedroom 1 | AF13: =$AC$2 -> ….. SOURCE of LOSS ….. | AG13: =$W$13 -> LOS | AH13: =F13 -> 310 | AI13: =AD13 -> …. | AJ13: =AE13 -> Bedroom 1 | AK13: =$AH$2 -> ….. C.P.S. …... | AL13: =$W$13 -> LOS | AN13: =H13 -> 410 | AO13: =AI13 -> …. | AP13: =AJ13 -> Bedroom 1 | AQ13: =$AN$2 -> NON SALVAGEABLE ITEMS | AR13: =$W$13 -> LOS | AS13: =J13 -> 810 | AT13: . | AU13: =AP13 -> Bedroom 1 | AV13: =AV12 -> … MITIGATION EQUIPMENT & W.I.P . ... | AW13: =$W$13 -> LOS | AX13: =L13 -> 6110.1 | AY13: . | AZ13: =AZ12 -> .. DAY 1 … | BA13: =AU13 -> Bedroom 1 | BB13: =BB12 -> ... MC READINGS .. | BC13: =$W$13 -> LOS | BD13: =M13 -> 6210.2 | BE13: . | BF13: =BA13 -> Bedroom 1 | BG13: =BG12 -> ... MC READINGS .. | BH13: =$W$13 -> LOS | BI13: =N13 -> 6310.3 | BJ13: . | BK13: =BK12 -> ….. DAY 3 ….. | BL13: =BF13 -> Bedroom 1 | BM13: =BM12 -> ... MC READINGS .. | BN13: =$W$13 -> LOS | BO13: =O13 -> 6410.4 | BP13: . | BQ13: =BQ12 -> ….. DAY 4 ….. | BR13: =BL13 -> Bedroom 1 | BS13: =BS12 -> ... MC READINGS .. | BT13: =$W$13 -> LOS | BU13: =BU12+1 -> 7202.2 | BV13: =BV12 -> ….. DAY 2 ….. | BW13: DRY CHAMBER # 2 | BX13: RH &T & GPP | CB13: =V14 -> BR1 Closet | CC13: =W14 -> ….......... | CE13: .
A14: =V14 -> BR1 Closet | B14: =T14 -> 111 | D14: =D13+1 -> 211 | F14: =F13+1 -> 311 | H14: =H13+1 -> 411 | J14: 811 | L14: =L13+1 -> 6111.1 | M14: =M13+1 -> 6211.2 | N14: =N13+1 -> 6311.3 | O14: =O13+1 -> 6411.4 | P14: =P12+1 -> 7103.1 | Q14: =Q12+1 -> 7203.2 | R14: =R12+1 -> 7303.3 | S14: =S12+1 -> 7403.4 | T14: 111 | U14: …. | V14: ='ROOMS#'!R14 -> BR1 Closet | W14: ….......... | X14: =T14 -> 111 | Y14: =U14 -> …. | Z14: =V14 -> BR1 Closet | AA14: =$X$2 -> = … ROOM OVERVIEW PICS ... DAY 1 … | AB14: =$W$14 -> ….......... | AC14: =D14 -> 211 | AD14: =Y14 -> …. | AE14: =Z14 -> BR1 Closet | AF14: =$AC$2 -> ….. SOURCE of LOSS ….. | AG14: =$W$14 -> ….......... | AH14: =F14 -> 311 | AI14: =AD14 -> …. | AJ14: =AE14 -> BR1 Closet | AK14: =$AH$2 -> ….. C.P.S. …... | AL14: =$W$14 -> ….......... | AN14: =H14 -> 411 | AO14: =AI14 -> …. | AP14: =AJ14 -> BR1 Closet | AQ14: =$AN$2 -> NON SALVAGEABLE ITEMS | AR14: =$W$14 -> ….......... | AS14: =J14 -> 811 | AT14: . | AU14: =AP14 -> BR1 Closet | AV14: =AV13 -> … MITIGATION EQUIPMENT & W.I.P . ... | AW14: =$W$14 -> ….......... | AX14: =L14 -> 6111.1 | AY14: . | AZ14: =AZ13 -> .. DAY 1 … | BA14: =AU14 -> BR1 Closet | BB14: =BB13 -> ... MC READINGS .. | BC14: =$W$14 -> ….......... | BD14: =M14 -> 6211.2 | BE14: . | BF14: =BA14 -> BR1 Closet | BG14: =BG13 -> ... MC READINGS .. | BH14: =$W$14 -> ….......... | BI14: =N14 -> 6311.3 | BJ14: . | BK14: =BK13 -> ….. DAY 3 ….. | BL14: =BF14 -> BR1 Closet | BM14: =BM13 -> ... MC READINGS .. | BN14: =$W$14 -> ….......... | BO14: =O14 -> 6411.4 | BP14: . | BQ14: =BQ13 -> ….. DAY 4 ….. | BR14: =BL14 -> BR1 Closet | BS14: =BS13 -> ... MC READINGS .. | BT14: =$W$14 -> ….......... | BU14: =BU13+1 -> 7203.2 | BV14: =BV12 -> ….. DAY 2 ….. | BW14: DRY CHAMBER # 3 | BX14: RH &T & GPP | CB14: =V15 -> Bedroom 2 | CC14: =W15 -> LOS | CE14: .
A15: =V15 -> Bedroom 2 | B15: =T15 -> 112 | D15: =D14+1 -> 212 | F15: =F14+1 -> 312 | H15: =H14+1 -> 412 | J15: 812 | L15: =L14+1 -> 6112.1 | M15: =M14+1 -> 6212.2 | N15: =N14+1 -> 6312.3 | O15: =O14+1 -> 6412.4 | P15: DRY CHAMBER 4 | T15: 112 | U15: …. | V15: ='ROOMS#'!R15 -> Bedroom 2 | W15: LOS | X15: =T15 -> 112 | Y15: =U15 -> …. | Z15: =V15 -> Bedroom 2 | AA15: =$X$2 -> = … ROOM OVERVIEW PICS ... DAY 1 … | AB15: =$W$15 -> LOS | AC15: =D15 -> 212 | AD15: =Y15 -> …. | AE15: =Z15 -> Bedroom 2 | AF15: =$AC$2 -> ….. SOURCE of LOSS ….. | AG15: =$W$15 -> LOS | AH15: =F15 -> 312 | AI15: =AD15 -> …. | AJ15: =AE15 -> Bedroom 2 | AK15: =$AH$2 -> ….. C.P.S. …... | AL15: =$W$15 -> LOS | AN15: =H15 -> 412 | AO15: =AI15 -> …. | AP15: =AJ15 -> Bedroom 2 | AQ15: =$AN$2 -> NON SALVAGEABLE ITEMS | AR15: =$W$15 -> LOS | AS15: =J15 -> 812 | AT15: . | AU15: =AP15 -> Bedroom 2 | AV15: =AV14 -> … MITIGATION EQUIPMENT & W.I.P . ... | AW15: =$W$15 -> LOS | AX15: =L15 -> 6112.1 | AY15: . | AZ15: =AZ14 -> .. DAY 1 … | BA15: =AU15 -> Bedroom 2 | BB15: =BB14 -> ... MC READINGS .. | BC15: =$W$15 -> LOS | BD15: =M15 -> 6212.2 | BE15: . | BF15: =BA15 -> Bedroom 2 | BG15: =BG14 -> ... MC READINGS .. | BH15: =$W$15 -> LOS | BI15: =N15 -> 6312.3 | BJ15: . | BK15: =BK14 -> ….. DAY 3 ….. | BL15: =BF15 -> Bedroom 2 | BM15: =BM14 -> ... MC READINGS .. | BN15: =$W$15 -> LOS | BO15: =O15 -> 6412.4 | BP15: . | BQ15: =BQ14 -> ….. DAY 4 ….. | BR15: =BL15 -> Bedroom 2 | BS15: =BS14 -> ... MC READINGS .. | BT15: =$W$15 -> LOS | BU15: =BU14+1 -> 7204.2 | BV15: =BV13 -> ….. DAY 2 ….. | BW15: DRY CHAMBER # 4 | BX15: RH &T & GPP | CB15: =V16 -> BR2 Closet, | CC15: =W16 -> LOS | CE15: .
A16: =V16 -> BR2 Closet, | B16: =T16 -> 113 | D16: =D15+1 -> 213 | F16: =F15+1 -> 313 | H16: =H15+1 -> 413 | J16: 813 | L16: =L15+1 -> 6113.1 | M16: =M15+1 -> 6213.2 | N16: =N15+1 -> 6313.3 | O16: =O15+1 -> 6413.4 | P16: =P14+1 -> 7104.1 | Q16: =Q14+1 -> 7204.2 | R16: =R14+1 -> 7304.3 | S16: =S14+1 -> 7404.4 | T16: 113 | U16: …. | V16: ='ROOMS#'!R16 -> BR2 Closet, | W16: LOS | X16: =T16 -> 113 | Y16: =U16 -> …. | Z16: =V16 -> BR2 Closet, | AA16: =$X$2 -> = … ROOM OVERVIEW PICS ... DAY 1 … | AB16: =$W$16 -> LOS | AC16: =D16 -> 213 | AD16: =Y16 -> …. | AE16: =Z16 -> BR2 Closet, | AF16: =$AC$2 -> ….. SOURCE of LOSS ….. | AG16: =$W$16 -> LOS | AH16: =F16 -> 313 | AI16: =AD16 -> …. | AJ16: =AE16 -> BR2 Closet, | AK16: =$AH$2 -> ….. C.P.S. …... | AL16: =$W$16 -> LOS | AN16: =H16 -> 413 | AO16: =AI16 -> …. | AP16: =AJ16 -> BR2 Closet, | AQ16: =$AN$2 -> NON SALVAGEABLE ITEMS | AR16: =$W$16 -> LOS | AS16: =J16 -> 813 | AT16: . | AU16: =AP16 -> BR2 Closet, | AV16: =AV15 -> … MITIGATION EQUIPMENT & W.I.P . ... | AW16: =$W$16 -> LOS | AX16: =L16 -> 6113.1 | AY16: . | AZ16: =AZ15 -> .. DAY 1 … | BA16: =AU16 -> BR2 Closet, | BB16: =BB15 -> ... MC READINGS .. | BC16: =$W$16 -> LOS | BD16: =M16 -> 6213.2 | BE16: . | BF16: =BA16 -> BR2 Closet, | BG16: =BG15 -> ... MC READINGS .. | BH16: =$W$16 -> LOS | BI16: =N16 -> 6313.3 | BJ16: . | BK16: =BK15 -> ….. DAY 3 ….. | BL16: =BF16 -> BR2 Closet, | BM16: =BM15 -> ... MC READINGS .. | BN16: =$W$16 -> LOS | BO16: =O16 -> 6413.4 | BP16: . | BQ16: =BQ15 -> ….. DAY 4 ….. | BR16: =BL16 -> BR2 Closet, | BS16: =BS15 -> ... MC READINGS .. | BT16: =$W$16 -> LOS | BU16: =BU15+1 -> 7205.2 | BV16: =BV14 -> ….. DAY 2 ….. | BW16: DRY CHAMBER # 5 | BX16: RH &T & GPP | CB16: =V17 -> 0 | CC16: =W17 -> LOS | CE16: .
A17: =V17 -> 0 | B17: =T17 -> 114 | D17: =D16+1 -> 214 | F17: =F16+1 -> 314 | H17: =H16+1 -> 414 | J17: 814 | L17: =L16+1 -> 6114.1 | M17: =M16+1 -> 6214.2 | N17: =N16+1 -> 6314.3 | O17: =O16+1 -> 6414.4 | P17: DRY CHAMBER 5 | T17: 114 | U17: …. | V17: ='ROOMS#'!R17 -> 0 | W17: LOS | X17: =T17 -> 114 | Y17: =U17 -> …. | Z17: =V17 -> 0 | AA17: =$X$2 -> = … ROOM OVERVIEW PICS ... DAY 1 … | AB17: =$W$17 -> LOS | AC17: =D17 -> 214 | AD17: =Y17 -> …. | AE17: =Z17 -> 0 | AF17: =$AC$2 -> ….. SOURCE of LOSS ….. | AG17: =$W$17 -> LOS | AH17: =F17 -> 314 | AI17: =AD17 -> …. | AJ17: =AE17 -> 0 | AK17: =$AH$2 -> ….. C.P.S. …... | AL17: =$W$17 -> LOS | AN17: =H17 -> 414 | AO17: =AI17 -> …. | AP17: =AJ17 -> 0 | AQ17: =$AN$2 -> NON SALVAGEABLE ITEMS | AR17: =$W$17 -> LOS | AS17: =J17 -> 814 | AT17: . | AU17: =AP17 -> 0 | AV17: =AV16 -> … MITIGATION EQUIPMENT & W.I.P . ... | AW17: =$W$17 -> LOS | AX17: =L17 -> 6114.1 | AY17: . | AZ17: =AZ16 -> .. DAY 1 … | BA17: =AU17 -> 0 | BB17: =BB16 -> ... MC READINGS .. | BC17: =$W$17 -> LOS | BD17: =M17 -> 6214.2 | BE17: . | BF17: =BA17 -> 0 | BG17: =BG16 -> ... MC READINGS .. | BH17: =$W$17 -> LOS | BI17: =N17 -> 6314.3 | BJ17: . | BK17: =BK16 -> ….. DAY 3 ….. | BL17: =BF17 -> 0 | BM17: =BM16 -> ... MC READINGS .. | BN17: =$W$17 -> LOS | BO17: =O17 -> 6414.4 | BP17: . | BQ17: =BQ16 -> ….. DAY 4 ….. | BR17: =BL17 -> 0 | BS17: =BS16 -> ... MC READINGS .. | BT17: =$W$17 -> LOS | BU17: 7300 | BV17: ….. DAY 3 ….. | BW17: =BW4 -> RH &T & GPP DRY CHAMBERS [DC] .READ INGS =========== | CB17: =V18 -> 0 | CC17: =W18 -> LOS | CE17: .
A18: =V18 -> 0 | B18: =T18 -> 115 | D18: =D17+1 -> 215 | F18: =F17+1 -> 315 | H18: =H17+1 -> 415 | J18: 815 | L18: =L17+1 -> 6115.1 | M18: =M17+1 -> 6215.2 | N18: =N17+1 -> 6315.3 | O18: =O17+1 -> 6415.4 | P18: =P16+1 -> 7105.1 | Q18: =Q16+1 -> 7205.2 | R18: =R16+1 -> 7305.3 | S18: =S16+1 -> 7405.4 | T18: 115 | U18: …. | V18: ='ROOMS#'!R18 -> 0 | W18: LOS | X18: =T18 -> 115 | Y18: =U18 -> …. | Z18: =V18 -> 0 | AA18: =$X$2 -> = … ROOM OVERVIEW PICS ... DAY 1 … | AB18: =$W$18 -> LOS | AC18: =D18 -> 215 | AD18: =Y18 -> …. | AE18: =Z18 -> 0 | AF18: =$AC$2 -> ….. SOURCE of LOSS ….. | AG18: =$W$18 -> LOS | AH18: =F18 -> 315 | AI18: =AD18 -> …. | AJ18: =AE18 -> 0 | AK18: =$AH$2 -> ….. C.P.S. …... | AL18: =$W$18 -> LOS | AN18: =H18 -> 415 | AO18: =AI18 -> …. | AP18: =AJ18 -> 0 | AQ18: =$AN$2 -> NON SALVAGEABLE ITEMS | AR18: =$W$18 -> LOS | AS18: =J18 -> 815 | AT18: . | AU18: =AP18 -> 0 | AV18: =AV17 -> … MITIGATION EQUIPMENT & W.I.P . ... | AW18: =$W$18 -> LOS | AX18: =L18 -> 6115.1 | AY18: . | AZ18: =AZ17 -> .. DAY 1 … | BA18: =AU18 -> 0 | BB18: =BB17 -> ... MC READINGS .. | BC18: =$W$18 -> LOS | BD18: =M18 -> 6215.2 | BE18: . | BF18: =BA18 -> 0 | BG18: =BG17 -> ... MC READINGS .. | BH18: =$W$18 -> LOS | BI18: =N18 -> 6315.3 | BJ18: . | BK18: =BK17 -> ….. DAY 3 ….. | BL18: =BF18 -> 0 | BM18: =BM17 -> ... MC READINGS .. | BN18: =$W$18 -> LOS | BO18: =O18 -> 6415.4 | BP18: . | BQ18: =BQ17 -> ….. DAY 4 ….. | BR18: =BL18 -> 0 | BS18: =BS17 -> ... MC READINGS .. | BT18: =$W$18 -> LOS | BU18: =BU17 -> 7300 | BV18: =BV17 -> ….. DAY 3 ….. | BW18: EXTERIOR & UNAFFECTED AREA | CB18: =V19 -> 0 | CC18: =W19 -> LOS | CE18: .
A19: =V19 -> 0 | B19: =T19 -> 116 | D19: =D18+1 -> 216 | F19: =F18+1 -> 316 | H19: =H18+1 -> 416 | J19: 816 | L19: =L18+1 -> 6116.1 | M19: =M18+1 -> 6216.2 | N19: =N18+1 -> 6316.3 | O19: =O18+1 -> 6416.4 | T19: 116 | U19: …. | V19: ='ROOMS#'!R19 -> 0 | W19: LOS | X19: =T19 -> 116 | Y19: =U19 -> …. | Z19: =V19 -> 0 | AA19: =$X$2 -> = … ROOM OVERVIEW PICS ... DAY 1 … | AB19: =$W$19 -> LOS | AC19: =D19 -> 216 | AD19: =Y19 -> …. | AE19: =Z19 -> 0 | AF19: =$AC$2 -> ….. SOURCE of LOSS ….. | AG19: =$W$19 -> LOS | AH19: =F19 -> 316 | AI19: =AD19 -> …. | AJ19: =AE19 -> 0 | AK19: =$AH$2 -> ….. C.P.S. …... | AL19: =$W$19 -> LOS | AN19: =H19 -> 416 | AO19: =AI19 -> …. | AP19: =AJ19 -> 0 | AQ19: =$AN$2 -> NON SALVAGEABLE ITEMS | AR19: =$W$19 -> LOS | AS19: =J19 -> 816 | AT19: . | AU19: =AP19 -> 0 | AV19: =AV18 -> … MITIGATION EQUIPMENT & W.I.P . ... | AW19: =$W$19 -> LOS | AX19: =L19 -> 6116.1 | AY19: . | AZ19: =AZ18 -> .. DAY 1 … | BA19: =AU19 -> 0 | BB19: =BB18 -> ... MC READINGS .. | BC19: =$W$19 -> LOS | BD19: =M19 -> 6216.2 | BE19: . | BF19: =BA19 -> 0 | BG19: =BG18 -> ... MC READINGS .. | BH19: =$W$19 -> LOS | BI19: =N19 -> 6316.3 | BJ19: . | BK19: =BK18 -> ….. DAY 3 ….. | BL19: =BF19 -> 0 | BM19: =BM18 -> ... MC READINGS .. | BN19: =$W$19 -> LOS | BO19: =O19 -> 6416.4 | BP19: . | BQ19: =BQ18 -> ….. DAY 4 ….. | BR19: =BL19 -> 0 | BS19: =BS18 -> ... MC READINGS .. | BT19: =$W$19 -> LOS | BU19: =BU18+1 -> 7301 | BV19: =BV18 -> ….. DAY 3 ….. | BW19: DRY CHAMBER # 1 | BX19: RH &T & GPP | CB19: =V20 -> 0 | CC19: =W20 -> LOS | CE19: .
A20: =V20 -> 0 | B20: =T20 -> 117 | D20: =D19+1 -> 217 | F20: =F19+1 -> 317 | H20: =H19+1 -> 417 | J20: 817 | L20: =L19+1 -> 6117.1 | M20: =M19+1 -> 6217.2 | N20: =N19+1 -> 6317.3 | O20: =O19+1 -> 6417.4 | T20: 117 | U20: …. | V20: ='ROOMS#'!R20 -> 0 | W20: LOS | X20: =T20 -> 117 | Y20: =U20 -> …. | Z20: =V20 -> 0 | AA20: =$X$2 -> = … ROOM OVERVIEW PICS ... DAY 1 … | AB20: =$W$20 -> LOS | AC20: =D20 -> 217 | AD20: =Y20 -> …. | AE20: =Z20 -> 0 | AF20: =$AC$2 -> ….. SOURCE of LOSS ….. | AG20: =$W$20 -> LOS | AH20: =F20 -> 317 | AI20: =AD20 -> …. | AJ20: =AE20 -> 0 | AK20: =$AH$2 -> ….. C.P.S. …... | AL20: =$W$20 -> LOS | AN20: =H20 -> 417 | AO20: =AI20 -> …. | AP20: =AJ20 -> 0 | AQ20: =$AN$2 -> NON SALVAGEABLE ITEMS | AR20: =$W$20 -> LOS | AS20: =J20 -> 817 | AT20: . | AU20: =AP20 -> 0 | AV20: =AV19 -> … MITIGATION EQUIPMENT & W.I.P . ... | AW20: =$W$20 -> LOS | AX20: =L20 -> 6117.1 | AY20: . | AZ20: =AZ19 -> .. DAY 1 … | BA20: =AU20 -> 0 | BB20: =BB19 -> ... MC READINGS .. | BC20: =$W$20 -> LOS | BD20: =M20 -> 6217.2 | BE20: . | BF20: =BA20 -> 0 | BG20: =BG19 -> ... MC READINGS .. | BH20: =$W$20 -> LOS | BI20: =N20 -> 6317.3 | BJ20: . | BK20: =BK19 -> ….. DAY 3 ….. | BL20: =BF20 -> 0 | BM20: =BM19 -> ... MC READINGS .. | BN20: =$W$20 -> LOS | BO20: =O20 -> 6417.4 | BP20: . | BQ20: =BQ19 -> ….. DAY 4 ….. | BR20: =BL20 -> 0 | BS20: =BS19 -> ... MC READINGS .. | BT20: =$W$20 -> LOS | BU20: =BU19+1 -> 7302 | BV20: =BV19 -> ….. DAY 3 ….. | BW20: DRY CHAMBER # 2 | BX20: RH &T & GPP | CB20: =V21 -> 0 | CC20: =W21 -> LOS | CE20: .
A21: =V21 -> 0 | B21: =T21 -> 118 | D21: =D20+1 -> 218 | F21: =F20+1 -> 318 | H21: =H20+1 -> 418 | J21: 818 | L21: =L20+1 -> 6118.1 | M21: =M20+1 -> 6218.2 | N21: =N20+1 -> 6318.3 | O21: =O20+1 -> 6418.4 | T21: 118 | U21: …. | V21: ='ROOMS#'!R21 -> 0 | W21: LOS | X21: =T21 -> 118 | Y21: =U21 -> …. | Z21: =V21 -> 0 | AA21: =$X$2 -> = … ROOM OVERVIEW PICS ... DAY 1 … | AB21: =$W$21 -> LOS | AC21: =D21 -> 218 | AD21: =Y21 -> …. | AE21: =Z21 -> 0 | AF21: =$AC$2 -> ….. SOURCE of LOSS ….. | AG21: =$W$21 -> LOS | AH21: =F21 -> 318 | AI21: =AD21 -> …. | AJ21: =AE21 -> 0 | AK21: =$AH$2 -> ….. C.P.S. …... | AL21: =$W$21 -> LOS | AN21: =H21 -> 418 | AO21: =AI21 -> …. | AP21: =AJ21 -> 0 | AQ21: =$AN$2 -> NON SALVAGEABLE ITEMS | AR21: =$W$21 -> LOS | AS21: =J21 -> 818 | AT21: . | AU21: =AP21 -> 0 | AV21: =AV20 -> … MITIGATION EQUIPMENT & W.I.P . ... | AW21: =$W$21 -> LOS | AX21: =L21 -> 6118.1 | AY21: . | AZ21: =AZ20 -> .. DAY 1 … | BA21: =AU21 -> 0 | BB21: =BB20 -> ... MC READINGS .. | BC21: =$W$21 -> LOS | BD21: =M21 -> 6218.2 | BE21: . | BF21: =BA21 -> 0 | BG21: =BG20 -> ... MC READINGS .. | BH21: =$W$21 -> LOS | BI21: =N21 -> 6318.3 | BJ21: . | BK21: =BK20 -> ….. DAY 3 ….. | BL21: =BF21 -> 0 | BM21: =BM20 -> ... MC READINGS .. | BN21: =$W$21 -> LOS | BO21: =O21 -> 6418.4 | BP21: . | BQ21: =BQ20 -> ….. DAY 4 ….. | BR21: =BL21 -> 0 | BS21: =BS20 -> ... MC READINGS .. | BT21: =$W$21 -> LOS | BU21: =BU20+1 -> 7303 | BV21: =BV19 -> ….. DAY 3 ….. | BW21: DRY CHAMBER # 3 | BX21: RH &T & GPP | CB21: =V22 -> 0 | CC21: =W22 -> LOS | CE21: .
A22: =V22 -> 0 | B22: =T22 -> 119 | D22: =D21+1 -> 219 | F22: =F21+1 -> 319 | H22: =H21+1 -> 419 | J22: 819 | L22: =L21+1 -> 6119.1 | M22: =M21+1 -> 6219.2 | N22: =N21+1 -> 6319.3 | O22: =O21+1 -> 6419.4 | T22: 119 | U22: …. | V22: ='ROOMS#'!R22 -> 0 | W22: LOS | X22: =T22 -> 119 | Y22: =U22 -> …. | Z22: =V22 -> 0 | AA22: =$X$2 -> = … ROOM OVERVIEW PICS ... DAY 1 … | AB22: =$W$22 -> LOS | AC22: =D22 -> 219 | AD22: =Y22 -> …. | AE22: =Z22 -> 0 | AF22: =$AC$2 -> ….. SOURCE of LOSS ….. | AG22: =$W$22 -> LOS | AH22: =F22 -> 319 | AI22: =AD22 -> …. | AJ22: =AE22 -> 0 | AK22: =$AH$2 -> ….. C.P.S. …... | AL22: =$W$22 -> LOS | AN22: =H22 -> 419 | AO22: =AI22 -> …. | AP22: =AJ22 -> 0 | AQ22: =$AN$2 -> NON SALVAGEABLE ITEMS | AR22: =$W$22 -> LOS | AS22: =J22 -> 819 | AT22: . | AU22: =AP22 -> 0 | AV22: =AV21 -> … MITIGATION EQUIPMENT & W.I.P . ... | AW22: =$W$22 -> LOS | AX22: =L22 -> 6119.1 | AY22: . | AZ22: =AZ21 -> .. DAY 1 … | BA22: =AU22 -> 0 | BB22: =BB21 -> ... MC READINGS .. | BC22: =$W$22 -> LOS | BD22: =M22 -> 6219.2 | BE22: . | BF22: =BA22 -> 0 | BG22: =BG21 -> ... MC READINGS .. | BH22: =$W$22 -> LOS | BI22: =N22 -> 6319.3 | BJ22: . | BK22: =BK21 -> ….. DAY 3 ….. | BL22: =BF22 -> 0 | BM22: =BM21 -> ... MC READINGS .. | BN22: =$W$22 -> LOS | BO22: =O22 -> 6419.4 | BP22: . | BQ22: =BQ21 -> ….. DAY 4 ….. | BR22: =BL22 -> 0 | BS22: =BS21 -> ... MC READINGS .. | BT22: =$W$22 -> LOS | BU22: =BU21+1 -> 7304 | BV22: =BV20 -> ….. DAY 3 ….. | BW22: DRY CHAMBER # 4 | BX22: RH &T & GPP | CB22: =V23 -> 0 | CC22: =W23 -> ….......... | CE22: .
A23: =V23 -> 0 | B23: =T23 -> 120 | D23: =D22+1 -> 220 | F23: =F22+1 -> 320 | H23: =H22+1 -> 420 | J23: 820 | L23: =L22+1 -> 6120.1 | M23: =M22+1 -> 6220.2 | N23: =N22+1 -> 6320.3 | O23: =O22+1 -> 6420.4 | T23: 120 | U23: …. | V23: ='ROOMS#'!R23 -> 0 | W23: ….......... | X23: =T23 -> 120 | Y23: =U23 -> …. | Z23: =V23 -> 0 | AA23: =$X$2 -> = … ROOM OVERVIEW PICS ... DAY 1 … | AB23: =$W$23 -> ….......... | AC23: =D23 -> 220 | AD23: =Y23 -> …. | AE23: =Z23 -> 0 | AF23: =$AC$2 -> ….. SOURCE of LOSS ….. | AG23: =$W$23 -> ….......... | AH23: =F23 -> 320 | AI23: =AD23 -> …. | AJ23: =AE23 -> 0 | AK23: =$AH$2 -> ….. C.P.S. …... | AL23: =$W$23 -> ….......... | AN23: =H23 -> 420 | AO23: =AI23 -> …. | AP23: =AJ23 -> 0 | AQ23: =$AN$2 -> NON SALVAGEABLE ITEMS | AR23: =$W$23 -> ….......... | AS23: =J23 -> 820 | AT23: . | AU23: =AP23 -> 0 | AV23: =AV22 -> … MITIGATION EQUIPMENT & W.I.P . ... | AW23: =$W$23 -> ….......... | AX23: =L23 -> 6120.1 | AY23: . | AZ23: =AZ22 -> .. DAY 1 … | BA23: =AU23 -> 0 | BB23: =BB22 -> ... MC READINGS .. | BC23: =$W$23 -> ….......... | BD23: =M23 -> 6220.2 | BE23: . | BF23: =BA23 -> 0 | BG23: =BG22 -> ... MC READINGS .. | BH23: =$W$23 -> ….......... | BI23: =N23 -> 6320.3 | BJ23: . | BK23: =BK22 -> ….. DAY 3 ….. | BL23: =BF23 -> 0 | BM23: =BM22 -> ... MC READINGS .. | BN23: =$W$23 -> ….......... | BO23: =O23 -> 6420.4 | BP23: . | BQ23: =BQ22 -> ….. DAY 4 ….. | BR23: =BL23 -> 0 | BS23: =BS22 -> ... MC READINGS .. | BT23: =$W$23 -> ….......... | BU23: 7400 | BV23: ….. DAY 4 ….. | BW23: =BW17 -> RH &T & GPP DRY CHAMBERS [DC] .READ INGS =========== | CB23: =V24 -> 0 | CC23: =W24 -> ….......... | CE23: .
A24: =V24 -> 0 | B24: =T24 -> 121 | D24: =D23+1 -> 221 | F24: =F23+1 -> 321 | H24: =H23+1 -> 421 | J24: 821 | L24: =L23+1 -> 6121.1 | M24: =M23+1 -> 6221.2 | N24: =N23+1 -> 6321.3 | O24: =O23+1 -> 6421.4 | T24: 121 | U24: …. | V24: ='ROOMS#'!R24 -> 0 | W24: ….......... | X24: =T24 -> 121 | Y24: =U24 -> …. | Z24: =V24 -> 0 | AA24: =$X$2 -> = … ROOM OVERVIEW PICS ... DAY 1 … | AB24: =$W$24 -> ….......... | AC24: =D24 -> 221 | AD24: =Y24 -> …. | AE24: =Z24 -> 0 | AF24: =$AC$2 -> ….. SOURCE of LOSS ….. | AG24: =$W$24 -> ….......... | AH24: =F24 -> 321 | AI24: =AD24 -> …. | AJ24: =AE24 -> 0 | AK24: =$AH$2 -> ….. C.P.S. …... | AL24: =$W$24 -> ….......... | AN24: =H24 -> 421 | AO24: =AI24 -> …. | AP24: =AJ24 -> 0 | AQ24: =$AN$2 -> NON SALVAGEABLE ITEMS | AR24: =$W$24 -> ….......... | AS24: =J24 -> 821 | AT24: . | AU24: =AP24 -> 0 | AV24: =AV23 -> … MITIGATION EQUIPMENT & W.I.P . ... | AW24: =$W$24 -> ….......... | AX24: =L24 -> 6121.1 | AY24: . | AZ24: =AZ23 -> .. DAY 1 … | BA24: =AU24 -> 0 | BB24: =BB23 -> ... MC READINGS .. | BC24: =$W$24 -> ….......... | BD24: =M24 -> 6221.2 | BE24: . | BF24: =BA24 -> 0 | BG24: =BG23 -> ... MC READINGS .. | BH24: =$W$24 -> ….......... | BI24: =N24 -> 6321.3 | BJ24: . | BK24: =BK23 -> ….. DAY 3 ….. | BL24: =BF24 -> 0 | BM24: =BM23 -> ... MC READINGS .. | BN24: =$W$24 -> ….......... | BO24: =O24 -> 6421.4 | BP24: . | BQ24: =BQ23 -> ….. DAY 4 ….. | BR24: =BL24 -> 0 | BS24: =BS23 -> ... MC READINGS .. | BT24: =$W$24 -> ….......... | BU24: 7400 | BV24: ….. DAY 4 ….. | BW24: EXTERIOR & UNAFFECTED AREA | CB24: =V25 -> 0 | CC24: =W25 -> ….......... | CE24: .
A25: =V25 -> 0 | B25: =T25 -> 122 | D25: =D24+1 -> 222 | F25: =F24+1 -> 322 | H25: =H24+1 -> 422 | J25: 822 | L25: =L24+1 -> 6122.1 | M25: =M24+1 -> 6222.2 | N25: =N24+1 -> 6322.3 | O25: =O24+1 -> 6422.4 | T25: 122 | U25: …. | V25: ='ROOMS#'!R25 -> 0 | W25: ….......... | X25: =T25 -> 122 | Y25: =U25 -> …. | Z25: =V25 -> 0 | AA25: =$X$2 -> = … ROOM OVERVIEW PICS ... DAY 1 … | AB25: =$W$25 -> ….......... | AC25: =D25 -> 222 | AD25: =Y25 -> …. | AE25: =Z25 -> 0 | AF25: =$AC$2 -> ….. SOURCE of LOSS ….. | AG25: =$W$25 -> ….......... | AH25: =F25 -> 322 | AI25: =AD25 -> …. | AJ25: =AE25 -> 0 | AK25: =$AH$2 -> ….. C.P.S. …... | AL25: =$W$25 -> ….......... | AN25: =H25 -> 422 | AO25: =AI25 -> …. | AP25: =AJ25 -> 0 | AQ25: =$AN$2 -> NON SALVAGEABLE ITEMS | AR25: =$W$25 -> ….......... | AS25: =J25 -> 822 | AT25: . | AU25: =AP25 -> 0 | AV25: =AV24 -> … MITIGATION EQUIPMENT & W.I.P . ... | AW25: =$W$25 -> ….......... | AX25: =L25 -> 6122.1 | AY25: . | AZ25: =AZ24 -> .. DAY 1 … | BA25: =AU25 -> 0 | BB25: =BB24 -> ... MC READINGS .. | BC25: =$W$25 -> ….......... | BD25: =M25 -> 6222.2 | BE25: . | BF25: =BA25 -> 0 | BG25: =BG24 -> ... MC READINGS .. | BH25: =$W$25 -> ….......... | BI25: =N25 -> 6322.3 | BJ25: . | BK25: =BK24 -> ….. DAY 3 ….. | BL25: =BF25 -> 0 | BM25: =BM24 -> ... MC READINGS .. | BN25: =$W$25 -> ….......... | BO25: =O25 -> 6422.4 | BP25: . | BQ25: =BQ24 -> ….. DAY 4 ….. | BR25: =BL25 -> 0 | BS25: =BS24 -> ... MC READINGS .. | BT25: =$W$25 -> ….......... | BU25: =BU24+1 -> 7401 | BV25: =BV24 -> ….. DAY 4 ….. | BW25: DRY CHAMBER # 1 | BX25: RH &T & GPP | CB25: =V26 -> 0 | CC25: =W26 -> ….......... | CE25: .
A26: =V26 -> 0 | B26: =T26 -> 123 | D26: =D25+1 -> 223 | F26: =F25+1 -> 323 | H26: =H25+1 -> 423 | J26: 823 | L26: =L25+1 -> 6123.1 | M26: =M25+1 -> 6223.2 | N26: =N25+1 -> 6323.3 | O26: =O25+1 -> 6423.4 | T26: 123 | U26: …. | V26: ='ROOMS#'!R26 -> 0 | W26: ….......... | X26: =T26 -> 123 | Y26: =U26 -> …. | Z26: =V26 -> 0 | AA26: =$X$2 -> = … ROOM OVERVIEW PICS ... DAY 1 … | AB26: =$W$26 -> ….......... | AC26: =D26 -> 223 | AD26: =Y26 -> …. | AE26: =Z26 -> 0 | AF26: =$AC$2 -> ….. SOURCE of LOSS ….. | AG26: =$W$26 -> ….......... | AH26: =F26 -> 323 | AI26: =AD26 -> …. | AJ26: =AE26 -> 0 | AK26: =$AH$2 -> ….. C.P.S. …... | AL26: =$W$26 -> ….......... | AN26: =H26 -> 423 | AO26: =AI26 -> …. | AP26: =AJ26 -> 0 | AQ26: =$AN$2 -> NON SALVAGEABLE ITEMS | AR26: =$W$26 -> ….......... | AS26: =J26 -> 823 | AT26: . | AU26: =AP26 -> 0 | AV26: =AV25 -> … MITIGATION EQUIPMENT & W.I.P . ... | AW26: =$W$26 -> ….......... | AX26: =L26 -> 6123.1 | AY26: . | AZ26: =AZ25 -> .. DAY 1 … | BA26: =AU26 -> 0 | BB26: =BB25 -> ... MC READINGS .. | BC26: =$W$26 -> ….......... | BD26: =M26 -> 6223.2 | BE26: . | BF26: =BA26 -> 0 | BG26: =BG25 -> ... MC READINGS .. | BH26: =$W$26 -> ….......... | BI26: =N26 -> 6323.3 | BJ26: . | BK26: =BK25 -> ….. DAY 3 ….. | BL26: =BF26 -> 0 | BM26: =BM25 -> ... MC READINGS .. | BN26: =$W$26 -> ….......... | BO26: =O26 -> 6423.4 | BP26: . | BQ26: =BQ25 -> ….. DAY 4 ….. | BR26: =BL26 -> 0 | BS26: =BS25 -> ... MC READINGS .. | BT26: =$W$26 -> ….......... | BU26: =BU25+1 -> 7402 | BV26: =BV25 -> ….. DAY 4 ….. | BW26: DRY CHAMBER # 2 | BX26: RH &T & GPP | CB26: =V27 -> 0 | CC26: =W27 -> ….......... | CE26: .
A27: =V27 -> 0 | B27: =T27 -> 124 | D27: =D26+1 -> 224 | F27: =F26+1 -> 324 | H27: =H26+1 -> 424 | J27: 824 | L27: =L26+1 -> 6124.1 | M27: =M26+1 -> 6224.2 | N27: =N26+1 -> 6324.3 | O27: =O26+1 -> 6424.4 | T27: 124 | U27: …. | V27: ='ROOMS#'!R27 -> 0 | W27: ….......... | X27: =T27 -> 124 | Y27: =U27 -> …. | Z27: =V27 -> 0 | AA27: =$X$2 -> = … ROOM OVERVIEW PICS ... DAY 1 … | AB27: =$W$27 -> ….......... | AC27: =D27 -> 224 | AD27: =Y27 -> …. | AE27: =Z27 -> 0 | AF27: =$AC$2 -> ….. SOURCE of LOSS ….. | AG27: =$W$27 -> ….......... | AH27: =F27 -> 324 | AI27: =AD27 -> …. | AJ27: =AE27 -> 0 | AK27: =$AH$2 -> ….. C.P.S. …... | AL27: =$W$27 -> ….......... | AN27: =H27 -> 424 | AO27: =AI27 -> …. | AP27: =AJ27 -> 0 | AQ27: =$AN$2 -> NON SALVAGEABLE ITEMS | AR27: =$W$27 -> ….......... | AS27: =J27 -> 824 | AT27: . | AU27: =AP27 -> 0 | AV27: =AV26 -> … MITIGATION EQUIPMENT & W.I.P . ... | AW27: =$W$27 -> ….......... | AX27: =L27 -> 6124.1 | AY27: . | AZ27: =AZ26 -> .. DAY 1 … | BA27: =AU27 -> 0 | BB27: =BB26 -> ... MC READINGS .. | BC27: =$W$27 -> ….......... | BD27: =M27 -> 6224.2 | BE27: . | BF27: =BA27 -> 0 | BG27: =BG26 -> ... MC READINGS .. | BH27: =$W$27 -> ….......... | BI27: =N27 -> 6324.3 | BJ27: . | BK27: =BK26 -> ….. DAY 3 ….. | BL27: =BF27 -> 0 | BM27: =BM26 -> ... MC READINGS .. | BN27: =$W$27 -> ….......... | BO27: =O27 -> 6424.4 | BP27: . | BQ27: =BQ26 -> ….. DAY 4 ….. | BR27: =BL27 -> 0 | BS27: =BS26 -> ... MC READINGS .. | BT27: =$W$27 -> ….......... | BU27: =BU26+1 -> 7403 | BV27: =BV25 -> ….. DAY 4 ….. | BW27: DRY CHAMBER # 3 | BX27: RH &T & GPP | CB27: =V28 -> 0 | CC27: =W28 -> 0 | CE27: .
A28: =V28 -> 0 | B28: =T28 -> 125 | D28: =D27+1 -> 225 | F28: =F27+1 -> 325 | H28: =H27+1 -> 425 | J28: 825 | L28: =L27+1 -> 6125.1 | M28: =M27+1 -> 6225.2 | N28: =N27+1 -> 6325.3 | O28: =O27+1 -> 6425.4 | T28: 125 | U28: …. | V28: ='ROOMS#'!R28 -> 0 | X28: =T28 -> 125 | Y28: =U28 -> …. | Z28: =V28 -> 0 | AA28: =$X$2 -> = … ROOM OVERVIEW PICS ... DAY 1 … | AB28: =$W$28 -> 0 | AC28: =D28 -> 225 | AD28: =Y28 -> …. | AE28: =Z28 -> 0 | AF28: =$AC$2 -> ….. SOURCE of LOSS ….. | AG28: =$W$28 -> 0 | AH28: =F28 -> 325 | AI28: =AD28 -> …. | AJ28: =AE28 -> 0 | AK28: =$AH$2 -> ….. C.P.S. …... | AL28: =$W$28 -> 0 | AN28: =H28 -> 425 | AO28: =AI28 -> …. | AP28: =AJ28 -> 0 | AQ28: =$AN$2 -> NON SALVAGEABLE ITEMS | AR28: =$W$28 -> 0 | AS28: =J28 -> 825 | AT28: . | AU28: =AP28 -> 0 | AV28: =AV27 -> … MITIGATION EQUIPMENT & W.I.P . ... | AW28: =$W$28 -> 0 | AX28: =L28 -> 6125.1 | AY28: . | AZ28: =AZ27 -> .. DAY 1 … | BA28: =AU28 -> 0 | BB28: =BB27 -> ... MC READINGS .. | BC28: =$W$28 -> 0 | BD28: =M28 -> 6225.2 | BE28: . | BF28: =BA28 -> 0 | BG28: =BG27 -> ... MC READINGS .. | BH28: =$W$28 -> 0 | BI28: =N28 -> 6325.3 | BJ28: . | BK28: =BK27 -> ….. DAY 3 ….. | BL28: =BF28 -> 0 | BM28: =BM27 -> ... MC READINGS .. | BN28: =$W$28 -> 0 | BO28: =O28 -> 6425.4 | BP28: . | BQ28: =BQ27 -> ….. DAY 4 ….. | BR28: =BL28 -> 0 | BS28: =BS27 -> ... MC READINGS .. | BT28: =$W$28 -> 0 | BU28: =BU27+1 -> 7404 | BV28: =BV26 -> ….. DAY 4 ….. | BW28: DRY CHAMBER # 4 | BX28: RH &T & GPP | CB28: =V29 -> 0 | CC28: =W29 -> 0 | CE28: .
X30: 103.. Dining Room ... = ROOM OVERVIEW PICS ...DAY 1 ...LOS

Sheet DRAWS
A1: DRAW SCHEDULE
A2: Property-owner Name | B2: =+'[1]jobinfo(2)'!C1 -> MONTGOMERY, JAVIONNA ANTONIO | C2: =+'[1]jobinfo(2)'!B26 -> Insurance Co. Name | D2: =+'[1]jobinfo(2)'!C26 -> INS CO
A3: Property address: street | B3: =+'[1]jobinfo(2)'!C2 -> 3034 Ashwood Road, | C3: =+'[1]jobinfo(2)'!B27 -> Claim # | D3: =+'[1]jobinfo(2)'!C27 -> CLM# TBD
A4: Property city, state, zip | B4: =+'[1]jobinfo(2)'!C3 -> Cleveland, OH, USA 44120 | C4: =+'[1]jobinfo(2)'!B11 -> Cause of Loss | D4: =+'[1]jobinfo(2)'!C11 -> WATER BATHTUB OVERFLOW
A5: Customer Email | B5: =+'[1]jobinfo(2)'!C4 -> JAVIONNA@ICLOUD.COM | C5: =+'[1]jobinfo(2)'!B12 -> date of loss | D5: =+'[1]jobinfo(2)'!C12 -> Saturday, August 26, 2025
A6: Cst-owner Phone# | B6: =+'[1]jobinfo(2)'!C5 -> (216) 551-5572 | C6: =+'[1]jobinfo(2)'!B13 -> rebuild type 1 | D6: =+'[1]jobinfo(2)'!C13 -> interior repairs LVL1
B7: _______________________ | C7: =+'[1]jobinfo(2)'!B14 -> rebuild type 2 | D7: =+'[1]jobinfo(2)'!C14 -> interior repairs LVL2
A8: Customer may wish to alter the original job work scope and or add additional work.
A10: Each item will be individually addressed with the best interest of the customer in mind.
C11: LOCATION & Basic damage / work Description | D11: Scope notes | E11: Photos | F11: Sketch
A12: # 0 = Master bedroom | B12: Ceilings N corner | C12: repair water damage drywall paint
A13: DRAW # | B13: PERCENTAGE OF WORK COMPLETED | D13: {_______} | E13: {_______} | F13: TTD
A14: 1 | B14: INITIAL DEPOSIT | D14: 0.33 | F14: =+D14 -> 0.33
A15: 2 | B15: 0.5 | D15: 0.33 | F15: =+D15+D14 -> 0.66
A16: 3 | B16: 0.75 | D16: 0.1 | F16: =+F15+D16 -> 0.76
A17: 4 | B17: 0.9 | D17: 0.14 | F17: =+F16+D17 -> 0.9
A18: 5 | B18: 1 | D18: 0.1 | F18: =+F17+D18 -> 1
H20: GC & SUB TERMS % | J20: CASH FLOW | O20: JOB = | P20: ='[1]jobinfo(2)'!C51 -> OH25 MONTGOMERY
H21: ='[1]jobinfo(2)'!C100 -> All Phase Consulting, LLC | K21: =+'[1]jobinfo(2)'!D100 -> Wayside Builders, LLC | N21: APC | P21: ='[1]jobinfo(2)'!C1 -> MONTGOMERY, JAVIONNA ANTONIO
H22: ='[1]jobinfo(2)'!C112 -> Joe Jones, PM 216.450.7228 | K22: ='[1]jobinfo(2)'!D112 -> Tony Jones 216.347.2656 | P22: ='[1]jobinfo(2)'!C2 -> 3034 Ashwood Road,
P23: ='[1]jobinfo(2)'!C3 -> Cleveland, OH, USA 44120
H24: ='[1]jobinfo(2)'!B5 -> Cst-owner Phone# | I24: ='[1]jobinfo(2)'!C5 -> (216) 551-5572 | J24: ='[1]jobinfo(2)'!B26 -> Insurance Co. Name | K24: ='[1]jobinfo(2)'!C26 -> INS CO | L24: ='[1]jobinfo(2)'!B37 -> adj contents | M24: ='[1]jobinfo(2)'!C37 -> 0
H25: ='[1]jobinfo(2)'!B6 -> Co-Owner.cst#2 | I25: ='[1]jobinfo(2)'!C6 -> 0 | J25: ='[1]jobinfo(2)'!B27 -> Claim # | K25: ='[1]jobinfo(2)'!C27 -> CLM# TBD | L25: ='[1]jobinfo(2)'!B38 -> adj CPS phone # | M25: ='[1]jobinfo(2)'!C38 -> 0 | O25: ='[1]jobinfo(2)'!B34 -> Field Adjuster Name | P25: ='[1]jobinfo(2)'!C34 -> 0
H26: ='[1]jobinfo(2)'!B11 -> Cause of Loss | I26: ='[1]jobinfo(2)'!C11 -> WATER BATHTUB OVERFLOW | J26: ='[1]jobinfo(2)'!B28 -> policy # | K26: ='[1]jobinfo(2)'!C28 -> PL # TBD | L26: ='[1]jobinfo(2)'!B39 -> adj CPS email | M26: ='[1]jobinfo(2)'!C39 -> 0 | O26: ='[1]jobinfo(2)'!B35 -> Phone # field adj | P26: ='[1]jobinfo(2)'!C35 -> 0
H27: ='[1]jobinfo(2)'!B12 -> date of loss | I27: ='[1]jobinfo(2)'!C12 -> Saturday, August 26, 2025 | J27: ='[1]jobinfo(2)'!B29 -> Email INS. co. | K27: ='[1]jobinfo(2)'!C29 -> 0 | L27: ='[1]jobinfo(2)'!B40 -> TMP adj | M27: ='[1]jobinfo(2)'!C40 -> 0 | O27: ='[1]jobinfo(2)'!B36 -> Field adj email | P27: ='[1]jobinfo(2)'!C36 -> 0
H28: ='[1]jobinfo(2)'!B13 -> rebuild type 1 | I28: ='[1]jobinfo(2)'!C13 -> interior repairs LVL1 | J28: ='[1]jobinfo(2)'!B30 -> DESK Adjuster DA | K28: ='[1]jobinfo(2)'!C30 -> 0 | L28: ='[1]jobinfo(2)'!B41 -> TMP adj phone # | M28: ='[1]jobinfo(2)'!C41 -> 0 | O28: ='[1]jobinfo(2)'!B21 -> Year Built | P28: ='[1]jobinfo(2)'!C21 -> POST 1978
H29: ='[1]jobinfo(2)'!B14 -> rebuild type 2 | I29: ='[1]jobinfo(2)'!C14 -> interior repairs LVL2 | J29: ='[1]jobinfo(2)'!B31 -> DA Phone | K29: ='[1]jobinfo(2)'!C31 -> 0 | L29: ='[1]jobinfo(2)'!B42 -> adj TMP email | M29: ='[1]jobinfo(2)'!C42 -> 0 | O29: ='[1]jobinfo(2)'!B22 -> Contract Date | P29: ='[1]jobinfo(2)'!C22 -> 45896
H30: ='[1]jobinfo(2)'!B15 -> rebuild type 3 | I30: ='[1]jobinfo(2)'!C15 -> interior repairs BSMNT | J30: ='[1]jobinfo(2)'!B32 -> DA Ph. Ext. # | K30: ='[1]jobinfo(2)'!C32 -> 0 | O30: ='[1]jobinfo(2)'!B19 -> Replacement | P30: ='[1]jobinfo(2)'!C19 -> Y
H31: ='[1]jobinfo(2)'!B16 -> DEMO | I31: ='[1]jobinfo(2)'!C16 -> Y | J31: ='[1]jobinfo(2)'!B33 -> DA Email | K31: ='[1]jobinfo(2)'!C33 -> 0 | O31: ='[1]jobinfo(2)'!B23 -> Loss of use/ ALE | P31: ='[1]jobinfo(2)'!C23 -> TBD | Q31: ='[1]jobinfo(2)'!B18 -> Other Structures | R31: ='[1]jobinfo(2)'!C18 -> NA
H32: ='[1]jobinfo(2)'!B17 -> Mitigation | I32: ='[1]jobinfo(2)'!C17 -> Y | K32: ='[1]jobinfo(2)'!B20 -> CPS / CLN / CON/ CGN | L32: ='[1]jobinfo(2)'!C20 -> NA | O32: ='[1]jobinfo(2)'!B24 -> Breathing issue | P32: ='[1]jobinfo(2)'!C24 -> TBD | Q32: ='[1]jobinfo(2)'!B25 -> HMR | R32: ='[1]jobinfo(2)'!C25 -> TBD
H34: ESTIMATES | J34: BEST CASE SCENARIO | N34: MOST LIKELY | Q34: WORST CASE SCENARIO
J35: 1 | K35: SUB | L35: =K21 -> Wayside Builders, LLC | N35: 0.7 | O35: =L35 -> Wayside Builders, LLC | Q35: 0.5 | R35: =K35 -> SUB
H36: Roof & EXT Mitigation TEMP. & EMERGENCY REPAIRS | J36: 1 | K36: 0 | L36: =J36*K36 -> 0 | N36: =J36*$N$35 -> 0.7 | O36: =N36*K36 -> 0 | Q36: =J36*$Q$35 -> 0.5 | R36: =Q36*K36 -> 0 | U36: 0.5 | V36: 0.5
H37: TREE & EXT Mitigation TEMP. & EMERGENCY REPAIRS | J37: 1 | K37: 0 | L37: =J37*K37 -> 0 | N37: =J37*$N$35 -> 0.7 | O37: =N37*K37 -> 0 | Q37: =J37*$Q$35 -> 0.5 | R37: =Q37*K37 -> 0
H38: Mitigation INTERIOR | J38: 33149.78 | K38: 0.2 | L38: =J38*K38 -> 6629.956 | N38: =J38*$N$35 -> 23204.846 | O38: =N38*K38 -> 4640.9692 | Q38: =J38*$Q$35 -> 16574.89 | R38: =Q38*K38 -> 3314.978 | U38: 0.66 | V38: 0.33
H39: Contents_ PERSONAL PROPERTY Packout = CPS | J39: 0 | K39: 0.2 | L39: =J39*K39 -> 0 | N39: =J39*$N$35 -> 0 | O39: =N39*K39 -> 0 | Q39: =J39*$Q$35 -> 0 | R39: =Q39*K39 -> 0 | U39: 0.66 | V39: 0.33
H40: REBUILD Interior & EXTERIOR | J40: =97116.91-J38-4 -> 63963.13 | K40: 0.8 | L40: =J40*K40 -> 51170.504 | N40: =J40*$N$35 -> 44774.191 | O40: =N40*K40 -> 35819.353 | Q40: =J40*$Q$35 -> 31981.565 | R40: =Q40*K40 -> 25585.252 | U40: 0.8 | V40: 0.2
H41: Roof & EXT REBUILD | J41: 1 | K41: 0 | L41: =J41*K41 -> 0 | N41: =J41*$N$35 -> 0.7 | O41: =N41*K41 -> 0 | Q41: =J41*$Q$35 -> 0.5 | R41: =Q41*K41 -> 0
H42: PERSONAL PROPERTY REPLACEMENT Customer's * | J42: 0 | K42: 0.1 | L42: =J42*K42 -> 0 | N42: =J42*$N$35 -> 0 | O42: =N42*K42 -> 0 | Q42: =J42*$Q$35 -> 0 | R42: =Q42*K42 -> 0 | U42: 0.66 | V42: 0.33
H43: TOTALS | J43: =SUM(J36:J42) -> 97115.91 | L43: =SUM(L36:L42) -> 57800.46 | N43: =SUM(N36:N42) -> 67981.137 | O43: =SUM(O36:O42) -> 40460.322 | Q43: =SUM(Q36:Q42) -> 48557.955 | R43: =SUM(R36:R42) -> 28900.23
H45: ESTIMATES | J45: BEST CASE SCENARIO | N45: POTENTIAL ADDITIONAL FUNDS | Q45: WORST CASE SCENARIO
J46: 1 | K46: APC | N46: 0.7 | O46: =L46 -> 0 | Q46: 0.5 | R46: =K46 -> APC
H47: Roof & EXT Mitigation TEMP. & EMERGENCY REPAIRS | J47: =J36 -> 1 | K47: =100%-K36 -> 1 | L47: =J47*K47 -> 1 | N47: =J47*$N$35 -> 0.7 | O47: =N47*K47 -> 0.7 | Q47: =J47*$Q$35 -> 0.5 | R47: =Q47*K47 -> 0.5
H48: TREE & EXT Mitigation TEMP. & EMERGENCY REPAIRS | J48: 1 | K48: =100%-K37 -> 1 | L48: =J48*K48 -> 1 | N48: =J48*$N$35 -> 0.7 | O48: =N48*K48 -> 0.7 | Q48: =J48*$Q$35 -> 0.5 | R48: =Q48*K48 -> 0.5
H49: Mitigation INTERIOR | J49: =J38 -> 33149.78 | K49: =100%-K38 -> 0.8 | L49: =J49*K49 -> 26519.824 | N49: =J49*$N$35 -> 23204.846 | O49: =N49*K49 -> 18563.877 | Q49: =J49*$Q$35 -> 16574.89 | R49: =Q49*K49 -> 13259.912
H50: Contents_ PERSONAL PROPERTY Packout = CPS | J50: 0 | K50: =100%-K39 -> 0.8 | L50: =J50*K50 -> 0 | N50: =J50*$N$35 -> 0 | O50: =N50*K50 -> 0 | Q50: =J50*$Q$35 -> 0 | R50: =Q50*K50 -> 0
H51: REBUILD Interior & EXTERIOR | J51: =J40 -> 63963.13 | K51: =100%-K40 -> 0.2 | L51: =J51*K51 -> 12792.626 | N51: =J51*$N$35 -> 44774.191 | O51: =N51*K51 -> 8954.8382 | Q51: =J51*$Q$35 -> 31981.565 | R51: =Q51*K51 -> 6396.313
H52: Roof & EXT REBUILD | J52: 1 | K52: =100%-K41 -> 1 | L52: =J52*K52 -> 1 | N52: =J52*$N$35 -> 0.7 | O52: =N52*K52 -> 0.7 | Q52: =J52*$Q$35 -> 0.5 | R52: =Q52*K52 -> 0.5
H53: PERSONAL PROPERTY REPLACEMENT Customer's * | J53: 0 | K53: =100%-K42 -> 0.9 | L53: =J53*K53 -> 0 | N53: =J53*$N$35 -> 0 | O53: =N53*K53 -> 0 | Q53: =J53*$Q$35 -> 0 | R53: =Q53*K53 -> 0
H54: TOTALS | J54: =SUM(J47:J53) -> 97115.91 | L54: =SUM(L47:L53) -> 39315.45 | N54: =SUM(N47:N53) -> 67981.137 | O54: =SUM(O47:O53) -> 27520.815 | Q54: =SUM(Q47:Q53) -> 48557.955 | R54: =SUM(R47:R53) -> 19657.725
H55: GROSS TOTAL TO DATE | J55: HENDKING
H56: REBUILD Interior & EXTERIOR | J56: =J54 -> 97115.91 | K56: APC
H57: Mitigation INTERIOR | J57: =-J49 -> -33149.78
J58: =J57+J56 -> 63966.13
I59: 0.2 | J59: =-J58*I59 -> -12793.226 | K59: =-J59 -> 12793.226
J60: =J58+J59 -> 51172.904
H62: advance | J62: -20000
J63: =J60+J62 -> 31172.904
H65: repayment | J65: 14000 | K65: =-J65 -> -14000
J66: 1
J67: =J63+J65 -> 45172.904
H68: advance | J68: 7000
J70: =J67+J68 -> 52172.904
H73: Mitigation INTERIOR
I74: =J49 -> 33149.78
I75: 0.2 | J75: =I74*I75 -> 6629.956 | K75: =I74-J75 -> 26519.824
J76: =J70+J75 -> 58802.86 | K76: =SUM(K59:K75) -> 25313.05 | N76: 33150
N77: 36917.18 | Q77: =N77 -> 36917.18
N78: =N76+N77 -> 70067.18 | Q78: =K82 -> 7836.73
N79: 20000 | Q79: =+Q77+Q78 -> 44753.91
J80: =J76+K76 -> 84115.91 | K80: =I74 -> 33149.78 | L80: MIT TOTAL T APC | N80: =N78+N79 -> 90067.18 | Q80: =+N81 -> 7048.73
J81: =-J62 -> 20000 | K81: =-K76 -> -25313.05 | L81: NET DUE | N81: =J84-N80 -> 7048.73 | O81: DEPRECIATION HELD
J82: =J80+J81 -> 104115.91 | K82: =K80+K81 -> 7836.73 | L82: DUE IAN/HARDROCK | N82: =+N80+N81 -> 97115.91 | Q82: =SUM(Q79:Q81) -> 51802.64
J83: =-J68 -> -7000
J84: =J82+J83 -> 97115.91

Sheet LISTS ENC
D1: HOW2
A2: L3 | B2: 3 LEVELS NO ROOF; 2NDFLOOR WATER LEAK ; CPS [Y] | D2: RETREIVE
B3: 3 LEVELS NO ROOF; 2NDFLOOR WATER LEAK ; CPS [N]
B4: ATTIC ROOMS ONLY
B5: All Room list Fire Smoke All
A8: L3 | B8: 3 LEVELS HOUSE; NO ROOF; 2NDFLOOR WATER LEAK ; CPS [Y] | D8: Jobsite Verification
B9: Jobsite Verification | K9: Living Room,
B10: LEVEL1 = PRIMARY ROOM [A]
B11: Garage,
B12: FOYER, | K12: Dining Room,
B13: Guest Closet, | K13: Kitchen,
B14: Living Room, | K14: Nook,
B15: Dining Room, | K15: Pantry,
B16: Kitchen, | K16: Hallway,
B17: Nook, | K17: Linen Closet,
B18: Pantry | K18: Bedroom 1,
B19: Hallway, | K19: Bedroom Closet 1,
B20: Linen Closet, | K20: Bedroom 2,
B21: DEN/SUNROOM/REC ROOM
B22: BATH GUEST
B23: FOYER, REAR/SIDE
B24: STAIRS UP
B25: ADD A ROOM LEVEL 1
B27: LEVEL1 = POTENTIAL ADDITIONAL ROOMS [B]
B28: OFFICE
B29: LAUNDRY
B30: Primary Bedroom,
B31: PBR Closet 1
B32: PBR Closet 2
B33: PBR Bathroom,
... B43: BATH UP
B44: Bedroom 1, | K44: Bedroom Closet 2,
B45: BR1 Closet | K45: Primary Bedroom,
B46: Bedroom 2 | K46: Primary Bedroom Closet 2,
B47: BR2 Closet | K47: Primary Bathroom,
B48: Bath 2
B49: Primary Bedroom, | K49: Rec Room/ office,
B50: PBR Closet 1 | K50: Garage,
B51: PBR Closet 2
B52: PBR Bathroom, | K52: Guest Bathroom
B54: LEVEL 2 = POTENTIAL ADDITIONAL ROOMS [B]
B55: Rec Room/ office,
B56: LINEN CLOSET 2
B57: Bath 3
B58: Rec Room/ office,
B60: LEVEL BASEMENT = PRIMARY ROOMS [A]
B61: FOYER SIDE ENTRY
B62: STAIRS TO BASEMENT
B63: FAMILYROOM/MAN CAVE
B64: UTILITY ROOM
B65: LAUNDRY ROOM
B66: Bathroom DN
... B123: Interior list & ROOF
B128: 1. 1.Jobsite Verification (Address Photos) | D128: Foyer DN
B129: 2. 2.Source of Loss Pics (ROOMS / STRUCTURAL) , | D129: Living Room DN
B130: 3. 3.FOYER/ENTRY ROOM, | D130: Guest Closet DN
B131: 4. ROOM2
B132: 5. ROOM3 | D132: Dining Room DN
B133: 6. ROOM4 | D133: Hallway DN @ BR&BATH
B134: 7. ROOM5 | D134: Bedroom 1 DN
B135: 8. 4. CPS1 DAY 1 CONTENTS ROOM OVERVIEW / DOCUMENT PICS | D135: Primary BR DN
B136: 9. 5. CPS2 DAY2 CONTENTS OVERVIEW WIP BOXES PACKOUT PICS, | D136: Primary BR Closet DN
B137: 10. 6. CPS3 DAY3 CONTENTS OVERVIEW STORAGE MOVE OUT PICS, | D137: Bedroom 2 DN
B138: 11. 7. CPS4 CONTENTS OVERVIEW PACK-BACK / RESET PICS, | D138: BR 2 Closet DN
B139: 12. 8. MITIGATION EQUIPMENT OVERVIEW INTERIOR & WIP, | D139: Bathroom DN
B140: 13. 9. MITIGATION Readings Moisture = MC, | D140: Linen Closet DN
B141: 14. 10. MITIGATION READINGS = RH, TEMP F & DEH & EXTERIOR, | D141: Kitchen DN
B142: 15. 11. REPLACEMENT 1 CON OVERVIEW DAY PICS, | D142: Pantry Down DN
B143: 16. 12. REPLACEMENT 2 CON WIP, | D143: Hallway/ Closet Dn
... B163: 36. ROOM LABELS | D163: 3rd Floor Up Stairs
D164: 3rd Floot Bedroom Closet
D165: 3rd Floor Bedroom/REC 1
D166: 3rd Floor Living Room
D167: 3rd Floor Kitchen
D168: 3rd Floor Storage 1
D169: 3rd Floor Hallway Bedroom
B170: Interior list & ROOF / 5DAY MIT | D170: 3rd Floor Closet Hall
B171: 1. Jobsite Verification (Address Photos), | D171: 3rd Floor Guest Closet 1
B172: 2. Source of Loss Pics (ROOMS / STRUCTURAL) , | D172: 3rd Floor Guest Closet 2
B173: 3.FOYER/ENTRY ROOM, | D173: Bathroom 3rd Floor
B174: 5. CPS2 DAY2 CONTENTS OVERVIEW WIP BOXES PACKOUT PICS, | D174: 3RD FLR Storage 2
B175: 6. CPS3 DAY3 CONTENTS OVERVIEW STORAGE MOVE OUT PICS , | D175: 3rd Floor Porch
B176: 7. CPS4 CONTENTS OVERVIEW PACK-BACK / RESET PICS, | D176: Basement COMMON AREA ====
B177: 8. MITIGATION EQUIPMENT OVERVIEW INTERIOR & WIP , | D177: Laundry Room
B178: 9. MITIGATION Readings Moisture = MC, | D178: STORAGE RR
B179: 10. MITIGATION READINGS = RH, TEMP F & DEH & EXTERIOR, | D179: === MITIGATION LABELS =====
B180: 11. REPLACEMENT 1 CON OVERVIEW DAY PICS, | D180: Mitigation Equipment
B181: 12. REPLACEMENT 2 CON WIP, | D181: STABILIZATION
... B192: RHT DAY 4, | D192: PPR REPLACEMENT ITEMS
B193: RHT DAY 5,
B194: MC DAY1 ,
B195: MC DAY 2,
B196: MC DAY3,
B197: MC DAY 4,
B198: MC DAY 5,
B199: STABILIZATION READINGS,
B200: MIT LABELS,
B201: ROOM LABELS
B204: Jobsite Verification & Source of Loss
B205: 1. Jobsite Verification (Address Photos)
...

Sheet kit bath
B1: =+'[2]jobinfo(2)'!$C$1 -> MONTGOMERY, JAVIONNA ANTONIO | C1: =+'[2]jobinfo(2)'!$C$2 -> 3034 Ashwood Road, | E1: =+'[2]jobinfo(2)'!$C$3 -> Cleveland, OH, USA 44120 | F1: ='[2]jobinfo(2)'!$C$11 -> WATER BATHTUB OVER | T1: ='[2]jobinfo(2)'!$C$5 -> (216) 551-5572
B2: Kitchen | C2: CABINETS | E2: Type /Quality / Grade:
B3: Standard- Builder Grade / High Grade / Premium / Deluxe / CUSTOM
A4: BASE | C4: _______________ | D4: _______________ | E4: _______________ | F4: LF total =____________
B5: SB SIZE | C5: _______________ | D5: _______________ | E5: _______________
B6: DB SIZE | C6: _______________ | D6: _______________ | E6: _______________
B7: B ____SIZES | C7: _______________ | D7: _______________ | E7: _______________
B8: SPECIALTY | C8: _______________ | D8: _______________ | E8: _______________
C9: _______________ | D9: _______________ | E9: _______________
C10: _______________ | D10: _______________ | E10: _______________
B11: UPPER Cabinets | C11: _______________ | D11: _______________ | E11: _______________ | F11: LF total =____________
B12: WIDTH X HEIGHT | C12: _______________
C13: _______________
B14: FULL HEIGHT CAB | C14: _______________
B16: COUNTER TOP | C16: FORMICA | D16: GRANITE | E16: OTHER __________ | F16: SF total =____________
C17: NOTES:
B18: APPLIANCES
B19: REFRIGERATOR | E19: ICE MAKER
B20: STOVE/OVEN | C20: GAS or ELECTRIC | E20: BUILT IN or Stand Alone
B21: Micro wave | C21: __________________________ | E21: BUILT IN or Stand Alone
B22: EXHAUST/VENT FAN | C22: __________________________ | E22: BUILT IN or Stand Alone
B23: Dishwasher | C23: __________________________ | E23: BUILT IN or Stand Alone
B24: Garbage disposal
B26: BATHROOM
B27: VANITY | C27: SIZE _________ | D27: GRADE ________ | E27: ____ COUNTER TOP __________
B28: TOWEL RACKS | C28: QTY =
B29: BATHTUB | E29: __________________________ | F29: ___________________
B30: Shower surround Type | C30: SIZE _________ | D30: GRADE ________ | E30: __________________________
B31: Shower doors | C31: Shower Curtain & Rod
B32: VENT FAN

Sheet BLD codes
A1: 3137.11 Conformity With National Electrical Code
A3: § 3131.06 Repairs after Fire Damage Whenever the operation of a system has been the cause of a fire, such system shall not be used or operated until it has been inspected by the Commissioner and such alterations and changes made as are deemed necessary by him or her to permit safe operation of the system, and no alterations or repairs shall be made without a permit issued by the Commissioner.
A4: § 3131.08 Firestopping (a) Where the installation of pipes or ducts in walls or partitions requires the removal of any firestopping, the space around the pipes or ducts at the points where firestopping was removed shall be tightly filled with mineral wool or other noncombustible insulating material. (b) Where pipes, ducts, stacks, or fittings pass through a floor construction, all open spaces around them shall be filled with mineral wood, or other incombustible insulating material. (c) Whenever baseboard or wall registers located at the top of supply or return air ducts are installed in stud framed walls or partitions or in construction having concealed interior spaces, an approved firestop shall be installed approximately three (3) inches above such register or grille. In stud framed construction such firestops shall extend the full width and depth of the stud space.
A8: Cleveland, OH primarily adopts the International Residential Code (IRC) for residential buildings.
A9: The city may also reference the International Building Code (IBC) for certain aspects of construction.
A11: Ensure compliance with zoning regulations that may affect residential construction.
A13: Always verify the latest code updates, as building regulations can change frequently.
A16: § 3137.11 Conformity With National Electrical Code Except as otherwise provided in this Building Code, or in statutes, or in rules or regulations promulgated by authority of statute, all electrical wiring and equipment shall be in accordance with the provisions of NFiPA 70 entitled “National Electrical Code,” as listed in OAC Chapter 4101:2-46.
A18: § 3137.12 Residential Electrical Rehabilitation (a) Scope. The provisions of this section shall apply to the rehabilitation of electrical systems in one (1), two (2) and three (3) familydwelling units when they have been determined to be inadequate as specified in subsection (b) hereof.
A20: dwelling units when they have been determined to be inadequate as specified in subsection (b)
A21: hereof.
A22: (b) Evidence of inadequate Wiring. Evidence of inadequate wiring shall include one (1) or more of
... A109: tenant, excepting those dwellings where the owner pays for the energy consumed.

Sheet docs
A1: DOCS Table of Contents
B2: 01 Info Page Only
A3: O | B3: JOB INFO
A4: O | B4: =+'quick chklst'!A1 -> BASIC SUMMARY OF RESTORATION PROCESS; (Quick version).
A6: O | B6: =+#REF! -> #REF!
A7: O | B7: =ENC!#REF! -> #REF!
A8: O | B8: =ENC!A1 -> ENCIRCLE
A9: O | B9: =+#REF! -> #REF!
A10: O | B10: =+#REF! -> #REF!
A11: O | B11: =+'how2'!A115 -> Note on creating the New Custmer Contract & Docs
A12: O | B12: JOB INFO (2) …......... for exporting

Sheet XACTIMATE
A1: Xactimate NEW PROJECTS | B1: ='jobinfo(2)'!C51 -> OH25THOMAS@GERTRUDE
A2: 00. SKETCH SKTH | B2: DMO | D2: XACT Supplement[SPLM]
A3: 01 Rebuild, RBLD | B3: 90 CPS | C3: PPR
A4: 65, exterior mitigation EXT-EMS | B4: 80. Interior Mitigation EMS MIT
A5: INSURED INFO
A6: NAME | B6: EMAIL
A7: =+'jobinfo(2)'!C1 -> THOMAS, ANITA | B7: =+'jobinfo(2)'!C4 -> A@EM
A8: ADDRESS TYPE | B8: HOME | C8: DEFAULT
A9: STREET | B9: CITY | C9: STATE / ZIP CODE | D9: COUNTRY
A10: =+'jobinfo(2)'!C2 -> 6600 GERTRUDE | B10: =+'jobinfo(2)'!C3 -> Cleveland, OH 44105 | D10: USA
A11: PHONE Type | B11: CELLULAR | C11: =+'jobinfo(2)'!C5 -> (216) 315-2040
A13: DATES Date Entered | B13: DATE ASSIGNED | C13: EST. COMPLETED | D13: JOB COMPLETED
A14: =+'jobinfo(2)'!C22 -> 45836 | B14: TBD | C14: TBD | D14: TBD
A16: PERSONNEL | B16: ESTIMATOR | D16: REFERENCE -== Insurance Co. Name
B17: ='jobinfo(2)'!C112 -> Joe Jones, PM 216.450.7228 | D17: =+'jobinfo(2)'!C26 -> ALLSTATE INS CO.
A19: Type Of Estimate/LOSS | B19: Deductible | C19: File Number = Claim # | D19: ='jobinfo(2)'!B28 -> policy #
A20: =+'jobinfo(2)'!C11 -> Water Damage=WTR | B20: tbd | C20: =+'jobinfo(2)'!C27 -> CLM | D20: =+'jobinfo(2)'!C28 -> 880 022 226
A22: XACTIMATE | B22: NEW CUSTOMER INFO | D22: PAGE 2
A23: PARAMETERS
A25: PRICING
A26: Checkpoint Price List | B26: Price List | C26: Tax Jurisdiction | D26: Price lIst filter
A27: N/A | B27: =B10 -> Cleveland, OH 44105 | C27: HIGHEST AVAILABLE | D27: N/A
B28: =+'jobinfo(2)'!C12 -> Friday, September 12, 2025
A29: REPRICE | B29: N/A | C29: N/A | D29: CONTRACTOR
A31: ADD ONS | B31: N/A | C31: [__] | D31: ='jobinfo(2)'!C100 -> All Phase Consulting, LLC
A33: Depreciation Options | C33: N/A
A35: Overhead and Profit (O&P) | B35: Overhead | C35: Profit
B36: 0.1 | C36: 0.1 | D36: N/A
A38: Report Text | B38: COMPANY HEADER | C38: =+'jobinfo(2)'!C100 -> All Phase Consulting, LLC
B39: OPENING STATEMENT | C39: APC FULL STATEMENT | D39: DEFAULT =APC
B40: CLOSING STATEMENT | C40: THNAK YOU | D40: DEFAULT =APC
A42: SUPPLIED OR ENTERED BY OTHERS
A43: SKETCHES | B43: Retrieve | C43: FLR PLAN @ ENCIRCLE | D43: IMPORT FPLN | F43: Thought For The Day
A44: SCOPE INPUT | B44: Retrieve | C44: [__] | F44: You can tell whether a man is clever by his answers.
A45: =+'jobinfo(2)'!B53 -> Room/Area 101 | B45: =+'jobinfo(2)'!C53 -> Living Room, | C45: =+'jobinfo(2)'!B66 -> Room/Area 14 | D45: =+'jobinfo(2)'!C66 -> STAIRS TO BASEMENT | F45: You can tell whether a man is wise by his questions.
A46: =+'jobinfo(2)'!B54 -> Room/Area 102 | B46: =+'jobinfo(2)'!C54 -> GUEST CLOSET | C46: =+'jobinfo(2)'!B67 -> Room/Area 15 | D46: =+'jobinfo(2)'!C67 -> LAUNDRY/UTILITY ROOM
A47: =+'jobinfo(2)'!B55 -> Room/Area 103 | B47: =+'jobinfo(2)'!C55 -> Dining Room, | C47: =+'jobinfo(2)'!B68 -> Room/Area 16 | D47: =+'jobinfo(2)'!C68 -> STORAGE UNDER STAIRS
A48: =+'jobinfo(2)'!B56 -> Room/Area 104 | B48: =+'jobinfo(2)'!C56 -> DEN | C48: =+'jobinfo(2)'!B69 -> Room/Area 17 | D48: =+'jobinfo(2)'!C69 -> STORAGE ROOM # 1
A49: =+'jobinfo(2)'!B57 -> Room/Area 105 | B49: =+'jobinfo(2)'!C57 -> Kitchen, | C49: =+'jobinfo(2)'!B70 -> Room/Area 18 | D49: =+'jobinfo(2)'!C70 -> STORAGE ROOM # 2
A50: =+'jobinfo(2)'!B58 -> Room/Area 106 | B50: =+'jobinfo(2)'!C58 -> STAIRS UP | C50: =+'jobinfo(2)'!B71 -> Room/Area 19 | D50: =+'jobinfo(2)'!C71 -> STORAGE ROOM # 3
A51: =+'jobinfo(2)'!B59 -> Room/Area 107 | B51: =+'jobinfo(2)'!C59 -> HALL UP | C51: =+'jobinfo(2)'!B72 -> Room/Area 20 | D51: =+'jobinfo(2)'!C72 -> 0
A52: =+'jobinfo(2)'!B60 -> Room/Area 8 | B52: =+'jobinfo(2)'!C60 -> LINEN CLOSET | C52: =+'jobinfo(2)'!B73 -> Room/Area 21 | D52: =+'jobinfo(2)'!C73 -> 0
A53: =+'jobinfo(2)'!B61 -> Room/Area 9 | B53: =+'jobinfo(2)'!C61 -> BATH UP | C53: =+'jobinfo(2)'!B74 -> Room/Area 22 | D53: =+'jobinfo(2)'!C74 -> 0
A54: =+'jobinfo(2)'!B62 -> Room/Area 10 | B54: =+'jobinfo(2)'!C62 -> Bedroom 1, | C54: =+'jobinfo(2)'!B75 -> Room/Area 23 | D54: =+'jobinfo(2)'!C75 -> 0
A55: =+'jobinfo(2)'!B63 -> Room/Area 11 | B55: =+'jobinfo(2)'!C63 -> BR1 Closet | C55: =+'jobinfo(2)'!B76 -> Room/Area 24 | D55: =+'jobinfo(2)'!C76 -> 0
A56: =+'jobinfo(2)'!B64 -> Room/Area 12 | B56: =+'jobinfo(2)'!C64 -> Bedroom 2 | C56: =+'jobinfo(2)'!B77 -> Room/Area 25 | D56: =+'jobinfo(2)'!C77 -> 0
A57: =+'jobinfo(2)'!B65 -> Room/Area 13 | B57: =+'jobinfo(2)'!C65 -> BR2 Closet
A60: 1. Xactimate Supplements [SPLM]
B61: 01 Rebuild
B62: 65 Exterior mitigation
B63: 80 Interior mitigation
B64: 90 CPS
B65: Other
D74: 00 | E74: 00 SKETCH | H74: UPLOAD TO ENCIRCLE
D75: 65 | E75: 65, exterior mitigation | I75: =1+#REF! -> #REF!
D76: 70 | E76: 80, Interior mitigation | I76: =1+I75 -> #REF!
E77: Misc/Other Xactimate | I77: =1+#REF! -> #REF!
B78: XACTIMATE = Estimates Supplemental [SPLM] | D78: 01 | E78: 01 Rebuild | I78: =1+I77 -> #REF!
D79: 65 | E79: 65, exterior mitigation | I79: =1+I78 -> #REF!
D80: 70 | E80: 80, Interior mitigation | I80: =1+I79 -> #REF!
D81: 90 | E81: 90 CPS | I81: =1+I80 -> #REF!
E82: Misc/Other Xactimate | I82: =1+I81 -> #REF!
B83: MICA or ENCIRCLE or XACTIMATE | E83: 80 | I83: MICA or ENCIRCLE
A84: Staff Notifications
A85: ENCIRCLE | B85: ENCIRCLE NEW CUSTOMER CREATED | F85: CREATED INSIDE ENCIRCLE AS INDIVIDUAL ROOMS = 1 REPORT SET UP | I85: ENCIRCLE
B86: cklst 60 contract rep docs/initial pics | E86: 60
B87: cklst 70 interior scope | E87: 70
B88: cklst 80 int mitigation | E88: 80
B89: cklst 90 CON CPS 01 | E89: 90
B93: 01 Rebuild
B94: 65 Exterior mitigation
B99: 80 Interior mitigation
B100: 90 CPS
B101: Other

Sheet ENC
A1: ENCIRCLE | B1: CLAIM INBOX | D1: NEW CUSTOMER INFO
A3: Claim Identifier
A4: CARRIER IDENTIFIER | B4: CONTRACTOR IDENTIFIER | D4: ASSIGNMENT IDENTIFIER
A5: ='jobinfo(2)'!C27 -> CLM | B5: ='jobinfo(2)'!C51 -> OH25THOMAS@GERTRUDE | D5: =B5 -> OH25THOMAS@GERTRUDE
A7: Policyholder Details
A8: POLICYHOLDER NAME | B8: POLICYHOLDER EMAIL | C8: POLICYHOLDER PHONE NUMBER
A9: =+'jobinfo(2)'!C1 -> THOMAS, ANITA | B9: =+'jobinfo(2)'!C4 -> A@EM | D9: =+'jobinfo(2)'!C5 -> (216) 315-2040
A11: Address Details
A12: ADDRESS
A13: =+'jobinfo(2)'!C2 -> 6600 GERTRUDE | B13: =+'jobinfo(2)'!C3 -> Cleveland, OH 44105
A15: Claim Details
A16: DATE OF LOSS | D16: POLICY NUMBER
A17: ='jobinfo(2)'!C12 -> Friday, September 12, 2025 | D17: =+'jobinfo(2)'!C28 -> 880 022 226
A18: DATE CLAIM CREATED | C18: PROJECT MANAGER
A19: ='jobinfo(2)'!C22 -> 45836 | C19: ='jobinfo(2)'!C112 -> Joe Jones, PM 216.450.7228
A20: TYPE OF LOSS | D20: CAT CODE
A21: ='jobinfo(2)'!C11 -> Water Damage=WTR | D21: TBD
A22: INSURANCE COMPANY | C22: CLAIM SUMMARY (LOSS DETAILS)
A23: ='jobinfo(2)'!C26 -> ALLSTATE INS CO. | C23: INPUT DETAILS/INFO PROVIDED
A24: ADJUSTER
A25: ='jobinfo(2)'!C30 -> 0
A26: BROKER / AGENT
A27: AS NEEDED

Sheet how2
B1: Insurance Customer new contract "HOW TO CREATE"
A2: 1 | B2: Open the Computer to Microsoft Excel and open "Checklists/Estimates /" file.
A4: 2 | B4: Go to sheet "(job info" tab) Verify company name and or update
B5: To update Go to sheet/tab COMPANY HEADER (co header)
B6: Selct and copy header info and paste into contract tab/sheet @ A1
B7: Template - A | C7: WSB TJ | D7: Template - C | E7: APC JJ
B8: Template - B | C8: WSB JJ GA | D8: Template - D | E8: WSB JJ OH
B10: Or go to google drive and open/download file template
C11: (File, Open, Browse, Checklist, New Customer)
A12: 3 | B12: After Opening file Template, Save As A New File: | E12: Required
B13: Create (New) Sub-Folder for job, inside "Estimates" Folder,
B14: Or go to google drive and upload the new file open/download file template
B15: Save as per file naming format (See Below)
C16: City/Area - Year-Company- Customer Name - Job Type - Insurer Abbreviation
B17: example = ATL 2019 Brown 05 RFG- SFI
A18: Job Types & Codes: | C18: Roofing = RFG | D18: Wind=Wind | E18: TREE
C19: Water Damage=WTR | D19: Hurricane =HURR | E19: FIRE
A21: 4 | B21: Go to ….. "job info(2)"….. tab & Enter Data:
B22: If info is already in job info tab then erase info, enter TBD in all cells or overwrite existing data with new info.
B23: A} | C23: Customer Info | E23: Required
B24: B} | C24: Loss/damage Info | E24: Required
B25: C} | C25: Insurer Info (policy # required) | E25: Required
B26: D} | C26: Room Index/AREA ID (If Available) | E26: Required
B27: E} | C27: Mortgage company info; if applicable & when available (loan status)
A29: 5 | B29: Brief Claim Narrative (if Available) | E29: Required
A31: 6 | B31: Save File
A33: 7 | B33: Print entire workbook as PDF; save to new named folder (see above)
B34: print areas are preset, for some tabs only one page may print , as per design
A35: 8 | B35: Email PDF as attachment (subject = contract docs out to customer name):
A36: 9 | B36: Include MOU {PDF}(copy & paste job info tab to update or use stock form)
A37: CC: | B37: A} | C37: manage.apc@gmail.com | E37: Required
B38: B} | C38: Field Rep.
B39: C} | C39: Customer
A40: 10 | B40: Upload a copy to Google Drive | E40: Required
B41: Estimates = Proof of Loss Supporting Documentation | E41: work in progress 10192019
A42: 1 | B42: Index of Required Pictures
B43: ********* Using the ENCIRCLE & APC APP will guide you thru this process *********
B45: Pictures are a critical part of the full process for payment !!!
B46: Estimates = Proof of Loss Supporting Documentation
A47: 2 | B47: Open the following file templates and update or use "Master Forms Field Docs Template"
B48: Mitigation$_______ | D48: WTR | E48: (File, Open,Browse
B49: Demo $________ | D49: New CST
B50: Rebuild $________ | D50: WTR
B51: Contents $________ | D51: Sub Contractor
A54: 3 | B54: After Opening file Template, Save As A New File: | E54: Required
B55: Create (New) Sub-Folder for job, inside Estimates Folder,
B57: Save as per file naming format (See Below)
C58: City/Area - Year - Customer Name - Job Type - Insurer Abbreviation
C59: example = Atl - 2019 - Brown - RFG- SFI
A60: Job Types & Codes: | C60: Roofing = RFG | D60: Wind=Wind | E60: TREE
C61: Mitigation$_______ | D61: Hurricane =HURR | E61: FIRE
C63: Demo $________ | E63: ( File, Open, Browse )
C64: Rebuild $________
C65: Contents $________
A67: 4 | B67: Go to job info tab & Enter Data:
B68: Copy & paste job info tab to update or use stock form)
B70: ROOF & EXTERIOR MITIGATION
B72: INTERIOR MITIGATION & DEMO
C73: DEMOLITION DMO
C74: SECONDARY DAMAGES HAZARDOUS MATERIALS REMEDIATION/HMR
C75: MITIGATION EQUIPMENT
C76: DRY LOGS DOCS & TRIP MONITORING
B79: CONTENTS;
B80: a | C80: PACKOUT Storage Only
B81: b | C81: Cleaning INHOUSE
B82: c | C82: Cleaning Sent to outside vendor
B83: d | C83: CONTENTS, REPLACEMENT ITEMS CPS / CON
B85: REBUILD CLOSEOUT
A87: OFS DOCS | B87: cklst 01 Job info page only | D87: 01
B88: BINDER TABS
B89: cklst 20 Intial contact Forms POI | D89: 20
B90: cklst 30 Insurer,, mtge ,, cst | D90: 30
B91: cklst 25 CLAIM BRIEF | C91: 25 | D91: 25
B92: cklst 99 cashflow | D92: 99
A94: CUSTOMER | B94: cklst 50 contract sig pgs | D94: 50
B95: cklst 51 contract notary pgs | D95: 51
B96: cklst 52 claim reporting info | D96: 52
B97: cklst 56 MOU | D97: 56
A99: REP / CREW @ JOB | B99: cklst 60 contract rep docs | D99: 60
B100: Order EagleView, ROOF QS __ | D100: PREM report____Xact EV#_____
B101: 00 Pics ENCIRCLE NEW CST CREATED
B103: cklst 65 Ext mitigation Roof | D103: 65
B104: cklst 70 interior scope | D104: 70
B105: cklst 80 int mitigation | D105: 80
B106: cklst 90 CON CPS 01 | D106: 90
B107: cklst 1155 Job Forms ONLY | D107: 155
A115: Note on creating the New Custmer Contract & Docs
A117: Actually we send an individualized preprinted contract and associated docs to each customer.
A118: See next email for info that we need to create those docs.
A120: Also, we will send over to you the Excel file
A121: The Excel populates the individualized preprinted contract and associated docs.
A123: So you may use the email to gather the info and
A124: then copy and paste into the Excel "contract doc".
A126: Or you may enter the info directly into the Excel file and
A127: then create a PDF file to forward to the customer for signature.
A128: See the HOW TO tab or below in the Excel file for further details.
A130: This process creates the following:
A132: professional-looking documents
... A137: Please recall that we also working to create an app that serves;
B138: the young single person, first-time homeowner,
...
