Workbook
Name a...new_customer: #REF!
Name a...new_customer: #REF!
Name a...new_customer: #REF!
Name basicroompichow2: #REF!
Name box_names: +#REF!
Name Column.a.new.cst: #REF!
Name culpepper: #REF!
Name data: #REF!
Name Document_Stacking_List: #REF!
Name Enter_new_cst_data: #REF!
Name Jefferies: #REF!
Name LOVEJOY_INTERIOR: #REF!
Name Lovejoy_ROOF: #REF!
Name LxWxH: #REF!
Name new_customer: #REF!
Name PRICE_P: #REF!
Name Robinson: #REF!
Name sigtj: "Picture 9859"
Name SubContractor_Summary: #REF!
Name Wayside_Builders__LLC_…...OH: #REF!
Name WSB...GA.Wayside_Builders__LLC……GA: #REF!

Sheet docs
A1: DOCS Table of Contents
B2: 01 Info Page Only
A3: O | B3: JOB INFO
A4: O | B4: =+'quick chklst'!A1 -> BASIC SUMMARY OF RESTORATION PROCESS; (Quick version).
A6: O | B6: =+#REF! -> #REF!
A7: O | B7: =ENC!#REF! -> #REF!
A8: O | B8: =ENC!A1 -> ENCIRCLE
A9: O | B9: =+#REF! -> #REF!
A10: O | B10: =+#REF! -> #REF!
A11: O | B11: =+'how2'!A115 -> Note on creating the New Custmer Contract & Docs
A12: O | B12: JOB INFO (2) …......... for exporting

Sheet quick chklst
A1: BASIC SUMMARY OF RESTORATION PROCESS; (Quick version). | D1: =+'jobinfo(2)'!C2 -> 3922 E 189 STR
A2: JOB | C2: =+'jobinfo(2)'!C51 -> OH25 BROWNLEE @E189 | D2: =+'jobinfo(2)'!C3 -> CLEVELAND, OH 44128
A3: 1 | B3: Introduction, Analysis & Verification | C3: Introduction, Analysis & Verification /source/referred by: | D3: Status Notes / %
C4: Who is the Insurance Company ?!? | D4: ='jobinfo(2)'!C26 -> ALLSTATE INS CO. | G4: 100
A5: POI | C5: Does customer Comprehend Our Role in the process? | D5: Y
C6: Is this a COVERED INSURANCE Claim? Or Self Pay ? | D6: Y
C7: IS THE DAMAGE $ MORE THAN THE DEDUCTIBLE? | D7: Y
C8: Do they have coverage; for AOB? = POLICY & DEC PAGE | D8: Y | G8: 200
A9: 2 | B9: Contracts & Documentation | C9: Contracts & Documentation | D9: Y
C10: Has Customer been fully advised of Contract Contents? | D10: Y
C11: Has Customer had a full Consultation to Our Terms & Conditions? | D11: Y | G11: 500
A12: DOC | C12: Does Customer FULLY Agree to Terms &Conditions? Signed / Initials? | D12: Y
C13: Notary Page explained/ Fast track | D13: Y
A14: mou | C14: Company investment (dollars, time ,materials)into their Project? | D14: Y
C15: Mutual trust , cooperation & confidence | D15: Y
A16: 3 | C16: CLAIM REPORTING;DOES THE CUSTOMER HAVE REQUIRED INFO? | D16: Y
A17: INS | C17: Insurer Mitigation / DMO / CPS Approval Info Sheet | D17: Y | G17: 100
A18: PICS | C18: Create ENCIRCLE project (Pictures critical part of PAYMENTprocess! | D18: Y
A19: mit | B19: Mitigation & Demolition | C19: Mitigation & Demolition (ROOM LABELS POSTED)
A20: 4 | C20: Roof & EXT Mitigation TEMPORARY & EMERGENCY REPAIRS | D20: Y | G20: 1000
A21: 5 | C21: Contents_ item list_; storage details; security explained? | D21: Y | G21: 2000
A22: 6 | C22: Interior Mitigation; household disruption explained? | D22: NA | G22: 2000
C23: HMR / Secondary Damages; Equipment & Electricity $ | D23: NA
A24: esx | B24: Estimates | C24: Estimates (Inspection/Scope Form)
C25: SKETCH/DRAWING;[1] sheet per floor
A26: 7 | C26: Interior & EXTERIOR REBUILD | G26: 200
C27: EXTERIOR MITIGATION | D27: Y
C28: INTERIOR Mitigation & Demolition | D28: NA
A29: 8 | B29: Insurance Company Meetings | C29: Insurance Company Meetings
A30: adj | C30: Docs for adjuster meeting; Print & bind docs BE PRESENT WHEN ADJUSTER VISITS The PROPERTY. | G30: 500
A31: 9 | B31: Cashflow General Contractor / Subcontracts | C31: Cashflow General Contractor / Subcontracts
A32: job | C32: Contents
A33: 10 | B33: Mitigation & Demolition | C33: & EXterior Mitigation & Demolition
B34: Interior Mitigation & Demolition | C34: Closeout Interior Mitigation & Demolition
C35: Rebuild
G36: =SUM(G1:G35) -> 6600
C37: BASIC SUMMARY OF RESTORATION PROCESS; (Quick version). | D37: =+'jobinfo(2)'!$C$2 -> 3922 E 189 STR
A38: JOB | C38: =+'jobinfo(2)'!C51 -> OH25 BROWNLEE @E189 | D38: =+'jobinfo(2)'!$C$3 -> CLEVELAND, OH 44128
A39: 1 | B39: Introduction, Analysis & Verification | C39: Introduction, Analysis & Verification /source/referred by: | D39: ='jobinfo(2)'!$C$27 -> CLM
C40: Who is the Insurance Company ?!? | D40: ='jobinfo(2)'!$C$26 -> ALLSTATE INS CO.
A41: POI | C41: Does customer Comprehend DEDUCTABLE PAYMENT? PAID____
C42: Do they have coverage; for AOB? = POLICY & DEC PAGE
A43: 2 | B43: Contracts & Documentation | C43: Contracts & Documentation
A44: Customer full Consultation to Our Terms & Conditions? Comprehend Our Role in process?
C45: CONTRACT SIGNED / Notary Page explained/ Fast track
A46: mou | C46: Mutual trust/cooperation & confidence/Company investment dollars, time ,materials?
A47: 3 | C47: CLAIM REPORTING;DOES THE CUSTOMER HAVE REQUIRED INFO?
A48: INS | C48: Insurer Mitigation / DMO / CPS Approval Info Sheet
A49: EGV | C49: Order REPORT ; Eagleview Roof/ Siding / PLUMBERS / FIRE / POLICE
A50: PICS | C50: Create ENCIRCLE project; ENTER NEW CUSTOMER INFO; SHARE 2 TEAM
C51: Create ENCIRCLE FLOOR PLAN & VERIFY COMPLETE
A52: EXCEL | C52: CREATE EXCEL FILE; Copy & Paste DATA from Encircle
C53: RUN EXCEL MACRO & VERIFY
A55: mit | B55: Mitigation & Demolition | C55: Mitigation & Demolition (ROOM LABELS POSTED)
A56: CREATE & SEND; MIT EQUIPMENT SETUP / CPS / ROOMS SCOPE FORM /
A57: 4 | C57: Roof & EXT Mitigation TEMPORARY & EMERGENCY REPAIRS
A58: 5 | C58: Contents_ item list_; storage details; security explained?
A59: 6 | C59: Interior Mitigation; household disruption explained?
C60: HMR / Secondary Damages; Equipment & Electricity $
A61: esx | B61: Estimates | C61: CREATE XACTIMATE PROJECT; Copy & Paste DATA from Encircle
C62: GET Inspection/Scope Form [ ENCIRCLE or Genius Scan]
A63: IMPORT The ENCIRCLE FLOOR PLAN to XACTIMATE/ CREATE PROJECT SKETCH
C64: EXTERIOR MITIGATION
A65: 7 | C65: INTERIOR Mitigation & Demolition
C66: Interior & EXTERIOR REBUILD
C67: Contents
A68: 8 | B68: Insurance Company Meetings | C68: Insurance Company Meetings ENCIRCLE FLOOR PLAN & SCOPE SHEET
A69: adj | C69: Adjuster meeting DOCS; Print & bind docs / PRESENT FOR ADJUSTER VISITS
C70: ENCIRLE / EXCEL / XACTIMATE REPORTS: …Retrieve/DOWNLOAD REPORTS; (Create as needed)
C71: MIT …. Ext & INT …...CPS….... REPL = CON …..... REBUILD
C72: EMAIL Estimates & REPORTS to Insurer.
A73: 9 | B73: Cashflow General Contractor / Subcontracts | C73: Cashflow General Contractor / Subcontracts
C74: Followup & Collect Payments
A75: job | C75: Contents
A76: 10 | B76: Mitigation & Demolition | C76: & EXterior Mitigation & Demolition
B77: Interior Mitigation & Demolition | C77: Closeout Interior Mitigation & Demolition
C78: Interior & EXTERIOR REBUILD
A79: BASIC JOB WORKFLOW | D79: ='jobinfo(2)'!$C$51 -> OH25 BROWNLEE @E189
A80: Has Customer had a full Consultation to WORK PROCESS | D80: ='jobinfo(2)'!$C$1 -> BROWNLEE, KEN
A81: explain | C81: CPS; storage details; security explained? | D81: ='jobinfo(2)'!$C$2 -> 3922 E 189 STR
C82: INT MIT DMO household disruption?
C83: MIT EQUIPMENT RUNNING (3 DAYS); ELECTRIC BILL REIMBURSEMENT | D83: ='jobinfo(2)'!$C$4 -> KHAIAKEN@SBCGLOBAL.NET
D84: ='jobinfo(2)'!$C$5 -> 2163241337
C86: Create ENCIRCLE project (Pictures critical part of PAYMENTprocess!)
A87: CREW TO …...... JOB | C87: Create & Post room Labels (Traffic Area = foot coverings) | D87: ='jobinfo(2)'!$C$27 -> CLM
C88: Verify & Add Rooms to Encircle; as needed; Verify | D88: ='jobinfo(2)'!$C$11 -> WATER
C89: Take Room Overview Pics = …. Job Scope FORM | D89: ='jobinfo(2)'!$C$12 -> 45986
C90: Inspection/Scope Form [Send to ENCIRCLE or via Genius scan] | D90: ='jobinfo(2)'!$C$13 -> interior repairs LVL1
C91: Take CPS # 1 Pics contents Overview Pics ... (CPS#2, Cps#3, CPS#4) | D91: ='jobinfo(2)'!$C$14 -> interior repairs LVL2
C92: Scan/Create Floor Plan / Submit to Encircle; / Print Copy for Adjuster | D92: ='jobinfo(2)'!$C$15 -> 0
C94: MITIGATION CHECKLIST/WORK FLOW
C95: Set Up Basic Equipment….... / ....... Protect Contents, Floors, & Walls
C97: Roof & EXT / Interior Mitigation TEMPORARY & EMERGENCY REPAIRS
C98: INTERIOR Mitigation & Demolition; household disruption explained?
C99: Interior & EXTERIOR REBUILD Estimates (Inspection/Scope Forms)
C100: Contents_ item list_; storage details; security explained?
C102: CREATE EXCEL FILE; Copy & Paste DATA from Encircle
C103: Run Excel Macro; create Templates & Subfolders
C104: Enter Room Sizes (from Encircle Floor Plan) & Damage Percentages %: @ jobinfo2
C105: Calculate MIT Equipment (MITEqpmnt ALL) & Deliver To Jobsite/Set Up Equipment
...

Sheet OFS INITIAL CKLST
B1: OFFICE QUICKLIST | D1: ='jobinfo(2)'!C1 -> BROWNLEE, KEN
A2: INITIAL DOCS IN ( to start claim)
A3: 1 | B3: VERIFY / ASSESS DAMAGE; Full Consultation to Our Terms/Conditions? MOU Our Role in process? | C3: REQUEST IN & OUT | E3: 201
A4: 2 | B4: POLICY & DEC PAGE = ACV or Replacement Do they have coverage; | C4: REQUEST IN | D4: ='jobinfo(2)'!C2 -> 3922 E 189 STR | E4: =E3+1 -> 202
A5: 3 | B5: Does customer Comprehend AOB? DEDUCTABLE PAYMENT? PAID____ | C5: REQUEST IN | E5: =E4+1 -> 203
A6: 4 | B6: Create ENCIRCLE project; CONTRACT SIGNED / Notary Page explained = Fast track ….AOB? | C6: REQUEST SENT & IN | E6: =E5+1 -> 204
A7: 5 | B7: JOBSITE VERIFICATION PICS & ROOMS VIDEO …..& SHORT ROOM LIST... (upon initial visit) | C7: CREATE | D7: ='jobinfo(2)'!B5 -> Cst-owner Phone# | E7: =E6+1 -> 205
A8: INITIAL DOCS OUT TO CUSTOMER ( to start claim) | D8: ='jobinfo(2)'!C5 -> 2163241337 | E8: =E7+1 -> 206
A9: 6 | B9: CLAIM REPORTING Info Sheet;Insurer Approval [Mitigation/DMO/CPS] DOCUMENT CONTACT | C9: REQUEST SENT & IN | E9: =E8+1 -> 207
A10: 7 | B10: MOU SENT OUT TO CUSTOMER | C10: REQUEST SENT & IN | D10: ='jobinfo(2)'!C4 -> KHAIAKEN@SBCGLOBAL.NET | E10: =E9+1 -> 208
A11: INITIAL REPORTS/DOCS GENERATED ( to start claim) | E11: =E10+1 -> 209
A12: 8 | B12: Order REPORT ..; Eagleview Roof / …. Siding / ….. PLUMBERS / …. FIRE / …..POLICE | C12: CREATE | E12: =E11+1 -> 210
B13: LEAD HMR TESTING
A14: 9 | B14: ENCIRCLE FLOOR PLAN …................... CREATED @ JOBSITE | C14: CREATE | E14: =E12+1 -> 211
A15: 10 | B15: Create ENCIRCLE Project; ROOM LISTS….. SHARE 2 TEAM Option ( V2 then Merge) | C15: CREATE | E15: =E14+1 -> 212
B16: SELECT JOB TYPE per STOCK ROOM LISTS; = WTR / FIRE or RFG & WTR | C16: CREATE | D16: ='jobinfo(2)'!C26 -> ALLSTATE INS CO. | E16: =E15+1 -> 213
B17: Determine / Input job Room names per jobsite visit ROOM ORDER SET-UP | C17: CREATE | E17: =E16+1 -> 214
B18: GENERATE ROOM LABELS & CPS BOX LABELS ; EMAIL OUT | C18: CREATE | E18: =E17+1 -> 215
B19: 100 ROOMS Overview / 360 = Scope Form | C19: CREATE | E19: =E18+1 -> 216
B20: 400 SOURCE OF LOSS 500 CPS DAY 1 / 2 / 3 / 4 | C20: CREATE | E20: =E19+1 -> 217
B21: 800 MIT W.I.P. & EQPT Mitigation LABELS (Demolition) | C21: CREATE | E21: =E20+1 -> 218
B22: READINGS DAY 1 / 2 / 3 / 4 … 6000 MC & 7000 RHT+GPP | C22: CREATE | E22: =E21+1 -> 219
A23: 12 | B23: IMPORT & EDIT The ENCIRCLE FLOOR PLAN (PRINT AS NEEDED) | C23: IN | E23: =E22+1 -> 220
A24: 13 | B24: (UPDATE AS NEEDED) CREATE ROOM Names LISTS in ENCIRCLE & EXCEL | E24: =E23+1 -> 221
A25: 14 | B25: RUN EXCEL MACRO & VERIFY TEMPLATES | C25: CREATE | D25: ='jobinfo(2)'!C27 -> CLM | E25: =E24+1 -> 222
A26: AUTOMATE THE FOLLOWING | E26: =E25+1 -> 223
A27: GENERATE LABELS = ROOMS / CPS BOXES / MITIGATION EQUIPTMENT PLACEMENT; …. | C27: EMAIL OUT | E27: =E26+1 -> 224
A28: 16 | B28: RUN EXCEL MACRO 4 MITIGATION WORK & EQUIPMENT | C28: CREATE | E28: =E27+1 -> 225
A29: 17 | B29: CREATE & SEND; ROOMS SCOPE FORM (FUTURE = 360 CAMERA) | C29: EMAIL OUT
A30: 19 | B30: Mitigation LABELS (Demolition) | C30: EMAIL OUT
A31: 20 | B31: Enter Room Sizes (from Encircle Floor Plan) & Damage Percentages %: @ jobinfo2 | C31: CREATE
A32: 21 | B32: Calculate MIT Equipment (MIT Eqpmnt ALL) & Deliver To Jobsite/Set Up Equipment | C32: EMAIL OUT
B33: CREATE & SEND; MIT EQUIPMENT SETUP WORK & EQUIPMENT FORM | C33: EMAIL OUT
A34: 22 | B34: Calculate/Estimate CPS Supplies | C34: EMAIL OUT
A35: 23 | B35: Order & Deliver to Jobsite…..... Packout Supplies = boxes / tape / shrink wrap | C35: EMAIL OUT
A36: 24 | B36: GET Inspection/Scope Form [ ENCIRCLE or Genius Scan] sent from app | C36: REQUEST IN
A37: 25 | B37: CREATE XACTIMATE PROJECT; (Copy & Paste DATA from Encircle)
B38: Estimates
A40: 26
A41: 27
A42: 28
A43: 29
A44: 30
A45: 31
I46: JOBSITE FLOW SHEET
I47: ACCESS or Create ENCIRCLE project; SHARE 2 TEAM
I48: Create ENCIRCLE FLOOR PLAN & VERIFY COMPLETE
I49: ='quick chklst'!C54 -> 0
I50: BASIC SUMMARY OF RESTORATION PROCESS; (Quick version). | J50: =+'jobinfo(2)'!$C$2 -> 3922 E 189 STR
G51: JOB | I51: =+'jobinfo(2)'!C138 -> ALLSTATE INS CO. | J51: =+'jobinfo(2)'!$C$3 -> CLEVELAND, OH 44128
G52: PICS | I52: Create ENCIRCLE project; ENTER NEW CUSTOMER INFO; SHARE 2 TEAM
I53: Create ENCIRCLE FLOOR PLAN & VERIFY COMPLETE
G54: CREATE & SEND; MIT EQUIPMENT SETUP / CPS / ROOMS SCOPE FORM /
G55: mit | H55: Mitigation & Demolition | I55: Mitigation & Demolition (ROOM LABELS POSTED)
G56: 4 | I56: Roof & EXT Mitigation TEMPORARY & EMERGENCY REPAIRS
G57: 5 | I57: Contents_ item list_; storage details; security explained?
G58: 6 | I58: Interior Mitigation; household disruption explained?
I59: HMR / Secondary Damages; Equipment & Electricity $
I60: GET Inspection/Scope Form [ ENCIRCLE or Genius Scan]
I61: EXTERIOR MITIGATION
G62: 7 | I62: INTERIOR Mitigation & Demolition
I63: Interior & EXTERIOR REBUILD
I64: Contents
G65: 8 | H65: Insurance Company Meetings | I65: Insurance Company Meetings ENCIRCLE FLOOR PLAN & SCOPE SHEET
G66: adj | I66: Adjuster meeting DOCS; Print & bind docs / PRESENT FOR ADJUSTER VISITS
I67: MIT …. Ext & INT …...CPS….... REPL = CON …..... REBUILD
G68: job | I68: Contents
G69: 10 | H69: Mitigation & Demolition | I69: & EXterior Mitigation & Demolition
H70: Interior Mitigation & Demolition | I70: Closeout Interior Mitigation & Demolition
I71: Interior & EXTERIOR REBUILD
G72: BASIC JOB WORKFLOW | J72: ='jobinfo(2)'!$C$51 -> OH25 BROWNLEE @E189
G73: Has Customer had a full Consultation to WORK PROCESS | J73: ='jobinfo(2)'!$C$1 -> BROWNLEE, KEN
G74: explain | I74: CPS; storage details; security explained? | J74: ='jobinfo(2)'!$C$2 -> 3922 E 189 STR
I75: INT MIT DMO household disruption?
I76: MIT EQUIPMENT RUNNING (3 DAYS); ELECTRIC BILL REIMBURSEMENT | J76: ='jobinfo(2)'!$C$4 -> KHAIAKEN@SBCGLOBAL.NET
J77: ='jobinfo(2)'!$C$5 -> 2163241337
I78: Create ENCIRCLE project (Pictures critical part of PAYMENTprocess!)
G79: CREW TO …...... JOB | I79: Create & Post room Labels (Traffic Area = foot coverings) | J79: ='jobinfo(2)'!$C$27 -> CLM
I80: Verify & Add Rooms to Encircle; as needed; Verify | J80: ='jobinfo(2)'!$C$11 -> WATER
I81: Take Room Overview Pics = …. Job Scope FORM | J81: ='jobinfo(2)'!$C$12 -> 45986
I82: Inspection/Scope Form [Send to ENCIRCLE or via Genius scan] | J82: ='jobinfo(2)'!$C$13 -> interior repairs LVL1
I83: Take CPS # 1 Pics contents Overview Pics ... (CPS#2, Cps#3, CPS#4) | J83: ='jobinfo(2)'!$C$14 -> interior repairs LVL2
I84: Scan/Create Floor Plan / Submit to Encircle; / Print Copy for Adjuster | J84: ='jobinfo(2)'!$C$15 -> 0
I85: MITIGATION CHECKLIST/WORK FLOW
I86: Set Up Basic Equipment….... / ....... Protect Contents, Floors, & Walls
I87: Roof & EXT / Interior Mitigation TEMPORARY & EMERGENCY REPAIRS
I89: INTERIOR Mitigation & Demolition; household disruption explained?
I90: Interior & EXTERIOR REBUILD Estimates (Inspection/Scope Forms)
I91: Contents_ item list_; storage details; security explained?
I93: Enter Room Sizes (from Encircle Floor Plan) & Damage Percentages %: @ jobinfo2
I94: Calculate MIT Equipment (MITEqpmnt ALL) & Deliver To Jobsite/Set Up Equipment
I95: Calculate CPS Supplies & Deliver to Jobsite…..... Packout Contents; boxes/tape/wrap
I97: ENCIRLE / EXCEL / XACTIMATE REPORTS: …Retrieve/DOWNLOAD REPORTS; (Create as needed)
G98: Email # 1 1 & 2 . CONTRACT . 3. W9 .4. JOB VERIFICATION /SOURCE OF LOSS
G99: 5. MIT.. CPS .. REBUILD ,,, REPLACE ITEMS 6. XACT INVOICE & ESX
G100: Email # 2 … 7..ROOMS Overview …./.. 8. MIT CPS REBUILD REPLACE /… 9. TMPL30 /…10 OTHER

Sheet jobinfo(2)
A1: Customer | B1: Property-Owner Name | C1: BROWNLEE, KEN | O1: Enter info here | S1: ADD SOS LINK
B2: Property address: street | C2: 3922 E 189 STR | O2: New Customer Info required | P2: NEEDS TO SELF POPULATE | S2: LINK TO VIDEOS
B3: Property city, state, zip | C3: CLEVELAND, OH 44128 | S3: BEFORE AND AFTER P[CS
B4: Customer Email | C4: KHAIAKEN@SBCGLOBAL.NET | S4: CLE ATL NY NC NY
B5: Cst-owner Phone# | C5: 2163241337
B6: Co-Owner.cst#2 | C6: NA
B7: cst ph # 2 | C7: NA | S7: RFG WIP…CURRENT JOBS
B8: Cst address # 2 | C8: NA | S8: SIGNAGE
B9: city, state-cst#2 | C9: NA
B10: email-cst #2 | C10: NA
A11: Loss Info | B11: Cause of Loss | C11: WATER | O11: Wind = Roof | P11: Water Damage=WTR | Q11: Fire Smoke | R11: Wind=Tree | S11: Hurricane =HURR
B12: date of loss | C12: 45986 | O12: rebuild type
B13: rebuild type 1 | C13: interior repairs LVL1 | O13: roofing shingles replacement | Q13: fencing
B14: rebuild type 2 | C14: interior repairs LVL2 | O14: interior repairs | Q14: shed
B15: rebuild type 3 | O15: exterior repairs | Q15: porch patio
B16: DEMO | C16: Y | O16: Y
B17: Mitigation | C17: Y | O17: Y
B18: Other Structures | C18: NA | O18: Y
A19: CPS | B19: Replacement | C19: Y | O19: Y
B20: CPS / CLN / CON/ CGN | C20: Y | O20: Y
B21: Year Built | C21: 1956 | O21: TBD
B22: Contract Date | C22: =C12+1 -> 45987 | O22: TBD | P22: pre 1980 | Q22: post 1980
B23: Loss of use/ ALE | C23: Y | O23: sample cost 3
B24: Breathing issue | C24: TBD | O24: doctor letter
B25: HMR | C25: TBD | O25: lab test
B26: Insurance Co. Name | C26: ALLSTATE INS CO. | O26: Insurance Company Supplied Info | P26: Per declaration pages | R26: 34-H-6822C9-2
A27: Insurance Co. | B27: Claim # | C27: CLM | P27: Assigned by Insurer
B28: policy # | C28: PL3\ | P28: Per declaration pages | Q28: OFP DWF 7266580
B29: Email INS. co. | C29: claims@claims.allstate.com | P29: Per declaration pages
B30: DESK Adjuster DA | P30: Assigned by Insurer
B31: DA Phone | P31: customer service rep
B32: DA Ph. Ext. # | P32: Hazel
B33: DA Email | P33: 43789
B34: Field Adjuster Name | P34: 5pm
B35: Phone # field adj
B36: Field adj email
B37: adj contents | P37: Assigned by Insurer
B38: adj CPS phone #
B39: adj CPS email
B40: TMP adj | P40: Assigned by Insurer
B41: TMP adj phone #
B42: adj TMP email
B43: ATT: Loss Draft Dept. | P43: =+P26 -> Per declaration pages
B44: address ins overnight mail
B45: city, state-zip ins
B46: Insurance Co. Phone
B47: Website Ins Co.
B48: Mailing address INS
B49: Mail city, state, zip INS | P49: Leave Label/ID tag in place for each room/area until final completion !!!
B50: FAX Ins. Co
B51: NEW CUSTOMER # | C51: OH25 BROWNLEE @E189 | D51: ='ROOMS-out'!H115 -> 100 | E51: ='ROOMS-out'!J115 -> 200 | F51: ='ROOMS-out'!L115 -> 300 | G51: ='ROOMS-out'!N115 -> 400 | H51: ='ROOMS-out'!P115 -> 500 | I51: ='ROOMS-out'!R115 -> 600 | J51: ='ROOMS-out'!T115 -> 700 | K51: ='ROOMS-out'!X115 -> 9100
B52: ROOM ID | C52: =C1 -> BROWNLEE, KEN | D52: ='ROOMS-out'!H113 -> OVERVIEW PICS .. | E52: ='ROOMS-out'!J113 -> SOURCE of LOSS | F52: ='ROOMS-out'!L113 -> CPS | G52: ='ROOMS-out'!N113 -> PPR | H52: ='ROOMS-out'!P113 -> DEMO | I52: ='ROOMS-out'!R113 -> WTR MIT EQUIP. | J52: ='ROOMS-out'!T113 -> HMR | K52: ='ROOMS-out'!U113 -> 0 | M52: Scope | N52: Pics | O52: Floor 1 | P52: Floor 2 | Q52: BASEMENT | R52: Affected Areas, Include Line of Sight room /areas
A53: 1 | B53: Room/Area 101 | C53: Living Room, | D53: =D51+1 -> 101 | E53: =E51+1 -> 201 | F53: =F51+1 -> 301 | G53: =G51+1 -> 401 | H53: =H51+1 -> 501 | I53: =I51+1 -> 601 | J53: =J51+1 -> 701 | K53: =K51+1 -> 9101 | O53: Foyer | P53: Stairs UP | Q53: Basement | R53: ROOM Name & Number | S53: LOCATION & Basic damage / work Description
A54: 2 | B54: Room/Area 102 | C54: HALLWAY | D54: =D53+1 -> 102 | E54: =E53+1 -> 202 | F54: =F53+1 -> 302 | G54: =G53+1 -> 402 | H54: =H53+1 -> 502 | I54: =I53+1 -> 602 | J54: =J53+1 -> 702 | K54: =K53+1 -> 9102 | O54: Guest Closet | P54: Bathroom | Q54: Stairs 1 | R54: example # 0 = Master bedroom | S54: Ceilings N corner | T54: repair water damage drywall paint
A55: 3 | B55: Room/Area 103 | C55: Kitchen, | D55: =D54+1 -> 103 | E55: =E54+1 -> 203 | F55: =F54+1 -> 303 | G55: =G54+1 -> 403 | H55: =H54+1 -> 503 | I55: =I54+1 -> 603 | J55: =J54+1 -> 703 | K55: =K54+1 -> 9103 | O55: Front Hall | P55: Hallway- up | Q55: Storage | T55: Scope | U55: Pics | V55: Sketch
A56: 4 | B56: Room/Area 104 | C56: DEN | D56: =D55+1 -> 104 | E56: =E55+1 -> 204 | F56: =F55+1 -> 304 | G56: =G55+1 -> 404 | H56: =H55+1 -> 504 | I56: =I55+1 -> 604 | J56: =J55+1 -> 704 | O56: Living Room | P56: Linen CLST | Q56: Hallway- DN | R56: {#=_1_} | S56: {____} | U56: {_______} {_ _____}
A57: 5 | B57: Room/Area 105 | C57: STAIRS UP | D57: =D56+1 -> 105 | E57: =E56+1 -> 205 | F57: =F56+1 -> 305 | G57: =G56+1 -> 405 | H57: =H56+1 -> 505 | I57: =I56+1 -> 605 | J57: =J56+1 -> 705 | O57: Dining Room | P57: Bedroom # 1 | Q57: Laundry | R57: Room/Area 1
A58: 6 | B58: Room/Area 106 | C58: HALL UP | D58: =D57+1 -> 106 | E58: =E57+1 -> 206 | F58: =F57+1 -> 306 | G58: =G57+1 -> 406 | H58: =H57+1 -> 506 | I58: =I57+1 -> 606 | J58: =J57+1 -> 706 | O58: Hallway- DN | P58: Closet BR # 1 | Q58: Utility
A59: 7 | B59: Room/Area 107 | C59: PBR UP | D59: =D58+1 -> 107 | E59: =E58+1 -> 207 | F59: =F58+1 -> 307 | G59: =G58+1 -> 407 | H59: =H58+1 -> 507 | I59: =I58+1 -> 607 | J59: =J58+1 -> 707 | O59: DEN | P59: Bedroom # 2 | Q59: Man cave
A60: 8 | B60: Room/Area 8 | C60: BATH UP | D60: =D59+1 -> 108 | E60: =E59+1 -> 208 | F60: =F59+1 -> 308 | G60: =G59+1 -> 408 | H60: =H59+1 -> 508 | I60: =I59+1 -> 608 | J60: =J59+1 -> 708 | O60: FAMILY ROOM | P60: Closet BR # 2 | Q60: Crawlspace
A61: 9 | B61: Room/Area 9 | C61: BR-2 UP | D61: =D60+1 -> 109 | E61: =E60+1 -> 209 | F61: =F60+1 -> 309 | G61: =G60+1 -> 409 | H61: =H60+1 -> 509 | I61: =I60+1 -> 609 | J61: =J60+1 -> 709 | O61: Kitchen | P61: Bedroom # 3 | Q61: EXTERIOR | S61: Jobsite Verification (Address Photos)
A62: 10 | B62: Room/Area 10 | C62: GUEST CLOSET | D62: =D61+1 -> 110 | E62: =E61+1 -> 210 | F62: =F61+1 -> 310 | G62: =G61+1 -> 410 | H62: =H61+1 -> 510 | I62: =I61+1 -> 610 | J62: =J61+1 -> 710 | O62: Pantry | P62: Closet BR # 3 | Q62: Roof shingle replace | S62: Source of Loss Pics
A63: 11 | B63: Room/Area 11 | C63: BATH DN | D63: =D62+1 -> 111 | E63: =E62+1 -> 211 | F63: =F62+1 -> 311 | G63: =G62+1 -> 411 | H63: =H62+1 -> 511 | I63: =I62+1 -> 611 | J63: =J62+1 -> 711 | O63: Nook | P63: Master Bedroom | Q63: Vinyl siding | S63: FOYER/ENTRY ROOM
A64: 12 | B64: Room/Area 12 | C64: SHOWER | D64: =D63+1 -> 112 | E64: =E63+1 -> 212 | F64: =F63+1 -> 312 | G64: =G63+1 -> 412 | H64: =H63+1 -> 512 | I64: =I63+1 -> 612 | J64: =J63+1 -> 712 | O64: Guest Bath | P64: Master BR Closet | Q64: fencing
A65: 13 | B65: Room/Area 13 | D65: =D64+1 -> 113 | E65: =E64+1 -> 213 | F65: =F64+1 -> 313 | G65: =G64+1 -> 413 | H65: =H64+1 -> 513 | I65: =I64+1 -> 613 | J65: =J64+1 -> 713 | O65: Office | P65: Master Bathroom | Q65: shed
A66: 14 | B66: Room/Area 14 | D66: =D65+1 -> 114 | E66: =E65+1 -> 214 | F66: =F65+1 -> 314 | G66: =G65+1 -> 414 | H66: =H65+1 -> 514 | I66: =I65+1 -> 614 | J66: =J65+1 -> 714 | O66: SUNROOM | Q66: exterior repairs
A67: 15 | B67: Room/Area 15 | D67: =D66+1 -> 115 | E67: =E66+1 -> 215 | F67: =F66+1 -> 315 | G67: =G66+1 -> 415 | H67: =H66+1 -> 515 | I67: =I66+1 -> 615 | J67: =J66+1 -> 715 | O67: ATTIC | Q67: Porches
A68: 16 | B68: Room/Area 16 | D68: =D67+1 -> 116 | E68: =E67+1 -> 216 | F68: =F67+1 -> 316 | G68: =G67+1 -> 416 | H68: =H67+1 -> 516 | I68: =I67+1 -> 616 | J68: =J67+1 -> 716 | O68: Storage | Q68: Garage
A69: 17 | B69: Room/Area 17 | D69: =D68+1 -> 117 | E69: =E68+1 -> 217 | F69: =F68+1 -> 317 | G69: =G68+1 -> 417 | H69: =H68+1 -> 517 | I69: =I68+1 -> 617 | J69: =J68+1 -> 717 | O69: Stairs 2 | Q69: Deck/patio
A70: 18 | B70: Room/Area 18 | D70: =D69+1 -> 118 | E70: =E69+1 -> 218 | F70: =F69+1 -> 318 | G70: =G69+1 -> 418 | H70: =H69+1 -> 518 | I70: =I69+1 -> 618 | J70: =J69+1 -> 718 | Q70: yard area
A71: 19 | B71: Room/Area 19 | D71: =D70+1 -> 119 | E71: =E70+1 -> 219 | F71: =F70+1 -> 319 | G71: =G70+1 -> 419 | H71: =H70+1 -> 519 | I71: =I70+1 -> 619 | J71: =J70+1 -> 719 | Q71: Windows
A72: 20 | B72: Room/Area 20 | D72: =D71+1 -> 120 | E72: =E71+1 -> 220 | F72: =F71+1 -> 320 | G72: =G71+1 -> 420 | H72: =H71+1 -> 520 | I72: =I71+1 -> 620 | J72: =J71+1 -> 720
A73: 21 | B73: Room/Area 21 | D73: =D72+1 -> 121 | E73: =E72+1 -> 221 | F73: =F72+1 -> 321 | G73: =G72+1 -> 421 | H73: =H72+1 -> 521 | I73: =I72+1 -> 621 | J73: =J72+1 -> 721
A74: 22 | B74: Room/Area 22 | D74: =D73+1 -> 122 | E74: =E73+1 -> 222 | F74: =F73+1 -> 322 | G74: =G73+1 -> 422 | H74: =H73+1 -> 522 | I74: =I73+1 -> 622 | J74: =J73+1 -> 722
A75: 23 | B75: Room/Area 23 | D75: =D74+1 -> 123 | E75: =E74+1 -> 223 | F75: =F74+1 -> 323 | G75: =G74+1 -> 423 | H75: =H74+1 -> 523 | I75: =I74+1 -> 623 | J75: =J74+1 -> 723
A76: 24 | B76: Room/Area 24 | D76: =D75+1 -> 124 | E76: =E75+1 -> 224 | F76: =F75+1 -> 324 | G76: =G75+1 -> 424 | H76: =H75+1 -> 524 | I76: =I75+1 -> 624 | J76: =J75+1 -> 724
A77: 25 | B77: Room/Area 25 | D77: =D76+1 -> 125 | E77: =E76+1 -> 225 | F77: =F76+1 -> 325 | G77: =G76+1 -> 425 | H77: =H76+1 -> 525 | I77: =I76+1 -> 625 | J77: =J76+1 -> 725
A78: 26 | B78: Mortgage co | D78: =D77+1 -> 126 | E78: =E77+1 -> 226 | F78: =F77+1 -> 326 | G78: =G77+1 -> 426 | H78: =H77+1 -> 526 | I78: =I77+1 -> 626 | J78: =J77+1 -> 726 | O78: Customer Supplied Info | P78: Per mortgage statement
A79: 27 | B79: Account# Mtge Co. | D79: =D78+1 -> 127 | E79: =E78+1 -> 227 | F79: =F78+1 -> 327 | G79: =G78+1 -> 427 | H79: =H78+1 -> 527 | I79: =I78+1 -> 627 | J79: =J78+1 -> 727
A80: 28 | B80: Loan status | D80: =D79+1 -> 128 | E80: =E79+1 -> 228 | F80: =F79+1 -> 328 | G80: =G79+1 -> 428 | H80: =H79+1 -> 528 | I80: =I79+1 -> 628 | J80: =J79+1 -> 728 | P80: Loan status = current, foreclosure, Paid in full, Late days
A81: 29 | B81: contact person mtge | D81: =D80+1 -> 129 | E81: =E80+1 -> 229 | F81: =F80+1 -> 329 | G81: =G80+1 -> 429 | H81: =H80+1 -> 529 | I81: =I80+1 -> 629 | J81: =J80+1 -> 729
A82: 30 | B82: Phone # MTGE contact | D82: =D81+1 -> 130 | E82: =E81+1 -> 230 | F82: =F81+1 -> 330 | G82: =G81+1 -> 430 | H82: =H81+1 -> 530 | I82: =I81+1 -> 630 | J82: =J81+1 -> 730
A83: 31 | B83: Ph. Ext. Mtge contact | D83: =D82+1 -> 131 | E83: =E82+1 -> 231 | F83: =F82+1 -> 331 | G83: =G82+1 -> 431 | H83: =H82+1 -> 531 | I83: =I82+1 -> 631 | J83: =J82+1 -> 731
A84: Mortgage Company | D84: =D83+1 -> 132 | E84: =E83+1 -> 232 | F84: =F83+1 -> 332 | G84: =G83+1 -> 432 | H84: =H83+1 -> 532 | I84: =I83+1 -> 632 | J84: =J83+1 -> 732
B85: Attn.: Loss Draft Dept | D85: =D84+1 -> 133 | E85: =E84+1 -> 233 | F85: =F84+1 -> 333 | G85: =G84+1 -> 433 | H85: =H84+1 -> 533 | I85: =I84+1 -> 633 | J85: =J84+1 -> 733
B86: Mtge OVN mail | D86: =D85+1 -> 134 | E86: =E85+1 -> 234 | F86: =F85+1 -> 334 | G86: =G85+1 -> 434 | H86: =H85+1 -> 534 | I86: =I85+1 -> 634 | J86: =J85+1 -> 734
B87: city, St., zip ,mtge OVN | D87: =D86+1 -> 135 | E87: =E86+1 -> 235 | F87: =F86+1 -> 335 | G87: =G86+1 -> 435 | H87: =H86+1 -> 535 | I87: =I86+1 -> 635 | J87: =J86+1 -> 735
B88: Phone # MTGE co. | D88: =D87+1 -> 136 | E88: =E87+1 -> 236 | F88: =F87+1 -> 336 | G88: =G87+1 -> 436 | H88: =H87+1 -> 536 | I88: =I87+1 -> 636 | J88: =J87+1 -> 736
B89: email mtge | D89: =D88+1 -> 137 | E89: =E88+1 -> 237 | F89: =F88+1 -> 337 | G89: =G88+1 -> 437 | H89: =H88+1 -> 537 | I89: =I88+1 -> 637 | J89: =J88+1 -> 737
B90: mtge website | D90: =D89+1 -> 138 | E90: =E89+1 -> 238 | F90: =F89+1 -> 338 | G90: =G89+1 -> 438 | H90: =H89+1 -> 538 | I90: =I89+1 -> 638 | J90: =J89+1 -> 738
B91: MTGE co. Fax # | D91: =D90+1 -> 139 | E91: =E90+1 -> 239 | F91: =F90+1 -> 339 | G91: =G90+1 -> 439 | H91: =H90+1 -> 539 | I91: =I90+1 -> 639 | J91: =J90+1 -> 739
B92: Mailing address mtge | D92: =D91+1 -> 140 | E92: =E91+1 -> 240 | F92: =F91+1 -> 340 | G92: =G91+1 -> 440 | H92: =H91+1 -> 540 | I92: =I91+1 -> 640 | J92: =J91+1 -> 740
B93: Mail city, state, zip mtge | D93: =D92+1 -> 141 | E93: =E92+1 -> 241 | F93: =F92+1 -> 341 | G93: =G92+1 -> 441 | H93: =H92+1 -> 541 | I93: =I92+1 -> 641 | J93: =J92+1 -> 741
D94: =D93+1 -> 142 | E94: =E93+1 -> 242 | F94: =F93+1 -> 342 | G94: =G93+1 -> 442 | H94: =H93+1 -> 542 | I94: =I93+1 -> 642 | J94: =J93+1 -> 742
B95: Initial Offer / phase 1 contract amount | D95: =D94+1 -> 143 | E95: =E94+1 -> 243 | F95: =F94+1 -> 343 | G95: =G94+1 -> 443 | H95: =H94+1 -> 543 | I95: =I94+1 -> 643 | J95: =J94+1 -> 743
B96: Draw Request | D96: =D95+1 -> 144 | E96: =E95+1 -> 244 | F96: =F95+1 -> 344 | G96: =G95+1 -> 444 | H96: =H95+1 -> 544 | I96: =I95+1 -> 644 | J96: =J95+1 -> 744
B97: Cust id | D97: =D96+1 -> 145 | E97: =E96+1 -> 245 | F97: =F96+1 -> 345 | G97: =G96+1 -> 445 | H97: =H96+1 -> 545 | I97: =I96+1 -> 645 | J97: =J96+1 -> 745
D98: =D97+1 -> 146 | E98: =E97+1 -> 246 | F98: =F97+1 -> 346 | G98: =G97+1 -> 446 | H98: =H97+1 -> 546 | I98: =I97+1 -> 646 | J98: =J97+1 -> 746
D99: =D98+1 -> 147 | E99: =E98+1 -> 247 | F99: =F98+1 -> 347 | G99: =G98+1 -> 447 | H99: =H98+1 -> 547 | I99: =I98+1 -> 647 | J99: =J98+1 -> 747
B100: co name | C100: All Phase Consulting, LLC | R100: AK Builders Group LLC | S100: Platinum One Properties, LLC | T100: PROVISO INVESTMENTS | U100: J THOMAS CONTRACTING, LLC | V100: ALL PHASE CONSULTING, LLC | W100: Wayside Builders, LLC | X100: Wayside Builders, LLC | Y100: Alpha Omega Construction | Z100: YASMEEN PROPERTIES.INC
...

Sheet ROOMS#
A1: LISTS | C1: INPUT = ROOM NAMES | E1: LOS / TRAVEL | G1: OUTPUT = | I1: ROOM NAME ADD TO ENCIRCLE ROOM LISTS | K1: LOS / TRAVEL | M1: OUTPUT = ENC ROOM NAME | Q1: LOS / TRAVEL | S1: OUTPUT = ENC ROOM NAME | W1: LOS / TRAVEL | Y1: OUTPUT = ENC ROOM NAME | AC1: LOS / TRAVEL | AE1: ,,,,,, DMO = DEMOLITION ….... | AI1: LOS / TRAVEL | AK1: … WTR MITIGATION EQUIPMENT & W.I.P . ... | AO1: LOS / TRAVEL | AQ1: … HMR MITIGATION EQUIPMENT & W.I.P . ... | AU1: LOS / TRAVEL | AW1: … DAY # 0 … MC READINGS STABILIZATION | BD1: ... DAY1 MC READINGS .. | BI1: LOS / TRAVEL | BK1: ... DAY2 MC READINGS .. | BO1: LOS / TRAVEL | BQ1: ... DAY3 MC READINGS .. | BU1: LOS / TRAVEL | BW1: ... DAY4 MC READINGS | CA1: LOS / TRAVEL | CC1: RH &T & GPP DRY CHAMBERS [DC] .READ INGS | CJ1: DEFAULT TMP1 1 | CL1: WTR METER | CM1: ADD CPS OVERVIEW = MULTIPLE ROOMS / WITH LABELS | CX1: ROOM LABELS
A2: = … JOB/ROOMS OVERVIEW PICS .. | G2: =A2 -> = … JOB/ROOMS OVERVIEW PICS .. | M2: ….. SOURCE of LOSS PICS ….. | S2: ….. C.P.S. …... | Y2: NON SALVAGEABLE ITEMS | AB2: ='ROOMS-out'!I1 -> 0 | AE2: ,,,,,, DMO = DEMOLITION ….... | AK2: ='ROOMS-out'!K1 -> 0 | AQ2: ='ROOMS-out'!Q1 -> 0 | AW2: =AW1 -> … DAY # 0 … MC READINGS STABILIZATION | BD2: .. DAY 1 … | BK2: ….. DAY 2 ….. | BQ2: ….. DAY 3 ….. | BW2: ….. DAY 4 ….. | CC2: ….. DAY 1 ….. | CJ2: KITCHEN CABINETS SIZES | CM2: BATHROOM VANITY SIZE & FIXTURES | CX2: ROOM LABELS
A3: =A4-1 -> 100 | B3: …. | C3: =A2 -> = … JOB/ROOMS OVERVIEW PICS .. | D3: , | E3: ======= | G3: =A3 -> 100 | H3: =B3 -> …. | I3: =G2 -> = … JOB/ROOMS OVERVIEW PICS .. | K3: ====== | M3: 200 | N3: =H3 -> …. | O3: =M2 -> ….. SOURCE of LOSS PICS ….. | P3: ==================== | Q3: ====== | S3: 300 | T3: =N3 -> …. | U3: =S2 -> ….. C.P.S. …... | V3: ============== | W3: ====== | Y3: 400 | Z3: =T3 -> …. | AA3: =Y2 -> NON SALVAGEABLE ITEMS | AB3: ============================== | AE3: 500 | AF3: …. | AG3: =AE2 -> ,,,,,, DMO = DEMOLITION ….... | AH3: ============================== | AI3: ============================== | AK3: 600 | AL3: . | AM3: MITIGATION EQUIPMENT & W.I.P. ================ MIT & WIP === | AO3: ============================== | AQ3: 700 | AR3: . | AS3: =AQ1 -> … HMR MITIGATION EQUIPMENT & W.I.P . ... | AU3: ============================== | AW3: 8000 | AX3: ….. | AY3: ======= DAY # 0 ….. MC READINGS STABILIZATION =============== | BD3: 8100 | BE3: . | BF3: =BD1 -> ... DAY1 MC READINGS .. | BG3: ========= | BH3: =============== | BI3: ===== | BK3: =BD3+100 -> 8200 | BL3: . | BM3: =BK1 -> ... DAY2 MC READINGS .. | BN3: =============== | BO3: ====== | BQ3: =BK3+100 -> 8300 | BR3: . | BS3: =BQ2 -> ….. DAY 3 ….. | BT3: ===================== | BU3: ====== | BW3: =BQ3+100 -> 8400 | BX3: . | BY3: =BW2 -> ….. DAY 4 ….. | BZ3: =============== | CA3: =$E$3 -> ======= | CC3: =CC5-0.1 -> 9099.9 | CD3: =CC1 -> RH &T & GPP DRY CHAMBERS [DC] .READ INGS | CF3: ---------------- | CJ3: 0 | CK3: ….. | CL3: DEFAULT LIST EXISTS (AS BELOW); CLICK DROPDOWN MENU; ADD JOB TYPES AS NEEDED | CX3: =C3 -> = … JOB/ROOMS OVERVIEW PICS .. | CY3: =========
A4: 101 | B4: …. | C4: ='jobinfo(2)'!C53 -> Living Room, | D4: , | E4: …......... | G4: =A4 -> 101 | H4: =B4 -> …. | I4: =C4 -> Living Room, | J4: =$G$2 -> = … JOB/ROOMS OVERVIEW PICS .. | K4: =$E$4 -> …......... | M4: =M3+1 -> 201 | N4: =H4 -> …. | O4: =I4 -> Living Room, | P4: =$M$2 -> ….. SOURCE of LOSS PICS ….. | Q4: =$E$4 -> …......... | S4: =S3+1 -> 301 | T4: =N4 -> …. | U4: =O4 -> Living Room, | V4: =$S$2 -> ….. C.P.S. …... | W4: =$E$4 -> …......... | Y4: =Y3+1 -> 401 | Z4: =T4 -> …. | AA4: =U4 -> Living Room, | AB4: =$Y$2 -> NON SALVAGEABLE ITEMS | AC4: =$E$4 -> …......... | AE4: =AE3+1 -> 501 | AF4: …. | AG4: =AA4 -> Living Room, | AH4: =AG3 -> ,,,,,, DMO = DEMOLITION ….... | AI4: =E4 -> …......... | AK4: =AK3+1 -> 601 | AL4: . | AM4: =AA4 -> Living Room, | AN4: =AK1 -> … WTR MITIGATION EQUIPMENT & W.I.P . ... | AO4: =$E$4 -> …......... | AQ4: =AQ3+1 -> 701 | AR4: . | AS4: =AG4 -> Living Room, | AT4: =AQ1 -> … HMR MITIGATION EQUIPMENT & W.I.P . ... | AU4: =$E$4 -> …......... | AW4: =AW3+1 -> 8001 | AX4: . | AY4: =C4 -> Living Room, | AZ4: =AW1 -> … DAY # 0 … MC READINGS STABILIZATION | BD4: 8101.1 | BE4: . | BF4: =AM4 -> Living Room, | BG4: =BD1 -> ... DAY1 MC READINGS .. | BI4: =$E$4 -> …......... | BK4: =BK3+1.2 -> 8201.2 | BL4: . | BM4: =BF4 -> Living Room, | BN4: =BK1 -> ... DAY2 MC READINGS .. | BO4: =$E$4 -> …......... | BQ4: =BQ3+1.3 -> 8301.3 | BR4: . | BS4: =BM4 -> Living Room, | BT4: =BQ1 -> ... DAY3 MC READINGS .. | BU4: =$E$4 -> …......... | BW4: =BW3+1.4 -> 8401.4 | BX4: . | BY4: =BS4 -> Living Room, | BZ4: =BW1 -> ... DAY4 MC READINGS | CA4: =$E$4 -> …......... | CC4: 9100 | CD4: RH &T & GPP DRY CHAMBERS [DC] .READ INGS =========== | CE4: =CC2 -> ….. DAY 1 ….. | CJ4: 0.0001 | CK4: ….. | CL4: JOBSITE VERIFICATION | CX4: =C4 -> Living Room, | CY4: =E4 -> ….........
A5: 102 | B5: …. | C5: ='jobinfo(2)'!C54 -> HALLWAY | D5: , | E5: ….......... | G5: =A5 -> 102 | H5: =B5 -> …. | I5: =C5 -> HALLWAY | J5: =$G$2 -> = … JOB/ROOMS OVERVIEW PICS .. | K5: =$E$5 -> ….......... | M5: =M4+1 -> 202 | N5: =H5 -> …. | O5: =I5 -> HALLWAY | P5: =$M$2 -> ….. SOURCE of LOSS PICS ….. | Q5: =$E$5 -> ….......... | S5: =S4+1 -> 302 | T5: =N5 -> …. | U5: =O5 -> HALLWAY | V5: =$S$2 -> ….. C.P.S. …... | W5: =$E$5 -> ….......... | Y5: =Y4+1 -> 402 | Z5: =T5 -> …. | AA5: =U5 -> HALLWAY | AB5: =$Y$2 -> NON SALVAGEABLE ITEMS | AC5: =$E$5 -> ….......... | AE5: =AE4+1 -> 502 | AF5: …. | AG5: =AA5 -> HALLWAY | AH5: =AH4 -> ,,,,,, DMO = DEMOLITION ….... | AI5: =E5 -> ….......... | AK5: =AK4+1 -> 602 | AL5: . | AM5: =AA5 -> HALLWAY | AN5: =AN4 -> … WTR MITIGATION EQUIPMENT & W.I.P . ... | AO5: =$E$5 -> ….......... | AQ5: =AQ4+1 -> 702 | AR5: . | AS5: =AG5 -> HALLWAY | AT5: =AT4 -> … HMR MITIGATION EQUIPMENT & W.I.P . ... | AU5: =$E$5 -> ….......... | AW5: =AW4+1 -> 8002 | AX5: . | AY5: =C5 -> HALLWAY | AZ5: =AZ4 -> … DAY # 0 … MC READINGS STABILIZATION | BD5: =BD4+1 -> 8102.1 | BE5: . | BF5: =AM5 -> HALLWAY | BG5: =BG4 -> ... DAY1 MC READINGS .. | BI5: =$E$5 -> ….......... | BK5: =BK4+1 -> 8202.2 | BL5: . | BM5: =BF5 -> HALLWAY | BN5: =BN4 -> ... DAY2 MC READINGS .. | BO5: =$E$5 -> ….......... | BQ5: =BQ4+1 -> 8302.3 | BR5: . | BS5: =BM5 -> HALLWAY | BT5: =BT4 -> ... DAY3 MC READINGS .. | BU5: =$E$5 -> ….......... | BW5: =BW4+1 -> 8402.4 | BX5: . | BY5: =BS5 -> HALLWAY | BZ5: =BZ4 -> ... DAY4 MC READINGS | CA5: =$E$5 -> ….......... | CC5: =CC4 -> 9100 | CD5: EXTERIOR & UNAFFECTED AREA | CE5: =CC2 -> ….. DAY 1 ….. | CF5: RH &T & GPP | CJ5: 0.0002 | CK5: . | CL5: MECHANICALS = WATER METER READING & PLUMBING REPORT/INVOICE | CN5: , | CO5: ====== | CX5: =C5 -> HALLWAY | CY5: =E5 -> …..........
A6: 103 | B6: …. | C6: ='jobinfo(2)'!C55 -> Kitchen, | D6: , | E6: …......... | G6: =A6 -> 103 | H6: =B6 -> …. | I6: =C6 -> Kitchen, | J6: =$G$2 -> = … JOB/ROOMS OVERVIEW PICS .. | K6: =$E$6 -> …......... | M6: =M5+1 -> 203 | N6: =H6 -> …. | O6: =I6 -> Kitchen, | P6: =$M$2 -> ….. SOURCE of LOSS PICS ….. | Q6: =$E$6 -> …......... | S6: =S5+1 -> 303 | T6: =N6 -> …. | U6: =O6 -> Kitchen, | V6: =$S$2 -> ….. C.P.S. …... | W6: =$E$6 -> …......... | Y6: =Y5+1 -> 403 | Z6: =T6 -> …. | AA6: =U6 -> Kitchen, | AB6: =$Y$2 -> NON SALVAGEABLE ITEMS | AC6: =$E$6 -> …......... | AE6: =AE5+1 -> 503 | AF6: …. | AG6: =AA6 -> Kitchen, | AH6: =AH5 -> ,,,,,, DMO = DEMOLITION ….... | AI6: =E6 -> …......... | AK6: =AK5+1 -> 603 | AL6: . | AM6: =AA6 -> Kitchen, | AN6: =AN5 -> … WTR MITIGATION EQUIPMENT & W.I.P . ... | AO6: =$E$6 -> …......... | AQ6: =AQ5+1 -> 703 | AR6: . | AS6: =AG6 -> Kitchen, | AT6: =AT5 -> … HMR MITIGATION EQUIPMENT & W.I.P . ... | AU6: =$E$6 -> …......... | AW6: =AW5+1 -> 8003 | AX6: . | AY6: =C6 -> Kitchen, | AZ6: =AZ5 -> … DAY # 0 … MC READINGS STABILIZATION | BD6: =BD5+1 -> 8103.1 | BE6: . | BF6: =AM6 -> Kitchen, | BG6: =BG5 -> ... DAY1 MC READINGS .. | BI6: =$E$6 -> …......... | BK6: =BK5+1 -> 8203.2 | BL6: . | BM6: =BF6 -> Kitchen, | BN6: =BN5 -> ... DAY2 MC READINGS .. | BO6: =$E$6 -> …......... | BQ6: =BQ5+1 -> 8303.3 | BR6: . | BS6: =BM6 -> Kitchen, | BT6: =BT5 -> ... DAY3 MC READINGS .. | BU6: =$E$6 -> …......... | BW6: =BW5+1 -> 8403.4 | BX6: . | BY6: =BS6 -> Kitchen, | BZ6: =BZ5 -> ... DAY4 MC READINGS | CA6: =$E$6 -> …......... | CC6: =CC5+1.1 -> 9101.1 | CD6: DRY CHAMBER # 1 | CE6: =CE5 -> ….. DAY 1 ….. | CF6: RH &T & GPP | CJ6: 0.0003 | CK6: . | CL6: MECHANICALS = ELECTRICAL HAZARDS | CN6: , | CO6: ====== | CX6: =C6 -> Kitchen, | CY6: =E6 -> ….........
A7: 104 | B7: …. | C7: ='jobinfo(2)'!C56 -> DEN | D7: , | E7: …......... | G7: =A7 -> 104 | H7: =B7 -> …. | I7: =C7 -> DEN | J7: =$G$2 -> = … JOB/ROOMS OVERVIEW PICS .. | K7: =$E$7 -> …......... | M7: =M6+1 -> 204 | N7: =H7 -> …. | O7: =I7 -> DEN | P7: =$M$2 -> ….. SOURCE of LOSS PICS ….. | Q7: =$E$7 -> …......... | S7: =S6+1 -> 304 | T7: =N7 -> …. | U7: =O7 -> DEN | V7: =$S$2 -> ….. C.P.S. …... | W7: =$E$7 -> …......... | Y7: =Y6+1 -> 404 | Z7: =T7 -> …. | AA7: =U7 -> DEN | AB7: =$Y$2 -> NON SALVAGEABLE ITEMS | AC7: =$E$7 -> …......... | AE7: =AE6+1 -> 504 | AF7: …. | AG7: =AA7 -> DEN | AH7: =AH6 -> ,,,,,, DMO = DEMOLITION ….... | AI7: =E7 -> …......... | AK7: =AK6+1 -> 604 | AL7: . | AM7: =AA7 -> DEN | AN7: =AN6 -> … WTR MITIGATION EQUIPMENT & W.I.P . ... | AO7: =$E$7 -> …......... | AQ7: =AQ6+1 -> 704 | AR7: . | AS7: =AG7 -> DEN | AT7: =AT6 -> … HMR MITIGATION EQUIPMENT & W.I.P . ... | AU7: =$E$7 -> …......... | AW7: =AW6+1 -> 8004 | AX7: . | AY7: =C7 -> DEN | AZ7: =AZ6 -> … DAY # 0 … MC READINGS STABILIZATION | BD7: =BD6+1 -> 8104.1 | BE7: . | BF7: =AM7 -> DEN | BG7: =BG6 -> ... DAY1 MC READINGS .. | BI7: =$E$7 -> …......... | BK7: =BK6+1 -> 8204.2 | BL7: . | BM7: =BF7 -> DEN | BN7: =BN6 -> ... DAY2 MC READINGS .. | BO7: =$E$7 -> …......... | BQ7: =BQ6+1 -> 8304.3 | BR7: . | BS7: =BM7 -> DEN | BT7: =BT6 -> ... DAY3 MC READINGS .. | BU7: =$E$7 -> …......... | BW7: =BW6+1 -> 8404.4 | BX7: . | BY7: =BS7 -> DEN | BZ7: =BZ6 -> ... DAY4 MC READINGS | CA7: =$E$7 -> …......... | CC7: =CC6+1 -> 9102.1 | CD7: DRY CHAMBER # 2 | CE7: =CE6 -> ….. DAY 1 ….. | CF7: RH &T & GPP | CJ7: 0.0004 | CK7: . | CL7: EXT DAMAGE IF APPLICABLE | CM7: ROOF TARPS …............................. | CN7: , | CO7: ====== | CX7: =C7 -> DEN | CY7: =E7 -> ….........
A8: 105 | B8: …. | C8: ='jobinfo(2)'!C57 -> STAIRS UP | D8: , | E8: …......... | G8: =A8 -> 105 | H8: =B8 -> …. | I8: =C8 -> STAIRS UP | J8: =$G$2 -> = … JOB/ROOMS OVERVIEW PICS .. | K8: =$E$8 -> …......... | M8: =M7+1 -> 205 | N8: =H8 -> …. | O8: =I8 -> STAIRS UP | P8: =$M$2 -> ….. SOURCE of LOSS PICS ….. | Q8: =$E$8 -> …......... | S8: =S7+1 -> 305 | T8: =N8 -> …. | U8: =O8 -> STAIRS UP | V8: =$S$2 -> ….. C.P.S. …... | W8: =$E$8 -> …......... | Y8: =Y7+1 -> 405 | Z8: =T8 -> …. | AA8: =U8 -> STAIRS UP | AB8: =$Y$2 -> NON SALVAGEABLE ITEMS | AC8: =$E$8 -> …......... | AE8: =AE7+1 -> 505 | AF8: …. | AG8: =AA8 -> STAIRS UP | AH8: =AH7 -> ,,,,,, DMO = DEMOLITION ….... | AI8: =E8 -> …......... | AK8: =AK7+1 -> 605 | AL8: . | AM8: =AA8 -> STAIRS UP | AN8: =AN7 -> … WTR MITIGATION EQUIPMENT & W.I.P . ... | AO8: =$E$8 -> …......... | AQ8: =AQ7+1 -> 705 | AR8: . | AS8: =AG8 -> STAIRS UP | AT8: =AT7 -> … HMR MITIGATION EQUIPMENT & W.I.P . ... | AU8: =$E$8 -> …......... | AW8: =AW7+1 -> 8005 | AX8: . | AY8: =C8 -> STAIRS UP | AZ8: =AZ7 -> … DAY # 0 … MC READINGS STABILIZATION | BD8: =BD7+1 -> 8105.1 | BE8: . | BF8: =AM8 -> STAIRS UP | BG8: =BG7 -> ... DAY1 MC READINGS .. | BI8: =$E$8 -> …......... | BK8: =BK7+1 -> 8205.2 | BL8: . | BM8: =BF8 -> STAIRS UP | BN8: =BN7 -> ... DAY2 MC READINGS .. | BO8: =$E$8 -> …......... | BQ8: =BQ7+1 -> 8305.3 | BR8: . | BS8: =BM8 -> STAIRS UP | BT8: =BT7 -> ... DAY3 MC READINGS .. | BU8: =$E$8 -> …......... | BW8: =BW7+1 -> 8405.4 | BX8: . | BY8: =BS8 -> STAIRS UP | BZ8: =BZ7 -> ... DAY4 MC READINGS | CA8: =$E$8 -> …......... | CC8: =CC7+1 -> 9103.1 | CD8: DRY CHAMBER # 3 | CE8: =CE7 -> ….. DAY 1 ….. | CF8: RH &T & GPP | CJ8: 1997 | CK8: . | CL8: LEAD & HMR TESTING | CM8: LAB RESULTS | CN8: , | CO8: ====== | CX8: =C8 -> STAIRS UP | CY8: =E8 -> ….........
A9: 106 | B9: …. | C9: ='jobinfo(2)'!C58 -> HALL UP | D9: , | E9: LOS / TRAVEL | G9: =A9 -> 106 | H9: =B9 -> …. | I9: =C9 -> HALL UP | J9: =$G$2 -> = … JOB/ROOMS OVERVIEW PICS .. | K9: =$E$9 -> LOS / TRAVEL | M9: =M8+1 -> 206 | N9: =H9 -> …. | O9: =I9 -> HALL UP | P9: =$M$2 -> ….. SOURCE of LOSS PICS ….. | Q9: =$E$9 -> LOS / TRAVEL | S9: =S8+1 -> 306 | T9: =N9 -> …. | U9: =O9 -> HALL UP | V9: =$S$2 -> ….. C.P.S. …... | W9: =$E$9 -> LOS / TRAVEL | Y9: =Y8+1 -> 406 | Z9: =T9 -> …. | AA9: =U9 -> HALL UP | AB9: =$Y$2 -> NON SALVAGEABLE ITEMS | AC9: =$E$9 -> LOS / TRAVEL | AE9: =AE8+1 -> 506 | AF9: …. | AG9: =AA9 -> HALL UP | AH9: =AH8 -> ,,,,,, DMO = DEMOLITION ….... | AI9: =E9 -> LOS / TRAVEL | AK9: =AK8+1 -> 606 | AL9: . | AM9: =AA9 -> HALL UP | AN9: =AN8 -> … WTR MITIGATION EQUIPMENT & W.I.P . ... | AO9: =$E$9 -> LOS / TRAVEL | AQ9: =AQ8+1 -> 706 | AR9: . | AS9: =AG9 -> HALL UP | AT9: =AT8 -> … HMR MITIGATION EQUIPMENT & W.I.P . ... | AU9: =$E$9 -> LOS / TRAVEL | AW9: =AW8+1 -> 8006 | AX9: . | AY9: =C9 -> HALL UP | AZ9: =AZ8 -> … DAY # 0 … MC READINGS STABILIZATION | BD9: =BD8+1 -> 8106.1 | BE9: . | BF9: =AM9 -> HALL UP | BG9: =BG8 -> ... DAY1 MC READINGS .. | BI9: =$E$9 -> LOS / TRAVEL | BK9: =BK8+1 -> 8206.2 | BL9: . | BM9: =BF9 -> HALL UP | BN9: =BN8 -> ... DAY2 MC READINGS .. | BO9: =$E$9 -> LOS / TRAVEL | BQ9: =BQ8+1 -> 8306.3 | BR9: . | BS9: =BM9 -> HALL UP | BT9: =BT8 -> ... DAY3 MC READINGS .. | BU9: =$E$9 -> LOS / TRAVEL | BW9: =BW8+1 -> 8406.4 | BX9: . | BY9: =BS9 -> HALL UP | BZ9: =BZ8 -> ... DAY4 MC READINGS | CA9: =$E$9 -> LOS / TRAVEL | CC9: =CC8+1 -> 9104.1 | CD9: DRY CHAMBER # 4 | CE9: =CE8 -> ….. DAY 1 ….. | CF9: RH &T & GPP | CJ9: 1998 | CK9: . | CL9: KITCHEN CABINETS SIZES | CM9: U & L =LF/ CT = SF; APPLIANCES | CN9: , | CO9: ====== | CX9: =C9 -> HALL UP | CY9: =E9 -> LOS / TRAVEL
A10: 107 | B10: …. | C10: ='jobinfo(2)'!C59 -> PBR UP | D10: , | E10: …......... | G10: =A10 -> 107 | H10: =B10 -> …. | I10: =C10 -> PBR UP | J10: =$G$2 -> = … JOB/ROOMS OVERVIEW PICS .. | K10: =$E$10 -> …......... | M10: =M9+1 -> 207 | N10: =H10 -> …. | O10: =I10 -> PBR UP | P10: =$M$2 -> ….. SOURCE of LOSS PICS ….. | Q10: =$E$10 -> …......... | S10: =S9+1 -> 307 | T10: =N10 -> …. | U10: =O10 -> PBR UP | V10: =$S$2 -> ….. C.P.S. …... | W10: =$E$10 -> …......... | Y10: =Y9+1 -> 407 | Z10: =T10 -> …. | AA10: =U10 -> PBR UP | AB10: =$Y$2 -> NON SALVAGEABLE ITEMS | AC10: =$E$10 -> …......... | AE10: =AE9+1 -> 507 | AF10: …. | AG10: =AA10 -> PBR UP | AH10: =AH9 -> ,,,,,, DMO = DEMOLITION ….... | AI10: =E10 -> …......... | AK10: =AK9+1 -> 607 | AL10: . | AM10: =AA10 -> PBR UP | AN10: =AN9 -> … WTR MITIGATION EQUIPMENT & W.I.P . ... | AO10: =$E$10 -> …......... | AQ10: =AQ9+1 -> 707 | AR10: . | AS10: =AG10 -> PBR UP | AT10: =AT9 -> … HMR MITIGATION EQUIPMENT & W.I.P . ... | AU10: =$E$10 -> …......... | AW10: =AW9+1 -> 8007 | AX10: . | AY10: =C10 -> PBR UP | AZ10: =AZ9 -> … DAY # 0 … MC READINGS STABILIZATION | BD10: =BD9+1 -> 8107.1 | BE10: . | BF10: =AM10 -> PBR UP | BG10: =BG9 -> ... DAY1 MC READINGS .. | BI10: =$E$10 -> …......... | BK10: =BK9+1 -> 8207.2 | BL10: . | BM10: =BF10 -> PBR UP | BN10: =BN9 -> ... DAY2 MC READINGS .. | BO10: =$E$10 -> …......... | BQ10: =BQ9+1 -> 8307.3 | BR10: . | BS10: =BM10 -> PBR UP | BT10: =BT9 -> ... DAY3 MC READINGS .. | BU10: =$E$10 -> …......... | BW10: =BW9+1 -> 8407.4 | BX10: . | BY10: =BS10 -> PBR UP | BZ10: =BZ9 -> ... DAY4 MC READINGS | CA10: =$E$10 -> …......... | CC10: =CC5+100.2 -> 9200.2 | CD10: =CD4 -> RH &T & GPP DRY CHAMBERS [DC] .READ INGS =========== | CE10: ….. DAY 2 ….. | CF10: RH &T & GPP | CJ10: 1999 | CK10: . | CL10: BATHROOM FIXTURES | CM10: CAB SIZE & FIXTURES & TYPE | CN10: , | CO10: ====== | CX10: =C10 -> PBR UP | CY10: =E10 -> ….........
A11: 108 | B11: …. | C11: ='jobinfo(2)'!C60 -> BATH UP | D11: , | E11: …......... | G11: =A11 -> 108 | H11: =B11 -> …. | I11: =C11 -> BATH UP | J11: =$G$2 -> = … JOB/ROOMS OVERVIEW PICS .. | K11: =$E$11 -> …......... | M11: =M10+1 -> 208 | N11: =H11 -> …. | O11: =I11 -> BATH UP | P11: =$M$2 -> ….. SOURCE of LOSS PICS ….. | Q11: =$E$11 -> …......... | S11: =S10+1 -> 308 | T11: =N11 -> …. | U11: =O11 -> BATH UP | V11: =$S$2 -> ….. C.P.S. …... | W11: =$E$11 -> …......... | Y11: =Y10+1 -> 408 | Z11: =T11 -> …. | AA11: =U11 -> BATH UP | AB11: =$Y$2 -> NON SALVAGEABLE ITEMS | AC11: =$E$11 -> …......... | AE11: =AE10+1 -> 508 | AF11: …. | AG11: =AA11 -> BATH UP | AH11: =AH10 -> ,,,,,, DMO = DEMOLITION ….... | AI11: =E11 -> …......... | AK11: =AK10+1 -> 608 | AL11: . | AM11: =AA11 -> BATH UP | AN11: =AN10 -> … WTR MITIGATION EQUIPMENT & W.I.P . ... | AO11: =$E$11 -> …......... | AQ11: =AQ10+1 -> 708 | AR11: . | AS11: =AG11 -> BATH UP | AT11: =AT10 -> … HMR MITIGATION EQUIPMENT & W.I.P . ... | AU11: =$E$11 -> …......... | AW11: =AW10+1 -> 8008 | AX11: . | AY11: =C11 -> BATH UP | AZ11: =AZ10 -> … DAY # 0 … MC READINGS STABILIZATION | BD11: =BD10+1 -> 8108.1 | BE11: . | BF11: =AM11 -> BATH UP | BG11: =BG10 -> ... DAY1 MC READINGS .. | BI11: =$E$11 -> …......... | BK11: =BK10+1 -> 8208.2 | BL11: . | BM11: =BF11 -> BATH UP | BN11: =BN10 -> ... DAY2 MC READINGS .. | BO11: =$E$11 -> …......... | BQ11: =BQ10+1 -> 8308.3 | BR11: . | BS11: =BM11 -> BATH UP | BT11: =BT10 -> ... DAY3 MC READINGS .. | BU11: =$E$11 -> …......... | BW11: =BW10+1 -> 8408.4 | BX11: . | BY11: =BS11 -> BATH UP | BZ11: =BZ10 -> ... DAY4 MC READINGS | CA11: =$E$11 -> …......... | CC11: =CC10 -> 9200.2 | CD11: EXTERIOR & UNAFFECTED AREA | CE11: =CE10 -> ….. DAY 2 ….. | CF11: RH &T & GPP | CJ11: 3222 | CK11: . | CL11: CPS DAY2 WIP | CM11: OVERVIEW WIP BOXES PACKOUT PICS | CN11: , | CO11: ====== | CX11: =C11 -> BATH UP | CY11: =E11 -> ….........
A12: 109 | B12: …. | C12: ='jobinfo(2)'!C61 -> BR-2 UP | D12: , | E12: …......... | G12: =A12 -> 109 | H12: =B12 -> …. | I12: =C12 -> BR-2 UP | J12: =$G$2 -> = … JOB/ROOMS OVERVIEW PICS .. | K12: =$E$12 -> …......... | M12: =M11+1 -> 209 | N12: =H12 -> …. | O12: =I12 -> BR-2 UP | P12: =$M$2 -> ….. SOURCE of LOSS PICS ….. | Q12: =$E$12 -> …......... | S12: =S11+1 -> 309 | T12: =N12 -> …. | U12: =O12 -> BR-2 UP | V12: =$S$2 -> ….. C.P.S. …... | W12: =$E$12 -> …......... | Y12: =Y11+1 -> 409 | Z12: =T12 -> …. | AA12: =U12 -> BR-2 UP | AB12: =$Y$2 -> NON SALVAGEABLE ITEMS | AC12: =$E$12 -> …......... | AE12: =AE11+1 -> 509 | AF12: …. | AG12: =AA12 -> BR-2 UP | AH12: =AH11 -> ,,,,,, DMO = DEMOLITION ….... | AI12: =E12 -> …......... | AK12: =AK11+1 -> 609 | AL12: . | AM12: =AA12 -> BR-2 UP | AN12: =AN11 -> … WTR MITIGATION EQUIPMENT & W.I.P . ... | AO12: =$E$12 -> …......... | AQ12: =AQ11+1 -> 709 | AR12: . | AS12: =AG12 -> BR-2 UP | AT12: =AT11 -> … HMR MITIGATION EQUIPMENT & W.I.P . ... | AU12: =$E$12 -> …......... | AW12: =AW11+1 -> 8009 | AX12: . | AY12: =C12 -> BR-2 UP | AZ12: =AZ11 -> … DAY # 0 … MC READINGS STABILIZATION | BD12: =BD11+1 -> 8109.1 | BE12: . | BF12: =AM12 -> BR-2 UP | BG12: =BG11 -> ... DAY1 MC READINGS .. | BI12: =$E$12 -> …......... | BK12: =BK11+1 -> 8209.2 | BL12: . | BM12: =BF12 -> BR-2 UP | BN12: =BN11 -> ... DAY2 MC READINGS .. | BO12: =$E$12 -> …......... | BQ12: =BQ11+1 -> 8309.3 | BR12: . | BS12: =BM12 -> BR-2 UP | BT12: =BT11 -> ... DAY3 MC READINGS .. | BU12: =$E$12 -> …......... | BW12: =BW11+1 -> 8409.4 | BX12: . | BY12: =BS12 -> BR-2 UP | BZ12: =BZ11 -> ... DAY4 MC READINGS | CA12: =$E$12 -> …......... | CC12: =CC11+1 -> 9201.2 | CD12: DRY CHAMBER # 1 | CE12: =CE11 -> ….. DAY 2 ….. | CF12: RH &T & GPP | CJ12: 3322 | CK12: . | CL12: CPS3 DAY3 STORAGE | CM12: OVERVIEW STORAGE MOVE OUT PICS | CN12: , | CO12: ====== | CX12: =C12 -> BR-2 UP | CY12: =E12 -> ….........
A13: 110 | B13: …. | C13: ='jobinfo(2)'!C62 -> GUEST CLOSET | D13: , | E13: …......... | G13: =A13 -> 110 | H13: =B13 -> …. | I13: =C13 -> GUEST CLOSET | J13: =$G$2 -> = … JOB/ROOMS OVERVIEW PICS .. | K13: =$E$13 -> …......... | M13: =M12+1 -> 210 | N13: =H13 -> …. | O13: =I13 -> GUEST CLOSET | P13: =$M$2 -> ….. SOURCE of LOSS PICS ….. | Q13: =$E$13 -> …......... | S13: =S12+1 -> 310 | T13: =N13 -> …. | U13: =O13 -> GUEST CLOSET | V13: =$S$2 -> ….. C.P.S. …... | W13: =$E$13 -> …......... | Y13: =Y12+1 -> 410 | Z13: =T13 -> …. | AA13: =U13 -> GUEST CLOSET | AB13: =$Y$2 -> NON SALVAGEABLE ITEMS | AC13: =$E$13 -> …......... | AE13: =AE12+1 -> 510 | AF13: …. | AG13: =AA13 -> GUEST CLOSET | AH13: =AH12 -> ,,,,,, DMO = DEMOLITION ….... | AI13: =E13 -> …......... | AK13: =AK12+1 -> 610 | AL13: . | AM13: =AA13 -> GUEST CLOSET | AN13: =AN12 -> … WTR MITIGATION EQUIPMENT & W.I.P . ... | AO13: =$E$13 -> …......... | AQ13: =AQ12+1 -> 710 | AR13: . | AS13: =AG13 -> GUEST CLOSET | AT13: =AT12 -> … HMR MITIGATION EQUIPMENT & W.I.P . ... | AU13: =$E$13 -> …......... | AW13: =AW12+1 -> 8010 | AX13: . | AY13: =C13 -> GUEST CLOSET | AZ13: =AZ12 -> … DAY # 0 … MC READINGS STABILIZATION | BD13: =BD12+1 -> 8110.1 | BE13: . | BF13: =AM13 -> GUEST CLOSET | BG13: =BG12 -> ... DAY1 MC READINGS .. | BI13: =$E$13 -> …......... | BK13: =BK12+1 -> 8210.2 | BL13: . | BM13: =BF13 -> GUEST CLOSET | BN13: =BN12 -> ... DAY2 MC READINGS .. | BO13: =$E$13 -> …......... | BQ13: =BQ12+1 -> 8310.3 | BR13: . | BS13: =BM13 -> GUEST CLOSET | BT13: =BT12 -> ... DAY3 MC READINGS .. | BU13: =$E$13 -> …......... | BW13: =BW12+1 -> 8410.4 | BX13: . | BY13: =BS13 -> GUEST CLOSET | BZ13: =BZ12 -> ... DAY4 MC READINGS | CA13: =$E$13 -> …......... | CC13: =CC12+1 -> 9202.2 | CD13: DRY CHAMBER # 2 | CE13: =CE12 -> ….. DAY 2 ….. | CF13: RH &T & GPP | CJ13: 3444 | CK13: . | CL13: CPS4 DAY4 PACKBACK | CM13: OVERVIEW PACK-BACK / RESET PICS | CN13: , | CO13: ====== | CX13: =C13 -> GUEST CLOSET | CY13: =E13 -> ….........
A14: 111 | B14: …. | C14: ='jobinfo(2)'!C63 -> BATH DN | D14: , | E14: LOS / TRAVEL | G14: =A14 -> 111 | H14: =B14 -> …. | I14: =C14 -> BATH DN | J14: =$G$2 -> = … JOB/ROOMS OVERVIEW PICS .. | K14: =$E$14 -> LOS / TRAVEL | M14: =M13+1 -> 211 | N14: =H14 -> …. | O14: =I14 -> BATH DN | P14: =$M$2 -> ….. SOURCE of LOSS PICS ….. | Q14: =$E$14 -> LOS / TRAVEL | S14: =S13+1 -> 311 | T14: =N14 -> …. | U14: =O14 -> BATH DN | V14: =$S$2 -> ….. C.P.S. …... | W14: =$E$14 -> LOS / TRAVEL | Y14: =Y13+1 -> 411 | Z14: =T14 -> …. | AA14: =U14 -> BATH DN | AB14: =$Y$2 -> NON SALVAGEABLE ITEMS | AC14: =$E$14 -> LOS / TRAVEL | AE14: =AE13+1 -> 511 | AF14: …. | AG14: =AA14 -> BATH DN | AH14: =AH13 -> ,,,,,, DMO = DEMOLITION ….... | AI14: =E14 -> LOS / TRAVEL | AK14: =AK13+1 -> 611 | AL14: . | AM14: =AA14 -> BATH DN | AN14: =AN13 -> … WTR MITIGATION EQUIPMENT & W.I.P . ... | AO14: =$E$14 -> LOS / TRAVEL | AQ14: =AQ13+1 -> 711 | AR14: . | AS14: =AG14 -> BATH DN | AT14: =AT13 -> … HMR MITIGATION EQUIPMENT & W.I.P . ... | AU14: =$E$14 -> LOS / TRAVEL | AW14: =AW13+1 -> 8011 | AX14: . | AY14: =C14 -> BATH DN | AZ14: =AZ13 -> … DAY # 0 … MC READINGS STABILIZATION | BD14: =BD13+1 -> 8111.1 | BE14: . | BF14: =AM14 -> BATH DN | BG14: =BG13 -> ... DAY1 MC READINGS .. | BI14: =$E$14 -> LOS / TRAVEL | BK14: =BK13+1 -> 8211.2 | BL14: . | BM14: =BF14 -> BATH DN | BN14: =BN13 -> ... DAY2 MC READINGS .. | BO14: =$E$14 -> LOS / TRAVEL | BQ14: =BQ13+1 -> 8311.3 | BR14: . | BS14: =BM14 -> BATH DN | BT14: =BT13 -> ... DAY3 MC READINGS .. | BU14: =$E$14 -> LOS / TRAVEL | BW14: =BW13+1 -> 8411.4 | BX14: . | BY14: =BS14 -> BATH DN | BZ14: =BZ13 -> ... DAY4 MC READINGS | CA14: =$E$14 -> LOS / TRAVEL | CC14: =CC13+1 -> 9203.2 | CD14: DRY CHAMBER # 3 | CE14: =CE12 -> ….. DAY 2 ….. | CF14: RH &T & GPP | CJ14: 4111.1 | CK14: . | CL14: REPLACEMENT 1 CON OVERVIEW DAY PICS, | CN14: , | CO14: ====== | CX14: =C14 -> BATH DN | CY14: =E14 -> LOS / TRAVEL
A15: 112 | B15: …. | C15: ='jobinfo(2)'!C64 -> SHOWER | D15: , | E15: …......... | G15: =A15 -> 112 | H15: =B15 -> …. | I15: =C15 -> SHOWER | J15: =$G$2 -> = … JOB/ROOMS OVERVIEW PICS .. | K15: =$E$15 -> …......... | M15: =M14+1 -> 212 | N15: =H15 -> …. | O15: =I15 -> SHOWER | P15: =$M$2 -> ….. SOURCE of LOSS PICS ….. | Q15: =$E$15 -> …......... | S15: =S14+1 -> 312 | T15: =N15 -> …. | U15: =O15 -> SHOWER | V15: =$S$2 -> ….. C.P.S. …... | W15: =$E$15 -> …......... | Y15: =Y14+1 -> 412 | Z15: =T15 -> …. | AA15: =U15 -> SHOWER | AB15: =$Y$2 -> NON SALVAGEABLE ITEMS | AC15: =$E$15 -> …......... | AE15: =AE14+1 -> 512 | AF15: …. | AG15: =AA15 -> SHOWER | AH15: =AH14 -> ,,,,,, DMO = DEMOLITION ….... | AI15: =E15 -> …......... | AK15: =AK14+1 -> 612 | AL15: . | AM15: =AA15 -> SHOWER | AN15: =AN14 -> … WTR MITIGATION EQUIPMENT & W.I.P . ... | AO15: =$E$15 -> …......... | AQ15: =AQ14+1 -> 712 | AR15: . | AS15: =AG15 -> SHOWER | AT15: =AT14 -> … HMR MITIGATION EQUIPMENT & W.I.P . ... | AU15: =$E$15 -> …......... | AW15: =AW14+1 -> 8012 | AX15: . | AY15: =C15 -> SHOWER | AZ15: =AZ14 -> … DAY # 0 … MC READINGS STABILIZATION | BD15: =BD14+1 -> 8112.1 | BE15: . | BF15: =AM15 -> SHOWER | BG15: =BG14 -> ... DAY1 MC READINGS .. | BI15: =$E$15 -> …......... | BK15: =BK14+1 -> 8212.2 | BL15: . | BM15: =BF15 -> SHOWER | BN15: =BN14 -> ... DAY2 MC READINGS .. | BO15: =$E$15 -> …......... | BQ15: =BQ14+1 -> 8312.3 | BR15: . | BS15: =BM15 -> SHOWER | BT15: =BT14 -> ... DAY3 MC READINGS .. | BU15: =$E$15 -> …......... | BW15: =BW14+1 -> 8412.4 | BX15: . | BY15: =BS15 -> SHOWER | BZ15: =BZ14 -> ... DAY4 MC READINGS | CA15: =$E$15 -> …......... | CC15: =CC14+1 -> 9204.2 | CD15: DRY CHAMBER # 4 | CE15: =CE13 -> ….. DAY 2 ….. | CF15: RH &T & GPP | CJ15: 4222.2 | CK15: . | CL15: REPLACEMENT 2 CON WIP, | CN15: , | CX15: =C15 -> SHOWER | CY15: =E15 -> ….........
A16: 113 | B16: …. | C16: ='jobinfo(2)'!C65 -> 0 | D16: , | E16: LOS / TRAVEL | G16: =A16 -> 113 | H16: =B16 -> …. | I16: =C16 -> 0 | J16: =$G$2 -> = … JOB/ROOMS OVERVIEW PICS .. | K16: =$E$16 -> LOS / TRAVEL | M16: =M15+1 -> 213 | N16: =H16 -> …. | O16: =I16 -> 0 | P16: =$M$2 -> ….. SOURCE of LOSS PICS ….. | Q16: =$E$16 -> LOS / TRAVEL | S16: =S15+1 -> 313 | T16: =N16 -> …. | U16: =O16 -> 0 | V16: =$S$2 -> ….. C.P.S. …... | W16: =$E$16 -> LOS / TRAVEL | Y16: =Y15+1 -> 413 | Z16: =T16 -> …. | AA16: =U16 -> 0 | AB16: =$Y$2 -> NON SALVAGEABLE ITEMS | AC16: =$E$16 -> LOS / TRAVEL | AE16: =AE15+1 -> 513 | AF16: …. | AG16: =AA16 -> 0 | AH16: =AH15 -> ,,,,,, DMO = DEMOLITION ….... | AI16: =E16 -> LOS / TRAVEL | AK16: =AK15+1 -> 613 | AL16: . | AM16: =AA16 -> 0 | AN16: =AN15 -> … WTR MITIGATION EQUIPMENT & W.I.P . ... | AO16: =$E$16 -> LOS / TRAVEL | AQ16: =AQ15+1 -> 713 | AR16: . | AS16: =AG16 -> 0 | AT16: =AT15 -> … HMR MITIGATION EQUIPMENT & W.I.P . ... | AU16: =$E$16 -> LOS / TRAVEL | AW16: =AW15+1 -> 8013 | AX16: . | AY16: =C16 -> 0 | AZ16: =AZ15 -> … DAY # 0 … MC READINGS STABILIZATION | BD16: =BD15+1 -> 8113.1 | BE16: . | BF16: =AM16 -> 0 | BG16: =BG15 -> ... DAY1 MC READINGS .. | BI16: =$E$16 -> LOS / TRAVEL | BK16: =BK15+1 -> 8213.2 | BL16: . | BM16: =BF16 -> 0 | BN16: =BN15 -> ... DAY2 MC READINGS .. | BO16: =$E$16 -> LOS / TRAVEL | BQ16: =BQ15+1 -> 8313.3 | BR16: . | BS16: =BM16 -> 0 | BT16: =BT15 -> ... DAY3 MC READINGS .. | BU16: =$E$16 -> LOS / TRAVEL | BW16: =BW15+1 -> 8413.4 | BX16: . | BY16: =BS16 -> 0 | BZ16: =BZ15 -> ... DAY4 MC READINGS | CA16: =$E$16 -> LOS / TRAVEL | CC16: =CC11+100.1 -> 9300.3 | CD16: =CD4 -> RH &T & GPP DRY CHAMBERS [DC] .READ INGS =========== | CE16: ….. DAY 3 ….. | CF16: RH &T & GPP | CJ16: 4333.3 | CK16: . | CL16: REPLACEMENT 3 CON STORAGE | CN16: , | CX16: =C16 -> 0 | CY16: =E16 -> LOS / TRAVEL
A17: 114 | B17: …. | C17: ='jobinfo(2)'!C66 -> 0 | D17: , | E17: …......... | G17: =A17 -> 114 | H17: =B17 -> …. | I17: =C17 -> 0 | J17: =$G$2 -> = … JOB/ROOMS OVERVIEW PICS .. | K17: =$E$17 -> …......... | M17: =M16+1 -> 214 | N17: =H17 -> …. | O17: =I17 -> 0 | P17: =$M$2 -> ….. SOURCE of LOSS PICS ….. | Q17: =$E$17 -> …......... | S17: =S16+1 -> 314 | T17: =N17 -> …. | U17: =O17 -> 0 | V17: =$S$2 -> ….. C.P.S. …... | W17: =$E$17 -> …......... | Y17: =Y16+1 -> 414 | Z17: =T17 -> …. | AA17: =U17 -> 0 | AB17: =$Y$2 -> NON SALVAGEABLE ITEMS | AC17: =$E$17 -> …......... | AE17: =AE16+1 -> 514 | AF17: …. | AG17: =AA17 -> 0 | AH17: =AH16 -> ,,,,,, DMO = DEMOLITION ….... | AI17: =E17 -> …......... | AK17: =AK16+1 -> 614 | AL17: . | AM17: =AA17 -> 0 | AN17: =AN16 -> … WTR MITIGATION EQUIPMENT & W.I.P . ... | AO17: =$E$17 -> …......... | AQ17: =AQ16+1 -> 714 | AR17: . | AS17: =AG17 -> 0 | AT17: =AT16 -> … HMR MITIGATION EQUIPMENT & W.I.P . ... | AU17: =$E$17 -> …......... | AW17: =AW16+1 -> 8014 | AX17: . | AY17: =C17 -> 0 | AZ17: =AZ16 -> … DAY # 0 … MC READINGS STABILIZATION | BD17: =BD16+1 -> 8114.1 | BE17: . | BF17: =AM17 -> 0 | BG17: =BG16 -> ... DAY1 MC READINGS .. | BI17: =$E$17 -> …......... | BK17: =BK16+1 -> 8214.2 | BL17: . | BM17: =BF17 -> 0 | BN17: =BN16 -> ... DAY2 MC READINGS .. | BO17: =$E$17 -> …......... | BQ17: =BQ16+1 -> 8314.3 | BR17: . | BS17: =BM17 -> 0 | BT17: =BT16 -> ... DAY3 MC READINGS .. | BU17: =$E$17 -> …......... | BW17: =BW16+1 -> 8414.4 | BX17: . | BY17: =BS17 -> 0 | BZ17: =BZ16 -> ... DAY4 MC READINGS | CA17: =$E$17 -> …......... | CC17: =CC16 -> 9300.3 | CD17: EXTERIOR & UNAFFECTED AREA | CE17: =CE16 -> ….. DAY 3 ….. | CF17: RH &T & GPP | CJ17: 4444.4 | CK17: . | CL17: REPLACEMENT 4 CON DISPOSAL, | CN17: , | CX17: =C17 -> 0 | CY17: =E17 -> ….........
A18: 115 | B18: …. | C18: ='jobinfo(2)'!C67 -> 0 | D18: , | E18: …......... | G18: =A18 -> 115 | H18: =B18 -> …. | I18: =C18 -> 0 | J18: =$G$2 -> = … JOB/ROOMS OVERVIEW PICS .. | K18: =$E$18 -> …......... | M18: =M17+1 -> 215 | N18: =H18 -> …. | O18: =I18 -> 0 | P18: =$M$2 -> ….. SOURCE of LOSS PICS ….. | Q18: =$E$18 -> …......... | S18: =S17+1 -> 315 | T18: =N18 -> …. | U18: =O18 -> 0 | V18: =$S$2 -> ….. C.P.S. …... | W18: =$E$18 -> …......... | Y18: =Y17+1 -> 415 | Z18: =T18 -> …. | AA18: =U18 -> 0 | AB18: =$Y$2 -> NON SALVAGEABLE ITEMS | AC18: =$E$18 -> …......... | AE18: =AE17+1 -> 515 | AF18: …. | AG18: =AA18 -> 0 | AH18: =AH17 -> ,,,,,, DMO = DEMOLITION ….... | AI18: =E18 -> …......... | AK18: =AK17+1 -> 615 | AL18: . | AM18: =AA18 -> 0 | AN18: =AN17 -> … WTR MITIGATION EQUIPMENT & W.I.P . ... | AO18: =$E$18 -> …......... | AQ18: =AQ17+1 -> 715 | AR18: . | AS18: =AG18 -> 0 | AT18: =AT17 -> … HMR MITIGATION EQUIPMENT & W.I.P . ... | AU18: =$E$18 -> …......... | AW18: =AW17+1 -> 8015 | AX18: . | AY18: =C18 -> 0 | AZ18: =AZ17 -> … DAY # 0 … MC READINGS STABILIZATION | BD18: =BD17+1 -> 8115.1 | BE18: . | BF18: =AM18 -> 0 | BG18: =BG17 -> ... DAY1 MC READINGS .. | BI18: =$E$18 -> …......... | BK18: =BK17+1 -> 8215.2 | BL18: . | BM18: =BF18 -> 0 | BN18: =BN17 -> ... DAY2 MC READINGS .. | BO18: =$E$18 -> …......... | BQ18: =BQ17+1 -> 8315.3 | BR18: . | BS18: =BM18 -> 0 | BT18: =BT17 -> ... DAY3 MC READINGS .. | BU18: =$E$18 -> …......... | BW18: =BW17+1 -> 8415.4 | BX18: . | BY18: =BS18 -> 0 | BZ18: =BZ17 -> ... DAY4 MC READINGS | CA18: =$E$18 -> …......... | CC18: =CC17+1 -> 9301.3 | CD18: DRY CHAMBER # 1 | CE18: =CE17 -> ….. DAY 3 ….. | CF18: RH &T & GPP | CJ18: 9998 | CK18: . | CL18: REBUILD OVERVIEW WORK IN PROGRESS.......WIP, | CN18: , | CO18: ====== | CX18: =C18 -> 0 | CY18: =E18 -> ….........
A19: 116 | B19: …. | C19: ='jobinfo(2)'!C68 -> 0 | D19: , | E19: …......... | G19: =A19 -> 116 | H19: =B19 -> …. | I19: =C19 -> 0 | J19: =$G$2 -> = … JOB/ROOMS OVERVIEW PICS .. | K19: =$E$19 -> …......... | M19: =M18+1 -> 216 | N19: =H19 -> …. | O19: =I19 -> 0 | P19: =$M$2 -> ….. SOURCE of LOSS PICS ….. | Q19: =$E$19 -> …......... | S19: =S18+1 -> 316 | T19: =N19 -> …. | U19: =O19 -> 0 | V19: =$S$2 -> ….. C.P.S. …... | W19: =$E$19 -> …......... | Y19: =Y18+1 -> 416 | Z19: =T19 -> …. | AA19: =U19 -> 0 | AB19: =$Y$2 -> NON SALVAGEABLE ITEMS | AC19: =$E$19 -> …......... | AE19: =AE18+1 -> 516 | AF19: …. | AG19: =AA19 -> 0 | AH19: =AH18 -> ,,,,,, DMO = DEMOLITION ….... | AI19: =E19 -> …......... | AK19: =AK18+1 -> 616 | AL19: . | AM19: =AA19 -> 0 | AN19: =AN18 -> … WTR MITIGATION EQUIPMENT & W.I.P . ... | AO19: =$E$19 -> …......... | AQ19: =AQ18+1 -> 716 | AR19: . | AS19: =AG19 -> 0 | AT19: =AT18 -> … HMR MITIGATION EQUIPMENT & W.I.P . ... | AU19: =$E$19 -> …......... | AW19: =AW18+1 -> 8016 | AX19: . | AY19: =C19 -> 0 | AZ19: =AZ18 -> … DAY # 0 … MC READINGS STABILIZATION | BD19: =BD18+1 -> 8116.1 | BE19: . | BF19: =AM19 -> 0 | BG19: =BG18 -> ... DAY1 MC READINGS .. | BI19: =$E$19 -> …......... | BK19: =BK18+1 -> 8216.2 | BL19: . | BM19: =BF19 -> 0 | BN19: =BN18 -> ... DAY2 MC READINGS .. | BO19: =$E$19 -> …......... | BQ19: =BQ18+1 -> 8316.3 | BR19: . | BS19: =BM19 -> 0 | BT19: =BT18 -> ... DAY3 MC READINGS .. | BU19: =$E$19 -> …......... | BW19: =BW18+1 -> 8416.4 | BX19: . | BY19: =BS19 -> 0 | BZ19: =BZ18 -> ... DAY4 MC READINGS | CA19: =$E$19 -> …......... | CC19: =CC18+1 -> 9302.3 | CD19: DRY CHAMBER # 2 | CE19: =CE18 -> ….. DAY 3 ….. | CF19: RH &T & GPP | CJ19: 9999 | CK19: . | CL19: REBUILD INTERIOR COMPLETED WORK, | CN19: , | CX19: =C19 -> 0 | CY19: =E19 -> ….........
A20: 117 | B20: …. | C20: ='jobinfo(2)'!C69 -> 0 | D20: , | E20: …......... | G20: =A20 -> 117 | H20: =B20 -> …. | I20: =C20 -> 0 | J20: =$G$2 -> = … JOB/ROOMS OVERVIEW PICS .. | K20: =$E$20 -> …......... | M20: =M19+1 -> 217 | N20: =H20 -> …. | O20: =I20 -> 0 | P20: =$M$2 -> ….. SOURCE of LOSS PICS ….. | Q20: =$E$20 -> …......... | S20: =S19+1 -> 317 | T20: =N20 -> …. | U20: =O20 -> 0 | V20: =$S$2 -> ….. C.P.S. …... | W20: =$E$20 -> …......... | Y20: =Y19+1 -> 417 | Z20: =T20 -> …. | AA20: =U20 -> 0 | AB20: =$Y$2 -> NON SALVAGEABLE ITEMS | AC20: =$E$20 -> …......... | AE20: =AE19+1 -> 517 | AF20: …. | AG20: =AA20 -> 0 | AH20: =AH19 -> ,,,,,, DMO = DEMOLITION ….... | AI20: =E20 -> …......... | AK20: =AK19+1 -> 617 | AL20: . | AM20: =AA20 -> 0 | AN20: =AN19 -> … WTR MITIGATION EQUIPMENT & W.I.P . ... | AO20: =$E$20 -> …......... | AQ20: =AQ19+1 -> 717 | AR20: . | AS20: =AG20 -> 0 | AT20: =AT19 -> … HMR MITIGATION EQUIPMENT & W.I.P . ... | AU20: =$E$20 -> …......... | AW20: =AW19+1 -> 8017 | AX20: . | AY20: =C20 -> 0 | AZ20: =AZ19 -> … DAY # 0 … MC READINGS STABILIZATION | BD20: =BD19+1 -> 8117.1 | BE20: . | BF20: =AM20 -> 0 | BG20: =BG19 -> ... DAY1 MC READINGS .. | BI20: =$E$20 -> …......... | BK20: =BK19+1 -> 8217.2 | BL20: . | BM20: =BF20 -> 0 | BN20: =BN19 -> ... DAY2 MC READINGS .. | BO20: =$E$20 -> …......... | BQ20: =BQ19+1 -> 8317.3 | BR20: . | BS20: =BM20 -> 0 | BT20: =BT19 -> ... DAY3 MC READINGS .. | BU20: =$E$20 -> …......... | BW20: =BW19+1 -> 8417.4 | BX20: . | BY20: =BS20 -> 0 | BZ20: =BZ19 -> ... DAY4 MC READINGS | CA20: =$E$20 -> …......... | CC20: =CC19+1 -> 9303.3 | CD20: DRY CHAMBER # 3 | CE20: =CE18 -> ….. DAY 3 ….. | CF20: RH &T & GPP | CN20: , | CX20: =C20 -> 0 | CY20: =E20 -> ….........
A21: 118 | B21: …. | C21: ='jobinfo(2)'!C70 -> 0 | D21: , | E21: …......... | G21: =A21 -> 118 | H21: =B21 -> …. | I21: =C21 -> 0 | J21: =$G$2 -> = … JOB/ROOMS OVERVIEW PICS .. | K21: =$E$21 -> …......... | M21: =M20+1 -> 218 | N21: =H21 -> …. | O21: =I21 -> 0 | P21: =$M$2 -> ….. SOURCE of LOSS PICS ….. | Q21: =$E$21 -> …......... | S21: =S20+1 -> 318 | T21: =N21 -> …. | U21: =O21 -> 0 | V21: =$S$2 -> ….. C.P.S. …... | W21: =$E$21 -> …......... | Y21: =Y20+1 -> 418 | Z21: =T21 -> …. | AA21: =U21 -> 0 | AB21: =$Y$2 -> NON SALVAGEABLE ITEMS | AC21: =$E$21 -> …......... | AE21: =AE20+1 -> 518 | AF21: …. | AG21: =AA21 -> 0 | AH21: =AH20 -> ,,,,,, DMO = DEMOLITION ….... | AI21: =E21 -> …......... | AK21: =AK20+1 -> 618 | AL21: . | AM21: =AA21 -> 0 | AN21: =AN20 -> … WTR MITIGATION EQUIPMENT & W.I.P . ... | AO21: =$E$21 -> …......... | AQ21: =AQ20+1 -> 718 | AR21: . | AS21: =AG21 -> 0 | AT21: =AT20 -> … HMR MITIGATION EQUIPMENT & W.I.P . ... | AU21: =$E$21 -> …......... | AW21: =AW20+1 -> 8018 | AX21: . | AY21: =C21 -> 0 | AZ21: =AZ20 -> … DAY # 0 … MC READINGS STABILIZATION | BD21: =BD20+1 -> 8118.1 | BE21: . | BF21: =AM21 -> 0 | BG21: =BG20 -> ... DAY1 MC READINGS .. | BI21: =$E$21 -> …......... | BK21: =BK20+1 -> 8218.2 | BL21: . | BM21: =BF21 -> 0 | BN21: =BN20 -> ... DAY2 MC READINGS .. | BO21: =$E$21 -> …......... | BQ21: =BQ20+1 -> 8318.3 | BR21: . | BS21: =BM21 -> 0 | BT21: =BT20 -> ... DAY3 MC READINGS .. | BU21: =$E$21 -> …......... | BW21: =BW20+1 -> 8418.4 | BX21: . | BY21: =BS21 -> 0 | BZ21: =BZ20 -> ... DAY4 MC READINGS | CA21: =$E$21 -> …......... | CC21: =CC20+1 -> 9304.3 | CD21: DRY CHAMBER # 4 | CE21: =CE19 -> ….. DAY 3 ….. | CF21: RH &T & GPP | CN21: , | CX21: =C21 -> 0 | CY21: =E21 -> ….........
A22: 119 | B22: …. | C22: ='jobinfo(2)'!C71 -> 0 | D22: , | E22: …......... | G22: =A22 -> 119 | H22: =B22 -> …. | I22: =C22 -> 0 | J22: =$G$2 -> = … JOB/ROOMS OVERVIEW PICS .. | K22: =$E$22 -> …......... | M22: =M21+1 -> 219 | N22: =H22 -> …. | O22: =I22 -> 0 | P22: =$M$2 -> ….. SOURCE of LOSS PICS ….. | Q22: =$E$22 -> …......... | S22: =S21+1 -> 319 | T22: =N22 -> …. | U22: =O22 -> 0 | V22: =$S$2 -> ….. C.P.S. …... | W22: =$E$22 -> …......... | Y22: =Y21+1 -> 419 | Z22: =T22 -> …. | AA22: =U22 -> 0 | AB22: =$Y$2 -> NON SALVAGEABLE ITEMS | AC22: =$E$22 -> …......... | AE22: =AE21+1 -> 519 | AF22: …. | AG22: =AA22 -> 0 | AH22: =AH21 -> ,,,,,, DMO = DEMOLITION ….... | AI22: =E22 -> …......... | AK22: =AK21+1 -> 619 | AL22: . | AM22: =AA22 -> 0 | AN22: =AN21 -> … WTR MITIGATION EQUIPMENT & W.I.P . ... | AO22: =$E$22 -> …......... | AQ22: =AQ21+1 -> 719 | AR22: . | AS22: =AG22 -> 0 | AT22: =AT21 -> … HMR MITIGATION EQUIPMENT & W.I.P . ... | AU22: =$E$22 -> …......... | AW22: =AW21+1 -> 8019 | AX22: . | AY22: =C22 -> 0 | AZ22: =AZ21 -> … DAY # 0 … MC READINGS STABILIZATION | BD22: =BD21+1 -> 8119.1 | BE22: . | BF22: =AM22 -> 0 | BG22: =BG21 -> ... DAY1 MC READINGS .. | BI22: =$E$22 -> …......... | BK22: =BK21+1 -> 8219.2 | BL22: . | BM22: =BF22 -> 0 | BN22: =BN21 -> ... DAY2 MC READINGS .. | BO22: =$E$22 -> …......... | BQ22: =BQ21+1 -> 8319.3 | BR22: . | BS22: =BM22 -> 0 | BT22: =BT21 -> ... DAY3 MC READINGS .. | BU22: =$E$22 -> …......... | BW22: =BW21+1 -> 8419.4 | BX22: . | BY22: =BS22 -> 0 | BZ22: =BZ21 -> ... DAY4 MC READINGS | CA22: =$E$22 -> …......... | CC22: =CC17+100.1 -> 9400.4 | CD22: =CD16 -> RH &T & GPP DRY CHAMBERS [DC] .READ INGS =========== | CE22: ….. DAY 4 ….. | CF22: RH &T & GPP | CN22: , | CX22: =C22 -> 0 | CY22: =E22 -> ….........
A23: 120 | B23: …. | C23: ='jobinfo(2)'!C72 -> 0 | D23: , | E23: …......... | G23: =A23 -> 120 | H23: =B23 -> …. | I23: =C23 -> 0 | J23: =$G$2 -> = … JOB/ROOMS OVERVIEW PICS .. | K23: =$E$23 -> …......... | M23: =M22+1 -> 220 | N23: =H23 -> …. | O23: =I23 -> 0 | P23: =$M$2 -> ….. SOURCE of LOSS PICS ….. | Q23: =$E$23 -> …......... | S23: =S22+1 -> 320 | T23: =N23 -> …. | U23: =O23 -> 0 | V23: =$S$2 -> ….. C.P.S. …... | W23: =$E$23 -> …......... | Y23: =Y22+1 -> 420 | Z23: =T23 -> …. | AA23: =U23 -> 0 | AB23: =$Y$2 -> NON SALVAGEABLE ITEMS | AC23: =$E$23 -> …......... | AE23: =AE22+1 -> 520 | AF23: …. | AG23: =AA23 -> 0 | AH23: =AH22 -> ,,,,,, DMO = DEMOLITION ….... | AI23: =E23 -> …......... | AK23: =AK22+1 -> 620 | AL23: . | AM23: =AA23 -> 0 | AN23: =AN22 -> … WTR MITIGATION EQUIPMENT & W.I.P . ... | AO23: =$E$23 -> …......... | AQ23: =AQ22+1 -> 720 | AR23: . | AS23: =AG23 -> 0 | AT23: =AT22 -> … HMR MITIGATION EQUIPMENT & W.I.P . ... | AU23: =$E$23 -> …......... | AW23: =AW22+1 -> 8020 | AX23: . | AY23: =C23 -> 0 | AZ23: =AZ22 -> … DAY # 0 … MC READINGS STABILIZATION | BD23: =BD22+1 -> 8120.1 | BE23: . | BF23: =AM23 -> 0 | BG23: =BG22 -> ... DAY1 MC READINGS .. | BI23: =$E$23 -> …......... | BK23: =BK22+1 -> 8220.2 | BL23: . | BM23: =BF23 -> 0 | BN23: =BN22 -> ... DAY2 MC READINGS .. | BO23: =$E$23 -> …......... | BQ23: =BQ22+1 -> 8320.3 | BR23: . | BS23: =BM23 -> 0 | BT23: =BT22 -> ... DAY3 MC READINGS .. | BU23: =$E$23 -> …......... | BW23: =BW22+1 -> 8420.4 | BX23: . | BY23: =BS23 -> 0 | BZ23: =BZ22 -> ... DAY4 MC READINGS | CA23: =$E$23 -> …......... | CC23: =CC22+1 -> 9401.4 | CD23: EXTERIOR & UNAFFECTED AREA | CE23: ….. DAY 4 ….. | CF23: RH &T & GPP | CN23: , | CX23: =C23 -> 0 | CY23: =E23 -> ….........
A24: 121 | B24: …. | C24: ='jobinfo(2)'!C73 -> 0 | D24: , | E24: …......... | G24: =A24 -> 121 | H24: =B24 -> …. | I24: =C24 -> 0 | J24: =$G$2 -> = … JOB/ROOMS OVERVIEW PICS .. | K24: =$E$24 -> …......... | M24: =M23+1 -> 221 | N24: =H24 -> …. | O24: =I24 -> 0 | P24: =$M$2 -> ….. SOURCE of LOSS PICS ….. | Q24: =$E$24 -> …......... | S24: =S23+1 -> 321 | T24: =N24 -> …. | U24: =O24 -> 0 | V24: =$S$2 -> ….. C.P.S. …... | W24: =$E$24 -> …......... | Y24: =Y23+1 -> 421 | Z24: =T24 -> …. | AA24: =U24 -> 0 | AB24: =$Y$2 -> NON SALVAGEABLE ITEMS | AC24: =$E$24 -> …......... | AE24: =AE23+1 -> 521 | AF24: …. | AG24: =AA24 -> 0 | AH24: =AH23 -> ,,,,,, DMO = DEMOLITION ….... | AI24: =E24 -> …......... | AK24: =AK23+1 -> 621 | AL24: . | AM24: =AA24 -> 0 | AN24: =AN23 -> … WTR MITIGATION EQUIPMENT & W.I.P . ... | AO24: =$E$24 -> …......... | AQ24: =AQ23+1 -> 721 | AR24: . | AS24: =AG24 -> 0 | AT24: =AT23 -> … HMR MITIGATION EQUIPMENT & W.I.P . ... | AU24: =$E$24 -> …......... | AW24: =AW23+1 -> 8021 | AX24: . | AY24: =C24 -> 0 | AZ24: =AZ23 -> … DAY # 0 … MC READINGS STABILIZATION | BD24: =BD23+1 -> 8121.1 | BE24: . | BF24: =AM24 -> 0 | BG24: =BG23 -> ... DAY1 MC READINGS .. | BI24: =$E$24 -> …......... | BK24: =BK23+1 -> 8221.2 | BL24: . | BM24: =BF24 -> 0 | BN24: =BN23 -> ... DAY2 MC READINGS .. | BO24: =$E$24 -> …......... | BQ24: =BQ23+1 -> 8321.3 | BR24: . | BS24: =BM24 -> 0 | BT24: =BT23 -> ... DAY3 MC READINGS .. | BU24: =$E$24 -> …......... | BW24: =BW23+1 -> 8421.4 | BX24: . | BY24: =BS24 -> 0 | BZ24: =BZ23 -> ... DAY4 MC READINGS | CA24: =$E$24 -> …......... | CC24: =CC23+1 -> 9402.4 | CD24: DRY CHAMBER # 1 | CE24: =CE23 -> ….. DAY 4 ….. | CF24: RH &T & GPP | CN24: , | CX24: =C24 -> 0 | CY24: =E24 -> ….........
A25: 122 | B25: …. | C25: ='jobinfo(2)'!C74 -> 0 | D25: , | E25: …......... | G25: =A25 -> 122 | H25: =B25 -> …. | I25: =C25 -> 0 | J25: =$G$2 -> = … JOB/ROOMS OVERVIEW PICS .. | K25: =$E$25 -> …......... | M25: =M24+1 -> 222 | N25: =H25 -> …. | O25: =I25 -> 0 | P25: =$M$2 -> ….. SOURCE of LOSS PICS ….. | Q25: =$E$25 -> …......... | S25: =S24+1 -> 322 | T25: =N25 -> …. | U25: =O25 -> 0 | V25: =$S$2 -> ….. C.P.S. …... | W25: =$E$25 -> …......... | Y25: =Y24+1 -> 422 | Z25: =T25 -> …. | AA25: =U25 -> 0 | AB25: =$Y$2 -> NON SALVAGEABLE ITEMS | AC25: =$E$25 -> …......... | AE25: =AE24+1 -> 522 | AF25: …. | AG25: =AA25 -> 0 | AH25: =AH24 -> ,,,,,, DMO = DEMOLITION ….... | AI25: =E25 -> …......... | AK25: =AK24+1 -> 622 | AL25: . | AM25: =AA25 -> 0 | AN25: =AN24 -> … WTR MITIGATION EQUIPMENT & W.I.P . ... | AO25: =$E$25 -> …......... | AQ25: =AQ24+1 -> 722 | AR25: . | AS25: =AG25 -> 0 | AT25: =AT24 -> … HMR MITIGATION EQUIPMENT & W.I.P . ... | AU25: =$E$25 -> …......... | AW25: =AW24+1 -> 8022 | AX25: . | AY25: =C25 -> 0 | AZ25: =AZ24 -> … DAY # 0 … MC READINGS STABILIZATION | BD25: =BD24+1 -> 8122.1 | BE25: . | BF25: =AM25 -> 0 | BG25: =BG24 -> ... DAY1 MC READINGS .. | BI25: =$E$25 -> …......... | BK25: =BK24+1 -> 8222.2 | BL25: . | BM25: =BF25 -> 0 | BN25: =BN24 -> ... DAY2 MC READINGS .. | BO25: =$E$25 -> …......... | BQ25: =BQ24+1 -> 8322.3 | BR25: . | BS25: =BM25 -> 0 | BT25: =BT24 -> ... DAY3 MC READINGS .. | BU25: =$E$25 -> …......... | BW25: =BW24+1 -> 8422.4 | BX25: . | BY25: =BS25 -> 0 | BZ25: =BZ24 -> ... DAY4 MC READINGS | CA25: =$E$25 -> …......... | CC25: =CC24+1 -> 9403.4 | CD25: DRY CHAMBER # 2 | CE25: =CE24 -> ….. DAY 4 ….. | CF25: RH &T & GPP | CN25: , | CX25: =C25 -> 0 | CY25: =E25 -> ….........
A26: 123 | B26: …. | C26: ='jobinfo(2)'!C75 -> 0 | D26: , | E26: …......... | G26: =A26 -> 123 | H26: =B26 -> …. | I26: =C26 -> 0 | J26: =$G$2 -> = … JOB/ROOMS OVERVIEW PICS .. | K26: =$E$26 -> …......... | M26: =M25+1 -> 223 | N26: =H26 -> …. | O26: =I26 -> 0 | P26: =$M$2 -> ….. SOURCE of LOSS PICS ….. | Q26: =$E$26 -> …......... | S26: =S25+1 -> 323 | T26: =N26 -> …. | U26: =O26 -> 0 | V26: =$S$2 -> ….. C.P.S. …... | W26: =$E$26 -> …......... | Y26: =Y25+1 -> 423 | Z26: =T26 -> …. | AA26: =U26 -> 0 | AB26: =$Y$2 -> NON SALVAGEABLE ITEMS | AC26: =$E$26 -> …......... | AE26: =AE25+1 -> 523 | AF26: …. | AG26: =AA26 -> 0 | AH26: =AH25 -> ,,,,,, DMO = DEMOLITION ….... | AI26: =E26 -> …......... | AK26: =AK25+1 -> 623 | AL26: . | AM26: =AA26 -> 0 | AN26: =AN25 -> … WTR MITIGATION EQUIPMENT & W.I.P . ... | AO26: =$E$26 -> …......... | AQ26: =AQ25+1 -> 723 | AR26: . | AS26: =AG26 -> 0 | AT26: =AT25 -> … HMR MITIGATION EQUIPMENT & W.I.P . ... | AU26: =$E$26 -> …......... | AW26: =AW25+1 -> 8023 | AX26: . | AY26: =C26 -> 0 | AZ26: =AZ25 -> … DAY # 0 … MC READINGS STABILIZATION | BD26: =BD25+1 -> 8123.1 | BE26: . | BF26: =AM26 -> 0 | BG26: =BG25 -> ... DAY1 MC READINGS .. | BI26: =$E$26 -> …......... | BK26: =BK25+1 -> 8223.2 | BL26: . | BM26: =BF26 -> 0 | BN26: =BN25 -> ... DAY2 MC READINGS .. | BO26: =$E$26 -> …......... | BQ26: =BQ25+1 -> 8323.3 | BR26: . | BS26: =BM26 -> 0 | BT26: =BT25 -> ... DAY3 MC READINGS .. | BU26: =$E$26 -> …......... | BW26: =BW25+1 -> 8423.4 | BX26: . | BY26: =BS26 -> 0 | BZ26: =BZ25 -> ... DAY4 MC READINGS | CA26: =$E$26 -> …......... | CC26: =CC25+1 -> 9404.4 | CD26: DRY CHAMBER # 3 | CE26: =CE24 -> ….. DAY 4 ….. | CF26: RH &T & GPP | CN26: , | CX26: =C26 -> 0 | CY26: =E26 -> ….........
A27: 124 | B27: …. | C27: ='jobinfo(2)'!C76 -> 0 | D27: , | E27: …......... | G27: =A27 -> 124 | H27: =B27 -> …. | I27: =C27 -> 0 | J27: =$G$2 -> = … JOB/ROOMS OVERVIEW PICS .. | K27: =$E$27 -> …......... | M27: =M26+1 -> 224 | N27: =H27 -> …. | O27: =I27 -> 0 | P27: =$M$2 -> ….. SOURCE of LOSS PICS ….. | Q27: =$E$27 -> …......... | S27: =S26+1 -> 324 | T27: =N27 -> …. | U27: =O27 -> 0 | V27: =$S$2 -> ….. C.P.S. …... | W27: =$E$27 -> …......... | Y27: =Y26+1 -> 424 | Z27: =T27 -> …. | AA27: =U27 -> 0 | AB27: =$Y$2 -> NON SALVAGEABLE ITEMS | AC27: =$E$27 -> …......... | AE27: =AE26+1 -> 524 | AF27: …. | AG27: =AA27 -> 0 | AH27: =AH26 -> ,,,,,, DMO = DEMOLITION ….... | AI27: =E27 -> …......... | AK27: =AK26+1 -> 624 | AL27: . | AM27: =AA27 -> 0 | AN27: =AN26 -> … WTR MITIGATION EQUIPMENT & W.I.P . ... | AO27: =$E$27 -> …......... | AQ27: =AQ26+1 -> 724 | AR27: . | AS27: =AG27 -> 0 | AT27: =AT26 -> … HMR MITIGATION EQUIPMENT & W.I.P . ... | AU27: =$E$27 -> …......... | AW27: =AW26+1 -> 8024 | AX27: . | AY27: =C27 -> 0 | AZ27: =AZ26 -> … DAY # 0 … MC READINGS STABILIZATION | BD27: =BD26+1 -> 8124.1 | BE27: . | BF27: =AM27 -> 0 | BG27: =BG26 -> ... DAY1 MC READINGS .. | BI27: =$E$27 -> …......... | BK27: =BK26+1 -> 8224.2 | BL27: . | BM27: =BF27 -> 0 | BN27: =BN26 -> ... DAY2 MC READINGS .. | BO27: =$E$27 -> …......... | BQ27: =BQ26+1 -> 8324.3 | BR27: . | BS27: =BM27 -> 0 | BT27: =BT26 -> ... DAY3 MC READINGS .. | BU27: =$E$27 -> …......... | BW27: =BW26+1 -> 8424.4 | BX27: . | BY27: =BS27 -> 0 | BZ27: =BZ26 -> ... DAY4 MC READINGS | CA27: =$E$27 -> …......... | CC27: =CC26+1 -> 9405.4 | CD27: DRY CHAMBER # 4 | CE27: =CE25 -> ….. DAY 4 ….. | CF27: RH &T & GPP | CN27: , | CX27: =C27 -> 0 | CY27: =E27 -> ….........
A28: 125 | B28: …. | C28: ='jobinfo(2)'!C77 -> 0 | D28: , | E28: …......... | G28: =A28 -> 125 | H28: =B28 -> …. | I28: =C28 -> 0 | J28: =$G$2 -> = … JOB/ROOMS OVERVIEW PICS .. | K28: =$E$28 -> …......... | M28: =M27+1 -> 225 | N28: =H28 -> …. | O28: =I28 -> 0 | P28: =$M$2 -> ….. SOURCE of LOSS PICS ….. | Q28: =$E$28 -> …......... | S28: =S27+1 -> 325 | T28: =N28 -> …. | U28: =O28 -> 0 | V28: =$S$2 -> ….. C.P.S. …... | W28: =$E$28 -> …......... | Y28: =Y27+1 -> 425 | Z28: =T28 -> …. | AA28: =U28 -> 0 | AB28: =$Y$2 -> NON SALVAGEABLE ITEMS | AC28: =$E$28 -> …......... | AE28: =AE27+1 -> 525 | AF28: …. | AG28: =AA28 -> 0 | AH28: =AH27 -> ,,,,,, DMO = DEMOLITION ….... | AI28: =E28 -> …......... | AK28: =AK27+1 -> 625 | AL28: . | AM28: =AA28 -> 0 | AN28: =AN27 -> … WTR MITIGATION EQUIPMENT & W.I.P . ... | AO28: =$E$28 -> …......... | AQ28: =AQ27+1 -> 725 | AR28: . | AS28: =AG28 -> 0 | AT28: =AT27 -> … HMR MITIGATION EQUIPMENT & W.I.P . ... | AU28: =$E$28 -> …......... | AW28: =AW27+1 -> 8025 | AX28: . | AY28: =C28 -> 0 | AZ28: =AZ27 -> … DAY # 0 … MC READINGS STABILIZATION | BD28: =BD27+1 -> 8125.1 | BE28: . | BF28: =AM28 -> 0 | BG28: =BG27 -> ... DAY1 MC READINGS .. | BI28: =$E$28 -> …......... | BK28: =BK27+1 -> 8225.2 | BL28: . | BM28: =BF28 -> 0 | BN28: =BN27 -> ... DAY2 MC READINGS .. | BO28: =$E$28 -> …......... | BQ28: =BQ27+1 -> 8325.3 | BR28: . | BS28: =BM28 -> 0 | BT28: =BT27 -> ... DAY3 MC READINGS .. | BU28: =$E$28 -> …......... | BW28: =BW27+1 -> 8425.4 | BX28: . | BY28: =BS28 -> 0 | BZ28: =BZ27 -> ... DAY4 MC READINGS | CA28: =$E$28 -> …......... | CN28: , | CX28: =C28 -> 0 | CY28: =E28 -> ….........
C30: FORMAT OF ROOM LISTS | BD30: ... MC READINGS .. | BK30: ... MC READINGS ..
C31: MUST BE 5 COLUMNS WIDE | BD31: ….. DAY 2 ….. | BK31: ….. DAY 3 …..
C32: LOGIC
C33: each work type will have leading numerical prefix
C34: Group work tpys together for easier field id of rooms ti capture picturs for
CR39: Bedroom 2 | CV39: NA
CV40: FCC CARPET/FCW
CV41: WALL/PLASTER
CV42: WALL/PLASTER

Sheet ROOMS-out
B1: ROOMS PREFIX CODE # | E1: OLD#
A2: 0.01 | B2: ='ROOMS#'!CL4 -> JOBSITE VERIFICATION
A4: 0.02 | B4: EXTERIOR DAMAGES | C4: ( IF APPLICABLE )
A6: 0.03 | B6: ='ROOMS#'!CL5 -> MECHANICALS = WATER METER READING & PLUMBING REPORT/INVOICE
A8: 0.04 | B8: ='ROOMS#'!CL6 -> MECHANICALS = ELECTRICAL HAZARDS | C8: ( IF APPLICABLE )
A10: 0.05 | B10: ='ROOMS#'!CL9 -> KITCHEN CABINETS SIZES | C10: ( IF APPLICABLE )
A12: 0.06 | B12: ='ROOMS#'!CL10 -> BATHROOM FIXTURES | C12: ( IF APPLICABLE )
A15: 100 | B15: ROOMS OVERVIEW | E15: 100
A17: 200 | B17: SOURCE of LOSS | E17: 200
A19: 300 | B19: CPS | E19: 300
A20: 3222 | B20: ='ROOMS#'!CL11 -> CPS DAY2 WIP
A21: 3322 | B21: ='ROOMS#'!CL12 -> CPS3 DAY3 STORAGE
A22: 3444 | B22: ='ROOMS#'!CL13 -> CPS4 DAY4 PACKBACK
A24: 400 | B24: PPR | E24: 400
A25: 411.1 | B25: ='ROOMS#'!CL14 -> REPLACEMENT 1 CON OVERVIEW DAY PICS,
A26: 422.2 | B26: ='ROOMS#'!CL15 -> REPLACEMENT 2 CON WIP,
A27: 433.3 | B27: ='ROOMS#'!CL16 -> REPLACEMENT 3 CON STORAGE
A28: 444.4 | B28: ='ROOMS#'!CL17 -> REPLACEMENT 4 CON DISPOSAL,
A30: 500 | B30: DMO DEMO | E30: 500
A32: 600 | B32: ='ROOMS#'!AK1 -> … WTR MITIGATION EQUIPMENT & W.I.P . ... | E32: 800
A34: 7000 | B34: HMR
A35: 7999 | B35: ='ROOMS#'!CL8 -> LEAD & HMR TESTING
A38: 8000 | B38: ======= DAY # 0 ….. MC READINGS STABILIZATION ===============
A40: 8100 | B40: MC ... READ INGS | E40: 6000
A42: 8100.1 | B42: ... DAY1 MC READINGS ..
A44: 8200.2 | B44: ... DAY2 MC READINGS ..
A46: 8300.3 | B46: ... DAY3 MC READINGS ..
A48: 8400.4 | B48: ... DAY4 MC READINGS
A66: 9000 | B66: ='ROOMS#'!CC1 -> RH &T & GPP DRY CHAMBERS [DC] .READ INGS | E66: 7100
A67: 9100 | B67: RH &T & GPP DRY CHAMBERS [DC] .READ INGS =========== | C67: ….. DAY 1 …..
A68: 9100 | B68: EXTERIOR & UNAFFECTED AREA | C68: ….. DAY 1 …..
A69: 9101.1 | B69: DRY CHAMBER # 1 | C69: ….. DAY 1 …..
A70: 9102.1 | B70: DRY CHAMBER # 2 | C70: ….. DAY 1 …..
A71: 9103.1 | B71: DRY CHAMBER # 3 | C71: ….. DAY 1 …..
A72: 9104.1 | B72: DRY CHAMBER # 4 | C72: ….. DAY 1 …..
A74: 9200.2 | B74: RH &T & GPP DRY CHAMBERS [DC] .READ INGS =========== | C74: ….. DAY 2 …..
A75: 9200.2 | B75: EXTERIOR & UNAFFECTED AREA | C75: ….. DAY 2 …..
A76: 9201.2 | B76: DRY CHAMBER # 1 | C76: ….. DAY 2 …..
A77: 9202.2 | B77: DRY CHAMBER # 2 | C77: ….. DAY 2 …..
A78: 9203.2 | B78: DRY CHAMBER # 3 | C78: ….. DAY 2 …..
A79: 9204.2 | B79: DRY CHAMBER # 4 | C79: ….. DAY 2 …..
... A93: 9405.4 | B93: DRY CHAMBER # 4 | C93: ….. DAY 4 …..
A95: 9998 | B95: ='ROOMS#'!CL18 -> REBUILD OVERVIEW WORK IN PROGRESS.......WIP,
A97: 9999 | B97: ='ROOMS#'!CL19 -> REBUILD INTERIOR COMPLETED WORK,
F98: ROOMS PREFIX CODE #
F99: ='jobinfo(2)'!$C$51 -> OH25 BROWNLEE @E189 | K99: ='jobinfo(2)'!$C$2 -> 3922 E 189 STR | Q99: ='jobinfo(2)'!$C$3 -> CLEVELAND, OH 44128
F101: JOBSITE VERIFICATION | T101: 0.01
F103: EXTERIOR DAMAGES | J103: ( IF APPLICABLE ) | T103: 0.02
F105: MECHANICALS = WATER METER READING & PLUMBING REPORT/INVOICE | T105: 0.03
J106: ( IF APPLICABLE )
F107: MECHANICALS = ELECTRICAL HAZARDS | M107: ( IF APPLICABLE ) | T107: 0.04
F109: KITCHEN CABINETS SIZES | M109: ( IF APPLICABLE ) | T109: 0.05
F111: BATHROOM FIXTURES | J111: ( IF APPLICABLE ) | T111: 0.06
G113: LOS | H113: OVERVIEW PICS .. | J113: ='ROOMS-out'!B17 -> SOURCE of LOSS | L113: CPS | N113: PPR | P113: DEMO | R113: WTR MIT EQUIP. | T113: HMR | V113: MC READINGS | X113: RH&T&GPP [DC] .READ INGS
G114: TRVL
F115: ROOM | H115: =A15 -> 100 | J115: =A17 -> 200 | L115: =A19 -> 300 | N115: =A24 -> 400 | P115: =A30 -> 500 | R115: ='ROOMS#'!AK3 -> 600 | T115: ='ROOMS#'!AQ3 -> 700 | V115: ='ROOMS#'!AW3 -> 8000 | X115: ='ROOMS#'!CC5 -> 9100
F116: ='jobinfo(2)'!C53 -> Living Room, | H116: =H115+1 -> 101 | J116: =J115+1 -> 201 | L116: =L115+1 -> 301 | N116: =N115+1 -> 401 | P116: =P115+1 -> 501 | R116: =R115+1 -> 601 | T116: =T115+1 -> 701 | V116: =V115+1 -> 8001 | X116: =X115+1 -> 9101
F117: ='jobinfo(2)'!C54 -> HALLWAY | H117: =H116+1 -> 102 | J117: =J116+1 -> 202 | L117: =L116+1 -> 302 | N117: =N116+1 -> 402 | P117: =P116+1 -> 502 | R117: =R116+1 -> 602 | T117: =T116+1 -> 702 | V117: =V116+1 -> 8002 | X117: =X116+1 -> 9102
F118: ='jobinfo(2)'!C55 -> Kitchen, | H118: =H117+1 -> 103 | J118: =J117+1 -> 203 | L118: =L117+1 -> 303 | N118: =N117+1 -> 403 | P118: =P117+1 -> 503 | R118: =R117+1 -> 603 | T118: =T117+1 -> 703 | V118: =V117+1 -> 8003 | X118: =X117+1 -> 9103
F119: ='jobinfo(2)'!C56 -> DEN | H119: =H118+1 -> 104 | J119: =J118+1 -> 204 | L119: =L118+1 -> 304 | N119: =N118+1 -> 404 | P119: =P118+1 -> 504 | R119: =R118+1 -> 604 | T119: =T118+1 -> 704 | V119: =V118+1 -> 8004 | X119: =X118+1 -> 9104
F120: ='jobinfo(2)'!C57 -> STAIRS UP | H120: =H119+1 -> 105 | J120: =J119+1 -> 205 | L120: =L119+1 -> 305 | N120: =N119+1 -> 405 | P120: =P119+1 -> 505 | R120: =R119+1 -> 605 | T120: =T119+1 -> 705 | V120: =V119+1 -> 8005 | X120: =X119+1 -> 9105
F121: ='jobinfo(2)'!C58 -> HALL UP | H121: =H120+1 -> 106 | J121: =J120+1 -> 206 | L121: =L120+1 -> 306 | N121: =N120+1 -> 406 | P121: =P120+1 -> 506 | R121: =R120+1 -> 606 | T121: =T120+1 -> 706 | V121: =V120+1 -> 8006 | X121: =X120+1 -> 9106
F122: ='jobinfo(2)'!C59 -> PBR UP | H122: =H121+1 -> 107 | J122: =J121+1 -> 207 | L122: =L121+1 -> 307 | N122: =N121+1 -> 407 | P122: =P121+1 -> 507 | R122: =R121+1 -> 607 | T122: =T121+1 -> 707 | V122: =V121+1 -> 8007 | X122: =X121+1 -> 9107
F123: ='jobinfo(2)'!C60 -> BATH UP | H123: =H122+1 -> 108 | J123: =J122+1 -> 208 | L123: =L122+1 -> 308 | N123: =N122+1 -> 408 | P123: =P122+1 -> 508 | R123: =R122+1 -> 608 | T123: =T122+1 -> 708 | V123: =V122+1 -> 8008 | X123: =X122+1 -> 9108
F124: ='jobinfo(2)'!C61 -> BR-2 UP | H124: =H123+1 -> 109 | J124: =J123+1 -> 209 | L124: =L123+1 -> 309 | N124: =N123+1 -> 409 | P124: =P123+1 -> 509 | R124: =R123+1 -> 609 | T124: =T123+1 -> 709 | V124: =V123+1 -> 8009 | X124: =X123+1 -> 9109
F125: ='jobinfo(2)'!C62 -> GUEST CLOSET | H125: =H124+1 -> 110 | J125: =J124+1 -> 210 | L125: =L124+1 -> 310 | N125: =N124+1 -> 410 | P125: =P124+1 -> 510 | R125: =R124+1 -> 610 | T125: =T124+1 -> 710 | V125: =V124+1 -> 8010 | X125: =X124+1 -> 9110
F126: =F99 -> OH25 BROWNLEE @E189 | K126: =K99 -> 3922 E 189 STR | Q126: =Q99 -> CLEVELAND, OH 44128
H128: =H113 -> OVERVIEW PICS .. | J128: =J113 -> SOURCE of LOSS | L128: =L113 -> CPS | N128: =N113 -> PPR | P128: =P113 -> DEMO | R128: =R113 -> WTR MIT EQUIP. | T128: =T113 -> HMR | V128: =V113 -> MC READINGS | X128: =X113 -> RH&T&GPP [DC] .READ INGS
F129: ROOM
F130: ='jobinfo(2)'!C63 -> BATH DN | H130: =H125+1 -> 111 | J130: =J125+1 -> 211 | L130: =L125+1 -> 311 | N130: =N125+1 -> 411 | P130: =P125+1 -> 511 | R130: =R125+1 -> 611 | T130: =T125+1 -> 711 | V130: =V125+1 -> 8011 | X130: =X125+1 -> 9111
F131: ='jobinfo(2)'!C64 -> SHOWER | H131: =H130+1 -> 112 | J131: =J130+1 -> 212 | L131: =L130+1 -> 312 | N131: =N130+1 -> 412 | P131: =P130+1 -> 512 | R131: =R130+1 -> 612 | T131: =T130+1 -> 712 | V131: =V130+1 -> 8012 | X131: =X130+1 -> 9112
F132: ='jobinfo(2)'!C65 -> 0 | H132: =H131+1 -> 113 | J132: =J131+1 -> 213 | L132: =L131+1 -> 313 | N132: =N131+1 -> 413 | P132: =P131+1 -> 513 | R132: =R131+1 -> 613 | T132: =T131+1 -> 713 | V132: =V131+1 -> 8013 | X132: =X131+1 -> 9113
F133: ='jobinfo(2)'!C66 -> 0 | H133: =H132+1 -> 114 | J133: =J132+1 -> 214 | L133: =L132+1 -> 314 | N133: =N132+1 -> 414 | P133: =P132+1 -> 514 | R133: =R132+1 -> 614 | T133: =T132+1 -> 714 | V133: =V132+1 -> 8014 | X133: =X132+1 -> 9114
F134: ='jobinfo(2)'!C67 -> 0 | H134: =H133+1 -> 115 | J134: =J133+1 -> 215 | L134: =L133+1 -> 315 | N134: =N133+1 -> 415 | P134: =P133+1 -> 515 | R134: =R133+1 -> 615 | T134: =T133+1 -> 715 | V134: =V133+1 -> 8015 | X134: =X133+1 -> 9115
F135: ='jobinfo(2)'!C68 -> 0 | H135: =H134+1 -> 116 | J135: =J134+1 -> 216 | L135: =L134+1 -> 316 | N135: =N134+1 -> 416 | P135: =P134+1 -> 516 | R135: =R134+1 -> 616 | T135: =T134+1 -> 716 | V135: =V134+1 -> 8016 | X135: =X134+1 -> 9116
F136: ='jobinfo(2)'!C69 -> 0 | H136: =H135+1 -> 117 | J136: =J135+1 -> 217 | L136: =L135+1 -> 317 | N136: =N135+1 -> 417 | P136: =P135+1 -> 517 | R136: =R135+1 -> 617 | T136: =T135+1 -> 717 | V136: =V135+1 -> 8017 | X136: =X135+1 -> 9117
F137: ='jobinfo(2)'!C70 -> 0 | H137: =H136+1 -> 118 | J137: =J136+1 -> 218 | L137: =L136+1 -> 318 | N137: =N136+1 -> 418 | P137: =P136+1 -> 518 | R137: =R136+1 -> 618 | T137: =T136+1 -> 718 | V137: =V136+1 -> 8018 | X137: =X136+1 -> 9118
F138: ='jobinfo(2)'!C71 -> 0 | H138: =H137+1 -> 119 | J138: =J137+1 -> 219 | L138: =L137+1 -> 319 | N138: =N137+1 -> 419 | P138: =P137+1 -> 519 | R138: =R137+1 -> 619 | T138: =T137+1 -> 719 | V138: =V137+1 -> 8019 | X138: =X137+1 -> 9119
F139: ='jobinfo(2)'!C72 -> 0 | H139: =H138+1 -> 120 | J139: =J138+1 -> 220 | L139: =L138+1 -> 320 | N139: =N138+1 -> 420 | P139: =P138+1 -> 520 | R139: =R138+1 -> 620 | T139: =T138+1 -> 720 | V139: =V138+1 -> 8020 | X139: =X138+1 -> 9120
F140: ='jobinfo(2)'!C73 -> 0 | H140: =H139+1 -> 121 | J140: =J139+1 -> 221 | L140: =L139+1 -> 321 | N140: =N139+1 -> 421 | P140: =P139+1 -> 521 | R140: =R139+1 -> 621 | T140: =T139+1 -> 721 | V140: =V139+1 -> 8021 | X140: =X139+1 -> 9121
F141: ='jobinfo(2)'!C74 -> 0 | H141: =H140+1 -> 122 | J141: =J140+1 -> 222 | L141: =L140+1 -> 322 | N141: =N140+1 -> 422 | P141: =P140+1 -> 522 | R141: =R140+1 -> 622 | T141: =T140+1 -> 722 | V141: =V140+1 -> 8022 | X141: =X140+1 -> 9122
F142: ='jobinfo(2)'!C75 -> 0 | H142: =H141+1 -> 123 | J142: =J141+1 -> 223 | L142: =L141+1 -> 323 | N142: =N141+1 -> 423 | P142: =P141+1 -> 523 | R142: =R141+1 -> 623 | T142: =T141+1 -> 723 | V142: =V141+1 -> 8023 | X142: =X141+1 -> 9123
... F144: ='jobinfo(2)'!C77 -> 0 | H144: =H143+1 -> 125 | J144: =J143+1 -> 225 | L144: =L143+1 -> 325 | N144: =N143+1 -> 425 | P144: =P143+1 -> 525 | R144: =R143+1 -> 625 | T144: =T143+1 -> 725 | V144: =V143+1 -> 8025 | X144: =X143+1 -> 9125
B146: = … ROOM OVERVIEW PICS ... DAY 1 … | L146: LOS / TRAVEL
B147: =B148-1 -> 100 | F147: ….
B148: 101 | F148: …. | L148: =======
B149: 102 | F149: …. | L149: LOS
B150: 103 | F150: …. | L150: LOS
B151: 104 | F151: …. | L151: LOS
B152: 105 | F152: …. | L152: …..........
B153: 106 | F153: …. | L153: …..........
B154: 107 | F154: …. | L154: …..........
B155: 108 | F155: …. | L155: …..........
B156: 109 | F156: …. | L156: …..........
B157: 110 | F157: …. | L157: …..........
B158: 111 | F158: …. | L158: LOS
B159: 112 | F159: …. | L159: …..........
... B172: 125 | F172: …. | L172: …..........
B173: OUTPUT = ROOM NAME ADD TO ENCIRCLE ROOM LISTS | I173: LOS / TRAVEL
B174: =B146 -> = … ROOM OVERVIEW PICS ... DAY 1 …
...

Sheet DRAWS
A1: DRAW SCHEDULE
A2: Property-owner Name | B2: =+'[1]jobinfo(2)'!C1 -> LACEY, EUNICE | C2: =+'[1]jobinfo(2)'!B26 -> Insurance Co. Name | D2: =+'[1]jobinfo(2)'!C26 -> AAA Insurance
A3: Property address: street | B3: =+'[1]jobinfo(2)'!C2 -> 13601 5th Ave | C3: =+'[1]jobinfo(2)'!B27 -> Claim # | D3: =+'[1]jobinfo(2)'!C27 -> #017095711
A4: Property city, state, zip | B4: =+'[1]jobinfo(2)'!C3 -> East Cleveland, OH | C4: =+'[1]jobinfo(2)'!B11 -> Cause of Loss | D4: =+'[1]jobinfo(2)'!C11 -> BATHTUB OVERFLOW
A5: Customer Email | B5: =+'[1]jobinfo(2)'!C4 -> Emedlacey@gmail.com | C5: =+'[1]jobinfo(2)'!B12 -> date of loss | D5: =+'[1]jobinfo(2)'!C12 -> 45765
A6: Cst-owner Phone# | B6: =+'[1]jobinfo(2)'!C5 -> (216) 450-4913 | C6: =+'[1]jobinfo(2)'!B13 -> rebuild type 1 | D6: =+'[1]jobinfo(2)'!C13 -> interior repairs LVL2
B7: _______________________ | C7: =+'[1]jobinfo(2)'!B14 -> rebuild type 2 | D7: =+'[1]jobinfo(2)'!C14 -> interior repairs LVL1
A8: Customer may wish to alter the original job work scope and or add additional work.
A10: Each item will be individually addressed with the best interest of the customer in mind.
C11: LOCATION & Basic damage / work Description | D11: Scope notes | E11: Photos | F11: Sketch
A12: # 0 = Master bedroom | B12: Ceilings N corner | C12: repair water damage drywall paint
A13: DRAW # | B13: PERCENTAGE OF WORK COMPLETED | D13: {_______} | E13: {_______} | F13: TTD
A14: 1 | B14: INITIAL DEPOSIT | D14: 0.33 | F14: =+D14 -> 0.33
A15: 2 | B15: 0.5 | D15: 0.33 | F15: =+D15+D14 -> 0.66
A16: 3 | B16: 0.75 | D16: 0.1 | F16: =+F15+D16 -> 0.76
A17: 4 | B17: 0.9 | D17: 0.14 | F17: =+F16+D17 -> 0.9
A18: 5 | B18: 1 | D18: 0.1 | F18: =+F17+D18 -> 1
H20: GC & SUB TERMS % | J20: CASH FLOW | O20: JOB = | P20: ='[1]jobinfo(2)'!C51 -> OH25 LACEY, E
H21: ='[1]jobinfo(2)'!C100 -> All Phase Consulting, LLC | K21: =+'[1]jobinfo(2)'!D100 -> Wayside Builders, LLC | N21: APC | P21: ='[1]jobinfo(2)'!C1 -> LACEY, EUNICE
H22: ='[1]jobinfo(2)'!C112 -> Joe Jones, PM 216.450.7228 | K22: ='[1]jobinfo(2)'!D112 -> Tony Jones 216.347.2656 | P22: ='[1]jobinfo(2)'!C2 -> 13601 5th Ave
P23: ='[1]jobinfo(2)'!C3 -> East Cleveland, OH
H24: ='[1]jobinfo(2)'!B5 -> Cst-owner Phone# | I24: ='[1]jobinfo(2)'!C5 -> (216) 450-4913 | J24: ='[1]jobinfo(2)'!B26 -> Insurance Co. Name | K24: ='[1]jobinfo(2)'!C26 -> AAA Insurance | L24: ='[1]jobinfo(2)'!B37 -> adj contents | M24: ='[1]jobinfo(2)'!C37 -> TBD
H25: ='[1]jobinfo(2)'!B6 -> Co-Owner.cst#2 | I25: ='[1]jobinfo(2)'!C6 -> TBD | J25: ='[1]jobinfo(2)'!B27 -> Claim # | K25: ='[1]jobinfo(2)'!C27 -> #017095711 | L25: ='[1]jobinfo(2)'!B38 -> adj CPS phone # | M25: ='[1]jobinfo(2)'!C38 -> TBD | O25: ='[1]jobinfo(2)'!B34 -> Field Adjuster Name | P25: ='[1]jobinfo(2)'!C34 -> FA
H26: ='[1]jobinfo(2)'!B11 -> Cause of Loss | I26: ='[1]jobinfo(2)'!C11 -> BATHTUB OVERFLOW | J26: ='[1]jobinfo(2)'!B28 -> policy # | K26: ='[1]jobinfo(2)'!C28 -> OHH000190052 | L26: ='[1]jobinfo(2)'!B39 -> adj CPS email | M26: ='[1]jobinfo(2)'!C39 -> TBD | O26: ='[1]jobinfo(2)'!B35 -> Phone # field adj | P26: ='[1]jobinfo(2)'!C35 -> FA
H27: ='[1]jobinfo(2)'!B12 -> date of loss | I27: ='[1]jobinfo(2)'!C12 -> 45765 | J27: ='[1]jobinfo(2)'!B29 -> Email INS. co. | K27: ='[1]jobinfo(2)'!C29 -> STAPLES.OLIVIA @ace.aaa.com | L27: ='[1]jobinfo(2)'!B40 -> TMP adj | M27: ='[1]jobinfo(2)'!C40 -> TBD | O27: ='[1]jobinfo(2)'!B36 -> Field adj email | P27: ='[1]jobinfo(2)'!C36 -> PH
H28: ='[1]jobinfo(2)'!B13 -> rebuild type 1 | I28: ='[1]jobinfo(2)'!C13 -> interior repairs LVL2 | J28: ='[1]jobinfo(2)'!B30 -> DESK Adjuster DA | K28: ='[1]jobinfo(2)'!C30 -> STAPLES, OLIVIA 207 776 6150 | L28: ='[1]jobinfo(2)'!B41 -> TMP adj phone # | M28: ='[1]jobinfo(2)'!C41 -> TBD | O28: ='[1]jobinfo(2)'!B21 -> Year Built | P28: ='[1]jobinfo(2)'!C21 -> PRE 1978
H29: ='[1]jobinfo(2)'!B14 -> rebuild type 2 | I29: ='[1]jobinfo(2)'!C14 -> interior repairs LVL1 | J29: ='[1]jobinfo(2)'!B31 -> DA Phone | K29: ='[1]jobinfo(2)'!C31 -> 207 776 6150 | L29: ='[1]jobinfo(2)'!B42 -> adj TMP email | M29: ='[1]jobinfo(2)'!C42 -> TBD | O29: ='[1]jobinfo(2)'!B22 -> Contract Date | P29: ='[1]jobinfo(2)'!C22 -> 45822
H30: ='[1]jobinfo(2)'!B15 -> rebuild type 3 | I30: ='[1]jobinfo(2)'!C15 -> BASEMENT | J30: ='[1]jobinfo(2)'!B32 -> DA Ph. Ext. # | K30: ='[1]jobinfo(2)'!C32 -> 207 776 6150 | O30: ='[1]jobinfo(2)'!B19 -> Replacement | P30: ='[1]jobinfo(2)'!C19 -> Y
H31: ='[1]jobinfo(2)'!B16 -> DEMO | I31: ='[1]jobinfo(2)'!C16 -> Y | J31: ='[1]jobinfo(2)'!B33 -> DA Email | K31: ='[1]jobinfo(2)'!C33 -> STAPLES.OLIVIA @ace.aaa.com | O31: ='[1]jobinfo(2)'!B23 -> Loss of use/ ALE | P31: ='[1]jobinfo(2)'!C23 -> Y | Q31: ='[1]jobinfo(2)'!B18 -> Other Structures | R31: ='[1]jobinfo(2)'!C18 -> NA
H32: ='[1]jobinfo(2)'!B17 -> Mitigation | I32: ='[1]jobinfo(2)'!C17 -> Y | K32: ='[1]jobinfo(2)'!B20 -> CPS / CLN / CON/ CGN | L32: ='[1]jobinfo(2)'!C20 -> Y | O32: ='[1]jobinfo(2)'!B24 -> Breathing issue | P32: ='[1]jobinfo(2)'!C24 -> TBD | Q32: ='[1]jobinfo(2)'!B25 -> HMR | R32: ='[1]jobinfo(2)'!C25 -> TBD
H34: ESTIMATES | J34: BEST CASE SCENARIO | N34: MOST LIKELY | Q34: WORST CASE SCENARIO
J35: 1 | K35: SUB | L35: =K21 -> Wayside Builders, LLC | N35: 0.7 | O35: =L35 -> Wayside Builders, LLC | Q35: 0.5 | R35: =K35 -> SUB
H36: Roof & EXT Mitigation TEMP. & EMERGENCY REPAIRS | J36: 1 | K36: 0 | L36: =J36*K36 -> 0 | N36: =J36*$N$35 -> 0.7 | O36: =N36*K36 -> 0 | Q36: =J36*$Q$35 -> 0.5 | R36: =Q36*K36 -> 0 | U36: 0.5 | V36: 0.5
H37: TREE & EXT Mitigation TEMP. & EMERGENCY REPAIRS | J37: 1 | K37: 0 | L37: =J37*K37 -> 0 | N37: =J37*$N$35 -> 0.7 | O37: =N37*K37 -> 0 | Q37: =J37*$Q$35 -> 0.5 | R37: =Q37*K37 -> 0
H38: Mitigation INTERIOR | J38: 33149.78 | K38: 0.2 | L38: =J38*K38 -> 6629.956 | N38: =J38*$N$35 -> 23204.846 | O38: =N38*K38 -> 4640.9692 | Q38: =J38*$Q$35 -> 16574.89 | R38: =Q38*K38 -> 3314.978 | U38: 0.66 | V38: 0.33
H39: Contents_ PERSONAL PROPERTY Packout = CPS | J39: 0 | K39: 0.2 | L39: =J39*K39 -> 0 | N39: =J39*$N$35 -> 0 | O39: =N39*K39 -> 0 | Q39: =J39*$Q$35 -> 0 | R39: =Q39*K39 -> 0 | U39: 0.66 | V39: 0.33
H40: REBUILD Interior & EXTERIOR | J40: =97116.91-J38-4 -> 63963.13 | K40: 0.8 | L40: =J40*K40 -> 51170.504 | N40: =J40*$N$35 -> 44774.191 | O40: =N40*K40 -> 35819.353 | Q40: =J40*$Q$35 -> 31981.565 | R40: =Q40*K40 -> 25585.252 | U40: 0.8 | V40: 0.2
H41: Roof & EXT REBUILD | J41: 1 | K41: 0 | L41: =J41*K41 -> 0 | N41: =J41*$N$35 -> 0.7 | O41: =N41*K41 -> 0 | Q41: =J41*$Q$35 -> 0.5 | R41: =Q41*K41 -> 0
H42: PERSONAL PROPERTY REPLACEMENT Customer's * | J42: 0 | K42: 0.1 | L42: =J42*K42 -> 0 | N42: =J42*$N$35 -> 0 | O42: =N42*K42 -> 0 | Q42: =J42*$Q$35 -> 0 | R42: =Q42*K42 -> 0 | U42: 0.66 | V42: 0.33
H43: TOTALS | J43: =SUM(J36:J42) -> 97115.91 | L43: =SUM(L36:L42) -> 57800.46 | N43: =SUM(N36:N42) -> 67981.137 | O43: =SUM(O36:O42) -> 40460.322 | Q43: =SUM(Q36:Q42) -> 48557.955 | R43: =SUM(R36:R42) -> 28900.23
H45: ESTIMATES | J45: BEST CASE SCENARIO | N45: POTENTIAL ADDITIONAL FUNDS | Q45: WORST CASE SCENARIO
J46: 1 | K46: APC | N46: 0.7 | O46: =L46 -> 0 | Q46: 0.5 | R46: =K46 -> APC
H47: Roof & EXT Mitigation TEMP. & EMERGENCY REPAIRS | J47: =J36 -> 1 | K47: =100%-K36 -> 1 | L47: =J47*K47 -> 1 | N47: =J47*$N$35 -> 0.7 | O47: =N47*K47 -> 0.7 | Q47: =J47*$Q$35 -> 0.5 | R47: =Q47*K47 -> 0.5
H48: TREE & EXT Mitigation TEMP. & EMERGENCY REPAIRS | J48: 1 | K48: =100%-K37 -> 1 | L48: =J48*K48 -> 1 | N48: =J48*$N$35 -> 0.7 | O48: =N48*K48 -> 0.7 | Q48: =J48*$Q$35 -> 0.5 | R48: =Q48*K48 -> 0.5
H49: Mitigation INTERIOR | J49: =J38 -> 33149.78 | K49: =100%-K38 -> 0.8 | L49: =J49*K49 -> 26519.824 | N49: =J49*$N$35 -> 23204.846 | O49: =N49*K49 -> 18563.877 | Q49: =J49*$Q$35 -> 16574.89 | R49: =Q49*K49 -> 13259.912
H50: Contents_ PERSONAL PROPERTY Packout = CPS | J50: 0 | K50: =100%-K39 -> 0.8 | L50: =J50*K50 -> 0 | N50: =J50*$N$35 -> 0 | O50: =N50*K50 -> 0 | Q50: =J50*$Q$35 -> 0 | R50: =Q50*K50 -> 0
H51: REBUILD Interior & EXTERIOR | J51: =J40 -> 63963.13 | K51: =100%-K40 -> 0.2 | L51: =J51*K51 -> 12792.626 | N51: =J51*$N$35 -> 44774.191 | O51: =N51*K51 -> 8954.8382 | Q51: =J51*$Q$35 -> 31981.565 | R51: =Q51*K51 -> 6396.313
H52: Roof & EXT REBUILD | J52: 1 | K52: =100%-K41 -> 1 | L52: =J52*K52 -> 1 | N52: =J52*$N$35 -> 0.7 | O52: =N52*K52 -> 0.7 | Q52: =J52*$Q$35 -> 0.5 | R52: =Q52*K52 -> 0.5
H53: PERSONAL PROPERTY REPLACEMENT Customer's * | J53: 0 | K53: =100%-K42 -> 0.9 | L53: =J53*K53 -> 0 | N53: =J53*$N$35 -> 0 | O53: =N53*K53 -> 0 | Q53: =J53*$Q$35 -> 0 | R53: =Q53*K53 -> 0
H54: TOTALS | J54: =SUM(J47:J53) -> 97115.91 | L54: =SUM(L47:L53) -> 39315.45 | N54: =SUM(N47:N53) -> 67981.137 | O54: =SUM(O47:O53) -> 27520.815 | Q54: =SUM(Q47:Q53) -> 48557.955 | R54: =SUM(R47:R53) -> 19657.725
H55: GROSS TOTAL TO DATE | J55: HENDKING
H56: REBUILD Interior & EXTERIOR | J56: =J54 -> 97115.91 | K56: APC
H57: Mitigation INTERIOR | J57: =-J49 -> -33149.78
J58: =J57+J56 -> 63966.13
I59: 0.2 | J59: =-J58*I59 -> -12793.226 | K59: =-J59 -> 12793.226
J60: =J58+J59 -> 51172.904
H62: advance | J62: -20000
J63: =J60+J62 -> 31172.904
H65: repayment | J65: 14000 | K65: =-J65 -> -14000
J66: 1
J67: =J63+J65 -> 45172.904
H68: advance | J68: 7000
J70: =J67+J68 -> 52172.904
H73: Mitigation INTERIOR
I74: =J49 -> 33149.78
I75: 0.2 | J75: =I74*I75 -> 6629.956 | K75: =I74-J75 -> 26519.824
J76: =J70+J75 -> 58802.86 | K76: =SUM(K59:K75) -> 25313.05 | N76: 33150
N77: 36917.18 | Q77: =N77 -> 36917.18
N78: =N76+N77 -> 70067.18 | Q78: =K82 -> 7836.73
N79: 20000 | Q79: =+Q77+Q78 -> 44753.91
J80: =J76+K76 -> 84115.91 | K80: =I74 -> 33149.78 | L80: MIT TOTAL T APC | N80: =N78+N79 -> 90067.18 | Q80: =+N81 -> 7048.73
J81: =-J62 -> 20000 | K81: =-K76 -> -25313.05 | L81: NET DUE | N81: =J84-N80 -> 7048.73 | O81: DEPRECIATION HELD
J82: =J80+J81 -> 104115.91 | K82: =K80+K81 -> 7836.73 | L82: DUE IAN/HARDROCK | N82: =+N80+N81 -> 97115.91 | Q82: =SUM(Q79:Q81) -> 51802.64
J83: =-J68 -> -7000
J84: =J82+J83 -> 97115.91

Sheet WIP
D1: HOW2
A2: L3 | B2: 3 LEVELS NO ROOF; 2NDFLOOR WATER LEAK ; CPS [Y] | D2: RETREIVE
B3: 3 LEVELS NO ROOF; 2NDFLOOR WATER LEAK ; CPS [N]
B4: ATTIC ROOMS ONLY
B5: All Room list Fire Smoke All
A8: L3 | B8: 3 LEVELS HOUSE; NO ROOF; 2NDFLOOR WATER LEAK ; CPS [Y] | D8: Jobsite Verification
B9: Jobsite Verification | K9: Living Room,
B10: LEVEL1 = PRIMARY ROOM [A]
B11: Garage,
B12: FOYER, | K12: Dining Room,
B13: Guest Closet, | K13: Kitchen,
B14: Living Room, | K14: Nook,
B15: Dining Room, | K15: Pantry,
B16: Kitchen, | K16: Hallway,
B17: Nook, | K17: Linen Closet,
B18: Pantry | K18: Bedroom 1,
B19: Hallway, | K19: Bedroom Closet 1,
B20: Linen Closet, | K20: Bedroom 2,
B21: DEN/SUNROOM/REC ROOM
B22: BATH GUEST
B23: FOYER, REAR/SIDE
B24: STAIRS UP
B25: ADD A ROOM LEVEL 1
B27: LEVEL1 = POTENTIAL ADDITIONAL ROOMS [B]
B28: OFFICE
B29: LAUNDRY
B30: Primary Bedroom,
B31: PBR Closet 1
B32: PBR Closet 2
B33: PBR Bathroom,
... B43: BATH UP
B44: Bedroom 1, | K44: Bedroom Closet 2,
B45: BR1 Closet | D45: “who is the Regional Claims VP for Ohio?” | K45: Primary Bedroom,
B46: Bedroom 2 | K46: Primary Bedroom Closet 2,
B47: BR2 Closet | K47: Primary Bathroom,
B48: Bath 2
B49: Primary Bedroom, | K49: Rec Room/ office,
B50: PBR Closet 1 | K50: Garage,
B51: PBR Closet 2
B52: PBR Bathroom, | K52: Guest Bathroom
B54: LEVEL 2 = POTENTIAL ADDITIONAL ROOMS [B]
B55: Rec Room/ office,
B56: LINEN CLOSET 2
B57: Bath 3
B58: Rec Room/ office,
B60: LEVEL BASEMENT = PRIMARY ROOMS [A]
B61: FOYER SIDE ENTRY
B62: STAIRS TO BASEMENT
B63: FAMILYROOM/MAN CAVE
B64: UTILITY ROOM
B65: LAUNDRY ROOM
B66: Bathroom DN
... B123: Interior list & ROOF
B128: 1. 1.Jobsite Verification (Address Photos) | D128: Foyer DN
B129: 2. 2.Source of Loss Pics (ROOMS / STRUCTURAL) , | D129: Living Room DN
B130: 3. 3.FOYER/ENTRY ROOM, | D130: Guest Closet DN
B131: 4. ROOM2
B132: 5. ROOM3 | D132: Dining Room DN
B133: 6. ROOM4 | D133: Hallway DN @ BR&BATH
B134: 7. ROOM5 | D134: Bedroom 1 DN
B135: 8. 4. CPS1 DAY 1 CONTENTS ROOM OVERVIEW / DOCUMENT PICS | D135: Primary BR DN
B136: 9. 5. CPS2 DAY2 CONTENTS OVERVIEW WIP BOXES PACKOUT PICS, | D136: Primary BR Closet DN
B137: 10. 6. CPS3 DAY3 CONTENTS OVERVIEW STORAGE MOVE OUT PICS, | D137: Bedroom 2 DN
B138: 11. 7. CPS4 CONTENTS OVERVIEW PACK-BACK / RESET PICS, | D138: BR 2 Closet DN
B139: 12. 8. MITIGATION EQUIPMENT OVERVIEW INTERIOR & WIP, | D139: Bathroom DN
B140: 13. 9. MITIGATION Readings Moisture = MC, | D140: Linen Closet DN
B141: 14. 10. MITIGATION READINGS = RH, TEMP F & DEH & EXTERIOR, | D141: Kitchen DN
B142: 15. 11. REPLACEMENT 1 CON OVERVIEW DAY PICS, | D142: Pantry Down DN
B143: 16. 12. REPLACEMENT 2 CON WIP, | D143: Hallway/ Closet Dn
... B163: 36. ROOM LABELS | D163: 3rd Floor Up Stairs
D164: 3rd Floot Bedroom Closet
D165: 3rd Floor Bedroom/REC 1
D166: 3rd Floor Living Room
D167: 3rd Floor Kitchen
D168: 3rd Floor Storage 1
D169: 3rd Floor Hallway Bedroom
B170: Interior list & ROOF / 5DAY MIT | D170: 3rd Floor Closet Hall
B171: 1. Jobsite Verification (Address Photos), | D171: 3rd Floor Guest Closet 1
B172: 2. Source of Loss Pics (ROOMS / STRUCTURAL) , | D172: 3rd Floor Guest Closet 2
B173: 3.FOYER/ENTRY ROOM, | D173: Bathroom 3rd Floor
B174: 5. CPS2 DAY2 CONTENTS OVERVIEW WIP BOXES PACKOUT PICS, | D174: 3RD FLR Storage 2
B175: 6. CPS3 DAY3 CONTENTS OVERVIEW STORAGE MOVE OUT PICS , | D175: 3rd Floor Porch
B176: 7. CPS4 CONTENTS OVERVIEW PACK-BACK / RESET PICS, | D176: Basement COMMON AREA ====
B177: 8. MITIGATION EQUIPMENT OVERVIEW INTERIOR & WIP , | D177: Laundry Room
B178: 9. MITIGATION Readings Moisture = MC, | D178: STORAGE RR
B179: 10. MITIGATION READINGS = RH, TEMP F & DEH & EXTERIOR, | D179: === MITIGATION LABELS =====
B180: 11. REPLACEMENT 1 CON OVERVIEW DAY PICS, | D180: Mitigation Equipment
B181: 12. REPLACEMENT 2 CON WIP, | D181: STABILIZATION
... B192: RHT DAY 4, | D192: PPR REPLACEMENT ITEMS
B193: RHT DAY 5,
B194: MC DAY1 ,
B195: MC DAY 2,
B196: MC DAY3,
B197: MC DAY 4,
B198: MC DAY 5,
B199: STABILIZATION READINGS,
B200: MIT LABELS,
B201: ROOM LABELS
B204: Jobsite Verification & Source of Loss
B205: 1. Jobsite Verification (Address Photos)
...

Sheet kit bath
B1: =+'jobinfo(2)'!$C$1 -> BROWNLEE, KEN | C1: =+'jobinfo(2)'!$C$2 -> 3922 E 189 STR | E1: =+'jobinfo(2)'!$C$3 -> CLEVELAND, OH 44128 | F1: =+'jobinfo(2)'!$C$11 -> WATER | T1: ='[2]jobinfo(2)'!$C$5 -> (216) 551-5572
B2: Kitchen | C2: CABINETS | E2: Type /Quality / Grade:
B3: Standard- Builder Grade / High Grade / Premium / Deluxe / CUSTOM
A4: BASE | C4: _______________ | D4: _______________ | E4: _______________ | F4: LF total =____________
B5: SB SIZE | C5: _______________ | D5: _______________ | E5: _______________
B6: DB SIZE | C6: _______________ | D6: _______________ | E6: _______________
B7: B ____SIZES | C7: _______________ | D7: _______________ | E7: _______________
B8: SPECIALTY | C8: _______________ | D8: _______________ | E8: _______________
C9: _______________ | D9: _______________ | E9: _______________
C10: _______________ | D10: _______________ | E10: _______________
B11: UPPER Cabinets | C11: _______________ | D11: _______________ | E11: _______________ | F11: LF total =____________
B12: WIDTH X HEIGHT | C12: _______________
C13: _______________
B14: FULL HEIGHT CAB | C14: _______________
B16: COUNTER TOP | C16: FORMICA | D16: GRANITE | E16: OTHER __________ | F16: SF total =____________
C17: NOTES:
B18: APPLIANCES
B19: REFRIGERATOR | E19: ICE MAKER
B20: STOVE/OVEN | C20: GAS or ELECTRIC | E20: BUILT IN or Stand Alone
B21: Micro wave | C21: __________________________ | E21: BUILT IN or Stand Alone
B22: EXHAUST/VENT FAN | C22: __________________________ | E22: BUILT IN or Stand Alone
B23: Dishwasher | C23: __________________________ | E23: BUILT IN or Stand Alone
B24: Garbage disposal
B26: BATHROOM
B27: VANITY | C27: SIZE _________ | D27: GRADE ________ | E27: ____ COUNTER TOP __________
B28: TOWEL RACKS | C28: QTY =
B29: BATHTUB | E29: __________________________ | F29: ___________________
B30: Shower surround Type | C30: SIZE _________ | D30: GRADE ________ | E30: __________________________
B31: Shower doors | C31: Shower Curtain & Rod
B32: VENT FAN

Sheet BLD codes
A1: 3137.11 Conformity With National Electrical Code
A3: § 3131.06 Repairs after Fire Damage Whenever the operation of a system has been the cause of a fire, such system shall not be used or operated until it has been inspected by the Commissioner and such alterations and changes made as are deemed necessary by him or her to permit safe operation of the system, and no alterations or repairs shall be made without a permit issued by the Commissioner.
A4: § 3131.08 Firestopping (a) Where the installation of pipes or ducts in walls or partitions requires the removal of any firestopping, the space around the pipes or ducts at the points where firestopping was removed shall be tightly filled with mineral wool or other noncombustible insulating material. (b) Where pipes, ducts, stacks, or fittings pass through a floor construction, all open spaces around them shall be filled with mineral wood, or other incombustible insulating material. (c) Whenever baseboard or wall registers located at the top of supply or return air ducts are installed in stud framed walls or partitions or in construction having concealed interior spaces, an approved firestop shall be installed approximately three (3) inches above such register or grille. In stud framed construction such firestops shall extend the full width and depth of the stud space.
A8: Cleveland, OH primarily adopts the International Residential Code (IRC) for residential buildings.
A9: The city may also reference the International Building Code (IBC) for certain aspects of construction.
A11: Ensure compliance with zoning regulations that may affect residential construction.
A13: Always verify the latest code updates, as building regulations can change frequently.
A16: § 3137.11 Conformity With National Electrical Code Except as otherwise provided in this Building Code, or in statutes, or in rules or regulations promulgated by authority of statute, all electrical wiring and equipment shall be in accordance with the provisions of NFiPA 70 entitled “National Electrical Code,” as listed in OAC Chapter 4101:2-46.
A18: § 3137.12 Residential Electrical Rehabilitation (a) Scope. The provisions of this section shall apply to the rehabilitation of electrical systems in one (1), two (2) and three (3) familydwelling units when they have been determined to be inadequate as specified in subsection (b) hereof.
A20: dwelling units when they have been determined to be inadequate as specified in subsection (b)
A21: hereof.
A22: (b) Evidence of inadequate Wiring. Evidence of inadequate wiring shall include one (1) or more of
... A109: tenant, excepting those dwellings where the owner pays for the energy consumed.

Sheet XACTIMATE
A1: Xactimate NEW PROJECTS | B1: ='jobinfo(2)'!C51 -> OH25 BROWNLEE @E189
A2: 00. SKETCH SKTH | B2: DMO | D2: XACT Supplement[SPLM]
A3: 01 Rebuild, RBLD | B3: 90 CPS | C3: PPR
A4: 65, exterior mitigation EXT-EMS | B4: 80. Interior Mitigation EMS MIT
A5: INSURED INFO
A6: NAME | B6: EMAIL
A7: =+'jobinfo(2)'!C1 -> BROWNLEE, KEN | B7: =+'jobinfo(2)'!C4 -> KHAIAKEN@SBCGLOBAL.NET
A8: ADDRESS TYPE | B8: HOME | C8: DEFAULT
A9: STREET | B9: CITY | C9: STATE / ZIP CODE | D9: COUNTRY
A10: =+'jobinfo(2)'!C2 -> 3922 E 189 STR | B10: =+'jobinfo(2)'!C3 -> CLEVELAND, OH 44128 | D10: USA
A11: PHONE Type | B11: CELLULAR | C11: =+'jobinfo(2)'!C5 -> 2163241337
A13: DATES Date Entered | B13: DATE ASSIGNED | C13: EST. COMPLETED | D13: JOB COMPLETED
A14: =+'jobinfo(2)'!C22 -> 45987 | B14: TBD | C14: TBD | D14: TBD
A16: PERSONNEL | B16: ESTIMATOR | D16: REFERENCE -== Insurance Co. Name
B17: ='jobinfo(2)'!C112 -> Joe Jones, PM 216.450.7228 | D17: =+'jobinfo(2)'!C26 -> ALLSTATE INS CO.
A19: Type Of Estimate/LOSS | B19: Deductible | C19: File Number = Claim # | D19: ='jobinfo(2)'!B28 -> policy #
A20: =+'jobinfo(2)'!C11 -> WATER | B20: tbd | C20: =+'jobinfo(2)'!C27 -> CLM | D20: =+'jobinfo(2)'!C28 -> PL3\
A22: XACTIMATE | B22: NEW CUSTOMER INFO | D22: PAGE 2
A23: PARAMETERS
A25: PRICING
A26: Checkpoint Price List | B26: Price List | C26: Tax Jurisdiction | D26: Price lIst filter
A27: N/A | B27: =B10 -> CLEVELAND, OH 44128 | C27: HIGHEST AVAILABLE | D27: N/A
B28: =+'jobinfo(2)'!C12 -> 45986
A29: REPRICE | B29: N/A | C29: N/A | D29: CONTRACTOR
A31: ADD ONS | B31: N/A | C31: [__] | D31: ='jobinfo(2)'!C100 -> All Phase Consulting, LLC
A33: Depreciation Options | C33: N/A
A35: Overhead and Profit (O&P) | B35: Overhead | C35: Profit
B36: 0.1 | C36: 0.1 | D36: N/A
A38: Report Text | B38: COMPANY HEADER | C38: =+'jobinfo(2)'!C100 -> All Phase Consulting, LLC
B39: OPENING STATEMENT | C39: APC FULL STATEMENT | D39: DEFAULT =APC
B40: CLOSING STATEMENT | C40: THNAK YOU | D40: DEFAULT =APC
A42: SUPPLIED OR ENTERED BY OTHERS
A43: SKETCHES | B43: Retrieve | C43: FLR PLAN @ ENCIRCLE | D43: IMPORT FPLN | F43: Thought For The Day
A44: SCOPE INPUT | B44: Retrieve | C44: [__] | F44: You can tell whether a man is clever by his answers.
A45: =+'jobinfo(2)'!B53 -> Room/Area 101 | B45: =+'jobinfo(2)'!C53 -> Living Room, | C45: =+'jobinfo(2)'!B66 -> Room/Area 14 | D45: =+'jobinfo(2)'!C66 -> 0 | F45: You can tell whether a man is wise by his questions.
A46: =+'jobinfo(2)'!B54 -> Room/Area 102 | B46: =+'jobinfo(2)'!C54 -> HALLWAY | C46: =+'jobinfo(2)'!B67 -> Room/Area 15 | D46: =+'jobinfo(2)'!C67 -> 0
A47: =+'jobinfo(2)'!B55 -> Room/Area 103 | B47: =+'jobinfo(2)'!C55 -> Kitchen, | C47: =+'jobinfo(2)'!B68 -> Room/Area 16 | D47: =+'jobinfo(2)'!C68 -> 0
A48: =+'jobinfo(2)'!B56 -> Room/Area 104 | B48: =+'jobinfo(2)'!C56 -> DEN | C48: =+'jobinfo(2)'!B69 -> Room/Area 17 | D48: =+'jobinfo(2)'!C69 -> 0
A49: =+'jobinfo(2)'!B57 -> Room/Area 105 | B49: =+'jobinfo(2)'!C57 -> STAIRS UP | C49: =+'jobinfo(2)'!B70 -> Room/Area 18 | D49: =+'jobinfo(2)'!C70 -> 0
A50: =+'jobinfo(2)'!B58 -> Room/Area 106 | B50: =+'jobinfo(2)'!C58 -> HALL UP | C50: =+'jobinfo(2)'!B71 -> Room/Area 19 | D50: =+'jobinfo(2)'!C71 -> 0
A51: =+'jobinfo(2)'!B59 -> Room/Area 107 | B51: =+'jobinfo(2)'!C59 -> PBR UP | C51: =+'jobinfo(2)'!B72 -> Room/Area 20 | D51: =+'jobinfo(2)'!C72 -> 0
A52: =+'jobinfo(2)'!B60 -> Room/Area 8 | B52: =+'jobinfo(2)'!C60 -> BATH UP | C52: =+'jobinfo(2)'!B73 -> Room/Area 21 | D52: =+'jobinfo(2)'!C73 -> 0
A53: =+'jobinfo(2)'!B61 -> Room/Area 9 | B53: =+'jobinfo(2)'!C61 -> BR-2 UP | C53: =+'jobinfo(2)'!B74 -> Room/Area 22 | D53: =+'jobinfo(2)'!C74 -> 0
A54: =+'jobinfo(2)'!B62 -> Room/Area 10 | B54: =+'jobinfo(2)'!C62 -> GUEST CLOSET | C54: =+'jobinfo(2)'!B75 -> Room/Area 23 | D54: =+'jobinfo(2)'!C75 -> 0
A55: =+'jobinfo(2)'!B63 -> Room/Area 11 | B55: =+'jobinfo(2)'!C63 -> BATH DN | C55: =+'jobinfo(2)'!B76 -> Room/Area 24 | D55: =+'jobinfo(2)'!C76 -> 0
A56: =+'jobinfo(2)'!B64 -> Room/Area 12 | B56: =+'jobinfo(2)'!C64 -> SHOWER | C56: =+'jobinfo(2)'!B77 -> Room/Area 25 | D56: =+'jobinfo(2)'!C77 -> 0
A57: =+'jobinfo(2)'!B65 -> Room/Area 13 | B57: =+'jobinfo(2)'!C65 -> 0
A60: 1. Xactimate Supplements [SPLM]
B61: 01 Rebuild
B62: 65 Exterior mitigation
B63: 80 Interior mitigation
B64: 90 CPS
B65: Other
D74: 00 | E74: 00 SKETCH | H74: UPLOAD TO ENCIRCLE
D75: 65 | E75: 65, exterior mitigation | I75: =1+#REF! -> #REF!
D76: 70 | E76: 80, Interior mitigation | I76: =1+I75 -> #REF!
E77: Misc/Other Xactimate | I77: =1+#REF! -> #REF!
B78: XACTIMATE = Estimates Supplemental [SPLM] | D78: 01 | E78: 01 Rebuild | I78: =1+I77 -> #REF!
D79: 65 | E79: 65, exterior mitigation | I79: =1+I78 -> #REF!
D80: 70 | E80: 80, Interior mitigation | I80: =1+I79 -> #REF!
D81: 90 | E81: 90 CPS | I81: =1+I80 -> #REF!
E82: Misc/Other Xactimate | I82: =1+I81 -> #REF!
B83: MICA or ENCIRCLE or XACTIMATE | E83: 80 | I83: MICA or ENCIRCLE
A84: Staff Notifications
A85: ENCIRCLE | B85: ENCIRCLE NEW CUSTOMER CREATED | F85: CREATED INSIDE ENCIRCLE AS INDIVIDUAL ROOMS = 1 REPORT SET UP | I85: ENCIRCLE
B86: cklst 60 contract rep docs/initial pics | E86: 60
B87: cklst 70 interior scope | E87: 70
B88: cklst 80 int mitigation | E88: 80
B89: cklst 90 CON CPS 01 | E89: 90
B93: 01 Rebuild
B94: 65 Exterior mitigation
B99: 80 Interior mitigation
B100: 90 CPS
B101: Other

Sheet ENC
A1: ENCIRCLE | B1: CLAIM INBOX | D1: NEW CUSTOMER INFO
A3: Claim Identifier
A4: CARRIER IDENTIFIER | B4: CONTRACTOR IDENTIFIER | D4: ASSIGNMENT IDENTIFIER
A5: ='jobinfo(2)'!C27 -> CLM | B5: ='jobinfo(2)'!C51 -> OH25 BROWNLEE @E189 | D5: =B5 -> OH25 BROWNLEE @E189
A7: Policyholder Details
A8: POLICYHOLDER NAME | B8: POLICYHOLDER EMAIL | C8: POLICYHOLDER PHONE NUMBER
A9: =+'jobinfo(2)'!C1 -> BROWNLEE, KEN | B9: =+'jobinfo(2)'!C4 -> KHAIAKEN@SBCGLOBAL.NET | D9: =+'jobinfo(2)'!C5 -> 2163241337
A11: Address Details
A12: ADDRESS
A13: =+'jobinfo(2)'!C2 -> 3922 E 189 STR | B13: =+'jobinfo(2)'!C3 -> CLEVELAND, OH 44128
A15: Claim Details
A16: DATE OF LOSS | D16: POLICY NUMBER
A17: ='jobinfo(2)'!C12 -> 45986 | D17: =+'jobinfo(2)'!C28 -> PL3\
A18: DATE CLAIM CREATED | C18: PROJECT MANAGER
A19: ='jobinfo(2)'!C22 -> 45987 | C19: ='jobinfo(2)'!C112 -> Joe Jones, PM 216.450.7228
A20: TYPE OF LOSS | D20: CAT CODE
A21: ='jobinfo(2)'!C11 -> WATER | D21: TBD
A22: INSURANCE COMPANY | C22: CLAIM SUMMARY (LOSS DETAILS)
A23: ='jobinfo(2)'!C26 -> ALLSTATE INS CO. | C23: INPUT DETAILS/INFO PROVIDED
A24: ADJUSTER
A25: ='jobinfo(2)'!C30 -> 0
A26: BROKER / AGENT
A27: AS NEEDED

Sheet Sheet1
A1: All Phase Consulting LLC
A2: JJ
A3: Property/
A4: TEST CLAIM V1
A5: OverviewActivityPaymentsGeneral NotesStructures & RoomsStatusContentsHydro
A6: Overview
A7: Reorder Rooms
A8: Rooms
A9: Rooms
A11: 0.0001 ….. JOBSITE VERIFICATION (0)
A12: 0.0002 . MECHANICALS = WATER METER READING & PLUMBING REPORT/INVOICE (0)
A13: 0.0003 . MECHANICALS = ELECTRICAL HAZARDS (0)
... A366: 9999.0 . REBUILD INTERIOR COMPLETED WORK (0)

Sheet how2
B1: Insurance Customer new contract "HOW TO CREATE"
A2: 1 | B2: Open the Computer to Microsoft Excel and open "Checklists/Estimates /" file.
A4: 2 | B4: Go to sheet "(job info" tab) Verify company name and or update
B5: To update Go to sheet/tab COMPANY HEADER (co header)
B6: Selct and copy header info and paste into contract tab/sheet @ A1
B7: Template - A | C7: WSB TJ | D7: Template - C | E7: APC JJ
B8: Template - B | C8: WSB JJ GA | D8: Template - D | E8: WSB JJ OH
B10: Or go to google drive and open/download file template
C11: (File, Open, Browse, Checklist, New Customer)
A12: 3 | B12: After Opening file Template, Save As A New File: | E12: Required
B13: Create (New) Sub-Folder for job, inside "Estimates" Folder,
B14: Or go to google drive and upload the new file open/download file template
B15: Save as per file naming format (See Below)
C16: City/Area - Year-Company- Customer Name - Job Type - Insurer Abbreviation
B17: example = ATL 2019 Brown 05 RFG- SFI
A18: Job Types & Codes: | C18: Roofing = RFG | D18: Wind=Wind | E18: TREE
C19: Water Damage=WTR | D19: Hurricane =HURR | E19: FIRE
A21: 4 | B21: Go to ….. "job info(2)"….. tab & Enter Data:
B22: If info is already in job info tab then erase info, enter TBD in all cells or overwrite existing data with new info.
B23: A} | C23: Customer Info | E23: Required
B24: B} | C24: Loss/damage Info | E24: Required
B25: C} | C25: Insurer Info (policy # required) | E25: Required
B26: D} | C26: Room Index/AREA ID (If Available) | E26: Required
B27: E} | C27: Mortgage company info; if applicable & when available (loan status)
A29: 5 | B29: Brief Claim Narrative (if Available) | E29: Required
A31: 6 | B31: Save File
A33: 7 | B33: Print entire workbook as PDF; save to new named folder (see above)
B34: print areas are preset, for some tabs only one page may print , as per design
A35: 8 | B35: Email PDF as attachment (subject = contract docs out to customer name):
A36: 9 | B36: Include MOU {PDF}(copy & paste job info tab to update or use stock form)
A37: CC: | B37: A} | C37: manage.apc@gmail.com | E37: Required
B38: B} | C38: Field Rep.
B39: C} | C39: Customer
A40: 10 | B40: Upload a copy to Google Drive | E40: Required
B41: Estimates = Proof of Loss Supporting Documentation | E41: work in progress 10192019
A42: 1 | B42: Index of Required Pictures
B43: ********* Using the ENCIRCLE & APC APP will guide you thru this process *********
B45: Pictures are a critical part of the full process for payment !!!
B46: Estimates = Proof of Loss Supporting Documentation
A47: 2 | B47: Open the following file templates and update or use "Master Forms Field Docs Template"
B48: Mitigation$_______ | D48: WTR | E48: (File, Open,Browse
B49: Demo $________ | D49: New CST
B50: Rebuild $________ | D50: WTR
B51: Contents $________ | D51: Sub Contractor
A54: 3 | B54: After Opening file Template, Save As A New File: | E54: Required
B55: Create (New) Sub-Folder for job, inside Estimates Folder,
B57: Save as per file naming format (See Below)
C58: City/Area - Year - Customer Name - Job Type - Insurer Abbreviation
C59: example = Atl - 2019 - Brown - RFG- SFI
A60: Job Types & Codes: | C60: Roofing = RFG | D60: Wind=Wind | E60: TREE
C61: Mitigation$_______ | D61: Hurricane =HURR | E61: FIRE
C63: Demo $________ | E63: ( File, Open, Browse )
C64: Rebuild $________
C65: Contents $________
A67: 4 | B67: Go to job info tab & Enter Data:
B68: Copy & paste job info tab to update or use stock form)
B70: ROOF & EXTERIOR MITIGATION
B72: INTERIOR MITIGATION & DEMO
C73: DEMOLITION DMO
C74: SECONDARY DAMAGES HAZARDOUS MATERIALS REMEDIATION/HMR
C75: MITIGATION EQUIPMENT
C76: DRY LOGS DOCS & TRIP MONITORING
B79: CONTENTS;
B80: a | C80: PACKOUT Storage Only
B81: b | C81: Cleaning INHOUSE
B82: c | C82: Cleaning Sent to outside vendor
B83: d | C83: CONTENTS, REPLACEMENT ITEMS CPS / CON
B85: REBUILD CLOSEOUT
A87: OFS DOCS | B87: cklst 01 Job info page only | D87: 01
B88: BINDER TABS
B89: cklst 20 Intial contact Forms POI | D89: 20
B90: cklst 30 Insurer,, mtge ,, cst | D90: 30
B91: cklst 25 CLAIM BRIEF | C91: 25 | D91: 25
B92: cklst 99 cashflow | D92: 99
A94: CUSTOMER | B94: cklst 50 contract sig pgs | D94: 50
B95: cklst 51 contract notary pgs | D95: 51
B96: cklst 52 claim reporting info | D96: 52
B97: cklst 56 MOU | D97: 56
A99: REP / CREW @ JOB | B99: cklst 60 contract rep docs | D99: 60
B100: Order EagleView, ROOF QS __ | D100: PREM report____Xact EV#_____
B101: 00 Pics ENCIRCLE NEW CST CREATED
B103: cklst 65 Ext mitigation Roof | D103: 65
B104: cklst 70 interior scope | D104: 70
B105: cklst 80 int mitigation | D105: 80
B106: cklst 90 CON CPS 01 | D106: 90
B107: cklst 1155 Job Forms ONLY | D107: 155
A115: Note on creating the New Custmer Contract & Docs
A117: Actually we send an individualized preprinted contract and associated docs to each customer.
A118: See next email for info that we need to create those docs.
A120: Also, we will send over to you the Excel file
A121: The Excel populates the individualized preprinted contract and associated docs.
A123: So you may use the email to gather the info and
A124: then copy and paste into the Excel "contract doc".
A126: Or you may enter the info directly into the Excel file and
A127: then create a PDF file to forward to the customer for signature.
A128: See the HOW TO tab or below in the Excel file for further details.
A130: This process creates the following:
A132: professional-looking documents
... A137: Please recall that we also working to create an app that serves;
B138: the young single person, first-time homeowner,
...
